Workbook

Sheet Смета по ТСН-2001(с доп.43
A1: =Source!B1 -> Smeta.RU (495) 974-1589
J2: Форма № 4б
A3: 02-01-01 Строительство КЛ - 10 кВ траншея
A4: (наименование стройки и/или объекта)
A6: =CONCATENATE( "ЛОКАЛЬНАЯ СМЕТА № ",IF(Source!F12<>"Новый объект", Source!F12, "")) -> ЛОКАЛЬНАЯ СМЕТА № 02-01-01 КЛ - 10 кВ траншея
A8: Строительство КЛ - 10 кВ траншея
A9: (наименование работ и затрат)
A11: =CONCATENATE( "Основание: чертежи № ", Source!J12) -> Основание: чертежи №
I13: В базисном уровне цен | J13: В текущем уровне цен
E14: Сметная стоимость | I14: =I15+I16+I17+I18 -> 34.55 | J14: =J15+J16+J17+J18 -> 359.12 | K14: тыс.руб.
E15: Строительные работы | I15: =ROUND(SUM(X1:X400)/1000, 2) -> 6.77 | J15: =ROUND((Source!P501)/1000, 2) -> 99.86 | K15: тыс.руб.
E16: Работы по монтажу оборудования | I16: =ROUND(SUM(Y1:Y400)/1000, 2) -> 27.78 | J16: =ROUND((Source!P502)/1000, 2) -> 259.26 | K16: тыс.руб.
E17: Оборудование | I17: =ROUND(SUM(Z1:Z400)/1000, 2) -> 0 | J17: =ROUND((Source!P493)/1000, 2) -> 0 | K17: тыс.руб.
E18: Прочие работы и затраты | I18: =ROUND(SUM(AA1:AA400)/1000, 2) -> 0 | J18: =ROUND((Source!P503+Source!P504)/1000, 2) -> 0 | K18: тыс.руб.
E19: Средства на оплату труда | I19: =ROUND(SUM(W1:W400)/1000, 2) -> 1.14 | J19: =((Source!P499 + Source!P498)/1000) -> 39.43562 | K19: тыс.руб.
E20: Затраты труда | I20: =SUM(AB1:AB400) -> 87.630626 | K20: чел.-ч.
E21: Кроме того:
E22: Возврат материалов | I22: =ROUND(SUM(AE1:AE400)/1000, 2) -> 0 | J22: =SUM(AF1:AF400)/1000 -> 0 | K22: тыс.руб.
A24: Составлен(а) по ТСН-2001 с учетом Дополнения №: 73
A25: № и период сборника коэффициентов (индексов) пересчета: Коэффициенты к ТСН-2001 МГЭ №212 III квартал 2024 года | AP25: № и период сборника коэффициентов (индексов) пересчета: Коэффициенты к ТСН-2001 МГЭ №212 III квартал 2024 года
A26: № п/п | B26: Шифр расценки и коды ресурсов | C26: Наименование работ и затрат | D26: Ед. изм. | E26: Кол-во единиц | F26: Цена на ед. изм., руб. | G26: Попра- вочные коэффи- циенты | H26: Коэффи- циенты зимних удорожа- ний | I26: Всего затрат в базисном уровне цен, руб. | J26: Коэффи- циенты (индек- сы) пере- счета, нормы НР и СП | K26: ВСЕГО затрат в текущем уровне цен, руб.
A27: 1 | B27: 2 | C27: 3 | D27: 4 | E27: 5 | F27: 6 | G27: 7 | H27: 8 | I27: 9 | J27: 10 | K27: 11
A29: =CONCATENATE("Раздел: ",IF(Source!G24<>"Новый раздел", Source!G24, "")) -> Раздел: Земляные работы
A30: 1 | B30: 3.1-51-1 Поправка: О.П. п.3.4.30.г | C30: Разработка грунта вручную в траншеях глубиной до 2 м без креплений с откосами группа грунтов 1-3 | D30: =Source!DW29 -> 100 м3 грунта | E30: =Source!I29 -> 0.03672 | Q30: =ROUND((Source!DN29/100)*ROUND((ROUND((Source!AF29*Source!AV29*Source!I29),2)),2), 2) -> 103.2 | R30: =Source!X29 -> 2951.03 | S30: =ROUND((Source!DO29/100)*ROUND((ROUND((Source!AF29*Source!AV29*Source!I29),2)),2), 2) -> 75.68 | T30: =Source!Y29 -> 1390.72 | U30: =ROUND((175/100)*ROUND((ROUND((Source!AE29*Source!AV29*Source!I29),2)),2), 2) -> 0 | V30: =ROUND((160/100)*ROUND(ROUND((ROUND((Source!AE29*Source!AV29*Source!I29),2)*Source!BS29),2), 2), 2) -> 0 | AI30: 0
C31: ="Объем: "&Source!I29&"=12,24*"&"0,3/"&"100" -> Объем: 0,03672=12,24*0,3/100
C32: ЗП | F32: =Source!AO29 -> 2042.62 | G32: =Source!DG29 -> *1,05 | H32: =Source!AV29 -> 1.248 | I32: =ROUND((ROUND((Source!AF29*Source!AV29*Source!I29),2)),2) -> 98.29 | J32: =IF(Source!BA29<> 0, Source!BA29, 1) -> 34.51 | K32: =Source!S29 -> 3391.99 | W32: =I32 -> 98.29
C33: НР от ЗП | D33: % | E33: =Source!DN29 -> 105 | I33: =SUM(Q30:Q32) -> 103.2 | J33: =Source!BZ29 -> 87 | K33: =SUM(R30:R32) -> 2951.03
C34: СП от ЗП | D34: % | E34: =Source!DO29 -> 77 | I34: =SUM(S30:S33) -> 75.68 | J34: =Source!CA29 -> 41 | K34: =SUM(T30:T33) -> 1390.72
C35: ЗТР | D35: чел-ч | E35: =Source!AQ29 -> 192.7 | G35: =Source!DI29 -> *1,05 | H35: =Source!AV29 -> 1.248 | I35: =Source!U29 -> 9.272317 | AB35: =I35 -> 9.272317
C36: Всего по позиции: | H36: =I32+I33+I34+0 -> 277.17 | J36: =K32+K33+K34+0 -> 7733.74 | O36: =I32+I33+I34+0 -> 277.17 | P36: =K32+K33+K34+0 -> 7733.74 | X36: =IF(Source!BI29<=1,I32+I33+I34-0, 0) -> 277.17 | Y36: =IF(Source!BI29=2,I32+I33+I34-0, 0) -> 0 | Z36: =IF(Source!BI29=3,I32+I33+I34-0, 0) -> 0 | AA36: =IF(Source!BI29=4,I32+I33+I34,0) -> 0
A38: 2 | B38: 3.1-7-2 Поправка: О.П. п.3.4.30.г | C38: Разработка грунта с погрузкой на автомобили-самосвалы экскаваторами с ковшом вместимостью 0,25 м3 группа грунтов 1-3 | D38: =Source!DW31 -> 100 м3 грунта | E38: =Source!I31 -> 0.0481 | Q38: =ROUND((Source!DN31/100)*ROUND((ROUND((Source!AF31*Source!AV31*Source!I31),2)),2), 2) -> 1.78 | R38: =Source!X31 -> 59.04 | S38: =ROUND((Source!DO31/100)*ROUND((ROUND((Source!AF31*Source!AV31*Source!I31),2)),2), 2) -> 1.4 | T38: =Source!Y31 -> 32.03 | U38: =ROUND((175/100)*ROUND((ROUND((Source!AE31*Source!AV31*Source!I31),2)),2), 2) -> 13.97 | V38: =ROUND((160/100)*ROUND(ROUND((ROUND((Source!AE31*Source!AV31*Source!I31),2)*Source!BS31),2), 2), 2) -> 440.62 | AI38: 0
C39: ="Объем: "&Source!I31&"=4,81/"&"100" -> Объем: 0,0481=4,81/100
C40: ЗП | F40: =Source!AO31 -> 30.15 | G40: =Source!DG31 -> *1,05 | H40: =Source!AV31 -> 1.192 | I40: =ROUND((ROUND((Source!AF31*Source!AV31*Source!I31),2)),2) -> 1.82 | J40: =IF(Source!BA31<> 0, Source!BA31, 1) -> 34.51 | K40: =Source!S31 -> 62.81 | W40: =I40 -> 1.82
C41: ЭМ | F41: =Source!AM31 -> 1340.63 | G41: =Source!DE31 -> *1,05 | H41: =Source!AV31 -> 1.192 | I41: =(ROUND((ROUND((((Source!ET31*1.05))*Source!AV31*Source!I31),2)),2)+ROUND((ROUND(((Source!AE31-((Source!EU31*1.05)))*Source!AV31*Source!I31),2)),2)) -> 80.71 | J41: =IF(Source!BB31<> 0, Source!BB31, 1) -> 12.15 | K41: =Source!Q31 -> 980.63
C42: в т.ч. ЗПМ | F42: =Source!AN31 -> 132.48 | G42: =Source!DF31 -> *1,05 | H42: =Source!AV31 -> 1.192 | I42: =ROUND((ROUND((Source!AE31*Source!AV31*Source!I31),2)),2) -> 7.98 | J42: =IF(Source!BS31<> 0, Source!BS31, 1) -> 34.51 | K42: =Source!R31 -> 275.39 | W42: =I42 -> 7.98
C43: НР от ЗП | D43: % | E43: =Source!DN31 -> 98 | I43: =SUM(Q38:Q42) -> 1.78 | J43: =Source!BZ31 -> 94 | K43: =SUM(R38:R42) -> 59.04
C44: СП от ЗП | D44: % | E44: =Source!DO31 -> 77 | I44: =SUM(S38:S43) -> 1.4 | J44: =Source!CA31 -> 51 | K44: =SUM(T38:T43) -> 32.03
C45: НР и СП от ЗПМ | D45: % | E45: =175 -> 175 | I45: =SUM(U38:U44) -> 13.97 | J45: =160 -> 160 | K45: =SUM(V38:V44) -> 440.62
C46: ЗТР | D46: чел-ч | E46: =Source!AQ31 -> 2.95 | G46: =Source!DI31 -> *1,05 | H46: =Source!AV31 -> 1.192 | I46: =Source!U31 -> 0.17759578 | AB46: =I46 -> 0.17759578
C47: Всего по позиции: | H47: =I40+I41+I43+I44+I45+0 -> 99.68 | J47: =K40+K41+K43+K44+K45+0 -> 1575.13 | O47: =I40+I41+I43+I44+I45+0 -> 99.68 | P47: =K40+K41+K43+K44+K45+0 -> 1575.13 | X47: =IF(Source!BI31<=1,I40+I41+I43+I44+I45-0, 0) -> 99.68 | Y47: =IF(Source!BI31=2,I40+I41+I43+I44+I45-0, 0) -> 0 | Z47: =IF(Source!BI31=3,I40+I41+I43+I44+I45-0, 0) -> 0 | AA47: =IF(Source!BI31=4,I40+I41+I43+I44+I45,0) -> 0
A49: 3 | B49: 3.1-3-2 Поправка: О.П. п.3.4.30.г | C49: Разработка грунта в отвал экскаваторами с ковшом вместимостью 0,25 м3 группа грунтов 1-3 | D49: =Source!DW33 -> 100 м3 грунта | E49: =Source!I33 -> 0.03758 | Q49: =ROUND((Source!DN33/100)*ROUND((ROUND((Source!AF33*Source!AV33*Source!I33),2)),2), 2) -> 0.56 | R49: =Source!X33 -> 18.49 | S49: =ROUND((Source!DO33/100)*ROUND((ROUND((Source!AF33*Source!AV33*Source!I33),2)),2), 2) -> 0.44 | T49: =Source!Y33 -> 10.03 | U49: =ROUND((175/100)*ROUND((ROUND((Source!AE33*Source!AV33*Source!I33),2)),2), 2) -> 7.56 | V49: =ROUND((160/100)*ROUND(ROUND((ROUND((Source!AE33*Source!AV33*Source!I33),2)*Source!BS33),2), 2), 2) -> 238.53 | AI49: 0
C50: ="Объем: "&Source!I33&"=12,24/"&"100-"&""&Source!I29&"-"&""&Source!I31&"" -> Объем: 0,03758=12,24/100-0,03672-0,0481
C51: ЗП | F51: =Source!AO33 -> 12.16 | G51: =Source!DG33 -> *1,05 | H51: =Source!AV33 -> 1.192 | I51: =ROUND((ROUND((Source!AF33*Source!AV33*Source!I33),2)),2) -> 0.57 | J51: =IF(Source!BA33<> 0, Source!BA33, 1) -> 34.51 | K51: =Source!S33 -> 19.67 | W51: =I51 -> 0.57
C52: ЭМ | F52: =Source!AM33 -> 932.06 | G52: =Source!DE33 -> *1,05 | H52: =Source!AV33 -> 1.192 | I52: =(ROUND((ROUND((((Source!ET33*1.05))*Source!AV33*Source!I33),2)),2)+ROUND((ROUND(((Source!AE33-((Source!EU33*1.05)))*Source!AV33*Source!I33),2)),2)) -> 43.84 | J52: =IF(Source!BB33<> 0, Source!BB33, 1) -> 12.17 | K52: =Source!Q33 -> 533.53
C53: в т.ч. ЗПМ | F53: =Source!AN33 -> 91.89 | G53: =Source!DF33 -> *1,05 | H53: =Source!AV33 -> 1.192 | I53: =ROUND((ROUND((Source!AE33*Source!AV33*Source!I33),2)),2) -> 4.32 | J53: =IF(Source!BS33<> 0, Source!BS33, 1) -> 34.51 | K53: =Source!R33 -> 149.08 | W53: =I53 -> 4.32
C54: НР от ЗП | D54: % | E54: =Source!DN33 -> 98 | I54: =SUM(Q49:Q53) -> 0.56 | J54: =Source!BZ33 -> 94 | K54: =SUM(R49:R53) -> 18.49
C55: СП от ЗП | D55: % | E55: =Source!DO33 -> 77 | I55: =SUM(S49:S54) -> 0.44 | J55: =Source!CA33 -> 51 | K55: =SUM(T49:T54) -> 10.03
C56: НР и СП от ЗПМ | D56: % | E56: =175 -> 175 | I56: =SUM(U49:U55) -> 7.56 | J56: =160 -> 160 | K56: =SUM(V49:V55) -> 238.53
C57: ЗТР | D57: чел-ч | E57: =Source!AQ33 -> 1.19 | G57: =Source!DI33 -> *1,05 | H57: =Source!AV33 -> 1.192 | I57: =Source!U33 -> 0.055971802 | AB57: =I57 -> 0.055971802
C58: Всего по позиции: | H58: =I51+I52+I54+I55+I56+0 -> 52.97 | J58: =K51+K52+K54+K55+K56+0 -> 820.25 | O58: =I51+I52+I54+I55+I56+0 -> 52.97 | P58: =K51+K52+K54+K55+K56+0 -> 820.25 | X58: =IF(Source!BI33<=1,I51+I52+I54+I55+I56-0, 0) -> 52.97 | Y58: =IF(Source!BI33=2,I51+I52+I54+I55+I56-0, 0) -> 0 | Z58: =IF(Source!BI33=3,I51+I52+I54+I55+I56-0, 0) -> 0 | AA58: =IF(Source!BI33=4,I51+I52+I54+I55+I56,0) -> 0
A60: 4 | B60: 3.1-53-1 Поправка: О.П. п.3.4.30.г | C60: Засыпка вручную траншей, пазух котлованов и ям группа грунтов 1-3 | D60: =Source!DW35 -> 100 м3 грунта | E60: =Source!I35 -> 0.02406 | Q60: =ROUND((Source!DN35/100)*ROUND((ROUND((Source!AF35*Source!AV35*Source!I35),2)),2), 2) -> 34.8 | R60: =Source!X35 -> 994.98 | S60: =ROUND((Source!DO35/100)*ROUND((ROUND((Source!AF35*Source!AV35*Source!I35),2)),2), 2) -> 25.52 | T60: =Source!Y35 -> 468.9 | U60: =ROUND((175/100)*ROUND((ROUND((Source!AE35*Source!AV35*Source!I35),2)),2), 2) -> 0 | V60: =ROUND((160/100)*ROUND(ROUND((ROUND((Source!AE35*Source!AV35*Source!I35),2)*Source!BS35),2), 2), 2) -> 0 | AI60: 0
C61: ="Объем: "&Source!I35&"=8,02*"&"0,3/"&"100" -> Объем: 0,02406=8,02*0,3/100
C62: ЗП | F62: =Source!AO35 -> 1051.13 | G62: =Source!DG35 -> *1,05 | H62: =Source!AV35 -> 1.248 | I62: =ROUND((ROUND((Source!AF35*Source!AV35*Source!I35),2)),2) -> 33.14 | J62: =IF(Source!BA35<> 0, Source!BA35, 1) -> 34.51 | K62: =Source!S35 -> 1143.66 | W62: =I62 -> 33.14
C63: НР от ЗП | D63: % | E63: =Source!DN35 -> 105 | I63: =SUM(Q60:Q62) -> 34.8 | J63: =Source!BZ35 -> 87 | K63: =SUM(R60:R62) -> 994.98
C64: СП от ЗП | D64: % | E64: =Source!DO35 -> 77 | I64: =SUM(S60:S63) -> 25.52 | J64: =Source!CA35 -> 41 | K64: =SUM(T60:T63) -> 468.9
C65: ЗТР | D65: чел-ч | E65: =Source!AQ35 -> 107.04 | G65: =Source!DI35 -> *1,05 | H65: =Source!AV35 -> 1.248 | I65: =Source!U35 -> 3.3747811 | AB65: =I65 -> 3.3747811
C66: Всего по позиции: | H66: =I62+I63+I64+0 -> 93.46 | J66: =K62+K63+K64+0 -> 2607.54 | O66: =I62+I63+I64+0 -> 93.46 | P66: =K62+K63+K64+0 -> 2607.54 | X66: =IF(Source!BI35<=1,I62+I63+I64-0, 0) -> 93.46 | Y66: =IF(Source!BI35=2,I62+I63+I64-0, 0) -> 0 | Z66: =IF(Source!BI35=3,I62+I63+I64-0, 0) -> 0 | AA66: =IF(Source!BI35=4,I62+I63+I64,0) -> 0
A68: 5 | B68: 3.1-14-1 Поправка: О.П. п.3.4.30.г | C68: Засыпка траншей и котлованов бульдозерами мощностью 59 (80) кВт (л.с.) при перемещении грунта до 5 м группа грунтов 1-3 | D68: =Source!DW37 -> 100 м3 грунта | E68: =Source!I37 -> 0.05614 | Q68: =ROUND((Source!DN37/100)*ROUND((ROUND((Source!AF37*Source!AV37*Source!I37),2)),2), 2) -> 0 | R68: =Source!X37 -> 0 | S68: =ROUND((Source!DO37/100)*ROUND((ROUND((Source!AF37*Source!AV37*Source!I37),2)),2), 2) -> 0 | T68: =Source!Y37 -> 0 | U68: =ROUND((175/100)*ROUND((ROUND((Source!AE37*Source!AV37*Source!I37),2)),2), 2) -> 1.37 | V68: =ROUND((160/100)*ROUND(ROUND((ROUND((Source!AE37*Source!AV37*Source!I37),2)*Source!BS37),2), 2), 2) -> 43.07 | AI68: 0
C69: ="Объем: "&Source!I37&"=8,02*"&"0,7/"&"100" -> Объем: 0,05614=8,02*0,7/100
C70: ЭМ | F70: =Source!AM37 -> 130.01 | G70: =Source!DE37 -> *1,05 | H70: =Source!AV37 -> 1.014 | I70: =(ROUND((ROUND((((Source!ET37*1.05))*Source!AV37*Source!I37),2)),2)+ROUND((ROUND(((Source!AE37-((Source!EU37*1.05)))*Source!AV37*Source!I37),2)),2)) -> 7.77 | J70: =IF(Source!BB37<> 0, Source!BB37, 1) -> 12.08 | K70: =Source!Q37 -> 93.86
C71: в т.ч. ЗПМ | F71: =Source!AN37 -> 12.98 | G71: =Source!DF37 -> *1,05 | H71: =Source!AV37 -> 1.014 | I71: =ROUND((ROUND((Source!AE37*Source!AV37*Source!I37),2)),2) -> 0.78 | J71: =IF(Source!BS37<> 0, Source!BS37, 1) -> 34.51 | K71: =Source!R37 -> 26.92 | W71: =I71 -> 0.78
C72: НР и СП от ЗПМ | D72: % | E72: =175 -> 175 | I72: =SUM(U68:U71) -> 1.37 | J72: =160 -> 160 | K72: =SUM(V68:V71) -> 43.07
C73: Всего по позиции: | H73: =I70+I72+0 -> 9.14 | J73: =K70+K72+0 -> 136.93 | O73: =I70+I72+0 -> 9.14 | P73: =K70+K72+0 -> 136.93 | X73: =IF(Source!BI37<=1,I70+I72-0, 0) -> 9.14 | Y73: =IF(Source!BI37=2,I70+I72-0, 0) -> 0 | Z73: =IF(Source!BI37=3,I70+I72-0, 0) -> 0 | AA73: =IF(Source!BI37=4,I70+I72,0) -> 0
A76: =CONCATENATE("Итого по разделу: ",IF(Source!G59<>"Новый раздел", Source!G59, "")) -> Итого по разделу: Земляные работы | H76: =SUM(O29:O75) -> 532.42 | J76: =SUM(P29:P75) -> 12873.59
A77: Итого по ТСН-2001.16 | H77: =SUM(AC29:AC76) -> 0 | J77: =SUM(AD29:AD76) -> 0
A78: Итого возвратных сумм | H78: =SUM(AE29:AE77) -> 0 | J78: =SUM(AF29:AF77) -> 0
A80: =CONCATENATE("Раздел: ",IF(Source!G89<>"Новый раздел", Source!G89, "")) -> Раздел: Монтажные работы
A81: 16 | B81: 4.8-74-1 Поправка: О.П. п.3.4.30.г Поправка: Гл.4.Прил.2.2.п.2.2.3_04.00.01.01.001 | C81: Устройство постели при одном кабеле в траншее | D81: =Source!DW94 -> 100 М КАБЕЛЯ | E81: =Source!I94 -> 0.0765 | Q81: =ROUND((Source!DN94/100)*ROUND((ROUND((Source!AF94*Source!AV94*Source!I94),2)),2), 2) -> 8.62 | R81: =Source!X94 -> 244.47 | S81: =ROUND((Source!DO94/100)*ROUND((ROUND((Source!AF94*Source!AV94*Source!I94),2)),2), 2) -> 5.39 | T81: =Source!Y94 -> 114.26 | U81: =ROUND((175/100)*ROUND((ROUND((Source!AE94*Source!AV94*Source!I94),2)),2), 2) -> 10.38 | V81: =ROUND((160/100)*ROUND(ROUND((ROUND((Source!AE94*Source!AV94*Source!I94),2)*Source!BS94),2), 2), 2) -> 327.42 | AI81: 0
C82: ="Объем: "&Source!I94&"=25,5/"&"100*"&"0,3" -> Объем: 0,0765=25,5/100*0,3
C83: ЗП | F83: =Source!AO94 -> 74.91 | G83: =Source!DG94 -> *1,05)*1,2 | H83: =Source!AV94 -> 1.067 | I83: =ROUND((ROUND((Source!AF94*Source!AV94*Source!I94),2)),2) -> 7.7 | J83: =IF(Source!BA94<> 0, Source!BA94, 1) -> 34.51 | K83: =Source!S94 -> 265.73 | W83: =I83 -> 7.7
C84: ЭМ | F84: =Source!AM94 -> 379.77 | G84: =Source!DE94 -> *1,05)*1,2 | H84: =Source!AV94 -> 1.067 | I84: =(ROUND((ROUND(((((Source!ET94*1.05)*1.2))*Source!AV94*Source!I94),2)),2)+ROUND((ROUND(((Source!AE94-(((Source!EU94*1.05)*1.2)))*Source!AV94*Source!I94),2)),2)) -> 39.06 | J84: =IF(Source!BB94<> 0, Source!BB94, 1) -> 12.86 | K84: =Source!Q94 -> 502.31
C85: в т.ч. ЗПМ | F85: =Source!AN94 -> 57.67 | G85: =Source!DF94 -> *1,05)*1,2 | H85: =Source!AV94 -> 1.067 | I85: =ROUND((ROUND((Source!AE94*Source!AV94*Source!I94),2)),2) -> 5.93 | J85: =IF(Source!BS94<> 0, Source!BS94, 1) -> 34.51 | K85: =Source!R94 -> 204.64 | W85: =I85 -> 5.93
C86: НР от ЗП | D86: % | E86: =Source!DN94 -> 112 | I86: =SUM(Q81:Q85) -> 8.62 | J86: =Source!BZ94 -> 92 | K86: =SUM(R81:R85) -> 244.47
C87: СП от ЗП | D87: % | E87: =Source!DO94 -> 70 | I87: =SUM(S81:S86) -> 5.39 | J87: =Source!CA94 -> 43 | K87: =SUM(T81:T86) -> 114.26
C88: НР и СП от ЗПМ | D88: % | E88: =175 -> 175 | I88: =SUM(U81:U87) -> 10.38 | J88: =160 -> 160 | K88: =SUM(V81:V87) -> 327.42
C89: ЗТР | D89: чел-ч | E89: =Source!AQ94 -> 6.08 | G89: =Source!DI94 -> *1,05)*1,2 | H89: =Source!AV94 -> 1.067 | I89: =Source!U94 -> 0.62531663 | AB89: =I89 -> 0.62531663
C90: Всего по позиции: | H90: =I83+I84+I86+I87+I88+0 -> 71.15 | J90: =K83+K84+K86+K87+K88+0 -> 1454.19 | O90: =I83+I84+I86+I87+I88+0 -> 71.15 | P90: =K83+K84+K86+K87+K88+0 -> 1454.19 | X90: =IF(Source!BI94<=1,I83+I84+I86+I87+I88-0, 0) -> 0 | Y90: =IF(Source!BI94=2,I83+I84+I86+I87+I88-0, 0) -> 71.15 | Z90: =IF(Source!BI94=3,I83+I84+I86+I87+I88-0, 0) -> 0 | AA90: =IF(Source!BI94=4,I83+I84+I86+I87+I88,0) -> 0
A92: 17 | B92: 4.8-74-1 Поправка: О.П. п.3.4.30.г | C92: Устройство постели при одном кабеле в траншее | D92: =Source!DW96 -> 100 М КАБЕЛЯ | E92: =Source!I96 -> 0.1785 | Q92: =ROUND((Source!DN96/100)*ROUND((ROUND((Source!AF96*Source!AV96*Source!I96),2)),2), 2) -> 16.78 | R92: =Source!X96 -> 475.6 | S92: =ROUND((Source!DO96/100)*ROUND((ROUND((Source!AF96*Source!AV96*Source!I96),2)),2), 2) -> 10.49 | T92: =Source!Y96 -> 222.29 | U92: =ROUND((175/100)*ROUND((ROUND((Source!AE96*Source!AV96*Source!I96),2)),2), 2) -> 20.18 | V92: =ROUND((160/100)*ROUND(ROUND((ROUND((Source!AE96*Source!AV96*Source!I96),2)*Source!BS96),2), 2), 2) -> 636.64 | AI92: 0
C93: ="Объем: "&Source!I96&"=(25,5*"&"0,7)/"&"100" -> Объем: 0,1785=(25,5*0,7)/100
C94: ЗП | F94: =Source!AO96 -> 74.91 | G94: =Source!DG96 -> *1,05 | H94: =Source!AV96 -> 1.067 | I94: =ROUND((ROUND((Source!AF96*Source!AV96*Source!I96),2)),2) -> 14.98 | J94: =IF(Source!BA96<> 0, Source!BA96, 1) -> 34.51 | K94: =Source!S96 -> 516.96 | W94: =I94 -> 14.98
C95: ЭМ | F95: =Source!AM96 -> 379.77 | G95: =Source!DE96 -> *1,05 | H95: =Source!AV96 -> 1.067 | I95: =(ROUND((ROUND((((Source!ET96*1.05))*Source!AV96*Source!I96),2)),2)+ROUND((ROUND(((Source!AE96-((Source!EU96*1.05)))*Source!AV96*Source!I96),2)),2)) -> 75.95 | J95: =IF(Source!BB96<> 0, Source!BB96, 1) -> 12.86 | K95: =Source!Q96 -> 976.72
C96: в т.ч. ЗПМ | F96: =Source!AN96 -> 57.67 | G96: =Source!DF96 -> *1,05 | H96: =Source!AV96 -> 1.067 | I96: =ROUND((ROUND((Source!AE96*Source!AV96*Source!I96),2)),2) -> 11.53 | J96: =IF(Source!BS96<> 0, Source!BS96, 1) -> 34.51 | K96: =Source!R96 -> 397.9 | W96: =I96 -> 11.53
C97: НР от ЗП | D97: % | E97: =Source!DN96 -> 112 | I97: =SUM(Q92:Q96) -> 16.78 | J97: =Source!BZ96 -> 92 | K97: =SUM(R92:R96) -> 475.6
C98: СП от ЗП | D98: % | E98: =Source!DO96 -> 70 | I98: =SUM(S92:S97) -> 10.49 | J98: =Source!CA96 -> 43 | K98: =SUM(T92:T97) -> 222.29
C99: НР и СП от ЗПМ | D99: % | E99: =175 -> 175 | I99: =SUM(U92:U98) -> 20.18 | J99: =160 -> 160 | K99: =SUM(V92:V98) -> 636.64
C100: ЗТР | D100: чел-ч | E100: =Source!AQ96 -> 6.08 | G100: =Source!DI96 -> *1,05 | H100: =Source!AV96 -> 1.067 | I100: =Source!U96 -> 1.2158934 | AB100: =I100 -> 1.2158934
C101: Всего по позиции: | H101: =I94+I95+I97+I98+I99+0 -> 138.38 | J101: =K94+K95+K97+K98+K99+0 -> 2828.21 | O101: =I94+I95+I97+I98+I99+0 -> 138.38 | P101: =K94+K95+K97+K98+K99+0 -> 2828.21 | X101: =IF(Source!BI96<=1,I94+I95+I97+I98+I99-0, 0) -> 0 | Y101: =IF(Source!BI96=2,I94+I95+I97+I98+I99-0, 0) -> 138.38 | Z101: =IF(Source!BI96=3,I94+I95+I97+I98+I99-0, 0) -> 0 | AA101: =IF(Source!BI96=4,I94+I95+I97+I98+I99,0) -> 0
A103: 18 | B103: 4.8-74-2 Поправка: О.П. п.3.4.30.г Поправка: О.П. п.3.4.30.а | C103: Добавлять на каждый последующий кабель при устройстве постели (к норме и расценке 4.8-74-1) | D103: =Source!DW98 -> 100 М КАБЕЛЯ | E103: =Source!I98 -> 0.2085 | Q103: =ROUND((Source!DN98/100)*ROUND((ROUND((Source!AF98*Source!AV98*Source!I98),2)),2), 2) -> 8.81 | R103: =Source!X98 -> 249.86 | S103: =ROUND((Source!DO98/100)*ROUND((ROUND((Source!AF98*Source!AV98*Source!I98),2)),2), 2) -> 5.51 | T103: =Source!Y98 -> 116.78 | U103: =ROUND((175/100)*ROUND((ROUND((Source!AE98*Source!AV98*Source!I98),2)),2), 2) -> 8.1 | V103: =ROUND((160/100)*ROUND(ROUND((ROUND((Source!AE98*Source!AV98*Source!I98),2)*Source!BS98),2), 2), 2) -> 255.65 | AI103: 0
C104: ="Объем: "&Source!I98&"=69,5*"&"0,3/"&"100" -> Объем: 0,2085=69,5*0,3/100
C105: ЗП | F105: =Source!AO98 -> 28.09 | G105: =Source!DG98 -> *1,05)*1,2 | H105: =Source!AV98 -> 1.067 | I105: =ROUND((ROUND((Source!AF98*Source!AV98*Source!I98),2)),2) -> 7.87 | J105: =IF(Source!BA98<> 0, Source!BA98, 1) -> 34.51 | K105: =Source!S98 -> 271.59 | W105: =I105 -> 7.87
C106: ЭМ | F106: =Source!AM98 -> 108.86 | G106: =Source!DE98 -> *1,05)*1,2 | H106: =Source!AV98 -> 1.067 | I106: =(ROUND((ROUND(((((Source!ET98*1.05)*1.2))*Source!AV98*Source!I98),2)),2)+ROUND((ROUND(((Source!AE98-(((Source!EU98*1.05)*1.2)))*Source!AV98*Source!I98),2)),2)) -> 30.51 | J106: =IF(Source!BB98<> 0, Source!BB98, 1) -> 12.86 | K106: =Source!Q98 -> 392.36
C107: в т.ч. ЗПМ | F107: =Source!AN98 -> 16.53 | G107: =Source!DF98 -> *1,05)*1,2 | H107: =Source!AV98 -> 1.067 | I107: =ROUND((ROUND((Source!AE98*Source!AV98*Source!I98),2)),2) -> 4.63 | J107: =IF(Source!BS98<> 0, Source!BS98, 1) -> 34.51 | K107: =Source!R98 -> 159.78 | W107: =I107 -> 4.63
C108: НР от ЗП | D108: % | E108: =Source!DN98 -> 112 | I108: =SUM(Q103:Q107) -> 8.81 | J108: =Source!BZ98 -> 92 | K108: =SUM(R103:R107) -> 249.86
C109: СП от ЗП | D109: % | E109: =Source!DO98 -> 70 | I109: =SUM(S103:S108) -> 5.51 | J109: =Source!CA98 -> 43 | K109: =SUM(T103:T108) -> 116.78
C110: НР и СП от ЗПМ | D110: % | E110: =175 -> 175 | I110: =SUM(U103:U109) -> 8.1 | J110: =160 -> 160 | K110: =SUM(V103:V109) -> 255.65
C111: ЗТР | D111: чел-ч | E111: =Source!AQ98 -> 2.28 | G111: =Source!DI98 -> *1,05)*1,2 | H111: =Source!AV98 -> 1.067 | I111: =Source!U98 -> 0.63911038 | AB111: =I111 -> 0.63911038
C112: Всего по позиции: | H112: =I105+I106+I108+I109+I110+0 -> 60.8 | J112: =K105+K106+K108+K109+K110+0 -> 1286.24 | O112: =I105+I106+I108+I109+I110+0 -> 60.8 | P112: =K105+K106+K108+K109+K110+0 -> 1286.24 | X112: =IF(Source!BI98<=1,I105+I106+I108+I109+I110-0, 0) -> 0 | Y112: =IF(Source!BI98=2,I105+I106+I108+I109+I110-0, 0) -> 60.8 | Z112: =IF(Source!BI98=3,I105+I106+I108+I109+I110-0, 0) -> 0 | AA112: =IF(Source!BI98=4,I105+I106+I108+I109+I110,0) -> 0
A114: 19 | B114: 4.8-74-2 Поправка: О.П. п.3.4.30.г | C114: Добавлять на каждый последующий кабель при устройстве постели (к норме и расценке 4.8-74-1) | D114: =Source!DW100 -> 100 М КАБЕЛЯ | E114: =Source!I100 -> 0.4865 | Q114: =ROUND((Source!DN100/100)*ROUND((ROUND((Source!AF100*Source!AV100*Source!I100),2)),2), 2) -> 17.15 | R114: =Source!X100 -> 486.08 | S114: =ROUND((Source!DO100/100)*ROUND((ROUND((Source!AF100*Source!AV100*Source!I100),2)),2), 2) -> 10.72 | T114: =Source!Y100 -> 227.19 | U114: =ROUND((175/100)*ROUND((ROUND((Source!AE100*Source!AV100*Source!I100),2)),2), 2) -> 15.77 | V114: =ROUND((160/100)*ROUND(ROUND((ROUND((Source!AE100*Source!AV100*Source!I100),2)*Source!BS100),2), 2), 2) -> 497.5 | AI114: 0
C115: ="Объем: "&Source!I100&"=(69,5*"&"0,7)/"&"100" -> Объем: 0,4865=(69,5*0,7)/100
C116: ЗП | F116: =Source!AO100 -> 28.09 | G116: =Source!DG100 -> *1,05 | H116: =Source!AV100 -> 1.067 | I116: =ROUND((ROUND((Source!AF100*Source!AV100*Source!I100),2)),2) -> 15.31 | J116: =IF(Source!BA100<> 0, Source!BA100, 1) -> 34.51 | K116: =Source!S100 -> 528.35 | W116: =I116 -> 15.31
...

Sheet Source
A1: 0 | B1: Smeta.RU (495) 974-1589 | D1: _PS_ | F1: 0 | G1: 0 | H1: 0 | I1: Smeta.RU | K1: 1 | L1: 75112 | M1: 10 | N1: 11 | O1: 15 | P1: 0 | Q1: 1
A12: 1 | B12: 519 | C12: 1 | D12: =ROW(A484) -> 484 | E12: 0 | F12: 02-01-01 КЛ - 10 кВ траншея | G12: 02-01-01 | I12: 0 | K12: 0 | L12: 0 | M12: 4098 | O12: 0 | P12: 0 | Q12: 0 | R12: 175 | S12: 160 | T12: 1 | V12: 0 | BB12: 0 | BH12: Сметные нормы списания | BI12: Коды ОКП для ТСН-2001 МГЭ (История развития) | BJ12: 1 | BK12: 1 | BL12: 0 | BM12: 0 | BN12: 1 | BO12: 0 | BP12: 6 | BQ12: 2 | BR12: 1 | BS12: 1 | BT12: 0 | BU12: 0 | BV12: 0 | BW12: 0 | BX12: 0 | BZ12: Типовой расчет для ТСН-2001 МГЭ, Новая методика с выпуска доп. 43 (Строительство), Доп 73 | CA12: История развития для ТСН-2001 (МГЭ) 73 доп от 17.07.2024 | CB12: История развития для ТСН-2001 (МГЭ) 73 доп от 17.07.2024 | CC12: История развития для ТСН-2001 (МГЭ) 73 доп от 17.07.2024 | CD12: История развития для ТСН-2001 (МГЭ) 73 доп от 17.07.2024 | CE12: Поправки для ТСН-2001 от 16.04.2024 г. доп.72 | CF12: 0 | CG12: 0 | CH12: 8 | CK12: 79 | CQ12: Территориальные сметные нормативы для Москвы (ТСН-2001) | CR12: ТЕР | CS12: 41660 | CT12: 1 | CU12: 73 | CY12: 0 | EC12: 0
A15: 15 | B15: 1
A18: 52 | B18: =B484 -> 519 | C18: =C484 -> 1 | D18: =D484 -> 12 | E18: =E484 -> 0 | F18: =F484 -> 02-01-01 КЛ - 10 кВ траншея | G18: =G484 -> 02-01-01 | O18: =O484 -> 32252.82 | P18: =P484 -> 30165.58 | Q18: =Q484 -> 1076.15 | R18: =R484 -> 131.64 | S18: =S484 -> 1011.09 | T18: =T484 -> 0 | U18: =U484 -> 87.630626 | V18: =V484 -> 0 | ... GX18: =GX484 -> 0
A20: 3 | B20: 1 | D20: =ROW(A454) -> 454 | F20: Новая локальная смета | G20: Строительство КЛ 10 кВ | I20: 0 | K20: -1 | L20: Новая локальная смета | S20: 0 | T20: 0 | V20: 0 | BX20: 0 | CF20: 0 | CG20: 0
A22: 52 | B22: =B454 -> 1 | C22: =C454 -> 3 | D22: =D454 -> 20 | E22: =E454 -> 0 | F22: =F454 -> Новая локальная смета | G22: =G454 -> Строительство КЛ 10 кВ | O22: =O454 -> 32252.82 | P22: =P454 -> 30165.58 | Q22: =Q454 -> 1076.15 | R22: =R454 -> 131.64 | S22: =S454 -> 1011.09 | T22: =T454 -> 0 | U22: =U454 -> 87.630626 | V22: =V454 -> 0 | ... GX22: =GX454 -> 0
A24: 4 | B24: 1 | D24: =ROW(A59) -> 59 | F24: Новый раздел | G24: Земляные работы | I24: 0 | K24: 0 | S24: 0 | T24: 0 | V24: 0 | BX24: 0 | CJ24: 0
A26: 52 | B26: =B59 -> 1 | C26: =C59 -> 4 | D26: =D59 -> 24 | E26: =E59 -> 0 | F26: =F59 -> Новый раздел | G26: =G59 -> Земляные работы | O26: =O59 -> 266.14 | P26: =P59 -> 0 | Q26: =Q59 -> 132.32 | R26: =R59 -> 13.08 | S26: =S59 -> 133.82 | T26: =T59 -> 0 | U26: =U59 -> 12.880666 | V26: =V59 -> 0 | ... GX26: =GX59 -> 0
A28: 17 | B28: 1 | D28: =ROW(EtalonRes!A1) -> 1 | E28: 1 | F28: 3.1-51-1 | G28: Разработка грунта вручную в траншеях глубиной до 2 м без креплений с откосами группа грунтов 1-3 | H28: 100 м3 грунта | I28: =ROUND(12.24*0.3/100,9) -> 0.03672 | J28: 0 | K28: =ROUND(12.24*0.3/100,9) -> 0.03672 | O28: =ROUND(CP28,2) -> 98.29 | P28: =ROUND((ROUND((AC28*AW28*I28),2)*BC28),2) -> 0 | Q28: =(ROUND((ROUND((((ET28*1.05))*AV28*I28),2)*BB28),2)+ROUND((ROUND(((AE28-((EU28*1.05)))*AV28*I28),2)*BS28),2)) -> 0 | R28: =ROUND((ROUND((AE28*AV28*I28),2)*BS28),2) -> 0 | S28: =ROUND((ROUND((AF28*AV28*I28),2)*BA28),2) -> 98.29 | T28: =ROUND(CU28*I28,2) -> 0 | U28: =CV28*I28 -> 9.272317 | V28: =CW28*I28 -> 0 | W28: =ROUND(CX28*I28,2) -> 0 | X28: =ROUND(CY28,2) -> 103.2 | Y28: =ROUND(CZ28,2) -> 75.68 | AA28: 56622490 | AB28: =ROUND((AC28+AD28+AF28),6) -> 2144.751 | AC28: =ROUND((ES28),6) -> 0 | AD28: =ROUND(((((ET28*1.05))-((EU28*1.05)))+AE28),6) -> 0 | AE28: =ROUND(((EU28*1.05)),6) -> 0 | AF28: =ROUND(((EV28*1.05)),6) -> 2144.751 | AG28: =ROUND((AP28),6) -> 0 | AH28: =((EW28*1.05)) -> 202.335 | AI28: =((EX28*1.05)) -> 0 | AJ28: =(AS28) -> 0 | AK28: 2042.62 | AL28: 0 | AM28: 0 | AN28: 0 | AO28: 2042.62 | AP28: 0 | AQ28: 192.7 | AR28: 0 | AS28: 0 | AT28: 105 | AU28: 77 | AV28: 1.248 | AW28: 1 | AZ28: 1 | BA28: 1 | BB28: 1 | BC28: 1 | BH28: 0 | BI28: 1 | BJ28: ТСН-2001.3. Доп. 1-42. Сб. 1, т. 51, поз. 1 | BM28: 16 | BN28: 0 | BP28: 0 | BQ28: 30 | BR28: 0 | BS28: 1 | BT28: 1 | BU28: 1 | BV28: 1 | BW28: 1 | BX28: 1 | BZ28: 105 | CA28: 77 | CE28: 30 | CF28: 0 | CG28: 0 | CM28: 0 | CN28: Поправка: О.П. п.3.4.30.г Наименование: В отношении объектов, реализуемых с привлечением средств бюджета города Москвы, затраты, учитывающие усложненные условия производства работ (стесненность, сложность складирования и транспортной логистики, наличие в зоне производства работ действующего технологического оборудования или движения технологического транспорта и т.п.), определяются заказчиком в задании на проектирование при составлении локальных сметных расчетов (смет): для объектов города Москвы, расположенных за пределами Московской кольцевой автомобильной дороги | CO28: 0 | CP28: =(P28+Q28+S28) -> 98.29 | CQ28: =ROUND((ROUND((AC28*AW28*1),2)*BC28),2) -> 0 | CR28: =(ROUND((ROUND((((ET28*1.05))*AV28*1),2)*BB28),2)+ROUND((ROUND(((AE28-((EU28*1.05)))*AV28*1),2)*BS28),2)) -> 0 | CS28: =ROUND((ROUND((AE28*AV28*1),2)*BS28),2) -> 0 | CT28: =ROUND((ROUND((AF28*AV28*1),2)*BA28),2) -> 2676.65 | CU28: =AG28 -> 0 | CV28: =(AH28*AV28) -> 252.51408 | CW28: =AI28 -> 0 | CX28: =AJ28 -> 0 | CY28: =((S28*BZ28)/100) -> 103.2045 | CZ28: =((S28*CA28)/100) -> 75.6833 | DB28: 1 | DE28: *1,05 | DF28: *1,05 | DG28: *1,05 | DI28: *1,05 | DJ28: *1,05 | DN28: 0 | DO28: 0 | DP28: 1 | DQ28: 1 | DU28: 1013 | DV28: 100 м3 грунта | DW28: 100 м3 грунта | DX28: 1 | EE28: 51696099 | EF28: 30 | EG28: Строительные работы | EH28: 0 | EJ28: 1 | EK28: 16 | EL28: ТСН-2001.3-1. 1-49...1-55 | EM28: ТСН-2001.3-1-15 | EO28: Поправка: О.П. п.3.4.30.г | EQ28: 131072 | ER28: 2042.62 | ES28: 0 | ET28: 0 | EU28: 0 | EV28: 2042.62 | EW28: 192.7 | EX28: 0 | EY28: 0 | FQ28: 0 | FR28: 0 | FS28: 0 | FX28: 105 | FY28: 77 | GD28: 0 | GF28: -2104602307 | GG28: 2 | GH28: 1 | GI28: -2 | GJ28: 0 | GK28: =ROUND(R28*(R12)/100,2) -> 0 | GL28: =ROUND(IF(AND(BH28=3,BI28=3,FS28<>0),P28,0),2) -> 0 | GM28: =ROUND(O28+X28+Y28+GK28,2)+GX28 -> 277.17 | GN28: =IF(OR(BI28=0,BI28=1),GM28-GX28,0) -> 277.17 | GO28: =IF(BI28=2,GM28-GX28,0) -> 0 | GP28: =IF(BI28=4,GM28-GX28,0) -> 0 | GR28: 0 | GS28: 0 | GT28: 0 | GV28: =ROUND((GT28),6) -> 0 | GW28: 1 | GX28: =ROUND(HC28*I28,2) -> 0 | HA28: 0 | HB28: 0 | HC28: =GV28*GW28 -> 0 | HS28: 0 | IK28: 0
A29: 17 | B29: 1 | D29: =ROW(EtalonRes!A2) -> 2 | E29: 1 | F29: 3.1-51-1 | G29: Разработка грунта вручную в траншеях глубиной до 2 м без креплений с откосами группа грунтов 1-3 | H29: 100 м3 грунта | I29: =ROUND(12.24*0.3/100,9) -> 0.03672 | J29: 0 | K29: =ROUND(12.24*0.3/100,9) -> 0.03672 | O29: =ROUND(CP29,2) -> 3391.99 | P29: =ROUND((ROUND((AC29*AW29*I29),2)*BC29),2) -> 0 | Q29: =(ROUND((ROUND((((ET29*1.05))*AV29*I29),2)*BB29),2)+ROUND((ROUND(((AE29-((EU29*1.05)))*AV29*I29),2)*BS29),2)) -> 0 | R29: =ROUND((ROUND((AE29*AV29*I29),2)*BS29),2) -> 0 | S29: =ROUND((ROUND((AF29*AV29*I29),2)*BA29),2) -> 3391.99 | T29: =ROUND(CU29*I29,2) -> 0 | U29: =CV29*I29 -> 9.272317 | V29: =CW29*I29 -> 0 | W29: =ROUND(CX29*I29,2) -> 0 | X29: =ROUND(CY29,2) -> 2951.03 | Y29: =ROUND(CZ29,2) -> 1390.72 | AA29: 56610029 | AB29: =ROUND((AC29+AD29+AF29),6) -> 2144.751 | AC29: =ROUND((ES29),6) -> 0 | AD29: =ROUND(((((ET29*1.05))-((EU29*1.05)))+AE29),6) -> 0 | AE29: =ROUND(((EU29*1.05)),6) -> 0 | AF29: =ROUND(((EV29*1.05)),6) -> 2144.751 | AG29: =ROUND((AP29),6) -> 0 | AH29: =((EW29*1.05)) -> 202.335 | AI29: =((EX29*1.05)) -> 0 | AJ29: =(AS29) -> 0 | AK29: 2042.62 | AL29: 0 | AM29: 0 | AN29: 0 | AO29: 2042.62 | AP29: 0 | AQ29: 192.7 | AR29: 0 | AS29: 0 | AT29: 87 | AU29: 41 | AV29: 1.248 | AW29: 1 | AZ29: 1 | BA29: 34.51 | BB29: 1 | BC29: 1 | BH29: 0 | BI29: 1 | BJ29: ТСН-2001.3. Доп. 1-42. Сб. 1, т. 51, поз. 1 | BM29: 16 | BN29: 0 | BO29: 3.1-51-1 | BP29: 1 | BQ29: 30 | BR29: 0 | BS29: 34.51 | BT29: 1 | BU29: 1 | BV29: 1 | BW29: 1 | BX29: 1 | BZ29: 87 | CA29: 41 | CE29: 30 | CF29: 0 | CG29: 0 | CM29: 0 | CN29: Поправка: О.П. п.3.4.30.г Наименование: В отношении объектов, реализуемых с привлечением средств бюджета города Москвы, затраты, учитывающие усложненные условия производства работ (стесненность, сложность складирования и транспортной логистики, наличие в зоне производства работ действующего технологического оборудования или движения технологического транспорта и т.п.), определяются заказчиком в задании на проектирование при составлении локальных сметных расчетов (смет): для объектов города Москвы, расположенных за пределами Московской кольцевой автомобильной дороги | CO29: 0 | CP29: =(P29+Q29+S29) -> 3391.99 | CQ29: =ROUND((ROUND((AC29*AW29*1),2)*BC29),2) -> 0 | CR29: =(ROUND((ROUND((((ET29*1.05))*AV29*1),2)*BB29),2)+ROUND((ROUND(((AE29-((EU29*1.05)))*AV29*1),2)*BS29),2)) -> 0 | CS29: =ROUND((ROUND((AE29*AV29*1),2)*BS29),2) -> 0 | CT29: =ROUND((ROUND((AF29*AV29*1),2)*BA29),2) -> 92371.19 | CU29: =AG29 -> 0 | CV29: =(AH29*AV29) -> 252.51408 | CW29: =AI29 -> 0 | CX29: =AJ29 -> 0 | CY29: =S29*(BZ29/100) -> 2951.0313 | CZ29: =S29*(CA29/100) -> 1390.7159 | DB29: 2 | DE29: *1,05 | DF29: *1,05 | DG29: *1,05 | DI29: *1,05 | DJ29: *1,05 | DN29: 105 | DO29: 77 | DP29: 1.248 | DQ29: 1 | DU29: 1013 | DV29: 100 м3 грунта | DW29: 100 м3 грунта | DX29: 1 | EE29: 51696099 | EF29: 30 | EG29: Строительные работы | EH29: 0 | EJ29: 1 | EK29: 16 | EL29: ТСН-2001.3-1. 1-49...1-55 | EM29: ТСН-2001.3-1-15 | EO29: Поправка: О.П. п.3.4.30.г | EQ29: 131072 | ER29: 2042.62 | ES29: 0 | ET29: 0 | EU29: 0 | EV29: 2042.62 | EW29: 192.7 | EX29: 0 | EY29: 0 | FQ29: 0 | FR29: 0 | FS29: 0 | FX29: 105 | FY29: 77 | GD29: 0 | GF29: -2104602307 | GG29: 2 | GH29: 1 | GI29: 2 | GJ29: 0 | GK29: =ROUND(R29*(S12)/100,2) -> 0 | GL29: =ROUND(IF(AND(BH29=3,BI29=3,FS29<>0),P29,0),2) -> 0 | GM29: =ROUND(O29+X29+Y29+GK29,2)+GX29 -> 7733.74 | GN29: =IF(OR(BI29=0,BI29=1),GM29-GX29,0) -> 7733.74 | GO29: =IF(BI29=2,GM29-GX29,0) -> 0 | GP29: =IF(BI29=4,GM29-GX29,0) -> 0 | GR29: 0 | GS29: 3 | GT29: 0 | GV29: =ROUND((GT29),6) -> 0 | GW29: 1 | GX29: =ROUND(HC29*I29,2) -> 0 | HA29: 0 | HB29: 0 | HC29: =GV29*GW29 -> 0 | HS29: 0 | IK29: 0
A30: 17 | B30: 1 | D30: =ROW(EtalonRes!A5) -> 5 | E30: 2 | F30: 3.1-7-2 | G30: Разработка грунта с погрузкой на автомобили-самосвалы экскаваторами с ковшом вместимостью 0,25 м3 группа грунтов 1-3 | H30: 100 м3 грунта | I30: =ROUND(4.81/100,9) -> 0.0481 | J30: 0 | K30: =ROUND(4.81/100,9) -> 0.0481 | O30: =ROUND(CP30,2) -> 82.53 | P30: =ROUND((ROUND((AC30*AW30*I30),2)*BC30),2) -> 0 | Q30: =(ROUND((ROUND((((ET30*1.05))*AV30*I30),2)*BB30),2)+ROUND((ROUND(((AE30-((EU30*1.05)))*AV30*I30),2)*BS30),2)) -> 80.71 | R30: =ROUND((ROUND((AE30*AV30*I30),2)*BS30),2) -> 7.98 | S30: =ROUND((ROUND((AF30*AV30*I30),2)*BA30),2) -> 1.82 | T30: =ROUND(CU30*I30,2) -> 0 | U30: =CV30*I30 -> 0.17759578 | V30: =CW30*I30 -> 0 | W30: =ROUND(CX30*I30,2) -> 0 | X30: =ROUND(CY30,2) -> 1.78 | Y30: =ROUND(CZ30,2) -> 1.4 | AA30: 56622490 | AB30: =ROUND((AC30+AD30+AF30),6) -> 1439.319 | AC30: =ROUND((ES30),6) -> 0 | AD30: =ROUND(((((ET30*1.05))-((EU30*1.05)))+AE30),6) -> 1407.6615 | AE30: =ROUND(((EU30*1.05)),6) -> 139.104 | AF30: =ROUND(((EV30*1.05)),6) -> 31.6575 | AG30: =ROUND((AP30),6) -> 0 | AH30: =((EW30*1.05)) -> 3.0975 | AI30: =((EX30*1.05)) -> 0 | AJ30: =(AS30) -> 0 | AK30: 1370.78 | AL30: 0 | AM30: 1340.63 | AN30: 132.48 | AO30: 30.15 | AP30: 0 | AQ30: 2.95 | AR30: 0 | AS30: 0 | AT30: 98 | AU30: 77 | AV30: 1.192 | AW30: 1 | AZ30: 1 | BA30: 1 | BB30: 1 | BC30: 1 | BH30: 0 | BI30: 1 | BJ30: ТСН-2001.3 Доп. 70, Сб. 1, т. 7, поз. 2 | BM30: 2 | BN30: 0 | BP30: 0 | BQ30: 30 | BR30: 0 | BS30: 1 | BT30: 1 | BU30: 1 | BV30: 1 | BW30: 1 | BX30: 1 | BZ30: 98 | CA30: 77 | CE30: 30 | CF30: 0 | CG30: 0 | CM30: 0 | CN30: Поправка: О.П. п.3.4.30.г Наименование: В отношении объектов, реализуемых с привлечением средств бюджета города Москвы, затраты, учитывающие усложненные условия производства работ (стесненность, сложность складирования и транспортной логистики, наличие в зоне производства работ действующего технологического оборудования или движения технологического транспорта и т.п.), определяются заказчиком в задании на проектирование при составлении локальных сметных расчетов (смет): для объектов города Москвы, расположенных за пределами Московской кольцевой автомобильной дороги | CO30: 0 | CP30: =(P30+Q30+S30) -> 82.53 | CQ30: =ROUND((ROUND((AC30*AW30*1),2)*BC30),2) -> 0 | CR30: =(ROUND((ROUND((((ET30*1.05))*AV30*1),2)*BB30),2)+ROUND((ROUND(((AE30-((EU30*1.05)))*AV30*1),2)*BS30),2)) -> 1677.93 | CS30: =ROUND((ROUND((AE30*AV30*1),2)*BS30),2) -> 165.81 | CT30: =ROUND((ROUND((AF30*AV30*1),2)*BA30),2) -> 37.74 | CU30: =AG30 -> 0 | CV30: =(AH30*AV30) -> 3.69222 | CW30: =AI30 -> 0 | CX30: =AJ30 -> 0 | CY30: =((S30*BZ30)/100) -> 1.7836 | CZ30: =((S30*CA30)/100) -> 1.4014 | DB30: 3 | DE30: *1,05 | DF30: *1,05 | DG30: *1,05 | DI30: *1,05 | DJ30: *1,05 | DN30: 0 | DO30: 0 | DP30: 1 | DQ30: 1 | DU30: 1013 | DV30: 100 м3 грунта | DW30: 100 м3 грунта | DX30: 1 | EE30: 51696085 | EF30: 30 | EG30: Строительные работы | EH30: 0 | EJ30: 1 | EK30: 2 | EL30: ТСН-2001.3-1. 1-1...1-7 | EM30: ТСН-2001.3-1-1 | EO30: Поправка: О.П. п.3.4.30.г | EQ30: 131072 | ER30: 1370.78 | ES30: 0 | ET30: 1340.63 | EU30: 132.48 | EV30: 30.15 | EW30: 2.95 | EX30: 0 | EY30: 0 | FQ30: 0 | FR30: 0 | FS30: 0 | FX30: 98 | FY30: 77 | GD30: 0 | GF30: -1260581983 | GG30: 2 | GH30: 1 | GI30: -2 | GJ30: 0 | GK30: =ROUND(R30*(R12)/100,2) -> 13.97 | GL30: =ROUND(IF(AND(BH30=3,BI30=3,FS30<>0),P30,0),2) -> 0 | GM30: =ROUND(O30+X30+Y30+GK30,2)+GX30 -> 99.68 | GN30: =IF(OR(BI30=0,BI30=1),GM30-GX30,0) -> 99.68 | GO30: =IF(BI30=2,GM30-GX30,0) -> 0 | GP30: =IF(BI30=4,GM30-GX30,0) -> 0 | GR30: 0 | GS30: 0 | GT30: 0 | GV30: =ROUND((GT30),6) -> 0 | GW30: 1 | GX30: =ROUND(HC30*I30,2) -> 0 | HA30: 0 | HB30: 0 | HC30: =GV30*GW30 -> 0 | HS30: 0 | IK30: 0
A31: 17 | B31: 1 | D31: =ROW(EtalonRes!A8) -> 8 | E31: 2 | F31: 3.1-7-2 | G31: Разработка грунта с погрузкой на автомобили-самосвалы экскаваторами с ковшом вместимостью 0,25 м3 группа грунтов 1-3 | H31: 100 м3 грунта | I31: =ROUND(4.81/100,9) -> 0.0481 | J31: 0 | K31: =ROUND(4.81/100,9) -> 0.0481 | O31: =ROUND(CP31,2) -> 1043.44 | P31: =ROUND((ROUND((AC31*AW31*I31),2)*BC31),2) -> 0 | Q31: =(ROUND((ROUND((((ET31*1.05))*AV31*I31),2)*BB31),2)+ROUND((ROUND(((AE31-((EU31*1.05)))*AV31*I31),2)*BS31),2)) -> 980.63 | R31: =ROUND((ROUND((AE31*AV31*I31),2)*BS31),2) -> 275.39 | S31: =ROUND((ROUND((AF31*AV31*I31),2)*BA31),2) -> 62.81 | T31: =ROUND(CU31*I31,2) -> 0 | U31: =CV31*I31 -> 0.17759578 | V31: =CW31*I31 -> 0 | W31: =ROUND(CX31*I31,2) -> 0 | X31: =ROUND(CY31,2) -> 59.04 | Y31: =ROUND(CZ31,2) -> 32.03 | AA31: 56610029 | AB31: =ROUND((AC31+AD31+AF31),6) -> 1439.319 | AC31: =ROUND((ES31),6) -> 0 | AD31: =ROUND(((((ET31*1.05))-((EU31*1.05)))+AE31),6) -> 1407.6615 | AE31: =ROUND(((EU31*1.05)),6) -> 139.104 | AF31: =ROUND(((EV31*1.05)),6) -> 31.6575 | AG31: =ROUND((AP31),6) -> 0 | AH31: =((EW31*1.05)) -> 3.0975 | AI31: =((EX31*1.05)) -> 0 | AJ31: =(AS31) -> 0 | AK31: 1370.78 | AL31: 0 | AM31: 1340.63 | AN31: 132.48 | AO31: 30.15 | AP31: 0 | AQ31: 2.95 | AR31: 0 | AS31: 0 | AT31: 94 | AU31: 51 | AV31: 1.192 | AW31: 1 | AZ31: 1 | BA31: 34.51 | BB31: 12.15 | BC31: 1 | BH31: 0 | BI31: 1 | BJ31: ТСН-2001.3 Доп. 70, Сб. 1, т. 7, поз. 2 | BM31: 2 | BN31: 0 | BO31: 3.1-7-2 | BP31: 1 | BQ31: 30 | BR31: 0 | BS31: 34.51 | BT31: 1 | BU31: 1 | BV31: 1 | BW31: 1 | BX31: 1 | BZ31: 94 | CA31: 51 | CE31: 30 | CF31: 0 | CG31: 0 | CM31: 0 | CN31: Поправка: О.П. п.3.4.30.г Наименование: В отношении объектов, реализуемых с привлечением средств бюджета города Москвы, затраты, учитывающие усложненные условия производства работ (стесненность, сложность складирования и транспортной логистики, наличие в зоне производства работ действующего технологического оборудования или движения технологического транспорта и т.п.), определяются заказчиком в задании на проектирование при составлении локальных сметных расчетов (смет): для объектов города Москвы, расположенных за пределами Московской кольцевой автомобильной дороги | CO31: 0 | CP31: =(P31+Q31+S31) -> 1043.44 | CQ31: =ROUND((ROUND((AC31*AW31*1),2)*BC31),2) -> 0 | CR31: =(ROUND((ROUND((((ET31*1.05))*AV31*1),2)*BB31),2)+ROUND((ROUND(((AE31-((EU31*1.05)))*AV31*1),2)*BS31),2)) -> 20386.85 | CS31: =ROUND((ROUND((AE31*AV31*1),2)*BS31),2) -> 5722.1 | CT31: =ROUND((ROUND((AF31*AV31*1),2)*BA31),2) -> 1302.41 | CU31: =AG31 -> 0 | CV31: =(AH31*AV31) -> 3.69222 | CW31: =AI31 -> 0 | CX31: =AJ31 -> 0 | CY31: =S31*(BZ31/100) -> 59.0414 | CZ31: =S31*(CA31/100) -> 32.0331 | DB31: 4 | DE31: *1,05 | DF31: *1,05 | DG31: *1,05 | DI31: *1,05 | DJ31: *1,05 | DN31: 98 | DO31: 77 | DP31: 1.192 | DQ31: 1 | DU31: 1013 | DV31: 100 м3 грунта | DW31: 100 м3 грунта | DX31: 1 | EE31: 51696085 | EF31: 30 | EG31: Строительные работы | EH31: 0 | EJ31: 1 | EK31: 2 | EL31: ТСН-2001.3-1. 1-1...1-7 | EM31: ТСН-2001.3-1-1 | EO31: Поправка: О.П. п.3.4.30.г | EQ31: 131072 | ER31: 1370.78 | ES31: 0 | ET31: 1340.63 | EU31: 132.48 | EV31: 30.15 | EW31: 2.95 | EX31: 0 | EY31: 0 | FQ31: 0 | FR31: 0 | FS31: 0 | FX31: 98 | FY31: 77 | GD31: 0 | GF31: -1260581983 | GG31: 2 | GH31: 1 | GI31: 2 | GJ31: 0 | GK31: =ROUND(R31*(S12)/100,2) -> 440.62 | GL31: =ROUND(IF(AND(BH31=3,BI31=3,FS31<>0),P31,0),2) -> 0 | GM31: =ROUND(O31+X31+Y31+GK31,2)+GX31 -> 1575.13 | GN31: =IF(OR(BI31=0,BI31=1),GM31-GX31,0) -> 1575.13 | GO31: =IF(BI31=2,GM31-GX31,0) -> 0 | GP31: =IF(BI31=4,GM31-GX31,0) -> 0 | GR31: 0 | GS31: 3 | GT31: 0 | GV31: =ROUND((GT31),6) -> 0 | GW31: 1 | GX31: =ROUND(HC31*I31,2) -> 0 | HA31: 0 | HB31: 0 | HC31: =GV31*GW31 -> 0 | HS31: 0 | IK31: 0
A32: 17 | B32: 1 | D32: =ROW(EtalonRes!A10) -> 10 | E32: 3 | F32: 3.1-3-2 | G32: Разработка грунта в отвал экскаваторами с ковшом вместимостью 0,25 м3 группа грунтов 1-3 | H32: 100 м3 грунта | I32: =ROUND(12.24/100-I28-I30,9) -> 0.03758 | J32: 0 | K32: =ROUND(12.24/100-I28-I30,9) -> 0.03758 | O32: =ROUND(CP32,2) -> 44.41 | P32: =ROUND((ROUND((AC32*AW32*I32),2)*BC32),2) -> 0 | Q32: =(ROUND((ROUND((((ET32*1.05))*AV32*I32),2)*BB32),2)+ROUND((ROUND(((AE32-((EU32*1.05)))*AV32*I32),2)*BS32),2)) -> 43.84 | R32: =ROUND((ROUND((AE32*AV32*I32),2)*BS32),2) -> 4.32 | S32: =ROUND((ROUND((AF32*AV32*I32),2)*BA32),2) -> 0.57 | T32: =ROUND(CU32*I32,2) -> 0 | U32: =CV32*I32 -> 0.055971802 | V32: =CW32*I32 -> 0 | W32: =ROUND(CX32*I32,2) -> 0 | X32: =ROUND(CY32,2) -> 0.56 | Y32: =ROUND(CZ32,2) -> 0.44 | AA32: 56622490 | AB32: =ROUND((AC32+AD32+AF32),6) -> 991.431 | AC32: =ROUND((ES32),6) -> 0 | AD32: =ROUND(((((ET32*1.05))-((EU32*1.05)))+AE32),6) -> 978.663 | AE32: =ROUND(((EU32*1.05)),6) -> 96.4845 | AF32: =ROUND(((EV32*1.05)),6) -> 12.768 | AG32: =ROUND((AP32),6) -> 0 | AH32: =((EW32*1.05)) -> 1.2495 | AI32: =((EX32*1.05)) -> 0 | AJ32: =(AS32) -> 0 | AK32: 944.22 | AL32: 0 | AM32: 932.06 | AN32: 91.89 | AO32: 12.16 | AP32: 0 | AQ32: 1.19 | AR32: 0 | AS32: 0 | AT32: 98 | AU32: 77 | AV32: 1.192 | AW32: 1 | AZ32: 1 | BA32: 1 | BB32: 1 | BC32: 1 | BH32: 0 | BI32: 1 | BJ32: ТСН-2001.3 Доп. 68, Сб. 1, т. 3, поз. 2 | BM32: 2 | BN32: 0 | BP32: 0 | BQ32: 30 | BR32: 0 | BS32: 1 | BT32: 1 | BU32: 1 | BV32: 1 | BW32: 1 | BX32: 1 | BZ32: 98 | CA32: 77 | CE32: 30 | CF32: 0 | CG32: 0 | CM32: 0 | CN32: Поправка: О.П. п.3.4.30.г Наименование: В отношении объектов, реализуемых с привлечением средств бюджета города Москвы, затраты, учитывающие усложненные условия производства работ (стесненность, сложность складирования и транспортной логистики, наличие в зоне производства работ действующего технологического оборудования или движения технологического транспорта и т.п.), определяются заказчиком в задании на проектирование при составлении локальных сметных расчетов (смет): для объектов города Москвы, расположенных за пределами Московской кольцевой автомобильной дороги | CO32: 0 | CP32: =(P32+Q32+S32) -> 44.41 | CQ32: =ROUND((ROUND((AC32*AW32*1),2)*BC32),2) -> 0 | CR32: =(ROUND((ROUND((((ET32*1.05))*AV32*1),2)*BB32),2)+ROUND((ROUND(((AE32-((EU32*1.05)))*AV32*1),2)*BS32),2)) -> 1166.57 | CS32: =ROUND((ROUND((AE32*AV32*1),2)*BS32),2) -> 115.01 | CT32: =ROUND((ROUND((AF32*AV32*1),2)*BA32),2) -> 15.22 | CU32: =AG32 -> 0 | CV32: =(AH32*AV32) -> 1.489404 | CW32: =AI32 -> 0 | CX32: =AJ32 -> 0 | CY32: =((S32*BZ32)/100) -> 0.5586 | CZ32: =((S32*CA32)/100) -> 0.4389 | DB32: 5 | DE32: *1,05 | DF32: *1,05 | DG32: *1,05 | DI32: *1,05 | DJ32: *1,05 | DN32: 0 | DO32: 0 | DP32: 1 | DQ32: 1 | DU32: 1013 | DV32: 100 м3 грунта | DW32: 100 м3 грунта | DX32: 1 | EE32: 51696085 | EF32: 30 | EG32: Строительные работы | EH32: 0 | EJ32: 1 | EK32: 2 | EL32: ТСН-2001.3-1. 1-1...1-7 | EM32: ТСН-2001.3-1-1 | EO32: Поправка: О.П. п.3.4.30.г | EQ32: 131072 | ER32: 944.22 | ES32: 0 | ET32: 932.06 | EU32: 91.89 | EV32: 12.16 | EW32: 1.19 | EX32: 0 | EY32: 0 | FQ32: 0 | FR32: 0 | FS32: 0 | FX32: 98 | FY32: 77 | GD32: 0 | GF32: 864155608 | GG32: 2 | GH32: 1 | GI32: -2 | GJ32: 0 | GK32: =ROUND(R32*(R12)/100,2) -> 7.56 | GL32: =ROUND(IF(AND(BH32=3,BI32=3,FS32<>0),P32,0),2) -> 0 | GM32: =ROUND(O32+X32+Y32+GK32,2)+GX32 -> 52.97 | GN32: =IF(OR(BI32=0,BI32=1),GM32-GX32,0) -> 52.97 | GO32: =IF(BI32=2,GM32-GX32,0) -> 0 | GP32: =IF(BI32=4,GM32-GX32,0) -> 0 | GR32: 0 | GS32: 0 | GT32: 0 | GV32: =ROUND((GT32),6) -> 0 | GW32: 1 | GX32: =ROUND(HC32*I32,2) -> 0 | HA32: 0 | HB32: 0 | HC32: =GV32*GW32 -> 0 | HS32: 0 | IK32: 0
A33: 17 | B33: 1 | D33: =ROW(EtalonRes!A12) -> 12 | E33: 3 | F33: 3.1-3-2 | G33: Разработка грунта в отвал экскаваторами с ковшом вместимостью 0,25 м3 группа грунтов 1-3 | H33: 100 м3 грунта | I33: =ROUND(12.24/100-I29-I31,9) -> 0.03758 | J33: 0 | K33: =ROUND(12.24/100-I29-I31,9) -> 0.03758 | O33: =ROUND(CP33,2) -> 553.2 | P33: =ROUND((ROUND((AC33*AW33*I33),2)*BC33),2) -> 0 | Q33: =(ROUND((ROUND((((ET33*1.05))*AV33*I33),2)*BB33),2)+ROUND((ROUND(((AE33-((EU33*1.05)))*AV33*I33),2)*BS33),2)) -> 533.53 | R33: =ROUND((ROUND((AE33*AV33*I33),2)*BS33),2) -> 149.08 | S33: =ROUND((ROUND((AF33*AV33*I33),2)*BA33),2) -> 19.67 | T33: =ROUND(CU33*I33,2) -> 0 | U33: =CV33*I33 -> 0.055971802 | V33: =CW33*I33 -> 0 | W33: =ROUND(CX33*I33,2) -> 0 | X33: =ROUND(CY33,2) -> 18.49 | Y33: =ROUND(CZ33,2) -> 10.03 | AA33: 56610029 | AB33: =ROUND((AC33+AD33+AF33),6) -> 991.431 | AC33: =ROUND((ES33),6) -> 0 | AD33: =ROUND(((((ET33*1.05))-((EU33*1.05)))+AE33),6) -> 978.663 | AE33: =ROUND(((EU33*1.05)),6) -> 96.4845 | AF33: =ROUND(((EV33*1.05)),6) -> 12.768 | AG33: =ROUND((AP33),6) -> 0 | AH33: =((EW33*1.05)) -> 1.2495 | AI33: =((EX33*1.05)) -> 0 | AJ33: =(AS33) -> 0 | AK33: 944.22 | AL33: 0 | AM33: 932.06 | AN33: 91.89 | AO33: 12.16 | AP33: 0 | AQ33: 1.19 | AR33: 0 | AS33: 0 | AT33: 94 | AU33: 51 | AV33: 1.192 | AW33: 1 | AZ33: 1 | BA33: 34.51 | BB33: 12.17 | BC33: 1 | BH33: 0 | BI33: 1 | BJ33: ТСН-2001.3 Доп. 68, Сб. 1, т. 3, поз. 2 | BM33: 2 | BN33: 0 | BO33: 3.1-3-2 | BP33: 1 | BQ33: 30 | BR33: 0 | BS33: 34.51 | BT33: 1 | BU33: 1 | BV33: 1 | BW33: 1 | BX33: 1 | BZ33: 94 | CA33: 51 | CE33: 30 | CF33: 0 | CG33: 0 | CM33: 0 | CN33: Поправка: О.П. п.3.4.30.г Наименование: В отношении объектов, реализуемых с привлечением средств бюджета города Москвы, затраты, учитывающие усложненные условия производства работ (стесненность, сложность складирования и транспортной логистики, наличие в зоне производства работ действующего технологического оборудования или движения технологического транспорта и т.п.), определяются заказчиком в задании на проектирование при составлении локальных сметных расчетов (смет): для объектов города Москвы, расположенных за пределами Московской кольцевой автомобильной дороги | CO33: 0 | CP33: =(P33+Q33+S33) -> 553.2 | CQ33: =ROUND((ROUND((AC33*AW33*1),2)*BC33),2) -> 0 | CR33: =(ROUND((ROUND((((ET33*1.05))*AV33*1),2)*BB33),2)+ROUND((ROUND(((AE33-((EU33*1.05)))*AV33*1),2)*BS33),2)) -> 14197.16 | CS33: =ROUND((ROUND((AE33*AV33*1),2)*BS33),2) -> 3969 | CT33: =ROUND((ROUND((AF33*AV33*1),2)*BA33),2) -> 525.24 | CU33: =AG33 -> 0 | CV33: =(AH33*AV33) -> 1.489404 | CW33: =AI33 -> 0 | CX33: =AJ33 -> 0 | CY33: =S33*(BZ33/100) -> 18.4898 | CZ33: =S33*(CA33/100) -> 10.0317 | DB33: 6 | DE33: *1,05 | DF33: *1,05 | DG33: *1,05 | DI33: *1,05 | DJ33: *1,05 | DN33: 98 | DO33: 77 | DP33: 1.192 | DQ33: 1 | DU33: 1013 | DV33: 100 м3 грунта | DW33: 100 м3 грунта | DX33: 1 | EE33: 51696085 | EF33: 30 | EG33: Строительные работы | EH33: 0 | EJ33: 1 | EK33: 2 | EL33: ТСН-2001.3-1. 1-1...1-7 | EM33: ТСН-2001.3-1-1 | EO33: Поправка: О.П. п.3.4.30.г | EQ33: 131072 | ER33: 944.22 | ES33: 0 | ET33: 932.06 | EU33: 91.89 | EV33: 12.16 | EW33: 1.19 | EX33: 0 | EY33: 0 | FQ33: 0 | FR33: 0 | FS33: 0 | FX33: 98 | FY33: 77 | GD33: 0 | GF33: 864155608 | GG33: 2 | GH33: 1 | GI33: 2 | GJ33: 0 | GK33: =ROUND(R33*(S12)/100,2) -> 238.53 | GL33: =ROUND(IF(AND(BH33=3,BI33=3,FS33<>0),P33,0),2) -> 0 | GM33: =ROUND(O33+X33+Y33+GK33,2)+GX33 -> 820.25 | GN33: =IF(OR(BI33=0,BI33=1),GM33-GX33,0) -> 820.25 | GO33: =IF(BI33=2,GM33-GX33,0) -> 0 | GP33: =IF(BI33=4,GM33-GX33,0) -> 0 | GR33: 0 | GS33: 3 | GT33: 0 | GV33: =ROUND((GT33),6) -> 0 | GW33: 1 | GX33: =ROUND(HC33*I33,2) -> 0 | HA33: 0 | HB33: 0 | HC33: =GV33*GW33 -> 0 | HS33: 0 | IK33: 0
A34: 17 | B34: 1 | D34: =ROW(EtalonRes!A13) -> 13 | E34: 4 | F34: 3.1-53-1 | G34: Засыпка вручную траншей, пазух котлованов и ям группа грунтов 1-3 | H34: 100 м3 грунта | I34: =ROUND(8.02*0.3/100,9) -> 0.02406 | J34: 0 | K34: =ROUND(8.02*0.3/100,9) -> 0.02406 | O34: =ROUND(CP34,2) -> 33.14 | P34: =ROUND((ROUND((AC34*AW34*I34),2)*BC34),2) -> 0 | Q34: =(ROUND((ROUND((((ET34*1.05))*AV34*I34),2)*BB34),2)+ROUND((ROUND(((AE34-((EU34*1.05)))*AV34*I34),2)*BS34),2)) -> 0 | R34: =ROUND((ROUND((AE34*AV34*I34),2)*BS34),2) -> 0 | S34: =ROUND((ROUND((AF34*AV34*I34),2)*BA34),2) -> 33.14 | T34: =ROUND(CU34*I34,2) -> 0 | U34: =CV34*I34 -> 3.3747811 | V34: =CW34*I34 -> 0 | W34: =ROUND(CX34*I34,2) -> 0 | X34: =ROUND(CY34,2) -> 34.8 | Y34: =ROUND(CZ34,2) -> 25.52 | AA34: 56622490 | AB34: =ROUND((AC34+AD34+AF34),6) -> 1103.6865 | AC34: =ROUND((ES34),6) -> 0 | AD34: =ROUND(((((ET34*1.05))-((EU34*1.05)))+AE34),6) -> 0 | AE34: =ROUND(((EU34*1.05)),6) -> 0 | AF34: =ROUND(((EV34*1.05)),6) -> 1103.6865 | AG34: =ROUND((AP34),6) -> 0 | AH34: =((EW34*1.05)) -> 112.392 | AI34: =((EX34*1.05)) -> 0 | AJ34: =(AS34) -> 0 | AK34: 1051.13 | AL34: 0 | AM34: 0 | AN34: 0 | AO34: 1051.13 | AP34: 0 | AQ34: 107.04 | AR34: 0 | AS34: 0 | AT34: 105 | AU34: 77 | AV34: 1.248 | AW34: 1 | AZ34: 1 | BA34: 1 | BB34: 1 | BC34: 1 | BH34: 0 | BI34: 1 | BJ34: ТСН-2001.3. Доп. 1-42. Сб. 1, т. 53, поз. 1 | BM34: 16 | BN34: 0 | BP34: 0 | BQ34: 30 | BR34: 0 | BS34: 1 | BT34: 1 | BU34: 1 | BV34: 1 | BW34: 1 | BX34: 1 | BZ34: 105 | CA34: 77 | CE34: 30 | CF34: 0 | CG34: 0 | CM34: 0 | CN34: Поправка: О.П. п.3.4.30.г Наименование: В отношении объектов, реализуемых с привлечением средств бюджета города Москвы, затраты, учитывающие усложненные условия производства работ (стесненность, сложность складирования и транспортной логистики, наличие в зоне производства работ действующего технологического оборудования или движения технологического транспорта и т.п.), определяются заказчиком в задании на проектирование при составлении локальных сметных расчетов (смет): для объектов города Москвы, расположенных за пределами Московской кольцевой автомобильной дороги | CO34: 0 | CP34: =(P34+Q34+S34) -> 33.14 | CQ34: =ROUND((ROUND((AC34*AW34*1),2)*BC34),2) -> 0 | CR34: =(ROUND((ROUND((((ET34*1.05))*AV34*1),2)*BB34),2)+ROUND((ROUND(((AE34-((EU34*1.05)))*AV34*1),2)*BS34),2)) -> 0 | CS34: =ROUND((ROUND((AE34*AV34*1),2)*BS34),2) -> 0 | CT34: =ROUND((ROUND((AF34*AV34*1),2)*BA34),2) -> 1377.4 | CU34: =AG34 -> 0 | CV34: =(AH34*AV34) -> 140.26522 | CW34: =AI34 -> 0 | CX34: =AJ34 -> 0 | CY34: =((S34*BZ34)/100) -> 34.797 | CZ34: =((S34*CA34)/100) -> 25.5178 | DB34: 7 | DE34: *1,05 | DF34: *1,05 | DG34: *1,05 | DI34: *1,05 | DJ34: *1,05 | DN34: 0 | DO34: 0 | DP34: 1 | DQ34: 1 | DU34: 1013 | DV34: 100 м3 грунта | DW34: 100 м3 грунта | DX34: 1 | EE34: 51696099 | EF34: 30 | EG34: Строительные работы | EH34: 0 | EJ34: 1 | EK34: 16 | EL34: ТСН-2001.3-1. 1-49...1-55 | EM34: ТСН-2001.3-1-15 | EO34: Поправка: О.П. п.3.4.30.г | EQ34: 131072 | ER34: 1051.13 | ES34: 0 | ET34: 0 | EU34: 0 | EV34: 1051.13 | EW34: 107.04 | EX34: 0 | EY34: 0 | FQ34: 0 | FR34: 0 | FS34: 0 | FX34: 105 | FY34: 77 | GD34: 0 | GF34: 1725378853 | GG34: 2 | GH34: 1 | GI34: -2 | GJ34: 0 | GK34: =ROUND(R34*(R12)/100,2) -> 0 | GL34: =ROUND(IF(AND(BH34=3,BI34=3,FS34<>0),P34,0),2) -> 0 | GM34: =ROUND(O34+X34+Y34+GK34,2)+GX34 -> 93.46 | GN34: =IF(OR(BI34=0,BI34=1),GM34-GX34,0) -> 93.46 | GO34: =IF(BI34=2,GM34-GX34,0) -> 0 | GP34: =IF(BI34=4,GM34-GX34,0) -> 0 | GR34: 0 | GS34: 0 | GT34: 0 | GV34: =ROUND((GT34),6) -> 0 | GW34: 1 | GX34: =ROUND(HC34*I34,2) -> 0 | HA34: 0 | HB34: 0 | HC34: =GV34*GW34 -> 0 | HS34: 0 | IK34: 0
A35: 17 | B35: 1 | D35: =ROW(EtalonRes!A14) -> 14 | E35: 4 | F35: 3.1-53-1 | G35: Засыпка вручную траншей, пазух котлованов и ям группа грунтов 1-3 | H35: 100 м3 грунта | I35: =ROUND(8.02*0.3/100,9) -> 0.02406 | J35: 0 | K35: =ROUND(8.02*0.3/100,9) -> 0.02406 | O35: =ROUND(CP35,2) -> 1143.66 | P35: =ROUND((ROUND((AC35*AW35*I35),2)*BC35),2) -> 0 | Q35: =(ROUND((ROUND((((ET35*1.05))*AV35*I35),2)*BB35),2)+ROUND((ROUND(((AE35-((EU35*1.05)))*AV35*I35),2)*BS35),2)) -> 0 | R35: =ROUND((ROUND((AE35*AV35*I35),2)*BS35),2) -> 0 | S35: =ROUND((ROUND((AF35*AV35*I35),2)*BA35),2) -> 1143.66 | T35: =ROUND(CU35*I35,2) -> 0 | U35: =CV35*I35 -> 3.3747811 | V35: =CW35*I35 -> 0 | W35: =ROUND(CX35*I35,2) -> 0 | X35: =ROUND(CY35,2) -> 994.98 | Y35: =ROUND(CZ35,2) -> 468.9 | AA35: 56610029 | AB35: =ROUND((AC35+AD35+AF35),6) -> 1103.6865 | AC35: =ROUND((ES35),6) -> 0 | AD35: =ROUND(((((ET35*1.05))-((EU35*1.05)))+AE35),6) -> 0 | AE35: =ROUND(((EU35*1.05)),6) -> 0 | AF35: =ROUND(((EV35*1.05)),6) -> 1103.6865 | AG35: =ROUND((AP35),6) -> 0 | AH35: =((EW35*1.05)) -> 112.392 | AI35: =((EX35*1.05)) -> 0 | AJ35: =(AS35) -> 0 | AK35: 1051.13 | AL35: 0 | AM35: 0 | AN35: 0 | AO35: 1051.13 | AP35: 0 | AQ35: 107.04 | AR35: 0 | AS35: 0 | AT35: 87 | AU35: 41 | AV35: 1.248 | AW35: 1 | AZ35: 1 | BA35: 34.51 | BB35: 1 | BC35: 1 | BH35: 0 | BI35: 1 | BJ35: ТСН-2001.3. Доп. 1-42. Сб. 1, т. 53, поз. 1 | BM35: 16 | BN35: 0 | BO35: 3.1-53-1 | BP35: 1 | BQ35: 30 | BR35: 0 | BS35: 34.51 | BT35: 1 | BU35: 1 | BV35: 1 | BW35: 1 | BX35: 1 | BZ35: 87 | CA35: 41 | CE35: 30 | CF35: 0 | CG35: 0 | CM35: 0 | CN35: Поправка: О.П. п.3.4.30.г Наименование: В отношении объектов, реализуемых с привлечением средств бюджета города Москвы, затраты, учитывающие усложненные условия производства работ (стесненность, сложность складирования и транспортной логистики, наличие в зоне производства работ действующего технологического оборудования или движения технологического транспорта и т.п.), определяются заказчиком в задании на проектирование при составлении локальных сметных расчетов (смет): для объектов города Москвы, расположенных за пределами Московской кольцевой автомобильной дороги | CO35: 0 | CP35: =(P35+Q35+S35) -> 1143.66 | CQ35: =ROUND((ROUND((AC35*AW35*1),2)*BC35),2) -> 0 | CR35: =(ROUND((ROUND((((ET35*1.05))*AV35*1),2)*BB35),2)+ROUND((ROUND(((AE35-((EU35*1.05)))*AV35*1),2)*BS35),2)) -> 0 | CS35: =ROUND((ROUND((AE35*AV35*1),2)*BS35),2) -> 0 | CT35: =ROUND((ROUND((AF35*AV35*1),2)*BA35),2) -> 47534.07 | CU35: =AG35 -> 0 | CV35: =(AH35*AV35) -> 140.26522 | CW35: =AI35 -> 0 | CX35: =AJ35 -> 0 | CY35: =S35*(BZ35/100) -> 994.9842 | CZ35: =S35*(CA35/100) -> 468.9006 | DB35: 8 | DE35: *1,05 | DF35: *1,05 | DG35: *1,05 | DI35: *1,05 | DJ35: *1,05 | DN35: 105 | DO35: 77 | DP35: 1.248 | DQ35: 1 | DU35: 1013 | DV35: 100 м3 грунта | DW35: 100 м3 грунта | DX35: 1 | EE35: 51696099 | EF35: 30 | EG35: Строительные работы | EH35: 0 | EJ35: 1 | EK35: 16 | EL35: ТСН-2001.3-1. 1-49...1-55 | EM35: ТСН-2001.3-1-15 | EO35: Поправка: О.П. п.3.4.30.г | EQ35: 131072 | ER35: 1051.13 | ES35: 0 | ET35: 0 | EU35: 0 | EV35: 1051.13 | EW35: 107.04 | EX35: 0 | EY35: 0 | FQ35: 0 | FR35: 0 | FS35: 0 | FX35: 105 | FY35: 77 | GD35: 0 | GF35: 1725378853 | GG35: 2 | GH35: 1 | GI35: 2 | GJ35: 0 | GK35: =ROUND(R35*(S12)/100,2) -> 0 | GL35: =ROUND(IF(AND(BH35=3,BI35=3,FS35<>0),P35,0),2) -> 0 | GM35: =ROUND(O35+X35+Y35+GK35,2)+GX35 -> 2607.54 | GN35: =IF(OR(BI35=0,BI35=1),GM35-GX35,0) -> 2607.54 | GO35: =IF(BI35=2,GM35-GX35,0) -> 0 | GP35: =IF(BI35=4,GM35-GX35,0) -> 0 | GR35: 0 | GS35: 3 | GT35: 0 | GV35: =ROUND((GT35),6) -> 0 | GW35: 1 | GX35: =ROUND(HC35*I35,2) -> 0 | HA35: 0 | HB35: 0 | HC35: =GV35*GW35 -> 0 | HS35: 0 | IK35: 0
A36: 17 | B36: 1 | D36: =ROW(EtalonRes!A15) -> 15 | E36: 5 | F36: 3.1-14-1 | G36: Засыпка траншей и котлованов бульдозерами мощностью 59 (80) кВт (л.с.) при перемещении грунта до 5 м группа грунтов 1-3 | H36: 100 м3 грунта | I36: =ROUND(8.02*0.7/100,9) -> 0.05614 | J36: 0 | K36: =ROUND(8.02*0.7/100,9) -> 0.05614 | O36: =ROUND(CP36,2) -> 7.77 | P36: =ROUND((ROUND((AC36*AW36*I36),2)*BC36),2) -> 0 | Q36: =(ROUND((ROUND((((ET36*1.05))*AV36*I36),2)*BB36),2)+ROUND((ROUND(((AE36-((EU36*1.05)))*AV36*I36),2)*BS36),2)) -> 7.77 | R36: =ROUND((ROUND((AE36*AV36*I36),2)*BS36),2) -> 0.78 | S36: =ROUND((ROUND((AF36*AV36*I36),2)*BA36),2) -> 0 | T36: =ROUND(CU36*I36,2) -> 0 | U36: =CV36*I36 -> 0 | V36: =CW36*I36 -> 0 | W36: =ROUND(CX36*I36,2) -> 0 | X36: =ROUND(CY36,2) -> 0 | Y36: =ROUND(CZ36,2) -> 0 | AA36: 56622490 | AB36: =ROUND((AC36+AD36+AF36),6) -> 136.5105 | AC36: =ROUND((ES36),6) -> 0 | AD36: =ROUND(((((ET36*1.05))-((EU36*1.05)))+AE36),6) -> 136.5105 | AE36: =ROUND(((EU36*1.05)),6) -> 13.629 | AF36: =ROUND(((EV36*1.05)),6) -> 0 | AG36: =ROUND((AP36),6) -> 0 | AH36: =((EW36*1.05)) -> 0 | AI36: =((EX36*1.05)) -> 0 | AJ36: =(AS36) -> 0 | AK36: 130.01 | AL36: 0 | AM36: 130.01 | AN36: 12.98 | AO36: 0 | AP36: 0 | AQ36: 0 | AR36: 0 | AS36: 0 | AT36: 98 | AU36: 77 | AV36: 1.014 | AW36: 1 | AZ36: 1 | BA36: 1 | BB36: 1 | BC36: 1 | BH36: 0 | BI36: 1 | BJ36: ТСН-2001.3 Доп. 68, Сб. 1, т. 14, поз. 1 | BM36: 5 | BN36: 0 | BP36: 0 | BQ36: 30 | BR36: 0 | BS36: 1 | BT36: 1 | BU36: 1 | BV36: 1 | BW36: 1 | BX36: 1 | BZ36: 98 | CA36: 77 | CE36: 30 | CF36: 0 | CG36: 0 | CM36: 0 | CN36: Поправка: О.П. п.3.4.30.г Наименование: В отношении объектов, реализуемых с привлечением средств бюджета города Москвы, затраты, учитывающие усложненные условия производства работ (стесненность, сложность складирования и транспортной логистики, наличие в зоне производства работ действующего технологического оборудования или движения технологического транспорта и т.п.), определяются заказчиком в задании на проектирование при составлении локальных сметных расчетов (смет): для объектов города Москвы, расположенных за пределами Московской кольцевой автомобильной дороги | CO36: 0 | CP36: =(P36+Q36+S36) -> 7.77 | CQ36: =ROUND((ROUND((AC36*AW36*1),2)*BC36),2) -> 0 | CR36: =(ROUND((ROUND((((ET36*1.05))*AV36*1),2)*BB36),2)+ROUND((ROUND(((AE36-((EU36*1.05)))*AV36*1),2)*BS36),2)) -> 138.42 | CS36: =ROUND((ROUND((AE36*AV36*1),2)*BS36),2) -> 13.82 | CT36: =ROUND((ROUND((AF36*AV36*1),2)*BA36),2) -> 0 | CU36: =AG36 -> 0 | CV36: =(AH36*AV36) -> 0 | CW36: =AI36 -> 0 | CX36: =AJ36 -> 0 | CY36: =((S36*BZ36)/100) -> 0 | CZ36: =((S36*CA36)/100) -> 0 | DB36: 9 | DE36: *1,05 | DF36: *1,05 | DG36: *1,05 | DI36: *1,05 | DJ36: *1,05 | DN36: 0 | DO36: 0 | DP36: 1 | DQ36: 1 | DU36: 1013 | DV36: 100 м3 грунта | DW36: 100 м3 грунта | DX36: 1 | EE36: 51696088 | EF36: 30 | EG36: Строительные работы | EH36: 0 | EJ36: 1 | EK36: 5 | EL36: ТСН-2001.3-1. 1-11...1-17 | EM36: ТСН-2001.3-1-4 | EO36: Поправка: О.П. п.3.4.30.г | EQ36: 131072 | ER36: 130.01 | ES36: 0 | ET36: 130.01 | EU36: 12.98 | EV36: 0 | EW36: 0 | EX36: 0 | EY36: 0 | FQ36: 0 | FR36: 0 | FS36: 0 | FX36: 98 | FY36: 77 | GD36: 0 | GF36: 1539452637 | GG36: 2 | GH36: 1 | GI36: -2 | GJ36: 0 | GK36: =ROUND(R36*(R12)/100,2) -> 1.37 | GL36: =ROUND(IF(AND(BH36=3,BI36=3,FS36<>0),P36,0),2) -> 0 | GM36: =ROUND(O36+X36+Y36+GK36,2)+GX36 -> 9.14 | GN36: =IF(OR(BI36=0,BI36=1),GM36-GX36,0) -> 9.14 | GO36: =IF(BI36=2,GM36-GX36,0) -> 0 | GP36: =IF(BI36=4,GM36-GX36,0) -> 0 | GR36: 0 | GS36: 0 | GT36: 0 | GV36: =ROUND((GT36),6) -> 0 | GW36: 1 | GX36: =ROUND(HC36*I36,2) -> 0 | HA36: 0 | HB36: 0 | HC36: =GV36*GW36 -> 0 | HS36: 0 | IK36: 0
A37: 17 | B37: 1 | D37: =ROW(EtalonRes!A16) -> 16 | E37: 5 | F37: 3.1-14-1 | G37: Засыпка траншей и котлованов бульдозерами мощностью 59 (80) кВт (л.с.) при перемещении грунта до 5 м группа грунтов 1-3 | H37: 100 м3 грунта | I37: =ROUND(8.02*0.7/100,9) -> 0.05614 | J37: 0 | K37: =ROUND(8.02*0.7/100,9) -> 0.05614 | O37: =ROUND(CP37,2) -> 93.86 | P37: =ROUND((ROUND((AC37*AW37*I37),2)*BC37),2) -> 0 | Q37: =(ROUND((ROUND((((ET37*1.05))*AV37*I37),2)*BB37),2)+ROUND((ROUND(((AE37-((EU37*1.05)))*AV37*I37),2)*BS37),2)) -> 93.86 | R37: =ROUND((ROUND((AE37*AV37*I37),2)*BS37),2) -> 26.92 | S37: =ROUND((ROUND((AF37*AV37*I37),2)*BA37),2) -> 0 | T37: =ROUND(CU37*I37,2) -> 0 | U37: =CV37*I37 -> 0 | V37: =CW37*I37 -> 0 | W37: =ROUND(CX37*I37,2) -> 0 | X37: =ROUND(CY37,2) -> 0 | Y37: =ROUND(CZ37,2) -> 0 | AA37: 56610029 | AB37: =ROUND((AC37+AD37+AF37),6) -> 136.5105 | AC37: =ROUND((ES37),6) -> 0 | AD37: =ROUND(((((ET37*1.05))-((EU37*1.05)))+AE37),6) -> 136.5105 | AE37: =ROUND(((EU37*1.05)),6) -> 13.629 | AF37: =ROUND(((EV37*1.05)),6) -> 0 | AG37: =ROUND((AP37),6) -> 0 | AH37: =((EW37*1.05)) -> 0 | AI37: =((EX37*1.05)) -> 0 | AJ37: =(AS37) -> 0 | AK37: 130.01 | AL37: 0 | AM37: 130.01 | AN37: 12.98 | AO37: 0 | AP37: 0 | AQ37: 0 | AR37: 0 | AS37: 0 | AT37: 94 | AU37: 51 | AV37: 1.014 | AW37: 1 | AZ37: 1 | BA37: 34.51 | BB37: 12.08 | BC37: 1 | BH37: 0 | BI37: 1 | BJ37: ТСН-2001.3 Доп. 68, Сб. 1, т. 14, поз. 1 | BM37: 5 | BN37: 0 | BO37: 3.1-14-1 | BP37: 1 | BQ37: 30 | BR37: 0 | BS37: 34.51 | BT37: 1 | BU37: 1 | BV37: 1 | BW37: 1 | BX37: 1 | BZ37: 94 | CA37: 51 | CE37: 30 | CF37: 0 | CG37: 0 | CM37: 0 | CN37: Поправка: О.П. п.3.4.30.г Наименование: В отношении объектов, реализуемых с привлечением средств бюджета города Москвы, затраты, учитывающие усложненные условия производства работ (стесненность, сложность складирования и транспортной логистики, наличие в зоне производства работ действующего технологического оборудования или движения технологического транспорта и т.п.), определяются заказчиком в задании на проектирование при составлении локальных сметных расчетов (смет): для объектов города Москвы, расположенных за пределами Московской кольцевой автомобильной дороги | CO37: 0 | CP37: =(P37+Q37+S37) -> 93.86 | CQ37: =ROUND((ROUND((AC37*AW37*1),2)*BC37),2) -> 0 | CR37: =(ROUND((ROUND((((ET37*1.05))*AV37*1),2)*BB37),2)+ROUND((ROUND(((AE37-((EU37*1.05)))*AV37*1),2)*BS37),2)) -> 1672.11 | CS37: =ROUND((ROUND((AE37*AV37*1),2)*BS37),2) -> 476.93 | CT37: =ROUND((ROUND((AF37*AV37*1),2)*BA37),2) -> 0 | CU37: =AG37 -> 0 | CV37: =(AH37*AV37) -> 0 | CW37: =AI37 -> 0 | CX37: =AJ37 -> 0 | CY37: =S37*(BZ37/100) -> 0 | CZ37: =S37*(CA37/100) -> 0 | DB37: 10 | DE37: *1,05 | DF37: *1,05 | DG37: *1,05 | DI37: *1,05 | DJ37: *1,05 | DN37: 98 | DO37: 77 | DP37: 1.014 | DQ37: 1 | DU37: 1013 | DV37: 100 м3 грунта | DW37: 100 м3 грунта | DX37: 1 | EE37: 51696088 | EF37: 30 | EG37: Строительные работы | EH37: 0 | EJ37: 1 | EK37: 5 | EL37: ТСН-2001.3-1. 1-11...1-17 | EM37: ТСН-2001.3-1-4 | EO37: Поправка: О.П. п.3.4.30.г | EQ37: 131072 | ER37: 130.01 | ES37: 0 | ET37: 130.01 | EU37: 12.98 | EV37: 0 | EW37: 0 | EX37: 0 | EY37: 0 | FQ37: 0 | FR37: 0 | FS37: 0 | FX37: 98 | FY37: 77 | GD37: 0 | GF37: 1539452637 | GG37: 2 | GH37: 1 | GI37: 2 | GJ37: 0 | GK37: =ROUND(R37*(S12)/100,2) -> 43.07 | GL37: =ROUND(IF(AND(BH37=3,BI37=3,FS37<>0),P37,0),2) -> 0 | GM37: =ROUND(O37+X37+Y37+GK37,2)+GX37 -> 136.93 | GN37: =IF(OR(BI37=0,BI37=1),GM37-GX37,0) -> 136.93 | GO37: =IF(BI37=2,GM37-GX37,0) -> 0 | GP37: =IF(BI37=4,GM37-GX37,0) -> 0 | GR37: 0 | GS37: 3 | GT37: 0 | GV37: =ROUND((GT37),6) -> 0 | GW37: 1 | GX37: =ROUND(HC37*I37,2) -> 0 | HA37: 0 | HB37: 0 | HC37: =GV37*GW37 -> 0 | HS37: 0 | IK37: 0
A38: 17 | B38: 1 | D38: =ROW(EtalonRes!A20) -> 20 | E38: 6 | F38: 3.34-17-4 | G38: Устройство трубопроводов из асбестоцементных труб с соединением манжетами полиэтиленовыми более 2-х отверстий | H38: 1 канало-километр трубопровода | I38: 0 | J38: 0 | K38: 0 | O38: =ROUND(CP38,2) -> 0 | P38: =ROUND((ROUND((AC38*AW38*I38),2)*BC38),2) -> 0 | Q38: =(ROUND((ROUND((((ET38*1.05))*AV38*I38),2)*BB38),2)+ROUND((ROUND(((AE38-((EU38*1.05)))*AV38*I38),2)*BS38),2)) -> 0 | R38: =ROUND((ROUND((AE38*AV38*I38),2)*BS38),2) -> 0 | S38: =ROUND((ROUND((AF38*AV38*I38),2)*BA38),2) -> 0 | T38: =ROUND(CU38*I38,2) -> 0 | U38: =CV38*I38 -> 0 | V38: =CW38*I38 -> 0 | W38: =ROUND(CX38*I38,2) -> 0 | X38: =ROUND(CY38,2) -> 0 | Y38: =ROUND(CZ38,2) -> 0 | AA38: 56622490 | AB38: =ROUND((AC38+AD38+AF38),6) -> 21174.122 | AC38: =ROUND((ES38),6) -> 19554.14 | AD38: =ROUND(((((ET38*1.05))-((EU38*1.05)))+AE38),6) -> 0 | AE38: =ROUND(((EU38*1.05)),6) -> 0 | AF38: =ROUND(((EV38*1.05)),6) -> 1619.982 | AG38: =ROUND((AP38),6) -> 0 | AH38: =((EW38*1.05)) -> 144.9 | AI38: =((EX38*1.05)) -> 0 | AJ38: =(AS38) -> 0 | AK38: 21096.98 | AL38: 19554.14 | AM38: 0 | AN38: 0 | AO38: 1542.84 | AP38: 0 | AQ38: 138 | AR38: 0 | AS38: 0 | AT38: 112 | AU38: 70 | AV38: 1.067 | AW38: 1.081 | AZ38: 1 | BA38: 1 | BB38: 1 | BC38: 1 | BH38: 0 | BI38: 1 | BJ38: ТСН-2001.3. Доп. 1-42. Сб. 34, т. 17, поз. 4 | BM38: 242 | BN38: 0 | BP38: 0 | BQ38: 30 | BR38: 0 | BS38: 1 | BT38: 1 | BU38: 1 | BV38: 1 | BW38: 1 | BX38: 1 | BZ38: 112 | CA38: 70 | CE38: 30 | CF38: 0 | CG38: 0 | CM38: 0 | CN38: Поправка: О.П. п.3.4.30.г Наименование: В отношении объектов, реализуемых с привлечением средств бюджета города Москвы, затраты, учитывающие усложненные условия производства работ (стесненность, сложность складирования и транспортной логистики, наличие в зоне производства работ действующего технологического оборудования или движения технологического транспорта и т.п.), определяются заказчиком в задании на проектирование при составлении локальных сметных расчетов (смет): для объектов города Москвы, расположенных за пределами Московской кольцевой автомобильной дороги | CO38: 0 | CP38: =(P38+Q38+S38) -> 0 | CQ38: =ROUND((ROUND((AC38*AW38*1),2)*BC38),2) -> 21138.03 | CR38: =(ROUND((ROUND((((ET38*1.05))*AV38*1),2)*BB38),2)+ROUND((ROUND(((AE38-((EU38*1.05)))*AV38*1),2)*BS38),2)) -> 0 | CS38: =ROUND((ROUND((AE38*AV38*1),2)*BS38),2) -> 0 | CT38: =ROUND((ROUND((AF38*AV38*1),2)*BA38),2) -> 1728.52 | CU38: =AG38 -> 0 | CV38: =(AH38*AV38) -> 154.6083 | CW38: =AI38 -> 0 | CX38: =AJ38 -> 0 | CY38: =((S38*BZ38)/100) -> 0 | CZ38: =((S38*CA38)/100) -> 0 | DB38: 11 | DE38: *1,05 | DF38: *1,05 | DG38: *1,05 | DI38: *1,05 | DJ38: *1,05 | DN38: 0 | DO38: 0 | DP38: 1 | DQ38: 1 | DU38: 1013 | DV38: 1 канало-километр трубопровода | DW38: 1 канало-километр трубопровода | DX38: 1 | EE38: 51696281 | EF38: 30 | EG38: Строительные работы | EH38: 0 | EJ38: 1 | EK38: 242 | EL38: ТСН-2001.3-34. 34-17...34-28 | EM38: ТСН-2001.3-34-6 | EO38: Поправка: О.П. п.3.4.30.г | EQ38: 131072 | ER38: 21096.98 | ES38: 19554.14 | ET38: 0 | EU38: 0 | EV38: 1542.84 | EW38: 138 | EX38: 0 | EY38: 0 | FQ38: 0 | FR38: 0 | FS38: 2 | FX38: 112 | FY38: 70 | GD38: 0 | GF38: -1466514599 | GG38: 2 | GH38: 1 | GI38: -2 | GJ38: 0 | GK38: =ROUND(R38*(R12)/100,2) -> 0 | GL38: =ROUND(IF(AND(BH38=3,BI38=3,FS38<>0),P38,0),2) -> 0 | GM38: =ROUND(O38+X38+Y38+GK38,2)+GX38 -> 0 | GN38: =IF(OR(BI38=0,BI38=1),GM38-GX38,0) -> 0 | GO38: =IF(BI38=2,GM38-GX38,0) -> 0 | GP38: =IF(BI38=4,GM38-GX38,0) -> 0 | GR38: 0 | GS38: 0 | GT38: 0 | GV38: =ROUND((GT38),6) -> 0 | GW38: 1 | GX38: =ROUND(HC38*I38,2) -> 0 | HA38: 0 | HB38: 0 | HC38: =GV38*GW38 -> 0 | HS38: 0 | IK38: 0
A39: 17 | B39: 1 | D39: =ROW(EtalonRes!A24) -> 24 | E39: 6 | F39: 3.34-17-4 | G39: Устройство трубопроводов из асбестоцементных труб с соединением манжетами полиэтиленовыми более 2-х отверстий | H39: 1 канало-километр трубопровода | I39: 0 | J39: 0 | K39: 0 | O39: =ROUND(CP39,2) -> 0 | P39: =ROUND((ROUND((AC39*AW39*I39),2)*BC39),2) -> 0 | Q39: =(ROUND((ROUND((((ET39*1.05))*AV39*I39),2)*BB39),2)+ROUND((ROUND(((AE39-((EU39*1.05)))*AV39*I39),2)*BS39),2)) -> 0 | R39: =ROUND((ROUND((AE39*AV39*I39),2)*BS39),2) -> 0 | S39: =ROUND((ROUND((AF39*AV39*I39),2)*BA39),2) -> 0 | T39: =ROUND(CU39*I39,2) -> 0 | U39: =CV39*I39 -> 0 | V39: =CW39*I39 -> 0 | W39: =ROUND(CX39*I39,2) -> 0 | X39: =ROUND(CY39,2) -> 0 | Y39: =ROUND(CZ39,2) -> 0 | AA39: 56610029 | AB39: =ROUND((AC39+AD39+AF39),6) -> 21174.122 | AC39: =ROUND((ES39),6) -> 19554.14 | AD39: =ROUND(((((ET39*1.05))-((EU39*1.05)))+AE39),6) -> 0 | AE39: =ROUND(((EU39*1.05)),6) -> 0 | AF39: =ROUND(((EV39*1.05)),6) -> 1619.982 | AG39: =ROUND((AP39),6) -> 0 | AH39: =((EW39*1.05)) -> 144.9 | AI39: =((EX39*1.05)) -> 0 | AJ39: =(AS39) -> 0 | AK39: 21096.98 | AL39: 19554.14 | AM39: 0 | AN39: 0 | AO39: 1542.84 | AP39: 0 | AQ39: 138 | AR39: 0 | AS39: 0 | AT39: 92 | AU39: 41 | AV39: 1.067 | AW39: 1.081 | AZ39: 1 | BA39: 34.51 | BB39: 1 | BC39: 7.65 | BH39: 0 | BI39: 1 | BJ39: ТСН-2001.3. Доп. 1-42. Сб. 34, т. 17, поз. 4 | BM39: 242 | BN39: 0 | BO39: 3.34-17-4 | BP39: 1 | BQ39: 30 | BR39: 0 | BS39: 34.51 | BT39: 1 | BU39: 1 | BV39: 1 | BW39: 1 | BX39: 1 | BZ39: 92 | CA39: 41 | CE39: 30 | CF39: 0 | CG39: 0 | CM39: 0 | CN39: Поправка: О.П. п.3.4.30.г Наименование: В отношении объектов, реализуемых с привлечением средств бюджета города Москвы, затраты, учитывающие усложненные условия производства работ (стесненность, сложность складирования и транспортной логистики, наличие в зоне производства работ действующего технологического оборудования или движения технологического транспорта и т.п.), определяются заказчиком в задании на проектирование при составлении локальных сметных расчетов (смет): для объектов города Москвы, расположенных за пределами Московской кольцевой автомобильной дороги | CO39: 0 | CP39: =(P39+Q39+S39) -> 0 | CQ39: =ROUND((ROUND((AC39*AW39*1),2)*BC39),2) -> 161705.93 | CR39: =(ROUND((ROUND((((ET39*1.05))*AV39*1),2)*BB39),2)+ROUND((ROUND(((AE39-((EU39*1.05)))*AV39*1),2)*BS39),2)) -> 0 | CS39: =ROUND((ROUND((AE39*AV39*1),2)*BS39),2) -> 0 | CT39: =ROUND((ROUND((AF39*AV39*1),2)*BA39),2) -> 59651.23 | CU39: =AG39 -> 0 | CV39: =(AH39*AV39) -> 154.6083 | CW39: =AI39 -> 0 | CX39: =AJ39 -> 0 | CY39: =S39*(BZ39/100) -> 0 | CZ39: =S39*(CA39/100) -> 0 | DB39: 12 | DE39: *1,05 | DF39: *1,05 | DG39: *1,05 | DI39: *1,05 | DJ39: *1,05 | DN39: 112 | DO39: 70 | DP39: 1.067 | DQ39: 1.081 | DU39: 1013 | DV39: 1 канало-километр трубопровода | DW39: 1 канало-километр трубопровода | DX39: 1 | EE39: 51696281 | EF39: 30 | EG39: Строительные работы | EH39: 0 | EJ39: 1 | EK39: 242 | EL39: ТСН-2001.3-34. 34-17...34-28 | EM39: ТСН-2001.3-34-6 | EO39: Поправка: О.П. п.3.4.30.г | EQ39: 131072 | ER39: 21096.98 | ES39: 19554.14 | ET39: 0 | EU39: 0 | EV39: 1542.84 | EW39: 138 | EX39: 0 | EY39: 0 | FQ39: 0 | FR39: 0 | FS39: 2 | FX39: 112 | FY39: 70 | GD39: 0 | GF39: -1466514599 | GG39: 2 | GH39: 1 | GI39: 2 | GJ39: 0 | GK39: =ROUND(R39*(S12)/100,2) -> 0 | GL39: =ROUND(IF(AND(BH39=3,BI39=3,FS39<>0),P39,0),2) -> 0 | GM39: =ROUND(O39+X39+Y39+GK39,2)+GX39 -> 0 | GN39: =IF(OR(BI39=0,BI39=1),GM39-GX39,0) -> 0 | GO39: =IF(BI39=2,GM39-GX39,0) -> 0 | GP39: =IF(BI39=4,GM39-GX39,0) -> 0 | GR39: 0 | GS39: 3 | GT39: 0 | GV39: =ROUND((GT39),6) -> 0 | GW39: 1 | GX39: =ROUND(HC39*I39,2) -> 0 | HA39: 0 | HB39: 0 | HC39: =GV39*GW39 -> 0 | HS39: 0 | IK39: 0
A40: 17 | B40: 1 | E40: 7 | F40: 1.12-3-25 | G40: Трубы хризотилцементные безнапорные, марка БНТ, диаметр условного прохода 100 мм, внутренний диаметр 100 мм | H40: м | I40: =ROUND(-(I38)*1000,9) -> 0 | J40: 0 | K40: =ROUND(-(I38)*1000,9) -> 0 | O40: =ROUND(CP40,2) -> 0 | P40: =ROUND((ROUND((AC40*AW40*I40),2)*BC40),2) -> 0 | Q40: =(ROUND((ROUND((((ET40*1.05))*AV40*I40),2)*BB40),2)+ROUND((ROUND(((AE40-((EU40*1.05)))*AV40*I40),2)*BS40),2)) -> 0 | R40: =ROUND((ROUND((AE40*AV40*I40),2)*BS40),2) -> 0 | S40: =ROUND((ROUND((AF40*AV40*I40),2)*BA40),2) -> 0 | T40: =ROUND(CU40*I40,2) -> 0 | U40: =CV40*I40 -> 0 | V40: =CW40*I40 -> 0 | W40: =ROUND(CX40*I40,2) -> 0 | X40: =ROUND(CY40,2) -> 0 | Y40: =ROUND(CZ40,2) -> 0 | AA40: 56622490 | AB40: =ROUND((AC40+AD40+AF40),6) -> 15.01 | AC40: =ROUND((ES40),6) -> 15.01 | AD40: =ROUND(((((ET40*1.05))-((EU40*1.05)))+AE40),6) -> 0 | AE40: =ROUND(((EU40*1.05)),6) -> 0 | AF40: =ROUND(((EV40*1.05)),6) -> 0 | AG40: =ROUND((AP40),6) -> 0 | AH40: =((EW40*1.05)) -> 0 | AI40: =((EX40*1.05)) -> 0 | AJ40: =(AS40) -> 0 | AK40: 15.01 | AL40: 15.01 | AM40: 0 | AN40: 0 | AO40: 0 | AP40: 0 | AQ40: 0 | AR40: 0 | AS40: 0 | AT40: 0 | AU40: 0 | AV40: 1 | AW40: 1 | AZ40: 1 | BA40: 1 | BB40: 1 | BC40: 1 | BH40: 3 | BI40: 1 | BJ40: ТСН-2001.1 Доп. 70, Р. 12, о. 3, поз. 25 | BM40: 1617 | BN40: 0 | BP40: 0 | BQ40: 200 | BR40: 0 | BS40: 1 | BT40: 1 | BU40: 1 | BV40: 1 | BW40: 1 | BX40: 1 | BZ40: 0 | CA40: 0 | CE40: 30 | CF40: 0 | CG40: 0 | CM40: 0 | CN40: Поправка: О.П. п.3.4.30.г Наименование: В отношении объектов, реализуемых с привлечением средств бюджета города Москвы, затраты, учитывающие усложненные условия производства работ (стесненность, сложность складирования и транспортной логистики, наличие в зоне производства работ действующего технологического оборудования или движения технологического транспорта и т.п.), определяются заказчиком в задании на проектирование при составлении локальных сметных расчетов (смет): для объектов города Москвы, расположенных за пределами Московской кольцевой автомобильной дороги | CO40: 0 | CP40: =(P40+Q40+S40) -> 0 | CQ40: =ROUND((ROUND((AC40*AW40*1),2)*BC40),2) -> 15.01 | CR40: =(ROUND((ROUND((((ET40*1.05))*AV40*1),2)*BB40),2)+ROUND((ROUND(((AE40-((EU40*1.05)))*AV40*1),2)*BS40),2)) -> 0 | CS40: =ROUND((ROUND((AE40*AV40*1),2)*BS40),2) -> 0 | CT40: =ROUND((ROUND((AF40*AV40*1),2)*BA40),2) -> 0 | CU40: =AG40 -> 0 | CV40: =(AH40*AV40) -> 0 | CW40: =AI40 -> 0 | CX40: =AJ40 -> 0 | CY40: =((S40*BZ40)/100) -> 0 | CZ40: =((S40*CA40)/100) -> 0 | DB40: 13 | DE40: *1,05 | DF40: *1,05 | DG40: *1,05 | DI40: *1,05 | DJ40: *1,05 | DN40: 0 | DO40: 0 | DP40: 1 | DQ40: 1 | DU40: 1003 | DV40: м | DW40: м | DX40: 1 | EE40: 51697656 | EF40: 200 | EG40: Материалы строительные | EH40: 0 | EJ40: 1 | EK40: 1617 | EL40: ТСН-2001.1 Материалы строительные | EM40: ТСН-2001.1-1 | EO40: Поправка: О.П. п.3.4.30.г | EQ40: 131072 | ER40: 15.01 | ES40: 15.01 | ET40: 0 | EU40: 0 | EV40: 0 | EW40: 0 | EX40: 0 | EY40: 0 | FQ40: 0 | FR40: 0 | FS40: 0 | FX40: 0 | FY40: 0 | GD40: 0 | GF40: 1181244062 | GG40: 2 | GH40: 1 | GI40: -2 | GJ40: 0 | GK40: =ROUND(R40*(R12)/100,2) -> 0 | GL40: =ROUND(IF(AND(BH40=3,BI40=3,FS40<>0),P40,0),2) -> 0 | GM40: =ROUND(O40+X40+Y40+GK40,2)+GX40 -> 0 | GN40: =IF(OR(BI40=0,BI40=1),GM40-GX40,0) -> 0 | GO40: =IF(BI40=2,GM40-GX40,0) -> 0 | GP40: =IF(BI40=4,GM40-GX40,0) -> 0 | GR40: 0 | GS40: 0 | GT40: 0 | GV40: =ROUND((GT40),6) -> 0 | GW40: 1 | GX40: =ROUND(HC40*I40,2) -> 0 | HA40: 0 | HB40: 0 | HC40: =GV40*GW40 -> 0 | HS40: 0 | IK40: 0
A41: 17 | B41: 1 | E41: 7 | F41: 1.12-3-25 | G41: Трубы хризотилцементные безнапорные, марка БНТ, диаметр условного прохода 100 мм, внутренний диаметр 100 мм | H41: м | I41: =ROUND(-(I39)*1000,9) -> 0 | J41: 0 | K41: =ROUND(-(I39)*1000,9) -> 0 | O41: =ROUND(CP41,2) -> 0 | P41: =ROUND((ROUND((AC41*AW41*I41),2)*BC41),2) -> 0 | Q41: =(ROUND((ROUND((((ET41*1.05))*AV41*I41),2)*BB41),2)+ROUND((ROUND(((AE41-((EU41*1.05)))*AV41*I41),2)*BS41),2)) -> 0 | R41: =ROUND((ROUND((AE41*AV41*I41),2)*BS41),2) -> 0 | S41: =ROUND((ROUND((AF41*AV41*I41),2)*BA41),2) -> 0 | T41: =ROUND(CU41*I41,2) -> 0 | U41: =CV41*I41 -> 0 | V41: =CW41*I41 -> 0 | W41: =ROUND(CX41*I41,2) -> 0 | X41: =ROUND(CY41,2) -> 0 | Y41: =ROUND(CZ41,2) -> 0 | AA41: 56610029 | AB41: =ROUND((AC41+AD41+AF41),6) -> 15.01 | AC41: =ROUND((ES41),6) -> 15.01 | AD41: =ROUND(((((ET41*1.05))-((EU41*1.05)))+AE41),6) -> 0 | AE41: =ROUND(((EU41*1.05)),6) -> 0 | AF41: =ROUND(((EV41*1.05)),6) -> 0 | AG41: =ROUND((AP41),6) -> 0 | AH41: =((EW41*1.05)) -> 0 | AI41: =((EX41*1.05)) -> 0 | AJ41: =(AS41) -> 0 | AK41: 15.01 | AL41: 15.01 | AM41: 0 | AN41: 0 | AO41: 0 | AP41: 0 | AQ41: 0 | AR41: 0 | AS41: 0 | AT41: 0 | AU41: 0 | AV41: 1 | AW41: 1 | AZ41: 1 | BA41: 1 | BB41: 1 | BC41: 9.11 | BH41: 3 | BI41: 1 | BJ41: ТСН-2001.1 Доп. 70, Р. 12, о. 3, поз. 25 | BM41: 1617 | BN41: 0 | BO41: 1.12-3-25 | BP41: 1 | BQ41: 200 | BR41: 0 | BS41: 1 | BT41: 1 | BU41: 1 | BV41: 1 | BW41: 1 | BX41: 1 | BZ41: 0 | CA41: 0 | CE41: 30 | CF41: 0 | CG41: 0 | CM41: 0 | CN41: Поправка: О.П. п.3.4.30.г Наименование: В отношении объектов, реализуемых с привлечением средств бюджета города Москвы, затраты, учитывающие усложненные условия производства работ (стесненность, сложность складирования и транспортной логистики, наличие в зоне производства работ действующего технологического оборудования или движения технологического транспорта и т.п.), определяются заказчиком в задании на проектирование при составлении локальных сметных расчетов (смет): для объектов города Москвы, расположенных за пределами Московской кольцевой автомобильной дороги | CO41: 0 | CP41: =(P41+Q41+S41) -> 0 | CQ41: =ROUND((ROUND((AC41*AW41*1),2)*BC41),2) -> 136.74 | CR41: =(ROUND((ROUND((((ET41*1.05))*AV41*1),2)*BB41),2)+ROUND((ROUND(((AE41-((EU41*1.05)))*AV41*1),2)*BS41),2)) -> 0 | CS41: =ROUND((ROUND((AE41*AV41*1),2)*BS41),2) -> 0 | CT41: =ROUND((ROUND((AF41*AV41*1),2)*BA41),2) -> 0 | CU41: =AG41 -> 0 | CV41: =(AH41*AV41) -> 0 | CW41: =AI41 -> 0 | CX41: =AJ41 -> 0 | CY41: =S41*(BZ41/100) -> 0 | CZ41: =S41*(CA41/100) -> 0 | DB41: 14 | DE41: *1,05 | DF41: *1,05 | DG41: *1,05 | DI41: *1,05 | DJ41: *1,05 | DN41: 0 | DO41: 0 | DP41: 1 | DQ41: 1 | DU41: 1003 | DV41: м | DW41: м | DX41: 1 | EE41: 51697656 | EF41: 200 | EG41: Материалы строительные | EH41: 0 | EJ41: 1 | EK41: 1617 | EL41: ТСН-2001.1 Материалы строительные | EM41: ТСН-2001.1-1 | EO41: Поправка: О.П. п.3.4.30.г | EQ41: 131072 | ER41: 15.01 | ES41: 15.01 | ET41: 0 | EU41: 0 | EV41: 0 | EW41: 0 | EX41: 0 | EY41: 0 | FQ41: 0 | FR41: 0 | FS41: 0 | FX41: 0 | FY41: 0 | GD41: 0 | GF41: 1181244062 | GG41: 2 | GH41: 1 | GI41: 2 | GJ41: 0 | GK41: =ROUND(R41*(S12)/100,2) -> 0 | GL41: =ROUND(IF(AND(BH41=3,BI41=3,FS41<>0),P41,0),2) -> 0 | GM41: =ROUND(O41+X41+Y41+GK41,2)+GX41 -> 0 | GN41: =IF(OR(BI41=0,BI41=1),GM41-GX41,0) -> 0 | GO41: =IF(BI41=2,GM41-GX41,0) -> 0 | GP41: =IF(BI41=4,GM41-GX41,0) -> 0 | GR41: 0 | GS41: 3 | GT41: 0 | GV41: =ROUND((GT41),6) -> 0 | GW41: 1 | GX41: =ROUND(HC41*I41,2) -> 0 | HA41: 0 | HB41: 0 | HC41: =GV41*GW41 -> 0 | HS41: 0 | IK41: 0
A42: 17 | B42: 1 | E42: 8 | F42: 1.12-3-26 | G42: Трубы хризотилцементные безнапорные, марка БНТ, диаметр условного прохода 150 мм, внутренний диаметр 141 мм | H42: м | I42: =ROUND((I38)*1000,9) -> 0 | J42: 0 | K42: =ROUND((I38)*1000,9) -> 0 | O42: =ROUND(CP42,2) -> 0 | P42: =ROUND((ROUND((AC42*AW42*I42),2)*BC42),2) -> 0 | Q42: =(ROUND((ROUND((((ET42*1.05))*AV42*I42),2)*BB42),2)+ROUND((ROUND(((AE42-((EU42*1.05)))*AV42*I42),2)*BS42),2)) -> 0 | R42: =ROUND((ROUND((AE42*AV42*I42),2)*BS42),2) -> 0 | S42: =ROUND((ROUND((AF42*AV42*I42),2)*BA42),2) -> 0 | T42: =ROUND(CU42*I42,2) -> 0 | U42: =CV42*I42 -> 0 | V42: =CW42*I42 -> 0 | W42: =ROUND(CX42*I42,2) -> 0 | X42: =ROUND(CY42,2) -> 0 | Y42: =ROUND(CZ42,2) -> 0 | AA42: 56622490 | AB42: =ROUND((AC42+AD42+AF42),6) -> 24.4 | AC42: =ROUND((ES42),6) -> 24.4 | AD42: =ROUND(((((ET42*1.05))-((EU42*1.05)))+AE42),6) -> 0 | AE42: =ROUND(((EU42*1.05)),6) -> 0 | AF42: =ROUND(((EV42*1.05)),6) -> 0 | AG42: =ROUND((AP42),6) -> 0 | AH42: =((EW42*1.05)) -> 0 | AI42: =((EX42*1.05)) -> 0 | AJ42: =(AS42) -> 0 | AK42: 24.4 | AL42: 24.4 | AM42: 0 | AN42: 0 | AO42: 0 | AP42: 0 | AQ42: 0 | AR42: 0 | AS42: 0 | AT42: 0 | AU42: 0 | AV42: 1 | AW42: 1 | AZ42: 1 | BA42: 1 | BB42: 1 | BC42: 1 | BH42: 3 | BI42: 1 | BJ42: ТСН-2001.1 Доп. 70, Р. 12, о. 3, поз. 26 | BM42: 1617 | BN42: 0 | BP42: 0 | BQ42: 200 | BR42: 0 | BS42: 1 | BT42: 1 | BU42: 1 | BV42: 1 | BW42: 1 | BX42: 1 | BZ42: 0 | CA42: 0 | CE42: 30 | CF42: 0 | CG42: 0 | CM42: 0 | CN42: Поправка: О.П. п.3.4.30.г Наименование: В отношении объектов, реализуемых с привлечением средств бюджета города Москвы, затраты, учитывающие усложненные условия производства работ (стесненность, сложность складирования и транспортной логистики, наличие в зоне производства работ действующего технологического оборудования или движения технологического транспорта и т.п.), определяются заказчиком в задании на проектирование при составлении локальных сметных расчетов (смет): для объектов города Москвы, расположенных за пределами Московской кольцевой автомобильной дороги | CO42: 0 | CP42: =(P42+Q42+S42) -> 0 | CQ42: =ROUND((ROUND((AC42*AW42*1),2)*BC42),2) -> 24.4 | CR42: =(ROUND((ROUND((((ET42*1.05))*AV42*1),2)*BB42),2)+ROUND((ROUND(((AE42-((EU42*1.05)))*AV42*1),2)*BS42),2)) -> 0 | CS42: =ROUND((ROUND((AE42*AV42*1),2)*BS42),2) -> 0 | CT42: =ROUND((ROUND((AF42*AV42*1),2)*BA42),2) -> 0 | CU42: =AG42 -> 0 | CV42: =(AH42*AV42) -> 0 | CW42: =AI42 -> 0 | CX42: =AJ42 -> 0 | CY42: =((S42*BZ42)/100) -> 0 | CZ42: =((S42*CA42)/100) -> 0 | DB42: 15 | DE42: *1,05 | DF42: *1,05 | DG42: *1,05 | DI42: *1,05 | DJ42: *1,05 | DN42: 0 | DO42: 0 | DP42: 1 | DQ42: 1 | DU42: 1003 | DV42: м | DW42: м | DX42: 1 | EE42: 51697656 | EF42: 200 | EG42: Материалы строительные | EH42: 0 | EJ42: 1 | EK42: 1617 | EL42: ТСН-2001.1 Материалы строительные | EM42: ТСН-2001.1-1 | EO42: Поправка: О.П. п.3.4.30.г | EQ42: 131072 | ER42: 24.4 | ES42: 24.4 | ET42: 0 | EU42: 0 | EV42: 0 | EW42: 0 | EX42: 0 | EY42: 0 | FQ42: 0 | FR42: 0 | FS42: 0 | FX42: 0 | FY42: 0 | GD42: 0 | GF42: -1982695880 | GG42: 2 | GH42: 1 | GI42: -2 | GJ42: 0 | GK42: =ROUND(R42*(R12)/100,2) -> 0 | GL42: =ROUND(IF(AND(BH42=3,BI42=3,FS42<>0),P42,0),2) -> 0 | GM42: =ROUND(O42+X42+Y42+GK42,2)+GX42 -> 0 | GN42: =IF(OR(BI42=0,BI42=1),GM42-GX42,0) -> 0 | GO42: =IF(BI42=2,GM42-GX42,0) -> 0 | GP42: =IF(BI42=4,GM42-GX42,0) -> 0 | GR42: 0 | GS42: 0 | GT42: 0 | GV42: =ROUND((GT42),6) -> 0 | GW42: 1 | GX42: =ROUND(HC42*I42,2) -> 0 | HA42: 0 | HB42: 0 | HC42: =GV42*GW42 -> 0 | HS42: 0 | IK42: 0
A43: 17 | B43: 1 | E43: 8 | F43: 1.12-3-26 | G43: Трубы хризотилцементные безнапорные, марка БНТ, диаметр условного прохода 150 мм, внутренний диаметр 141 мм | H43: м | I43: =ROUND((I39)*1000,9) -> 0 | J43: 0 | K43: =ROUND((I39)*1000,9) -> 0 | O43: =ROUND(CP43,2) -> 0 | P43: =ROUND((ROUND((AC43*AW43*I43),2)*BC43),2) -> 0 | Q43: =(ROUND((ROUND((((ET43*1.05))*AV43*I43),2)*BB43),2)+ROUND((ROUND(((AE43-((EU43*1.05)))*AV43*I43),2)*BS43),2)) -> 0 | R43: =ROUND((ROUND((AE43*AV43*I43),2)*BS43),2) -> 0 | S43: =ROUND((ROUND((AF43*AV43*I43),2)*BA43),2) -> 0 | T43: =ROUND(CU43*I43,2) -> 0 | U43: =CV43*I43 -> 0 | V43: =CW43*I43 -> 0 | W43: =ROUND(CX43*I43,2) -> 0 | X43: =ROUND(CY43,2) -> 0 | Y43: =ROUND(CZ43,2) -> 0 | AA43: 56610029 | AB43: =ROUND((AC43+AD43+AF43),6) -> 24.4 | AC43: =ROUND((ES43),6) -> 24.4 | AD43: =ROUND(((((ET43*1.05))-((EU43*1.05)))+AE43),6) -> 0 | AE43: =ROUND(((EU43*1.05)),6) -> 0 | AF43: =ROUND(((EV43*1.05)),6) -> 0 | AG43: =ROUND((AP43),6) -> 0 | AH43: =((EW43*1.05)) -> 0 | AI43: =((EX43*1.05)) -> 0 | AJ43: =(AS43) -> 0 | AK43: 24.4 | AL43: 24.4 | AM43: 0 | AN43: 0 | AO43: 0 | AP43: 0 | AQ43: 0 | AR43: 0 | AS43: 0 | AT43: 0 | AU43: 0 | AV43: 1 | AW43: 1 | AZ43: 1 | BA43: 1 | BB43: 1 | BC43: 9.22 | BH43: 3 | BI43: 1 | BJ43: ТСН-2001.1 Доп. 70, Р. 12, о. 3, поз. 26 | BM43: 1617 | BN43: 0 | BO43: 1.12-3-26 | BP43: 1 | BQ43: 200 | BR43: 0 | BS43: 1 | BT43: 1 | BU43: 1 | BV43: 1 | BW43: 1 | BX43: 1 | BZ43: 0 | CA43: 0 | CE43: 30 | CF43: 0 | CG43: 0 | CM43: 0 | CN43: Поправка: О.П. п.3.4.30.г Наименование: В отношении объектов, реализуемых с привлечением средств бюджета города Москвы, затраты, учитывающие усложненные условия производства работ (стесненность, сложность складирования и транспортной логистики, наличие в зоне производства работ действующего технологического оборудования или движения технологического транспорта и т.п.), определяются заказчиком в задании на проектирование при составлении локальных сметных расчетов (смет): для объектов города Москвы, расположенных за пределами Московской кольцевой автомобильной дороги | CO43: 0 | CP43: =(P43+Q43+S43) -> 0 | CQ43: =ROUND((ROUND((AC43*AW43*1),2)*BC43),2) -> 224.97 | CR43: =(ROUND((ROUND((((ET43*1.05))*AV43*1),2)*BB43),2)+ROUND((ROUND(((AE43-((EU43*1.05)))*AV43*1),2)*BS43),2)) -> 0 | CS43: =ROUND((ROUND((AE43*AV43*1),2)*BS43),2) -> 0 | CT43: =ROUND((ROUND((AF43*AV43*1),2)*BA43),2) -> 0 | CU43: =AG43 -> 0 | CV43: =(AH43*AV43) -> 0 | CW43: =AI43 -> 0 | CX43: =AJ43 -> 0 | CY43: =S43*(BZ43/100) -> 0 | CZ43: =S43*(CA43/100) -> 0 | DB43: 16 | DE43: *1,05 | DF43: *1,05 | DG43: *1,05 | DI43: *1,05 | DJ43: *1,05 | DN43: 0 | DO43: 0 | DP43: 1 | DQ43: 1 | DU43: 1003 | DV43: м | DW43: м | DX43: 1 | EE43: 51697656 | EF43: 200 | EG43: Материалы строительные | EH43: 0 | EJ43: 1 | EK43: 1617 | EL43: ТСН-2001.1 Материалы строительные | EM43: ТСН-2001.1-1 | EO43: Поправка: О.П. п.3.4.30.г | EQ43: 131072 | ER43: 24.4 | ES43: 24.4 | ET43: 0 | EU43: 0 | EV43: 0 | EW43: 0 | EX43: 0 | EY43: 0 | FQ43: 0 | FR43: 0 | FS43: 0 | FX43: 0 | FY43: 0 | GD43: 0 | GF43: -1982695880 | GG43: 2 | GH43: 1 | GI43: 2 | GJ43: 0 | GK43: =ROUND(R43*(S12)/100,2) -> 0 | GL43: =ROUND(IF(AND(BH43=3,BI43=3,FS43<>0),P43,0),2) -> 0 | GM43: =ROUND(O43+X43+Y43+GK43,2)+GX43 -> 0 | GN43: =IF(OR(BI43=0,BI43=1),GM43-GX43,0) -> 0 | GO43: =IF(BI43=2,GM43-GX43,0) -> 0 | GP43: =IF(BI43=4,GM43-GX43,0) -> 0 | GR43: 0 | GS43: 3 | GT43: 0 | GV43: =ROUND((GT43),6) -> 0 | GW43: 1 | GX43: =ROUND(HC43*I43,2) -> 0 | HA43: 0 | HB43: 0 | HC43: =GV43*GW43 -> 0 | HS43: 0 | IK43: 0
A44: 17 | B44: 1 | D44: =ROW(EtalonRes!A29) -> 29 | E44: 9 | F44: 3.34-55-5 | G44: Устройство кабельной канализации из полиэтиленовых труб диаметром 160 мм, первая труба | H44: 1 км трубопровода | I44: 0 | J44: 0 | K44: 0 | O44: =ROUND(CP44,2) -> 0 | P44: =ROUND((ROUND((AC44*AW44*I44),2)*BC44),2) -> 0 | Q44: =(ROUND((ROUND((((ET44*1.05))*AV44*I44),2)*BB44),2)+ROUND((ROUND(((AE44-((EU44*1.05)))*AV44*I44),2)*BS44),2)) -> 0 | R44: =ROUND((ROUND((AE44*AV44*I44),2)*BS44),2) -> 0 | S44: =ROUND((ROUND((AF44*AV44*I44),2)*BA44),2) -> 0 | T44: =ROUND(CU44*I44,2) -> 0 | U44: =CV44*I44 -> 0 | V44: =CW44*I44 -> 0 | W44: =ROUND(CX44*I44,2) -> 0 | X44: =ROUND(CY44,2) -> 0 | Y44: =ROUND(CZ44,2) -> 0 | AA44: 56622490 | AB44: =ROUND((AC44+AD44+AF44),6) -> 1927.695 | AC44: =ROUND((ES44),6) -> 0 | AD44: =ROUND(((((ET44*1.05))-((EU44*1.05)))+AE44),6) -> 271.6455 | AE44: =ROUND(((EU44*1.05)),6) -> 29.8095 | AF44: =ROUND(((EV44*1.05)),6) -> 1656.0495 | AG44: =ROUND((AP44),6) -> 0 | AH44: =((EW44*1.05)) -> 155.2425 | AI44: =((EX44*1.05)) -> 0 | AJ44: =(AS44) -> 0 | AK44: 1835.9 | AL44: 0 | AM44: 258.71 | AN44: 28.39 | AO44: 1577.19 | AP44: 0 | AQ44: 147.85 | AR44: 0 | AS44: 0 | AT44: 112 | AU44: 70 | AV44: 1.067 | AW44: 1.081 | AZ44: 1 | BA44: 1 | BB44: 1 | BC44: 1 | BH44: 0 | BI44: 1 | BJ44: ТСН-2001.3 Доп. 68, Сб. 34, т. 55, поз. 5 | BM44: 2254 | BN44: 0 | BP44: 0 | BQ44: 30 | BR44: 0 | BS44: 1 | BT44: 1 | BU44: 1 | BV44: 1 | BW44: 1 | BX44: 1 | BZ44: 112 | CA44: 70 | CE44: 30 | CF44: 0 | CG44: 0 | CM44: 0 | CN44: Поправка: О.П. п.3.4.30.г Наименование: В отношении объектов, реализуемых с привлечением средств бюджета города Москвы, затраты, учитывающие усложненные условия производства работ (стесненность, сложность складирования и транспортной логистики, наличие в зоне производства работ действующего технологического оборудования или движения технологического транспорта и т.п.), определяются заказчиком в задании на проектирование при составлении локальных сметных расчетов (смет): для объектов города Москвы, расположенных за пределами Московской кольцевой автомобильной дороги | CO44: 0 | CP44: =(P44+Q44+S44) -> 0 | CQ44: =ROUND((ROUND((AC44*AW44*1),2)*BC44),2) -> 0 | CR44: =(ROUND((ROUND((((ET44*1.05))*AV44*1),2)*BB44),2)+ROUND((ROUND(((AE44-((EU44*1.05)))*AV44*1),2)*BS44),2)) -> 289.85 | CS44: =ROUND((ROUND((AE44*AV44*1),2)*BS44),2) -> 31.81 | CT44: =ROUND((ROUND((AF44*AV44*1),2)*BA44),2) -> 1767 | CU44: =AG44 -> 0 | CV44: =(AH44*AV44) -> 165.64375 | CW44: =AI44 -> 0 | CX44: =AJ44 -> 0 | CY44: =((S44*BZ44)/100) -> 0 | CZ44: =((S44*CA44)/100) -> 0 | DB44: 17 | DE44: *1,05 | DF44: *1,05 | DG44: *1,05 | DI44: *1,05 | DJ44: *1,05 | DN44: 0 | DO44: 0 | DP44: 1 | DQ44: 1 | DU44: 1013 | DV44: 1 км трубопровода | DW44: 1 км трубопровода | DX44: 1 | EE44: 51698335 | EF44: 30 | EG44: Строительные работы | EH44: 0 | EJ44: 1 | EK44: 2254 | EL44: ТСН-2001.3-34. 34-55-1...34-55-10 (доп. 68) | EM44: ТСН-2001.3-34-20 | EO44: Поправка: О.П. п.3.4.30.г | EQ44: 131072 | ER44: 1835.9 | ES44: 0 | ET44: 258.71 | EU44: 28.39 | EV44: 1577.19 | EW44: 147.85 | EX44: 0 | EY44: 0 | FQ44: 0 | FR44: 0 | FS44: 0 | FX44: 112 | FY44: 70 | GD44: 0 | GF44: -1068329133 | GG44: 2 | GH44: 1 | GI44: -2 | GJ44: 0 | GK44: =ROUND(R44*(R12)/100,2) -> 0 | GL44: =ROUND(IF(AND(BH44=3,BI44=3,FS44<>0),P44,0),2) -> 0 | GM44: =ROUND(O44+X44+Y44+GK44,2)+GX44 -> 0 | GN44: =IF(OR(BI44=0,BI44=1),GM44-GX44,0) -> 0 | GO44: =IF(BI44=2,GM44-GX44,0) -> 0 | GP44: =IF(BI44=4,GM44-GX44,0) -> 0 | GR44: 0 | GS44: 0 | GT44: 0 | GV44: =ROUND((GT44),6) -> 0 | GW44: 1 | GX44: =ROUND(HC44*I44,2) -> 0 | HA44: 0 | HB44: 0 | HC44: =GV44*GW44 -> 0 | HS44: 0 | IK44: 0
A45: 17 | B45: 1 | D45: =ROW(EtalonRes!A34) -> 34 | E45: 9 | F45: 3.34-55-5 | G45: Устройство кабельной канализации из полиэтиленовых труб диаметром 160 мм, первая труба | H45: 1 км трубопровода | I45: 0 | J45: 0 | K45: 0 | O45: =ROUND(CP45,2) -> 0 | P45: =ROUND((ROUND((AC45*AW45*I45),2)*BC45),2) -> 0 | Q45: =(ROUND((ROUND((((ET45*1.05))*AV45*I45),2)*BB45),2)+ROUND((ROUND(((AE45-((EU45*1.05)))*AV45*I45),2)*BS45),2)) -> 0 | R45: =ROUND((ROUND((AE45*AV45*I45),2)*BS45),2) -> 0 | S45: =ROUND((ROUND((AF45*AV45*I45),2)*BA45),2) -> 0 | T45: =ROUND(CU45*I45,2) -> 0 | U45: =CV45*I45 -> 0 | V45: =CW45*I45 -> 0 | W45: =ROUND(CX45*I45,2) -> 0 | X45: =ROUND(CY45,2) -> 0 | Y45: =ROUND(CZ45,2) -> 0 | AA45: 56610029 | AB45: =ROUND((AC45+AD45+AF45),6) -> 1927.695 | AC45: =ROUND((ES45),6) -> 0 | AD45: =ROUND(((((ET45*1.05))-((EU45*1.05)))+AE45),6) -> 271.6455 | AE45: =ROUND(((EU45*1.05)),6) -> 29.8095 | AF45: =ROUND(((EV45*1.05)),6) -> 1656.0495 | AG45: =ROUND((AP45),6) -> 0 | AH45: =((EW45*1.05)) -> 155.2425 | AI45: =((EX45*1.05)) -> 0 | AJ45: =(AS45) -> 0 | AK45: 1835.9 | AL45: 0 | AM45: 258.71 | AN45: 28.39 | AO45: 1577.19 | AP45: 0 | AQ45: 147.85 | AR45: 0 | AS45: 0 | AT45: 92 | AU45: 41 | AV45: 1.067 | AW45: 1.081 | AZ45: 1 | BA45: 34.51 | BB45: 11.8 | BC45: 1 | BH45: 0 | BI45: 1 | BJ45: ТСН-2001.3 Доп. 68, Сб. 34, т. 55, поз. 5 | BM45: 2254 | BN45: 0 | BO45: 3.34-55-5 | BP45: 1 | BQ45: 30 | BR45: 0 | BS45: 34.51 | BT45: 1 | BU45: 1 | BV45: 1 | BW45: 1 | BX45: 1 | BZ45: 92 | CA45: 41 | CE45: 30 | CF45: 0 | CG45: 0 | CM45: 0 | CN45: Поправка: О.П. п.3.4.30.г Наименование: В отношении объектов, реализуемых с привлечением средств бюджета города Москвы, затраты, учитывающие усложненные условия производства работ (стесненность, сложность складирования и транспортной логистики, наличие в зоне производства работ действующего технологического оборудования или движения технологического транспорта и т.п.), определяются заказчиком в задании на проектирование при составлении локальных сметных расчетов (смет): для объектов города Москвы, расположенных за пределами Московской кольцевой автомобильной дороги | CO45: 0 | CP45: =(P45+Q45+S45) -> 0 | CQ45: =ROUND((ROUND((AC45*AW45*1),2)*BC45),2) -> 0 | CR45: =(ROUND((ROUND((((ET45*1.05))*AV45*1),2)*BB45),2)+ROUND((ROUND(((AE45-((EU45*1.05)))*AV45*1),2)*BS45),2)) -> 3420.23 | CS45: =ROUND((ROUND((AE45*AV45*1),2)*BS45),2) -> 1097.76 | CT45: =ROUND((ROUND((AF45*AV45*1),2)*BA45),2) -> 60979.17 | CU45: =AG45 -> 0 | CV45: =(AH45*AV45) -> 165.64375 | CW45: =AI45 -> 0 | CX45: =AJ45 -> 0 | CY45: =S45*(BZ45/100) -> 0 | CZ45: =S45*(CA45/100) -> 0 | DB45: 18 | DE45: *1,05 | DF45: *1,05 | DG45: *1,05 | DI45: *1,05 | DJ45: *1,05 | DN45: 112 | DO45: 70 | DP45: 1.067 | DQ45: 1.081 | DU45: 1013 | DV45: 1 км трубопровода | DW45: 1 км трубопровода | DX45: 1 | EE45: 51698335 | EF45: 30 | EG45: Строительные работы | EH45: 0 | EJ45: 1 | EK45: 2254 | EL45: ТСН-2001.3-34. 34-55-1...34-55-10 (доп. 68) | EM45: ТСН-2001.3-34-20 | EO45: Поправка: О.П. п.3.4.30.г | EQ45: 131072 | ER45: 1835.9 | ES45: 0 | ET45: 258.71 | EU45: 28.39 | EV45: 1577.19 | EW45: 147.85 | EX45: 0 | EY45: 0 | FQ45: 0 | FR45: 0 | FS45: 0 | FX45: 112 | FY45: 70 | GD45: 0 | GF45: -1068329133 | GG45: 2 | GH45: 1 | GI45: 2 | GJ45: 0 | GK45: =ROUND(R45*(S12)/100,2) -> 0 | GL45: =ROUND(IF(AND(BH45=3,BI45=3,FS45<>0),P45,0),2) -> 0 | GM45: =ROUND(O45+X45+Y45+GK45,2)+GX45 -> 0 | GN45: =IF(OR(BI45=0,BI45=1),GM45-GX45,0) -> 0 | GO45: =IF(BI45=2,GM45-GX45,0) -> 0 | GP45: =IF(BI45=4,GM45-GX45,0) -> 0 | GR45: 0 | GS45: 3 | GT45: 0 | GV45: =ROUND((GT45),6) -> 0 | GW45: 1 | GX45: =ROUND(HC45*I45,2) -> 0 | HA45: 0 | HB45: 0 | HC45: =GV45*GW45 -> 0 | HS45: 0 | IK45: 0
A46: 17 | B46: 1 | D46: =ROW(EtalonRes!A40) -> 40 | E46: 10 | F46: 3.34-55-6 | G46: Добавлять на каждую последующую трубу к позиции 3.34-55-5 | H46: 1 км трубопровода | I46: 0 | J46: 0 | K46: 0 | O46: =ROUND(CP46,2) -> 0 | P46: =ROUND((ROUND((AC46*AW46*I46),2)*BC46),2) -> 0 | Q46: =(ROUND((ROUND((((ET46*1.05))*AV46*I46),2)*BB46),2)+ROUND((ROUND(((AE46-((EU46*1.05)))*AV46*I46),2)*BS46),2)) -> 0 | R46: =ROUND((ROUND((AE46*AV46*I46),2)*BS46),2) -> 0 | S46: =ROUND((ROUND((AF46*AV46*I46),2)*BA46),2) -> 0 | T46: =ROUND(CU46*I46,2) -> 0 | U46: =CV46*I46 -> 0 | V46: =CW46*I46 -> 0 | W46: =ROUND(CX46*I46,2) -> 0 | X46: =ROUND(CY46,2) -> 0 | Y46: =ROUND(CZ46,2) -> 0 | AA46: 56622490 | AB46: =ROUND((AC46+AD46+AF46),6) -> 1495.0845 | AC46: =ROUND((ES46),6) -> 0 | AD46: =ROUND(((((ET46*1.05))-((EU46*1.05)))+AE46),6) -> 268.7685 | AE46: =ROUND(((EU46*1.05)),6) -> 29.484 | AF46: =ROUND(((EV46*1.05)),6) -> 1226.316 | AG46: =ROUND((AP46),6) -> 0 | AH46: =((EW46*1.05)) -> 113.19 | AI46: =((EX46*1.05)) -> 0 | AJ46: =(AS46) -> 0 | AK46: 1423.89 | AL46: 0 | AM46: 255.97 | AN46: 28.08 | AO46: 1167.92 | AP46: 0 | AQ46: 107.8 | AR46: 0 | AS46: 0 | AT46: 112 | AU46: 70 | AV46: 1.067 | AW46: 1.081 | AZ46: 1 | BA46: 1 | BB46: 1 | BC46: 1 | BH46: 0 | BI46: 1 | BJ46: ТСН-2001.3 Доп. 68, Сб. 34, т. 55, поз. 6 | BM46: 2254 | BN46: 0 | BP46: 0 | BQ46: 30 | BR46: 0 | BS46: 1 | BT46: 1 | BU46: 1 | BV46: 1 | BW46: 1 | BX46: 1 | BZ46: 112 | CA46: 70 | CE46: 30 | CF46: 0 | CG46: 0 | CM46: 0 | CN46: Поправка: О.П. п.3.4.30.г Наименование: В отношении объектов, реализуемых с привлечением средств бюджета города Москвы, затраты, учитывающие усложненные условия производства работ (стесненность, сложность складирования и транспортной логистики, наличие в зоне производства работ действующего технологического оборудования или движения технологического транспорта и т.п.), определяются заказчиком в задании на проектирование при составлении локальных сметных расчетов (смет): для объектов города Москвы, расположенных за пределами Московской кольцевой автомобильной дороги | CO46: 0 | CP46: =(P46+Q46+S46) -> 0 | CQ46: =ROUND((ROUND((AC46*AW46*1),2)*BC46),2) -> 0 | CR46: =(ROUND((ROUND((((ET46*1.05))*AV46*1),2)*BB46),2)+ROUND((ROUND(((AE46-((EU46*1.05)))*AV46*1),2)*BS46),2)) -> 286.78 | CS46: =ROUND((ROUND((AE46*AV46*1),2)*BS46),2) -> 31.46 | CT46: =ROUND((ROUND((AF46*AV46*1),2)*BA46),2) -> 1308.48 | CU46: =AG46 -> 0 | CV46: =(AH46*AV46) -> 120.77373 | CW46: =AI46 -> 0 | CX46: =AJ46 -> 0 | CY46: =((S46*BZ46)/100) -> 0 | CZ46: =((S46*CA46)/100) -> 0 | DB46: 19 | DE46: *1,05 | DF46: *1,05 | DG46: *1,05 | DI46: *1,05 | DJ46: *1,05 | DN46: 0 | DO46: 0 | DP46: 1 | DQ46: 1 | DU46: 1013 | DV46: 1 км трубопровода | DW46: 1 км трубопровода | DX46: 1 | EE46: 51698335 | EF46: 30 | EG46: Строительные работы | EH46: 0 | EJ46: 1 | EK46: 2254 | EL46: ТСН-2001.3-34. 34-55-1...34-55-10 (доп. 68) | EM46: ТСН-2001.3-34-20 | EO46: Поправка: О.П. п.3.4.30.г | EQ46: 131072 | ER46: 1423.89 | ES46: 0 | ET46: 255.97 | EU46: 28.08 | EV46: 1167.92 | EW46: 107.8 | EX46: 0 | EY46: 0 | FQ46: 0 | FR46: 0 | FS46: 0 | FX46: 112 | FY46: 70 | GD46: 0 | GF46: -654616270 | GG46: 2 | GH46: 1 | GI46: -2 | GJ46: 0 | GK46: =ROUND(R46*(R12)/100,2) -> 0 | GL46: =ROUND(IF(AND(BH46=3,BI46=3,FS46<>0),P46,0),2) -> 0 | GM46: =ROUND(O46+X46+Y46+GK46,2)+GX46 -> 0 | GN46: =IF(OR(BI46=0,BI46=1),GM46-GX46,0) -> 0 | GO46: =IF(BI46=2,GM46-GX46,0) -> 0 | GP46: =IF(BI46=4,GM46-GX46,0) -> 0 | GR46: 0 | GS46: 0 | GT46: 0 | GV46: =ROUND((GT46),6) -> 0 | GW46: 1 | GX46: =ROUND(HC46*I46,2) -> 0 | HA46: 0 | HB46: 0 | HC46: =GV46*GW46 -> 0 | HS46: 0 | IK46: 0
A47: 17 | B47: 1 | D47: =ROW(EtalonRes!A46) -> 46 | E47: 10 | F47: 3.34-55-6 | G47: Добавлять на каждую последующую трубу к позиции 3.34-55-5 | H47: 1 км трубопровода | I47: 0 | J47: 0 | K47: 0 | O47: =ROUND(CP47,2) -> 0 | P47: =ROUND((ROUND((AC47*AW47*I47),2)*BC47),2) -> 0 | Q47: =(ROUND((ROUND((((ET47*1.05))*AV47*I47),2)*BB47),2)+ROUND((ROUND(((AE47-((EU47*1.05)))*AV47*I47),2)*BS47),2)) -> 0 | R47: =ROUND((ROUND((AE47*AV47*I47),2)*BS47),2) -> 0 | S47: =ROUND((ROUND((AF47*AV47*I47),2)*BA47),2) -> 0 | T47: =ROUND(CU47*I47,2) -> 0 | U47: =CV47*I47 -> 0 | V47: =CW47*I47 -> 0 | W47: =ROUND(CX47*I47,2) -> 0 | X47: =ROUND(CY47,2) -> 0 | Y47: =ROUND(CZ47,2) -> 0 | AA47: 56610029 | AB47: =ROUND((AC47+AD47+AF47),6) -> 1495.0845 | AC47: =ROUND((ES47),6) -> 0 | AD47: =ROUND(((((ET47*1.05))-((EU47*1.05)))+AE47),6) -> 268.7685 | AE47: =ROUND(((EU47*1.05)),6) -> 29.484 | AF47: =ROUND(((EV47*1.05)),6) -> 1226.316 | AG47: =ROUND((AP47),6) -> 0 | AH47: =((EW47*1.05)) -> 113.19 | AI47: =((EX47*1.05)) -> 0 | AJ47: =(AS47) -> 0 | AK47: 1423.89 | AL47: 0 | AM47: 255.97 | AN47: 28.08 | AO47: 1167.92 | AP47: 0 | AQ47: 107.8 | AR47: 0 | AS47: 0 | AT47: 92 | AU47: 41 | AV47: 1.067 | AW47: 1.081 | AZ47: 1 | BA47: 34.51 | BB47: 11.8 | BC47: 1 | BH47: 0 | BI47: 1 | BJ47: ТСН-2001.3 Доп. 68, Сб. 34, т. 55, поз. 6 | BM47: 2254 | BN47: 0 | BO47: 3.34-55-6 | BP47: 1 | BQ47: 30 | BR47: 0 | BS47: 34.51 | BT47: 1 | BU47: 1 | BV47: 1 | BW47: 1 | BX47: 1 | BZ47: 92 | CA47: 41 | CE47: 30 | CF47: 0 | CG47: 0 | CM47: 0 | CN47: Поправка: О.П. п.3.4.30.г Наименование: В отношении объектов, реализуемых с привлечением средств бюджета города Москвы, затраты, учитывающие усложненные условия производства работ (стесненность, сложность складирования и транспортной логистики, наличие в зоне производства работ действующего технологического оборудования или движения технологического транспорта и т.п.), определяются заказчиком в задании на проектирование при составлении локальных сметных расчетов (смет): для объектов города Москвы, расположенных за пределами Московской кольцевой автомобильной дороги | CO47: 0 | CP47: =(P47+Q47+S47) -> 0 | CQ47: =ROUND((ROUND((AC47*AW47*1),2)*BC47),2) -> 0 | CR47: =(ROUND((ROUND((((ET47*1.05))*AV47*1),2)*BB47),2)+ROUND((ROUND(((AE47-((EU47*1.05)))*AV47*1),2)*BS47),2)) -> 3384 | CS47: =ROUND((ROUND((AE47*AV47*1),2)*BS47),2) -> 1085.68 | CT47: =ROUND((ROUND((AF47*AV47*1),2)*BA47),2) -> 45155.64 | CU47: =AG47 -> 0 | CV47: =(AH47*AV47) -> 120.77373 | CW47: =AI47 -> 0 | CX47: =AJ47 -> 0 | CY47: =S47*(BZ47/100) -> 0 | CZ47: =S47*(CA47/100) -> 0 | DB47: 20 | DE47: *1,05 | DF47: *1,05 | DG47: *1,05 | DI47: *1,05 | DJ47: *1,05 | DN47: 112 | DO47: 70 | DP47: 1.067 | DQ47: 1.081 | DU47: 1013 | DV47: 1 км трубопровода | DW47: 1 км трубопровода | DX47: 1 | EE47: 51698335 | EF47: 30 | EG47: Строительные работы | EH47: 0 | EJ47: 1 | EK47: 2254 | EL47: ТСН-2001.3-34. 34-55-1...34-55-10 (доп. 68) | EM47: ТСН-2001.3-34-20 | EO47: Поправка: О.П. п.3.4.30.г | EQ47: 131072 | ER47: 1423.89 | ES47: 0 | ET47: 255.97 | EU47: 28.08 | EV47: 1167.92 | EW47: 107.8 | EX47: 0 | EY47: 0 | FQ47: 0 | FR47: 0 | FS47: 0 | FX47: 112 | FY47: 70 | GD47: 0 | GF47: -654616270 | GG47: 2 | GH47: 1 | GI47: 2 | GJ47: 0 | GK47: =ROUND(R47*(S12)/100,2) -> 0 | GL47: =ROUND(IF(AND(BH47=3,BI47=3,FS47<>0),P47,0),2) -> 0 | GM47: =ROUND(O47+X47+Y47+GK47,2)+GX47 -> 0 | GN47: =IF(OR(BI47=0,BI47=1),GM47-GX47,0) -> 0 | GO47: =IF(BI47=2,GM47-GX47,0) -> 0 | GP47: =IF(BI47=4,GM47-GX47,0) -> 0 | GR47: 0 | GS47: 3 | GT47: 0 | GV47: =ROUND((GT47),6) -> 0 | GW47: 1 | GX47: =ROUND(HC47*I47,2) -> 0 | HA47: 0 | HB47: 0 | HC47: =GV47*GW47 -> 0 | HS47: 0 | IK47: 0
A48: 17 | B48: 1 | E48: 11 | F48: КП | G48: Труба ТЗК Энергопласт ТС3 160/8 SN8 F4 МКС | H48: м | I48: =ROUND((I44+I46)*1000,9) -> 0 | J48: 0 | K48: =ROUND((I44+I46)*1000,9) -> 0 | O48: =ROUND(CP48,2) -> 0 | P48: =ROUND((ROUND((AC48*AW48*I48),2)*BC48),2) -> 0 | Q48: =(ROUND((ROUND((((ET48*1.05))*AV48*I48),2)*BB48),2)+ROUND((ROUND(((AE48-((EU48*1.05)))*AV48*I48),2)*BS48),2)) -> 0 | R48: =ROUND((ROUND((AE48*AV48*I48),2)*BS48),2) -> 0 | S48: =ROUND((ROUND((AF48*AV48*I48),2)*BA48),2) -> 0 | T48: =ROUND(CU48*I48,2) -> 0 | U48: =CV48*I48 -> 0 | V48: =CW48*I48 -> 0 | W48: =ROUND(CX48*I48,2) -> 0 | X48: =ROUND(CY48,2) -> 0 | Y48: =ROUND(CZ48,2) -> 0 | AA48: 56622490 | AB48: =ROUND((AC48+AD48+AF48),6) -> 1076 | AC48: =ROUND((ES48),6) -> 1076 | AD48: =ROUND(((((ET48*1.05))-((EU48*1.05)))+AE48),6) -> 0 | AE48: =ROUND(((EU48*1.05)),6) -> 0 | AF48: =ROUND(((EV48*1.05)),6) -> 0 | AG48: =ROUND((AP48),6) -> 0 | AH48: =((EW48*1.05)) -> 0 | AI48: =((EX48*1.05)) -> 0 | AJ48: =(AS48) -> 0 | AK48: 1076 | AL48: 1076 | AM48: 0 | AN48: 0 | AO48: 0 | AP48: 0 | AQ48: 0 | AR48: 0 | AS48: 0 | AT48: 0 | AU48: 0 | AV48: 1 | AW48: 1 | AZ48: 1 | BA48: 1 | BB48: 1 | BC48: 1 | BH48: 3 | BI48: 1 | BM48: 1617 | BN48: 0 | BP48: 0 | BQ48: 200 | BR48: 0 | BS48: 1 | BT48: 1 | BU48: 1 | BV48: 1 | BW48: 1 | BX48: 1 | BZ48: 0 | CA48: 0 | CE48: 30 | CF48: 0 | CG48: 0 | CM48: 0 | CN48: Поправка: О.П. п.3.4.30.г Наименование: В отношении объектов, реализуемых с привлечением средств бюджета города Москвы, затраты, учитывающие усложненные условия производства работ (стесненность, сложность складирования и транспортной логистики, наличие в зоне производства работ действующего технологического оборудования или движения технологического транспорта и т.п.), определяются заказчиком в задании на проектирование при составлении локальных сметных расчетов (смет): для объектов города Москвы, расположенных за пределами Московской кольцевой автомобильной дороги | CO48: 0 | CP48: =(P48+Q48+S48) -> 0 | CQ48: =ROUND((ROUND((AC48*AW48*1),2)*BC48),2) -> 1076 | CR48: =(ROUND((ROUND((((ET48*1.05))*AV48*1),2)*BB48),2)+ROUND((ROUND(((AE48-((EU48*1.05)))*AV48*1),2)*BS48),2)) -> 0 | CS48: =ROUND((ROUND((AE48*AV48*1),2)*BS48),2) -> 0 | CT48: =ROUND((ROUND((AF48*AV48*1),2)*BA48),2) -> 0 | CU48: =AG48 -> 0 | CV48: =(AH48*AV48) -> 0 | CW48: =AI48 -> 0 | CX48: =AJ48 -> 0 | CY48: =((S48*BZ48)/100) -> 0 | CZ48: =((S48*CA48)/100) -> 0 | DB48: 21 | DE48: *1,05 | DF48: *1,05 | DG48: *1,05 | DI48: *1,05 | DJ48: *1,05 | DN48: 0 | DO48: 0 | DP48: 1 | DQ48: 1 | DU48: 1003 | DV48: м | DW48: м | DX48: 1 | EE48: 51697656 | EF48: 200 | EG48: Материалы строительные | EH48: 0 | EJ48: 1 | EK48: 1617 | EL48: ТСН-2001.1 Материалы строительные | EM48: ТСН-2001.1-1 | EO48: Поправка: О.П. п.3.4.30.г | EQ48: 131072 | ER48: 112.43 | ES48: 1076 | ET48: 0 | EU48: 0 | EV48: 0 | EW48: 0 | EX48: 0 | EY48: 0 | FQ48: 0 | FR48: 0 | FS48: 0 | FX48: 0 | FY48: 0 | GA48: [1 265,88 / 1,2] + 2% Трансп | GD48: 0 | GF48: -1840773881 | GG48: 2 | GH48: 4 | GI48: 3 | GJ48: 0 | GK48: =ROUND(R48*(R12)/100,2) -> 0 | GL48: =ROUND(IF(AND(BH48=3,BI48=3,FS48<>0),P48,0),2) -> 0 | GM48: =ROUND(O48+X48+Y48+GK48,2)+GX48 -> 0 | GN48: =IF(OR(BI48=0,BI48=1),GM48-GX48,0) -> 0 | GO48: =IF(BI48=2,GM48-GX48,0) -> 0 | GP48: =IF(BI48=4,GM48-GX48,0) -> 0 | GR48: 0 | GS48: 2 | GT48: 0 | GV48: =ROUND((GT48),6) -> 0 | GW48: 1 | GX48: =ROUND(HC48*I48,2) -> 0 | HA48: 0 | HB48: 0 | HC48: =GV48*GW48 -> 0 | HE48: 2 | HF48: 0 | HS48: 0 | IK48: 0
A49: 17 | B49: 1 | E49: 11 | F49: КП | G49: Труба ТЗК Энергопласт ТС3 160/8 SN8 F4 МКС | H49: м | I49: =ROUND((I45+I47)*1000,9) -> 0 | J49: 0 | K49: =ROUND((I45+I47)*1000,9) -> 0 | O49: =ROUND(CP49,2) -> 0 | P49: =ROUND((ROUND((AC49*AW49*I49),2)*BC49),2) -> 0 | Q49: =(ROUND((ROUND((((ET49*1.05))*AV49*I49),2)*BB49),2)+ROUND((ROUND(((AE49-((EU49*1.05)))*AV49*I49),2)*BS49),2)) -> 0 | R49: =ROUND((ROUND((AE49*AV49*I49),2)*BS49),2) -> 0 | S49: =ROUND((ROUND((AF49*AV49*I49),2)*BA49),2) -> 0 | T49: =ROUND(CU49*I49,2) -> 0 | U49: =CV49*I49 -> 0 | V49: =CW49*I49 -> 0 | W49: =ROUND(CX49*I49,2) -> 0 | X49: =ROUND(CY49,2) -> 0 | Y49: =ROUND(CZ49,2) -> 0 | AA49: 56610029 | AB49: =ROUND((AC49+AD49+AF49),6) -> 1076 | AC49: =ROUND((ES49),6) -> 1076 | AD49: =ROUND(((((ET49*1.05))-((EU49*1.05)))+AE49),6) -> 0 | AE49: =ROUND(((EU49*1.05)),6) -> 0 | AF49: =ROUND(((EV49*1.05)),6) -> 0 | AG49: =ROUND((AP49),6) -> 0 | AH49: =((EW49*1.05)) -> 0 | AI49: =((EX49*1.05)) -> 0 | AJ49: =(AS49) -> 0 | AK49: 1076 | AL49: 1076 | AM49: 0 | AN49: 0 | AO49: 0 | AP49: 0 | AQ49: 0 | AR49: 0 | AS49: 0 | AT49: 0 | AU49: 0 | AV49: 1 | AW49: 1 | AZ49: 1 | BA49: 1 | BB49: 1 | BC49: 1 | BH49: 3 | BI49: 1 | BM49: 1617 | BN49: 0 | BP49: 0 | BQ49: 200 | BR49: 0 | BS49: 1 | BT49: 1 | BU49: 1 | BV49: 1 | BW49: 1 | BX49: 1 | BZ49: 0 | CA49: 0 | CE49: 30 | CF49: 0 | CG49: 0 | CM49: 0 | CN49: Поправка: О.П. п.3.4.30.г Наименование: В отношении объектов, реализуемых с привлечением средств бюджета города Москвы, затраты, учитывающие усложненные условия производства работ (стесненность, сложность складирования и транспортной логистики, наличие в зоне производства работ действующего технологического оборудования или движения технологического транспорта и т.п.), определяются заказчиком в задании на проектирование при составлении локальных сметных расчетов (смет): для объектов города Москвы, расположенных за пределами Московской кольцевой автомобильной дороги | CO49: 0 | CP49: =(P49+Q49+S49) -> 0 | CQ49: =ROUND((ROUND((AC49*AW49*1),2)*BC49),2) -> 1076 | CR49: =(ROUND((ROUND((((ET49*1.05))*AV49*1),2)*BB49),2)+ROUND((ROUND(((AE49-((EU49*1.05)))*AV49*1),2)*BS49),2)) -> 0 | CS49: =ROUND((ROUND((AE49*AV49*1),2)*BS49),2) -> 0 | CT49: =ROUND((ROUND((AF49*AV49*1),2)*BA49),2) -> 0 | CU49: =AG49 -> 0 | CV49: =(AH49*AV49) -> 0 | CW49: =AI49 -> 0 | CX49: =AJ49 -> 0 | CY49: =S49*(BZ49/100) -> 0 | CZ49: =S49*(CA49/100) -> 0 | DB49: 22 | DE49: *1,05 | DF49: *1,05 | DG49: *1,05 | DI49: *1,05 | DJ49: *1,05 | DN49: 0 | DO49: 0 | DP49: 1 | DQ49: 1 | DU49: 1003 | DV49: м | DW49: м | DX49: 1 | EE49: 51697656 | EF49: 200 | EG49: Материалы строительные | EH49: 0 | EJ49: 1 | EK49: 1617 | EL49: ТСН-2001.1 Материалы строительные | EM49: ТСН-2001.1-1 | EO49: Поправка: О.П. п.3.4.30.г | EQ49: 131072 | ER49: 112.43 | ES49: 1076 | ET49: 0 | EU49: 0 | EV49: 0 | EW49: 0 | EX49: 0 | EY49: 0 | EZ49: 5 | FC49: 1 | FD49: 18 | FF49: 1265.88 | FQ49: 0 | FR49: 0 | FS49: 0 | FX49: 0 | FY49: 0 | GA49: [1 265,88 / 1,2] + 2% Трансп | GD49: 0 | GF49: -1840773881 | GG49: 2 | GH49: 3 | GI49: -2 | GJ49: 0 | GK49: =ROUND(R49*(S12)/100,2) -> 0 | GL49: =ROUND(IF(AND(BH49=3,BI49=3,FS49<>0),P49,0),2) -> 0 | GM49: =ROUND(O49+X49+Y49+GK49,2)+GX49 -> 0 | GN49: =IF(OR(BI49=0,BI49=1),GM49-GX49,0) -> 0 | GO49: =IF(BI49=2,GM49-GX49,0) -> 0 | GP49: =IF(BI49=4,GM49-GX49,0) -> 0 | GR49: 1 | GS49: 1 | GT49: 0 | GV49: =ROUND((GT49),6) -> 0 | GW49: 1 | GX49: =ROUND(HC49*I49,2) -> 0 | HA49: 0 | HB49: 0 | HC49: =GV49*GW49 -> 0 | HE49: 2 | HF49: 0 | HS49: 0 | IK49: 0
A50: 17 | B50: 1 | E50: 12 | F50: 1.1-1-766 | G50: Песок для строительных работ, рядовой (карьерный) | H50: м3 | I50: 0 | J50: 0 | K50: 0 | O50: =ROUND(CP50,2) -> 0 | P50: =ROUND((ROUND((AC50*AW50*I50),2)*BC50),2) -> 0 | Q50: =(ROUND((ROUND((((ET50*1.05))*AV50*I50),2)*BB50),2)+ROUND((ROUND(((AE50-((EU50*1.05)))*AV50*I50),2)*BS50),2)) -> 0 | R50: =ROUND((ROUND((AE50*AV50*I50),2)*BS50),2) -> 0 | S50: =ROUND((ROUND((AF50*AV50*I50),2)*BA50),2) -> 0 | T50: =ROUND(CU50*I50,2) -> 0 | U50: =CV50*I50 -> 0 | V50: =CW50*I50 -> 0 | W50: =ROUND(CX50*I50,2) -> 0 | X50: =ROUND(CY50,2) -> 0 | Y50: =ROUND(CZ50,2) -> 0 | AA50: 56622490 | AB50: =ROUND((AC50+AD50+AF50),6) -> 104.99 | AC50: =ROUND((ES50),6) -> 104.99 | AD50: =ROUND(((((ET50*1.05))-((EU50*1.05)))+AE50),6) -> 0 | AE50: =ROUND(((EU50*1.05)),6) -> 0 | AF50: =ROUND(((EV50*1.05)),6) -> 0 | AG50: =ROUND((AP50),6) -> 0 | AH50: =((EW50*1.05)) -> 0 | AI50: =((EX50*1.05)) -> 0 | AJ50: =(AS50) -> 0 | AK50: 104.99 | AL50: 104.99 | AM50: 0 | AN50: 0 | AO50: 0 | AP50: 0 | AQ50: 0 | AR50: 0 | AS50: 0 | AT50: 0 | AU50: 0 | AV50: 1 | AW50: 1 | AZ50: 1 | BA50: 1 | BB50: 1 | BC50: 1 | BH50: 3 | BI50: 1 | BJ50: ТСН-2001.1 Доп. 69, Р. 1, о. 1, поз. 766 | BM50: 1617 | BN50: 0 | BP50: 0 | BQ50: 200 | BR50: 0 | BS50: 1 | BT50: 1 | BU50: 1 | BV50: 1 | BW50: 1 | BX50: 1 | BZ50: 0 | CA50: 0 | CE50: 30 | CF50: 0 | CG50: 0 | CM50: 0 | CN50: Поправка: О.П. п.3.4.30.г Наименование: В отношении объектов, реализуемых с привлечением средств бюджета города Москвы, затраты, учитывающие усложненные условия производства работ (стесненность, сложность складирования и транспортной логистики, наличие в зоне производства работ действующего технологического оборудования или движения технологического транспорта и т.п.), определяются заказчиком в задании на проектирование при составлении локальных сметных расчетов (смет): для объектов города Москвы, расположенных за пределами Московской кольцевой автомобильной дороги | CO50: 0 | CP50: =(P50+Q50+S50) -> 0 | CQ50: =ROUND((ROUND((AC50*AW50*1),2)*BC50),2) -> 104.99 | CR50: =(ROUND((ROUND((((ET50*1.05))*AV50*1),2)*BB50),2)+ROUND((ROUND(((AE50-((EU50*1.05)))*AV50*1),2)*BS50),2)) -> 0 | CS50: =ROUND((ROUND((AE50*AV50*1),2)*BS50),2) -> 0 | CT50: =ROUND((ROUND((AF50*AV50*1),2)*BA50),2) -> 0 | CU50: =AG50 -> 0 | CV50: =(AH50*AV50) -> 0 | CW50: =AI50 -> 0 | CX50: =AJ50 -> 0 | CY50: =((S50*BZ50)/100) -> 0 | CZ50: =((S50*CA50)/100) -> 0 | DB50: 23 | DE50: *1,05 | DF50: *1,05 | DG50: *1,05 | DI50: *1,05 | DJ50: *1,05 | DN50: 0 | DO50: 0 | DP50: 1 | DQ50: 1 | DU50: 1007 | DV50: м3 | DW50: м3 | DX50: 1 | EE50: 51697656 | EF50: 200 | EG50: Материалы строительные | EH50: 0 | EJ50: 1 | EK50: 1617 | EL50: ТСН-2001.1 Материалы строительные | EM50: ТСН-2001.1-1 | EO50: Поправка: О.П. п.3.4.30.г | EQ50: 131072 | ER50: 104.99 | ES50: 104.99 | ET50: 0 | EU50: 0 | EV50: 0 | EW50: 0 | EX50: 0 | EY50: 0 | FQ50: 0 | FR50: 0 | FS50: 0 | FX50: 0 | FY50: 0 | GD50: 0 | GF50: -449487181 | GG50: 2 | GH50: 1 | GI50: -2 | GJ50: 0 | GK50: =ROUND(R50*(R12)/100,2) -> 0 | GL50: =ROUND(IF(AND(BH50=3,BI50=3,FS50<>0),P50,0),2) -> 0 | GM50: =ROUND(O50+X50+Y50+GK50,2)+GX50 -> 0 | GN50: =IF(OR(BI50=0,BI50=1),GM50-GX50,0) -> 0 | GO50: =IF(BI50=2,GM50-GX50,0) -> 0 | GP50: =IF(BI50=4,GM50-GX50,0) -> 0 | GR50: 0 | GS50: 0 | GT50: 0 | GV50: =ROUND((GT50),6) -> 0 | GW50: 1 | GX50: =ROUND(HC50*I50,2) -> 0 | HA50: 0 | HB50: 0 | HC50: =GV50*GW50 -> 0 | HS50: 0 | IK50: 0
A51: 17 | B51: 1 | E51: 12 | F51: 1.1-1-766 | G51: Песок для строительных работ, рядовой (карьерный) | H51: м3 | I51: 0 | J51: 0 | K51: 0 | O51: =ROUND(CP51,2) -> 0 | P51: =ROUND((ROUND((AC51*AW51*I51),2)*BC51),2) -> 0 | Q51: =(ROUND((ROUND((((ET51*1.05))*AV51*I51),2)*BB51),2)+ROUND((ROUND(((AE51-((EU51*1.05)))*AV51*I51),2)*BS51),2)) -> 0 | R51: =ROUND((ROUND((AE51*AV51*I51),2)*BS51),2) -> 0 | S51: =ROUND((ROUND((AF51*AV51*I51),2)*BA51),2) -> 0 | T51: =ROUND(CU51*I51,2) -> 0 | U51: =CV51*I51 -> 0 | V51: =CW51*I51 -> 0 | W51: =ROUND(CX51*I51,2) -> 0 | X51: =ROUND(CY51,2) -> 0 | Y51: =ROUND(CZ51,2) -> 0 | AA51: 56610029 | AB51: =ROUND((AC51+AD51+AF51),6) -> 104.99 | AC51: =ROUND((ES51),6) -> 104.99 | AD51: =ROUND(((((ET51*1.05))-((EU51*1.05)))+AE51),6) -> 0 | AE51: =ROUND(((EU51*1.05)),6) -> 0 | AF51: =ROUND(((EV51*1.05)),6) -> 0 | AG51: =ROUND((AP51),6) -> 0 | AH51: =((EW51*1.05)) -> 0 | AI51: =((EX51*1.05)) -> 0 | AJ51: =(AS51) -> 0 | AK51: 104.99 | AL51: 104.99 | AM51: 0 | AN51: 0 | AO51: 0 | AP51: 0 | AQ51: 0 | AR51: 0 | AS51: 0 | AT51: 0 | AU51: 0 | AV51: 1 | AW51: 1 | AZ51: 1 | BA51: 1 | BB51: 1 | BC51: 7.69 | BH51: 3 | BI51: 1 | BJ51: ТСН-2001.1 Доп. 69, Р. 1, о. 1, поз. 766 | BM51: 1617 | BN51: 0 | BO51: 1.1-1-766 | BP51: 1 | BQ51: 200 | BR51: 0 | BS51: 1 | BT51: 1 | BU51: 1 | BV51: 1 | BW51: 1 | BX51: 1 | BZ51: 0 | CA51: 0 | CE51: 30 | CF51: 0 | CG51: 0 | CM51: 0 | CN51: Поправка: О.П. п.3.4.30.г Наименование: В отношении объектов, реализуемых с привлечением средств бюджета города Москвы, затраты, учитывающие усложненные условия производства работ (стесненность, сложность складирования и транспортной логистики, наличие в зоне производства работ действующего технологического оборудования или движения технологического транспорта и т.п.), определяются заказчиком в задании на проектирование при составлении локальных сметных расчетов (смет): для объектов города Москвы, расположенных за пределами Московской кольцевой автомобильной дороги | CO51: 0 | CP51: =(P51+Q51+S51) -> 0 | CQ51: =ROUND((ROUND((AC51*AW51*1),2)*BC51),2) -> 807.37 | CR51: =(ROUND((ROUND((((ET51*1.05))*AV51*1),2)*BB51),2)+ROUND((ROUND(((AE51-((EU51*1.05)))*AV51*1),2)*BS51),2)) -> 0 | CS51: =ROUND((ROUND((AE51*AV51*1),2)*BS51),2) -> 0 | CT51: =ROUND((ROUND((AF51*AV51*1),2)*BA51),2) -> 0 | CU51: =AG51 -> 0 | CV51: =(AH51*AV51) -> 0 | CW51: =AI51 -> 0 | CX51: =AJ51 -> 0 | CY51: =S51*(BZ51/100) -> 0 | CZ51: =S51*(CA51/100) -> 0 | DB51: 24 | DE51: *1,05 | DF51: *1,05 | DG51: *1,05 | DI51: *1,05 | DJ51: *1,05 | DN51: 0 | DO51: 0 | DP51: 1 | DQ51: 1 | DU51: 1007 | DV51: м3 | DW51: м3 | DX51: 1 | EE51: 51697656 | EF51: 200 | EG51: Материалы строительные | EH51: 0 | EJ51: 1 | EK51: 1617 | EL51: ТСН-2001.1 Материалы строительные | EM51: ТСН-2001.1-1 | EO51: Поправка: О.П. п.3.4.30.г | EQ51: 131072 | ER51: 104.99 | ES51: 104.99 | ET51: 0 | EU51: 0 | EV51: 0 | EW51: 0 | EX51: 0 | EY51: 0 | FQ51: 0 | FR51: 0 | FS51: 0 | FX51: 0 | FY51: 0 | GD51: 0 | GF51: -449487181 | GG51: 2 | GH51: 1 | GI51: 2 | GJ51: 0 | GK51: =ROUND(R51*(S12)/100,2) -> 0 | GL51: =ROUND(IF(AND(BH51=3,BI51=3,FS51<>0),P51,0),2) -> 0 | GM51: =ROUND(O51+X51+Y51+GK51,2)+GX51 -> 0 | GN51: =IF(OR(BI51=0,BI51=1),GM51-GX51,0) -> 0 | GO51: =IF(BI51=2,GM51-GX51,0) -> 0 | GP51: =IF(BI51=4,GM51-GX51,0) -> 0 | GR51: 0 | GS51: 3 | GT51: 0 | GV51: =ROUND((GT51),6) -> 0 | GW51: 1 | GX51: =ROUND(HC51*I51,2) -> 0 | HA51: 0 | HB51: 0 | HC51: =GV51*GW51 -> 0 | HS51: 0 | IK51: 0
A52: 17 | B52: 1 | E52: 13 | F52: 1.12-3-62 | G52: Заглушка (пробка) полиэтиленовая для каналов кабельной канализации из хризотилцементных труб внутренним диаметром 150 мм | H52: шт. | I52: 0 | J52: 0 | K52: 0 | O52: =ROUND(CP52,2) -> 0 | P52: =ROUND((ROUND((AC52*AW52*I52),2)*BC52),2) -> 0 | Q52: =(ROUND((ROUND((((ET52*1.05))*AV52*I52),2)*BB52),2)+ROUND((ROUND(((AE52-((EU52*1.05)))*AV52*I52),2)*BS52),2)) -> 0 | R52: =ROUND((ROUND((AE52*AV52*I52),2)*BS52),2) -> 0 | S52: =ROUND((ROUND((AF52*AV52*I52),2)*BA52),2) -> 0 | T52: =ROUND(CU52*I52,2) -> 0 | U52: =CV52*I52 -> 0 | V52: =CW52*I52 -> 0 | W52: =ROUND(CX52*I52,2) -> 0 | X52: =ROUND(CY52,2) -> 0 | Y52: =ROUND(CZ52,2) -> 0 | AA52: 56622490 | AB52: =ROUND((AC52+AD52+AF52),6) -> 3.9 | AC52: =ROUND((ES52),6) -> 3.9 | AD52: =ROUND(((((ET52*1.05))-((EU52*1.05)))+AE52),6) -> 0 | AE52: =ROUND(((EU52*1.05)),6) -> 0 | AF52: =ROUND(((EV52*1.05)),6) -> 0 | AG52: =ROUND((AP52),6) -> 0 | AH52: =((EW52*1.05)) -> 0 | AI52: =((EX52*1.05)) -> 0 | AJ52: =(AS52) -> 0 | AK52: 3.9 | AL52: 3.9 | AM52: 0 | AN52: 0 | AO52: 0 | AP52: 0 | AQ52: 0 | AR52: 0 | AS52: 0 | AT52: 0 | AU52: 0 | AV52: 1 | AW52: 1 | AZ52: 1 | BA52: 1 | BB52: 1 | BC52: 1 | BH52: 3 | BI52: 1 | BJ52: ТСН-2001.1 Доп. 70, Р. 12, о. 3, поз. 62 | BM52: 1617 | BN52: 0 | BP52: 0 | BQ52: 200 | BR52: 0 | BS52: 1 | BT52: 1 | BU52: 1 | BV52: 1 | BW52: 1 | BX52: 1 | BZ52: 0 | CA52: 0 | CE52: 30 | CF52: 0 | CG52: 0 | CM52: 0 | CN52: Поправка: О.П. п.3.4.30.г Наименование: В отношении объектов, реализуемых с привлечением средств бюджета города Москвы, затраты, учитывающие усложненные условия производства работ (стесненность, сложность складирования и транспортной логистики, наличие в зоне производства работ действующего технологического оборудования или движения технологического транспорта и т.п.), определяются заказчиком в задании на проектирование при составлении локальных сметных расчетов (смет): для объектов города Москвы, расположенных за пределами Московской кольцевой автомобильной дороги | CO52: 0 | CP52: =(P52+Q52+S52) -> 0 | CQ52: =ROUND((ROUND((AC52*AW52*1),2)*BC52),2) -> 3.9 | CR52: =(ROUND((ROUND((((ET52*1.05))*AV52*1),2)*BB52),2)+ROUND((ROUND(((AE52-((EU52*1.05)))*AV52*1),2)*BS52),2)) -> 0 | CS52: =ROUND((ROUND((AE52*AV52*1),2)*BS52),2) -> 0 | CT52: =ROUND((ROUND((AF52*AV52*1),2)*BA52),2) -> 0 | CU52: =AG52 -> 0 | CV52: =(AH52*AV52) -> 0 | CW52: =AI52 -> 0 | CX52: =AJ52 -> 0 | CY52: =((S52*BZ52)/100) -> 0 | CZ52: =((S52*CA52)/100) -> 0 | DB52: 25 | DE52: *1,05 | DF52: *1,05 | DG52: *1,05 | DI52: *1,05 | DJ52: *1,05 | DN52: 0 | DO52: 0 | DP52: 1 | DQ52: 1 | DU52: 1010 | DV52: шт. | DW52: шт. | DX52: 1 | EE52: 51697656 | EF52: 200 | EG52: Материалы строительные | EH52: 0 | EJ52: 1 | EK52: 1617 | EL52: ТСН-2001.1 Материалы строительные | EM52: ТСН-2001.1-1 | EO52: Поправка: О.П. п.3.4.30.г | EQ52: 131072 | ER52: 3.9 | ES52: 3.9 | ET52: 0 | EU52: 0 | EV52: 0 | EW52: 0 | EX52: 0 | EY52: 0 | FQ52: 0 | FR52: 0 | FS52: 0 | FX52: 0 | FY52: 0 | GD52: 0 | GF52: 2014984288 | GG52: 2 | GH52: 1 | GI52: -2 | GJ52: 0 | GK52: =ROUND(R52*(R12)/100,2) -> 0 | GL52: =ROUND(IF(AND(BH52=3,BI52=3,FS52<>0),P52,0),2) -> 0 | GM52: =ROUND(O52+X52+Y52+GK52,2)+GX52 -> 0 | GN52: =IF(OR(BI52=0,BI52=1),GM52-GX52,0) -> 0 | GO52: =IF(BI52=2,GM52-GX52,0) -> 0 | GP52: =IF(BI52=4,GM52-GX52,0) -> 0 | GR52: 0 | GS52: 0 | GT52: 0 | GV52: =ROUND((GT52),6) -> 0 | GW52: 1 | GX52: =ROUND(HC52*I52,2) -> 0 | HA52: 0 | HB52: 0 | HC52: =GV52*GW52 -> 0 | HS52: 0 | IK52: 0
A53: 17 | B53: 1 | E53: 13 | F53: 1.12-3-62 | G53: Заглушка (пробка) полиэтиленовая для каналов кабельной канализации из хризотилцементных труб внутренним диаметром 150 мм | H53: шт. | I53: 0 | J53: 0 | K53: 0 | O53: =ROUND(CP53,2) -> 0 | P53: =ROUND((ROUND((AC53*AW53*I53),2)*BC53),2) -> 0 | Q53: =(ROUND((ROUND((((ET53*1.05))*AV53*I53),2)*BB53),2)+ROUND((ROUND(((AE53-((EU53*1.05)))*AV53*I53),2)*BS53),2)) -> 0 | R53: =ROUND((ROUND((AE53*AV53*I53),2)*BS53),2) -> 0 | S53: =ROUND((ROUND((AF53*AV53*I53),2)*BA53),2) -> 0 | T53: =ROUND(CU53*I53,2) -> 0 | U53: =CV53*I53 -> 0 | V53: =CW53*I53 -> 0 | W53: =ROUND(CX53*I53,2) -> 0 | X53: =ROUND(CY53,2) -> 0 | Y53: =ROUND(CZ53,2) -> 0 | AA53: 56610029 | AB53: =ROUND((AC53+AD53+AF53),6) -> 3.9 | AC53: =ROUND((ES53),6) -> 3.9 | AD53: =ROUND(((((ET53*1.05))-((EU53*1.05)))+AE53),6) -> 0 | AE53: =ROUND(((EU53*1.05)),6) -> 0 | AF53: =ROUND(((EV53*1.05)),6) -> 0 | AG53: =ROUND((AP53),6) -> 0 | AH53: =((EW53*1.05)) -> 0 | AI53: =((EX53*1.05)) -> 0 | AJ53: =(AS53) -> 0 | AK53: 3.9 | AL53: 3.9 | AM53: 0 | AN53: 0 | AO53: 0 | AP53: 0 | AQ53: 0 | AR53: 0 | AS53: 0 | AT53: 0 | AU53: 0 | AV53: 1 | AW53: 1 | AZ53: 1 | BA53: 1 | BB53: 1 | BC53: 13.93 | BH53: 3 | BI53: 1 | BJ53: ТСН-2001.1 Доп. 70, Р. 12, о. 3, поз. 62 | BM53: 1617 | BN53: 0 | BO53: 1.12-3-62 | BP53: 1 | BQ53: 200 | BR53: 0 | BS53: 1 | BT53: 1 | BU53: 1 | BV53: 1 | BW53: 1 | BX53: 1 | BZ53: 0 | CA53: 0 | CE53: 30 | CF53: 0 | CG53: 0 | CM53: 0 | CN53: Поправка: О.П. п.3.4.30.г Наименование: В отношении объектов, реализуемых с привлечением средств бюджета города Москвы, затраты, учитывающие усложненные условия производства работ (стесненность, сложность складирования и транспортной логистики, наличие в зоне производства работ действующего технологического оборудования или движения технологического транспорта и т.п.), определяются заказчиком в задании на проектирование при составлении локальных сметных расчетов (смет): для объектов города Москвы, расположенных за пределами Московской кольцевой автомобильной дороги | CO53: 0 | CP53: =(P53+Q53+S53) -> 0 | CQ53: =ROUND((ROUND((AC53*AW53*1),2)*BC53),2) -> 54.33 | CR53: =(ROUND((ROUND((((ET53*1.05))*AV53*1),2)*BB53),2)+ROUND((ROUND(((AE53-((EU53*1.05)))*AV53*1),2)*BS53),2)) -> 0 | CS53: =ROUND((ROUND((AE53*AV53*1),2)*BS53),2) -> 0 | CT53: =ROUND((ROUND((AF53*AV53*1),2)*BA53),2) -> 0 | CU53: =AG53 -> 0 | CV53: =(AH53*AV53) -> 0 | CW53: =AI53 -> 0 | CX53: =AJ53 -> 0 | CY53: =S53*(BZ53/100) -> 0 | CZ53: =S53*(CA53/100) -> 0 | DB53: 26 | DE53: *1,05 | DF53: *1,05 | DG53: *1,05 | DI53: *1,05 | DJ53: *1,05 | DN53: 0 | DO53: 0 | DP53: 1 | DQ53: 1 | DU53: 1010 | DV53: шт. | DW53: шт. | DX53: 1 | EE53: 51697656 | EF53: 200 | EG53: Материалы строительные | EH53: 0 | EJ53: 1 | EK53: 1617 | EL53: ТСН-2001.1 Материалы строительные | EM53: ТСН-2001.1-1 | EO53: Поправка: О.П. п.3.4.30.г | EQ53: 131072 | ER53: 3.9 | ES53: 3.9 | ET53: 0 | EU53: 0 | EV53: 0 | EW53: 0 | EX53: 0 | EY53: 0 | FQ53: 0 | FR53: 0 | FS53: 0 | FX53: 0 | FY53: 0 | GD53: 0 | GF53: 2014984288 | GG53: 2 | GH53: 1 | GI53: 2 | GJ53: 0 | GK53: =ROUND(R53*(S12)/100,2) -> 0 | GL53: =ROUND(IF(AND(BH53=3,BI53=3,FS53<>0),P53,0),2) -> 0 | GM53: =ROUND(O53+X53+Y53+GK53,2)+GX53 -> 0 | GN53: =IF(OR(BI53=0,BI53=1),GM53-GX53,0) -> 0 | GO53: =IF(BI53=2,GM53-GX53,0) -> 0 | GP53: =IF(BI53=4,GM53-GX53,0) -> 0 | GR53: 0 | GS53: 3 | GT53: 0 | GV53: =ROUND((GT53),6) -> 0 | GW53: 1 | GX53: =ROUND(HC53*I53,2) -> 0 | HA53: 0 | HB53: 0 | HC53: =GV53*GW53 -> 0 | HS53: 0 | IK53: 0
A54: 17 | B54: 1 | D54: =ROW(EtalonRes!A57) -> 57 | E54: 14 | F54: 3.13-30-1 | G54: Огнезащитное покрытие терморасширяющимися составами электрических кабелей с применением окрасочного безвоздушного агрегата | H54: 100 м2 покрытия | I54: 0 | J54: 0 | K54: 0 | O54: =ROUND(CP54,2) -> 0 | P54: =ROUND((ROUND((AC54*AW54*I54),2)*BC54),2) -> 0 | Q54: =(ROUND((ROUND((((ET54*1.05))*AV54*I54),2)*BB54),2)+ROUND((ROUND(((AE54-((EU54*1.05)))*AV54*I54),2)*BS54),2)) -> 0 | R54: =ROUND((ROUND((AE54*AV54*I54),2)*BS54),2) -> 0 | S54: =ROUND((ROUND((AF54*AV54*I54),2)*BA54),2) -> 0 | T54: =ROUND(CU54*I54,2) -> 0 | U54: =CV54*I54 -> 0 | V54: =CW54*I54 -> 0 | W54: =ROUND(CX54*I54,2) -> 0 | X54: =ROUND(CY54,2) -> 0 | Y54: =ROUND(CZ54,2) -> 0 | AA54: 56622490 | AB54: =ROUND((AC54+AD54+AF54),6) -> 2963.477 | AC54: =ROUND((ES54),6) -> 516.41 | AD54: =ROUND(((((ET54*1.05))-((EU54*1.05)))+AE54),6) -> 419.6115 | AE54: =ROUND(((EU54*1.05)),6) -> 0.6195 | AF54: =ROUND(((EV54*1.05)),6) -> 2027.4555 | AG54: =ROUND((AP54),6) -> 0 | AH54: =((EW54*1.05)) -> 141.75 | AI54: =((EX54*1.05)) -> 0 | AJ54: =(AS54) -> 0 | AK54: 2846.95 | AL54: 516.41 | AM54: 399.63 | AN54: 0.59 | AO54: 1930.91 | AP54: 0 | AQ54: 135 | AR54: 0 | AS54: 0 | AT54: 105 | AU54: 77 | AV54: 1.047 | AW54: 1 | AZ54: 1 | BA54: 1 | BB54: 1 | BC54: 1 | BH54: 0 | BI54: 1 | BJ54: ТСН-2001.3 Доп. 71, Сб. 13, т. 30, поз. 1 | BM54: 99 | BN54: 0 | BP54: 0 | BQ54: 30 | BR54: 0 | BS54: 1 | BT54: 1 | BU54: 1 | BV54: 1 | BW54: 1 | BX54: 1 | BZ54: 105 | CA54: 77 | CE54: 30 | CF54: 0 | CG54: 0 | CM54: 0 | CN54: Поправка: О.П. п.3.4.30.г Наименование: В отношении объектов, реализуемых с привлечением средств бюджета города Москвы, затраты, учитывающие усложненные условия производства работ (стесненность, сложность складирования и транспортной логистики, наличие в зоне производства работ действующего технологического оборудования или движения технологического транспорта и т.п.), определяются заказчиком в задании на проектирование при составлении локальных сметных расчетов (смет): для объектов города Москвы, расположенных за пределами Московской кольцевой автомобильной дороги | CO54: 0 | CP54: =(P54+Q54+S54) -> 0 | CQ54: =ROUND((ROUND((AC54*AW54*1),2)*BC54),2) -> 516.41 | CR54: =(ROUND((ROUND((((ET54*1.05))*AV54*1),2)*BB54),2)+ROUND((ROUND(((AE54-((EU54*1.05)))*AV54*1),2)*BS54),2)) -> 439.33 | CS54: =ROUND((ROUND((AE54*AV54*1),2)*BS54),2) -> 0.65 | CT54: =ROUND((ROUND((AF54*AV54*1),2)*BA54),2) -> 2122.75 | CU54: =AG54 -> 0 | CV54: =(AH54*AV54) -> 148.41225 | CW54: =AI54 -> 0 | CX54: =AJ54 -> 0 | CY54: =((S54*BZ54)/100) -> 0 | CZ54: =((S54*CA54)/100) -> 0 | DB54: 27 | DE54: *1,05 | DF54: *1,05 | DG54: *1,05 | DI54: *1,05 | DJ54: *1,05 | DN54: 0 | DO54: 0 | DP54: 1 | DQ54: 1 | DU54: 1013 | DV54: 100 м2 покрытия | DW54: 100 м2 покрытия | DX54: 1 | EE54: 51696138 | EF54: 30 | EG54: Строительные работы | EH54: 0 | EJ54: 1 | EK54: 99 | EL54: ТСН-2001.3-13. 13-17-6, 13-17-7, 13-18...13-38 | EM54: ТСН-2001.3-13-3 | EO54: Поправка: О.П. п.3.4.30.г | EQ54: 131072 | ER54: 2846.95 | ES54: 516.41 | ET54: 399.63 | EU54: 0.59 | EV54: 1930.91 | EW54: 135 | EX54: 0 | EY54: 0 | FQ54: 0 | FR54: 0 | FS54: 0 | FX54: 105 | FY54: 77 | GD54: 0 | GF54: 448414653 | GG54: 2 | GH54: 1 | GI54: -2 | GJ54: 0 | GK54: =ROUND(R54*(R12)/100,2) -> 0 | GL54: =ROUND(IF(AND(BH54=3,BI54=3,FS54<>0),P54,0),2) -> 0 | GM54: =ROUND(O54+X54+Y54+GK54,2)+GX54 -> 0 | GN54: =IF(OR(BI54=0,BI54=1),GM54-GX54,0) -> 0 | GO54: =IF(BI54=2,GM54-GX54,0) -> 0 | GP54: =IF(BI54=4,GM54-GX54,0) -> 0 | GR54: 0 | GS54: 0 | GT54: 0 | GV54: =ROUND((GT54),6) -> 0 | GW54: 1 | GX54: =ROUND(HC54*I54,2) -> 0 | HA54: 0 | HB54: 0 | HC54: =GV54*GW54 -> 0 | HS54: 0 | IK54: 0
A55: 17 | B55: 1 | D55: =ROW(EtalonRes!A68) -> 68 | E55: 14 | F55: 3.13-30-1 | G55: Огнезащитное покрытие терморасширяющимися составами электрических кабелей с применением окрасочного безвоздушного агрегата | H55: 100 м2 покрытия | I55: 0 | J55: 0 | K55: 0 | O55: =ROUND(CP55,2) -> 0 | P55: =ROUND((ROUND((AC55*AW55*I55),2)*BC55),2) -> 0 | Q55: =(ROUND((ROUND((((ET55*1.05))*AV55*I55),2)*BB55),2)+ROUND((ROUND(((AE55-((EU55*1.05)))*AV55*I55),2)*BS55),2)) -> 0 | R55: =ROUND((ROUND((AE55*AV55*I55),2)*BS55),2) -> 0 | S55: =ROUND((ROUND((AF55*AV55*I55),2)*BA55),2) -> 0 | T55: =ROUND(CU55*I55,2) -> 0 | U55: =CV55*I55 -> 0 | V55: =CW55*I55 -> 0 | W55: =ROUND(CX55*I55,2) -> 0 | X55: =ROUND(CY55,2) -> 0 | Y55: =ROUND(CZ55,2) -> 0 | AA55: 56610029 | AB55: =ROUND((AC55+AD55+AF55),6) -> 2963.477 | AC55: =ROUND((ES55),6) -> 516.41 | AD55: =ROUND(((((ET55*1.05))-((EU55*1.05)))+AE55),6) -> 419.6115 | AE55: =ROUND(((EU55*1.05)),6) -> 0.6195 | AF55: =ROUND(((EV55*1.05)),6) -> 2027.4555 | AG55: =ROUND((AP55),6) -> 0 | AH55: =((EW55*1.05)) -> 141.75 | AI55: =((EX55*1.05)) -> 0 | AJ55: =(AS55) -> 0 | AK55: 2846.95 | AL55: 516.41 | AM55: 399.63 | AN55: 0.59 | AO55: 1930.91 | AP55: 0 | AQ55: 135 | AR55: 0 | AS55: 0 | AT55: 87 | AU55: 41 | AV55: 1.047 | AW55: 1 | AZ55: 1 | BA55: 34.51 | BB55: 9.31 | BC55: 3.33 | BH55: 0 | BI55: 1 | BJ55: ТСН-2001.3 Доп. 71, Сб. 13, т. 30, поз. 1 | BM55: 99 | BN55: 0 | BO55: 3.13-30-1 | BP55: 1 | BQ55: 30 | BR55: 0 | BS55: 34.51 | BT55: 1 | BU55: 1 | BV55: 1 | BW55: 1 | BX55: 1 | BZ55: 87 | CA55: 41 | CE55: 30 | CF55: 0 | CG55: 0 | CM55: 0 | CN55: Поправка: О.П. п.3.4.30.г Наименование: В отношении объектов, реализуемых с привлечением средств бюджета города Москвы, затраты, учитывающие усложненные условия производства работ (стесненность, сложность складирования и транспортной логистики, наличие в зоне производства работ действующего технологического оборудования или движения технологического транспорта и т.п.), определяются заказчиком в задании на проектирование при составлении локальных сметных расчетов (смет): для объектов города Москвы, расположенных за пределами Московской кольцевой автомобильной дороги | CO55: 0 | CP55: =(P55+Q55+S55) -> 0 | CQ55: =ROUND((ROUND((AC55*AW55*1),2)*BC55),2) -> 1719.65 | CR55: =(ROUND((ROUND((((ET55*1.05))*AV55*1),2)*BB55),2)+ROUND((ROUND(((AE55-((EU55*1.05)))*AV55*1),2)*BS55),2)) -> 4090.16 | CS55: =ROUND((ROUND((AE55*AV55*1),2)*BS55),2) -> 22.43 | CT55: =ROUND((ROUND((AF55*AV55*1),2)*BA55),2) -> 73256.1 | CU55: =AG55 -> 0 | CV55: =(AH55*AV55) -> 148.41225 | CW55: =AI55 -> 0 | CX55: =AJ55 -> 0 | CY55: =S55*(BZ55/100) -> 0 | CZ55: =S55*(CA55/100) -> 0 | DB55: 28 | DE55: *1,05 | DF55: *1,05 | DG55: *1,05 | DI55: *1,05 | DJ55: *1,05 | DN55: 105 | DO55: 77 | DP55: 1.047 | DQ55: 1 | DU55: 1013 | DV55: 100 м2 покрытия | DW55: 100 м2 покрытия | DX55: 1 | EE55: 51696138 | EF55: 30 | EG55: Строительные работы | EH55: 0 | EJ55: 1 | EK55: 99 | EL55: ТСН-2001.3-13. 13-17-6, 13-17-7, 13-18...13-38 | EM55: ТСН-2001.3-13-3 | EO55: Поправка: О.П. п.3.4.30.г | EQ55: 131072 | ER55: 2846.95 | ES55: 516.41 | ET55: 399.63 | EU55: 0.59 | EV55: 1930.91 | EW55: 135 | EX55: 0 | EY55: 0 | FQ55: 0 | FR55: 0 | FS55: 0 | FX55: 105 | FY55: 77 | GD55: 0 | GF55: 448414653 | GG55: 2 | GH55: 1 | GI55: 2 | GJ55: 0 | GK55: =ROUND(R55*(S12)/100,2) -> 0 | GL55: =ROUND(IF(AND(BH55=3,BI55=3,FS55<>0),P55,0),2) -> 0 | GM55: =ROUND(O55+X55+Y55+GK55,2)+GX55 -> 0 | GN55: =IF(OR(BI55=0,BI55=1),GM55-GX55,0) -> 0 | GO55: =IF(BI55=2,GM55-GX55,0) -> 0 | GP55: =IF(BI55=4,GM55-GX55,0) -> 0 | GR55: 0 | GS55: 3 | GT55: 0 | GV55: =ROUND((GT55),6) -> 0 | GW55: 1 | GX55: =ROUND(HC55*I55,2) -> 0 | HA55: 0 | HB55: 0 | HC55: =GV55*GW55 -> 0 | HS55: 0 | IK55: 0
A56: 17 | B56: 1 | E56: 15 | F56: КП | G56: Огнезащитный состав СТАБИТЕРМ-225 3кп | H56: кг | I56: =ROUND(I54*1.36*100,9) -> 0 | J56: 0 | K56: =ROUND(I54*1.36*100,9) -> 0 | O56: =ROUND(CP56,2) -> 0 | P56: =ROUND((ROUND((AC56*AW56*I56),2)*BC56),2) -> 0 | Q56: =(ROUND((ROUND((((ET56*1.05))*AV56*I56),2)*BB56),2)+ROUND((ROUND(((AE56-((EU56*1.05)))*AV56*I56),2)*BS56),2)) -> 0 | R56: =ROUND((ROUND((AE56*AV56*I56),2)*BS56),2) -> 0 | S56: =ROUND((ROUND((AF56*AV56*I56),2)*BA56),2) -> 0 | T56: =ROUND(CU56*I56,2) -> 0 | U56: =CV56*I56 -> 0 | V56: =CW56*I56 -> 0 | W56: =ROUND(CX56*I56,2) -> 0 | X56: =ROUND(CY56,2) -> 0 | Y56: =ROUND(CZ56,2) -> 0 | AA56: 56622490 | AB56: =ROUND((AC56+AD56+AF56),6) -> 504.9 | AC56: =ROUND((ES56),6) -> 504.9 | AD56: =ROUND(((((ET56*1.05))-((EU56*1.05)))+AE56),6) -> 0 | AE56: =ROUND(((EU56*1.05)),6) -> 0 | AF56: =ROUND(((EV56*1.05)),6) -> 0 | AG56: =ROUND((AP56),6) -> 0 | AH56: =((EW56*1.05)) -> 0 | AI56: =((EX56*1.05)) -> 0 | AJ56: =(AS56) -> 0 | AK56: 504.9 | AL56: 504.9 | AM56: 0 | AN56: 0 | AO56: 0 | AP56: 0 | AQ56: 0 | AR56: 0 | AS56: 0 | AT56: 0 | AU56: 0 | AV56: 1 | AW56: 1 | AZ56: 1 | BA56: 1 | BB56: 1 | BC56: 1 | BH56: 3 | BI56: 1 | BM56: 1617 | BN56: 0 | BP56: 0 | BQ56: 200 | BR56: 0 | BS56: 1 | BT56: 1 | BU56: 1 | BV56: 1 | BW56: 1 | BX56: 1 | BZ56: 0 | CA56: 0 | CE56: 30 | CF56: 0 | CG56: 0 | CM56: 0 | CN56: Поправка: О.П. п.3.4.30.г Наименование: В отношении объектов, реализуемых с привлечением средств бюджета города Москвы, затраты, учитывающие усложненные условия производства работ (стесненность, сложность складирования и транспортной логистики, наличие в зоне производства работ действующего технологического оборудования или движения технологического транспорта и т.п.), определяются заказчиком в задании на проектирование при составлении локальных сметных расчетов (смет): для объектов города Москвы, расположенных за пределами Московской кольцевой автомобильной дороги | CO56: 0 | CP56: =(P56+Q56+S56) -> 0 | CQ56: =ROUND((ROUND((AC56*AW56*1),2)*BC56),2) -> 504.9 | CR56: =(ROUND((ROUND((((ET56*1.05))*AV56*1),2)*BB56),2)+ROUND((ROUND(((AE56-((EU56*1.05)))*AV56*1),2)*BS56),2)) -> 0 | CS56: =ROUND((ROUND((AE56*AV56*1),2)*BS56),2) -> 0 | CT56: =ROUND((ROUND((AF56*AV56*1),2)*BA56),2) -> 0 | CU56: =AG56 -> 0 | CV56: =(AH56*AV56) -> 0 | CW56: =AI56 -> 0 | CX56: =AJ56 -> 0 | CY56: =((S56*BZ56)/100) -> 0 | CZ56: =((S56*CA56)/100) -> 0 | DB56: 29 | DE56: *1,05 | DF56: *1,05 | DG56: *1,05 | DI56: *1,05 | DJ56: *1,05 | DN56: 0 | DO56: 0 | DP56: 1 | DQ56: 1 | DU56: 1009 | DV56: кг | DW56: кг | DX56: 1 | EE56: 51697656 | EF56: 200 | EG56: Материалы строительные | EH56: 0 | EJ56: 1 | EK56: 1617 | EL56: ТСН-2001.1 Материалы строительные | EM56: ТСН-2001.1-1 | EO56: Поправка: О.П. п.3.4.30.г | EQ56: 131072 | ER56: 52.75 | ES56: 504.9 | ET56: 0 | EU56: 0 | EV56: 0 | EW56: 0 | EX56: 0 | EY56: 0 | FQ56: 0 | FR56: 0 | FS56: 0 | FX56: 0 | FY56: 0 | GA56: [594 / 1,2] + 2% Трансп | GD56: 0 | GF56: -1921076346 | GG56: 2 | GH56: 4 | GI56: 3 | GJ56: 0 | GK56: =ROUND(R56*(R12)/100,2) -> 0 | GL56: =ROUND(IF(AND(BH56=3,BI56=3,FS56<>0),P56,0),2) -> 0 | GM56: =ROUND(O56+X56+Y56+GK56,2)+GX56 -> 0 | GN56: =IF(OR(BI56=0,BI56=1),GM56-GX56,0) -> 0 | GO56: =IF(BI56=2,GM56-GX56,0) -> 0 | GP56: =IF(BI56=4,GM56-GX56,0) -> 0 | GR56: 0 | GS56: 2 | GT56: 0 | GV56: =ROUND((GT56),6) -> 0 | GW56: 1 | GX56: =ROUND(HC56*I56,2) -> 0 | HA56: 0 | HB56: 0 | HC56: =GV56*GW56 -> 0 | HE56: 2 | HF56: 0 | HS56: 0 | IK56: 0
A57: 17 | B57: 1 | E57: 15 | F57: КП | G57: Огнезащитный состав СТАБИТЕРМ-225 3кп | H57: кг | I57: =ROUND(I55*1.36*100,9) -> 0 | J57: 0 | K57: =ROUND(I55*1.36*100,9) -> 0 | O57: =ROUND(CP57,2) -> 0 | P57: =ROUND((ROUND((AC57*AW57*I57),2)*BC57),2) -> 0 | Q57: =(ROUND((ROUND((((ET57*1.05))*AV57*I57),2)*BB57),2)+ROUND((ROUND(((AE57-((EU57*1.05)))*AV57*I57),2)*BS57),2)) -> 0 | R57: =ROUND((ROUND((AE57*AV57*I57),2)*BS57),2) -> 0 | S57: =ROUND((ROUND((AF57*AV57*I57),2)*BA57),2) -> 0 | T57: =ROUND(CU57*I57,2) -> 0 | U57: =CV57*I57 -> 0 | V57: =CW57*I57 -> 0 | W57: =ROUND(CX57*I57,2) -> 0 | X57: =ROUND(CY57,2) -> 0 | Y57: =ROUND(CZ57,2) -> 0 | AA57: 56610029 | AB57: =ROUND((AC57+AD57+AF57),6) -> 504.9 | AC57: =ROUND((ES57),6) -> 504.9 | AD57: =ROUND(((((ET57*1.05))-((EU57*1.05)))+AE57),6) -> 0 | AE57: =ROUND(((EU57*1.05)),6) -> 0 | AF57: =ROUND(((EV57*1.05)),6) -> 0 | AG57: =ROUND((AP57),6) -> 0 | AH57: =((EW57*1.05)) -> 0 | AI57: =((EX57*1.05)) -> 0 | AJ57: =(AS57) -> 0 | AK57: 504.9 | AL57: 504.9 | AM57: 0 | AN57: 0 | AO57: 0 | AP57: 0 | AQ57: 0 | AR57: 0 | AS57: 0 | AT57: 0 | AU57: 0 | AV57: 1 | AW57: 1 | AZ57: 1 | BA57: 1 | BB57: 1 | BC57: 1 | BH57: 3 | BI57: 1 | BM57: 1617 | BN57: 0 | BP57: 0 | BQ57: 200 | BR57: 0 | BS57: 1 | BT57: 1 | BU57: 1 | BV57: 1 | BW57: 1 | BX57: 1 | BZ57: 0 | CA57: 0 | CE57: 30 | CF57: 0 | CG57: 0 | CM57: 0 | CN57: Поправка: О.П. п.3.4.30.г Наименование: В отношении объектов, реализуемых с привлечением средств бюджета города Москвы, затраты, учитывающие усложненные условия производства работ (стесненность, сложность складирования и транспортной логистики, наличие в зоне производства работ действующего технологического оборудования или движения технологического транспорта и т.п.), определяются заказчиком в задании на проектирование при составлении локальных сметных расчетов (смет): для объектов города Москвы, расположенных за пределами Московской кольцевой автомобильной дороги | CO57: 0 | CP57: =(P57+Q57+S57) -> 0 | CQ57: =ROUND((ROUND((AC57*AW57*1),2)*BC57),2) -> 504.9 | CR57: =(ROUND((ROUND((((ET57*1.05))*AV57*1),2)*BB57),2)+ROUND((ROUND(((AE57-((EU57*1.05)))*AV57*1),2)*BS57),2)) -> 0 | CS57: =ROUND((ROUND((AE57*AV57*1),2)*BS57),2) -> 0 | CT57: =ROUND((ROUND((AF57*AV57*1),2)*BA57),2) -> 0 | CU57: =AG57 -> 0 | CV57: =(AH57*AV57) -> 0 | CW57: =AI57 -> 0 | CX57: =AJ57 -> 0 | CY57: =S57*(BZ57/100) -> 0 | CZ57: =S57*(CA57/100) -> 0 | DB57: 30 | DE57: *1,05 | DF57: *1,05 | DG57: *1,05 | DI57: *1,05 | DJ57: *1,05 | DN57: 0 | DO57: 0 | DP57: 1 | DQ57: 1 | DU57: 1009 | DV57: кг | DW57: кг | DX57: 1 | EE57: 51697656 | EF57: 200 | EG57: Материалы строительные | EH57: 0 | EJ57: 1 | EK57: 1617 | EL57: ТСН-2001.1 Материалы строительные | EM57: ТСН-2001.1-1 | EO57: Поправка: О.П. п.3.4.30.г | EQ57: 131072 | ER57: 52.75 | ES57: 504.9 | ET57: 0 | EU57: 0 | EV57: 0 | EW57: 0 | EX57: 0 | EY57: 0 | EZ57: 5 | FC57: 1 | FD57: 18 | FF57: 594 | FQ57: 0 | FR57: 0 | FS57: 0 | FX57: 0 | FY57: 0 | GA57: [594 / 1,2] + 2% Трансп | GD57: 0 | GF57: -1921076346 | GG57: 2 | GH57: 3 | GI57: -2 | GJ57: 0 | GK57: =ROUND(R57*(S12)/100,2) -> 0 | GL57: =ROUND(IF(AND(BH57=3,BI57=3,FS57<>0),P57,0),2) -> 0 | GM57: =ROUND(O57+X57+Y57+GK57,2)+GX57 -> 0 | GN57: =IF(OR(BI57=0,BI57=1),GM57-GX57,0) -> 0 | GO57: =IF(BI57=2,GM57-GX57,0) -> 0 | GP57: =IF(BI57=4,GM57-GX57,0) -> 0 | GR57: 1 | GS57: 1 | GT57: 0 | GV57: =ROUND((GT57),6) -> 0 | GW57: 1 | GX57: =ROUND(HC57*I57,2) -> 0 | HA57: 0 | HB57: 0 | HC57: =GV57*GW57 -> 0 | HE57: 2 | HF57: 0 | HS57: 0 | IK57: 0
A59: 51 | B59: =B24 -> 1 | C59: =A24 -> 4 | D59: =ROW(A24) -> 24 | F59: =IF(F24<>"",F24,"") -> Новый раздел | G59: =IF(G24<>"",G24,"") -> Земляные работы | H59: 0 | O59: =ROUND(AB59,2) -> 266.14 | P59: =ROUND(AC59,2) -> 0 | Q59: =ROUND(AD59,2) -> 132.32 | R59: =ROUND(AE59,2) -> 13.08 | S59: =ROUND(AF59,2) -> 133.82 | T59: =ROUND(AG59,2) -> 0 | U59: =AH59 -> 12.880666 | V59: =AI59 -> 0 | W59: =ROUND(AJ59,2) -> 0 | X59: =ROUND(AK59,2) -> 140.34 | Y59: =ROUND(AL59,2) -> 103.04 | AB59: =ROUND(SUMIF(AA28:AA57,"=56622490",O28:O57),2) -> 266.14 | AC59: =ROUND(SUMIF(AA28:AA57,"=56622490",P28:P57),2) -> 0 | AD59: =ROUND(SUMIF(AA28:AA57,"=56622490",Q28:Q57),2) -> 132.32 | AE59: =ROUND(SUMIF(AA28:AA57,"=56622490",R28:R57),2) -> 13.08 | AF59: =ROUND(SUMIF(AA28:AA57,"=56622490",S28:S57),2) -> 133.82 | AG59: =ROUND(SUMIF(AA28:AA57,"=56622490",T28:T57),2) -> 0 | AH59: =SUMIF(AA28:AA57,"=56622490",U28:U57) -> 12.880666 | AI59: =SUMIF(AA28:AA57,"=56622490",V28:V57) -> 0 | AJ59: =ROUND(SUMIF(AA28:AA57,"=56622490",W28:W57),2) -> 0 | AK59: =ROUND(SUMIF(AA28:AA57,"=56622490",X28:X57),2) -> 140.34 | AL59: =ROUND(SUMIF(AA28:AA57,"=56622490",Y28:Y57),2) -> 103.04 | AO59: =ROUND(BX59,2) -> 0 | AP59: =ROUND(BY59,2) -> 0 | AQ59: =ROUND(BZ59,2) -> 0 | AR59: =ROUND(CA59,2) -> 532.42 | AS59: =ROUND(CB59,2) -> 532.42 | AT59: =ROUND(CC59,2) -> 0 | AU59: =ROUND(CD59,2) -> 0 | AV59: =ROUND(CE59,2) -> 0 | ... BD59: =ROUND(CM59,2) -> 0 | BX59: =ROUND(SUMIF(AA28:AA57,"=56622490",FQ28:FQ57),2) -> 0 | BY59: =ROUND(SUMIF(AA28:AA57,"=56622490",FR28:FR57),2) -> 0 | BZ59: =ROUND(SUMIF(AA28:AA57,"=56622490",GL28:GL57),2) -> 0 | CA59: =ROUND(SUMIF(AA28:AA57,"=56622490",GM28:GM57),2) -> 532.42 | CB59: =ROUND(SUMIF(AA28:AA57,"=56622490",GN28:GN57),2) -> 532.42 | CC59: =ROUND(SUMIF(AA28:AA57,"=56622490",GO28:GO57),2) -> 0 | CD59: =ROUND(SUMIF(AA28:AA57,"=56622490",GP28:GP57),2) -> 0 | CE59: =AC59-BX59 -> 0 | CF59: =AC59-BY59 -> 0 | CG59: =BX59-BZ59 -> 0 | CH59: =AC59-BX59-BY59+BZ59 -> 0 | CI59: =BY59-BZ59 -> 0 | CJ59: =ROUND(SUMIF(AA28:AA57,"=56622490",GX28:GX57),2) -> 0 | CK59: =ROUND(SUMIF(AA28:AA57,"=56622490",GY28:GY57),2) -> 0 | CL59: =ROUND(SUMIF(AA28:AA57,"=56622490",GZ28:GZ57),2) -> 0 | CM59: =ROUND(SUMIF(AA28:AA57,"=56622490",HD28:HD57),2) -> 0 | DG59: =ROUND(DT59,2) -> 6226.15 | DH59: =ROUND(DU59,2) -> 0 | DI59: =ROUND(DV59,2) -> 1608.02 | DJ59: =ROUND(DW59,2) -> 451.39 | DK59: =ROUND(DX59,2) -> 4618.13 | DL59: =ROUND(DY59,2) -> 0 | DM59: =DZ59 -> 12.880666 | DN59: =EA59 -> 0 | DO59: =ROUND(EB59,2) -> 0 | DP59: =ROUND(EC59,2) -> 4023.54 | DQ59: =ROUND(ED59,2) -> 1901.68 | DT59: =ROUND(SUMIF(AA28:AA57,"=56610029",O28:O57),2) -> 6226.15 | DU59: =ROUND(SUMIF(AA28:AA57,"=56610029",P28:P57),2) -> 0 | DV59: =ROUND(SUMIF(AA28:AA57,"=56610029",Q28:Q57),2) -> 1608.02 | DW59: =ROUND(SUMIF(AA28:AA57,"=56610029",R28:R57),2) -> 451.39 | DX59: =ROUND(SUMIF(AA28:AA57,"=56610029",S28:S57),2) -> 4618.13 | DY59: =ROUND(SUMIF(AA28:AA57,"=56610029",T28:T57),2) -> 0 | DZ59: =SUMIF(AA28:AA57,"=56610029",U28:U57) -> 12.880666 | EA59: =SUMIF(AA28:AA57,"=56610029",V28:V57) -> 0 | EB59: =ROUND(SUMIF(AA28:AA57,"=56610029",W28:W57),2) -> 0 | EC59: =ROUND(SUMIF(AA28:AA57,"=56610029",X28:X57),2) -> 4023.54 | ED59: =ROUND(SUMIF(AA28:AA57,"=56610029",Y28:Y57),2) -> 1901.68 | EG59: =ROUND(FP59,2) -> 0 | EH59: =ROUND(FQ59,2) -> 0 | EI59: =ROUND(FR59,2) -> 0 | EJ59: =ROUND(FS59,2) -> 12873.59 | EK59: =ROUND(FT59,2) -> 12873.59 | EL59: =ROUND(FU59,2) -> 0 | EM59: =ROUND(FV59,2) -> 0 | EN59: =ROUND(FW59,2) -> 0 | ... EV59: =ROUND(GE59,2) -> 0 | FP59: =ROUND(SUMIF(AA28:AA57,"=56610029",FQ28:FQ57),2) -> 0 | FQ59: =ROUND(SUMIF(AA28:AA57,"=56610029",FR28:FR57),2) -> 0 | FR59: =ROUND(SUMIF(AA28:AA57,"=56610029",GL28:GL57),2) -> 0 | FS59: =ROUND(SUMIF(AA28:AA57,"=56610029",GM28:GM57),2) -> 12873.59 | FT59: =ROUND(SUMIF(AA28:AA57,"=56610029",GN28:GN57),2) -> 12873.59 | FU59: =ROUND(SUMIF(AA28:AA57,"=56610029",GO28:GO57),2) -> 0 | FV59: =ROUND(SUMIF(AA28:AA57,"=56610029",GP28:GP57),2) -> 0 | FW59: =DU59-FP59 -> 0 | FX59: =DU59-FQ59 -> 0 | FY59: =FP59-FR59 -> 0 | FZ59: =DU59-FP59-FQ59+FR59 -> 0 | GA59: =FQ59-FR59 -> 0 | GB59: =ROUND(SUMIF(AA28:AA57,"=56610029",GX28:GX57),2) -> 0 | GC59: =ROUND(SUMIF(AA28:AA57,"=56610029",GY28:GY57),2) -> 0 | GD59: =ROUND(SUMIF(AA28:AA57,"=56610029",GZ28:GZ57),2) -> 0 | GE59: =ROUND(SUMIF(AA28:AA57,"=56610029",HD28:HD57),2) -> 0 | GX59: 0
A61: 50 | B61: 0 | C61: 0 | D61: 1 | E61: 201 | F61: =ROUND(Source!O59,O61) -> 266.14 | G61: ПЗ | H61: Прямые затраты | K61: 201 | L61: 1 | M61: 3 | O61: 2 | P61: =ROUND(Source!DG59,O61) -> 6226.15 | W61: 266.14 | X61: 1 | Y61: 266.14 | Z61: 6226.15 | AA61: 1 | AB61: 6226.15
A62: 50 | B62: 0 | C62: 0 | D62: 1 | E62: 202 | F62: =ROUND(Source!P59,O62) -> 0 | G62: СтМатОб | H62: Стоимость материальных ресурсов (всего) | K62: 202 | L62: 2 | M62: 3 | O62: 2 | P62: =ROUND(Source!DH59,O62) -> 0 | W62: 0 | X62: 1 | Y62: 0 | Z62: 0 | AA62: 1 | AB62: 0
A63: 50 | B63: 0 | C63: 0 | D63: 1 | E63: 222 | F63: =ROUND(Source!AO59,O63) -> 0 | G63: СтМатОбЗак | H63: Стоимость материалов и оборудования заказчика | K63: 222 | L63: 3 | M63: 3 | O63: 2 | P63: =ROUND(Source!EG59,O63) -> 0 | W63: 0 | X63: 1 | Y63: 0 | Z63: 0 | AA63: 1 | AB63: 0
A64: 50 | B64: 0 | C64: 0 | D64: 1 | E64: 225 | F64: =ROUND(Source!AV59,O64) -> 0 | G64: СтМатОбПод | H64: Стоимость материалов и оборудования подрядчика | K64: 225 | L64: 4 | M64: 3 | O64: 2 | P64: =ROUND(Source!EN59,O64) -> 0 | W64: 0 | X64: 1 | Y64: 0 | Z64: 0 | AA64: 1 | AB64: 0
A65: 50 | B65: 0 | C65: 0 | D65: 1 | E65: 226 | F65: =ROUND(Source!AW59,O65) -> 0 | G65: СтМат | H65: Стоимость материалов (всего) | K65: 226 | L65: 5 | M65: 3 | O65: 2 | P65: =ROUND(Source!EO59,O65) -> 0 | W65: 0 | X65: 1 | Y65: 0 | Z65: 0 | AA65: 1 | AB65: 0
A66: 50 | B66: 0 | C66: 0 | D66: 1 | E66: 227 | F66: =ROUND(Source!AX59,O66) -> 0 | G66: СтМатЗак | H66: Стоимость материалов заказчика | K66: 227 | L66: 6 | M66: 3 | O66: 2 | P66: =ROUND(Source!EP59,O66) -> 0 | W66: 0 | X66: 1 | Y66: 0 | Z66: 0 | AA66: 1 | AB66: 0
A67: 50 | B67: 0 | C67: 0 | D67: 1 | E67: 228 | F67: =ROUND(Source!AY59,O67) -> 0 | G67: СтМатПод | H67: Стоимость материалов подрядчика | K67: 228 | L67: 7 | M67: 3 | O67: 2 | P67: =ROUND(Source!EQ59,O67) -> 0 | W67: 0 | X67: 1 | Y67: 0 | Z67: 0 | AA67: 1 | AB67: 0
A68: 50 | B68: 0 | C68: 0 | D68: 1 | E68: 216 | F68: =ROUND(Source!AP59,O68) -> 0 | G68: Оборуд | H68: Стоимость оборудования (всего) | K68: 216 | L68: 8 | M68: 3 | O68: 2 | P68: =ROUND(Source!EH59,O68) -> 0 | W68: 0 | X68: 1 | Y68: 0 | Z68: 0 | AA68: 1 | AB68: 0
A69: 50 | B69: 0 | C69: 0 | D69: 1 | E69: 223 | F69: =ROUND(Source!AQ59,O69) -> 0 | G69: ОборудЗак | H69: Стоимость оборудования заказчика | K69: 223 | L69: 9 | M69: 3 | O69: 2 | P69: =ROUND(Source!EI59,O69) -> 0 | W69: 0 | X69: 1 | Y69: 0 | Z69: 0 | AA69: 1 | AB69: 0
A70: 50 | B70: 0 | C70: 0 | D70: 1 | E70: 229 | F70: =ROUND(Source!AZ59,O70) -> 0 | G70: ОборудПод | H70: Стоимость оборудования подрядчика | K70: 229 | L70: 10 | M70: 3 | O70: 2 | P70: =ROUND(Source!ER59,O70) -> 0 | W70: 0 | X70: 1 | Y70: 0 | Z70: 0 | AA70: 1 | AB70: 0
A71: 50 | B71: 0 | C71: 0 | D71: 1 | E71: 203 | F71: =ROUND(Source!Q59,O71) -> 132.32 | G71: ЭММ | H71: Эксплуатация машин | K71: 203 | L71: 11 | M71: 3 | O71: 2 | P71: =ROUND(Source!DI59,O71) -> 1608.02 | W71: 132.32 | X71: 1 | Y71: 132.32 | Z71: 1608.02 | AA71: 1 | AB71: 1608.02
A72: 50 | B72: 0 | C72: 0 | D72: 1 | E72: 231 | F72: =ROUND(Source!BB59,O72) -> 0 | G72: ЭММсНРиСП | H72: Эксплуатация машин по ТСН-2001.16 | K72: 231 | L72: 12 | M72: 3 | O72: 2 | P72: =ROUND(Source!ET59,O72) -> 0 | W72: 0 | X72: 1 | Y72: 0 | Z72: 0 | AA72: 1 | AB72: 0
A73: 50 | B73: 0 | C73: 0 | D73: 1 | E73: 204 | F73: =ROUND(Source!R59,O73) -> 13.08 | G73: ЗПМ | H73: ЗП машинистов | K73: 204 | L73: 13 | M73: 3 | O73: 2 | P73: =ROUND(Source!DJ59,O73) -> 451.39 | W73: 13.08 | X73: 1 | Y73: 13.08 | Z73: 451.39 | AA73: 1 | AB73: 451.39
A74: 50 | B74: 0 | C74: 0 | D74: 1 | E74: 205 | F74: =ROUND(Source!S59,O74) -> 133.82 | G74: ОЗП | H74: Основная ЗП рабочих | K74: 205 | L74: 14 | M74: 3 | O74: 2 | P74: =ROUND(Source!DK59,O74) -> 4618.13 | W74: 133.82 | X74: 1 | Y74: 133.82 | Z74: 4618.13 | AA74: 1 | AB74: 4618.13
A75: 50 | B75: 0 | C75: 0 | D75: 1 | E75: 232 | F75: =ROUND(Source!BC59,O75) -> 0 | G75: ОЗПсНРиСП | H75: Основная ЗП рабочих по ТСН-2001.16 | K75: 232 | L75: 15 | M75: 3 | O75: 2 | P75: =ROUND(Source!EU59,O75) -> 0 | W75: 0 | X75: 1 | Y75: 0 | Z75: 0 | AA75: 1 | AB75: 0
A76: 50 | B76: 0 | C76: 0 | D76: 1 | E76: 214 | F76: =ROUND(Source!AS59,O76) -> 532.42 | G76: Строит | H76: Строительные работы с НР и СП | K76: 214 | L76: 16 | M76: 3 | O76: 2 | P76: =ROUND(Source!EK59,O76) -> 12873.59 | W76: 532.42 | X76: 1 | Y76: 532.42 | Z76: 12873.59 | AA76: 1 | AB76: 12873.59
A77: 50 | B77: 0 | C77: 0 | D77: 1 | E77: 215 | F77: =ROUND(Source!AT59,O77) -> 0 | G77: Монтаж | H77: Монтажные работы с НР и СП | K77: 215 | L77: 17 | M77: 3 | O77: 2 | P77: =ROUND(Source!EL59,O77) -> 0 | W77: 0 | X77: 1 | Y77: 0 | Z77: 0 | AA77: 1 | AB77: 0
A78: 50 | B78: 0 | C78: 0 | D78: 1 | E78: 217 | F78: =ROUND(Source!AU59,O78) -> 0 | G78: Прочие | H78: Прочие работы с НР и СП | K78: 217 | L78: 18 | M78: 3 | O78: 2 | P78: =ROUND(Source!EM59,O78) -> 0 | W78: 0 | X78: 1 | Y78: 0 | Z78: 0 | AA78: 1 | AB78: 0
A79: 50 | B79: 0 | C79: 0 | D79: 1 | E79: 230 | F79: =ROUND(Source!BA59,O79) -> 0 | G79: ПрочиеЗатр | H79: Прочие затраты по ТСН-2001.16 | K79: 230 | L79: 19 | M79: 3 | O79: 2 | P79: =ROUND(Source!ES59,O79) -> 0 | W79: 0 | X79: 1 | Y79: 0 | Z79: 0 | AA79: 1 | AB79: 0
A80: 50 | B80: 0 | C80: 0 | D80: 1 | E80: 206 | F80: =ROUND(Source!T59,O80) -> 0 | G80: ВозврМат | H80: Возврат материалов | K80: 206 | L80: 20 | M80: 3 | O80: 2 | P80: =ROUND(Source!DL59,O80) -> 0 | W80: 0 | X80: 1 | Y80: 0 | Z80: 0 | AA80: 1 | AB80: 0
A81: 50 | B81: 0 | C81: 0 | D81: 1 | E81: 207 | F81: =Source!U59 -> 12.880666 | G81: ТрудСтр | H81: Трудозатраты строителей | K81: 207 | L81: 21 | M81: 3 | O81: -1 | P81: =Source!DM59 -> 12.880666 | W81: 12.880666 | X81: 1 | Y81: 12.880666 | Z81: 12.880666 | AA81: 1 | AB81: 12.880666
A82: 50 | B82: 0 | C82: 0 | D82: 1 | E82: 208 | F82: =Source!V59 -> 0 | G82: ТрудМаш | H82: Трудозатраты машинистов | K82: 208 | L82: 22 | M82: 3 | O82: -1 | P82: =Source!DN59 -> 0 | W82: 0 | X82: 1 | Y82: 0 | Z82: 0 | AA82: 1 | AB82: 0
A83: 50 | B83: 0 | C83: 0 | D83: 1 | E83: 209 | F83: =ROUND(Source!W59,O83) -> 0 | G83: ТранспМат | H83: Транспорт материалов | K83: 209 | L83: 23 | M83: 3 | O83: 2 | P83: =ROUND(Source!DO59,O83) -> 0 | W83: 0 | X83: 1 | Y83: 0 | Z83: 0 | AA83: 1 | AB83: 0
A84: 50 | B84: 0 | C84: 0 | D84: 1 | E84: 233 | F84: =ROUND(Source!BD59,O84) -> 0 | G84: Перевозка | H84: Перевозка грузов | K84: 233 | L84: 24 | M84: 3 | O84: 2 | P84: =ROUND(Source!EV59,O84) -> 0 | W84: 0 | X84: 1 | Y84: 0 | Z84: 0 | AA84: 1 | AB84: 0
A85: 50 | B85: 0 | C85: 0 | D85: 1 | E85: 210 | F85: =ROUND(Source!X59,O85) -> 140.34 | G85: НР | H85: Накладные расходы | K85: 210 | L85: 25 | M85: 3 | O85: 2 | P85: =ROUND(Source!DP59,O85) -> 4023.54 | W85: 140.34 | X85: 1 | Y85: 140.34 | Z85: 4023.54 | AA85: 1 | AB85: 4023.54
A86: 50 | B86: 0 | C86: 0 | D86: 1 | E86: 211 | F86: =ROUND(Source!Y59,O86) -> 103.04 | G86: СмПриб | H86: Сметная прибыль | K86: 211 | L86: 26 | M86: 3 | O86: 2 | P86: =ROUND(Source!DQ59,O86) -> 1901.68 | W86: 103.04 | X86: 1 | Y86: 103.04 | Z86: 1901.68 | AA86: 1 | AB86: 1901.68
A87: 50 | B87: 0 | C87: 0 | D87: 1 | E87: 224 | F87: =ROUND(Source!AR59,O87) -> 532.42 | G87: Всего | H87: Всего с НР и СП | K87: 224 | L87: 27 | M87: 3 | O87: 2 | P87: =ROUND(Source!EJ59,O87) -> 12873.59 | W87: 532.42 | X87: 1 | Y87: 532.42 | Z87: 12873.59 | AA87: 1 | AB87: 12873.59
A89: 4 | B89: 1 | D89: =ROW(A148) -> 148 | F89: Новый раздел | G89: Монтажные работы | I89: 0 | K89: -1 | S89: 0 | T89: 0 | V89: 0 | BX89: 0 | CJ89: 0
A91: 52 | B91: =B148 -> 1 | C91: =C148 -> 4 | D91: =D148 -> 89 | E91: =E148 -> 0 | F91: =F148 -> Новый раздел | G91: =G148 -> Монтажные работы | O91: =O148 -> 27092.85 | P91: =P148 -> 26124.11 | Q91: =Q148 -> 400.9 | R91: =R148 -> 56.53 | S91: =S148 -> 567.84 | T91: =T148 -> 0 | U91: =U148 -> 46.373099 | V91: =V148 -> 0 | ... GX91: =GX148 -> 0
A93: 17 | B93: 1 | D93: =ROW(EtalonRes!A71) -> 71 | E93: 16 | F93: 4.8-74-1 | G93: Устройство постели при одном кабеле в траншее | H93: 100 М КАБЕЛЯ | I93: =ROUND(25.5/100*0.3,9) -> 0.0765 | J93: 0 | K93: =ROUND(25.5/100*0.3,9) -> 0.0765 | O93: =ROUND(CP93,2) -> 46.76 | P93: =ROUND((ROUND((AC93*AW93*I93),2)*BC93),2) -> 0 | Q93: =(ROUND((ROUND(((((ET93*1.05)*1.2))*AV93*I93),2)*BB93),2)+ROUND((ROUND(((AE93-(((EU93*1.05)*1.2)))*AV93*I93),2)*BS93),2)) -> 39.06 | R93: =ROUND((ROUND((AE93*AV93*I93),2)*BS93),2) -> 5.93 | S93: =ROUND((ROUND((AF93*AV93*I93),2)*BA93),2) -> 7.7 | T93: =ROUND(CU93*I93,2) -> 0 | U93: =CV93*I93 -> 0.62531663 | V93: =CW93*I93 -> 0 | W93: =ROUND(CX93*I93,2) -> 0 | X93: =ROUND(CY93,2) -> 8.62 | Y93: =ROUND(CZ93,2) -> 5.39 | AA93: 56622490 | AB93: =ROUND((AC93+AD93+AF93),6) -> 572.8968 | AC93: =ROUND(((ES93*1)),6) -> 0 | AD93: =ROUND((((((ET93*1.05)*1.2))-(((EU93*1.05)*1.2)))+AE93),6) -> 478.5102 | AE93: =ROUND((((EU93*1.05)*1.2)),6) -> 72.6642 | AF93: =ROUND((((EV93*1.05)*1.2)),6) -> 94.3866 | AG93: =ROUND((AP93),6) -> 0 | AH93: =(((EW93*1.05)*1.2)) -> 7.6608 | AI93: =(((EX93*1.05)*1.2)) -> 0 | AJ93: =(AS93) -> 0 | AK93: 454.68 | AL93: 0 | AM93: 379.77 | AN93: 57.67 | AO93: 74.91 | AP93: 0 | AQ93: 6.08 | AR93: 0 | AS93: 0 | AT93: 112 | AU93: 70 | AV93: 1.067 | AW93: 1.081 | AZ93: 1 | BA93: 1 | BB93: 1 | BC93: 1 | BH93: 0 | BI93: 2 | BJ93: ТСН-2001.4 Доп. 68, Сб. 8, т. 74, поз. 1 | BM93: 318 | BN93: 0 | BP93: 0 | BQ93: 40 | BR93: 0 | BS93: 1 | BT93: 1 | BU93: 1 | BV93: 1 | BW93: 1 | BX93: 1 | BZ93: 112 | CA93: 70 | CE93: 30 | CF93: 0 | CG93: 0 | CM93: 0 | CN93: Поправка: О.П. п.3.4.30.г Наименование: В отношении объектов, реализуемых с привлечением средств бюджета города Москвы, затраты, учитывающие усложненные условия производства работ (стесненность, сложность складирования и транспортной логистики, наличие в зоне производства работ действующего технологического оборудования или движения технологического транспорта и т.п.), определяются заказчиком в задании на проектирование при составлении локальных сметных расчетов (смет): для объектов города Москвы, расположенных за пределами Московской кольцевой автомобильной дороги Поправка: Гл.4.Прил.2.2.п.2.2.3_04.00.01.01.001 Наименование: При выполнении работ в охранной зоне воздушных линий электропередачи, в местах прохода коммуникаций электроснабжения в действующих электроустановках, вблизи конструкций и предметов, находящихся под напряжением (в случаях, когда полное снятие напряжения по производственным условиям невозможно), если это связано с ограничением действий рабочих специальными требованиями техники безопасности | CO93: 0 | CP93: =(P93+Q93+S93) -> 46.76 | CQ93: =ROUND((ROUND((AC93*AW93*1),2)*BC93),2) -> 0 | CR93: =(ROUND((ROUND(((((ET93*1.05)*1.2))*AV93*1),2)*BB93),2)+ROUND((ROUND(((AE93-(((EU93*1.05)*1.2)))*AV93*1),2)*BS93),2)) -> 510.57 | CS93: =ROUND((ROUND((AE93*AV93*1),2)*BS93),2) -> 77.53 | CT93: =ROUND((ROUND((AF93*AV93*1),2)*BA93),2) -> 100.71 | CU93: =AG93 -> 0 | CV93: =(AH93*AV93) -> 8.1740736 | CW93: =AI93 -> 0 | CX93: =AJ93 -> 0 | CY93: =((S93*BZ93)/100) -> 8.624 | CZ93: =((S93*CA93)/100) -> 5.39 | DB93: 31 | DD93: *1 | DE93: *1,05)*1,2 | DF93: *1,05)*1,2 | DG93: *1,05)*1,2 | DI93: *1,05)*1,2 | DJ93: *1,05)*1,2 | DN93: 0 | DO93: 0 | DP93: 1 | DQ93: 1 | DU93: 1013 | DV93: 100 М КАБЕЛЯ | DW93: 100 М КАБЕЛЯ | DX93: 1 | EE93: 51696357 | EF93: 40 | EG93: Монтаж оборудования | EH93: 0 | EJ93: 2 | EK93: 318 | EL93: ТСН-2001.4-8. 8-73...8-80 | EM93: ТСН-2001.4-8-3 | EO93: Поправка: О.П. п.3.4.30.г Поправка: Гл.4.Прил.2.2.п.2.2.3_04.00.01.01.001 | EQ93: 131072 | ER93: 454.68 | ES93: 0 | ET93: 379.77 | EU93: 57.67 | EV93: 74.91 | EW93: 6.08 | EX93: 0 | EY93: 0 | FQ93: 0 | FR93: 0 | FS93: 0 | FX93: 112 | FY93: 70 | GD93: 0 | GF93: 369100549 | GG93: 2 | GH93: 1 | GI93: -2 | GJ93: 0 | GK93: =ROUND(R93*(R12)/100,2) -> 10.38 | GL93: =ROUND(IF(AND(BH93=3,BI93=3,FS93<>0),P93,0),2) -> 0 | GM93: =ROUND(O93+X93+Y93+GK93,2)+GX93 -> 71.15 | GN93: =IF(OR(BI93=0,BI93=1),GM93-GX93,0) -> 0 | GO93: =IF(BI93=2,GM93-GX93,0) -> 71.15 | GP93: =IF(BI93=4,GM93-GX93,0) -> 0 | GR93: 0 | GS93: 0 | GT93: 0 | GV93: =ROUND((GT93),6) -> 0 | GW93: 1 | GX93: =ROUND(HC93*I93,2) -> 0 | HA93: 0 | HB93: 0 | HC93: =GV93*GW93 -> 0 | HS93: 0 | IK93: 0
A94: 17 | B94: 1 | D94: =ROW(EtalonRes!A74) -> 74 | E94: 16 | F94: 4.8-74-1 | G94: Устройство постели при одном кабеле в траншее | H94: 100 М КАБЕЛЯ | I94: =ROUND(25.5/100*0.3,9) -> 0.0765 | J94: 0 | K94: =ROUND(25.5/100*0.3,9) -> 0.0765 | O94: =ROUND(CP94,2) -> 768.04 | P94: =ROUND((ROUND((AC94*AW94*I94),2)*BC94),2) -> 0 | Q94: =(ROUND((ROUND(((((ET94*1.05)*1.2))*AV94*I94),2)*BB94),2)+ROUND((ROUND(((AE94-(((EU94*1.05)*1.2)))*AV94*I94),2)*BS94),2)) -> 502.31 | R94: =ROUND((ROUND((AE94*AV94*I94),2)*BS94),2) -> 204.64 | S94: =ROUND((ROUND((AF94*AV94*I94),2)*BA94),2) -> 265.73 | T94: =ROUND(CU94*I94,2) -> 0 | U94: =CV94*I94 -> 0.62531663 | V94: =CW94*I94 -> 0 | W94: =ROUND(CX94*I94,2) -> 0 | X94: =ROUND(CY94,2) -> 244.47 | Y94: =ROUND(CZ94,2) -> 114.26 | AA94: 56610029 | AB94: =ROUND((AC94+AD94+AF94),6) -> 572.8968 | AC94: =ROUND(((ES94*1)),6) -> 0 | AD94: =ROUND((((((ET94*1.05)*1.2))-(((EU94*1.05)*1.2)))+AE94),6) -> 478.5102 | AE94: =ROUND((((EU94*1.05)*1.2)),6) -> 72.6642 | AF94: =ROUND((((EV94*1.05)*1.2)),6) -> 94.3866 | AG94: =ROUND((AP94),6) -> 0 | AH94: =(((EW94*1.05)*1.2)) -> 7.6608 | AI94: =(((EX94*1.05)*1.2)) -> 0 | AJ94: =(AS94) -> 0 | AK94: 454.68 | AL94: 0 | AM94: 379.77 | AN94: 57.67 | AO94: 74.91 | AP94: 0 | AQ94: 6.08 | AR94: 0 | AS94: 0 | AT94: 92 | AU94: 43 | AV94: 1.067 | AW94: 1.081 | AZ94: 1 | BA94: 34.51 | BB94: 12.86 | BC94: 1 | BH94: 0 | BI94: 2 | BJ94: ТСН-2001.4 Доп. 68, Сб. 8, т. 74, поз. 1 | BM94: 318 | BN94: 0 | BO94: 4.8-74-1 | BP94: 1 | BQ94: 40 | BR94: 0 | BS94: 34.51 | BT94: 1 | BU94: 1 | BV94: 1 | BW94: 1 | BX94: 1 | BZ94: 92 | CA94: 43 | CE94: 30 | CF94: 0 | CG94: 0 | CM94: 0 | CN94: Поправка: О.П. п.3.4.30.г Наименование: В отношении объектов, реализуемых с привлечением средств бюджета города Москвы, затраты, учитывающие усложненные условия производства работ (стесненность, сложность складирования и транспортной логистики, наличие в зоне производства работ действующего технологического оборудования или движения технологического транспорта и т.п.), определяются заказчиком в задании на проектирование при составлении локальных сметных расчетов (смет): для объектов города Москвы, расположенных за пределами Московской кольцевой автомобильной дороги Поправка: Гл.4.Прил.2.2.п.2.2.3_04.00.01.01.001 Наименование: При выполнении работ в охранной зоне воздушных линий электропередачи, в местах прохода коммуникаций электроснабжения в действующих электроустановках, вблизи конструкций и предметов, находящихся под напряжением (в случаях, когда полное снятие напряжения по производственным условиям невозможно), если это связано с ограничением действий рабочих специальными требованиями техники безопасности | CO94: 0 | CP94: =(P94+Q94+S94) -> 768.04 | CQ94: =ROUND((ROUND((AC94*AW94*1),2)*BC94),2) -> 0 | CR94: =(ROUND((ROUND(((((ET94*1.05)*1.2))*AV94*1),2)*BB94),2)+ROUND((ROUND(((AE94-(((EU94*1.05)*1.2)))*AV94*1),2)*BS94),2)) -> 6565.93 | CS94: =ROUND((ROUND((AE94*AV94*1),2)*BS94),2) -> 2675.56 | CT94: =ROUND((ROUND((AF94*AV94*1),2)*BA94),2) -> 3475.5 | CU94: =AG94 -> 0 | CV94: =(AH94*AV94) -> 8.1740736 | CW94: =AI94 -> 0 | CX94: =AJ94 -> 0 | CY94: =S94*(BZ94/100) -> 244.4716 | CZ94: =S94*(CA94/100) -> 114.2639 | DB94: 33 | DD94: *1 | DE94: *1,05)*1,2 | DF94: *1,05)*1,2 | DG94: *1,05)*1,2 | DI94: *1,05)*1,2 | DJ94: *1,05)*1,2 | DN94: 112 | DO94: 70 | DP94: 1.067 | DQ94: 1.081 | DU94: 1013 | DV94: 100 М КАБЕЛЯ | DW94: 100 М КАБЕЛЯ | DX94: 1 | EE94: 51696357 | EF94: 40 | EG94: Монтаж оборудования | EH94: 0 | EJ94: 2 | EK94: 318 | EL94: ТСН-2001.4-8. 8-73...8-80 | EM94: ТСН-2001.4-8-3 | EO94: Поправка: О.П. п.3.4.30.г Поправка: Гл.4.Прил.2.2.п.2.2.3_04.00.01.01.001 | EQ94: 131072 | ER94: 454.68 | ES94: 0 | ET94: 379.77 | EU94: 57.67 | EV94: 74.91 | EW94: 6.08 | EX94: 0 | EY94: 0 | FQ94: 0 | FR94: 0 | FS94: 0 | FX94: 112 | FY94: 70 | GD94: 0 | GF94: 369100549 | GG94: 2 | GH94: 1 | GI94: 2 | GJ94: 0 | GK94: =ROUND(R94*(S12)/100,2) -> 327.42 | GL94: =ROUND(IF(AND(BH94=3,BI94=3,FS94<>0),P94,0),2) -> 0 | GM94: =ROUND(O94+X94+Y94+GK94,2)+GX94 -> 1454.19 | GN94: =IF(OR(BI94=0,BI94=1),GM94-GX94,0) -> 0 | GO94: =IF(BI94=2,GM94-GX94,0) -> 1454.19 | GP94: =IF(BI94=4,GM94-GX94,0) -> 0 | GR94: 0 | GS94: 3 | GT94: 0 | GV94: =ROUND((GT94),6) -> 0 | GW94: 1 | GX94: =ROUND(HC94*I94,2) -> 0 | HA94: 0 | HB94: 0 | HC94: =GV94*GW94 -> 0 | HS94: 0 | IK94: 0
A95: 17 | B95: 1 | D95: =ROW(EtalonRes!A77) -> 77 | E95: 17 | F95: 4.8-74-1 | G95: Устройство постели при одном кабеле в траншее | H95: 100 М КАБЕЛЯ | I95: =ROUND((25.5*0.7)/100,9) -> 0.1785 | J95: 0 | K95: =ROUND((25.5*0.7)/100,9) -> 0.1785 | O95: =ROUND(CP95,2) -> 90.93 | P95: =ROUND((ROUND((AC95*AW95*I95),2)*BC95),2) -> 0 | Q95: =(ROUND((ROUND((((ET95*1.05))*AV95*I95),2)*BB95),2)+ROUND((ROUND(((AE95-((EU95*1.05)))*AV95*I95),2)*BS95),2)) -> 75.95 | R95: =ROUND((ROUND((AE95*AV95*I95),2)*BS95),2) -> 11.53 | S95: =ROUND((ROUND((AF95*AV95*I95),2)*BA95),2) -> 14.98 | T95: =ROUND(CU95*I95,2) -> 0 | U95: =CV95*I95 -> 1.2158934 | V95: =CW95*I95 -> 0 | W95: =ROUND(CX95*I95,2) -> 0 | X95: =ROUND(CY95,2) -> 16.78 | Y95: =ROUND(CZ95,2) -> 10.49 | AA95: 56622490 | AB95: =ROUND((AC95+AD95+AF95),6) -> 477.414 | AC95: =ROUND((ES95),6) -> 0 | AD95: =ROUND(((((ET95*1.05))-((EU95*1.05)))+AE95),6) -> 398.7585 | AE95: =ROUND(((EU95*1.05)),6) -> 60.5535 | AF95: =ROUND(((EV95*1.05)),6) -> 78.6555 | AG95: =ROUND((AP95),6) -> 0 | AH95: =((EW95*1.05)) -> 6.384 | AI95: =((EX95*1.05)) -> 0 | AJ95: =(AS95) -> 0 | AK95: 454.68 | AL95: 0 | AM95: 379.77 | AN95: 57.67 | AO95: 74.91 | AP95: 0 | AQ95: 6.08 | AR95: 0 | AS95: 0 | AT95: 112 | AU95: 70 | AV95: 1.067 | AW95: 1.081 | AZ95: 1 | BA95: 1 | BB95: 1 | BC95: 1 | BH95: 0 | BI95: 2 | BJ95: ТСН-2001.4 Доп. 68, Сб. 8, т. 74, поз. 1 | BM95: 318 | BN95: 0 | BP95: 0 | BQ95: 40 | BR95: 0 | BS95: 1 | BT95: 1 | BU95: 1 | BV95: 1 | BW95: 1 | BX95: 1 | BZ95: 112 | CA95: 70 | CE95: 30 | CF95: 0 | CG95: 0 | CM95: 0 | CN95: Поправка: О.П. п.3.4.30.г Наименование: В отношении объектов, реализуемых с привлечением средств бюджета города Москвы, затраты, учитывающие усложненные условия производства работ (стесненность, сложность складирования и транспортной логистики, наличие в зоне производства работ действующего технологического оборудования или движения технологического транспорта и т.п.), определяются заказчиком в задании на проектирование при составлении локальных сметных расчетов (смет): для объектов города Москвы, расположенных за пределами Московской кольцевой автомобильной дороги | CO95: 0 | CP95: =(P95+Q95+S95) -> 90.93 | CQ95: =ROUND((ROUND((AC95*AW95*1),2)*BC95),2) -> 0 | CR95: =(ROUND((ROUND((((ET95*1.05))*AV95*1),2)*BB95),2)+ROUND((ROUND(((AE95-((EU95*1.05)))*AV95*1),2)*BS95),2)) -> 425.48 | CS95: =ROUND((ROUND((AE95*AV95*1),2)*BS95),2) -> 64.61 | CT95: =ROUND((ROUND((AF95*AV95*1),2)*BA95),2) -> 83.93 | CU95: =AG95 -> 0 | CV95: =(AH95*AV95) -> 6.811728 | CW95: =AI95 -> 0 | CX95: =AJ95 -> 0 | CY95: =((S95*BZ95)/100) -> 16.7776 | CZ95: =((S95*CA95)/100) -> 10.486 | DB95: 35 | DE95: *1,05 | DF95: *1,05 | DG95: *1,05 | DI95: *1,05 | DJ95: *1,05 | DN95: 0 | DO95: 0 | DP95: 1 | DQ95: 1 | DU95: 1013 | DV95: 100 М КАБЕЛЯ | DW95: 100 М КАБЕЛЯ | DX95: 1 | EE95: 51696357 | EF95: 40 | EG95: Монтаж оборудования | EH95: 0 | EJ95: 2 | EK95: 318 | EL95: ТСН-2001.4-8. 8-73...8-80 | EM95: ТСН-2001.4-8-3 | EO95: Поправка: О.П. п.3.4.30.г | EQ95: 131072 | ER95: 454.68 | ES95: 0 | ET95: 379.77 | EU95: 57.67 | EV95: 74.91 | EW95: 6.08 | EX95: 0 | EY95: 0 | FQ95: 0 | FR95: 0 | FS95: 0 | FX95: 112 | FY95: 70 | GD95: 0 | GF95: 369100549 | GG95: 2 | GH95: 1 | GI95: -2 | GJ95: 0 | GK95: =ROUND(R95*(R12)/100,2) -> 20.18 | GL95: =ROUND(IF(AND(BH95=3,BI95=3,FS95<>0),P95,0),2) -> 0 | GM95: =ROUND(O95+X95+Y95+GK95,2)+GX95 -> 138.38 | GN95: =IF(OR(BI95=0,BI95=1),GM95-GX95,0) -> 0 | GO95: =IF(BI95=2,GM95-GX95,0) -> 138.38 | GP95: =IF(BI95=4,GM95-GX95,0) -> 0 | GR95: 0 | GS95: 0 | GT95: 0 | GV95: =ROUND((GT95),6) -> 0 | GW95: 1 | GX95: =ROUND(HC95*I95,2) -> 0 | HA95: 0 | HB95: 0 | HC95: =GV95*GW95 -> 0 | HS95: 0 | IK95: 0
A96: 17 | B96: 1 | D96: =ROW(EtalonRes!A80) -> 80 | E96: 17 | F96: 4.8-74-1 | G96: Устройство постели при одном кабеле в траншее | H96: 100 М КАБЕЛЯ | I96: =ROUND((25.5*0.7)/100,9) -> 0.1785 | J96: 0 | K96: =ROUND((25.5*0.7)/100,9) -> 0.1785 | O96: =ROUND(CP96,2) -> 1493.68 | P96: =ROUND((ROUND((AC96*AW96*I96),2)*BC96),2) -> 0 | Q96: =(ROUND((ROUND((((ET96*1.05))*AV96*I96),2)*BB96),2)+ROUND((ROUND(((AE96-((EU96*1.05)))*AV96*I96),2)*BS96),2)) -> 976.72 | R96: =ROUND((ROUND((AE96*AV96*I96),2)*BS96),2) -> 397.9 | S96: =ROUND((ROUND((AF96*AV96*I96),2)*BA96),2) -> 516.96 | T96: =ROUND(CU96*I96,2) -> 0 | U96: =CV96*I96 -> 1.2158934 | V96: =CW96*I96 -> 0 | W96: =ROUND(CX96*I96,2) -> 0 | X96: =ROUND(CY96,2) -> 475.6 | Y96: =ROUND(CZ96,2) -> 222.29 | AA96: 56610029 | AB96: =ROUND((AC96+AD96+AF96),6) -> 477.414 | AC96: =ROUND((ES96),6) -> 0 | AD96: =ROUND(((((ET96*1.05))-((EU96*1.05)))+AE96),6) -> 398.7585 | AE96: =ROUND(((EU96*1.05)),6) -> 60.5535 | AF96: =ROUND(((EV96*1.05)),6) -> 78.6555 | AG96: =ROUND((AP96),6) -> 0 | AH96: =((EW96*1.05)) -> 6.384 | AI96: =((EX96*1.05)) -> 0 | AJ96: =(AS96) -> 0 | AK96: 454.68 | AL96: 0 | AM96: 379.77 | AN96: 57.67 | AO96: 74.91 | AP96: 0 | AQ96: 6.08 | AR96: 0 | AS96: 0 | AT96: 92 | AU96: 43 | AV96: 1.067 | AW96: 1.081 | AZ96: 1 | BA96: 34.51 | BB96: 12.86 | BC96: 1 | BH96: 0 | BI96: 2 | BJ96: ТСН-2001.4 Доп. 68, Сб. 8, т. 74, поз. 1 | BM96: 318 | BN96: 0 | BO96: 4.8-74-1 | BP96: 1 | BQ96: 40 | BR96: 0 | BS96: 34.51 | BT96: 1 | BU96: 1 | BV96: 1 | BW96: 1 | BX96: 1 | BZ96: 92 | CA96: 43 | CE96: 30 | CF96: 0 | CG96: 0 | CM96: 0 | CN96: Поправка: О.П. п.3.4.30.г Наименование: В отношении объектов, реализуемых с привлечением средств бюджета города Москвы, затраты, учитывающие усложненные условия производства работ (стесненность, сложность складирования и транспортной логистики, наличие в зоне производства работ действующего технологического оборудования или движения технологического транспорта и т.п.), определяются заказчиком в задании на проектирование при составлении локальных сметных расчетов (смет): для объектов города Москвы, расположенных за пределами Московской кольцевой автомобильной дороги | CO96: 0 | CP96: =(P96+Q96+S96) -> 1493.68 | CQ96: =ROUND((ROUND((AC96*AW96*1),2)*BC96),2) -> 0 | CR96: =(ROUND((ROUND((((ET96*1.05))*AV96*1),2)*BB96),2)+ROUND((ROUND(((AE96-((EU96*1.05)))*AV96*1),2)*BS96),2)) -> 5471.67 | CS96: =ROUND((ROUND((AE96*AV96*1),2)*BS96),2) -> 2229.69 | CT96: =ROUND((ROUND((AF96*AV96*1),2)*BA96),2) -> 2896.42 | CU96: =AG96 -> 0 | CV96: =(AH96*AV96) -> 6.811728 | CW96: =AI96 -> 0 | CX96: =AJ96 -> 0 | CY96: =S96*(BZ96/100) -> 475.6032 | CZ96: =S96*(CA96/100) -> 222.2928 | DB96: 36 | DE96: *1,05 | DF96: *1,05 | DG96: *1,05 | DI96: *1,05 | DJ96: *1,05 | DN96: 112 | DO96: 70 | DP96: 1.067 | DQ96: 1.081 | DU96: 1013 | DV96: 100 М КАБЕЛЯ | DW96: 100 М КАБЕЛЯ | DX96: 1 | EE96: 51696357 | EF96: 40 | EG96: Монтаж оборудования | EH96: 0 | EJ96: 2 | EK96: 318 | EL96: ТСН-2001.4-8. 8-73...8-80 | EM96: ТСН-2001.4-8-3 | EO96: Поправка: О.П. п.3.4.30.г | EQ96: 131072 | ER96: 454.68 | ES96: 0 | ET96: 379.77 | EU96: 57.67 | EV96: 74.91 | EW96: 6.08 | EX96: 0 | EY96: 0 | FQ96: 0 | FR96: 0 | FS96: 0 | FX96: 112 | FY96: 70 | GD96: 0 | GF96: 369100549 | GG96: 2 | GH96: 1 | GI96: 2 | GJ96: 0 | GK96: =ROUND(R96*(S12)/100,2) -> 636.64 | GL96: =ROUND(IF(AND(BH96=3,BI96=3,FS96<>0),P96,0),2) -> 0 | GM96: =ROUND(O96+X96+Y96+GK96,2)+GX96 -> 2828.21 | GN96: =IF(OR(BI96=0,BI96=1),GM96-GX96,0) -> 0 | GO96: =IF(BI96=2,GM96-GX96,0) -> 2828.21 | GP96: =IF(BI96=4,GM96-GX96,0) -> 0 | GR96: 0 | GS96: 3 | GT96: 0 | GV96: =ROUND((GT96),6) -> 0 | GW96: 1 | GX96: =ROUND(HC96*I96,2) -> 0 | HA96: 0 | HB96: 0 | HC96: =GV96*GW96 -> 0 | HS96: 0 | IK96: 0
A97: 17 | B97: 1 | D97: =ROW(EtalonRes!A83) -> 83 | E97: 18 | F97: 4.8-74-2 | G97: Добавлять на каждый последующий кабель при устройстве постели (к норме и расценке 4.8-74-1) | H97: 100 М КАБЕЛЯ | I97: =ROUND(69.5*0.3/100,9) -> 0.2085 | J97: 0 | K97: =ROUND(69.5*0.3/100,9) -> 0.2085 | O97: =ROUND(CP97,2) -> 38.38 | P97: =ROUND((ROUND((AC97*AW97*I97),2)*BC97),2) -> 0 | Q97: =(ROUND((ROUND(((((ET97*1.05)*1.2))*AV97*I97),2)*BB97),2)+ROUND((ROUND(((AE97-(((EU97*1.05)*1.2)))*AV97*I97),2)*BS97),2)) -> 30.51 | R97: =ROUND((ROUND((AE97*AV97*I97),2)*BS97),2) -> 4.63 | S97: =ROUND((ROUND((AF97*AV97*I97),2)*BA97),2) -> 7.87 | T97: =ROUND(CU97*I97,2) -> 0 | U97: =CV97*I97 -> 0.63911038 | V97: =CW97*I97 -> 0 | W97: =ROUND(CX97*I97,2) -> 0 | X97: =ROUND(CY97,2) -> 8.81 | Y97: =ROUND(CZ97,2) -> 5.51 | AA97: 56622490 | AB97: =ROUND((AC97+AD97+AF97),6) -> 172.557 | AC97: =ROUND((ES97),6) -> 0 | AD97: =ROUND((((((ET97*1.05)*1.2))-(((EU97*1.05)*1.2)))+AE97),6) -> 137.1636 | AE97: =ROUND((((EU97*1.05)*1.2)),6) -> 20.8278 | AF97: =ROUND((((EV97*1.05)*1.2)),6) -> 35.3934 | AG97: =ROUND((AP97),6) -> 0 | AH97: =(((EW97*1.05)*1.2)) -> 2.8728 | AI97: =(((EX97*1.05)*1.2)) -> 0 | AJ97: =(AS97) -> 0 | AK97: 136.95 | AL97: 0 | AM97: 108.86 | AN97: 16.53 | AO97: 28.09 | AP97: 0 | AQ97: 2.28 | AR97: 0 | AS97: 0 | AT97: 112 | AU97: 70 | AV97: 1.067 | AW97: 1.081 | AZ97: 1 | BA97: 1 | BB97: 1 | BC97: 1 | BH97: 0 | BI97: 2 | BJ97: ТСН-2001.4 Доп. 68, Сб. 8, т. 74, поз. 2 | BM97: 318 | BN97: 0 | BP97: 0 | BQ97: 40 | BR97: 0 | BS97: 1 | BT97: 1 | BU97: 1 | BV97: 1 | BW97: 1 | BX97: 1 | BZ97: 112 | CA97: 70 | CE97: 30 | CF97: 0 | CG97: 0 | CM97: 0 | CN97: Поправка: О.П. п.3.4.30.г Наименование: В отношении объектов, реализуемых с привлечением средств бюджета города Москвы, затраты, учитывающие усложненные условия производства работ (стесненность, сложность складирования и транспортной логистики, наличие в зоне производства работ действующего технологического оборудования или движения технологического транспорта и т.п.), определяются заказчиком в задании на проектирование при составлении локальных сметных расчетов (смет): для объектов города Москвы, расположенных за пределами Московской кольцевой автомобильной дороги Поправка: О.П. п.3.4.30.а Наименование: В отношении объектов, реализуемых с привлечением средств бюджета города Москвы, затраты, учитывающие усложненные условия производства работ (стесненность, сложность складирования и транспортной логистики, наличие в зоне производства работ действующего технологического оборудования или движения технологического транспорта и т.п.), определяются заказчиком в задании на проектирование при составлении локальных сметных расчетов (смет): для объектов, расположенных в пределах круговой магистральной системы улиц Садовое кольцо города Москвы | CO97: 0 | CP97: =(P97+Q97+S97) -> 38.38 | CQ97: =ROUND((ROUND((AC97*AW97*1),2)*BC97),2) -> 0 | CR97: =(ROUND((ROUND(((((ET97*1.05)*1.2))*AV97*1),2)*BB97),2)+ROUND((ROUND(((AE97-(((EU97*1.05)*1.2)))*AV97*1),2)*BS97),2)) -> 146.35 | CS97: =ROUND((ROUND((AE97*AV97*1),2)*BS97),2) -> 22.22 | CT97: =ROUND((ROUND((AF97*AV97*1),2)*BA97),2) -> 37.76 | CU97: =AG97 -> 0 | CV97: =(AH97*AV97) -> 3.0652776 | CW97: =AI97 -> 0 | CX97: =AJ97 -> 0 | CY97: =((S97*BZ97)/100) -> 8.8144 | CZ97: =((S97*CA97)/100) -> 5.509 | DB97: 37 | DE97: *1,05)*1,2 | DF97: *1,05)*1,2 | DG97: *1,05)*1,2 | DI97: *1,05)*1,2 | DJ97: *1,05)*1,2 | DN97: 0 | DO97: 0 | DP97: 1 | DQ97: 1 | DU97: 1013 | DV97: 100 М КАБЕЛЯ | DW97: 100 М КАБЕЛЯ | DX97: 1 | EE97: 51696357 | EF97: 40 | EG97: Монтаж оборудования | EH97: 0 | EJ97: 2 | EK97: 318 | EL97: ТСН-2001.4-8. 8-73...8-80 | EM97: ТСН-2001.4-8-3 | EO97: Поправка: О.П. п.3.4.30.г Поправка: О.П. п.3.4.30.а | EQ97: 131072 | ER97: 136.95 | ES97: 0 | ET97: 108.86 | EU97: 16.53 | EV97: 28.09 | EW97: 2.28 | EX97: 0 | EY97: 0 | FQ97: 0 | FR97: 0 | FS97: 0 | FX97: 112 | FY97: 70 | GD97: 0 | GF97: -2050852561 | GG97: 2 | GH97: 1 | GI97: -2 | GJ97: 0 | GK97: =ROUND(R97*(R12)/100,2) -> 8.1 | GL97: =ROUND(IF(AND(BH97=3,BI97=3,FS97<>0),P97,0),2) -> 0 | GM97: =ROUND(O97+X97+Y97+GK97,2)+GX97 -> 60.8 | GN97: =IF(OR(BI97=0,BI97=1),GM97-GX97,0) -> 0 | GO97: =IF(BI97=2,GM97-GX97,0) -> 60.8 | GP97: =IF(BI97=4,GM97-GX97,0) -> 0 | GR97: 0 | GS97: 0 | GT97: 0 | GV97: =ROUND((GT97),6) -> 0 | GW97: 1 | GX97: =ROUND(HC97*I97,2) -> 0 | HA97: 0 | HB97: 0 | HC97: =GV97*GW97 -> 0 | HS97: 0 | IK97: 0
A98: 17 | B98: 1 | D98: =ROW(EtalonRes!A86) -> 86 | E98: 18 | F98: 4.8-74-2 | G98: Добавлять на каждый последующий кабель при устройстве постели (к норме и расценке 4.8-74-1) | H98: 100 М КАБЕЛЯ | I98: =ROUND(69.5*0.3/100,9) -> 0.2085 | J98: 0 | K98: =ROUND(69.5*0.3/100,9) -> 0.2085 | O98: =ROUND(CP98,2) -> 663.95 | P98: =ROUND((ROUND((AC98*AW98*I98),2)*BC98),2) -> 0 | Q98: =(ROUND((ROUND(((((ET98*1.05)*1.2))*AV98*I98),2)*BB98),2)+ROUND((ROUND(((AE98-(((EU98*1.05)*1.2)))*AV98*I98),2)*BS98),2)) -> 392.36 | R98: =ROUND((ROUND((AE98*AV98*I98),2)*BS98),2) -> 159.78 | S98: =ROUND((ROUND((AF98*AV98*I98),2)*BA98),2) -> 271.59 | T98: =ROUND(CU98*I98,2) -> 0 | U98: =CV98*I98 -> 0.63911038 | V98: =CW98*I98 -> 0 | W98: =ROUND(CX98*I98,2) -> 0 | X98: =ROUND(CY98,2) -> 249.86 | Y98: =ROUND(CZ98,2) -> 116.78 | AA98: 56610029 | AB98: =ROUND((AC98+AD98+AF98),6) -> 172.557 | AC98: =ROUND((ES98),6) -> 0 | AD98: =ROUND((((((ET98*1.05)*1.2))-(((EU98*1.05)*1.2)))+AE98),6) -> 137.1636 | AE98: =ROUND((((EU98*1.05)*1.2)),6) -> 20.8278 | AF98: =ROUND((((EV98*1.05)*1.2)),6) -> 35.3934 | AG98: =ROUND((AP98),6) -> 0 | AH98: =(((EW98*1.05)*1.2)) -> 2.8728 | AI98: =(((EX98*1.05)*1.2)) -> 0 | AJ98: =(AS98) -> 0 | AK98: 136.95 | AL98: 0 | AM98: 108.86 | AN98: 16.53 | AO98: 28.09 | AP98: 0 | AQ98: 2.28 | AR98: 0 | AS98: 0 | AT98: 92 | AU98: 43 | AV98: 1.067 | AW98: 1.081 | AZ98: 1 | BA98: 34.51 | BB98: 12.86 | BC98: 1 | BH98: 0 | BI98: 2 | BJ98: ТСН-2001.4 Доп. 68, Сб. 8, т. 74, поз. 2 | BM98: 318 | BN98: 0 | BO98: 4.8-74-2 | BP98: 1 | BQ98: 40 | BR98: 0 | BS98: 34.51 | BT98: 1 | BU98: 1 | BV98: 1 | BW98: 1 | BX98: 1 | BZ98: 92 | CA98: 43 | CE98: 30 | CF98: 0 | CG98: 0 | CM98: 0 | CN98: Поправка: О.П. п.3.4.30.г Наименование: В отношении объектов, реализуемых с привлечением средств бюджета города Москвы, затраты, учитывающие усложненные условия производства работ (стесненность, сложность складирования и транспортной логистики, наличие в зоне производства работ действующего технологического оборудования или движения технологического транспорта и т.п.), определяются заказчиком в задании на проектирование при составлении локальных сметных расчетов (смет): для объектов города Москвы, расположенных за пределами Московской кольцевой автомобильной дороги Поправка: О.П. п.3.4.30.а Наименование: В отношении объектов, реализуемых с привлечением средств бюджета города Москвы, затраты, учитывающие усложненные условия производства работ (стесненность, сложность складирования и транспортной логистики, наличие в зоне производства работ действующего технологического оборудования или движения технологического транспорта и т.п.), определяются заказчиком в задании на проектирование при составлении локальных сметных расчетов (смет): для объектов, расположенных в пределах круговой магистральной системы улиц Садовое кольцо города Москвы | CO98: 0 | CP98: =(P98+Q98+S98) -> 663.95 | CQ98: =ROUND((ROUND((AC98*AW98*1),2)*BC98),2) -> 0 | CR98: =(ROUND((ROUND(((((ET98*1.05)*1.2))*AV98*1),2)*BB98),2)+ROUND((ROUND(((AE98-(((EU98*1.05)*1.2)))*AV98*1),2)*BS98),2)) -> 1882.06 | CS98: =ROUND((ROUND((AE98*AV98*1),2)*BS98),2) -> 766.81 | CT98: =ROUND((ROUND((AF98*AV98*1),2)*BA98),2) -> 1303.1 | CU98: =AG98 -> 0 | CV98: =(AH98*AV98) -> 3.0652776 | CW98: =AI98 -> 0 | CX98: =AJ98 -> 0 | CY98: =S98*(BZ98/100) -> 249.8628 | CZ98: =S98*(CA98/100) -> 116.7837 | DB98: 39 | DE98: *1,05)*1,2 | DF98: *1,05)*1,2 | DG98: *1,05)*1,2 | DI98: *1,05)*1,2 | DJ98: *1,05)*1,2 | DN98: 112 | DO98: 70 | DP98: 1.067 | DQ98: 1.081 | DU98: 1013 | DV98: 100 М КАБЕЛЯ | DW98: 100 М КАБЕЛЯ | DX98: 1 | EE98: 51696357 | EF98: 40 | EG98: Монтаж оборудования | EH98: 0 | EJ98: 2 | EK98: 318 | EL98: ТСН-2001.4-8. 8-73...8-80 | EM98: ТСН-2001.4-8-3 | EO98: Поправка: О.П. п.3.4.30.г Поправка: О.П. п.3.4.30.а | EQ98: 131072 | ER98: 136.95 | ES98: 0 | ET98: 108.86 | EU98: 16.53 | EV98: 28.09 | EW98: 2.28 | EX98: 0 | EY98: 0 | FQ98: 0 | FR98: 0 | FS98: 0 | FX98: 112 | FY98: 70 | GD98: 0 | GF98: -2050852561 | GG98: 2 | GH98: 1 | GI98: 2 | GJ98: 0 | GK98: =ROUND(R98*(S12)/100,2) -> 255.65 | GL98: =ROUND(IF(AND(BH98=3,BI98=3,FS98<>0),P98,0),2) -> 0 | GM98: =ROUND(O98+X98+Y98+GK98,2)+GX98 -> 1286.24 | GN98: =IF(OR(BI98=0,BI98=1),GM98-GX98,0) -> 0 | GO98: =IF(BI98=2,GM98-GX98,0) -> 1286.24 | GP98: =IF(BI98=4,GM98-GX98,0) -> 0 | GR98: 0 | GS98: 3 | GT98: 0 | GV98: =ROUND((GT98),6) -> 0 | GW98: 1 | GX98: =ROUND(HC98*I98,2) -> 0 | HA98: 0 | HB98: 0 | HC98: =GV98*GW98 -> 0 | HS98: 0 | IK98: 0
A99: 17 | B99: 1 | D99: =ROW(EtalonRes!A89) -> 89 | E99: 19 | F99: 4.8-74-2 | G99: Добавлять на каждый последующий кабель при устройстве постели (к норме и расценке 4.8-74-1) | H99: 100 М КАБЕЛЯ | I99: =ROUND((69.5*0.7)/100,9) -> 0.4865 | J99: 0 | K99: =ROUND((69.5*0.7)/100,9) -> 0.4865 | O99: =ROUND(CP99,2) -> 74.64 | P99: =ROUND((ROUND((AC99*AW99*I99),2)*BC99),2) -> 0 | Q99: =(ROUND((ROUND((((ET99*1.05))*AV99*I99),2)*BB99),2)+ROUND((ROUND(((AE99-((EU99*1.05)))*AV99*I99),2)*BS99),2)) -> 59.33 | R99: =ROUND((ROUND((AE99*AV99*I99),2)*BS99),2) -> 9.01 | S99: =ROUND((ROUND((AF99*AV99*I99),2)*BA99),2) -> 15.31 | T99: =ROUND(CU99*I99,2) -> 0 | U99: =CV99*I99 -> 1.2427146 | V99: =CW99*I99 -> 0 | W99: =ROUND(CX99*I99,2) -> 0 | X99: =ROUND(CY99,2) -> 17.15 | Y99: =ROUND(CZ99,2) -> 10.72 | AA99: 56622490 | AB99: =ROUND((AC99+AD99+AF99),6) -> 143.7975 | AC99: =ROUND((ES99),6) -> 0 | AD99: =ROUND(((((ET99*1.05))-((EU99*1.05)))+AE99),6) -> 114.303 | AE99: =ROUND(((EU99*1.05)),6) -> 17.3565 | AF99: =ROUND(((EV99*1.05)),6) -> 29.4945 | AG99: =ROUND((AP99),6) -> 0 | AH99: =((EW99*1.05)) -> 2.394 | AI99: =((EX99*1.05)) -> 0 | AJ99: =(AS99) -> 0 | AK99: 136.95 | AL99: 0 | AM99: 108.86 | AN99: 16.53 | AO99: 28.09 | AP99: 0 | AQ99: 2.28 | AR99: 0 | AS99: 0 | AT99: 112 | AU99: 70 | AV99: 1.067 | AW99: 1.081 | AZ99: 1 | BA99: 1 | BB99: 1 | BC99: 1 | BH99: 0 | BI99: 2 | BJ99: ТСН-2001.4 Доп. 68, Сб. 8, т. 74, поз. 2 | BM99: 318 | BN99: 0 | BP99: 0 | BQ99: 40 | BR99: 0 | BS99: 1 | BT99: 1 | BU99: 1 | BV99: 1 | BW99: 1 | BX99: 1 | BZ99: 112 | CA99: 70 | CE99: 30 | CF99: 0 | CG99: 0 | CM99: 0 | CN99: Поправка: О.П. п.3.4.30.г Наименование: В отношении объектов, реализуемых с привлечением средств бюджета города Москвы, затраты, учитывающие усложненные условия производства работ (стесненность, сложность складирования и транспортной логистики, наличие в зоне производства работ действующего технологического оборудования или движения технологического транспорта и т.п.), определяются заказчиком в задании на проектирование при составлении локальных сметных расчетов (смет): для объектов города Москвы, расположенных за пределами Московской кольцевой автомобильной дороги | CO99: 0 | CP99: =(P99+Q99+S99) -> 74.64 | CQ99: =ROUND((ROUND((AC99*AW99*1),2)*BC99),2) -> 0 | CR99: =(ROUND((ROUND((((ET99*1.05))*AV99*1),2)*BB99),2)+ROUND((ROUND(((AE99-((EU99*1.05)))*AV99*1),2)*BS99),2)) -> 121.96 | CS99: =ROUND((ROUND((AE99*AV99*1),2)*BS99),2) -> 18.52 | CT99: =ROUND((ROUND((AF99*AV99*1),2)*BA99),2) -> 31.47 | CU99: =AG99 -> 0 | CV99: =(AH99*AV99) -> 2.554398 | CW99: =AI99 -> 0 | CX99: =AJ99 -> 0 | CY99: =((S99*BZ99)/100) -> 17.1472 | CZ99: =((S99*CA99)/100) -> 10.717 | DB99: 41 | DE99: *1,05 | DF99: *1,05 | DG99: *1,05 | DI99: *1,05 | DJ99: *1,05 | DN99: 0 | DO99: 0 | DP99: 1 | DQ99: 1 | DU99: 1013 | DV99: 100 М КАБЕЛЯ | DW99: 100 М КАБЕЛЯ | DX99: 1 | EE99: 51696357 | EF99: 40 | EG99: Монтаж оборудования | EH99: 0 | EJ99: 2 | EK99: 318 | EL99: ТСН-2001.4-8. 8-73...8-80 | EM99: ТСН-2001.4-8-3 | EO99: Поправка: О.П. п.3.4.30.г | EQ99: 131072 | ER99: 136.95 | ES99: 0 | ET99: 108.86 | EU99: 16.53 | EV99: 28.09 | EW99: 2.28 | EX99: 0 | EY99: 0 | FQ99: 0 | FR99: 0 | FS99: 0 | FX99: 112 | FY99: 70 | GD99: 0 | GF99: -2050852561 | GG99: 2 | GH99: 1 | GI99: -2 | GJ99: 0 | GK99: =ROUND(R99*(R12)/100,2) -> 15.77 | GL99: =ROUND(IF(AND(BH99=3,BI99=3,FS99<>0),P99,0),2) -> 0 | GM99: =ROUND(O99+X99+Y99+GK99,2)+GX99 -> 118.28 | GN99: =IF(OR(BI99=0,BI99=1),GM99-GX99,0) -> 0 | GO99: =IF(BI99=2,GM99-GX99,0) -> 118.28 | GP99: =IF(BI99=4,GM99-GX99,0) -> 0 | GR99: 0 | GS99: 0 | GT99: 0 | GV99: =ROUND((GT99),6) -> 0 | GW99: 1 | GX99: =ROUND(HC99*I99,2) -> 0 | HA99: 0 | HB99: 0 | HC99: =GV99*GW99 -> 0 | HS99: 0 | IK99: 0
A100: 17 | B100: 1 | D100: =ROW(EtalonRes!A92) -> 92 | E100: 19 | F100: 4.8-74-2 | G100: Добавлять на каждый последующий кабель при устройстве постели (к норме и расценке 4.8-74-1) | H100: 100 М КАБЕЛЯ | I100: =ROUND((69.5*0.7)/100,9) -> 0.4865 | J100: 0 | K100: =ROUND((69.5*0.7)/100,9) -> 0.4865 | O100: =ROUND(CP100,2) -> 1291.33 | P100: =ROUND((ROUND((AC100*AW100*I100),2)*BC100),2) -> 0 | Q100: =(ROUND((ROUND((((ET100*1.05))*AV100*I100),2)*BB100),2)+ROUND((ROUND(((AE100-((EU100*1.05)))*AV100*I100),2)*BS100),2)) -> 762.98 | R100: =ROUND((ROUND((AE100*AV100*I100),2)*BS100),2) -> 310.94 | S100: =ROUND((ROUND((AF100*AV100*I100),2)*BA100),2) -> 528.35 | T100: =ROUND(CU100*I100,2) -> 0 | U100: =CV100*I100 -> 1.2427146 | V100: =CW100*I100 -> 0 | W100: =ROUND(CX100*I100,2) -> 0 | X100: =ROUND(CY100,2) -> 486.08 | Y100: =ROUND(CZ100,2) -> 227.19 | AA100: 56610029 | AB100: =ROUND((AC100+AD100+AF100),6) -> 143.7975 | AC100: =ROUND((ES100),6) -> 0 | AD100: =ROUND(((((ET100*1.05))-((EU100*1.05)))+AE100),6) -> 114.303 | AE100: =ROUND(((EU100*1.05)),6) -> 17.3565 | AF100: =ROUND(((EV100*1.05)),6) -> 29.4945 | AG100: =ROUND((AP100),6) -> 0 | AH100: =((EW100*1.05)) -> 2.394 | AI100: =((EX100*1.05)) -> 0 | AJ100: =(AS100) -> 0 | AK100: 136.95 | AL100: 0 | AM100: 108.86 | AN100: 16.53 | AO100: 28.09 | AP100: 0 | AQ100: 2.28 | AR100: 0 | AS100: 0 | AT100: 92 | AU100: 43 | AV100: 1.067 | AW100: 1.081 | AZ100: 1 | BA100: 34.51 | BB100: 12.86 | BC100: 1 | BH100: 0 | BI100: 2 | BJ100: ТСН-2001.4 Доп. 68, Сб. 8, т. 74, поз. 2 | BM100: 318 | BN100: 0 | BO100: 4.8-74-2 | BP100: 1 | BQ100: 40 | BR100: 0 | BS100: 34.51 | BT100: 1 | BU100: 1 | BV100: 1 | BW100: 1 | BX100: 1 | BZ100: 92 | CA100: 43 | CE100: 30 | CF100: 0 | CG100: 0 | CM100: 0 | CN100: Поправка: О.П. п.3.4.30.г Наименование: В отношении объектов, реализуемых с привлечением средств бюджета города Москвы, затраты, учитывающие усложненные условия производства работ (стесненность, сложность складирования и транспортной логистики, наличие в зоне производства работ действующего технологического оборудования или движения технологического транспорта и т.п.), определяются заказчиком в задании на проектирование при составлении локальных сметных расчетов (смет): для объектов города Москвы, расположенных за пределами Московской кольцевой автомобильной дороги | CO100: 0 | CP100: =(P100+Q100+S100) -> 1291.33 | CQ100: =ROUND((ROUND((AC100*AW100*1),2)*BC100),2) -> 0 | CR100: =(ROUND((ROUND((((ET100*1.05))*AV100*1),2)*BB100),2)+ROUND((ROUND(((AE100-((EU100*1.05)))*AV100*1),2)*BS100),2)) -> 1568.41 | CS100: =ROUND((ROUND((AE100*AV100*1),2)*BS100),2) -> 639.13 | CT100: =ROUND((ROUND((AF100*AV100*1),2)*BA100),2) -> 1086.03 | CU100: =AG100 -> 0 | CV100: =(AH100*AV100) -> 2.554398 | CW100: =AI100 -> 0 | CX100: =AJ100 -> 0 | CY100: =S100*(BZ100/100) -> 486.082 | CZ100: =S100*(CA100/100) -> 227.1905 | DB100: 42 | DE100: *1,05 | DF100: *1,05 | DG100: *1,05 | DI100: *1,05 | DJ100: *1,05 | DN100: 112 | DO100: 70 | DP100: 1.067 | DQ100: 1.081 | DU100: 1013 | DV100: 100 М КАБЕЛЯ | DW100: 100 М КАБЕЛЯ | DX100: 1 | EE100: 51696357 | EF100: 40 | EG100: Монтаж оборудования | EH100: 0 | EJ100: 2 | EK100: 318 | EL100: ТСН-2001.4-8. 8-73...8-80 | EM100: ТСН-2001.4-8-3 | EO100: Поправка: О.П. п.3.4.30.г | EQ100: 131072 | ER100: 136.95 | ES100: 0 | ET100: 108.86 | EU100: 16.53 | EV100: 28.09 | EW100: 2.28 | EX100: 0 | EY100: 0 | FQ100: 0 | FR100: 0 | FS100: 0 | FX100: 112 | FY100: 70 | GD100: 0 | GF100: -2050852561 | GG100: 2 | GH100: 1 | GI100: 2 | GJ100: 0 | GK100: =ROUND(R100*(S12)/100,2) -> 497.5 | GL100: =ROUND(IF(AND(BH100=3,BI100=3,FS100<>0),P100,0),2) -> 0 | GM100: =ROUND(O100+X100+Y100+GK100,2)+GX100 -> 2502.1 | GN100: =IF(OR(BI100=0,BI100=1),GM100-GX100,0) -> 0 | GO100: =IF(BI100=2,GM100-GX100,0) -> 2502.1 | GP100: =IF(BI100=4,GM100-GX100,0) -> 0 | GR100: 0 | GS100: 3 | GT100: 0 | GV100: =ROUND((GT100),6) -> 0 | GW100: 1 | GX100: =ROUND(HC100*I100,2) -> 0 | HA100: 0 | HB100: 0 | HC100: =GV100*GW100 -> 0 | HS100: 0 | IK100: 0
A101: 17 | B101: 1 | E101: 20 | F101: 1.1-1-766 | G101: Песок для строительных работ, рядовой (карьерный) | H101: м3 | I101: 4.22 | J101: 0 | K101: 4.22 | O101: =ROUND(CP101,2) -> 443.06 | P101: =ROUND((ROUND((AC101*AW101*I101),2)*BC101),2) -> 443.06 | Q101: =(ROUND((ROUND((((ET101*1.05))*AV101*I101),2)*BB101),2)+ROUND((ROUND(((AE101-((EU101*1.05)))*AV101*I101),2)*BS101),2)) -> 0 | R101: =ROUND((ROUND((AE101*AV101*I101),2)*BS101),2) -> 0 | S101: =ROUND((ROUND((AF101*AV101*I101),2)*BA101),2) -> 0 | T101: =ROUND(CU101*I101,2) -> 0 | U101: =CV101*I101 -> 0 | V101: =CW101*I101 -> 0 | W101: =ROUND(CX101*I101,2) -> 0 | X101: =ROUND(CY101,2) -> 0 | Y101: =ROUND(CZ101,2) -> 0 | AA101: 56622490 | AB101: =ROUND((AC101+AD101+AF101),6) -> 104.99 | AC101: =ROUND((ES101),6) -> 104.99 | AD101: =ROUND(((((ET101*1.05))-((EU101*1.05)))+AE101),6) -> 0 | AE101: =ROUND(((EU101*1.05)),6) -> 0 | AF101: =ROUND(((EV101*1.05)),6) -> 0 | AG101: =ROUND((AP101),6) -> 0 | AH101: =((EW101*1.05)) -> 0 | AI101: =((EX101*1.05)) -> 0 | AJ101: =(AS101) -> 0 | AK101: 104.99 | AL101: 104.99 | AM101: 0 | AN101: 0 | AO101: 0 | AP101: 0 | AQ101: 0 | AR101: 0 | AS101: 0 | AT101: 0 | AU101: 0 | AV101: 1 | AW101: 1 | AZ101: 1 | BA101: 1 | BB101: 1 | BC101: 1 | BH101: 3 | BI101: 1 | BJ101: ТСН-2001.1 Доп. 69, Р. 1, о. 1, поз. 766 | BM101: 1617 | BN101: 0 | BP101: 0 | BQ101: 200 | BR101: 0 | BS101: 1 | BT101: 1 | BU101: 1 | BV101: 1 | BW101: 1 | BX101: 1 | BZ101: 0 | CA101: 0 | CE101: 30 | CF101: 0 | CG101: 0 | CM101: 0 | CN101: Поправка: О.П. п.3.4.30.г Наименование: В отношении объектов, реализуемых с привлечением средств бюджета города Москвы, затраты, учитывающие усложненные условия производства работ (стесненность, сложность складирования и транспортной логистики, наличие в зоне производства работ действующего технологического оборудования или движения технологического транспорта и т.п.), определяются заказчиком в задании на проектирование при составлении локальных сметных расчетов (смет): для объектов города Москвы, расположенных за пределами Московской кольцевой автомобильной дороги | CO101: 0 | CP101: =(P101+Q101+S101) -> 443.06 | CQ101: =ROUND((ROUND((AC101*AW101*1),2)*BC101),2) -> 104.99 | CR101: =(ROUND((ROUND((((ET101*1.05))*AV101*1),2)*BB101),2)+ROUND((ROUND(((AE101-((EU101*1.05)))*AV101*1),2)*BS101),2)) -> 0 | CS101: =ROUND((ROUND((AE101*AV101*1),2)*BS101),2) -> 0 | CT101: =ROUND((ROUND((AF101*AV101*1),2)*BA101),2) -> 0 | CU101: =AG101 -> 0 | CV101: =(AH101*AV101) -> 0 | CW101: =AI101 -> 0 | CX101: =AJ101 -> 0 | CY101: =((S101*BZ101)/100) -> 0 | CZ101: =((S101*CA101)/100) -> 0 | DB101: 43 | DE101: *1,05 | DF101: *1,05 | DG101: *1,05 | DI101: *1,05 | DJ101: *1,05 | DN101: 0 | DO101: 0 | DP101: 1 | DQ101: 1 | DU101: 1007 | DV101: м3 | DW101: м3 | DX101: 1 | EE101: 51697656 | EF101: 200 | EG101: Материалы строительные | EH101: 0 | EJ101: 1 | EK101: 1617 | EL101: ТСН-2001.1 Материалы строительные | EM101: ТСН-2001.1-1 | EO101: Поправка: О.П. п.3.4.30.г | EQ101: 131072 | ER101: 104.99 | ES101: 104.99 | ET101: 0 | EU101: 0 | EV101: 0 | EW101: 0 | EX101: 0 | EY101: 0 | FQ101: 0 | FR101: 0 | FS101: 0 | FX101: 0 | FY101: 0 | GD101: 0 | GF101: -449487181 | GG101: 2 | GH101: 1 | GI101: -2 | GJ101: 0 | GK101: =ROUND(R101*(R12)/100,2) -> 0 | GL101: =ROUND(IF(AND(BH101=3,BI101=3,FS101<>0),P101,0),2) -> 0 | GM101: =ROUND(O101+X101+Y101+GK101,2)+GX101 -> 443.06 | GN101: =IF(OR(BI101=0,BI101=1),GM101-GX101,0) -> 443.06 | GO101: =IF(BI101=2,GM101-GX101,0) -> 0 | GP101: =IF(BI101=4,GM101-GX101,0) -> 0 | GR101: 0 | GS101: 0 | GT101: 0 | GV101: =ROUND((GT101),6) -> 0 | GW101: 1 | GX101: =ROUND(HC101*I101,2) -> 0 | HA101: 0 | HB101: 0 | HC101: =GV101*GW101 -> 0 | HS101: 0 | IK101: 0
A102: 17 | B102: 1 | E102: 20 | F102: 1.1-1-766 | G102: Песок для строительных работ, рядовой (карьерный) | H102: м3 | I102: 4.22 | J102: 0 | K102: 4.22 | O102: =ROUND(CP102,2) -> 3407.13 | P102: =ROUND((ROUND((AC102*AW102*I102),2)*BC102),2) -> 3407.13 | Q102: =(ROUND((ROUND((((ET102*1.05))*AV102*I102),2)*BB102),2)+ROUND((ROUND(((AE102-((EU102*1.05)))*AV102*I102),2)*BS102),2)) -> 0 | R102: =ROUND((ROUND((AE102*AV102*I102),2)*BS102),2) -> 0 | S102: =ROUND((ROUND((AF102*AV102*I102),2)*BA102),2) -> 0 | T102: =ROUND(CU102*I102,2) -> 0 | U102: =CV102*I102 -> 0 | V102: =CW102*I102 -> 0 | W102: =ROUND(CX102*I102,2) -> 0 | X102: =ROUND(CY102,2) -> 0 | Y102: =ROUND(CZ102,2) -> 0 | AA102: 56610029 | AB102: =ROUND((AC102+AD102+AF102),6) -> 104.99 | AC102: =ROUND((ES102),6) -> 104.99 | AD102: =ROUND(((((ET102*1.05))-((EU102*1.05)))+AE102),6) -> 0 | AE102: =ROUND(((EU102*1.05)),6) -> 0 | AF102: =ROUND(((EV102*1.05)),6) -> 0 | AG102: =ROUND((AP102),6) -> 0 | AH102: =((EW102*1.05)) -> 0 | AI102: =((EX102*1.05)) -> 0 | AJ102: =(AS102) -> 0 | AK102: 104.99 | AL102: 104.99 | AM102: 0 | AN102: 0 | AO102: 0 | AP102: 0 | AQ102: 0 | AR102: 0 | AS102: 0 | AT102: 0 | AU102: 0 | AV102: 1 | AW102: 1 | AZ102: 1 | BA102: 1 | BB102: 1 | BC102: 7.69 | BH102: 3 | BI102: 1 | BJ102: ТСН-2001.1 Доп. 69, Р. 1, о. 1, поз. 766 | BM102: 1617 | BN102: 0 | BO102: 1.1-1-766 | BP102: 1 | BQ102: 200 | BR102: 0 | BS102: 1 | BT102: 1 | BU102: 1 | BV102: 1 | BW102: 1 | BX102: 1 | BZ102: 0 | CA102: 0 | CE102: 30 | CF102: 0 | CG102: 0 | CM102: 0 | CN102: Поправка: О.П. п.3.4.30.г Наименование: В отношении объектов, реализуемых с привлечением средств бюджета города Москвы, затраты, учитывающие усложненные условия производства работ (стесненность, сложность складирования и транспортной логистики, наличие в зоне производства работ действующего технологического оборудования или движения технологического транспорта и т.п.), определяются заказчиком в задании на проектирование при составлении локальных сметных расчетов (смет): для объектов города Москвы, расположенных за пределами Московской кольцевой автомобильной дороги | CO102: 0 | CP102: =(P102+Q102+S102) -> 3407.13 | CQ102: =ROUND((ROUND((AC102*AW102*1),2)*BC102),2) -> 807.37 | CR102: =(ROUND((ROUND((((ET102*1.05))*AV102*1),2)*BB102),2)+ROUND((ROUND(((AE102-((EU102*1.05)))*AV102*1),2)*BS102),2)) -> 0 | CS102: =ROUND((ROUND((AE102*AV102*1),2)*BS102),2) -> 0 | CT102: =ROUND((ROUND((AF102*AV102*1),2)*BA102),2) -> 0 | CU102: =AG102 -> 0 | CV102: =(AH102*AV102) -> 0 | CW102: =AI102 -> 0 | CX102: =AJ102 -> 0 | CY102: =S102*(BZ102/100) -> 0 | CZ102: =S102*(CA102/100) -> 0 | DB102: 44 | DE102: *1,05 | DF102: *1,05 | DG102: *1,05 | DI102: *1,05 | DJ102: *1,05 | DN102: 0 | DO102: 0 | DP102: 1 | DQ102: 1 | DU102: 1007 | DV102: м3 | DW102: м3 | DX102: 1 | EE102: 51697656 | EF102: 200 | EG102: Материалы строительные | EH102: 0 | EJ102: 1 | EK102: 1617 | EL102: ТСН-2001.1 Материалы строительные | EM102: ТСН-2001.1-1 | EO102: Поправка: О.П. п.3.4.30.г | EQ102: 131072 | ER102: 104.99 | ES102: 104.99 | ET102: 0 | EU102: 0 | EV102: 0 | EW102: 0 | EX102: 0 | EY102: 0 | FQ102: 0 | FR102: 0 | FS102: 0 | FX102: 0 | FY102: 0 | GD102: 0 | GF102: -449487181 | GG102: 2 | GH102: 1 | GI102: 2 | GJ102: 0 | GK102: =ROUND(R102*(S12)/100,2) -> 0 | GL102: =ROUND(IF(AND(BH102=3,BI102=3,FS102<>0),P102,0),2) -> 0 | GM102: =ROUND(O102+X102+Y102+GK102,2)+GX102 -> 3407.13 | GN102: =IF(OR(BI102=0,BI102=1),GM102-GX102,0) -> 3407.13 | GO102: =IF(BI102=2,GM102-GX102,0) -> 0 | GP102: =IF(BI102=4,GM102-GX102,0) -> 0 | GR102: 0 | GS102: 3 | GT102: 0 | GV102: =ROUND((GT102),6) -> 0 | GW102: 1 | GX102: =ROUND(HC102*I102,2) -> 0 | HA102: 0 | HB102: 0 | HC102: =GV102*GW102 -> 0 | HS102: 0 | IK102: 0
A103: 17 | B103: 1 | D103: =ROW(EtalonRes!A106) -> 106 | E103: 21 | F103: 4.8-73-2 | G103: Прокладка кабеля напряжением до 35 кВ в готовых траншеях без покрытий при массе 1 м до 2 кг | H103: 100 М КАБЕЛЯ | I103: =ROUND(290.7/100*0.3,9) -> 0.8721 | J103: 0 | K103: =ROUND(290.7/100*0.3,9) -> 0.8721 | O103: =ROUND(CP103,2) -> 355.39 | P103: =ROUND((ROUND((AC103*AW103*I103),2)*BC103),2) -> 125.51 | Q103: =(ROUND((ROUND(((((ET103*1.05)*1.2))*AV103*I103),2)*BB103),2)+ROUND((ROUND(((AE103-(((EU103*1.05)*1.2)))*AV103*I103),2)*BS103),2)) -> 59.43 | R103: =ROUND((ROUND((AE103*AV103*I103),2)*BS103),2) -> 7.55 | S103: =ROUND((ROUND((AF103*AV103*I103),2)*BA103),2) -> 170.45 | T103: =ROUND(CU103*I103,2) -> 0 | U103: =CV103*I103 -> 13.83513 | V103: =CW103*I103 -> 0 | W103: =ROUND(CX103*I103,2) -> 0 | X103: =ROUND(CY103,2) -> 190.9 | Y103: =ROUND(CZ103,2) -> 119.32 | AA103: 56622490 | AB103: =ROUND((AC103+AD103+AF103),6) -> 380.1782 | AC103: =ROUND(((ES103*1)),6) -> 133.13 | AD103: =ROUND((((((ET103*1.05)*1.2))-(((EU103*1.05)*1.2)))+AE103),6) -> 63.8694 | AE103: =ROUND((((EU103*1.05)*1.2)),6) -> 8.1144 | AF103: =ROUND((((EV103*1.05)*1.2)),6) -> 183.1788 | AG103: =ROUND((AP103),6) -> 0 | AH103: =(((EW103*1.05)*1.2)) -> 14.868 | AI103: =(((EX103*1.05)*1.2)) -> 0 | AJ103: =(AS103) -> 0 | AK103: 329.2 | AL103: 133.13 | AM103: 50.69 | AN103: 6.44 | AO103: 145.38 | AP103: 0 | AQ103: 11.8 | AR103: 0 | AS103: 0 | AT103: 112 | AU103: 70 | AV103: 1.067 | AW103: 1.081 | AZ103: 1 | BA103: 1 | BB103: 1 | BC103: 1 | BH103: 0 | BI103: 2 | BJ103: ТСН-2001.4 Доп. 69, Сб. 8, т. 73, поз. 2 | BM103: 318 | BN103: 0 | BP103: 0 | BQ103: 40 | BR103: 0 | BS103: 1 | BT103: 1 | BU103: 1 | BV103: 1 | BW103: 1 | BX103: 1 | BZ103: 112 | CA103: 70 | CE103: 30 | CF103: 0 | CG103: 0 | CM103: 0 | CN103: Поправка: О.П. п.3.4.30.г Наименование: В отношении объектов, реализуемых с привлечением средств бюджета города Москвы, затраты, учитывающие усложненные условия производства работ (стесненность, сложность складирования и транспортной логистики, наличие в зоне производства работ действующего технологического оборудования или движения технологического транспорта и т.п.), определяются заказчиком в задании на проектирование при составлении локальных сметных расчетов (смет): для объектов города Москвы, расположенных за пределами Московской кольцевой автомобильной дороги Поправка: Гл.4.Прил.2.2.п.2.2.3_04.00.01.01.001 Наименование: При выполнении работ в охранной зоне воздушных линий электропередачи, в местах прохода коммуникаций электроснабжения в действующих электроустановках, вблизи конструкций и предметов, находящихся под напряжением (в случаях, когда полное снятие напряжения по производственным условиям невозможно), если это связано с ограничением действий рабочих специальными требованиями техники безопасности | CO103: 0 | CP103: =(P103+Q103+S103) -> 355.39 | CQ103: =ROUND((ROUND((AC103*AW103*1),2)*BC103),2) -> 143.91 | CR103: =(ROUND((ROUND(((((ET103*1.05)*1.2))*AV103*1),2)*BB103),2)+ROUND((ROUND(((AE103-(((EU103*1.05)*1.2)))*AV103*1),2)*BS103),2)) -> 68.15 | CS103: =ROUND((ROUND((AE103*AV103*1),2)*BS103),2) -> 8.66 | CT103: =ROUND((ROUND((AF103*AV103*1),2)*BA103),2) -> 195.45 | CU103: =AG103 -> 0 | CV103: =(AH103*AV103) -> 15.864156 | CW103: =AI103 -> 0 | CX103: =AJ103 -> 0 | CY103: =((S103*BZ103)/100) -> 190.904 | CZ103: =((S103*CA103)/100) -> 119.315 | DB103: 45 | DD103: *1 | DE103: *1,05)*1,2 | DF103: *1,05)*1,2 | DG103: *1,05)*1,2 | DI103: *1,05)*1,2 | DJ103: *1,05)*1,2 | DN103: 0 | DO103: 0 | DP103: 1 | DQ103: 1 | DU103: 1013 | DV103: 100 М КАБЕЛЯ | DW103: 100 М КАБЕЛЯ | DX103: 1 | EE103: 51696357 | EF103: 40 | EG103: Монтаж оборудования | EH103: 0 | EJ103: 2 | EK103: 318 | EL103: ТСН-2001.4-8. 8-73...8-80 | EM103: ТСН-2001.4-8-3 | EO103: Поправка: О.П. п.3.4.30.г Поправка: Гл.4.Прил.2.2.п.2.2.3_04.00.01.01.001 | EQ103: 131072 | ER103: 329.2 | ES103: 133.13 | ET103: 50.69 | EU103: 6.44 | EV103: 145.38 | EW103: 11.8 | EX103: 0 | EY103: 0 | FQ103: 0 | FR103: 0 | FS103: 0 | FX103: 112 | FY103: 70 | GD103: 0 | GF103: 1434814843 | GG103: 2 | GH103: 1 | GI103: -2 | GJ103: 0 | GK103: =ROUND(R103*(R12)/100,2) -> 13.21 | GL103: =ROUND(IF(AND(BH103=3,BI103=3,FS103<>0),P103,0),2) -> 0 | GM103: =ROUND(O103+X103+Y103+GK103,2)+GX103 -> 678.82 | GN103: =IF(OR(BI103=0,BI103=1),GM103-GX103,0) -> 0 | GO103: =IF(BI103=2,GM103-GX103,0) -> 678.82 | GP103: =IF(BI103=4,GM103-GX103,0) -> 0 | GR103: 0 | GS103: 0 | GT103: 0 | GV103: =ROUND((GT103),6) -> 0 | GW103: 1 | GX103: =ROUND(HC103*I103,2) -> 0 | HA103: 0 | HB103: 0 | HC103: =GV103*GW103 -> 0 | HS103: 0 | IK103: 0
A104: 17 | B104: 1 | D104: =ROW(EtalonRes!A120) -> 120 | E104: 21 | F104: 4.8-73-2 | G104: Прокладка кабеля напряжением до 35 кВ в готовых траншеях без покрытий при массе 1 м до 2 кг | H104: 100 М КАБЕЛЯ | I104: =ROUND(290.7/100*0.3,9) -> 0.8721 | J104: 0 | K104: =ROUND(290.7/100*0.3,9) -> 0.8721 | O104: =ROUND(CP104,2) -> 7418.14 | P104: =ROUND((ROUND((AC104*AW104*I104),2)*BC104),2) -> 812.05 | Q104: =(ROUND((ROUND(((((ET104*1.05)*1.2))*AV104*I104),2)*BB104),2)+ROUND((ROUND(((AE104-(((EU104*1.05)*1.2)))*AV104*I104),2)*BS104),2)) -> 723.86 | R104: =ROUND((ROUND((AE104*AV104*I104),2)*BS104),2) -> 260.55 | S104: =ROUND((ROUND((AF104*AV104*I104),2)*BA104),2) -> 5882.23 | T104: =ROUND(CU104*I104,2) -> 0 | U104: =CV104*I104 -> 13.83513 | V104: =CW104*I104 -> 0 | W104: =ROUND(CX104*I104,2) -> 0 | X104: =ROUND(CY104,2) -> 5411.65 | Y104: =ROUND(CZ104,2) -> 2529.36 | AA104: 56610029 | AB104: =ROUND((AC104+AD104+AF104),6) -> 380.1782 | AC104: =ROUND(((ES104*1)),6) -> 133.13 | AD104: =ROUND((((((ET104*1.05)*1.2))-(((EU104*1.05)*1.2)))+AE104),6) -> 63.8694 | AE104: =ROUND((((EU104*1.05)*1.2)),6) -> 8.1144 | AF104: =ROUND((((EV104*1.05)*1.2)),6) -> 183.1788 | AG104: =ROUND((AP104),6) -> 0 | AH104: =(((EW104*1.05)*1.2)) -> 14.868 | AI104: =(((EX104*1.05)*1.2)) -> 0 | AJ104: =(AS104) -> 0 | AK104: 329.2 | AL104: 133.13 | AM104: 50.69 | AN104: 6.44 | AO104: 145.38 | AP104: 0 | AQ104: 11.8 | AR104: 0 | AS104: 0 | AT104: 92 | AU104: 43 | AV104: 1.067 | AW104: 1.081 | AZ104: 1 | BA104: 34.51 | BB104: 12.18 | BC104: 6.47 | BH104: 0 | BI104: 2 | BJ104: ТСН-2001.4 Доп. 69, Сб. 8, т. 73, поз. 2 | BM104: 318 | BN104: 0 | BO104: 4.8-73-2 | BP104: 1 | BQ104: 40 | BR104: 0 | BS104: 34.51 | BT104: 1 | BU104: 1 | BV104: 1 | BW104: 1 | BX104: 1 | BZ104: 92 | CA104: 43 | CE104: 30 | CF104: 0 | CG104: 0 | CM104: 0 | CN104: Поправка: О.П. п.3.4.30.г Наименование: В отношении объектов, реализуемых с привлечением средств бюджета города Москвы, затраты, учитывающие усложненные условия производства работ (стесненность, сложность складирования и транспортной логистики, наличие в зоне производства работ действующего технологического оборудования или движения технологического транспорта и т.п.), определяются заказчиком в задании на проектирование при составлении локальных сметных расчетов (смет): для объектов города Москвы, расположенных за пределами Московской кольцевой автомобильной дороги Поправка: Гл.4.Прил.2.2.п.2.2.3_04.00.01.01.001 Наименование: При выполнении работ в охранной зоне воздушных линий электропередачи, в местах прохода коммуникаций электроснабжения в действующих электроустановках, вблизи конструкций и предметов, находящихся под напряжением (в случаях, когда полное снятие напряжения по производственным условиям невозможно), если это связано с ограничением действий рабочих специальными требованиями техники безопасности | CO104: 0 | CP104: =(P104+Q104+S104) -> 7418.14 | CQ104: =ROUND((ROUND((AC104*AW104*1),2)*BC104),2) -> 931.1 | CR104: =(ROUND((ROUND(((((ET104*1.05)*1.2))*AV104*1),2)*BB104),2)+ROUND((ROUND(((AE104-(((EU104*1.05)*1.2)))*AV104*1),2)*BS104),2)) -> 830.07 | CS104: =ROUND((ROUND((AE104*AV104*1),2)*BS104),2) -> 298.86 | CT104: =ROUND((ROUND((AF104*AV104*1),2)*BA104),2) -> 6744.98 | CU104: =AG104 -> 0 | CV104: =(AH104*AV104) -> 15.864156 | CW104: =AI104 -> 0 | CX104: =AJ104 -> 0 | CY104: =S104*(BZ104/100) -> 5411.6516 | CZ104: =S104*(CA104/100) -> 2529.3589 | DB104: 47 | DD104: *1 | DE104: *1,05)*1,2 | DF104: *1,05)*1,2 | DG104: *1,05)*1,2 | DI104: *1,05)*1,2 | DJ104: *1,05)*1,2 | DN104: 112 | DO104: 70 | DP104: 1.067 | DQ104: 1.081 | DU104: 1013 | DV104: 100 М КАБЕЛЯ | DW104: 100 М КАБЕЛЯ | DX104: 1 | EE104: 51696357 | EF104: 40 | EG104: Монтаж оборудования | EH104: 0 | EJ104: 2 | EK104: 318 | EL104: ТСН-2001.4-8. 8-73...8-80 | EM104: ТСН-2001.4-8-3 | EO104: Поправка: О.П. п.3.4.30.г Поправка: Гл.4.Прил.2.2.п.2.2.3_04.00.01.01.001 | EQ104: 131072 | ER104: 329.2 | ES104: 133.13 | ET104: 50.69 | EU104: 6.44 | EV104: 145.38 | EW104: 11.8 | EX104: 0 | EY104: 0 | FQ104: 0 | FR104: 0 | FS104: 0 | FX104: 112 | FY104: 70 | GD104: 0 | GF104: 1434814843 | GG104: 2 | GH104: 1 | GI104: 2 | GJ104: 0 | GK104: =ROUND(R104*(S12)/100,2) -> 416.88 | GL104: =ROUND(IF(AND(BH104=3,BI104=3,FS104<>0),P104,0),2) -> 0 | GM104: =ROUND(O104+X104+Y104+GK104,2)+GX104 -> 15776.03 | GN104: =IF(OR(BI104=0,BI104=1),GM104-GX104,0) -> 0 | GO104: =IF(BI104=2,GM104-GX104,0) -> 15776.03 | GP104: =IF(BI104=4,GM104-GX104,0) -> 0 | GR104: 0 | GS104: 3 | GT104: 0 | GV104: =ROUND((GT104),6) -> 0 | GW104: 1 | GX104: =ROUND(HC104*I104,2) -> 0 | HA104: 0 | HB104: 0 | HC104: =GV104*GW104 -> 0 | HS104: 0 | IK104: 0
A105: 17 | B105: 1 | D105: =ROW(EtalonRes!A134) -> 134 | E105: 22 | F105: 4.8-73-2 | G105: Прокладка кабеля напряжением до 35 кВ в готовых траншеях без покрытий при массе 1 м до 2 кг | H105: 100 М КАБЕЛЯ | I105: =ROUND(290.7/100*0.7,9) -> 2.0349 | J105: 0 | K105: =ROUND(290.7/100*0.7,9) -> 2.0349 | O105: =ROUND(CP105,2) -> 739.85 | P105: =ROUND((ROUND((AC105*AW105*I105),2)*BC105),2) -> 292.85 | Q105: =(ROUND((ROUND((((ET105*1.05))*AV105*I105),2)*BB105),2)+ROUND((ROUND(((AE105-((EU105*1.05)))*AV105*I105),2)*BS105),2)) -> 115.56 | R105: =ROUND((ROUND((AE105*AV105*I105),2)*BS105),2) -> 14.68 | S105: =ROUND((ROUND((AF105*AV105*I105),2)*BA105),2) -> 331.44 | T105: =ROUND(CU105*I105,2) -> 0 | U105: =CV105*I105 -> 26.901643 | V105: =CW105*I105 -> 0 | W105: =ROUND(CX105*I105,2) -> 0 | X105: =ROUND(CY105,2) -> 371.21 | Y105: =ROUND(CZ105,2) -> 232.01 | AA105: 56622490 | AB105: =ROUND((AC105+AD105+AF105),6) -> 339.0035 | AC105: =ROUND((ES105),6) -> 133.13 | AD105: =ROUND(((((ET105*1.05))-((EU105*1.05)))+AE105),6) -> 53.2245 | AE105: =ROUND(((EU105*1.05)),6) -> 6.762 | AF105: =ROUND(((EV105*1.05)),6) -> 152.649 | AG105: =ROUND((AP105),6) -> 0 | AH105: =((EW105*1.05)) -> 12.39 | AI105: =((EX105*1.05)) -> 0 | AJ105: =(AS105) -> 0 | AK105: 329.2 | AL105: 133.13 | AM105: 50.69 | AN105: 6.44 | AO105: 145.38 | AP105: 0 | AQ105: 11.8 | AR105: 0 | AS105: 0 | AT105: 112 | AU105: 70 | AV105: 1.067 | AW105: 1.081 | AZ105: 1 | BA105: 1 | BB105: 1 | BC105: 1 | BH105: 0 | BI105: 2 | BJ105: ТСН-2001.4 Доп. 69, Сб. 8, т. 73, поз. 2 | BM105: 318 | BN105: 0 | BP105: 0 | BQ105: 40 | BR105: 0 | BS105: 1 | BT105: 1 | BU105: 1 | BV105: 1 | BW105: 1 | BX105: 1 | BZ105: 112 | CA105: 70 | CE105: 30 | CF105: 0 | CG105: 0 | CM105: 0 | CN105: Поправка: О.П. п.3.4.30.г Наименование: В отношении объектов, реализуемых с привлечением средств бюджета города Москвы, затраты, учитывающие усложненные условия производства работ (стесненность, сложность складирования и транспортной логистики, наличие в зоне производства работ действующего технологического оборудования или движения технологического транспорта и т.п.), определяются заказчиком в задании на проектирование при составлении локальных сметных расчетов (смет): для объектов города Москвы, расположенных за пределами Московской кольцевой автомобильной дороги | CO105: 0 | CP105: =(P105+Q105+S105) -> 739.85 | CQ105: =ROUND((ROUND((AC105*AW105*1),2)*BC105),2) -> 143.91 | CR105: =(ROUND((ROUND((((ET105*1.05))*AV105*1),2)*BB105),2)+ROUND((ROUND(((AE105-((EU105*1.05)))*AV105*1),2)*BS105),2)) -> 56.79 | CS105: =ROUND((ROUND((AE105*AV105*1),2)*BS105),2) -> 7.22 | CT105: =ROUND((ROUND((AF105*AV105*1),2)*BA105),2) -> 162.88 | CU105: =AG105 -> 0 | CV105: =(AH105*AV105) -> 13.22013 | CW105: =AI105 -> 0 | CX105: =AJ105 -> 0 | CY105: =((S105*BZ105)/100) -> 371.2128 | CZ105: =((S105*CA105)/100) -> 232.008 | DB105: 49 | DE105: *1,05 | DF105: *1,05 | DG105: *1,05 | DI105: *1,05 | DJ105: *1,05 | DN105: 0 | DO105: 0 | DP105: 1 | DQ105: 1 | DU105: 1013 | DV105: 100 М КАБЕЛЯ | DW105: 100 М КАБЕЛЯ | DX105: 1 | EE105: 51696357 | EF105: 40 | EG105: Монтаж оборудования | EH105: 0 | EJ105: 2 | EK105: 318 | EL105: ТСН-2001.4-8. 8-73...8-80 | EM105: ТСН-2001.4-8-3 | EO105: Поправка: О.П. п.3.4.30.г | EQ105: 131072 | ER105: 329.2 | ES105: 133.13 | ET105: 50.69 | EU105: 6.44 | EV105: 145.38 | EW105: 11.8 | EX105: 0 | EY105: 0 | FQ105: 0 | FR105: 0 | FS105: 0 | FX105: 112 | FY105: 70 | GD105: 0 | GF105: 1434814843 | GG105: 2 | GH105: 1 | GI105: -2 | GJ105: 0 | GK105: =ROUND(R105*(R12)/100,2) -> 25.69 | GL105: =ROUND(IF(AND(BH105=3,BI105=3,FS105<>0),P105,0),2) -> 0 | GM105: =ROUND(O105+X105+Y105+GK105,2)+GX105 -> 1368.76 | GN105: =IF(OR(BI105=0,BI105=1),GM105-GX105,0) -> 0 | GO105: =IF(BI105=2,GM105-GX105,0) -> 1368.76 | GP105: =IF(BI105=4,GM105-GX105,0) -> 0 | GR105: 0 | GS105: 0 | GT105: 0 | GV105: =ROUND((GT105),6) -> 0 | GW105: 1 | GX105: =ROUND(HC105*I105,2) -> 0 | HA105: 0 | HB105: 0 | HC105: =GV105*GW105 -> 0 | HS105: 0 | IK105: 0
