Workbook

Sheet Смета по ТСН-2001(с доп.43
A1: =Source!B1 -> Smeta.RU (495) 974-1589
J2: Форма № 4б
A3: ПИР, СМР, ПНР, материалы, оборудование (за исключением замков, предоставляемых Заказчиком) по титулу: Строительство ТП-10/0,4кВ с тр-ми 2х400кВА, 4КЛ-10кВ от ТП-10/0,4кВ луч А,Б до КЛ-10кВ направлением ТП-10/0,4кВ № № 21782 - ТП-10/0,4кВ № 24478 луч А,Б, 8КЛ-0,4кВ от ТП-10/0,4кВ до ВРЩ-0,4кВ №1-3, в т.ч. ПИР: г.Москва, ул.Феодосийская, з/у 7 для нужд МКС – филиала ПАО «Россети Московский регион»
A4: (наименование стройки и/или объекта)
A6: ЛОКАЛЬНАЯ СМЕТА № 02-01-05
A8: Строительство КЛ 0,4 кВ в трубе
A9: (наименование работ и затрат)
A11: =CONCATENATE( "Основание: чертежи № ", Source!J12) -> Основание: чертежи №
I13: В базисном уровне цен | J13: В текущем уровне цен
E14: Сметная стоимость | I14: =I15+I16+I17+I18 -> 102.5 | J14: =J15+J16+J17+J18 -> 1143 | K14: тыс.руб.
E15: Строительные работы | I15: =ROUND((Source!F470)/1000, 2) -> 81.82 | J15: =ROUND((Source!P470)/1000, 2) -> 873.22 | K15: тыс.руб.
E16: Работы по монтажу оборудования | I16: =ROUND((Source!F471)/1000, 2) -> 20.68 | J16: =ROUND((Source!P471)/1000, 2) -> 269.78 | K16: тыс.руб.
E17: Оборудование | I17: =ROUND((Source!F462)/1000, 2) -> 0 | J17: =ROUND((Source!P462)/1000, 2) -> 0 | K17: тыс.руб.
E18: Прочие работы и затраты | I18: =ROUND((Source!F472+Source!F473)/1000, 2) -> 0 | J18: =ROUND((Source!P472+Source!P473)/1000, 2) -> 0 | K18: тыс.руб.
E19: Средства на оплату труда | I19: =(Source!F468+ Source!F467)/1000 -> 4.43823 | J19: =((Source!P468 + Source!P467)/1000) -> 153.16334 | K19: тыс.руб.
E20: Затраты труда | I20: =Source!F475 -> 345.40756 | K20: чел.-ч.
E21: Кроме того:
E22: Возврат материалов | I22: =SUM(Y1:Y191)/1000 -> 0 | J22: =SUM(Z1:Z191)/1000 -> 0 | K22: тыс.руб.
A24: Составлен(а) по ТСН-2001 с учетом Дополнения №: 73
A25: № и период сборника коэффициентов (индексов) пересчета: Коэффициенты к ТСН-2001 МГЭ №212 III квартал 2024 года | AP25: № и период сборника коэффициентов (индексов) пересчета: Коэффициенты к ТСН-2001 МГЭ №212 III квартал 2024 года
A26: № п/п | B26: Шифр расценки и коды ресурсов | C26: Наименование работ и затрат | D26: Ед. изм. | E26: Кол-во единиц | F26: Цена на ед. изм., руб. | G26: Попра- вочные коэффи- циенты | H26: Коэффи- циенты зимних удорожа- ний | I26: Всего в ценах на январь 2000 года, руб. | J26: Коэффи- циенты (индек- сы) пере- счета, нормы НР и СП | K26: ВСЕГО затрат в текущем уровне цен, руб.
A27: 1 | B27: 2 | C27: 3 | D27: 4 | E27: 5 | F27: 6 | G27: 7 | H27: 8 | I27: 9 | J27: 10 | K27: 11
A29: =CONCATENATE("Локальная смета: ",IF(Source!G20<>"Новая локальная смета", Source!G20, "")) -> Локальная смета:
A31: =CONCATENATE("Раздел: ",IF(Source!G24<>"Новый раздел", Source!G24, "")) -> Раздел: Строительные работы
A32: 1 | B32: 3.1-51-1 Поправка: О.П. п.3.4.30.в | C32: Разработка грунта вручную в траншеях глубиной до 2 м без креплений с откосами группа грунтов 1-3 | D32: =Source!DW28 -> 100 м3 грунта | E32: =Source!I28 -> 0.21327 | Q32: =Source!X28 -> 627.93 | R32: =Source!X29 -> 17955.08 | S32: =Source!Y28 -> 460.48 | T32: =Source!Y29 -> 8461.59 | U32: =ROUND((175/100)*ROUND(Source!R28, 2), 2) -> 0 | V32: =ROUND((160/100)*ROUND(Source!R29, 2), 2) -> 0 | AC32: 0
C33: ="Объем: "&Source!I28&"=71,09*"&"0,3/"&"100" -> Объем: 0,21327=71,09*0,3/100
C34: ЗП | F34: =Source!AO28 -> 2042.62 | G34: =Source!DG28 -> )*1,1 | H34: =Source!AV29 -> 1.248 | I34: =Source!S28 -> 598.03 | J34: =IF(Source!BA29<> 0, Source!BA29, 1) -> 34.51 | K34: =Source!S29 -> 20638.02
C35: НР от ЗП | D35: % | E35: =Source!DN29 -> 105 | I35: =SUM(Q32:Q34) -> 627.93 | J35: =Source!BZ29 -> 87 | K35: =SUM(R32:R34) -> 17955.08
C36: СП от ЗП | D36: % | E36: =Source!DO29 -> 77 | I36: =SUM(S32:S35) -> 460.48 | J36: =Source!CA29 -> 41 | K36: =SUM(T32:T35) -> 8461.59
C37: ЗТР | D37: чел-ч | E37: =Source!AQ28 -> 192.7 | G37: =Source!DI28 -> )*1,1 | H37: =Source!AV29 -> 1.248 | I37: =Source!U28 -> 56.418139
C38: Всего по позиции: | H38: =I34+I35+I36+0 -> 1686.44 | J38: =K34+K35+K36+0 -> 47054.69 | O38: =I34+I35+I36+0 -> 1686.44 | P38: =K34+K35+K36+0 -> 47054.69
A40: 2 | B40: 3.1-7-2 Поправка: О.П. п.3.4.30.в | C40: Разработка грунта с погрузкой на автомобили-самосвалы экскаваторами с ковшом вместимостью 0,25 м3 группа грунтов 1-3 | D40: =Source!DW30 -> 100 м3 грунта | E40: =Source!I30 -> 0.2559 | Q40: =Source!X30 -> 9.92 | R40: =Source!X31 -> 328.29 | S40: =Source!Y30 -> 7.79 | T40: =Source!Y31 -> 178.11 | U40: =ROUND((175/100)*ROUND(Source!R30, 2), 2) -> 77.79 | V40: =ROUND((160/100)*ROUND(Source!R31, 2), 2) -> 2454.35 | AC40: 0
C41: ="Объем: "&Source!I30&"=25,59/"&"100" -> Объем: 0,2559=25,59/100
C42: ЗП | F42: =Source!AO30 -> 30.15 | G42: =Source!DG30 -> )*1,1 | H42: =Source!AV31 -> 1.192 | I42: =Source!S30 -> 10.12 | J42: =IF(Source!BA31<> 0, Source!BA31, 1) -> 34.51 | K42: =Source!S31 -> 349.24
C43: ЭМ | F43: =Source!AM30 -> 1340.63 | G43: =Source!DE30 -> )*1,1 | H43: =Source!AV31 -> 1.192 | I43: =Source!Q30 -> 449.83 | J43: =IF(Source!BB31<> 0, Source!BB31, 1) -> 12.15 | K43: =Source!Q31 -> 5465.43
C44: в т.ч. ЗПМ | F44: =Source!AN30 -> 132.48 | G44: =Source!DF30 -> )*1,1 | H44: =Source!AV31 -> 1.192 | I44: =Source!R30 -> 44.45 | J44: =IF(Source!BS31<> 0, Source!BS31, 1) -> 34.51 | K44: =Source!R31 -> 1533.97
C45: НР от ЗП | D45: % | E45: =Source!DN31 -> 98 | I45: =SUM(Q40:Q44) -> 9.92 | J45: =Source!BZ31 -> 94 | K45: =SUM(R40:R44) -> 328.29
C46: СП от ЗП | D46: % | E46: =Source!DO31 -> 77 | I46: =SUM(S40:S45) -> 7.79 | J46: =Source!CA31 -> 51 | K46: =SUM(T40:T45) -> 178.11
C47: НР и СП от ЗПМ | D47: % | E47: =175 -> 175 | I47: =SUM(U40:U46) -> 77.79 | J47: =160 -> 160 | K47: =SUM(V40:V46) -> 2454.35
C48: ЗТР | D48: чел-ч | E48: =Source!AQ30 -> 2.95 | G48: =Source!DI30 -> )*1,1 | H48: =Source!AV31 -> 1.192 | I48: =Source!U30 -> 0.98983144
C49: Всего по позиции: | H49: =I42+I43+I45+I46+I47+0 -> 555.45 | J49: =K42+K43+K45+K46+K47+0 -> 8775.42 | O49: =I42+I43+I45+I46+I47+0 -> 555.45 | P49: =K42+K43+K45+K46+K47+0 -> 8775.42
A51: 3 | B51: 3.1-3-2 Поправка: О.П. п.3.4.30.в | C51: Разработка грунта в отвал экскаваторами с ковшом вместимостью 0,25 м3 группа грунтов 1-3 | D51: =Source!DW32 -> 100 м3 грунта | E51: =Source!I32 -> 0.24173 | Q51: =Source!X32 -> 3.77 | R51: =Source!X33 -> 124.89 | S51: =Source!Y32 -> 2.96 | T51: =Source!Y33 -> 67.76 | U51: =ROUND((175/100)*ROUND(Source!R32, 2), 2) -> 50.98 | V51: =ROUND((160/100)*ROUND(Source!R33, 2), 2) -> 1608.45 | AC51: 0
C52: ="Объем: "&Source!I32&"=71,09/"&"100-"&""&Source!I28&"-"&""&Source!I30&"" -> Объем: 0,24173=71,09/100-0,21327-0,2559
C53: ЗП | F53: =Source!AO32 -> 12.16 | G53: =Source!DG32 -> )*1,1 | H53: =Source!AV33 -> 1.192 | I53: =Source!S32 -> 3.85 | J53: =IF(Source!BA33<> 0, Source!BA33, 1) -> 34.51 | K53: =Source!S33 -> 132.86
C54: ЭМ | F54: =Source!AM32 -> 932.06 | G54: =Source!DE32 -> )*1,1 | H54: =Source!AV33 -> 1.192 | I54: =Source!Q32 -> 295.42 | J54: =IF(Source!BB33<> 0, Source!BB33, 1) -> 12.17 | K54: =Source!Q33 -> 3595.26
C55: в т.ч. ЗПМ | F55: =Source!AN32 -> 91.89 | G55: =Source!DF32 -> )*1,1 | H55: =Source!AV33 -> 1.192 | I55: =Source!R32 -> 29.13 | J55: =IF(Source!BS33<> 0, Source!BS33, 1) -> 34.51 | K55: =Source!R33 -> 1005.28
C56: НР от ЗП | D56: % | E56: =Source!DN33 -> 98 | I56: =SUM(Q51:Q55) -> 3.77 | J56: =Source!BZ33 -> 94 | K56: =SUM(R51:R55) -> 124.89
C57: СП от ЗП | D57: % | E57: =Source!DO33 -> 77 | I57: =SUM(S51:S56) -> 2.96 | J57: =Source!CA33 -> 51 | K57: =SUM(T51:T56) -> 67.76
C58: НР и СП от ЗПМ | D58: % | E58: =175 -> 175 | I58: =SUM(U51:U57) -> 50.98 | J58: =160 -> 160 | K58: =SUM(V51:V57) -> 1608.45
C59: ЗТР | D59: чел-ч | E59: =Source!AQ32 -> 1.19 | G59: =Source!DI32 -> )*1,1 | H59: =Source!AV33 -> 1.192 | I59: =Source!U32 -> 0.37717809
C60: Всего по позиции: | H60: =I53+I54+I56+I57+I58+0 -> 356.98 | J60: =K53+K54+K56+K57+K58+0 -> 5529.22 | O60: =I53+I54+I56+I57+I58+0 -> 356.98 | P60: =K53+K54+K56+K57+K58+0 -> 5529.22
A62: 4 | B62: 3.1-53-1 Поправка: О.П. п.3.4.30.в | C62: Засыпка вручную траншей, пазух котлованов и ям группа грунтов 1-3 | D62: =Source!DW34 -> 100 м3 грунта | E62: =Source!I34 -> 0.1365 | Q62: =Source!X34 -> 206.82 | R62: =Source!X35 -> 5913.76 | S62: =Source!Y34 -> 151.67 | T62: =Source!Y35 -> 2786.95 | U62: =ROUND((175/100)*ROUND(Source!R34, 2), 2) -> 0 | V62: =ROUND((160/100)*ROUND(Source!R35, 2), 2) -> 0 | AC62: 0
C63: ="Объем: "&Source!I34&"=45,5*"&"0,3/"&"100" -> Объем: 0,1365=45,5*0,3/100
C64: ЗП | F64: =Source!AO34 -> 1051.13 | G64: =Source!DG34 -> )*1,1 | H64: =Source!AV35 -> 1.248 | I64: =Source!S34 -> 196.97 | J64: =IF(Source!BA35<> 0, Source!BA35, 1) -> 34.51 | K64: =Source!S35 -> 6797.43
C65: НР от ЗП | D65: % | E65: =Source!DN35 -> 105 | I65: =SUM(Q62:Q64) -> 206.82 | J65: =Source!BZ35 -> 87 | K65: =SUM(R62:R64) -> 5913.76
C66: СП от ЗП | D66: % | E66: =Source!DO35 -> 77 | I66: =SUM(S62:S65) -> 151.67 | J66: =Source!CA35 -> 41 | K66: =SUM(T62:T65) -> 2786.95
C67: ЗТР | D67: чел-ч | E67: =Source!AQ34 -> 107.04 | G67: =Source!DI34 -> )*1,1 | H67: =Source!AV35 -> 1.248 | I67: =Source!U34 -> 20.057926
C68: Всего по позиции: | H68: =I64+I65+I66+0 -> 555.46 | J68: =K64+K65+K66+0 -> 15498.14 | O68: =I64+I65+I66+0 -> 555.46 | P68: =K64+K65+K66+0 -> 15498.14
A70: 5 | B70: 3.1-3-2 Поправка: О.П. п.3.4.30.в Поправка: Сб.3-1.т.3.1.п.3.1.13_03.01.01.22.001 | C70: Разработка грунта в отвал экскаваторами с ковшом вместимостью 0,25 м3 группа грунтов 1-3 | D70: =Source!DW36 -> 100 м3 грунта | E70: =Source!I36 -> 0.3185 | Q70: =Source!X36 -> 2.49 | R70: =Source!X37 -> 82.4 | S70: =Source!Y36 -> 1.96 | T70: =Source!Y37 -> 44.71 | U70: =ROUND((175/100)*ROUND(Source!R36, 2), 2) -> 60.45 | V70: =ROUND((160/100)*ROUND(Source!R37, 2), 2) -> 1907.17 | AC70: 0
C71: ="Объем: "&Source!I36&"=45,5*"&"0,7/"&"100" -> Объем: 0,3185=45,5*0,7/100
C72: ЗП | F72: =Source!AO36 -> 12.16 | G72: =Source!DG36 -> )*1,1)*0,5 | H72: =Source!AV37 -> 1.192 | I72: =Source!S36 -> 2.54 | J72: =IF(Source!BA37<> 0, Source!BA37, 1) -> 34.51 | K72: =Source!S37 -> 87.66
C73: ЭМ | F73: =Source!AM36 -> 932.06 | G73: =Source!DE36 -> )*1,1)*0,9 | H73: =Source!AV37 -> 1.192 | I73: =Source!Q36 -> 350.32 | J73: =IF(Source!BB37<> 0, Source!BB37, 1) -> 12.17 | K73: =Source!Q37 -> 4263.39
C74: в т.ч. ЗПМ | F74: =Source!AN36 -> 91.89 | G74: =Source!DF36 -> )*1,1)*0,9 | H74: =Source!AV37 -> 1.192 | I74: =Source!R36 -> 34.54 | J74: =IF(Source!BS37<> 0, Source!BS37, 1) -> 34.51 | K74: =Source!R37 -> 1191.98
C75: НР от ЗП | D75: % | E75: =Source!DN37 -> 98 | I75: =SUM(Q70:Q74) -> 2.49 | J75: =Source!BZ37 -> 94 | K75: =SUM(R70:R74) -> 82.4
C76: СП от ЗП | D76: % | E76: =Source!DO37 -> 77 | I76: =SUM(S70:S75) -> 1.96 | J76: =Source!CA37 -> 51 | K76: =SUM(T70:T75) -> 44.71
C77: НР и СП от ЗПМ | D77: % | E77: =175 -> 175 | I77: =SUM(U70:U76) -> 60.45 | J77: =160 -> 160 | K77: =SUM(V70:V76) -> 1907.17
C78: ЗТР | D78: чел-ч | E78: =Source!AQ36 -> 1.19 | G78: =Source!DI36 -> )*1,1)*0,5 | H78: =Source!AV37 -> 1.192 | I78: =Source!U36 -> 0.24848223
C79: Всего по позиции: | H79: =I72+I73+I75+I76+I77+0 -> 417.76 | J79: =K72+K73+K75+K76+K77+0 -> 6385.33 | O79: =I72+I73+I75+I76+I77+0 -> 417.76 | P79: =K72+K73+K75+K76+K77+0 -> 6385.33
A81: 6 | B81: 3.34-17-4 Поправка: О.П. п.3.4.30.в | C81: Устройство трубопроводов из асбестоцементных труб с соединением манжетами полиэтиленовыми более 2-х отверстий | D81: =Source!DW38 -> 1 канало-километр трубопровода | E81: =Source!I38 -> 0.033 | Q81: =Source!X38 -> 66.93 | R81: =Source!X39 -> 1897.33 | S81: =Source!Y38 -> 41.83 | T81: =Source!Y39 -> 845.55 | U81: =ROUND((175/100)*ROUND(Source!R38, 2), 2) -> 0 | V81: =ROUND((160/100)*ROUND(Source!R39, 2), 2) -> 0 | AC81: 0
C82: ="Объем: "&Source!I38&"=33/"&"1000" -> Объем: 0,033=33/1000
C83: ЗП | F83: =Source!AO38 -> 1542.84 | G83: =Source!DG38 -> )*1,1 | H83: =Source!AV39 -> 1.067 | I83: =Source!S38 -> 59.76 | J83: =IF(Source!BA39<> 0, Source!BA39, 1) -> 34.51 | K83: =Source!S39 -> 2062.32
C84: МР | F84: =Source!AL38 -> 19554.14 | G84: =Source!DD38 | H84: =Source!AW39 -> 1.081 | I84: =Source!P38 -> 697.55 | J84: =IF(Source!BC39<> 0, Source!BC39, 1) -> 7.65 | K84: =Source!P39 -> 5336.26
C85: НР от ЗП | D85: % | E85: =Source!DN39 -> 112 | I85: =SUM(Q81:Q84) -> 66.93 | J85: =Source!BZ39 -> 92 | K85: =SUM(R81:R84) -> 1897.33
C86: СП от ЗП | D86: % | E86: =Source!DO39 -> 70 | I86: =SUM(S81:S85) -> 41.83 | J86: =Source!CA39 -> 41 | K86: =SUM(T81:T85) -> 845.55
C87: ЗТР | D87: чел-ч | E87: =Source!AQ38 -> 138 | G87: =Source!DI38 -> )*1,1 | H87: =Source!AV39 -> 1.067 | I87: =Source!U38 -> 5.3450298
C88: Всего по позиции: | H88: =I83+I84+I85+I86+0 -> 866.07 | J88: =K83+K84+K85+K86+0 -> 10141.46 | O88: =I83+I84+I85+I86+0 -> 866.07 | P88: =K83+K84+K85+K86+0 -> 10141.46
A90: 9 | B90: 3.34-55-5 Поправка: О.П. п.3.4.30.в | C90: Устройство кабельной канализации из полиэтиленовых труб диаметром 160 мм, первая труба | D90: =Source!DW44 -> 1 км трубопровода | E90: =Source!I44 -> 0.053 | Q90: =Source!X44 -> 109.88 | R90: =Source!X45 -> 3114.92 | S90: =Source!Y44 -> 68.68 | T90: =Source!Y45 -> 1388.17 | U90: =ROUND((175/100)*ROUND(Source!R44, 2), 2) -> 3.1 | V90: =ROUND((160/100)*ROUND(Source!R45, 2), 2) -> 97.73 | AC90: 0
C91: ="Объем: "&Source!I44&"=53/"&"1000" -> Объем: 0,053=53/1000
C92: ЗП | F92: =Source!AO44 -> 1577.19 | G92: =Source!DG44 -> )*1,1 | H92: =Source!AV45 -> 1.067 | I92: =Source!S44 -> 98.11 | J92: =IF(Source!BA45<> 0, Source!BA45, 1) -> 34.51 | K92: =Source!S45 -> 3385.78
C93: ЭМ | F93: =Source!AM44 -> 258.71 | G93: =Source!DE44 -> )*1,1 | H93: =Source!AV45 -> 1.067 | I93: =Source!Q44 -> 16.09 | J93: =IF(Source!BB45<> 0, Source!BB45, 1) -> 11.8 | K93: =Source!Q45 -> 189.86
C94: в т.ч. ЗПМ | F94: =Source!AN44 -> 28.39 | G94: =Source!DF44 -> )*1,1 | H94: =Source!AV45 -> 1.067 | I94: =Source!R44 -> 1.77 | J94: =IF(Source!BS45<> 0, Source!BS45, 1) -> 34.51 | K94: =Source!R45 -> 61.08
C95: НР от ЗП | D95: % | E95: =Source!DN45 -> 112 | I95: =SUM(Q90:Q94) -> 109.88 | J95: =Source!BZ45 -> 92 | K95: =SUM(R90:R94) -> 3114.92
C96: СП от ЗП | D96: % | E96: =Source!DO45 -> 70 | I96: =SUM(S90:S95) -> 68.68 | J96: =Source!CA45 -> 41 | K96: =SUM(T90:T95) -> 1388.17
C97: НР и СП от ЗПМ | D97: % | E97: =175 -> 175 | I97: =SUM(U90:U96) -> 3.1 | J97: =160 -> 160 | K97: =SUM(V90:V96) -> 97.73
C98: ЗТР | D98: чел-ч | E98: =Source!AQ44 -> 147.85 | G98: =Source!DI44 -> )*1,1 | H98: =Source!AV45 -> 1.067 | I98: =Source!U44 -> 9.1971719
C99: Всего по позиции: | H99: =I92+I93+I95+I96+I97+0 -> 295.86 | J99: =K92+K93+K95+K96+K97+0 -> 8176.46 | O99: =I92+I93+I95+I96+I97+0 -> 295.86 | P99: =K92+K93+K95+K96+K97+0 -> 8176.46
A101: 11 | B101: 3.34-55-6 Поправка: О.П. п.3.4.30.в | C101: Добавлять на каждую последующую трубу к позиции 3.34-55-5 | D101: =Source!DW48 -> 1 км трубопровода | E101: =Source!I48 -> 0.34 | Q101: =Source!X48 -> 522 | R101: =Source!X49 -> 14797.35 | S101: =Source!Y48 -> 326.25 | T101: =Source!Y49 -> 6594.47 | U101: =ROUND((175/100)*ROUND(Source!R48, 2), 2) -> 19.62 | V101: =ROUND((160/100)*ROUND(Source!R49, 2), 2) -> 618.98 | AC101: 0
C102: ="Объем: "&Source!I48&"=340/"&"1000" -> Объем: 0,34=340/1000
C103: ЗП | F103: =Source!AO48 -> 1167.92 | G103: =Source!DG48 -> )*1,1 | H103: =Source!AV49 -> 1.067 | I103: =Source!S48 -> 466.07 | J103: =IF(Source!BA49<> 0, Source!BA49, 1) -> 34.51 | K103: =Source!S49 -> 16084.08
C104: ЭМ | F104: =Source!AM48 -> 255.97 | G104: =Source!DE48 -> )*1,1 | H104: =Source!AV49 -> 1.067 | I104: =Source!Q48 -> 102.15 | J104: =IF(Source!BB49<> 0, Source!BB49, 1) -> 11.8 | K104: =Source!Q49 -> 1205.37
C105: в т.ч. ЗПМ | F105: =Source!AN48 -> 28.08 | G105: =Source!DF48 -> )*1,1 | H105: =Source!AV49 -> 1.067 | I105: =Source!R48 -> 11.21 | J105: =IF(Source!BS49<> 0, Source!BS49, 1) -> 34.51 | K105: =Source!R49 -> 386.86
C106: НР от ЗП | D106: % | E106: =Source!DN49 -> 112 | I106: =SUM(Q101:Q105) -> 522 | J106: =Source!BZ49 -> 92 | K106: =SUM(R101:R105) -> 14797.35
C107: СП от ЗП | D107: % | E107: =Source!DO49 -> 70 | I107: =SUM(S101:S106) -> 326.25 | J107: =Source!CA49 -> 41 | K107: =SUM(T101:T106) -> 6594.47
C108: НР и СП от ЗПМ | D108: % | E108: =175 -> 175 | I108: =SUM(U101:U107) -> 19.62 | J108: =160 -> 160 | K108: =SUM(V101:V107) -> 618.98
C109: ЗТР | D109: чел-ч | E109: =Source!AQ48 -> 107.8 | G109: =Source!DI48 -> )*1,1 | H109: =Source!AV49 -> 1.067 | I109: =Source!U48 -> 43.018452
C110: Всего по позиции: | H110: =I103+I104+I106+I107+I108+0 -> 1436.09 | J110: =K103+K104+K106+K107+K108+0 -> 39300.25 | O110: =I103+I104+I106+I107+I108+0 -> 1436.09 | P110: =K103+K104+K106+K107+K108+0 -> 39300.25
A112: 13 | B112: цена поставщика Поправка: О.П. п.3.4.30.в | C112: Трубы Энергопласт ТС DN160х8 мм F4 93,04 = [906,23 / 9,74] | D112: =Source!DW52 -> м | E112: =Source!I52 -> 393 | F112: =Source!AL52 -> 93.04 | G112: =Source!DD52 -> *1,02 | H112: =Source!AW53 -> 1 | I112: =Source!P52 -> 37296.01 | J112: =IF(Source!BC53<> 0, Source!BC53, 1) -> 9.74 | K112: =Source!P53 -> 363263.14 | Q112: =Source!X52 -> 0 | R112: =Source!X53 -> 0 | S112: =Source!Y52 -> 0 | T112: =Source!Y53 -> 0 | U112: =ROUND((175/100)*ROUND(Source!R52, 2), 2) -> 0 | V112: =ROUND((160/100)*ROUND(Source!R53, 2), 2) -> 0 | AC112: 3
C113: Всего по позиции: | H113: =I112+0 -> 37296.01 | J113: =K112+0 -> 363263.14 | O113: =I112+0 -> 37296.01 | P113: =K112+0 -> 363263.14
A115: 14 | B115: 1.12-3-62 Поправка: О.П. п.3.4.30.в | C115: Заглушки (пробки) полиэтиленовые ПКП-2 для каналов кабельной канализации из асбестоцементных труб внутренним диаметром 150 мм | D115: =Source!DW54 -> шт. | E115: =Source!I54 -> 36 | F115: =Source!AL54 -> 3.9 | G115: =Source!DD54 | H115: =Source!AW55 -> 1 | I115: =Source!P54 -> 140.4 | J115: =IF(Source!BC55<> 0, Source!BC55, 1) -> 13.93 | K115: =Source!P55 -> 1955.77 | Q115: =Source!X54 -> 0 | R115: =Source!X55 -> 0 | S115: =Source!Y54 -> 0 | T115: =Source!Y55 -> 0 | U115: =ROUND((175/100)*ROUND(Source!R54, 2), 2) -> 0 | V115: =ROUND((160/100)*ROUND(Source!R55, 2), 2) -> 0 | AC115: 3
C116: Всего по позиции: | H116: =I115+0 -> 140.4 | J116: =K115+0 -> 1955.77 | O116: =I115+0 -> 140.4 | P116: =K115+0 -> 1955.77
...

Sheet Source
A1: 0 | B1: Smeta.RU (495) 974-1589 | D1: _PS_ | F1: 0 | G1: 0 | H1: 0 | I1: Smeta.RU | K1: 1 | L1: 75112 | M1: 10 | N1: 11 | O1: 15 | P1: 0 | Q1: 0
A12: 1 | B12: 489 | C12: 1 | D12: =ROW(A453) -> 453 | E12: 0 | F12: 02-01-05 КЛ 0,4 кВ труба | G12: 02-01-05 Строительство КЛ 0,4 кВ труба | I12: 0 | K12: 0 | L12: 0 | M12: 4098 | O12: 0 | P12: 0 | Q12: 0 | R12: 175 | S12: 160 | T12: 1 | V12: 0 | BB12: 0 | BH12: Сметные нормы списания | BI12: Коды ОКП для ТСН-2001 МГЭ (История развития) | BJ12: 1 | BK12: 1 | BL12: 0 | BM12: 0 | BN12: 1 | BO12: 0 | BP12: 6 | BQ12: 2 | BR12: 1 | BS12: 1 | BT12: 0 | BU12: 0 | BV12: 0 | BW12: 0 | BX12: 0 | BZ12: Типовой расчет для ТСН-2001 МГЭ, Новая методика с выпуска доп. 43 (Строительство), Доп 73 | CA12: История развития для ТСН-2001 (МГЭ) 73 доп от 17.07.2024 | CB12: История развития для ТСН-2001 (МГЭ) 73 доп от 17.07.2024 | CC12: История развития для ТСН-2001 (МГЭ) 73 доп от 17.07.2024 | CD12: История развития для ТСН-2001 (МГЭ) 73 доп от 17.07.2024 | CE12: Поправки для ТСН-2001 от 16.04.2024 г. доп.72 | CF12: 0 | CG12: 0 | CH12: 8 | CK12: 78 | CQ12: Территориальные сметные нормативы для Москвы (ТСН-2001) | CR12: ТЕР | CS12: 41660 | CT12: 1 | CU12: 73 | CY12: 0 | EC12: 0
A15: 15 | B15: 1
A18: 52 | B18: =B453 -> 489 | C18: =C453 -> 1 | D18: =D453 -> 12 | E18: =E453 -> 0 | F18: =F453 -> 02-01-05 КЛ 0,4 кВ труба | G18: =G453 -> 02-01-05 Строительство КЛ 0,4 кВ труба | O18: =O453 -> 94437.81 | P18: =P453 -> 87962.58 | Q18: =Q453 -> 2268.35 | R18: =R453 -> 231.35 | S18: =S453 -> 4206.88 | T18: =T453 -> 0 | U18: =U453 -> 345.40756 | V18: =V453 -> 0 | ... GX18: =GX453 -> 0
A20: 3 | B20: 1 | D20: =ROW(A423) -> 423 | F20: Новая локальная смета | G20: Новая локальная смета | I20: 0 | J20: I-217378-ЭС | K20: 0 | L20: Новая локальная смета | S20: 0 | T20: 0 | V20: 0 | BX20: 0 | CF20: 0 | CG20: 0
A22: 52 | B22: =B423 -> 1 | C22: =C423 -> 3 | D22: =D423 -> 20 | E22: =E423 -> 0 | F22: =F423 -> Новая локальная смета | G22: =G423 -> Новая локальная смета | O22: =O423 -> 94437.81 | P22: =P423 -> 87962.58 | Q22: =Q423 -> 2268.35 | R22: =R423 -> 231.35 | S22: =S423 -> 4206.88 | T22: =T423 -> 0 | U22: =U423 -> 345.40756 | V22: =V423 -> 0 | ... GX22: =GX423 -> 0
A24: 4 | B24: 1 | D24: =ROW(A63) -> 63 | F24: Новый раздел | G24: Строительные работы | I24: 0 | K24: 0 | S24: 0 | T24: 0 | V24: 0 | BX24: 0 | CJ24: 0
A26: 52 | B26: =B63 -> 1 | C26: =C63 -> 4 | D26: =D63 -> 24 | E26: =E63 -> 0 | F26: =F63 -> Новый раздел | G26: =G63 -> Строительные работы | O26: =O63 -> 43246.29 | P26: =P63 -> 40597.03 | Q26: =Q63 -> 1213.81 | R26: =R63 -> 121.1 | S26: =S63 -> 1435.45 | T26: =T63 -> 0 | U26: =U63 -> 135.65221 | V26: =V63 -> 0 | ... GX26: =GX63 -> 0
A28: 17 | B28: 1 | C28: =ROW(SmtRes!A1) -> 1 | D28: =ROW(EtalonRes!A1) -> 1 | E28: 1 | F28: 3.1-51-1 | G28: Разработка грунта вручную в траншеях глубиной до 2 м без креплений с откосами группа грунтов 1-3 | H28: 100 м3 грунта | I28: =ROUND(71.09*0.3/100,9) -> 0.21327 | J28: 0 | K28: =ROUND(71.09*0.3/100,9) -> 0.21327 | O28: =ROUND(CP28,2) -> 598.03 | P28: =ROUND((ROUND((AC28*AW28*I28),2)*BC28),2) -> 0 | Q28: =(ROUND((ROUND((((ET28*1.1))*AV28*I28),2)*BB28),2)+ROUND((ROUND(((AE28-((EU28*1.1)))*AV28*I28),2)*BS28),2)) -> 0 | R28: =ROUND((ROUND((AE28*AV28*I28),2)*BS28),2) -> 0 | S28: =ROUND((ROUND((AF28*AV28*I28),2)*BA28),2) -> 598.03 | T28: =ROUND(CU28*I28,2) -> 0 | U28: =CV28*I28 -> 56.418139 | V28: =CW28*I28 -> 0 | W28: =ROUND(CX28*I28,2) -> 0 | X28: =ROUND(CY28,2) -> 627.93 | Y28: =ROUND(CZ28,2) -> 460.48 | AA28: 56622586 | AB28: =ROUND((AC28+AD28+AF28),6) -> 2246.882 | AC28: =ROUND((ES28),6) -> 0 | AD28: =ROUND(((((ET28*1.1))-((EU28*1.1)))+AE28),6) -> 0 | AE28: =ROUND(((EU28*1.1)),6) -> 0 | AF28: =ROUND(((EV28*1.1)),6) -> 2246.882 | AG28: =ROUND((AP28),6) -> 0 | AH28: =((EW28*1.1)) -> 211.97 | AI28: =((EX28*1.1)) -> 0 | AJ28: =(AS28) -> 0 | AK28: 2042.62 | AL28: 0 | AM28: 0 | AN28: 0 | AO28: 2042.62 | AP28: 0 | AQ28: 192.7 | AR28: 0 | AS28: 0 | AT28: 105 | AU28: 77 | AV28: 1.248 | AW28: 1 | AZ28: 1 | BA28: 1 | BB28: 1 | BC28: 1 | BH28: 0 | BI28: 1 | BJ28: ТСН-2001.3. Доп. 1-42. Сб. 1, т. 51, поз. 1 | BM28: 16 | BN28: 0 | BP28: 0 | BQ28: 30 | BR28: 0 | BS28: 1 | BT28: 1 | BU28: 1 | BV28: 1 | BW28: 1 | BX28: 1 | BZ28: 105 | CA28: 77 | CE28: 30 | CF28: 0 | CG28: 0 | CM28: 0 | CN28: Поправка: О.П. п.3.4.30.в Наименование: В отношении объектов, реализуемых с привлечением средств бюджета города Москвы, затраты, учитывающие усложненные условия производства работ (стесненность, сложность складирования и транспортной логистики, наличие в зоне производства работ действующего технологического оборудования или движения технологического транспорта и т.п.), определяются заказчиком в задании на проектирование при составлении локальных сметных расчетов (смет): для объектов, расположенных за пределами Третьего транспортного кольца города Москвы, но в пределах Московской кольцевой автомобильной дороги | CO28: 0 | CP28: =(P28+Q28+S28) -> 598.03 | CQ28: =ROUND((ROUND((AC28*AW28*1),2)*BC28),2) -> 0 | CR28: =(ROUND((ROUND((((ET28*1.1))*AV28*1),2)*BB28),2)+ROUND((ROUND(((AE28-((EU28*1.1)))*AV28*1),2)*BS28),2)) -> 0 | CS28: =ROUND((ROUND((AE28*AV28*1),2)*BS28),2) -> 0 | CT28: =ROUND((ROUND((AF28*AV28*1),2)*BA28),2) -> 2804.11 | CU28: =AG28 -> 0 | CV28: =(AH28*AV28) -> 264.53856 | CW28: =AI28 -> 0 | CX28: =AJ28 -> 0 | CY28: =((S28*BZ28)/100) -> 627.9315 | CZ28: =((S28*CA28)/100) -> 460.4831 | DE28: )*1,1 | DF28: )*1,1 | DG28: )*1,1 | DI28: )*1,1 | DJ28: )*1,1 | DN28: 0 | DO28: 0 | DP28: 1 | DQ28: 1 | DU28: 1013 | DV28: 100 м3 грунта | DW28: 100 м3 грунта | DX28: 1 | EE28: 51696099 | EF28: 30 | EG28: Строительные работы | EH28: 0 | EJ28: 1 | EK28: 16 | EL28: ТСН-2001.3-1. 1-49...1-55 | EM28: ТСН-2001.3-1-15 | EO28: Поправка: О.П. п.3.4.30.в | EQ28: 131072 | ER28: 2042.62 | ES28: 0 | ET28: 0 | EU28: 0 | EV28: 2042.62 | EW28: 192.7 | EX28: 0 | EY28: 0 | FQ28: 0 | FR28: 0 | FS28: 0 | FX28: 105 | FY28: 77 | GD28: 0 | GF28: -2104602307 | GG28: 2 | GH28: 1 | GI28: -2 | GJ28: 0 | GK28: =ROUND(R28*(R12)/100,2) -> 0 | GL28: =ROUND(IF(AND(BH28=3,BI28=3,FS28<>0),P28,0),2) -> 0 | GM28: =ROUND(O28+X28+Y28+GK28,2)+GX28 -> 1686.44 | GN28: =IF(OR(BI28=0,BI28=1),GM28-GX28,0) -> 1686.44 | GO28: =IF(BI28=2,GM28-GX28,0) -> 0 | GP28: =IF(BI28=4,GM28-GX28,0) -> 0 | GR28: 0 | GS28: 0 | GT28: 0 | GV28: =ROUND((GT28),6) -> 0 | GW28: 1 | GX28: =ROUND(HC28*I28,2) -> 0 | HA28: 0 | HB28: 0 | HC28: =GV28*GW28 -> 0 | HS28: 0 | IK28: 0
A29: 17 | B29: 1 | C29: =ROW(SmtRes!A2) -> 2 | D29: =ROW(EtalonRes!A2) -> 2 | E29: 1 | F29: 3.1-51-1 | G29: Разработка грунта вручную в траншеях глубиной до 2 м без креплений с откосами группа грунтов 1-3 | H29: 100 м3 грунта | I29: =ROUND(71.09*0.3/100,9) -> 0.21327 | J29: 0 | K29: =ROUND(71.09*0.3/100,9) -> 0.21327 | O29: =ROUND(CP29,2) -> 20638.02 | P29: =ROUND((ROUND((AC29*AW29*I29),2)*BC29),2) -> 0 | Q29: =(ROUND((ROUND((((ET29*1.1))*AV29*I29),2)*BB29),2)+ROUND((ROUND(((AE29-((EU29*1.1)))*AV29*I29),2)*BS29),2)) -> 0 | R29: =ROUND((ROUND((AE29*AV29*I29),2)*BS29),2) -> 0 | S29: =ROUND((ROUND((AF29*AV29*I29),2)*BA29),2) -> 20638.02 | T29: =ROUND(CU29*I29,2) -> 0 | U29: =CV29*I29 -> 56.418139 | V29: =CW29*I29 -> 0 | W29: =ROUND(CX29*I29,2) -> 0 | X29: =ROUND(CY29,2) -> 17955.08 | Y29: =ROUND(CZ29,2) -> 8461.59 | AA29: 56616093 | AB29: =ROUND((AC29+AD29+AF29),6) -> 2246.882 | AC29: =ROUND((ES29),6) -> 0 | AD29: =ROUND(((((ET29*1.1))-((EU29*1.1)))+AE29),6) -> 0 | AE29: =ROUND(((EU29*1.1)),6) -> 0 | AF29: =ROUND(((EV29*1.1)),6) -> 2246.882 | AG29: =ROUND((AP29),6) -> 0 | AH29: =((EW29*1.1)) -> 211.97 | AI29: =((EX29*1.1)) -> 0 | AJ29: =(AS29) -> 0 | AK29: 2042.62 | AL29: 0 | AM29: 0 | AN29: 0 | AO29: 2042.62 | AP29: 0 | AQ29: 192.7 | AR29: 0 | AS29: 0 | AT29: 87 | AU29: 41 | AV29: 1.248 | AW29: 1 | AZ29: 1 | BA29: 34.51 | BB29: 1 | BC29: 1 | BH29: 0 | BI29: 1 | BJ29: ТСН-2001.3. Доп. 1-42. Сб. 1, т. 51, поз. 1 | BM29: 16 | BN29: 0 | BO29: 3.1-51-1 | BP29: 1 | BQ29: 30 | BR29: 0 | BS29: 34.51 | BT29: 1 | BU29: 1 | BV29: 1 | BW29: 1 | BX29: 1 | BZ29: 87 | CA29: 41 | CE29: 30 | CF29: 0 | CG29: 0 | CM29: 0 | CN29: Поправка: О.П. п.3.4.30.в Наименование: В отношении объектов, реализуемых с привлечением средств бюджета города Москвы, затраты, учитывающие усложненные условия производства работ (стесненность, сложность складирования и транспортной логистики, наличие в зоне производства работ действующего технологического оборудования или движения технологического транспорта и т.п.), определяются заказчиком в задании на проектирование при составлении локальных сметных расчетов (смет): для объектов, расположенных за пределами Третьего транспортного кольца города Москвы, но в пределах Московской кольцевой автомобильной дороги | CO29: 0 | CP29: =(P29+Q29+S29) -> 20638.02 | CQ29: =ROUND((ROUND((AC29*AW29*1),2)*BC29),2) -> 0 | CR29: =(ROUND((ROUND((((ET29*1.1))*AV29*1),2)*BB29),2)+ROUND((ROUND(((AE29-((EU29*1.1)))*AV29*1),2)*BS29),2)) -> 0 | CS29: =ROUND((ROUND((AE29*AV29*1),2)*BS29),2) -> 0 | CT29: =ROUND((ROUND((AF29*AV29*1),2)*BA29),2) -> 96769.84 | CU29: =AG29 -> 0 | CV29: =(AH29*AV29) -> 264.53856 | CW29: =AI29 -> 0 | CX29: =AJ29 -> 0 | CY29: =S29*(BZ29/100) -> 17955.077 | CZ29: =S29*(CA29/100) -> 8461.5882 | DE29: )*1,1 | DF29: )*1,1 | DG29: )*1,1 | DI29: )*1,1 | DJ29: )*1,1 | DN29: 105 | DO29: 77 | DP29: 1.248 | DQ29: 1 | DU29: 1013 | DV29: 100 м3 грунта | DW29: 100 м3 грунта | DX29: 1 | EE29: 51696099 | EF29: 30 | EG29: Строительные работы | EH29: 0 | EJ29: 1 | EK29: 16 | EL29: ТСН-2001.3-1. 1-49...1-55 | EM29: ТСН-2001.3-1-15 | EO29: Поправка: О.П. п.3.4.30.в | EQ29: 131072 | ER29: 2042.62 | ES29: 0 | ET29: 0 | EU29: 0 | EV29: 2042.62 | EW29: 192.7 | EX29: 0 | EY29: 0 | FQ29: 0 | FR29: 0 | FS29: 0 | FX29: 105 | FY29: 77 | GD29: 0 | GF29: -2104602307 | GG29: 2 | GH29: 1 | GI29: 2 | GJ29: 0 | GK29: =ROUND(R29*(S12)/100,2) -> 0 | GL29: =ROUND(IF(AND(BH29=3,BI29=3,FS29<>0),P29,0),2) -> 0 | GM29: =ROUND(O29+X29+Y29+GK29,2)+GX29 -> 47054.69 | GN29: =IF(OR(BI29=0,BI29=1),GM29-GX29,0) -> 47054.69 | GO29: =IF(BI29=2,GM29-GX29,0) -> 0 | GP29: =IF(BI29=4,GM29-GX29,0) -> 0 | GR29: 0 | GS29: 3 | GT29: 0 | GV29: =ROUND((GT29),6) -> 0 | GW29: 1 | GX29: =ROUND(HC29*I29,2) -> 0 | HA29: 0 | HB29: 0 | HC29: =GV29*GW29 -> 0 | HS29: 0 | IK29: 0
A30: 17 | B30: 1 | C30: =ROW(SmtRes!A6) -> 6 | D30: =ROW(EtalonRes!A5) -> 5 | E30: 2 | F30: 3.1-7-2 | G30: Разработка грунта с погрузкой на автомобили-самосвалы экскаваторами с ковшом вместимостью 0,25 м3 группа грунтов 1-3 | H30: 100 м3 грунта | I30: =ROUND(25.59/100,9) -> 0.2559 | J30: 0 | K30: =ROUND(25.59/100,9) -> 0.2559 | O30: =ROUND(CP30,2) -> 459.95 | P30: =ROUND((ROUND((AC30*AW30*I30),2)*BC30),2) -> 0 | Q30: =(ROUND((ROUND((((ET30*1.1))*AV30*I30),2)*BB30),2)+ROUND((ROUND(((AE30-((EU30*1.1)))*AV30*I30),2)*BS30),2)) -> 449.83 | R30: =ROUND((ROUND((AE30*AV30*I30),2)*BS30),2) -> 44.45 | S30: =ROUND((ROUND((AF30*AV30*I30),2)*BA30),2) -> 10.12 | T30: =ROUND(CU30*I30,2) -> 0 | U30: =CV30*I30 -> 0.98983144 | V30: =CW30*I30 -> 0 | W30: =ROUND(CX30*I30,2) -> 0 | X30: =ROUND(CY30,2) -> 9.92 | Y30: =ROUND(CZ30,2) -> 7.79 | AA30: 56622586 | AB30: =ROUND((AC30+AD30+AF30),6) -> 1507.858 | AC30: =ROUND((ES30),6) -> 0 | AD30: =ROUND(((((ET30*1.1))-((EU30*1.1)))+AE30),6) -> 1474.693 | AE30: =ROUND(((EU30*1.1)),6) -> 145.728 | AF30: =ROUND(((EV30*1.1)),6) -> 33.165 | AG30: =ROUND((AP30),6) -> 0 | AH30: =((EW30*1.1)) -> 3.245 | AI30: =((EX30*1.1)) -> 0 | AJ30: =(AS30) -> 0 | AK30: 1370.78 | AL30: 0 | AM30: 1340.63 | AN30: 132.48 | AO30: 30.15 | AP30: 0 | AQ30: 2.95 | AR30: 0 | AS30: 0 | AT30: 98 | AU30: 77 | AV30: 1.192 | AW30: 1 | AZ30: 1 | BA30: 1 | BB30: 1 | BC30: 1 | BH30: 0 | BI30: 1 | BJ30: ТСН-2001.3 Доп. 70, Сб. 1, т. 7, поз. 2 | BM30: 2 | BN30: 0 | BP30: 0 | BQ30: 30 | BR30: 0 | BS30: 1 | BT30: 1 | BU30: 1 | BV30: 1 | BW30: 1 | BX30: 1 | BZ30: 98 | CA30: 77 | CE30: 30 | CF30: 0 | CG30: 0 | CM30: 0 | CN30: Поправка: О.П. п.3.4.30.в Наименование: В отношении объектов, реализуемых с привлечением средств бюджета города Москвы, затраты, учитывающие усложненные условия производства работ (стесненность, сложность складирования и транспортной логистики, наличие в зоне производства работ действующего технологического оборудования или движения технологического транспорта и т.п.), определяются заказчиком в задании на проектирование при составлении локальных сметных расчетов (смет): для объектов, расположенных за пределами Третьего транспортного кольца города Москвы, но в пределах Московской кольцевой автомобильной дороги | CO30: 0 | CP30: =(P30+Q30+S30) -> 459.95 | CQ30: =ROUND((ROUND((AC30*AW30*1),2)*BC30),2) -> 0 | CR30: =(ROUND((ROUND((((ET30*1.1))*AV30*1),2)*BB30),2)+ROUND((ROUND(((AE30-((EU30*1.1)))*AV30*1),2)*BS30),2)) -> 1757.83 | CS30: =ROUND((ROUND((AE30*AV30*1),2)*BS30),2) -> 173.71 | CT30: =ROUND((ROUND((AF30*AV30*1),2)*BA30),2) -> 39.53 | CU30: =AG30 -> 0 | CV30: =(AH30*AV30) -> 3.86804 | CW30: =AI30 -> 0 | CX30: =AJ30 -> 0 | CY30: =((S30*BZ30)/100) -> 9.9176 | CZ30: =((S30*CA30)/100) -> 7.7924 | DE30: )*1,1 | DF30: )*1,1 | DG30: )*1,1 | DI30: )*1,1 | DJ30: )*1,1 | DN30: 0 | DO30: 0 | DP30: 1 | DQ30: 1 | DU30: 1013 | DV30: 100 м3 грунта | DW30: 100 м3 грунта | DX30: 1 | EE30: 51696085 | EF30: 30 | EG30: Строительные работы | EH30: 0 | EJ30: 1 | EK30: 2 | EL30: ТСН-2001.3-1. 1-1...1-7 | EM30: ТСН-2001.3-1-1 | EO30: Поправка: О.П. п.3.4.30.в | EQ30: 131072 | ER30: 1370.78 | ES30: 0 | ET30: 1340.63 | EU30: 132.48 | EV30: 30.15 | EW30: 2.95 | EX30: 0 | EY30: 0 | FQ30: 0 | FR30: 0 | FS30: 0 | FX30: 98 | FY30: 77 | GD30: 0 | GF30: -1260581983 | GG30: 2 | GH30: 1 | GI30: -2 | GJ30: 0 | GK30: =ROUND(R30*(R12)/100,2) -> 77.79 | GL30: =ROUND(IF(AND(BH30=3,BI30=3,FS30<>0),P30,0),2) -> 0 | GM30: =ROUND(O30+X30+Y30+GK30,2)+GX30 -> 555.45 | GN30: =IF(OR(BI30=0,BI30=1),GM30-GX30,0) -> 555.45 | GO30: =IF(BI30=2,GM30-GX30,0) -> 0 | GP30: =IF(BI30=4,GM30-GX30,0) -> 0 | GR30: 0 | GS30: 0 | GT30: 0 | GV30: =ROUND((GT30),6) -> 0 | GW30: 1 | GX30: =ROUND(HC30*I30,2) -> 0 | HA30: 0 | HB30: 0 | HC30: =GV30*GW30 -> 0 | HS30: 0 | IK30: 0
A31: 17 | B31: 1 | C31: =ROW(SmtRes!A10) -> 10 | D31: =ROW(EtalonRes!A8) -> 8 | E31: 2 | F31: 3.1-7-2 | G31: Разработка грунта с погрузкой на автомобили-самосвалы экскаваторами с ковшом вместимостью 0,25 м3 группа грунтов 1-3 | H31: 100 м3 грунта | I31: =ROUND(25.59/100,9) -> 0.2559 | J31: 0 | K31: =ROUND(25.59/100,9) -> 0.2559 | O31: =ROUND(CP31,2) -> 5814.67 | P31: =ROUND((ROUND((AC31*AW31*I31),2)*BC31),2) -> 0 | Q31: =(ROUND((ROUND((((ET31*1.1))*AV31*I31),2)*BB31),2)+ROUND((ROUND(((AE31-((EU31*1.1)))*AV31*I31),2)*BS31),2)) -> 5465.43 | R31: =ROUND((ROUND((AE31*AV31*I31),2)*BS31),2) -> 1533.97 | S31: =ROUND((ROUND((AF31*AV31*I31),2)*BA31),2) -> 349.24 | T31: =ROUND(CU31*I31,2) -> 0 | U31: =CV31*I31 -> 0.98983144 | V31: =CW31*I31 -> 0 | W31: =ROUND(CX31*I31,2) -> 0 | X31: =ROUND(CY31,2) -> 328.29 | Y31: =ROUND(CZ31,2) -> 178.11 | AA31: 56616093 | AB31: =ROUND((AC31+AD31+AF31),6) -> 1507.858 | AC31: =ROUND((ES31),6) -> 0 | AD31: =ROUND(((((ET31*1.1))-((EU31*1.1)))+AE31),6) -> 1474.693 | AE31: =ROUND(((EU31*1.1)),6) -> 145.728 | AF31: =ROUND(((EV31*1.1)),6) -> 33.165 | AG31: =ROUND((AP31),6) -> 0 | AH31: =((EW31*1.1)) -> 3.245 | AI31: =((EX31*1.1)) -> 0 | AJ31: =(AS31) -> 0 | AK31: 1370.78 | AL31: 0 | AM31: 1340.63 | AN31: 132.48 | AO31: 30.15 | AP31: 0 | AQ31: 2.95 | AR31: 0 | AS31: 0 | AT31: 94 | AU31: 51 | AV31: 1.192 | AW31: 1 | AZ31: 1 | BA31: 34.51 | BB31: 12.15 | BC31: 1 | BH31: 0 | BI31: 1 | BJ31: ТСН-2001.3 Доп. 70, Сб. 1, т. 7, поз. 2 | BM31: 2 | BN31: 0 | BO31: 3.1-7-2 | BP31: 1 | BQ31: 30 | BR31: 0 | BS31: 34.51 | BT31: 1 | BU31: 1 | BV31: 1 | BW31: 1 | BX31: 1 | BZ31: 94 | CA31: 51 | CE31: 30 | CF31: 0 | CG31: 0 | CM31: 0 | CN31: Поправка: О.П. п.3.4.30.в Наименование: В отношении объектов, реализуемых с привлечением средств бюджета города Москвы, затраты, учитывающие усложненные условия производства работ (стесненность, сложность складирования и транспортной логистики, наличие в зоне производства работ действующего технологического оборудования или движения технологического транспорта и т.п.), определяются заказчиком в задании на проектирование при составлении локальных сметных расчетов (смет): для объектов, расположенных за пределами Третьего транспортного кольца города Москвы, но в пределах Московской кольцевой автомобильной дороги | CO31: 0 | CP31: =(P31+Q31+S31) -> 5814.67 | CQ31: =ROUND((ROUND((AC31*AW31*1),2)*BC31),2) -> 0 | CR31: =(ROUND((ROUND((((ET31*1.1))*AV31*1),2)*BB31),2)+ROUND((ROUND(((AE31-((EU31*1.1)))*AV31*1),2)*BS31),2)) -> 21357.63 | CS31: =ROUND((ROUND((AE31*AV31*1),2)*BS31),2) -> 5994.73 | CT31: =ROUND((ROUND((AF31*AV31*1),2)*BA31),2) -> 1364.18 | CU31: =AG31 -> 0 | CV31: =(AH31*AV31) -> 3.86804 | CW31: =AI31 -> 0 | CX31: =AJ31 -> 0 | CY31: =S31*(BZ31/100) -> 328.2856 | CZ31: =S31*(CA31/100) -> 178.1124 | DE31: )*1,1 | DF31: )*1,1 | DG31: )*1,1 | DI31: )*1,1 | DJ31: )*1,1 | DN31: 98 | DO31: 77 | DP31: 1.192 | DQ31: 1 | DU31: 1013 | DV31: 100 м3 грунта | DW31: 100 м3 грунта | DX31: 1 | EE31: 51696085 | EF31: 30 | EG31: Строительные работы | EH31: 0 | EJ31: 1 | EK31: 2 | EL31: ТСН-2001.3-1. 1-1...1-7 | EM31: ТСН-2001.3-1-1 | EO31: Поправка: О.П. п.3.4.30.в | EQ31: 131072 | ER31: 1370.78 | ES31: 0 | ET31: 1340.63 | EU31: 132.48 | EV31: 30.15 | EW31: 2.95 | EX31: 0 | EY31: 0 | FQ31: 0 | FR31: 0 | FS31: 0 | FX31: 98 | FY31: 77 | GD31: 0 | GF31: -1260581983 | GG31: 2 | GH31: 1 | GI31: 2 | GJ31: 0 | GK31: =ROUND(R31*(S12)/100,2) -> 2454.35 | GL31: =ROUND(IF(AND(BH31=3,BI31=3,FS31<>0),P31,0),2) -> 0 | GM31: =ROUND(O31+X31+Y31+GK31,2)+GX31 -> 8775.42 | GN31: =IF(OR(BI31=0,BI31=1),GM31-GX31,0) -> 8775.42 | GO31: =IF(BI31=2,GM31-GX31,0) -> 0 | GP31: =IF(BI31=4,GM31-GX31,0) -> 0 | GR31: 0 | GS31: 3 | GT31: 0 | GV31: =ROUND((GT31),6) -> 0 | GW31: 1 | GX31: =ROUND(HC31*I31,2) -> 0 | HA31: 0 | HB31: 0 | HC31: =GV31*GW31 -> 0 | HS31: 0 | IK31: 0
A32: 17 | B32: 1 | C32: =ROW(SmtRes!A12) -> 12 | D32: =ROW(EtalonRes!A10) -> 10 | E32: 3 | F32: 3.1-3-2 | G32: Разработка грунта в отвал экскаваторами с ковшом вместимостью 0,25 м3 группа грунтов 1-3 | H32: 100 м3 грунта | I32: =ROUND(71.09/100-I28-I30,9) -> 0.24173 | J32: 0 | K32: =ROUND(71.09/100-I28-I30,9) -> 0.24173 | O32: =ROUND(CP32,2) -> 299.27 | P32: =ROUND((ROUND((AC32*AW32*I32),2)*BC32),2) -> 0 | Q32: =(ROUND((ROUND((((ET32*1.1))*AV32*I32),2)*BB32),2)+ROUND((ROUND(((AE32-((EU32*1.1)))*AV32*I32),2)*BS32),2)) -> 295.42 | R32: =ROUND((ROUND((AE32*AV32*I32),2)*BS32),2) -> 29.13 | S32: =ROUND((ROUND((AF32*AV32*I32),2)*BA32),2) -> 3.85 | T32: =ROUND(CU32*I32,2) -> 0 | U32: =CV32*I32 -> 0.37717809 | V32: =CW32*I32 -> 0 | W32: =ROUND(CX32*I32,2) -> 0 | X32: =ROUND(CY32,2) -> 3.77 | Y32: =ROUND(CZ32,2) -> 2.96 | AA32: 56622586 | AB32: =ROUND((AC32+AD32+AF32),6) -> 1038.642 | AC32: =ROUND((ES32),6) -> 0 | AD32: =ROUND(((((ET32*1.1))-((EU32*1.1)))+AE32),6) -> 1025.266 | AE32: =ROUND(((EU32*1.1)),6) -> 101.079 | AF32: =ROUND(((EV32*1.1)),6) -> 13.376 | AG32: =ROUND((AP32),6) -> 0 | AH32: =((EW32*1.1)) -> 1.309 | AI32: =((EX32*1.1)) -> 0 | AJ32: =(AS32) -> 0 | AK32: 944.22 | AL32: 0 | AM32: 932.06 | AN32: 91.89 | AO32: 12.16 | AP32: 0 | AQ32: 1.19 | AR32: 0 | AS32: 0 | AT32: 98 | AU32: 77 | AV32: 1.192 | AW32: 1 | AZ32: 1 | BA32: 1 | BB32: 1 | BC32: 1 | BH32: 0 | BI32: 1 | BJ32: ТСН-2001.3 Доп. 68, Сб. 1, т. 3, поз. 2 | BM32: 2 | BN32: 0 | BP32: 0 | BQ32: 30 | BR32: 0 | BS32: 1 | BT32: 1 | BU32: 1 | BV32: 1 | BW32: 1 | BX32: 1 | BZ32: 98 | CA32: 77 | CE32: 30 | CF32: 0 | CG32: 0 | CM32: 0 | CN32: Поправка: О.П. п.3.4.30.в Наименование: В отношении объектов, реализуемых с привлечением средств бюджета города Москвы, затраты, учитывающие усложненные условия производства работ (стесненность, сложность складирования и транспортной логистики, наличие в зоне производства работ действующего технологического оборудования или движения технологического транспорта и т.п.), определяются заказчиком в задании на проектирование при составлении локальных сметных расчетов (смет): для объектов, расположенных за пределами Третьего транспортного кольца города Москвы, но в пределах Московской кольцевой автомобильной дороги | CO32: 0 | CP32: =(P32+Q32+S32) -> 299.27 | CQ32: =ROUND((ROUND((AC32*AW32*1),2)*BC32),2) -> 0 | CR32: =(ROUND((ROUND((((ET32*1.1))*AV32*1),2)*BB32),2)+ROUND((ROUND(((AE32-((EU32*1.1)))*AV32*1),2)*BS32),2)) -> 1222.12 | CS32: =ROUND((ROUND((AE32*AV32*1),2)*BS32),2) -> 120.49 | CT32: =ROUND((ROUND((AF32*AV32*1),2)*BA32),2) -> 15.94 | CU32: =AG32 -> 0 | CV32: =(AH32*AV32) -> 1.560328 | CW32: =AI32 -> 0 | CX32: =AJ32 -> 0 | CY32: =((S32*BZ32)/100) -> 3.773 | CZ32: =((S32*CA32)/100) -> 2.9645 | DE32: )*1,1 | DF32: )*1,1 | DG32: )*1,1 | DI32: )*1,1 | DJ32: )*1,1 | DN32: 0 | DO32: 0 | DP32: 1 | DQ32: 1 | DU32: 1013 | DV32: 100 м3 грунта | DW32: 100 м3 грунта | DX32: 1 | EE32: 51696085 | EF32: 30 | EG32: Строительные работы | EH32: 0 | EJ32: 1 | EK32: 2 | EL32: ТСН-2001.3-1. 1-1...1-7 | EM32: ТСН-2001.3-1-1 | EO32: Поправка: О.П. п.3.4.30.в | EQ32: 131072 | ER32: 944.22 | ES32: 0 | ET32: 932.06 | EU32: 91.89 | EV32: 12.16 | EW32: 1.19 | EX32: 0 | EY32: 0 | FQ32: 0 | FR32: 0 | FS32: 0 | FX32: 98 | FY32: 77 | GD32: 0 | GF32: 864155608 | GG32: 2 | GH32: 1 | GI32: -2 | GJ32: 0 | GK32: =ROUND(R32*(R12)/100,2) -> 50.98 | GL32: =ROUND(IF(AND(BH32=3,BI32=3,FS32<>0),P32,0),2) -> 0 | GM32: =ROUND(O32+X32+Y32+GK32,2)+GX32 -> 356.98 | GN32: =IF(OR(BI32=0,BI32=1),GM32-GX32,0) -> 356.98 | GO32: =IF(BI32=2,GM32-GX32,0) -> 0 | GP32: =IF(BI32=4,GM32-GX32,0) -> 0 | GR32: 0 | GS32: 0 | GT32: 0 | GV32: =ROUND((GT32),6) -> 0 | GW32: 1 | GX32: =ROUND(HC32*I32,2) -> 0 | HA32: 0 | HB32: 0 | HC32: =GV32*GW32 -> 0 | HS32: 0 | IK32: 0
A33: 17 | B33: 1 | C33: =ROW(SmtRes!A14) -> 14 | D33: =ROW(EtalonRes!A12) -> 12 | E33: 3 | F33: 3.1-3-2 | G33: Разработка грунта в отвал экскаваторами с ковшом вместимостью 0,25 м3 группа грунтов 1-3 | H33: 100 м3 грунта | I33: =ROUND(71.09/100-I29-I31,9) -> 0.24173 | J33: 0 | K33: =ROUND(71.09/100-I29-I31,9) -> 0.24173 | O33: =ROUND(CP33,2) -> 3728.12 | P33: =ROUND((ROUND((AC33*AW33*I33),2)*BC33),2) -> 0 | Q33: =(ROUND((ROUND((((ET33*1.1))*AV33*I33),2)*BB33),2)+ROUND((ROUND(((AE33-((EU33*1.1)))*AV33*I33),2)*BS33),2)) -> 3595.26 | R33: =ROUND((ROUND((AE33*AV33*I33),2)*BS33),2) -> 1005.28 | S33: =ROUND((ROUND((AF33*AV33*I33),2)*BA33),2) -> 132.86 | T33: =ROUND(CU33*I33,2) -> 0 | U33: =CV33*I33 -> 0.37717809 | V33: =CW33*I33 -> 0 | W33: =ROUND(CX33*I33,2) -> 0 | X33: =ROUND(CY33,2) -> 124.89 | Y33: =ROUND(CZ33,2) -> 67.76 | AA33: 56616093 | AB33: =ROUND((AC33+AD33+AF33),6) -> 1038.642 | AC33: =ROUND((ES33),6) -> 0 | AD33: =ROUND(((((ET33*1.1))-((EU33*1.1)))+AE33),6) -> 1025.266 | AE33: =ROUND(((EU33*1.1)),6) -> 101.079 | AF33: =ROUND(((EV33*1.1)),6) -> 13.376 | AG33: =ROUND((AP33),6) -> 0 | AH33: =((EW33*1.1)) -> 1.309 | AI33: =((EX33*1.1)) -> 0 | AJ33: =(AS33) -> 0 | AK33: 944.22 | AL33: 0 | AM33: 932.06 | AN33: 91.89 | AO33: 12.16 | AP33: 0 | AQ33: 1.19 | AR33: 0 | AS33: 0 | AT33: 94 | AU33: 51 | AV33: 1.192 | AW33: 1 | AZ33: 1 | BA33: 34.51 | BB33: 12.17 | BC33: 1 | BH33: 0 | BI33: 1 | BJ33: ТСН-2001.3 Доп. 68, Сб. 1, т. 3, поз. 2 | BM33: 2 | BN33: 0 | BO33: 3.1-3-2 | BP33: 1 | BQ33: 30 | BR33: 0 | BS33: 34.51 | BT33: 1 | BU33: 1 | BV33: 1 | BW33: 1 | BX33: 1 | BZ33: 94 | CA33: 51 | CE33: 30 | CF33: 0 | CG33: 0 | CM33: 0 | CN33: Поправка: О.П. п.3.4.30.в Наименование: В отношении объектов, реализуемых с привлечением средств бюджета города Москвы, затраты, учитывающие усложненные условия производства работ (стесненность, сложность складирования и транспортной логистики, наличие в зоне производства работ действующего технологического оборудования или движения технологического транспорта и т.п.), определяются заказчиком в задании на проектирование при составлении локальных сметных расчетов (смет): для объектов, расположенных за пределами Третьего транспортного кольца города Москвы, но в пределах Московской кольцевой автомобильной дороги | CO33: 0 | CP33: =(P33+Q33+S33) -> 3728.12 | CQ33: =ROUND((ROUND((AC33*AW33*1),2)*BC33),2) -> 0 | CR33: =(ROUND((ROUND((((ET33*1.1))*AV33*1),2)*BB33),2)+ROUND((ROUND(((AE33-((EU33*1.1)))*AV33*1),2)*BS33),2)) -> 14873.2 | CS33: =ROUND((ROUND((AE33*AV33*1),2)*BS33),2) -> 4158.11 | CT33: =ROUND((ROUND((AF33*AV33*1),2)*BA33),2) -> 550.09 | CU33: =AG33 -> 0 | CV33: =(AH33*AV33) -> 1.560328 | CW33: =AI33 -> 0 | CX33: =AJ33 -> 0 | CY33: =S33*(BZ33/100) -> 124.8884 | CZ33: =S33*(CA33/100) -> 67.7586 | DE33: )*1,1 | DF33: )*1,1 | DG33: )*1,1 | DI33: )*1,1 | DJ33: )*1,1 | DN33: 98 | DO33: 77 | DP33: 1.192 | DQ33: 1 | DU33: 1013 | DV33: 100 м3 грунта | DW33: 100 м3 грунта | DX33: 1 | EE33: 51696085 | EF33: 30 | EG33: Строительные работы | EH33: 0 | EJ33: 1 | EK33: 2 | EL33: ТСН-2001.3-1. 1-1...1-7 | EM33: ТСН-2001.3-1-1 | EO33: Поправка: О.П. п.3.4.30.в | EQ33: 131072 | ER33: 944.22 | ES33: 0 | ET33: 932.06 | EU33: 91.89 | EV33: 12.16 | EW33: 1.19 | EX33: 0 | EY33: 0 | FQ33: 0 | FR33: 0 | FS33: 0 | FX33: 98 | FY33: 77 | GD33: 0 | GF33: 864155608 | GG33: 2 | GH33: 1 | GI33: 2 | GJ33: 0 | GK33: =ROUND(R33*(S12)/100,2) -> 1608.45 | GL33: =ROUND(IF(AND(BH33=3,BI33=3,FS33<>0),P33,0),2) -> 0 | GM33: =ROUND(O33+X33+Y33+GK33,2)+GX33 -> 5529.22 | GN33: =IF(OR(BI33=0,BI33=1),GM33-GX33,0) -> 5529.22 | GO33: =IF(BI33=2,GM33-GX33,0) -> 0 | GP33: =IF(BI33=4,GM33-GX33,0) -> 0 | GR33: 0 | GS33: 3 | GT33: 0 | GV33: =ROUND((GT33),6) -> 0 | GW33: 1 | GX33: =ROUND(HC33*I33,2) -> 0 | HA33: 0 | HB33: 0 | HC33: =GV33*GW33 -> 0 | HS33: 0 | IK33: 0
A34: 17 | B34: 1 | C34: =ROW(SmtRes!A15) -> 15 | D34: =ROW(EtalonRes!A13) -> 13 | E34: 4 | F34: 3.1-53-1 | G34: Засыпка вручную траншей, пазух котлованов и ям группа грунтов 1-3 | H34: 100 м3 грунта | I34: =ROUND(45.5*0.3/100,9) -> 0.1365 | J34: 0 | K34: =ROUND(45.5*0.3/100,9) -> 0.1365 | O34: =ROUND(CP34,2) -> 196.97 | P34: =ROUND((ROUND((AC34*AW34*I34),2)*BC34),2) -> 0 | Q34: =(ROUND((ROUND((((ET34*1.1))*AV34*I34),2)*BB34),2)+ROUND((ROUND(((AE34-((EU34*1.1)))*AV34*I34),2)*BS34),2)) -> 0 | R34: =ROUND((ROUND((AE34*AV34*I34),2)*BS34),2) -> 0 | S34: =ROUND((ROUND((AF34*AV34*I34),2)*BA34),2) -> 196.97 | T34: =ROUND(CU34*I34,2) -> 0 | U34: =CV34*I34 -> 20.057926 | V34: =CW34*I34 -> 0 | W34: =ROUND(CX34*I34,2) -> 0 | X34: =ROUND(CY34,2) -> 206.82 | Y34: =ROUND(CZ34,2) -> 151.67 | AA34: 56622586 | AB34: =ROUND((AC34+AD34+AF34),6) -> 1156.243 | AC34: =ROUND((ES34),6) -> 0 | AD34: =ROUND(((((ET34*1.1))-((EU34*1.1)))+AE34),6) -> 0 | AE34: =ROUND(((EU34*1.1)),6) -> 0 | AF34: =ROUND(((EV34*1.1)),6) -> 1156.243 | AG34: =ROUND((AP34),6) -> 0 | AH34: =((EW34*1.1)) -> 117.744 | AI34: =((EX34*1.1)) -> 0 | AJ34: =(AS34) -> 0 | AK34: 1051.13 | AL34: 0 | AM34: 0 | AN34: 0 | AO34: 1051.13 | AP34: 0 | AQ34: 107.04 | AR34: 0 | AS34: 0 | AT34: 105 | AU34: 77 | AV34: 1.248 | AW34: 1 | AZ34: 1 | BA34: 1 | BB34: 1 | BC34: 1 | BH34: 0 | BI34: 1 | BJ34: ТСН-2001.3. Доп. 1-42. Сб. 1, т. 53, поз. 1 | BM34: 16 | BN34: 0 | BP34: 0 | BQ34: 30 | BR34: 0 | BS34: 1 | BT34: 1 | BU34: 1 | BV34: 1 | BW34: 1 | BX34: 1 | BZ34: 105 | CA34: 77 | CE34: 30 | CF34: 0 | CG34: 0 | CM34: 0 | CN34: Поправка: О.П. п.3.4.30.в Наименование: В отношении объектов, реализуемых с привлечением средств бюджета города Москвы, затраты, учитывающие усложненные условия производства работ (стесненность, сложность складирования и транспортной логистики, наличие в зоне производства работ действующего технологического оборудования или движения технологического транспорта и т.п.), определяются заказчиком в задании на проектирование при составлении локальных сметных расчетов (смет): для объектов, расположенных за пределами Третьего транспортного кольца города Москвы, но в пределах Московской кольцевой автомобильной дороги | CO34: 0 | CP34: =(P34+Q34+S34) -> 196.97 | CQ34: =ROUND((ROUND((AC34*AW34*1),2)*BC34),2) -> 0 | CR34: =(ROUND((ROUND((((ET34*1.1))*AV34*1),2)*BB34),2)+ROUND((ROUND(((AE34-((EU34*1.1)))*AV34*1),2)*BS34),2)) -> 0 | CS34: =ROUND((ROUND((AE34*AV34*1),2)*BS34),2) -> 0 | CT34: =ROUND((ROUND((AF34*AV34*1),2)*BA34),2) -> 1442.99 | CU34: =AG34 -> 0 | CV34: =(AH34*AV34) -> 146.94451 | CW34: =AI34 -> 0 | CX34: =AJ34 -> 0 | CY34: =((S34*BZ34)/100) -> 206.8185 | CZ34: =((S34*CA34)/100) -> 151.6669 | DE34: )*1,1 | DF34: )*1,1 | DG34: )*1,1 | DI34: )*1,1 | DJ34: )*1,1 | DN34: 0 | DO34: 0 | DP34: 1 | DQ34: 1 | DU34: 1013 | DV34: 100 м3 грунта | DW34: 100 м3 грунта | DX34: 1 | EE34: 51696099 | EF34: 30 | EG34: Строительные работы | EH34: 0 | EJ34: 1 | EK34: 16 | EL34: ТСН-2001.3-1. 1-49...1-55 | EM34: ТСН-2001.3-1-15 | EO34: Поправка: О.П. п.3.4.30.в | EQ34: 131072 | ER34: 1051.13 | ES34: 0 | ET34: 0 | EU34: 0 | EV34: 1051.13 | EW34: 107.04 | EX34: 0 | EY34: 0 | FQ34: 0 | FR34: 0 | FS34: 0 | FX34: 105 | FY34: 77 | GD34: 0 | GF34: 1725378853 | GG34: 2 | GH34: 1 | GI34: -2 | GJ34: 0 | GK34: =ROUND(R34*(R12)/100,2) -> 0 | GL34: =ROUND(IF(AND(BH34=3,BI34=3,FS34<>0),P34,0),2) -> 0 | GM34: =ROUND(O34+X34+Y34+GK34,2)+GX34 -> 555.46 | GN34: =IF(OR(BI34=0,BI34=1),GM34-GX34,0) -> 555.46 | GO34: =IF(BI34=2,GM34-GX34,0) -> 0 | GP34: =IF(BI34=4,GM34-GX34,0) -> 0 | GR34: 0 | GS34: 0 | GT34: 0 | GV34: =ROUND((GT34),6) -> 0 | GW34: 1 | GX34: =ROUND(HC34*I34,2) -> 0 | HA34: 0 | HB34: 0 | HC34: =GV34*GW34 -> 0 | HS34: 0 | IK34: 0
A35: 17 | B35: 1 | C35: =ROW(SmtRes!A16) -> 16 | D35: =ROW(EtalonRes!A14) -> 14 | E35: 4 | F35: 3.1-53-1 | G35: Засыпка вручную траншей, пазух котлованов и ям группа грунтов 1-3 | H35: 100 м3 грунта | I35: =ROUND(45.5*0.3/100,9) -> 0.1365 | J35: 0 | K35: =ROUND(45.5*0.3/100,9) -> 0.1365 | O35: =ROUND(CP35,2) -> 6797.43 | P35: =ROUND((ROUND((AC35*AW35*I35),2)*BC35),2) -> 0 | Q35: =(ROUND((ROUND((((ET35*1.1))*AV35*I35),2)*BB35),2)+ROUND((ROUND(((AE35-((EU35*1.1)))*AV35*I35),2)*BS35),2)) -> 0 | R35: =ROUND((ROUND((AE35*AV35*I35),2)*BS35),2) -> 0 | S35: =ROUND((ROUND((AF35*AV35*I35),2)*BA35),2) -> 6797.43 | T35: =ROUND(CU35*I35,2) -> 0 | U35: =CV35*I35 -> 20.057926 | V35: =CW35*I35 -> 0 | W35: =ROUND(CX35*I35,2) -> 0 | X35: =ROUND(CY35,2) -> 5913.76 | Y35: =ROUND(CZ35,2) -> 2786.95 | AA35: 56616093 | AB35: =ROUND((AC35+AD35+AF35),6) -> 1156.243 | AC35: =ROUND((ES35),6) -> 0 | AD35: =ROUND(((((ET35*1.1))-((EU35*1.1)))+AE35),6) -> 0 | AE35: =ROUND(((EU35*1.1)),6) -> 0 | AF35: =ROUND(((EV35*1.1)),6) -> 1156.243 | AG35: =ROUND((AP35),6) -> 0 | AH35: =((EW35*1.1)) -> 117.744 | AI35: =((EX35*1.1)) -> 0 | AJ35: =(AS35) -> 0 | AK35: 1051.13 | AL35: 0 | AM35: 0 | AN35: 0 | AO35: 1051.13 | AP35: 0 | AQ35: 107.04 | AR35: 0 | AS35: 0 | AT35: 87 | AU35: 41 | AV35: 1.248 | AW35: 1 | AZ35: 1 | BA35: 34.51 | BB35: 1 | BC35: 1 | BH35: 0 | BI35: 1 | BJ35: ТСН-2001.3. Доп. 1-42. Сб. 1, т. 53, поз. 1 | BM35: 16 | BN35: 0 | BO35: 3.1-53-1 | BP35: 1 | BQ35: 30 | BR35: 0 | BS35: 34.51 | BT35: 1 | BU35: 1 | BV35: 1 | BW35: 1 | BX35: 1 | BZ35: 87 | CA35: 41 | CE35: 30 | CF35: 0 | CG35: 0 | CM35: 0 | CN35: Поправка: О.П. п.3.4.30.в Наименование: В отношении объектов, реализуемых с привлечением средств бюджета города Москвы, затраты, учитывающие усложненные условия производства работ (стесненность, сложность складирования и транспортной логистики, наличие в зоне производства работ действующего технологического оборудования или движения технологического транспорта и т.п.), определяются заказчиком в задании на проектирование при составлении локальных сметных расчетов (смет): для объектов, расположенных за пределами Третьего транспортного кольца города Москвы, но в пределах Московской кольцевой автомобильной дороги | CO35: 0 | CP35: =(P35+Q35+S35) -> 6797.43 | CQ35: =ROUND((ROUND((AC35*AW35*1),2)*BC35),2) -> 0 | CR35: =(ROUND((ROUND((((ET35*1.1))*AV35*1),2)*BB35),2)+ROUND((ROUND(((AE35-((EU35*1.1)))*AV35*1),2)*BS35),2)) -> 0 | CS35: =ROUND((ROUND((AE35*AV35*1),2)*BS35),2) -> 0 | CT35: =ROUND((ROUND((AF35*AV35*1),2)*BA35),2) -> 49797.58 | CU35: =AG35 -> 0 | CV35: =(AH35*AV35) -> 146.94451 | CW35: =AI35 -> 0 | CX35: =AJ35 -> 0 | CY35: =S35*(BZ35/100) -> 5913.7641 | CZ35: =S35*(CA35/100) -> 2786.9463 | DE35: )*1,1 | DF35: )*1,1 | DG35: )*1,1 | DI35: )*1,1 | DJ35: )*1,1 | DN35: 105 | DO35: 77 | DP35: 1.248 | DQ35: 1 | DU35: 1013 | DV35: 100 м3 грунта | DW35: 100 м3 грунта | DX35: 1 | EE35: 51696099 | EF35: 30 | EG35: Строительные работы | EH35: 0 | EJ35: 1 | EK35: 16 | EL35: ТСН-2001.3-1. 1-49...1-55 | EM35: ТСН-2001.3-1-15 | EO35: Поправка: О.П. п.3.4.30.в | EQ35: 131072 | ER35: 1051.13 | ES35: 0 | ET35: 0 | EU35: 0 | EV35: 1051.13 | EW35: 107.04 | EX35: 0 | EY35: 0 | FQ35: 0 | FR35: 0 | FS35: 0 | FX35: 105 | FY35: 77 | GD35: 0 | GF35: 1725378853 | GG35: 2 | GH35: 1 | GI35: 2 | GJ35: 0 | GK35: =ROUND(R35*(S12)/100,2) -> 0 | GL35: =ROUND(IF(AND(BH35=3,BI35=3,FS35<>0),P35,0),2) -> 0 | GM35: =ROUND(O35+X35+Y35+GK35,2)+GX35 -> 15498.14 | GN35: =IF(OR(BI35=0,BI35=1),GM35-GX35,0) -> 15498.14 | GO35: =IF(BI35=2,GM35-GX35,0) -> 0 | GP35: =IF(BI35=4,GM35-GX35,0) -> 0 | GR35: 0 | GS35: 3 | GT35: 0 | GV35: =ROUND((GT35),6) -> 0 | GW35: 1 | GX35: =ROUND(HC35*I35,2) -> 0 | HA35: 0 | HB35: 0 | HC35: =GV35*GW35 -> 0 | HS35: 0 | IK35: 0
A36: 17 | B36: 1 | C36: =ROW(SmtRes!A18) -> 18 | D36: =ROW(EtalonRes!A16) -> 16 | E36: 5 | F36: 3.1-3-2 | G36: Разработка грунта в отвал экскаваторами с ковшом вместимостью 0,25 м3 группа грунтов 1-3 | H36: 100 м3 грунта | I36: =ROUND(45.5*0.7/100,9) -> 0.3185 | J36: 0 | K36: =ROUND(45.5*0.7/100,9) -> 0.3185 | O36: =ROUND(CP36,2) -> 352.86 | P36: =ROUND((ROUND((AC36*AW36*I36),2)*BC36),2) -> 0 | Q36: =(ROUND((ROUND(((((ET36*1.1)*0.9))*AV36*I36),2)*BB36),2)+ROUND((ROUND(((AE36-(((EU36*1.1)*0.9)))*AV36*I36),2)*BS36),2)) -> 350.32 | R36: =ROUND((ROUND((AE36*AV36*I36),2)*BS36),2) -> 34.54 | S36: =ROUND((ROUND((AF36*AV36*I36),2)*BA36),2) -> 2.54 | T36: =ROUND(CU36*I36,2) -> 0 | U36: =CV36*I36 -> 0.24848223 | V36: =CW36*I36 -> 0 | W36: =ROUND(CX36*I36,2) -> 0 | X36: =ROUND(CY36,2) -> 2.49 | Y36: =ROUND(CZ36,2) -> 1.96 | AA36: 56622586 | AB36: =ROUND((AC36+AD36+AF36),6) -> 929.4274 | AC36: =ROUND(((ES36*1)),6) -> 0 | AD36: =ROUND((((((ET36*1.1)*0.9))-(((EU36*1.1)*0.9)))+AE36),6) -> 922.7394 | AE36: =ROUND((((EU36*1.1)*0.9)),6) -> 90.9711 | AF36: =ROUND((((EV36*1.1)*0.5)),6) -> 6.688 | AG36: =ROUND((AP36),6) -> 0 | AH36: =(((EW36*1.1)*0.5)) -> 0.6545 | AI36: =(((EX36*1.1)*0.9)) -> 0 | AJ36: =(AS36) -> 0 | AK36: 944.22 | AL36: 0 | AM36: 932.06 | AN36: 91.89 | AO36: 12.16 | AP36: 0 | AQ36: 1.19 | AR36: 0 | AS36: 0 | AT36: 98 | AU36: 77 | AV36: 1.192 | AW36: 1 | AZ36: 1 | BA36: 1 | BB36: 1 | BC36: 1 | BH36: 0 | BI36: 1 | BJ36: ТСН-2001.3 Доп. 68, Сб. 1, т. 3, поз. 2 | BM36: 2 | BN36: 0 | BP36: 0 | BQ36: 30 | BR36: 0 | BS36: 1 | BT36: 1 | BU36: 1 | BV36: 1 | BW36: 1 | BX36: 1 | BZ36: 98 | CA36: 77 | CE36: 30 | CF36: 0 | CG36: 0 | CM36: 0 | CN36: Поправка: О.П. п.3.4.30.в Наименование: В отношении объектов, реализуемых с привлечением средств бюджета города Москвы, затраты, учитывающие усложненные условия производства работ (стесненность, сложность складирования и транспортной логистики, наличие в зоне производства работ действующего технологического оборудования или движения технологического транспорта и т.п.), определяются заказчиком в задании на проектирование при составлении локальных сметных расчетов (смет): для объектов, расположенных за пределами Третьего транспортного кольца города Москвы, но в пределах Московской кольцевой автомобильной дороги Поправка: Сб.3-1.т.3.1.п.3.1.13_03.01.01.22.001 Наименование: При засыпке экскаватором траншей и котлованов ранее разработанным, не слежавшимся или разрыхлённым грунтом | CO36: 0 | CP36: =(P36+Q36+S36) -> 352.86 | CQ36: =ROUND((ROUND((AC36*AW36*1),2)*BC36),2) -> 0 | CR36: =(ROUND((ROUND(((((ET36*1.1)*0.9))*AV36*1),2)*BB36),2)+ROUND((ROUND(((AE36-(((EU36*1.1)*0.9)))*AV36*1),2)*BS36),2)) -> 1099.91 | CS36: =ROUND((ROUND((AE36*AV36*1),2)*BS36),2) -> 108.44 | CT36: =ROUND((ROUND((AF36*AV36*1),2)*BA36),2) -> 7.97 | CU36: =AG36 -> 0 | CV36: =(AH36*AV36) -> 0.780164 | CW36: =AI36 -> 0 | CX36: =AJ36 -> 0 | CY36: =((S36*BZ36)/100) -> 2.4892 | CZ36: =((S36*CA36)/100) -> 1.9558 | DD36: )*1 | DE36: )*1,1)*0,9 | DF36: )*1,1)*0,9 | DG36: )*1,1)*0,5 | DI36: )*1,1)*0,5 | DJ36: )*1,1)*0,9 | DN36: 0 | DO36: 0 | DP36: 1 | DQ36: 1 | DU36: 1013 | DV36: 100 м3 грунта | DW36: 100 м3 грунта | DX36: 1 | EE36: 51696085 | EF36: 30 | EG36: Строительные работы | EH36: 0 | EJ36: 1 | EK36: 2 | EL36: ТСН-2001.3-1. 1-1...1-7 | EM36: ТСН-2001.3-1-1 | EO36: Поправка: О.П. п.3.4.30.в Поправка: Сб.3-1.т.3.1.п.3.1.13_03.01.01.22.001 | EQ36: 131072 | ER36: 944.22 | ES36: 0 | ET36: 932.06 | EU36: 91.89 | EV36: 12.16 | EW36: 1.19 | EX36: 0 | EY36: 0 | FQ36: 0 | FR36: 0 | FS36: 0 | FX36: 98 | FY36: 77 | GD36: 0 | GF36: 864155608 | GG36: 2 | GH36: 1 | GI36: -2 | GJ36: 0 | GK36: =ROUND(R36*(R12)/100,2) -> 60.45 | GL36: =ROUND(IF(AND(BH36=3,BI36=3,FS36<>0),P36,0),2) -> 0 | GM36: =ROUND(O36+X36+Y36+GK36,2)+GX36 -> 417.76 | GN36: =IF(OR(BI36=0,BI36=1),GM36-GX36,0) -> 417.76 | GO36: =IF(BI36=2,GM36-GX36,0) -> 0 | GP36: =IF(BI36=4,GM36-GX36,0) -> 0 | GR36: 0 | GS36: 0 | GT36: 0 | GV36: =ROUND((GT36),6) -> 0 | GW36: 1 | GX36: =ROUND(HC36*I36,2) -> 0 | HA36: 0 | HB36: 0 | HC36: =GV36*GW36 -> 0 | HS36: 0 | IK36: 0
A37: 17 | B37: 1 | C37: =ROW(SmtRes!A20) -> 20 | D37: =ROW(EtalonRes!A18) -> 18 | E37: 5 | F37: 3.1-3-2 | G37: Разработка грунта в отвал экскаваторами с ковшом вместимостью 0,25 м3 группа грунтов 1-3 | H37: 100 м3 грунта | I37: =ROUND(45.5*0.7/100,9) -> 0.3185 | J37: 0 | K37: =ROUND(45.5*0.7/100,9) -> 0.3185 | O37: =ROUND(CP37,2) -> 4351.05 | P37: =ROUND((ROUND((AC37*AW37*I37),2)*BC37),2) -> 0 | Q37: =(ROUND((ROUND(((((ET37*1.1)*0.9))*AV37*I37),2)*BB37),2)+ROUND((ROUND(((AE37-(((EU37*1.1)*0.9)))*AV37*I37),2)*BS37),2)) -> 4263.39 | R37: =ROUND((ROUND((AE37*AV37*I37),2)*BS37),2) -> 1191.98 | S37: =ROUND((ROUND((AF37*AV37*I37),2)*BA37),2) -> 87.66 | T37: =ROUND(CU37*I37,2) -> 0 | U37: =CV37*I37 -> 0.24848223 | V37: =CW37*I37 -> 0 | W37: =ROUND(CX37*I37,2) -> 0 | X37: =ROUND(CY37,2) -> 82.4 | Y37: =ROUND(CZ37,2) -> 44.71 | AA37: 56616093 | AB37: =ROUND((AC37+AD37+AF37),6) -> 929.4274 | AC37: =ROUND(((ES37*1)),6) -> 0 | AD37: =ROUND((((((ET37*1.1)*0.9))-(((EU37*1.1)*0.9)))+AE37),6) -> 922.7394 | AE37: =ROUND((((EU37*1.1)*0.9)),6) -> 90.9711 | AF37: =ROUND((((EV37*1.1)*0.5)),6) -> 6.688 | AG37: =ROUND((AP37),6) -> 0 | AH37: =(((EW37*1.1)*0.5)) -> 0.6545 | AI37: =(((EX37*1.1)*0.9)) -> 0 | AJ37: =(AS37) -> 0 | AK37: 944.22 | AL37: 0 | AM37: 932.06 | AN37: 91.89 | AO37: 12.16 | AP37: 0 | AQ37: 1.19 | AR37: 0 | AS37: 0 | AT37: 94 | AU37: 51 | AV37: 1.192 | AW37: 1 | AZ37: 1 | BA37: 34.51 | BB37: 12.17 | BC37: 1 | BH37: 0 | BI37: 1 | BJ37: ТСН-2001.3 Доп. 68, Сб. 1, т. 3, поз. 2 | BM37: 2 | BN37: 0 | BO37: 3.1-3-2 | BP37: 1 | BQ37: 30 | BR37: 0 | BS37: 34.51 | BT37: 1 | BU37: 1 | BV37: 1 | BW37: 1 | BX37: 1 | BZ37: 94 | CA37: 51 | CE37: 30 | CF37: 0 | CG37: 0 | CM37: 0 | CN37: Поправка: О.П. п.3.4.30.в Наименование: В отношении объектов, реализуемых с привлечением средств бюджета города Москвы, затраты, учитывающие усложненные условия производства работ (стесненность, сложность складирования и транспортной логистики, наличие в зоне производства работ действующего технологического оборудования или движения технологического транспорта и т.п.), определяются заказчиком в задании на проектирование при составлении локальных сметных расчетов (смет): для объектов, расположенных за пределами Третьего транспортного кольца города Москвы, но в пределах Московской кольцевой автомобильной дороги Поправка: Сб.3-1.т.3.1.п.3.1.13_03.01.01.22.001 Наименование: При засыпке экскаватором траншей и котлованов ранее разработанным, не слежавшимся или разрыхлённым грунтом | CO37: 0 | CP37: =(P37+Q37+S37) -> 4351.05 | CQ37: =ROUND((ROUND((AC37*AW37*1),2)*BC37),2) -> 0 | CR37: =(ROUND((ROUND(((((ET37*1.1)*0.9))*AV37*1),2)*BB37),2)+ROUND((ROUND(((AE37-(((EU37*1.1)*0.9)))*AV37*1),2)*BS37),2)) -> 13385.9 | CS37: =ROUND((ROUND((AE37*AV37*1),2)*BS37),2) -> 3742.26 | CT37: =ROUND((ROUND((AF37*AV37*1),2)*BA37),2) -> 275.04 | CU37: =AG37 -> 0 | CV37: =(AH37*AV37) -> 0.780164 | CW37: =AI37 -> 0 | CX37: =AJ37 -> 0 | CY37: =S37*(BZ37/100) -> 82.4004 | CZ37: =S37*(CA37/100) -> 44.7066 | DD37: )*1 | DE37: )*1,1)*0,9 | DF37: )*1,1)*0,9 | DG37: )*1,1)*0,5 | DI37: )*1,1)*0,5 | DJ37: )*1,1)*0,9 | DN37: 98 | DO37: 77 | DP37: 1.192 | DQ37: 1 | DU37: 1013 | DV37: 100 м3 грунта | DW37: 100 м3 грунта | DX37: 1 | EE37: 51696085 | EF37: 30 | EG37: Строительные работы | EH37: 0 | EJ37: 1 | EK37: 2 | EL37: ТСН-2001.3-1. 1-1...1-7 | EM37: ТСН-2001.3-1-1 | EO37: Поправка: О.П. п.3.4.30.в Поправка: Сб.3-1.т.3.1.п.3.1.13_03.01.01.22.001 | EQ37: 131072 | ER37: 944.22 | ES37: 0 | ET37: 932.06 | EU37: 91.89 | EV37: 12.16 | EW37: 1.19 | EX37: 0 | EY37: 0 | FQ37: 0 | FR37: 0 | FS37: 0 | FX37: 98 | FY37: 77 | GD37: 0 | GF37: 864155608 | GG37: 2 | GH37: 1 | GI37: 2 | GJ37: 0 | GK37: =ROUND(R37*(S12)/100,2) -> 1907.17 | GL37: =ROUND(IF(AND(BH37=3,BI37=3,FS37<>0),P37,0),2) -> 0 | GM37: =ROUND(O37+X37+Y37+GK37,2)+GX37 -> 6385.33 | GN37: =IF(OR(BI37=0,BI37=1),GM37-GX37,0) -> 6385.33 | GO37: =IF(BI37=2,GM37-GX37,0) -> 0 | GP37: =IF(BI37=4,GM37-GX37,0) -> 0 | GR37: 0 | GS37: 3 | GT37: 0 | GV37: =ROUND((GT37),6) -> 0 | GW37: 1 | GX37: =ROUND(HC37*I37,2) -> 0 | HA37: 0 | HB37: 0 | HC37: =GV37*GW37 -> 0 | HS37: 0 | IK37: 0
A38: 17 | B38: 1 | C38: =ROW(SmtRes!A24) -> 24 | D38: =ROW(EtalonRes!A22) -> 22 | E38: 6 | F38: 3.34-17-4 | G38: Устройство трубопроводов из асбестоцементных труб с соединением манжетами полиэтиленовыми более 2-х отверстий | H38: 1 канало-километр трубопровода | I38: =ROUND(33/1000,9) -> 0.033 | J38: 0 | K38: =ROUND(33/1000,9) -> 0.033 | O38: =ROUND(CP38,2) -> 757.31 | P38: =ROUND((ROUND((AC38*AW38*I38),2)*BC38),2) -> 697.55 | Q38: =(ROUND((ROUND((((ET38*1.1))*AV38*I38),2)*BB38),2)+ROUND((ROUND(((AE38-((EU38*1.1)))*AV38*I38),2)*BS38),2)) -> 0 | R38: =ROUND((ROUND((AE38*AV38*I38),2)*BS38),2) -> 0 | S38: =ROUND((ROUND((AF38*AV38*I38),2)*BA38),2) -> 59.76 | T38: =ROUND(CU38*I38,2) -> 0 | U38: =CV38*I38 -> 5.3450298 | V38: =CW38*I38 -> 0 | W38: =ROUND(CX38*I38,2) -> 0 | X38: =ROUND(CY38,2) -> 66.93 | Y38: =ROUND(CZ38,2) -> 41.83 | AA38: 56622586 | AB38: =ROUND((AC38+AD38+AF38),6) -> 21251.264 | AC38: =ROUND((ES38),6) -> 19554.14 | AD38: =ROUND(((((ET38*1.1))-((EU38*1.1)))+AE38),6) -> 0 | AE38: =ROUND(((EU38*1.1)),6) -> 0 | AF38: =ROUND(((EV38*1.1)),6) -> 1697.124 | AG38: =ROUND((AP38),6) -> 0 | AH38: =((EW38*1.1)) -> 151.8 | AI38: =((EX38*1.1)) -> 0 | AJ38: =(AS38) -> 0 | AK38: 21096.98 | AL38: 19554.14 | AM38: 0 | AN38: 0 | AO38: 1542.84 | AP38: 0 | AQ38: 138 | AR38: 0 | AS38: 0 | AT38: 112 | AU38: 70 | AV38: 1.067 | AW38: 1.081 | AZ38: 1 | BA38: 1 | BB38: 1 | BC38: 1 | BH38: 0 | BI38: 1 | BJ38: ТСН-2001.3. Доп. 1-42. Сб. 34, т. 17, поз. 4 | BM38: 242 | BN38: 0 | BP38: 0 | BQ38: 30 | BR38: 0 | BS38: 1 | BT38: 1 | BU38: 1 | BV38: 1 | BW38: 1 | BX38: 1 | BZ38: 112 | CA38: 70 | CE38: 30 | CF38: 0 | CG38: 0 | CM38: 0 | CN38: Поправка: О.П. п.3.4.30.в Наименование: В отношении объектов, реализуемых с привлечением средств бюджета города Москвы, затраты, учитывающие усложненные условия производства работ (стесненность, сложность складирования и транспортной логистики, наличие в зоне производства работ действующего технологического оборудования или движения технологического транспорта и т.п.), определяются заказчиком в задании на проектирование при составлении локальных сметных расчетов (смет): для объектов, расположенных за пределами Третьего транспортного кольца города Москвы, но в пределах Московской кольцевой автомобильной дороги | CO38: 0 | CP38: =(P38+Q38+S38) -> 757.31 | CQ38: =ROUND((ROUND((AC38*AW38*1),2)*BC38),2) -> 21138.03 | CR38: =(ROUND((ROUND((((ET38*1.1))*AV38*1),2)*BB38),2)+ROUND((ROUND(((AE38-((EU38*1.1)))*AV38*1),2)*BS38),2)) -> 0 | CS38: =ROUND((ROUND((AE38*AV38*1),2)*BS38),2) -> 0 | CT38: =ROUND((ROUND((AF38*AV38*1),2)*BA38),2) -> 1810.83 | CU38: =AG38 -> 0 | CV38: =(AH38*AV38) -> 161.9706 | CW38: =AI38 -> 0 | CX38: =AJ38 -> 0 | CY38: =((S38*BZ38)/100) -> 66.9312 | CZ38: =((S38*CA38)/100) -> 41.832 | DE38: )*1,1 | DF38: )*1,1 | DG38: )*1,1 | DI38: )*1,1 | DJ38: )*1,1 | DN38: 0 | DO38: 0 | DP38: 1 | DQ38: 1 | DU38: 1013 | DV38: 1 канало-километр трубопровода | DW38: 1 канало-километр трубопровода | DX38: 1 | EE38: 51696281 | EF38: 30 | EG38: Строительные работы | EH38: 0 | EJ38: 1 | EK38: 242 | EL38: ТСН-2001.3-34. 34-17...34-28 | EM38: ТСН-2001.3-34-6 | EO38: Поправка: О.П. п.3.4.30.в | EQ38: 131072 | ER38: 21096.98 | ES38: 19554.14 | ET38: 0 | EU38: 0 | EV38: 1542.84 | EW38: 138 | EX38: 0 | EY38: 0 | FQ38: 0 | FR38: 0 | FS38: 0 | FX38: 112 | FY38: 70 | GD38: 0 | GF38: -1700748837 | GG38: 2 | GH38: 1 | GI38: -2 | GJ38: 0 | GK38: =ROUND(R38*(R12)/100,2) -> 0 | GL38: =ROUND(IF(AND(BH38=3,BI38=3,FS38<>0),P38,0),2) -> 0 | GM38: =ROUND(O38+X38+Y38+GK38,2)+GX38 -> 866.07 | GN38: =IF(OR(BI38=0,BI38=1),GM38-GX38,0) -> 866.07 | GO38: =IF(BI38=2,GM38-GX38,0) -> 0 | GP38: =IF(BI38=4,GM38-GX38,0) -> 0 | GR38: 0 | GS38: 0 | GT38: 0 | GV38: =ROUND((GT38),6) -> 0 | GW38: 1 | GX38: =ROUND(HC38*I38,2) -> 0 | HA38: 0 | HB38: 0 | HC38: =GV38*GW38 -> 0 | HS38: 0 | IK38: 0
A39: 17 | B39: 1 | C39: =ROW(SmtRes!A28) -> 28 | D39: =ROW(EtalonRes!A26) -> 26 | E39: 6 | F39: 3.34-17-4 | G39: Устройство трубопроводов из асбестоцементных труб с соединением манжетами полиэтиленовыми более 2-х отверстий | H39: 1 канало-километр трубопровода | I39: =ROUND(33/1000,9) -> 0.033 | J39: 0 | K39: =ROUND(33/1000,9) -> 0.033 | O39: =ROUND(CP39,2) -> 7398.58 | P39: =ROUND((ROUND((AC39*AW39*I39),2)*BC39),2) -> 5336.26 | Q39: =(ROUND((ROUND((((ET39*1.1))*AV39*I39),2)*BB39),2)+ROUND((ROUND(((AE39-((EU39*1.1)))*AV39*I39),2)*BS39),2)) -> 0 | R39: =ROUND((ROUND((AE39*AV39*I39),2)*BS39),2) -> 0 | S39: =ROUND((ROUND((AF39*AV39*I39),2)*BA39),2) -> 2062.32 | T39: =ROUND(CU39*I39,2) -> 0 | U39: =CV39*I39 -> 5.3450298 | V39: =CW39*I39 -> 0 | W39: =ROUND(CX39*I39,2) -> 0 | X39: =ROUND(CY39,2) -> 1897.33 | Y39: =ROUND(CZ39,2) -> 845.55 | AA39: 56616093 | AB39: =ROUND((AC39+AD39+AF39),6) -> 21251.264 | AC39: =ROUND((ES39),6) -> 19554.14 | AD39: =ROUND(((((ET39*1.1))-((EU39*1.1)))+AE39),6) -> 0 | AE39: =ROUND(((EU39*1.1)),6) -> 0 | AF39: =ROUND(((EV39*1.1)),6) -> 1697.124 | AG39: =ROUND((AP39),6) -> 0 | AH39: =((EW39*1.1)) -> 151.8 | AI39: =((EX39*1.1)) -> 0 | AJ39: =(AS39) -> 0 | AK39: 21096.98 | AL39: 19554.14 | AM39: 0 | AN39: 0 | AO39: 1542.84 | AP39: 0 | AQ39: 138 | AR39: 0 | AS39: 0 | AT39: 92 | AU39: 41 | AV39: 1.067 | AW39: 1.081 | AZ39: 1 | BA39: 34.51 | BB39: 1 | BC39: 7.65 | BH39: 0 | BI39: 1 | BJ39: ТСН-2001.3. Доп. 1-42. Сб. 34, т. 17, поз. 4 | BM39: 242 | BN39: 0 | BO39: 3.34-17-4 | BP39: 1 | BQ39: 30 | BR39: 0 | BS39: 34.51 | BT39: 1 | BU39: 1 | BV39: 1 | BW39: 1 | BX39: 1 | BZ39: 92 | CA39: 41 | CE39: 30 | CF39: 0 | CG39: 0 | CM39: 0 | CN39: Поправка: О.П. п.3.4.30.в Наименование: В отношении объектов, реализуемых с привлечением средств бюджета города Москвы, затраты, учитывающие усложненные условия производства работ (стесненность, сложность складирования и транспортной логистики, наличие в зоне производства работ действующего технологического оборудования или движения технологического транспорта и т.п.), определяются заказчиком в задании на проектирование при составлении локальных сметных расчетов (смет): для объектов, расположенных за пределами Третьего транспортного кольца города Москвы, но в пределах Московской кольцевой автомобильной дороги | CO39: 0 | CP39: =(P39+Q39+S39) -> 7398.58 | CQ39: =ROUND((ROUND((AC39*AW39*1),2)*BC39),2) -> 161705.93 | CR39: =(ROUND((ROUND((((ET39*1.1))*AV39*1),2)*BB39),2)+ROUND((ROUND(((AE39-((EU39*1.1)))*AV39*1),2)*BS39),2)) -> 0 | CS39: =ROUND((ROUND((AE39*AV39*1),2)*BS39),2) -> 0 | CT39: =ROUND((ROUND((AF39*AV39*1),2)*BA39),2) -> 62491.74 | CU39: =AG39 -> 0 | CV39: =(AH39*AV39) -> 161.9706 | CW39: =AI39 -> 0 | CX39: =AJ39 -> 0 | CY39: =S39*(BZ39/100) -> 1897.3344 | CZ39: =S39*(CA39/100) -> 845.5512 | DE39: )*1,1 | DF39: )*1,1 | DG39: )*1,1 | DI39: )*1,1 | DJ39: )*1,1 | DN39: 112 | DO39: 70 | DP39: 1.067 | DQ39: 1.081 | DU39: 1013 | DV39: 1 канало-километр трубопровода | DW39: 1 канало-километр трубопровода | DX39: 1 | EE39: 51696281 | EF39: 30 | EG39: Строительные работы | EH39: 0 | EJ39: 1 | EK39: 242 | EL39: ТСН-2001.3-34. 34-17...34-28 | EM39: ТСН-2001.3-34-6 | EO39: Поправка: О.П. п.3.4.30.в | EQ39: 131072 | ER39: 21096.98 | ES39: 19554.14 | ET39: 0 | EU39: 0 | EV39: 1542.84 | EW39: 138 | EX39: 0 | EY39: 0 | FQ39: 0 | FR39: 0 | FS39: 0 | FX39: 112 | FY39: 70 | GD39: 0 | GF39: -1700748837 | GG39: 2 | GH39: 1 | GI39: 2 | GJ39: 0 | GK39: =ROUND(R39*(S12)/100,2) -> 0 | GL39: =ROUND(IF(AND(BH39=3,BI39=3,FS39<>0),P39,0),2) -> 0 | GM39: =ROUND(O39+X39+Y39+GK39,2)+GX39 -> 10141.46 | GN39: =IF(OR(BI39=0,BI39=1),GM39-GX39,0) -> 10141.46 | GO39: =IF(BI39=2,GM39-GX39,0) -> 0 | GP39: =IF(BI39=4,GM39-GX39,0) -> 0 | GR39: 0 | GS39: 3 | GT39: 0 | GV39: =ROUND((GT39),6) -> 0 | GW39: 1 | GX39: =ROUND(HC39*I39,2) -> 0 | HA39: 0 | HB39: 0 | HC39: =GV39*GW39 -> 0 | HS39: 0 | IK39: 0
A40: 17 | B40: 1 | E40: 7 | F40: 1.12-3-25 | G40: Трубы хризотилцементные безнапорные, марка БНТ, диаметр условного прохода 100 мм, внутренний диаметр 100 мм | H40: м | I40: 0 | J40: 0 | K40: 0 | O40: =ROUND(CP40,2) -> 0 | P40: =ROUND((ROUND((AC40*AW40*I40),2)*BC40),2) -> 0 | Q40: =(ROUND((ROUND((((ET40*1.1))*AV40*I40),2)*BB40),2)+ROUND((ROUND(((AE40-((EU40*1.1)))*AV40*I40),2)*BS40),2)) -> 0 | R40: =ROUND((ROUND((AE40*AV40*I40),2)*BS40),2) -> 0 | S40: =ROUND((ROUND((AF40*AV40*I40),2)*BA40),2) -> 0 | T40: =ROUND(CU40*I40,2) -> 0 | U40: =CV40*I40 -> 0 | V40: =CW40*I40 -> 0 | W40: =ROUND(CX40*I40,2) -> 0 | X40: =ROUND(CY40,2) -> 0 | Y40: =ROUND(CZ40,2) -> 0 | AA40: 56622586 | AB40: =ROUND((AC40+AD40+AF40),6) -> 15.01 | AC40: =ROUND((ES40),6) -> 15.01 | AD40: =ROUND(((((ET40*1.1))-((EU40*1.1)))+AE40),6) -> 0 | AE40: =ROUND(((EU40*1.1)),6) -> 0 | AF40: =ROUND(((EV40*1.1)),6) -> 0 | AG40: =ROUND((AP40),6) -> 0 | AH40: =((EW40*1.1)) -> 0 | AI40: =((EX40*1.1)) -> 0 | AJ40: =(AS40) -> 0 | AK40: 15.01 | AL40: 15.01 | AM40: 0 | AN40: 0 | AO40: 0 | AP40: 0 | AQ40: 0 | AR40: 0 | AS40: 0 | AT40: 0 | AU40: 0 | AV40: 1 | AW40: 1 | AZ40: 1 | BA40: 1 | BB40: 1 | BC40: 1 | BH40: 3 | BI40: 1 | BJ40: ТСН-2001.1 Доп. 70, Р. 12, о. 3, поз. 25 | BM40: 1617 | BN40: 0 | BP40: 0 | BQ40: 200 | BR40: 0 | BS40: 1 | BT40: 1 | BU40: 1 | BV40: 1 | BW40: 1 | BX40: 1 | BZ40: 0 | CA40: 0 | CE40: 30 | CF40: 0 | CG40: 0 | CM40: 0 | CN40: Поправка: О.П. п.3.4.30.в Наименование: В отношении объектов, реализуемых с привлечением средств бюджета города Москвы, затраты, учитывающие усложненные условия производства работ (стесненность, сложность складирования и транспортной логистики, наличие в зоне производства работ действующего технологического оборудования или движения технологического транспорта и т.п.), определяются заказчиком в задании на проектирование при составлении локальных сметных расчетов (смет): для объектов, расположенных за пределами Третьего транспортного кольца города Москвы, но в пределах Московской кольцевой автомобильной дороги | CO40: 0 | CP40: =(P40+Q40+S40) -> 0 | CQ40: =ROUND((ROUND((AC40*AW40*1),2)*BC40),2) -> 15.01 | CR40: =(ROUND((ROUND((((ET40*1.1))*AV40*1),2)*BB40),2)+ROUND((ROUND(((AE40-((EU40*1.1)))*AV40*1),2)*BS40),2)) -> 0 | CS40: =ROUND((ROUND((AE40*AV40*1),2)*BS40),2) -> 0 | CT40: =ROUND((ROUND((AF40*AV40*1),2)*BA40),2) -> 0 | CU40: =AG40 -> 0 | CV40: =(AH40*AV40) -> 0 | CW40: =AI40 -> 0 | CX40: =AJ40 -> 0 | CY40: =((S40*BZ40)/100) -> 0 | CZ40: =((S40*CA40)/100) -> 0 | DE40: )*1,1 | DF40: )*1,1 | DG40: )*1,1 | DI40: )*1,1 | DJ40: )*1,1 | DN40: 0 | DO40: 0 | DP40: 1 | DQ40: 1 | DU40: 1003 | DV40: м | DW40: м | DX40: 1 | EE40: 51697656 | EF40: 200 | EG40: Материалы строительные | EH40: 0 | EJ40: 1 | EK40: 1617 | EL40: ТСН-2001.1 Материалы строительные | EM40: ТСН-2001.1-1 | EO40: Поправка: О.П. п.3.4.30.в | EQ40: 131072 | ER40: 15.01 | ES40: 15.01 | ET40: 0 | EU40: 0 | EV40: 0 | EW40: 0 | EX40: 0 | EY40: 0 | FQ40: 0 | FR40: 0 | FS40: 0 | FX40: 0 | FY40: 0 | GD40: 0 | GF40: 1181244062 | GG40: 2 | GH40: 1 | GI40: -2 | GJ40: 0 | GK40: =ROUND(R40*(R12)/100,2) -> 0 | GL40: =ROUND(IF(AND(BH40=3,BI40=3,FS40<>0),P40,0),2) -> 0 | GM40: =ROUND(O40+X40+Y40+GK40,2)+GX40 -> 0 | GN40: =IF(OR(BI40=0,BI40=1),GM40-GX40,0) -> 0 | GO40: =IF(BI40=2,GM40-GX40,0) -> 0 | GP40: =IF(BI40=4,GM40-GX40,0) -> 0 | GR40: 0 | GS40: 0 | GT40: 0 | GV40: =ROUND((GT40),6) -> 0 | GW40: 1 | GX40: =ROUND(HC40*I40,2) -> 0 | HA40: 0 | HB40: 0 | HC40: =GV40*GW40 -> 0 | HS40: 0 | IK40: 0
A41: 17 | B41: 1 | E41: 7 | F41: 1.12-3-25 | G41: Трубы хризотилцементные безнапорные, марка БНТ, диаметр условного прохода 100 мм, внутренний диаметр 100 мм | H41: м | I41: 0 | J41: 0 | K41: 0 | O41: =ROUND(CP41,2) -> 0 | P41: =ROUND((ROUND((AC41*AW41*I41),2)*BC41),2) -> 0 | Q41: =(ROUND((ROUND((((ET41*1.1))*AV41*I41),2)*BB41),2)+ROUND((ROUND(((AE41-((EU41*1.1)))*AV41*I41),2)*BS41),2)) -> 0 | R41: =ROUND((ROUND((AE41*AV41*I41),2)*BS41),2) -> 0 | S41: =ROUND((ROUND((AF41*AV41*I41),2)*BA41),2) -> 0 | T41: =ROUND(CU41*I41,2) -> 0 | U41: =CV41*I41 -> 0 | V41: =CW41*I41 -> 0 | W41: =ROUND(CX41*I41,2) -> 0 | X41: =ROUND(CY41,2) -> 0 | Y41: =ROUND(CZ41,2) -> 0 | AA41: 56616093 | AB41: =ROUND((AC41+AD41+AF41),6) -> 15.01 | AC41: =ROUND((ES41),6) -> 15.01 | AD41: =ROUND(((((ET41*1.1))-((EU41*1.1)))+AE41),6) -> 0 | AE41: =ROUND(((EU41*1.1)),6) -> 0 | AF41: =ROUND(((EV41*1.1)),6) -> 0 | AG41: =ROUND((AP41),6) -> 0 | AH41: =((EW41*1.1)) -> 0 | AI41: =((EX41*1.1)) -> 0 | AJ41: =(AS41) -> 0 | AK41: 15.01 | AL41: 15.01 | AM41: 0 | AN41: 0 | AO41: 0 | AP41: 0 | AQ41: 0 | AR41: 0 | AS41: 0 | AT41: 0 | AU41: 0 | AV41: 1 | AW41: 1 | AZ41: 1 | BA41: 1 | BB41: 1 | BC41: 9.11 | BH41: 3 | BI41: 1 | BJ41: ТСН-2001.1 Доп. 70, Р. 12, о. 3, поз. 25 | BM41: 1617 | BN41: 0 | BO41: 1.12-3-25 | BP41: 1 | BQ41: 200 | BR41: 0 | BS41: 1 | BT41: 1 | BU41: 1 | BV41: 1 | BW41: 1 | BX41: 1 | BZ41: 0 | CA41: 0 | CE41: 30 | CF41: 0 | CG41: 0 | CM41: 0 | CN41: Поправка: О.П. п.3.4.30.в Наименование: В отношении объектов, реализуемых с привлечением средств бюджета города Москвы, затраты, учитывающие усложненные условия производства работ (стесненность, сложность складирования и транспортной логистики, наличие в зоне производства работ действующего технологического оборудования или движения технологического транспорта и т.п.), определяются заказчиком в задании на проектирование при составлении локальных сметных расчетов (смет): для объектов, расположенных за пределами Третьего транспортного кольца города Москвы, но в пределах Московской кольцевой автомобильной дороги | CO41: 0 | CP41: =(P41+Q41+S41) -> 0 | CQ41: =ROUND((ROUND((AC41*AW41*1),2)*BC41),2) -> 136.74 | CR41: =(ROUND((ROUND((((ET41*1.1))*AV41*1),2)*BB41),2)+ROUND((ROUND(((AE41-((EU41*1.1)))*AV41*1),2)*BS41),2)) -> 0 | CS41: =ROUND((ROUND((AE41*AV41*1),2)*BS41),2) -> 0 | CT41: =ROUND((ROUND((AF41*AV41*1),2)*BA41),2) -> 0 | CU41: =AG41 -> 0 | CV41: =(AH41*AV41) -> 0 | CW41: =AI41 -> 0 | CX41: =AJ41 -> 0 | CY41: =S41*(BZ41/100) -> 0 | CZ41: =S41*(CA41/100) -> 0 | DE41: )*1,1 | DF41: )*1,1 | DG41: )*1,1 | DI41: )*1,1 | DJ41: )*1,1 | DN41: 0 | DO41: 0 | DP41: 1 | DQ41: 1 | DU41: 1003 | DV41: м | DW41: м | DX41: 1 | EE41: 51697656 | EF41: 200 | EG41: Материалы строительные | EH41: 0 | EJ41: 1 | EK41: 1617 | EL41: ТСН-2001.1 Материалы строительные | EM41: ТСН-2001.1-1 | EO41: Поправка: О.П. п.3.4.30.в | EQ41: 131072 | ER41: 15.01 | ES41: 15.01 | ET41: 0 | EU41: 0 | EV41: 0 | EW41: 0 | EX41: 0 | EY41: 0 | FQ41: 0 | FR41: 0 | FS41: 0 | FX41: 0 | FY41: 0 | GD41: 0 | GF41: 1181244062 | GG41: 2 | GH41: 1 | GI41: 2 | GJ41: 0 | GK41: =ROUND(R41*(S12)/100,2) -> 0 | GL41: =ROUND(IF(AND(BH41=3,BI41=3,FS41<>0),P41,0),2) -> 0 | GM41: =ROUND(O41+X41+Y41+GK41,2)+GX41 -> 0 | GN41: =IF(OR(BI41=0,BI41=1),GM41-GX41,0) -> 0 | GO41: =IF(BI41=2,GM41-GX41,0) -> 0 | GP41: =IF(BI41=4,GM41-GX41,0) -> 0 | GR41: 0 | GS41: 3 | GT41: 0 | GV41: =ROUND((GT41),6) -> 0 | GW41: 1 | GX41: =ROUND(HC41*I41,2) -> 0 | HA41: 0 | HB41: 0 | HC41: =GV41*GW41 -> 0 | HS41: 0 | IK41: 0
A42: 17 | B42: 1 | E42: 8 | F42: 1.12-3-26 | G42: Трубы хризотилцементные безнапорные, марка БНТ, диаметр условного прохода 150 мм, внутренний диаметр 141 мм | H42: м | I42: 0 | J42: 0 | K42: 0 | O42: =ROUND(CP42,2) -> 0 | P42: =ROUND((ROUND((AC42*AW42*I42),2)*BC42),2) -> 0 | Q42: =(ROUND((ROUND((((ET42*1.1))*AV42*I42),2)*BB42),2)+ROUND((ROUND(((AE42-((EU42*1.1)))*AV42*I42),2)*BS42),2)) -> 0 | R42: =ROUND((ROUND((AE42*AV42*I42),2)*BS42),2) -> 0 | S42: =ROUND((ROUND((AF42*AV42*I42),2)*BA42),2) -> 0 | T42: =ROUND(CU42*I42,2) -> 0 | U42: =CV42*I42 -> 0 | V42: =CW42*I42 -> 0 | W42: =ROUND(CX42*I42,2) -> 0 | X42: =ROUND(CY42,2) -> 0 | Y42: =ROUND(CZ42,2) -> 0 | AA42: 56622586 | AB42: =ROUND((AC42+AD42+AF42),6) -> 24.4 | AC42: =ROUND((ES42),6) -> 24.4 | AD42: =ROUND(((((ET42*1.1))-((EU42*1.1)))+AE42),6) -> 0 | AE42: =ROUND(((EU42*1.1)),6) -> 0 | AF42: =ROUND(((EV42*1.1)),6) -> 0 | AG42: =ROUND((AP42),6) -> 0 | AH42: =((EW42*1.1)) -> 0 | AI42: =((EX42*1.1)) -> 0 | AJ42: =(AS42) -> 0 | AK42: 24.4 | AL42: 24.4 | AM42: 0 | AN42: 0 | AO42: 0 | AP42: 0 | AQ42: 0 | AR42: 0 | AS42: 0 | AT42: 0 | AU42: 0 | AV42: 1 | AW42: 1 | AZ42: 1 | BA42: 1 | BB42: 1 | BC42: 1 | BH42: 3 | BI42: 1 | BJ42: ТСН-2001.1 Доп. 70, Р. 12, о. 3, поз. 26 | BM42: 1617 | BN42: 0 | BP42: 0 | BQ42: 200 | BR42: 0 | BS42: 1 | BT42: 1 | BU42: 1 | BV42: 1 | BW42: 1 | BX42: 1 | BZ42: 0 | CA42: 0 | CE42: 30 | CF42: 0 | CG42: 0 | CM42: 0 | CN42: Поправка: О.П. п.3.4.30.в Наименование: В отношении объектов, реализуемых с привлечением средств бюджета города Москвы, затраты, учитывающие усложненные условия производства работ (стесненность, сложность складирования и транспортной логистики, наличие в зоне производства работ действующего технологического оборудования или движения технологического транспорта и т.п.), определяются заказчиком в задании на проектирование при составлении локальных сметных расчетов (смет): для объектов, расположенных за пределами Третьего транспортного кольца города Москвы, но в пределах Московской кольцевой автомобильной дороги | CO42: 0 | CP42: =(P42+Q42+S42) -> 0 | CQ42: =ROUND((ROUND((AC42*AW42*1),2)*BC42),2) -> 24.4 | CR42: =(ROUND((ROUND((((ET42*1.1))*AV42*1),2)*BB42),2)+ROUND((ROUND(((AE42-((EU42*1.1)))*AV42*1),2)*BS42),2)) -> 0 | CS42: =ROUND((ROUND((AE42*AV42*1),2)*BS42),2) -> 0 | CT42: =ROUND((ROUND((AF42*AV42*1),2)*BA42),2) -> 0 | CU42: =AG42 -> 0 | CV42: =(AH42*AV42) -> 0 | CW42: =AI42 -> 0 | CX42: =AJ42 -> 0 | CY42: =((S42*BZ42)/100) -> 0 | CZ42: =((S42*CA42)/100) -> 0 | DE42: )*1,1 | DF42: )*1,1 | DG42: )*1,1 | DI42: )*1,1 | DJ42: )*1,1 | DN42: 0 | DO42: 0 | DP42: 1 | DQ42: 1 | DU42: 1003 | DV42: м | DW42: м | DX42: 1 | EE42: 51697656 | EF42: 200 | EG42: Материалы строительные | EH42: 0 | EJ42: 1 | EK42: 1617 | EL42: ТСН-2001.1 Материалы строительные | EM42: ТСН-2001.1-1 | EO42: Поправка: О.П. п.3.4.30.в | EQ42: 131072 | ER42: 24.4 | ES42: 24.4 | ET42: 0 | EU42: 0 | EV42: 0 | EW42: 0 | EX42: 0 | EY42: 0 | FQ42: 0 | FR42: 0 | FS42: 0 | FX42: 0 | FY42: 0 | GD42: 0 | GF42: -1982695880 | GG42: 2 | GH42: 1 | GI42: -2 | GJ42: 0 | GK42: =ROUND(R42*(R12)/100,2) -> 0 | GL42: =ROUND(IF(AND(BH42=3,BI42=3,FS42<>0),P42,0),2) -> 0 | GM42: =ROUND(O42+X42+Y42+GK42,2)+GX42 -> 0 | GN42: =IF(OR(BI42=0,BI42=1),GM42-GX42,0) -> 0 | GO42: =IF(BI42=2,GM42-GX42,0) -> 0 | GP42: =IF(BI42=4,GM42-GX42,0) -> 0 | GR42: 0 | GS42: 0 | GT42: 0 | GV42: =ROUND((GT42),6) -> 0 | GW42: 1 | GX42: =ROUND(HC42*I42,2) -> 0 | HA42: 0 | HB42: 0 | HC42: =GV42*GW42 -> 0 | HS42: 0 | IK42: 0
A43: 17 | B43: 1 | E43: 8 | F43: 1.12-3-26 | G43: Трубы хризотилцементные безнапорные, марка БНТ, диаметр условного прохода 150 мм, внутренний диаметр 141 мм | H43: м | I43: 0 | J43: 0 | K43: 0 | O43: =ROUND(CP43,2) -> 0 | P43: =ROUND((ROUND((AC43*AW43*I43),2)*BC43),2) -> 0 | Q43: =(ROUND((ROUND((((ET43*1.1))*AV43*I43),2)*BB43),2)+ROUND((ROUND(((AE43-((EU43*1.1)))*AV43*I43),2)*BS43),2)) -> 0 | R43: =ROUND((ROUND((AE43*AV43*I43),2)*BS43),2) -> 0 | S43: =ROUND((ROUND((AF43*AV43*I43),2)*BA43),2) -> 0 | T43: =ROUND(CU43*I43,2) -> 0 | U43: =CV43*I43 -> 0 | V43: =CW43*I43 -> 0 | W43: =ROUND(CX43*I43,2) -> 0 | X43: =ROUND(CY43,2) -> 0 | Y43: =ROUND(CZ43,2) -> 0 | AA43: 56616093 | AB43: =ROUND((AC43+AD43+AF43),6) -> 24.4 | AC43: =ROUND((ES43),6) -> 24.4 | AD43: =ROUND(((((ET43*1.1))-((EU43*1.1)))+AE43),6) -> 0 | AE43: =ROUND(((EU43*1.1)),6) -> 0 | AF43: =ROUND(((EV43*1.1)),6) -> 0 | AG43: =ROUND((AP43),6) -> 0 | AH43: =((EW43*1.1)) -> 0 | AI43: =((EX43*1.1)) -> 0 | AJ43: =(AS43) -> 0 | AK43: 24.4 | AL43: 24.4 | AM43: 0 | AN43: 0 | AO43: 0 | AP43: 0 | AQ43: 0 | AR43: 0 | AS43: 0 | AT43: 0 | AU43: 0 | AV43: 1 | AW43: 1 | AZ43: 1 | BA43: 1 | BB43: 1 | BC43: 9.22 | BH43: 3 | BI43: 1 | BJ43: ТСН-2001.1 Доп. 70, Р. 12, о. 3, поз. 26 | BM43: 1617 | BN43: 0 | BO43: 1.12-3-26 | BP43: 1 | BQ43: 200 | BR43: 0 | BS43: 1 | BT43: 1 | BU43: 1 | BV43: 1 | BW43: 1 | BX43: 1 | BZ43: 0 | CA43: 0 | CE43: 30 | CF43: 0 | CG43: 0 | CM43: 0 | CN43: Поправка: О.П. п.3.4.30.в Наименование: В отношении объектов, реализуемых с привлечением средств бюджета города Москвы, затраты, учитывающие усложненные условия производства работ (стесненность, сложность складирования и транспортной логистики, наличие в зоне производства работ действующего технологического оборудования или движения технологического транспорта и т.п.), определяются заказчиком в задании на проектирование при составлении локальных сметных расчетов (смет): для объектов, расположенных за пределами Третьего транспортного кольца города Москвы, но в пределах Московской кольцевой автомобильной дороги | CO43: 0 | CP43: =(P43+Q43+S43) -> 0 | CQ43: =ROUND((ROUND((AC43*AW43*1),2)*BC43),2) -> 224.97 | CR43: =(ROUND((ROUND((((ET43*1.1))*AV43*1),2)*BB43),2)+ROUND((ROUND(((AE43-((EU43*1.1)))*AV43*1),2)*BS43),2)) -> 0 | CS43: =ROUND((ROUND((AE43*AV43*1),2)*BS43),2) -> 0 | CT43: =ROUND((ROUND((AF43*AV43*1),2)*BA43),2) -> 0 | CU43: =AG43 -> 0 | CV43: =(AH43*AV43) -> 0 | CW43: =AI43 -> 0 | CX43: =AJ43 -> 0 | CY43: =S43*(BZ43/100) -> 0 | CZ43: =S43*(CA43/100) -> 0 | DE43: )*1,1 | DF43: )*1,1 | DG43: )*1,1 | DI43: )*1,1 | DJ43: )*1,1 | DN43: 0 | DO43: 0 | DP43: 1 | DQ43: 1 | DU43: 1003 | DV43: м | DW43: м | DX43: 1 | EE43: 51697656 | EF43: 200 | EG43: Материалы строительные | EH43: 0 | EJ43: 1 | EK43: 1617 | EL43: ТСН-2001.1 Материалы строительные | EM43: ТСН-2001.1-1 | EO43: Поправка: О.П. п.3.4.30.в | EQ43: 131072 | ER43: 24.4 | ES43: 24.4 | ET43: 0 | EU43: 0 | EV43: 0 | EW43: 0 | EX43: 0 | EY43: 0 | FQ43: 0 | FR43: 0 | FS43: 0 | FX43: 0 | FY43: 0 | GD43: 0 | GF43: -1982695880 | GG43: 2 | GH43: 1 | GI43: 2 | GJ43: 0 | GK43: =ROUND(R43*(S12)/100,2) -> 0 | GL43: =ROUND(IF(AND(BH43=3,BI43=3,FS43<>0),P43,0),2) -> 0 | GM43: =ROUND(O43+X43+Y43+GK43,2)+GX43 -> 0 | GN43: =IF(OR(BI43=0,BI43=1),GM43-GX43,0) -> 0 | GO43: =IF(BI43=2,GM43-GX43,0) -> 0 | GP43: =IF(BI43=4,GM43-GX43,0) -> 0 | GR43: 0 | GS43: 3 | GT43: 0 | GV43: =ROUND((GT43),6) -> 0 | GW43: 1 | GX43: =ROUND(HC43*I43,2) -> 0 | HA43: 0 | HB43: 0 | HC43: =GV43*GW43 -> 0 | HS43: 0 | IK43: 0
A44: 17 | B44: 1 | C44: =ROW(SmtRes!A32) -> 32 | D44: =ROW(EtalonRes!A31) -> 31 | E44: 9 | F44: 3.34-55-5 | G44: Устройство кабельной канализации из полиэтиленовых труб диаметром 160 мм, первая труба | H44: 1 км трубопровода | I44: =ROUND(53/1000,9) -> 0.053 | J44: 0 | K44: =ROUND(53/1000,9) -> 0.053 | O44: =ROUND(CP44,2) -> 114.2 | P44: =ROUND((ROUND((AC44*AW44*I44),2)*BC44),2) -> 0 | Q44: =(ROUND((ROUND((((ET44*1.1))*AV44*I44),2)*BB44),2)+ROUND((ROUND(((AE44-((EU44*1.1)))*AV44*I44),2)*BS44),2)) -> 16.09 | R44: =ROUND((ROUND((AE44*AV44*I44),2)*BS44),2) -> 1.77 | S44: =ROUND((ROUND((AF44*AV44*I44),2)*BA44),2) -> 98.11 | T44: =ROUND(CU44*I44,2) -> 0 | U44: =CV44*I44 -> 9.1971719 | V44: =CW44*I44 -> 0 | W44: =ROUND(CX44*I44,2) -> 0 | X44: =ROUND(CY44,2) -> 109.88 | Y44: =ROUND(CZ44,2) -> 68.68 | AA44: 56622586 | AB44: =ROUND((AC44+AD44+AF44),6) -> 2019.49 | AC44: =ROUND((ES44),6) -> 0 | AD44: =ROUND(((((ET44*1.1))-((EU44*1.1)))+AE44),6) -> 284.581 | AE44: =ROUND(((EU44*1.1)),6) -> 31.229 | AF44: =ROUND(((EV44*1.1)),6) -> 1734.909 | AG44: =ROUND((AP44),6) -> 0 | AH44: =((EW44*1.1)) -> 162.635 | AI44: =((EX44*1.1)) -> 0 | AJ44: =(AS44) -> 0 | AK44: 1835.9 | AL44: 0 | AM44: 258.71 | AN44: 28.39 | AO44: 1577.19 | AP44: 0 | AQ44: 147.85 | AR44: 0 | AS44: 0 | AT44: 112 | AU44: 70 | AV44: 1.067 | AW44: 1.081 | AZ44: 1 | BA44: 1 | BB44: 1 | BC44: 1 | BH44: 0 | BI44: 1 | BJ44: ТСН-2001.3 Доп. 68, Сб. 34, т. 55, поз. 5 | BM44: 2254 | BN44: 0 | BP44: 0 | BQ44: 30 | BR44: 0 | BS44: 1 | BT44: 1 | BU44: 1 | BV44: 1 | BW44: 1 | BX44: 1 | BZ44: 112 | CA44: 70 | CE44: 30 | CF44: 0 | CG44: 0 | CM44: 0 | CN44: Поправка: О.П. п.3.4.30.в Наименование: В отношении объектов, реализуемых с привлечением средств бюджета города Москвы, затраты, учитывающие усложненные условия производства работ (стесненность, сложность складирования и транспортной логистики, наличие в зоне производства работ действующего технологического оборудования или движения технологического транспорта и т.п.), определяются заказчиком в задании на проектирование при составлении локальных сметных расчетов (смет): для объектов, расположенных за пределами Третьего транспортного кольца города Москвы, но в пределах Московской кольцевой автомобильной дороги | CO44: 0 | CP44: =(P44+Q44+S44) -> 114.2 | CQ44: =ROUND((ROUND((AC44*AW44*1),2)*BC44),2) -> 0 | CR44: =(ROUND((ROUND((((ET44*1.1))*AV44*1),2)*BB44),2)+ROUND((ROUND(((AE44-((EU44*1.1)))*AV44*1),2)*BS44),2)) -> 303.65 | CS44: =ROUND((ROUND((AE44*AV44*1),2)*BS44),2) -> 33.32 | CT44: =ROUND((ROUND((AF44*AV44*1),2)*BA44),2) -> 1851.15 | CU44: =AG44 -> 0 | CV44: =(AH44*AV44) -> 173.53155 | CW44: =AI44 -> 0 | CX44: =AJ44 -> 0 | CY44: =((S44*BZ44)/100) -> 109.8832 | CZ44: =((S44*CA44)/100) -> 68.677 | DE44: )*1,1 | DF44: )*1,1 | DG44: )*1,1 | DI44: )*1,1 | DJ44: )*1,1 | DN44: 0 | DO44: 0 | DP44: 1 | DQ44: 1 | DU44: 1013 | DV44: 1 км трубопровода | DW44: 1 км трубопровода | DX44: 1 | EE44: 51698335 | EF44: 30 | EG44: Строительные работы | EH44: 0 | EJ44: 1 | EK44: 2254 | EL44: ТСН-2001.3-34. 34-55-1...34-55-10 (доп. 68) | EM44: ТСН-2001.3-34-20 | EO44: Поправка: О.П. п.3.4.30.в | EQ44: 131072 | ER44: 1835.9 | ES44: 0 | ET44: 258.71 | EU44: 28.39 | EV44: 1577.19 | EW44: 147.85 | EX44: 0 | EY44: 0 | FQ44: 0 | FR44: 0 | FS44: 0 | FX44: 112 | FY44: 70 | GD44: 0 | GF44: -1068329133 | GG44: 2 | GH44: 1 | GI44: -2 | GJ44: 0 | GK44: =ROUND(R44*(R12)/100,2) -> 3.1 | GL44: =ROUND(IF(AND(BH44=3,BI44=3,FS44<>0),P44,0),2) -> 0 | GM44: =ROUND(O44+X44+Y44+GK44,2)+GX44 -> 295.86 | GN44: =IF(OR(BI44=0,BI44=1),GM44-GX44,0) -> 295.86 | GO44: =IF(BI44=2,GM44-GX44,0) -> 0 | GP44: =IF(BI44=4,GM44-GX44,0) -> 0 | GR44: 0 | GS44: 0 | GT44: 0 | GV44: =ROUND((GT44),6) -> 0 | GW44: 1 | GX44: =ROUND(HC44*I44,2) -> 0 | HA44: 0 | HB44: 0 | HC44: =GV44*GW44 -> 0 | HS44: 0 | IK44: 0
A45: 17 | B45: 1 | C45: =ROW(SmtRes!A36) -> 36 | D45: =ROW(EtalonRes!A36) -> 36 | E45: 9 | F45: 3.34-55-5 | G45: Устройство кабельной канализации из полиэтиленовых труб диаметром 160 мм, первая труба | H45: 1 км трубопровода | I45: =ROUND(53/1000,9) -> 0.053 | J45: 0 | K45: =ROUND(53/1000,9) -> 0.053 | O45: =ROUND(CP45,2) -> 3575.64 | P45: =ROUND((ROUND((AC45*AW45*I45),2)*BC45),2) -> 0 | Q45: =(ROUND((ROUND((((ET45*1.1))*AV45*I45),2)*BB45),2)+ROUND((ROUND(((AE45-((EU45*1.1)))*AV45*I45),2)*BS45),2)) -> 189.86 | R45: =ROUND((ROUND((AE45*AV45*I45),2)*BS45),2) -> 61.08 | S45: =ROUND((ROUND((AF45*AV45*I45),2)*BA45),2) -> 3385.78 | T45: =ROUND(CU45*I45,2) -> 0 | U45: =CV45*I45 -> 9.1971719 | V45: =CW45*I45 -> 0 | W45: =ROUND(CX45*I45,2) -> 0 | X45: =ROUND(CY45,2) -> 3114.92 | Y45: =ROUND(CZ45,2) -> 1388.17 | AA45: 56616093 | AB45: =ROUND((AC45+AD45+AF45),6) -> 2019.49 | AC45: =ROUND((ES45),6) -> 0 | AD45: =ROUND(((((ET45*1.1))-((EU45*1.1)))+AE45),6) -> 284.581 | AE45: =ROUND(((EU45*1.1)),6) -> 31.229 | AF45: =ROUND(((EV45*1.1)),6) -> 1734.909 | AG45: =ROUND((AP45),6) -> 0 | AH45: =((EW45*1.1)) -> 162.635 | AI45: =((EX45*1.1)) -> 0 | AJ45: =(AS45) -> 0 | AK45: 1835.9 | AL45: 0 | AM45: 258.71 | AN45: 28.39 | AO45: 1577.19 | AP45: 0 | AQ45: 147.85 | AR45: 0 | AS45: 0 | AT45: 92 | AU45: 41 | AV45: 1.067 | AW45: 1.081 | AZ45: 1 | BA45: 34.51 | BB45: 11.8 | BC45: 1 | BH45: 0 | BI45: 1 | BJ45: ТСН-2001.3 Доп. 68, Сб. 34, т. 55, поз. 5 | BM45: 2254 | BN45: 0 | BO45: 3.34-55-5 | BP45: 1 | BQ45: 30 | BR45: 0 | BS45: 34.51 | BT45: 1 | BU45: 1 | BV45: 1 | BW45: 1 | BX45: 1 | BZ45: 92 | CA45: 41 | CE45: 30 | CF45: 0 | CG45: 0 | CM45: 0 | CN45: Поправка: О.П. п.3.4.30.в Наименование: В отношении объектов, реализуемых с привлечением средств бюджета города Москвы, затраты, учитывающие усложненные условия производства работ (стесненность, сложность складирования и транспортной логистики, наличие в зоне производства работ действующего технологического оборудования или движения технологического транспорта и т.п.), определяются заказчиком в задании на проектирование при составлении локальных сметных расчетов (смет): для объектов, расположенных за пределами Третьего транспортного кольца города Москвы, но в пределах Московской кольцевой автомобильной дороги | CO45: 0 | CP45: =(P45+Q45+S45) -> 3575.64 | CQ45: =ROUND((ROUND((AC45*AW45*1),2)*BC45),2) -> 0 | CR45: =(ROUND((ROUND((((ET45*1.1))*AV45*1),2)*BB45),2)+ROUND((ROUND(((AE45-((EU45*1.1)))*AV45*1),2)*BS45),2)) -> 3583.07 | CS45: =ROUND((ROUND((AE45*AV45*1),2)*BS45),2) -> 1149.87 | CT45: =ROUND((ROUND((AF45*AV45*1),2)*BA45),2) -> 63883.19 | CU45: =AG45 -> 0 | CV45: =(AH45*AV45) -> 173.53155 | CW45: =AI45 -> 0 | CX45: =AJ45 -> 0 | CY45: =S45*(BZ45/100) -> 3114.9176 | CZ45: =S45*(CA45/100) -> 1388.1698 | DE45: )*1,1 | DF45: )*1,1 | DG45: )*1,1 | DI45: )*1,1 | DJ45: )*1,1 | DN45: 112 | DO45: 70 | DP45: 1.067 | DQ45: 1.081 | DU45: 1013 | DV45: 1 км трубопровода | DW45: 1 км трубопровода | DX45: 1 | EE45: 51698335 | EF45: 30 | EG45: Строительные работы | EH45: 0 | EJ45: 1 | EK45: 2254 | EL45: ТСН-2001.3-34. 34-55-1...34-55-10 (доп. 68) | EM45: ТСН-2001.3-34-20 | EO45: Поправка: О.П. п.3.4.30.в | EQ45: 131072 | ER45: 1835.9 | ES45: 0 | ET45: 258.71 | EU45: 28.39 | EV45: 1577.19 | EW45: 147.85 | EX45: 0 | EY45: 0 | FQ45: 0 | FR45: 0 | FS45: 0 | FX45: 112 | FY45: 70 | GD45: 0 | GF45: -1068329133 | GG45: 2 | GH45: 1 | GI45: 2 | GJ45: 0 | GK45: =ROUND(R45*(S12)/100,2) -> 97.73 | GL45: =ROUND(IF(AND(BH45=3,BI45=3,FS45<>0),P45,0),2) -> 0 | GM45: =ROUND(O45+X45+Y45+GK45,2)+GX45 -> 8176.46 | GN45: =IF(OR(BI45=0,BI45=1),GM45-GX45,0) -> 8176.46 | GO45: =IF(BI45=2,GM45-GX45,0) -> 0 | GP45: =IF(BI45=4,GM45-GX45,0) -> 0 | GR45: 0 | GS45: 3 | GT45: 0 | GV45: =ROUND((GT45),6) -> 0 | GW45: 1 | GX45: =ROUND(HC45*I45,2) -> 0 | HA45: 0 | HB45: 0 | HC45: =GV45*GW45 -> 0 | HS45: 0 | IK45: 0
A46: 17 | B46: 1 | C46: =ROW(SmtRes!A40) -> 40 | D46: =ROW(EtalonRes!A41) -> 41 | E46: 10 | F46: 3.34-55-5 | G46: Устройство кабельной канализации из полиэтиленовых труб диаметром 160 мм, первая труба | H46: 1 км трубопровода | I46: 0 | J46: 0 | K46: 0 | O46: =ROUND(CP46,2) -> 0 | P46: =ROUND((ROUND((AC46*AW46*I46),2)*BC46),2) -> 0 | Q46: =(ROUND((ROUND((((ET46*1.1))*AV46*I46),2)*BB46),2)+ROUND((ROUND(((AE46-((EU46*1.1)))*AV46*I46),2)*BS46),2)) -> 0 | R46: =ROUND((ROUND((AE46*AV46*I46),2)*BS46),2) -> 0 | S46: =ROUND((ROUND((AF46*AV46*I46),2)*BA46),2) -> 0 | T46: =ROUND(CU46*I46,2) -> 0 | U46: =CV46*I46 -> 0 | V46: =CW46*I46 -> 0 | W46: =ROUND(CX46*I46,2) -> 0 | X46: =ROUND(CY46,2) -> 0 | Y46: =ROUND(CZ46,2) -> 0 | AA46: 56622586 | AB46: =ROUND((AC46+AD46+AF46),6) -> 2019.49 | AC46: =ROUND((ES46),6) -> 0 | AD46: =ROUND(((((ET46*1.1))-((EU46*1.1)))+AE46),6) -> 284.581 | AE46: =ROUND(((EU46*1.1)),6) -> 31.229 | AF46: =ROUND(((EV46*1.1)),6) -> 1734.909 | AG46: =ROUND((AP46),6) -> 0 | AH46: =((EW46*1.1)) -> 162.635 | AI46: =((EX46*1.1)) -> 0 | AJ46: =(AS46) -> 0 | AK46: 1835.9 | AL46: 0 | AM46: 258.71 | AN46: 28.39 | AO46: 1577.19 | AP46: 0 | AQ46: 147.85 | AR46: 0 | AS46: 0 | AT46: 112 | AU46: 70 | AV46: 1.067 | AW46: 1.081 | AZ46: 1 | BA46: 1 | BB46: 1 | BC46: 1 | BH46: 0 | BI46: 1 | BJ46: ТСН-2001.3 Доп. 68, Сб. 34, т. 55, поз. 5 | BM46: 2254 | BN46: 0 | BP46: 0 | BQ46: 30 | BR46: 0 | BS46: 1 | BT46: 1 | BU46: 1 | BV46: 1 | BW46: 1 | BX46: 1 | BZ46: 112 | CA46: 70 | CE46: 30 | CF46: 0 | CG46: 0 | CM46: 0 | CN46: Поправка: О.П. п.3.4.30.в Наименование: В отношении объектов, реализуемых с привлечением средств бюджета города Москвы, затраты, учитывающие усложненные условия производства работ (стесненность, сложность складирования и транспортной логистики, наличие в зоне производства работ действующего технологического оборудования или движения технологического транспорта и т.п.), определяются заказчиком в задании на проектирование при составлении локальных сметных расчетов (смет): для объектов, расположенных за пределами Третьего транспортного кольца города Москвы, но в пределах Московской кольцевой автомобильной дороги | CO46: 0 | CP46: =(P46+Q46+S46) -> 0 | CQ46: =ROUND((ROUND((AC46*AW46*1),2)*BC46),2) -> 0 | CR46: =(ROUND((ROUND((((ET46*1.1))*AV46*1),2)*BB46),2)+ROUND((ROUND(((AE46-((EU46*1.1)))*AV46*1),2)*BS46),2)) -> 303.65 | CS46: =ROUND((ROUND((AE46*AV46*1),2)*BS46),2) -> 33.32 | CT46: =ROUND((ROUND((AF46*AV46*1),2)*BA46),2) -> 1851.15 | CU46: =AG46 -> 0 | CV46: =(AH46*AV46) -> 173.53155 | CW46: =AI46 -> 0 | CX46: =AJ46 -> 0 | CY46: =((S46*BZ46)/100) -> 0 | CZ46: =((S46*CA46)/100) -> 0 | DE46: )*1,1 | DF46: )*1,1 | DG46: )*1,1 | DI46: )*1,1 | DJ46: )*1,1 | DN46: 0 | DO46: 0 | DP46: 1 | DQ46: 1 | DU46: 1013 | DV46: 1 км трубопровода | DW46: 1 км трубопровода | DX46: 1 | EE46: 51698335 | EF46: 30 | EG46: Строительные работы | EH46: 0 | EJ46: 1 | EK46: 2254 | EL46: ТСН-2001.3-34. 34-55-1...34-55-10 (доп. 68) | EM46: ТСН-2001.3-34-20 | EO46: Поправка: О.П. п.3.4.30.в | EQ46: 131072 | ER46: 1835.9 | ES46: 0 | ET46: 258.71 | EU46: 28.39 | EV46: 1577.19 | EW46: 147.85 | EX46: 0 | EY46: 0 | FQ46: 0 | FR46: 0 | FS46: 0 | FX46: 112 | FY46: 70 | GD46: 0 | GF46: -1068329133 | GG46: 2 | GH46: 1 | GI46: -2 | GJ46: 0 | GK46: =ROUND(R46*(R12)/100,2) -> 0 | GL46: =ROUND(IF(AND(BH46=3,BI46=3,FS46<>0),P46,0),2) -> 0 | GM46: =ROUND(O46+X46+Y46+GK46,2)+GX46 -> 0 | GN46: =IF(OR(BI46=0,BI46=1),GM46-GX46,0) -> 0 | GO46: =IF(BI46=2,GM46-GX46,0) -> 0 | GP46: =IF(BI46=4,GM46-GX46,0) -> 0 | GR46: 0 | GS46: 0 | GT46: 0 | GV46: =ROUND((GT46),6) -> 0 | GW46: 1 | GX46: =ROUND(HC46*I46,2) -> 0 | HA46: 0 | HB46: 0 | HC46: =GV46*GW46 -> 0 | HS46: 0 | IK46: 0
A47: 17 | B47: 1 | C47: =ROW(SmtRes!A44) -> 44 | D47: =ROW(EtalonRes!A46) -> 46 | E47: 10 | F47: 3.34-55-5 | G47: Устройство кабельной канализации из полиэтиленовых труб диаметром 160 мм, первая труба | H47: 1 км трубопровода | I47: 0 | J47: 0 | K47: 0 | O47: =ROUND(CP47,2) -> 0 | P47: =ROUND((ROUND((AC47*AW47*I47),2)*BC47),2) -> 0 | Q47: =(ROUND((ROUND((((ET47*1.1))*AV47*I47),2)*BB47),2)+ROUND((ROUND(((AE47-((EU47*1.1)))*AV47*I47),2)*BS47),2)) -> 0 | R47: =ROUND((ROUND((AE47*AV47*I47),2)*BS47),2) -> 0 | S47: =ROUND((ROUND((AF47*AV47*I47),2)*BA47),2) -> 0 | T47: =ROUND(CU47*I47,2) -> 0 | U47: =CV47*I47 -> 0 | V47: =CW47*I47 -> 0 | W47: =ROUND(CX47*I47,2) -> 0 | X47: =ROUND(CY47,2) -> 0 | Y47: =ROUND(CZ47,2) -> 0 | AA47: 56616093 | AB47: =ROUND((AC47+AD47+AF47),6) -> 2019.49 | AC47: =ROUND((ES47),6) -> 0 | AD47: =ROUND(((((ET47*1.1))-((EU47*1.1)))+AE47),6) -> 284.581 | AE47: =ROUND(((EU47*1.1)),6) -> 31.229 | AF47: =ROUND(((EV47*1.1)),6) -> 1734.909 | AG47: =ROUND((AP47),6) -> 0 | AH47: =((EW47*1.1)) -> 162.635 | AI47: =((EX47*1.1)) -> 0 | AJ47: =(AS47) -> 0 | AK47: 1835.9 | AL47: 0 | AM47: 258.71 | AN47: 28.39 | AO47: 1577.19 | AP47: 0 | AQ47: 147.85 | AR47: 0 | AS47: 0 | AT47: 92 | AU47: 41 | AV47: 1.067 | AW47: 1.081 | AZ47: 1 | BA47: 34.51 | BB47: 11.8 | BC47: 1 | BH47: 0 | BI47: 1 | BJ47: ТСН-2001.3 Доп. 68, Сб. 34, т. 55, поз. 5 | BM47: 2254 | BN47: 0 | BO47: 3.34-55-5 | BP47: 1 | BQ47: 30 | BR47: 0 | BS47: 34.51 | BT47: 1 | BU47: 1 | BV47: 1 | BW47: 1 | BX47: 1 | BZ47: 92 | CA47: 41 | CE47: 30 | CF47: 0 | CG47: 0 | CM47: 0 | CN47: Поправка: О.П. п.3.4.30.в Наименование: В отношении объектов, реализуемых с привлечением средств бюджета города Москвы, затраты, учитывающие усложненные условия производства работ (стесненность, сложность складирования и транспортной логистики, наличие в зоне производства работ действующего технологического оборудования или движения технологического транспорта и т.п.), определяются заказчиком в задании на проектирование при составлении локальных сметных расчетов (смет): для объектов, расположенных за пределами Третьего транспортного кольца города Москвы, но в пределах Московской кольцевой автомобильной дороги | CO47: 0 | CP47: =(P47+Q47+S47) -> 0 | CQ47: =ROUND((ROUND((AC47*AW47*1),2)*BC47),2) -> 0 | CR47: =(ROUND((ROUND((((ET47*1.1))*AV47*1),2)*BB47),2)+ROUND((ROUND(((AE47-((EU47*1.1)))*AV47*1),2)*BS47),2)) -> 3583.07 | CS47: =ROUND((ROUND((AE47*AV47*1),2)*BS47),2) -> 1149.87 | CT47: =ROUND((ROUND((AF47*AV47*1),2)*BA47),2) -> 63883.19 | CU47: =AG47 -> 0 | CV47: =(AH47*AV47) -> 173.53155 | CW47: =AI47 -> 0 | CX47: =AJ47 -> 0 | CY47: =S47*(BZ47/100) -> 0 | CZ47: =S47*(CA47/100) -> 0 | DE47: )*1,1 | DF47: )*1,1 | DG47: )*1,1 | DI47: )*1,1 | DJ47: )*1,1 | DN47: 112 | DO47: 70 | DP47: 1.067 | DQ47: 1.081 | DU47: 1013 | DV47: 1 км трубопровода | DW47: 1 км трубопровода | DX47: 1 | EE47: 51698335 | EF47: 30 | EG47: Строительные работы | EH47: 0 | EJ47: 1 | EK47: 2254 | EL47: ТСН-2001.3-34. 34-55-1...34-55-10 (доп. 68) | EM47: ТСН-2001.3-34-20 | EO47: Поправка: О.П. п.3.4.30.в | EQ47: 131072 | ER47: 1835.9 | ES47: 0 | ET47: 258.71 | EU47: 28.39 | EV47: 1577.19 | EW47: 147.85 | EX47: 0 | EY47: 0 | FQ47: 0 | FR47: 0 | FS47: 0 | FX47: 112 | FY47: 70 | GD47: 0 | GF47: -1068329133 | GG47: 2 | GH47: 1 | GI47: 2 | GJ47: 0 | GK47: =ROUND(R47*(S12)/100,2) -> 0 | GL47: =ROUND(IF(AND(BH47=3,BI47=3,FS47<>0),P47,0),2) -> 0 | GM47: =ROUND(O47+X47+Y47+GK47,2)+GX47 -> 0 | GN47: =IF(OR(BI47=0,BI47=1),GM47-GX47,0) -> 0 | GO47: =IF(BI47=2,GM47-GX47,0) -> 0 | GP47: =IF(BI47=4,GM47-GX47,0) -> 0 | GR47: 0 | GS47: 3 | GT47: 0 | GV47: =ROUND((GT47),6) -> 0 | GW47: 1 | GX47: =ROUND(HC47*I47,2) -> 0 | HA47: 0 | HB47: 0 | HC47: =GV47*GW47 -> 0 | HS47: 0 | IK47: 0
A48: 17 | B48: 1 | C48: =ROW(SmtRes!A49) -> 49 | D48: =ROW(EtalonRes!A52) -> 52 | E48: 11 | F48: 3.34-55-6 | G48: Добавлять на каждую последующую трубу к позиции 3.34-55-5 | H48: 1 км трубопровода | I48: =ROUND(340/1000,9) -> 0.34 | J48: 0 | K48: =ROUND(340/1000,9) -> 0.34 | O48: =ROUND(CP48,2) -> 568.22 | P48: =ROUND((ROUND((AC48*AW48*I48),2)*BC48),2) -> 0 | Q48: =(ROUND((ROUND((((ET48*1.1))*AV48*I48),2)*BB48),2)+ROUND((ROUND(((AE48-((EU48*1.1)))*AV48*I48),2)*BS48),2)) -> 102.15 | R48: =ROUND((ROUND((AE48*AV48*I48),2)*BS48),2) -> 11.21 | S48: =ROUND((ROUND((AF48*AV48*I48),2)*BA48),2) -> 466.07 | T48: =ROUND(CU48*I48,2) -> 0 | U48: =CV48*I48 -> 43.018452 | V48: =CW48*I48 -> 0 | W48: =ROUND(CX48*I48,2) -> 0 | X48: =ROUND(CY48,2) -> 522 | Y48: =ROUND(CZ48,2) -> 326.25 | AA48: 56622586 | AB48: =ROUND((AC48+AD48+AF48),6) -> 1566.279 | AC48: =ROUND((ES48),6) -> 0 | AD48: =ROUND(((((ET48*1.1))-((EU48*1.1)))+AE48),6) -> 281.567 | AE48: =ROUND(((EU48*1.1)),6) -> 30.888 | AF48: =ROUND(((EV48*1.1)),6) -> 1284.712 | AG48: =ROUND((AP48),6) -> 0 | AH48: =((EW48*1.1)) -> 118.58 | AI48: =((EX48*1.1)) -> 0 | AJ48: =(AS48) -> 0 | AK48: 1423.89 | AL48: 0 | AM48: 255.97 | AN48: 28.08 | AO48: 1167.92 | AP48: 0 | AQ48: 107.8 | AR48: 0 | AS48: 0 | AT48: 112 | AU48: 70 | AV48: 1.067 | AW48: 1.081 | AZ48: 1 | BA48: 1 | BB48: 1 | BC48: 1 | BH48: 0 | BI48: 1 | BJ48: ТСН-2001.3 Доп. 68, Сб. 34, т. 55, поз. 6 | BM48: 2254 | BN48: 0 | BP48: 0 | BQ48: 30 | BR48: 0 | BS48: 1 | BT48: 1 | BU48: 1 | BV48: 1 | BW48: 1 | BX48: 1 | BZ48: 112 | CA48: 70 | CE48: 30 | CF48: 0 | CG48: 0 | CM48: 0 | CN48: Поправка: О.П. п.3.4.30.в Наименование: В отношении объектов, реализуемых с привлечением средств бюджета города Москвы, затраты, учитывающие усложненные условия производства работ (стесненность, сложность складирования и транспортной логистики, наличие в зоне производства работ действующего технологического оборудования или движения технологического транспорта и т.п.), определяются заказчиком в задании на проектирование при составлении локальных сметных расчетов (смет): для объектов, расположенных за пределами Третьего транспортного кольца города Москвы, но в пределах Московской кольцевой автомобильной дороги | CO48: 0 | CP48: =(P48+Q48+S48) -> 568.22 | CQ48: =ROUND((ROUND((AC48*AW48*1),2)*BC48),2) -> 0 | CR48: =(ROUND((ROUND((((ET48*1.1))*AV48*1),2)*BB48),2)+ROUND((ROUND(((AE48-((EU48*1.1)))*AV48*1),2)*BS48),2)) -> 300.43 | CS48: =ROUND((ROUND((AE48*AV48*1),2)*BS48),2) -> 32.96 | CT48: =ROUND((ROUND((AF48*AV48*1),2)*BA48),2) -> 1370.79 | CU48: =AG48 -> 0 | CV48: =(AH48*AV48) -> 126.52486 | CW48: =AI48 -> 0 | CX48: =AJ48 -> 0 | CY48: =((S48*BZ48)/100) -> 521.9984 | CZ48: =((S48*CA48)/100) -> 326.249 | DE48: )*1,1 | DF48: )*1,1 | DG48: )*1,1 | DI48: )*1,1 | DJ48: )*1,1 | DN48: 0 | DO48: 0 | DP48: 1 | DQ48: 1 | DU48: 1013 | DV48: 1 км трубопровода | DW48: 1 км трубопровода | DX48: 1 | EE48: 51698335 | EF48: 30 | EG48: Строительные работы | EH48: 0 | EJ48: 1 | EK48: 2254 | EL48: ТСН-2001.3-34. 34-55-1...34-55-10 (доп. 68) | EM48: ТСН-2001.3-34-20 | EO48: Поправка: О.П. п.3.4.30.в | EQ48: 131072 | ER48: 1423.89 | ES48: 0 | ET48: 255.97 | EU48: 28.08 | EV48: 1167.92 | EW48: 107.8 | EX48: 0 | EY48: 0 | FQ48: 0 | FR48: 0 | FS48: 0 | FX48: 112 | FY48: 70 | GD48: 0 | GF48: -654616270 | GG48: 2 | GH48: 1 | GI48: -2 | GJ48: 0 | GK48: =ROUND(R48*(R12)/100,2) -> 19.62 | GL48: =ROUND(IF(AND(BH48=3,BI48=3,FS48<>0),P48,0),2) -> 0 | GM48: =ROUND(O48+X48+Y48+GK48,2)+GX48 -> 1436.09 | GN48: =IF(OR(BI48=0,BI48=1),GM48-GX48,0) -> 1436.09 | GO48: =IF(BI48=2,GM48-GX48,0) -> 0 | GP48: =IF(BI48=4,GM48-GX48,0) -> 0 | GR48: 0 | GS48: 0 | GT48: 0 | GV48: =ROUND((GT48),6) -> 0 | GW48: 1 | GX48: =ROUND(HC48*I48,2) -> 0 | HA48: 0 | HB48: 0 | HC48: =GV48*GW48 -> 0 | HS48: 0 | IK48: 0
A49: 17 | B49: 1 | C49: =ROW(SmtRes!A54) -> 54 | D49: =ROW(EtalonRes!A58) -> 58 | E49: 11 | F49: 3.34-55-6 | G49: Добавлять на каждую последующую трубу к позиции 3.34-55-5 | H49: 1 км трубопровода | I49: =ROUND(340/1000,9) -> 0.34 | J49: 0 | K49: =ROUND(340/1000,9) -> 0.34 | O49: =ROUND(CP49,2) -> 17289.45 | P49: =ROUND((ROUND((AC49*AW49*I49),2)*BC49),2) -> 0 | Q49: =(ROUND((ROUND((((ET49*1.1))*AV49*I49),2)*BB49),2)+ROUND((ROUND(((AE49-((EU49*1.1)))*AV49*I49),2)*BS49),2)) -> 1205.37 | R49: =ROUND((ROUND((AE49*AV49*I49),2)*BS49),2) -> 386.86 | S49: =ROUND((ROUND((AF49*AV49*I49),2)*BA49),2) -> 16084.08 | T49: =ROUND(CU49*I49,2) -> 0 | U49: =CV49*I49 -> 43.018452 | V49: =CW49*I49 -> 0 | W49: =ROUND(CX49*I49,2) -> 0 | X49: =ROUND(CY49,2) -> 14797.35 | Y49: =ROUND(CZ49,2) -> 6594.47 | AA49: 56616093 | AB49: =ROUND((AC49+AD49+AF49),6) -> 1566.279 | AC49: =ROUND((ES49),6) -> 0 | AD49: =ROUND(((((ET49*1.1))-((EU49*1.1)))+AE49),6) -> 281.567 | AE49: =ROUND(((EU49*1.1)),6) -> 30.888 | AF49: =ROUND(((EV49*1.1)),6) -> 1284.712 | AG49: =ROUND((AP49),6) -> 0 | AH49: =((EW49*1.1)) -> 118.58 | AI49: =((EX49*1.1)) -> 0 | AJ49: =(AS49) -> 0 | AK49: 1423.89 | AL49: 0 | AM49: 255.97 | AN49: 28.08 | AO49: 1167.92 | AP49: 0 | AQ49: 107.8 | AR49: 0 | AS49: 0 | AT49: 92 | AU49: 41 | AV49: 1.067 | AW49: 1.081 | AZ49: 1 | BA49: 34.51 | BB49: 11.8 | BC49: 1 | BH49: 0 | BI49: 1 | BJ49: ТСН-2001.3 Доп. 68, Сб. 34, т. 55, поз. 6 | BM49: 2254 | BN49: 0 | BO49: 3.34-55-6 | BP49: 1 | BQ49: 30 | BR49: 0 | BS49: 34.51 | BT49: 1 | BU49: 1 | BV49: 1 | BW49: 1 | BX49: 1 | BZ49: 92 | CA49: 41 | CE49: 30 | CF49: 0 | CG49: 0 | CM49: 0 | CN49: Поправка: О.П. п.3.4.30.в Наименование: В отношении объектов, реализуемых с привлечением средств бюджета города Москвы, затраты, учитывающие усложненные условия производства работ (стесненность, сложность складирования и транспортной логистики, наличие в зоне производства работ действующего технологического оборудования или движения технологического транспорта и т.п.), определяются заказчиком в задании на проектирование при составлении локальных сметных расчетов (смет): для объектов, расположенных за пределами Третьего транспортного кольца города Москвы, но в пределах Московской кольцевой автомобильной дороги | CO49: 0 | CP49: =(P49+Q49+S49) -> 17289.45 | CQ49: =ROUND((ROUND((AC49*AW49*1),2)*BC49),2) -> 0 | CR49: =(ROUND((ROUND((((ET49*1.1))*AV49*1),2)*BB49),2)+ROUND((ROUND(((AE49-((EU49*1.1)))*AV49*1),2)*BS49),2)) -> 3545.07 | CS49: =ROUND((ROUND((AE49*AV49*1),2)*BS49),2) -> 1137.45 | CT49: =ROUND((ROUND((AF49*AV49*1),2)*BA49),2) -> 47305.96 | CU49: =AG49 -> 0 | CV49: =(AH49*AV49) -> 126.52486 | CW49: =AI49 -> 0 | CX49: =AJ49 -> 0 | CY49: =S49*(BZ49/100) -> 14797.354 | CZ49: =S49*(CA49/100) -> 6594.4728 | DE49: )*1,1 | DF49: )*1,1 | DG49: )*1,1 | DI49: )*1,1 | DJ49: )*1,1 | DN49: 112 | DO49: 70 | DP49: 1.067 | DQ49: 1.081 | DU49: 1013 | DV49: 1 км трубопровода | DW49: 1 км трубопровода | DX49: 1 | EE49: 51698335 | EF49: 30 | EG49: Строительные работы | EH49: 0 | EJ49: 1 | EK49: 2254 | EL49: ТСН-2001.3-34. 34-55-1...34-55-10 (доп. 68) | EM49: ТСН-2001.3-34-20 | EO49: Поправка: О.П. п.3.4.30.в | EQ49: 131072 | ER49: 1423.89 | ES49: 0 | ET49: 255.97 | EU49: 28.08 | EV49: 1167.92 | EW49: 107.8 | EX49: 0 | EY49: 0 | FQ49: 0 | FR49: 0 | FS49: 0 | FX49: 112 | FY49: 70 | GD49: 0 | GF49: -654616270 | GG49: 2 | GH49: 1 | GI49: 2 | GJ49: 0 | GK49: =ROUND(R49*(S12)/100,2) -> 618.98 | GL49: =ROUND(IF(AND(BH49=3,BI49=3,FS49<>0),P49,0),2) -> 0 | GM49: =ROUND(O49+X49+Y49+GK49,2)+GX49 -> 39300.25 | GN49: =IF(OR(BI49=0,BI49=1),GM49-GX49,0) -> 39300.25 | GO49: =IF(BI49=2,GM49-GX49,0) -> 0 | GP49: =IF(BI49=4,GM49-GX49,0) -> 0 | GR49: 0 | GS49: 3 | GT49: 0 | GV49: =ROUND((GT49),6) -> 0 | GW49: 1 | GX49: =ROUND(HC49*I49,2) -> 0 | HA49: 0 | HB49: 0 | HC49: =GV49*GW49 -> 0 | HS49: 0 | IK49: 0
A50: 17 | B50: 1 | C50: =ROW(SmtRes!A59) -> 59 | D50: =ROW(EtalonRes!A64) -> 64 | E50: 12 | F50: 3.34-55-6 | G50: Добавлять на каждую последующую трубу к позиции 3.34-55-5 | H50: 1 км трубопровода | I50: 0 | J50: 0 | K50: 0 | O50: =ROUND(CP50,2) -> 0 | P50: =ROUND((ROUND((AC50*AW50*I50),2)*BC50),2) -> 0 | Q50: =(ROUND((ROUND((((ET50*1.1))*AV50*I50),2)*BB50),2)+ROUND((ROUND(((AE50-((EU50*1.1)))*AV50*I50),2)*BS50),2)) -> 0 | R50: =ROUND((ROUND((AE50*AV50*I50),2)*BS50),2) -> 0 | S50: =ROUND((ROUND((AF50*AV50*I50),2)*BA50),2) -> 0 | T50: =ROUND(CU50*I50,2) -> 0 | U50: =CV50*I50 -> 0 | V50: =CW50*I50 -> 0 | W50: =ROUND(CX50*I50,2) -> 0 | X50: =ROUND(CY50,2) -> 0 | Y50: =ROUND(CZ50,2) -> 0 | AA50: 56622586 | AB50: =ROUND((AC50+AD50+AF50),6) -> 1566.279 | AC50: =ROUND((ES50),6) -> 0 | AD50: =ROUND(((((ET50*1.1))-((EU50*1.1)))+AE50),6) -> 281.567 | AE50: =ROUND(((EU50*1.1)),6) -> 30.888 | AF50: =ROUND(((EV50*1.1)),6) -> 1284.712 | AG50: =ROUND((AP50),6) -> 0 | AH50: =((EW50*1.1)) -> 118.58 | AI50: =((EX50*1.1)) -> 0 | AJ50: =(AS50) -> 0 | AK50: 1423.89 | AL50: 0 | AM50: 255.97 | AN50: 28.08 | AO50: 1167.92 | AP50: 0 | AQ50: 107.8 | AR50: 0 | AS50: 0 | AT50: 112 | AU50: 70 | AV50: 1.067 | AW50: 1.081 | AZ50: 1 | BA50: 1 | BB50: 1 | BC50: 1 | BH50: 0 | BI50: 1 | BJ50: ТСН-2001.3 Доп. 68, Сб. 34, т. 55, поз. 6 | BM50: 2254 | BN50: 0 | BP50: 0 | BQ50: 30 | BR50: 0 | BS50: 1 | BT50: 1 | BU50: 1 | BV50: 1 | BW50: 1 | BX50: 1 | BZ50: 112 | CA50: 70 | CE50: 30 | CF50: 0 | CG50: 0 | CM50: 0 | CN50: Поправка: О.П. п.3.4.30.в Наименование: В отношении объектов, реализуемых с привлечением средств бюджета города Москвы, затраты, учитывающие усложненные условия производства работ (стесненность, сложность складирования и транспортной логистики, наличие в зоне производства работ действующего технологического оборудования или движения технологического транспорта и т.п.), определяются заказчиком в задании на проектирование при составлении локальных сметных расчетов (смет): для объектов, расположенных за пределами Третьего транспортного кольца города Москвы, но в пределах Московской кольцевой автомобильной дороги | CO50: 0 | CP50: =(P50+Q50+S50) -> 0 | CQ50: =ROUND((ROUND((AC50*AW50*1),2)*BC50),2) -> 0 | CR50: =(ROUND((ROUND((((ET50*1.1))*AV50*1),2)*BB50),2)+ROUND((ROUND(((AE50-((EU50*1.1)))*AV50*1),2)*BS50),2)) -> 300.43 | CS50: =ROUND((ROUND((AE50*AV50*1),2)*BS50),2) -> 32.96 | CT50: =ROUND((ROUND((AF50*AV50*1),2)*BA50),2) -> 1370.79 | CU50: =AG50 -> 0 | CV50: =(AH50*AV50) -> 126.52486 | CW50: =AI50 -> 0 | CX50: =AJ50 -> 0 | CY50: =((S50*BZ50)/100) -> 0 | CZ50: =((S50*CA50)/100) -> 0 | DE50: )*1,1 | DF50: )*1,1 | DG50: )*1,1 | DI50: )*1,1 | DJ50: )*1,1 | DN50: 0 | DO50: 0 | DP50: 1 | DQ50: 1 | DU50: 1013 | DV50: 1 км трубопровода | DW50: 1 км трубопровода | DX50: 1 | EE50: 51698335 | EF50: 30 | EG50: Строительные работы | EH50: 0 | EJ50: 1 | EK50: 2254 | EL50: ТСН-2001.3-34. 34-55-1...34-55-10 (доп. 68) | EM50: ТСН-2001.3-34-20 | EO50: Поправка: О.П. п.3.4.30.в | EQ50: 131072 | ER50: 1423.89 | ES50: 0 | ET50: 255.97 | EU50: 28.08 | EV50: 1167.92 | EW50: 107.8 | EX50: 0 | EY50: 0 | FQ50: 0 | FR50: 0 | FS50: 0 | FX50: 112 | FY50: 70 | GD50: 0 | GF50: -654616270 | GG50: 2 | GH50: 1 | GI50: -2 | GJ50: 0 | GK50: =ROUND(R50*(R12)/100,2) -> 0 | GL50: =ROUND(IF(AND(BH50=3,BI50=3,FS50<>0),P50,0),2) -> 0 | GM50: =ROUND(O50+X50+Y50+GK50,2)+GX50 -> 0 | GN50: =IF(OR(BI50=0,BI50=1),GM50-GX50,0) -> 0 | GO50: =IF(BI50=2,GM50-GX50,0) -> 0 | GP50: =IF(BI50=4,GM50-GX50,0) -> 0 | GR50: 0 | GS50: 0 | GT50: 0 | GV50: =ROUND((GT50),6) -> 0 | GW50: 1 | GX50: =ROUND(HC50*I50,2) -> 0 | HA50: 0 | HB50: 0 | HC50: =GV50*GW50 -> 0 | HS50: 0 | IK50: 0
A51: 17 | B51: 1 | C51: =ROW(SmtRes!A64) -> 64 | D51: =ROW(EtalonRes!A70) -> 70 | E51: 12 | F51: 3.34-55-6 | G51: Добавлять на каждую последующую трубу к позиции 3.34-55-5 | H51: 1 км трубопровода | I51: 0 | J51: 0 | K51: 0 | O51: =ROUND(CP51,2) -> 0 | P51: =ROUND((ROUND((AC51*AW51*I51),2)*BC51),2) -> 0 | Q51: =(ROUND((ROUND((((ET51*1.1))*AV51*I51),2)*BB51),2)+ROUND((ROUND(((AE51-((EU51*1.1)))*AV51*I51),2)*BS51),2)) -> 0 | R51: =ROUND((ROUND((AE51*AV51*I51),2)*BS51),2) -> 0 | S51: =ROUND((ROUND((AF51*AV51*I51),2)*BA51),2) -> 0 | T51: =ROUND(CU51*I51,2) -> 0 | U51: =CV51*I51 -> 0 | V51: =CW51*I51 -> 0 | W51: =ROUND(CX51*I51,2) -> 0 | X51: =ROUND(CY51,2) -> 0 | Y51: =ROUND(CZ51,2) -> 0 | AA51: 56616093 | AB51: =ROUND((AC51+AD51+AF51),6) -> 1566.279 | AC51: =ROUND((ES51),6) -> 0 | AD51: =ROUND(((((ET51*1.1))-((EU51*1.1)))+AE51),6) -> 281.567 | AE51: =ROUND(((EU51*1.1)),6) -> 30.888 | AF51: =ROUND(((EV51*1.1)),6) -> 1284.712 | AG51: =ROUND((AP51),6) -> 0 | AH51: =((EW51*1.1)) -> 118.58 | AI51: =((EX51*1.1)) -> 0 | AJ51: =(AS51) -> 0 | AK51: 1423.89 | AL51: 0 | AM51: 255.97 | AN51: 28.08 | AO51: 1167.92 | AP51: 0 | AQ51: 107.8 | AR51: 0 | AS51: 0 | AT51: 92 | AU51: 41 | AV51: 1.067 | AW51: 1.081 | AZ51: 1 | BA51: 34.51 | BB51: 11.8 | BC51: 1 | BH51: 0 | BI51: 1 | BJ51: ТСН-2001.3 Доп. 68, Сб. 34, т. 55, поз. 6 | BM51: 2254 | BN51: 0 | BO51: 3.34-55-6 | BP51: 1 | BQ51: 30 | BR51: 0 | BS51: 34.51 | BT51: 1 | BU51: 1 | BV51: 1 | BW51: 1 | BX51: 1 | BZ51: 92 | CA51: 41 | CE51: 30 | CF51: 0 | CG51: 0 | CM51: 0 | CN51: Поправка: О.П. п.3.4.30.в Наименование: В отношении объектов, реализуемых с привлечением средств бюджета города Москвы, затраты, учитывающие усложненные условия производства работ (стесненность, сложность складирования и транспортной логистики, наличие в зоне производства работ действующего технологического оборудования или движения технологического транспорта и т.п.), определяются заказчиком в задании на проектирование при составлении локальных сметных расчетов (смет): для объектов, расположенных за пределами Третьего транспортного кольца города Москвы, но в пределах Московской кольцевой автомобильной дороги | CO51: 0 | CP51: =(P51+Q51+S51) -> 0 | CQ51: =ROUND((ROUND((AC51*AW51*1),2)*BC51),2) -> 0 | CR51: =(ROUND((ROUND((((ET51*1.1))*AV51*1),2)*BB51),2)+ROUND((ROUND(((AE51-((EU51*1.1)))*AV51*1),2)*BS51),2)) -> 3545.07 | CS51: =ROUND((ROUND((AE51*AV51*1),2)*BS51),2) -> 1137.45 | CT51: =ROUND((ROUND((AF51*AV51*1),2)*BA51),2) -> 47305.96 | CU51: =AG51 -> 0 | CV51: =(AH51*AV51) -> 126.52486 | CW51: =AI51 -> 0 | CX51: =AJ51 -> 0 | CY51: =S51*(BZ51/100) -> 0 | CZ51: =S51*(CA51/100) -> 0 | DE51: )*1,1 | DF51: )*1,1 | DG51: )*1,1 | DI51: )*1,1 | DJ51: )*1,1 | DN51: 112 | DO51: 70 | DP51: 1.067 | DQ51: 1.081 | DU51: 1013 | DV51: 1 км трубопровода | DW51: 1 км трубопровода | DX51: 1 | EE51: 51698335 | EF51: 30 | EG51: Строительные работы | EH51: 0 | EJ51: 1 | EK51: 2254 | EL51: ТСН-2001.3-34. 34-55-1...34-55-10 (доп. 68) | EM51: ТСН-2001.3-34-20 | EO51: Поправка: О.П. п.3.4.30.в | EQ51: 131072 | ER51: 1423.89 | ES51: 0 | ET51: 255.97 | EU51: 28.08 | EV51: 1167.92 | EW51: 107.8 | EX51: 0 | EY51: 0 | FQ51: 0 | FR51: 0 | FS51: 0 | FX51: 112 | FY51: 70 | GD51: 0 | GF51: -654616270 | GG51: 2 | GH51: 1 | GI51: 2 | GJ51: 0 | GK51: =ROUND(R51*(S12)/100,2) -> 0 | GL51: =ROUND(IF(AND(BH51=3,BI51=3,FS51<>0),P51,0),2) -> 0 | GM51: =ROUND(O51+X51+Y51+GK51,2)+GX51 -> 0 | GN51: =IF(OR(BI51=0,BI51=1),GM51-GX51,0) -> 0 | GO51: =IF(BI51=2,GM51-GX51,0) -> 0 | GP51: =IF(BI51=4,GM51-GX51,0) -> 0 | GR51: 0 | GS51: 3 | GT51: 0 | GV51: =ROUND((GT51),6) -> 0 | GW51: 1 | GX51: =ROUND(HC51*I51,2) -> 0 | HA51: 0 | HB51: 0 | HC51: =GV51*GW51 -> 0 | HS51: 0 | IK51: 0
A52: 17 | B52: 1 | E52: 13 | F52: цена поставщика | G52: Трубы Энергопласт ТС DN160х8 мм F4 | H52: м | I52: 393 | J52: 0 | K52: 393 | O52: =ROUND(CP52,2) -> 37296.01 | P52: =ROUND((ROUND((AC52*AW52*I52),2)*BC52),2) -> 37296.01 | Q52: =(ROUND((ROUND((((ET52*1.1))*AV52*I52),2)*BB52),2)+ROUND((ROUND(((AE52-((EU52*1.1)))*AV52*I52),2)*BS52),2)) -> 0 | R52: =ROUND((ROUND((AE52*AV52*I52),2)*BS52),2) -> 0 | S52: =ROUND((ROUND((AF52*AV52*I52),2)*BA52),2) -> 0 | T52: =ROUND(CU52*I52,2) -> 0 | U52: =CV52*I52 -> 0 | V52: =CW52*I52 -> 0 | W52: =ROUND(CX52*I52,2) -> 0 | X52: =ROUND(CY52,2) -> 0 | Y52: =ROUND(CZ52,2) -> 0 | AA52: 56622586 | AB52: =ROUND((AC52+AD52+AF52),6) -> 94.9008 | AC52: =ROUND(((ES52*1.02)),6) -> 94.9008 | AD52: =ROUND(((((ET52*1.1))-((EU52*1.1)))+AE52),6) -> 0 | AE52: =ROUND(((EU52*1.1)),6) -> 0 | AF52: =ROUND(((EV52*1.1)),6) -> 0 | AG52: =ROUND((AP52),6) -> 0 | AH52: =((EW52*1.1)) -> 0 | AI52: =((EX52*1.1)) -> 0 | AJ52: =(AS52) -> 0 | AK52: 93.04 | AL52: 93.04 | AM52: 0 | AN52: 0 | AO52: 0 | AP52: 0 | AQ52: 0 | AR52: 0 | AS52: 0 | AT52: 0 | AU52: 0 | AV52: 1 | AW52: 1 | AZ52: 1 | BA52: 1 | BB52: 1 | BC52: 1 | BH52: 3 | BI52: 1 | BM52: 400002 | BN52: 0 | BP52: 0 | BQ52: 202 | BR52: 0 | BS52: 1 | BT52: 1 | BU52: 1 | BV52: 1 | BW52: 1 | BX52: 1 | BZ52: 0 | CA52: 0 | CE52: 30 | CF52: 0 | CG52: 0 | CM52: 0 | CN52: Поправка: О.П. п.3.4.30.в Наименование: В отношении объектов, реализуемых с привлечением средств бюджета города Москвы, затраты, учитывающие усложненные условия производства работ (стесненность, сложность складирования и транспортной логистики, наличие в зоне производства работ действующего технологического оборудования или движения технологического транспорта и т.п.), определяются заказчиком в задании на проектирование при составлении локальных сметных расчетов (смет): для объектов, расположенных за пределами Третьего транспортного кольца города Москвы, но в пределах Московской кольцевой автомобильной дороги | CO52: 0 | CP52: =(P52+Q52+S52) -> 37296.01 | CQ52: =ROUND((ROUND((AC52*AW52*1),2)*BC52),2) -> 94.9 | CR52: =(ROUND((ROUND((((ET52*1.1))*AV52*1),2)*BB52),2)+ROUND((ROUND(((AE52-((EU52*1.1)))*AV52*1),2)*BS52),2)) -> 0 | CS52: =ROUND((ROUND((AE52*AV52*1),2)*BS52),2) -> 0 | CT52: =ROUND((ROUND((AF52*AV52*1),2)*BA52),2) -> 0 | CU52: =AG52 -> 0 | CV52: =(AH52*AV52) -> 0 | CW52: =AI52 -> 0 | CX52: =AJ52 -> 0 | CY52: =((S52*BZ52)/100) -> 0 | CZ52: =((S52*CA52)/100) -> 0 | DD52: *1,02 | DE52: )*1,1 | DF52: )*1,1 | DG52: )*1,1 | DI52: )*1,1 | DJ52: )*1,1 | DN52: 0 | DO52: 0 | DP52: 1 | DQ52: 1 | DU52: 1003 | DV52: м | DW52: м | DX52: 1 | EE52: 51698006 | EF52: 202 | EG52: Материалы | EH52: 0 | EJ52: 1 | EK52: 400002 | EL52: Материалы, изделия и конструкции | EM52: Материалы | EO52: Поправка: О.П. п.3.4.30.в | EQ52: 131072 | ER52: 118.07 | ES52: 93.04 | ET52: 0 | EU52: 0 | EV52: 0 | EW52: 0 | EX52: 0 | EY52: 0 | FQ52: 0 | FR52: 0 | FS52: 0 | FX52: 0 | FY52: 0 | GA52: [906,23 / 9,74] | GD52: 0 | GF52: 955410639 | GG52: 2 | GH52: 4 | GI52: 3 | GJ52: 0 | GK52: =ROUND(R52*(R12)/100,2) -> 0 | GL52: =ROUND(IF(AND(BH52=3,BI52=3,FS52<>0),P52,0),2) -> 0 | GM52: =ROUND(O52+X52+Y52+GK52,2)+GX52 -> 37296.01 | GN52: =IF(OR(BI52=0,BI52=1),GM52-GX52,0) -> 37296.01 | GO52: =IF(BI52=2,GM52-GX52,0) -> 0 | GP52: =IF(BI52=4,GM52-GX52,0) -> 0 | GR52: 0 | GS52: 2 | GT52: 0 | GV52: =ROUND((GT52),6) -> 0 | GW52: 1 | GX52: =ROUND(HC52*I52,2) -> 0 | HA52: 0 | HB52: 0 | HC52: =GV52*GW52 -> 0 | HE52: 0 | HF52: 0 | HS52: 0 | IK52: 0
A53: 17 | B53: 1 | E53: 13 | F53: цена поставщика | G53: Трубы Энергопласт ТС DN160х8 мм F4 | H53: м | I53: 393 | J53: 0 | K53: 393 | O53: =ROUND(CP53,2) -> 363263.14 | P53: =ROUND((ROUND((AC53*AW53*I53),2)*BC53),2) -> 363263.14 | Q53: =(ROUND((ROUND((((ET53*1.1))*AV53*I53),2)*BB53),2)+ROUND((ROUND(((AE53-((EU53*1.1)))*AV53*I53),2)*BS53),2)) -> 0 | R53: =ROUND((ROUND((AE53*AV53*I53),2)*BS53),2) -> 0 | S53: =ROUND((ROUND((AF53*AV53*I53),2)*BA53),2) -> 0 | T53: =ROUND(CU53*I53,2) -> 0 | U53: =CV53*I53 -> 0 | V53: =CW53*I53 -> 0 | W53: =ROUND(CX53*I53,2) -> 0 | X53: =ROUND(CY53,2) -> 0 | Y53: =ROUND(CZ53,2) -> 0 | AA53: 56616093 | AB53: =ROUND((AC53+AD53+AF53),6) -> 94.9008 | AC53: =ROUND(((ES53*1.02)),6) -> 94.9008 | AD53: =ROUND(((((ET53*1.1))-((EU53*1.1)))+AE53),6) -> 0 | AE53: =ROUND(((EU53*1.1)),6) -> 0 | AF53: =ROUND(((EV53*1.1)),6) -> 0 | AG53: =ROUND((AP53),6) -> 0 | AH53: =((EW53*1.1)) -> 0 | AI53: =((EX53*1.1)) -> 0 | AJ53: =(AS53) -> 0 | AK53: 93.04 | AL53: 93.04 | AM53: 0 | AN53: 0 | AO53: 0 | AP53: 0 | AQ53: 0 | AR53: 0 | AS53: 0 | AT53: 0 | AU53: 0 | AV53: 1 | AW53: 1 | AZ53: 1 | BA53: 1 | BB53: 1 | BC53: 9.74 | BH53: 3 | BI53: 1 | BM53: 400002 | BN53: 0 | BP53: 0 | BQ53: 202 | BR53: 0 | BS53: 1 | BT53: 1 | BU53: 1 | BV53: 1 | BW53: 1 | BX53: 1 | BZ53: 0 | CA53: 0 | CE53: 30 | CF53: 0 | CG53: 0 | CM53: 0 | CN53: Поправка: О.П. п.3.4.30.в Наименование: В отношении объектов, реализуемых с привлечением средств бюджета города Москвы, затраты, учитывающие усложненные условия производства работ (стесненность, сложность складирования и транспортной логистики, наличие в зоне производства работ действующего технологического оборудования или движения технологического транспорта и т.п.), определяются заказчиком в задании на проектирование при составлении локальных сметных расчетов (смет): для объектов, расположенных за пределами Третьего транспортного кольца города Москвы, но в пределах Московской кольцевой автомобильной дороги | CO53: 0 | CP53: =(P53+Q53+S53) -> 363263.14 | CQ53: =ROUND((ROUND((AC53*AW53*1),2)*BC53),2) -> 924.33 | CR53: =(ROUND((ROUND((((ET53*1.1))*AV53*1),2)*BB53),2)+ROUND((ROUND(((AE53-((EU53*1.1)))*AV53*1),2)*BS53),2)) -> 0 | CS53: =ROUND((ROUND((AE53*AV53*1),2)*BS53),2) -> 0 | CT53: =ROUND((ROUND((AF53*AV53*1),2)*BA53),2) -> 0 | CU53: =AG53 -> 0 | CV53: =(AH53*AV53) -> 0 | CW53: =AI53 -> 0 | CX53: =AJ53 -> 0 | CY53: =S53*(BZ53/100) -> 0 | CZ53: =S53*(CA53/100) -> 0 | DD53: *1,02 | DE53: )*1,1 | DF53: )*1,1 | DG53: )*1,1 | DI53: )*1,1 | DJ53: )*1,1 | DN53: 0 | DO53: 0 | DP53: 1 | DQ53: 1 | DU53: 1003 | DV53: м | DW53: м | DX53: 1 | EE53: 51698006 | EF53: 202 | EG53: Материалы | EH53: 0 | EJ53: 1 | EK53: 400002 | EL53: Материалы, изделия и конструкции | EM53: Материалы | EO53: Поправка: О.П. п.3.4.30.в | EQ53: 131072 | ER53: 93.04 | ES53: 93.04 | ET53: 0 | EU53: 0 | EV53: 0 | EW53: 0 | EX53: 0 | EY53: 0 | EZ53: 5 | FC53: 0 | FD53: 18 | FF53: 906.23 | FQ53: 0 | FR53: 0 | FS53: 0 | FX53: 0 | FY53: 0 | GA53: [906,23 / 9,74] | GD53: 0 | GF53: 955410639 | GG53: 2 | GH53: 3 | GI53: 3 | GJ53: 0 | GK53: =ROUND(R53*(S12)/100,2) -> 0 | GL53: =ROUND(IF(AND(BH53=3,BI53=3,FS53<>0),P53,0),2) -> 0 | GM53: =ROUND(O53+X53+Y53+GK53,2)+GX53 -> 363263.14 | GN53: =IF(OR(BI53=0,BI53=1),GM53-GX53,0) -> 363263.14 | GO53: =IF(BI53=2,GM53-GX53,0) -> 0 | GP53: =IF(BI53=4,GM53-GX53,0) -> 0 | GR53: 1 | GS53: 1 | GT53: 0 | GV53: =ROUND((GT53),6) -> 0 | GW53: 1 | GX53: =ROUND(HC53*I53,2) -> 0 | HA53: 0 | HB53: 0 | HC53: =GV53*GW53 -> 0 | HE53: 0 | HF53: 0 | HS53: 0 | IK53: 0
A54: 17 | B54: 1 | E54: 14 | F54: 1.12-3-62 | G54: Заглушки (пробки) полиэтиленовые ПКП-2 для каналов кабельной канализации из асбестоцементных труб внутренним диаметром 150 мм | H54: шт. | I54: 36 | J54: 0 | K54: 36 | O54: =ROUND(CP54,2) -> 140.4 | P54: =ROUND((ROUND((AC54*AW54*I54),2)*BC54),2) -> 140.4 | Q54: =(ROUND((ROUND((((ET54*1.1))*AV54*I54),2)*BB54),2)+ROUND((ROUND(((AE54-((EU54*1.1)))*AV54*I54),2)*BS54),2)) -> 0 | R54: =ROUND((ROUND((AE54*AV54*I54),2)*BS54),2) -> 0 | S54: =ROUND((ROUND((AF54*AV54*I54),2)*BA54),2) -> 0 | T54: =ROUND(CU54*I54,2) -> 0 | U54: =CV54*I54 -> 0 | V54: =CW54*I54 -> 0 | W54: =ROUND(CX54*I54,2) -> 0 | X54: =ROUND(CY54,2) -> 0 | Y54: =ROUND(CZ54,2) -> 0 | AA54: 56622586 | AB54: =ROUND((AC54+AD54+AF54),6) -> 3.9 | AC54: =ROUND((ES54),6) -> 3.9 | AD54: =ROUND(((((ET54*1.1))-((EU54*1.1)))+AE54),6) -> 0 | AE54: =ROUND(((EU54*1.1)),6) -> 0 | AF54: =ROUND(((EV54*1.1)),6) -> 0 | AG54: =ROUND((AP54),6) -> 0 | AH54: =((EW54*1.1)) -> 0 | AI54: =((EX54*1.1)) -> 0 | AJ54: =(AS54) -> 0 | AK54: 3.9 | AL54: 3.9 | AM54: 0 | AN54: 0 | AO54: 0 | AP54: 0 | AQ54: 0 | AR54: 0 | AS54: 0 | AT54: 0 | AU54: 0 | AV54: 1 | AW54: 1 | AZ54: 1 | BA54: 1 | BB54: 1 | BC54: 1 | BH54: 3 | BI54: 1 | BJ54: ТСН-2001.1 Доп. 70, Р. 12, о. 3, поз. 62 | BM54: 1617 | BN54: 0 | BP54: 0 | BQ54: 200 | BR54: 0 | BS54: 1 | BT54: 1 | BU54: 1 | BV54: 1 | BW54: 1 | BX54: 1 | BZ54: 0 | CA54: 0 | CE54: 30 | CF54: 0 | CG54: 0 | CM54: 0 | CN54: Поправка: О.П. п.3.4.30.в Наименование: В отношении объектов, реализуемых с привлечением средств бюджета города Москвы, затраты, учитывающие усложненные условия производства работ (стесненность, сложность складирования и транспортной логистики, наличие в зоне производства работ действующего технологического оборудования или движения технологического транспорта и т.п.), определяются заказчиком в задании на проектирование при составлении локальных сметных расчетов (смет): для объектов, расположенных за пределами Третьего транспортного кольца города Москвы, но в пределах Московской кольцевой автомобильной дороги | CO54: 0 | CP54: =(P54+Q54+S54) -> 140.4 | CQ54: =ROUND((ROUND((AC54*AW54*1),2)*BC54),2) -> 3.9 | CR54: =(ROUND((ROUND((((ET54*1.1))*AV54*1),2)*BB54),2)+ROUND((ROUND(((AE54-((EU54*1.1)))*AV54*1),2)*BS54),2)) -> 0 | CS54: =ROUND((ROUND((AE54*AV54*1),2)*BS54),2) -> 0 | CT54: =ROUND((ROUND((AF54*AV54*1),2)*BA54),2) -> 0 | CU54: =AG54 -> 0 | CV54: =(AH54*AV54) -> 0 | CW54: =AI54 -> 0 | CX54: =AJ54 -> 0 | CY54: =((S54*BZ54)/100) -> 0 | CZ54: =((S54*CA54)/100) -> 0 | DE54: )*1,1 | DF54: )*1,1 | DG54: )*1,1 | DI54: )*1,1 | DJ54: )*1,1 | DN54: 0 | DO54: 0 | DP54: 1 | DQ54: 1 | DU54: 1010 | DV54: шт. | DW54: шт. | DX54: 1 | EE54: 51697656 | EF54: 200 | EG54: Материалы строительные | EH54: 0 | EJ54: 1 | EK54: 1617 | EL54: ТСН-2001.1 Материалы строительные | EM54: ТСН-2001.1-1 | EO54: Поправка: О.П. п.3.4.30.в | EQ54: 131072 | ER54: 3.9 | ES54: 3.9 | ET54: 0 | EU54: 0 | EV54: 0 | EW54: 0 | EX54: 0 | EY54: 0 | FQ54: 0 | FR54: 0 | FS54: 0 | FX54: 0 | FY54: 0 | GD54: 0 | GF54: -1761022056 | GG54: 2 | GH54: 1 | GI54: -2 | GJ54: 0 | GK54: =ROUND(R54*(R12)/100,2) -> 0 | GL54: =ROUND(IF(AND(BH54=3,BI54=3,FS54<>0),P54,0),2) -> 0 | GM54: =ROUND(O54+X54+Y54+GK54,2)+GX54 -> 140.4 | GN54: =IF(OR(BI54=0,BI54=1),GM54-GX54,0) -> 140.4 | GO54: =IF(BI54=2,GM54-GX54,0) -> 0 | GP54: =IF(BI54=4,GM54-GX54,0) -> 0 | GR54: 0 | GS54: 0 | GT54: 0 | GV54: =ROUND((GT54),6) -> 0 | GW54: 1 | GX54: =ROUND(HC54*I54,2) -> 0 | HA54: 0 | HB54: 0 | HC54: =GV54*GW54 -> 0 | HS54: 0 | IK54: 0
A55: 17 | B55: 1 | E55: 14 | F55: 1.12-3-62 | G55: Заглушки (пробки) полиэтиленовые ПКП-2 для каналов кабельной канализации из асбестоцементных труб внутренним диаметром 150 мм | H55: шт. | I55: 36 | J55: 0 | K55: 36 | O55: =ROUND(CP55,2) -> 1955.77 | P55: =ROUND((ROUND((AC55*AW55*I55),2)*BC55),2) -> 1955.77 | Q55: =(ROUND((ROUND((((ET55*1.1))*AV55*I55),2)*BB55),2)+ROUND((ROUND(((AE55-((EU55*1.1)))*AV55*I55),2)*BS55),2)) -> 0 | R55: =ROUND((ROUND((AE55*AV55*I55),2)*BS55),2) -> 0 | S55: =ROUND((ROUND((AF55*AV55*I55),2)*BA55),2) -> 0 | T55: =ROUND(CU55*I55,2) -> 0 | U55: =CV55*I55 -> 0 | V55: =CW55*I55 -> 0 | W55: =ROUND(CX55*I55,2) -> 0 | X55: =ROUND(CY55,2) -> 0 | Y55: =ROUND(CZ55,2) -> 0 | AA55: 56616093 | AB55: =ROUND((AC55+AD55+AF55),6) -> 3.9 | AC55: =ROUND((ES55),6) -> 3.9 | AD55: =ROUND(((((ET55*1.1))-((EU55*1.1)))+AE55),6) -> 0 | AE55: =ROUND(((EU55*1.1)),6) -> 0 | AF55: =ROUND(((EV55*1.1)),6) -> 0 | AG55: =ROUND((AP55),6) -> 0 | AH55: =((EW55*1.1)) -> 0 | AI55: =((EX55*1.1)) -> 0 | AJ55: =(AS55) -> 0 | AK55: 3.9 | AL55: 3.9 | AM55: 0 | AN55: 0 | AO55: 0 | AP55: 0 | AQ55: 0 | AR55: 0 | AS55: 0 | AT55: 0 | AU55: 0 | AV55: 1 | AW55: 1 | AZ55: 1 | BA55: 1 | BB55: 1 | BC55: 13.93 | BH55: 3 | BI55: 1 | BJ55: ТСН-2001.1 Доп. 70, Р. 12, о. 3, поз. 62 | BM55: 1617 | BN55: 0 | BO55: 1.12-3-62 | BP55: 1 | BQ55: 200 | BR55: 0 | BS55: 1 | BT55: 1 | BU55: 1 | BV55: 1 | BW55: 1 | BX55: 1 | BZ55: 0 | CA55: 0 | CE55: 30 | CF55: 0 | CG55: 0 | CM55: 0 | CN55: Поправка: О.П. п.3.4.30.в Наименование: В отношении объектов, реализуемых с привлечением средств бюджета города Москвы, затраты, учитывающие усложненные условия производства работ (стесненность, сложность складирования и транспортной логистики, наличие в зоне производства работ действующего технологического оборудования или движения технологического транспорта и т.п.), определяются заказчиком в задании на проектирование при составлении локальных сметных расчетов (смет): для объектов, расположенных за пределами Третьего транспортного кольца города Москвы, но в пределах Московской кольцевой автомобильной дороги | CO55: 0 | CP55: =(P55+Q55+S55) -> 1955.77 | CQ55: =ROUND((ROUND((AC55*AW55*1),2)*BC55),2) -> 54.33 | CR55: =(ROUND((ROUND((((ET55*1.1))*AV55*1),2)*BB55),2)+ROUND((ROUND(((AE55-((EU55*1.1)))*AV55*1),2)*BS55),2)) -> 0 | CS55: =ROUND((ROUND((AE55*AV55*1),2)*BS55),2) -> 0 | CT55: =ROUND((ROUND((AF55*AV55*1),2)*BA55),2) -> 0 | CU55: =AG55 -> 0 | CV55: =(AH55*AV55) -> 0 | CW55: =AI55 -> 0 | CX55: =AJ55 -> 0 | CY55: =S55*(BZ55/100) -> 0 | CZ55: =S55*(CA55/100) -> 0 | DE55: )*1,1 | DF55: )*1,1 | DG55: )*1,1 | DI55: )*1,1 | DJ55: )*1,1 | DN55: 0 | DO55: 0 | DP55: 1 | DQ55: 1 | DU55: 1010 | DV55: шт. | DW55: шт. | DX55: 1 | EE55: 51697656 | EF55: 200 | EG55: Материалы строительные | EH55: 0 | EJ55: 1 | EK55: 1617 | EL55: ТСН-2001.1 Материалы строительные | EM55: ТСН-2001.1-1 | EO55: Поправка: О.П. п.3.4.30.в | EQ55: 131072 | ER55: 3.9 | ES55: 3.9 | ET55: 0 | EU55: 0 | EV55: 0 | EW55: 0 | EX55: 0 | EY55: 0 | FQ55: 0 | FR55: 0 | FS55: 0 | FX55: 0 | FY55: 0 | GD55: 0 | GF55: -1761022056 | GG55: 2 | GH55: 1 | GI55: 2 | GJ55: 0 | GK55: =ROUND(R55*(S12)/100,2) -> 0 | GL55: =ROUND(IF(AND(BH55=3,BI55=3,FS55<>0),P55,0),2) -> 0 | GM55: =ROUND(O55+X55+Y55+GK55,2)+GX55 -> 1955.77 | GN55: =IF(OR(BI55=0,BI55=1),GM55-GX55,0) -> 1955.77 | GO55: =IF(BI55=2,GM55-GX55,0) -> 0 | GP55: =IF(BI55=4,GM55-GX55,0) -> 0 | GR55: 0 | GS55: 3 | GT55: 0 | GV55: =ROUND((GT55),6) -> 0 | GW55: 1 | GX55: =ROUND(HC55*I55,2) -> 0 | HA55: 0 | HB55: 0 | HC55: =GV55*GW55 -> 0 | HS55: 0 | IK55: 0
A56: 17 | B56: 1 | E56: 15 | F56: 1.1-1-766 | G56: Песок для строительных работ, рядовой (карьерный) | H56: м3 | I56: 23.46 | J56: 0 | K56: 23.46 | O56: =ROUND(CP56,2) -> 2463.07 | P56: =ROUND((ROUND((AC56*AW56*I56),2)*BC56),2) -> 2463.07 | Q56: =(ROUND((ROUND((((ET56*1.1))*AV56*I56),2)*BB56),2)+ROUND((ROUND(((AE56-((EU56*1.1)))*AV56*I56),2)*BS56),2)) -> 0 | R56: =ROUND((ROUND((AE56*AV56*I56),2)*BS56),2) -> 0 | S56: =ROUND((ROUND((AF56*AV56*I56),2)*BA56),2) -> 0 | T56: =ROUND(CU56*I56,2) -> 0 | U56: =CV56*I56 -> 0 | V56: =CW56*I56 -> 0 | W56: =ROUND(CX56*I56,2) -> 0 | X56: =ROUND(CY56,2) -> 0 | Y56: =ROUND(CZ56,2) -> 0 | AA56: 56622586 | AB56: =ROUND((AC56+AD56+AF56),6) -> 104.99 | AC56: =ROUND((ES56),6) -> 104.99 | AD56: =ROUND(((((ET56*1.1))-((EU56*1.1)))+AE56),6) -> 0 | AE56: =ROUND(((EU56*1.1)),6) -> 0 | AF56: =ROUND(((EV56*1.1)),6) -> 0 | AG56: =ROUND((AP56),6) -> 0 | AH56: =((EW56*1.1)) -> 0 | AI56: =((EX56*1.1)) -> 0 | AJ56: =(AS56) -> 0 | AK56: 104.99 | AL56: 104.99 | AM56: 0 | AN56: 0 | AO56: 0 | AP56: 0 | AQ56: 0 | AR56: 0 | AS56: 0 | AT56: 0 | AU56: 0 | AV56: 1 | AW56: 1 | AZ56: 1 | BA56: 1 | BB56: 1 | BC56: 1 | BH56: 3 | BI56: 1 | BJ56: ТСН-2001.1 Доп. 69, Р. 1, о. 1, поз. 766 | BM56: 1617 | BN56: 0 | BP56: 0 | BQ56: 200 | BR56: 0 | BS56: 1 | BT56: 1 | BU56: 1 | BV56: 1 | BW56: 1 | BX56: 1 | BZ56: 0 | CA56: 0 | CE56: 30 | CF56: 0 | CG56: 0 | CM56: 0 | CN56: Поправка: О.П. п.3.4.30.в Наименование: В отношении объектов, реализуемых с привлечением средств бюджета города Москвы, затраты, учитывающие усложненные условия производства работ (стесненность, сложность складирования и транспортной логистики, наличие в зоне производства работ действующего технологического оборудования или движения технологического транспорта и т.п.), определяются заказчиком в задании на проектирование при составлении локальных сметных расчетов (смет): для объектов, расположенных за пределами Третьего транспортного кольца города Москвы, но в пределах Московской кольцевой автомобильной дороги | CO56: 0 | CP56: =(P56+Q56+S56) -> 2463.07 | CQ56: =ROUND((ROUND((AC56*AW56*1),2)*BC56),2) -> 104.99 | CR56: =(ROUND((ROUND((((ET56*1.1))*AV56*1),2)*BB56),2)+ROUND((ROUND(((AE56-((EU56*1.1)))*AV56*1),2)*BS56),2)) -> 0 | CS56: =ROUND((ROUND((AE56*AV56*1),2)*BS56),2) -> 0 | CT56: =ROUND((ROUND((AF56*AV56*1),2)*BA56),2) -> 0 | CU56: =AG56 -> 0 | CV56: =(AH56*AV56) -> 0 | CW56: =AI56 -> 0 | CX56: =AJ56 -> 0 | CY56: =((S56*BZ56)/100) -> 0 | CZ56: =((S56*CA56)/100) -> 0 | DE56: )*1,1 | DF56: )*1,1 | DG56: )*1,1 | DI56: )*1,1 | DJ56: )*1,1 | DN56: 0 | DO56: 0 | DP56: 1 | DQ56: 1 | DU56: 1007 | DV56: м3 | DW56: м3 | DX56: 1 | EE56: 51697656 | EF56: 200 | EG56: Материалы строительные | EH56: 0 | EJ56: 1 | EK56: 1617 | EL56: ТСН-2001.1 Материалы строительные | EM56: ТСН-2001.1-1 | EO56: Поправка: О.П. п.3.4.30.в | EQ56: 131072 | ER56: 104.99 | ES56: 104.99 | ET56: 0 | EU56: 0 | EV56: 0 | EW56: 0 | EX56: 0 | EY56: 0 | FQ56: 0 | FR56: 0 | FS56: 0 | FX56: 0 | FY56: 0 | GD56: 0 | GF56: -449487181 | GG56: 2 | GH56: 1 | GI56: -2 | GJ56: 0 | GK56: =ROUND(R56*(R12)/100,2) -> 0 | GL56: =ROUND(IF(AND(BH56=3,BI56=3,FS56<>0),P56,0),2) -> 0 | GM56: =ROUND(O56+X56+Y56+GK56,2)+GX56 -> 2463.07 | GN56: =IF(OR(BI56=0,BI56=1),GM56-GX56,0) -> 2463.07 | GO56: =IF(BI56=2,GM56-GX56,0) -> 0 | GP56: =IF(BI56=4,GM56-GX56,0) -> 0 | GR56: 0 | GS56: 0 | GT56: 0 | GV56: =ROUND((GT56),6) -> 0 | GW56: 1 | GX56: =ROUND(HC56*I56,2) -> 0 | HA56: 0 | HB56: 0 | HC56: =GV56*GW56 -> 0 | HS56: 0 | IK56: 0
A57: 17 | B57: 1 | E57: 15 | F57: 1.1-1-766 | G57: Песок для строительных работ, рядовой (карьерный) | H57: м3 | I57: 23.46 | J57: 0 | K57: 23.46 | O57: =ROUND(CP57,2) -> 18941.01 | P57: =ROUND((ROUND((AC57*AW57*I57),2)*BC57),2) -> 18941.01 | Q57: =(ROUND((ROUND((((ET57*1.1))*AV57*I57),2)*BB57),2)+ROUND((ROUND(((AE57-((EU57*1.1)))*AV57*I57),2)*BS57),2)) -> 0 | R57: =ROUND((ROUND((AE57*AV57*I57),2)*BS57),2) -> 0 | S57: =ROUND((ROUND((AF57*AV57*I57),2)*BA57),2) -> 0 | T57: =ROUND(CU57*I57,2) -> 0 | U57: =CV57*I57 -> 0 | V57: =CW57*I57 -> 0 | W57: =ROUND(CX57*I57,2) -> 0 | X57: =ROUND(CY57,2) -> 0 | Y57: =ROUND(CZ57,2) -> 0 | AA57: 56616093 | AB57: =ROUND((AC57+AD57+AF57),6) -> 104.99 | AC57: =ROUND((ES57),6) -> 104.99 | AD57: =ROUND(((((ET57*1.1))-((EU57*1.1)))+AE57),6) -> 0 | AE57: =ROUND(((EU57*1.1)),6) -> 0 | AF57: =ROUND(((EV57*1.1)),6) -> 0 | AG57: =ROUND((AP57),6) -> 0 | AH57: =((EW57*1.1)) -> 0 | AI57: =((EX57*1.1)) -> 0 | AJ57: =(AS57) -> 0 | AK57: 104.99 | AL57: 104.99 | AM57: 0 | AN57: 0 | AO57: 0 | AP57: 0 | AQ57: 0 | AR57: 0 | AS57: 0 | AT57: 0 | AU57: 0 | AV57: 1 | AW57: 1 | AZ57: 1 | BA57: 1 | BB57: 1 | BC57: 7.69 | BH57: 3 | BI57: 1 | BJ57: ТСН-2001.1 Доп. 69, Р. 1, о. 1, поз. 766 | BM57: 1617 | BN57: 0 | BO57: 1.1-1-766 | BP57: 1 | BQ57: 200 | BR57: 0 | BS57: 1 | BT57: 1 | BU57: 1 | BV57: 1 | BW57: 1 | BX57: 1 | BZ57: 0 | CA57: 0 | CE57: 30 | CF57: 0 | CG57: 0 | CM57: 0 | CN57: Поправка: О.П. п.3.4.30.в Наименование: В отношении объектов, реализуемых с привлечением средств бюджета города Москвы, затраты, учитывающие усложненные условия производства работ (стесненность, сложность складирования и транспортной логистики, наличие в зоне производства работ действующего технологического оборудования или движения технологического транспорта и т.п.), определяются заказчиком в задании на проектирование при составлении локальных сметных расчетов (смет): для объектов, расположенных за пределами Третьего транспортного кольца города Москвы, но в пределах Московской кольцевой автомобильной дороги | CO57: 0 | CP57: =(P57+Q57+S57) -> 18941.01 | CQ57: =ROUND((ROUND((AC57*AW57*1),2)*BC57),2) -> 807.37 | CR57: =(ROUND((ROUND((((ET57*1.1))*AV57*1),2)*BB57),2)+ROUND((ROUND(((AE57-((EU57*1.1)))*AV57*1),2)*BS57),2)) -> 0 | CS57: =ROUND((ROUND((AE57*AV57*1),2)*BS57),2) -> 0 | CT57: =ROUND((ROUND((AF57*AV57*1),2)*BA57),2) -> 0 | CU57: =AG57 -> 0 | CV57: =(AH57*AV57) -> 0 | CW57: =AI57 -> 0 | CX57: =AJ57 -> 0 | CY57: =S57*(BZ57/100) -> 0 | CZ57: =S57*(CA57/100) -> 0 | DE57: )*1,1 | DF57: )*1,1 | DG57: )*1,1 | DI57: )*1,1 | DJ57: )*1,1 | DN57: 0 | DO57: 0 | DP57: 1 | DQ57: 1 | DU57: 1007 | DV57: м3 | DW57: м3 | DX57: 1 | EE57: 51697656 | EF57: 200 | EG57: Материалы строительные | EH57: 0 | EJ57: 1 | EK57: 1617 | EL57: ТСН-2001.1 Материалы строительные | EM57: ТСН-2001.1-1 | EO57: Поправка: О.П. п.3.4.30.в | EQ57: 131072 | ER57: 104.99 | ES57: 104.99 | ET57: 0 | EU57: 0 | EV57: 0 | EW57: 0 | EX57: 0 | EY57: 0 | FQ57: 0 | FR57: 0 | FS57: 0 | FX57: 0 | FY57: 0 | GD57: 0 | GF57: -449487181 | GG57: 2 | GH57: 1 | GI57: 2 | GJ57: 0 | GK57: =ROUND(R57*(S12)/100,2) -> 0 | GL57: =ROUND(IF(AND(BH57=3,BI57=3,FS57<>0),P57,0),2) -> 0 | GM57: =ROUND(O57+X57+Y57+GK57,2)+GX57 -> 18941.01 | GN57: =IF(OR(BI57=0,BI57=1),GM57-GX57,0) -> 18941.01 | GO57: =IF(BI57=2,GM57-GX57,0) -> 0 | GP57: =IF(BI57=4,GM57-GX57,0) -> 0 | GR57: 0 | GS57: 3 | GT57: 0 | GV57: =ROUND((GT57),6) -> 0 | GW57: 1 | GX57: =ROUND(HC57*I57,2) -> 0 | HA57: 0 | HB57: 0 | HC57: =GV57*GW57 -> 0 | HS57: 0 | IK57: 0
A58: 17 | B58: 1 | C58: =ROW(SmtRes!A73) -> 73 | D58: =ROW(EtalonRes!A81) -> 81 | E58: 16 | F58: 3.13-30-1 | G58: Огнезащитное покрытие терморасширяющимися составами электрических кабелей с применением окрасочного безвоздушного агрегата | H58: 100 м2 покрытия | I58: 0 | J58: 0 | K58: 0 | O58: =ROUND(CP58,2) -> 0 | P58: =ROUND((ROUND((AC58*AW58*I58),2)*BC58),2) -> 0 | Q58: =(ROUND((ROUND((((ET58*1.1))*AV58*I58),2)*BB58),2)+ROUND((ROUND(((AE58-((EU58*1.1)))*AV58*I58),2)*BS58),2)) -> 0 | R58: =ROUND((ROUND((AE58*AV58*I58),2)*BS58),2) -> 0 | S58: =ROUND((ROUND((AF58*AV58*I58),2)*BA58),2) -> 0 | T58: =ROUND(CU58*I58,2) -> 0 | U58: =CV58*I58 -> 0 | V58: =CW58*I58 -> 0 | W58: =ROUND(CX58*I58,2) -> 0 | X58: =ROUND(CY58,2) -> 0 | Y58: =ROUND(CZ58,2) -> 0 | AA58: 56622586 | AB58: =ROUND((AC58+AD58+AF58),6) -> 3080.004 | AC58: =ROUND((ES58),6) -> 516.41 | AD58: =ROUND(((((ET58*1.1))-((EU58*1.1)))+AE58),6) -> 439.593 | AE58: =ROUND(((EU58*1.1)),6) -> 0.649 | AF58: =ROUND(((EV58*1.1)),6) -> 2124.001 | AG58: =ROUND((AP58),6) -> 0 | AH58: =((EW58*1.1)) -> 148.5 | AI58: =((EX58*1.1)) -> 0 | AJ58: =(AS58) -> 0 | AK58: 2846.95 | AL58: 516.41 | AM58: 399.63 | AN58: 0.59 | AO58: 1930.91 | AP58: 0 | AQ58: 135 | AR58: 0 | AS58: 0 | AT58: 105 | AU58: 77 | AV58: 1.047 | AW58: 1 | AZ58: 1 | BA58: 1 | BB58: 1 | BC58: 1 | BH58: 0 | BI58: 1 | BJ58: ТСН-2001.3 Доп. 71, Сб. 13, т. 30, поз. 1 | BM58: 99 | BN58: 0 | BP58: 0 | BQ58: 30 | BR58: 0 | BS58: 1 | BT58: 1 | BU58: 1 | BV58: 1 | BW58: 1 | BX58: 1 | BZ58: 105 | CA58: 77 | CE58: 30 | CF58: 0 | CG58: 0 | CM58: 0 | CN58: Поправка: О.П. п.3.4.30.в Наименование: В отношении объектов, реализуемых с привлечением средств бюджета города Москвы, затраты, учитывающие усложненные условия производства работ (стесненность, сложность складирования и транспортной логистики, наличие в зоне производства работ действующего технологического оборудования или движения технологического транспорта и т.п.), определяются заказчиком в задании на проектирование при составлении локальных сметных расчетов (смет): для объектов, расположенных за пределами Третьего транспортного кольца города Москвы, но в пределах Московской кольцевой автомобильной дороги | CO58: 0 | CP58: =(P58+Q58+S58) -> 0 | CQ58: =ROUND((ROUND((AC58*AW58*1),2)*BC58),2) -> 516.41 | CR58: =(ROUND((ROUND((((ET58*1.1))*AV58*1),2)*BB58),2)+ROUND((ROUND(((AE58-((EU58*1.1)))*AV58*1),2)*BS58),2)) -> 460.25 | CS58: =ROUND((ROUND((AE58*AV58*1),2)*BS58),2) -> 0.68 | CT58: =ROUND((ROUND((AF58*AV58*1),2)*BA58),2) -> 2223.83 | CU58: =AG58 -> 0 | CV58: =(AH58*AV58) -> 155.4795 | CW58: =AI58 -> 0 | CX58: =AJ58 -> 0 | CY58: =((S58*BZ58)/100) -> 0 | CZ58: =((S58*CA58)/100) -> 0 | DE58: )*1,1 | DF58: )*1,1 | DG58: )*1,1 | DI58: )*1,1 | DJ58: )*1,1 | DN58: 0 | DO58: 0 | DP58: 1 | DQ58: 1 | DU58: 1013 | DV58: 100 м2 покрытия | DW58: 100 м2 покрытия | DX58: 1 | EE58: 51696138 | EF58: 30 | EG58: Строительные работы | EH58: 0 | EJ58: 1 | EK58: 99 | EL58: ТСН-2001.3-13. 13-17-6, 13-17-7, 13-18...13-38 | EM58: ТСН-2001.3-13-3 | EO58: Поправка: О.П. п.3.4.30.в | EQ58: 131072 | ER58: 2846.95 | ES58: 516.41 | ET58: 399.63 | EU58: 0.59 | EV58: 1930.91 | EW58: 135 | EX58: 0 | EY58: 0 | FQ58: 0 | FR58: 0 | FS58: 0 | FX58: 105 | FY58: 77 | GD58: 0 | GF58: 448414653 | GG58: 2 | GH58: 1 | GI58: -2 | GJ58: 0 | GK58: =ROUND(R58*(R12)/100,2) -> 0 | GL58: =ROUND(IF(AND(BH58=3,BI58=3,FS58<>0),P58,0),2) -> 0 | GM58: =ROUND(O58+X58+Y58+GK58,2)+GX58 -> 0 | GN58: =IF(OR(BI58=0,BI58=1),GM58-GX58,0) -> 0 | GO58: =IF(BI58=2,GM58-GX58,0) -> 0 | GP58: =IF(BI58=4,GM58-GX58,0) -> 0 | GR58: 0 | GS58: 0 | GT58: 0 | GV58: =ROUND((GT58),6) -> 0 | GW58: 1 | GX58: =ROUND(HC58*I58,2) -> 0 | HA58: 0 | HB58: 0 | HC58: =GV58*GW58 -> 0 | HS58: 0 | IK58: 0
A59: 17 | B59: 1 | C59: =ROW(SmtRes!A82) -> 82 | D59: =ROW(EtalonRes!A92) -> 92 | E59: 16 | F59: 3.13-30-1 | G59: Огнезащитное покрытие терморасширяющимися составами электрических кабелей с применением окрасочного безвоздушного агрегата | H59: 100 м2 покрытия | I59: 0 | J59: 0 | K59: 0 | O59: =ROUND(CP59,2) -> 0 | P59: =ROUND((ROUND((AC59*AW59*I59),2)*BC59),2) -> 0 | Q59: =(ROUND((ROUND((((ET59*1.1))*AV59*I59),2)*BB59),2)+ROUND((ROUND(((AE59-((EU59*1.1)))*AV59*I59),2)*BS59),2)) -> 0 | R59: =ROUND((ROUND((AE59*AV59*I59),2)*BS59),2) -> 0 | S59: =ROUND((ROUND((AF59*AV59*I59),2)*BA59),2) -> 0 | T59: =ROUND(CU59*I59,2) -> 0 | U59: =CV59*I59 -> 0 | V59: =CW59*I59 -> 0 | W59: =ROUND(CX59*I59,2) -> 0 | X59: =ROUND(CY59,2) -> 0 | Y59: =ROUND(CZ59,2) -> 0 | AA59: 56616093 | AB59: =ROUND((AC59+AD59+AF59),6) -> 3080.004 | AC59: =ROUND((ES59),6) -> 516.41 | AD59: =ROUND(((((ET59*1.1))-((EU59*1.1)))+AE59),6) -> 439.593 | AE59: =ROUND(((EU59*1.1)),6) -> 0.649 | AF59: =ROUND(((EV59*1.1)),6) -> 2124.001 | AG59: =ROUND((AP59),6) -> 0 | AH59: =((EW59*1.1)) -> 148.5 | AI59: =((EX59*1.1)) -> 0 | AJ59: =(AS59) -> 0 | AK59: 2846.95 | AL59: 516.41 | AM59: 399.63 | AN59: 0.59 | AO59: 1930.91 | AP59: 0 | AQ59: 135 | AR59: 0 | AS59: 0 | AT59: 87 | AU59: 41 | AV59: 1.047 | AW59: 1 | AZ59: 1 | BA59: 34.51 | BB59: 9.31 | BC59: 3.33 | BH59: 0 | BI59: 1 | BJ59: ТСН-2001.3 Доп. 71, Сб. 13, т. 30, поз. 1 | BM59: 99 | BN59: 0 | BO59: 3.13-30-1 | BP59: 1 | BQ59: 30 | BR59: 0 | BS59: 34.51 | BT59: 1 | BU59: 1 | BV59: 1 | BW59: 1 | BX59: 1 | BZ59: 87 | CA59: 41 | CE59: 30 | CF59: 0 | CG59: 0 | CM59: 0 | CN59: Поправка: О.П. п.3.4.30.в Наименование: В отношении объектов, реализуемых с привлечением средств бюджета города Москвы, затраты, учитывающие усложненные условия производства работ (стесненность, сложность складирования и транспортной логистики, наличие в зоне производства работ действующего технологического оборудования или движения технологического транспорта и т.п.), определяются заказчиком в задании на проектирование при составлении локальных сметных расчетов (смет): для объектов, расположенных за пределами Третьего транспортного кольца города Москвы, но в пределах Московской кольцевой автомобильной дороги | CO59: 0 | CP59: =(P59+Q59+S59) -> 0 | CQ59: =ROUND((ROUND((AC59*AW59*1),2)*BC59),2) -> 1719.65 | CR59: =(ROUND((ROUND((((ET59*1.1))*AV59*1),2)*BB59),2)+ROUND((ROUND(((AE59-((EU59*1.1)))*AV59*1),2)*BS59),2)) -> 4284.93 | CS59: =ROUND((ROUND((AE59*AV59*1),2)*BS59),2) -> 23.47 | CT59: =ROUND((ROUND((AF59*AV59*1),2)*BA59),2) -> 76744.37 | CU59: =AG59 -> 0 | CV59: =(AH59*AV59) -> 155.4795 | CW59: =AI59 -> 0 | CX59: =AJ59 -> 0 | CY59: =S59*(BZ59/100) -> 0 | CZ59: =S59*(CA59/100) -> 0 | DE59: )*1,1 | DF59: )*1,1 | DG59: )*1,1 | DI59: )*1,1 | DJ59: )*1,1 | DN59: 105 | DO59: 77 | DP59: 1.047 | DQ59: 1 | DU59: 1013 | DV59: 100 м2 покрытия | DW59: 100 м2 покрытия | DX59: 1 | EE59: 51696138 | EF59: 30 | EG59: Строительные работы | EH59: 0 | EJ59: 1 | EK59: 99 | EL59: ТСН-2001.3-13. 13-17-6, 13-17-7, 13-18...13-38 | EM59: ТСН-2001.3-13-3 | EO59: Поправка: О.П. п.3.4.30.в | EQ59: 131072 | ER59: 2846.95 | ES59: 516.41 | ET59: 399.63 | EU59: 0.59 | EV59: 1930.91 | EW59: 135 | EX59: 0 | EY59: 0 | FQ59: 0 | FR59: 0 | FS59: 0 | FX59: 105 | FY59: 77 | GD59: 0 | GF59: 448414653 | GG59: 2 | GH59: 1 | GI59: 2 | GJ59: 0 | GK59: =ROUND(R59*(S12)/100,2) -> 0 | GL59: =ROUND(IF(AND(BH59=3,BI59=3,FS59<>0),P59,0),2) -> 0 | GM59: =ROUND(O59+X59+Y59+GK59,2)+GX59 -> 0 | GN59: =IF(OR(BI59=0,BI59=1),GM59-GX59,0) -> 0 | GO59: =IF(BI59=2,GM59-GX59,0) -> 0 | GP59: =IF(BI59=4,GM59-GX59,0) -> 0 | GR59: 0 | GS59: 3 | GT59: 0 | GV59: =ROUND((GT59),6) -> 0 | GW59: 1 | GX59: =ROUND(HC59*I59,2) -> 0 | HA59: 0 | HB59: 0 | HC59: =GV59*GW59 -> 0 | HS59: 0 | IK59: 0
A60: 17 | B60: 1 | E60: 17 | F60: цена поставщика | G60: Огнезащитный состав СТАБИТЕРМ-225 3кп | H60: кг | I60: =ROUND(I58*100*1.36,9) -> 0 | J60: 0 | K60: =ROUND(I58*100*1.36,9) -> 0 | O60: =ROUND(CP60,2) -> 0 | P60: =ROUND((ROUND((AC60*AW60*I60),2)*BC60),2) -> 0 | Q60: =(ROUND((ROUND((((ET60*1.1))*AV60*I60),2)*BB60),2)+ROUND((ROUND(((AE60-((EU60*1.1)))*AV60*I60),2)*BS60),2)) -> 0 | R60: =ROUND((ROUND((AE60*AV60*I60),2)*BS60),2) -> 0 | S60: =ROUND((ROUND((AF60*AV60*I60),2)*BA60),2) -> 0 | T60: =ROUND(CU60*I60,2) -> 0 | U60: =CV60*I60 -> 0 | V60: =CW60*I60 -> 0 | W60: =ROUND(CX60*I60,2) -> 0 | X60: =ROUND(CY60,2) -> 0 | Y60: =ROUND(CZ60,2) -> 0 | AA60: 56622586 | AB60: =ROUND((AC60+AD60+AF60),6) -> 466.65 | AC60: =ROUND(((ES60*1.02)),6) -> 466.65 | AD60: =ROUND(((((ET60*1.1))-((EU60*1.1)))+AE60),6) -> 0 | AE60: =ROUND(((EU60*1.1)),6) -> 0 | AF60: =ROUND(((EV60*1.1)),6) -> 0 | AG60: =ROUND((AP60),6) -> 0 | AH60: =((EW60*1.1)) -> 0 | AI60: =((EX60*1.1)) -> 0 | AJ60: =(AS60) -> 0 | AK60: 457.5 | AL60: 457.5 | AM60: 0 | AN60: 0 | AO60: 0 | AP60: 0 | AQ60: 0 | AR60: 0 | AS60: 0 | AT60: 0 | AU60: 0 | AV60: 1 | AW60: 1 | AZ60: 1 | BA60: 1 | BB60: 1 | BC60: 1 | BH60: 3 | BI60: 1 | BM60: 400002 | BN60: 0 | BP60: 0 | BQ60: 202 | BR60: 0 | BS60: 1 | BT60: 1 | BU60: 1 | BV60: 1 | BW60: 1 | BX60: 1 | BZ60: 0 | CA60: 0 | CE60: 30 | CF60: 0 | CG60: 0 | CM60: 0 | CN60: Поправка: О.П. п.3.4.30.в Наименование: В отношении объектов, реализуемых с привлечением средств бюджета города Москвы, затраты, учитывающие усложненные условия производства работ (стесненность, сложность складирования и транспортной логистики, наличие в зоне производства работ действующего технологического оборудования или движения технологического транспорта и т.п.), определяются заказчиком в задании на проектирование при составлении локальных сметных расчетов (смет): для объектов, расположенных за пределами Третьего транспортного кольца города Москвы, но в пределах Московской кольцевой автомобильной дороги | CO60: 0 | CP60: =(P60+Q60+S60) -> 0 | CQ60: =ROUND((ROUND((AC60*AW60*1),2)*BC60),2) -> 466.65 | CR60: =(ROUND((ROUND((((ET60*1.1))*AV60*1),2)*BB60),2)+ROUND((ROUND(((AE60-((EU60*1.1)))*AV60*1),2)*BS60),2)) -> 0 | CS60: =ROUND((ROUND((AE60*AV60*1),2)*BS60),2) -> 0 | CT60: =ROUND((ROUND((AF60*AV60*1),2)*BA60),2) -> 0 | CU60: =AG60 -> 0 | CV60: =(AH60*AV60) -> 0 | CW60: =AI60 -> 0 | CX60: =AJ60 -> 0 | CY60: =((S60*BZ60)/100) -> 0 | CZ60: =((S60*CA60)/100) -> 0 | DD60: *1,02 | DE60: )*1,1 | DF60: )*1,1 | DG60: )*1,1 | DI60: )*1,1 | DJ60: )*1,1 | DN60: 0 | DO60: 0 | DP60: 1 | DQ60: 1 | DU60: 1009 | DV60: кг | DW60: кг | DX60: 1 | EE60: 51698006 | EF60: 202 | EG60: Материалы | EH60: 0 | EJ60: 1 | EK60: 400002 | EL60: Материалы, изделия и конструкции | EM60: Материалы | EO60: Поправка: О.П. п.3.4.30.в | EQ60: 131072 | ER60: 46.97 | ES60: 457.5 | ET60: 0 | EU60: 0 | EV60: 0 | EW60: 0 | EX60: 0 | EY60: 0 | FQ60: 0 | FR60: 0 | FS60: 0 | FX60: 0 | FY60: 0 | GA60: [549 / 1,2] | GD60: 0 | GF60: -1971647847 | GG60: 2 | GH60: 4 | GI60: 3 | GJ60: 0 | GK60: =ROUND(R60*(R12)/100,2) -> 0 | GL60: =ROUND(IF(AND(BH60=3,BI60=3,FS60<>0),P60,0),2) -> 0 | GM60: =ROUND(O60+X60+Y60+GK60,2)+GX60 -> 0 | GN60: =IF(OR(BI60=0,BI60=1),GM60-GX60,0) -> 0 | GO60: =IF(BI60=2,GM60-GX60,0) -> 0 | GP60: =IF(BI60=4,GM60-GX60,0) -> 0 | GR60: 0 | GS60: 2 | GT60: 0 | GV60: =ROUND((GT60),6) -> 0 | GW60: 1 | GX60: =ROUND(HC60*I60,2) -> 0 | HA60: 0 | HB60: 0 | HC60: =GV60*GW60 -> 0 | HE60: 0 | HF60: 0 | HS60: 0 | IK60: 0
A61: 17 | B61: 1 | E61: 17 | F61: цена поставщика | G61: Огнезащитный состав СТАБИТЕРМ-225 3кп | H61: кг | I61: =ROUND(I59*100*1.36,9) -> 0 | J61: 0 | K61: =ROUND(I59*100*1.36,9) -> 0 | O61: =ROUND(CP61,2) -> 0 | P61: =ROUND((ROUND((AC61*AW61*I61),2)*BC61),2) -> 0 | Q61: =(ROUND((ROUND((((ET61*1.1))*AV61*I61),2)*BB61),2)+ROUND((ROUND(((AE61-((EU61*1.1)))*AV61*I61),2)*BS61),2)) -> 0 | R61: =ROUND((ROUND((AE61*AV61*I61),2)*BS61),2) -> 0 | S61: =ROUND((ROUND((AF61*AV61*I61),2)*BA61),2) -> 0 | T61: =ROUND(CU61*I61,2) -> 0 | U61: =CV61*I61 -> 0 | V61: =CW61*I61 -> 0 | W61: =ROUND(CX61*I61,2) -> 0 | X61: =ROUND(CY61,2) -> 0 | Y61: =ROUND(CZ61,2) -> 0 | AA61: 56616093 | AB61: =ROUND((AC61+AD61+AF61),6) -> 466.65 | AC61: =ROUND(((ES61*1.02)),6) -> 466.65 | AD61: =ROUND(((((ET61*1.1))-((EU61*1.1)))+AE61),6) -> 0 | AE61: =ROUND(((EU61*1.1)),6) -> 0 | AF61: =ROUND(((EV61*1.1)),6) -> 0 | AG61: =ROUND((AP61),6) -> 0 | AH61: =((EW61*1.1)) -> 0 | AI61: =((EX61*1.1)) -> 0 | AJ61: =(AS61) -> 0 | AK61: 457.5 | AL61: 457.5 | AM61: 0 | AN61: 0 | AO61: 0 | AP61: 0 | AQ61: 0 | AR61: 0 | AS61: 0 | AT61: 0 | AU61: 0 | AV61: 1 | AW61: 1 | AZ61: 1 | BA61: 1 | BB61: 1 | BC61: 1 | BH61: 3 | BI61: 1 | BM61: 400002 | BN61: 0 | BP61: 0 | BQ61: 202 | BR61: 0 | BS61: 1 | BT61: 1 | BU61: 1 | BV61: 1 | BW61: 1 | BX61: 1 | BZ61: 0 | CA61: 0 | CE61: 30 | CF61: 0 | CG61: 0 | CM61: 0 | CN61: Поправка: О.П. п.3.4.30.в Наименование: В отношении объектов, реализуемых с привлечением средств бюджета города Москвы, затраты, учитывающие усложненные условия производства работ (стесненность, сложность складирования и транспортной логистики, наличие в зоне производства работ действующего технологического оборудования или движения технологического транспорта и т.п.), определяются заказчиком в задании на проектирование при составлении локальных сметных расчетов (смет): для объектов, расположенных за пределами Третьего транспортного кольца города Москвы, но в пределах Московской кольцевой автомобильной дороги | CO61: 0 | CP61: =(P61+Q61+S61) -> 0 | CQ61: =ROUND((ROUND((AC61*AW61*1),2)*BC61),2) -> 466.65 | CR61: =(ROUND((ROUND((((ET61*1.1))*AV61*1),2)*BB61),2)+ROUND((ROUND(((AE61-((EU61*1.1)))*AV61*1),2)*BS61),2)) -> 0 | CS61: =ROUND((ROUND((AE61*AV61*1),2)*BS61),2) -> 0 | CT61: =ROUND((ROUND((AF61*AV61*1),2)*BA61),2) -> 0 | CU61: =AG61 -> 0 | CV61: =(AH61*AV61) -> 0 | CW61: =AI61 -> 0 | CX61: =AJ61 -> 0 | CY61: =S61*(BZ61/100) -> 0 | CZ61: =S61*(CA61/100) -> 0 | DD61: *1,02 | DE61: )*1,1 | DF61: )*1,1 | DG61: )*1,1 | DI61: )*1,1 | DJ61: )*1,1 | DN61: 0 | DO61: 0 | DP61: 1 | DQ61: 1 | DU61: 1009 | DV61: кг | DW61: кг | DX61: 1 | EE61: 51698006 | EF61: 202 | EG61: Материалы | EH61: 0 | EJ61: 1 | EK61: 400002 | EL61: Материалы, изделия и конструкции | EM61: Материалы | EO61: Поправка: О.П. п.3.4.30.в | EQ61: 131072 | ER61: 46.97 | ES61: 457.5 | ET61: 0 | EU61: 0 | EV61: 0 | EW61: 0 | EX61: 0 | EY61: 0 | EZ61: 5 | FC61: 1 | FD61: 18 | FF61: 549 | FQ61: 0 | FR61: 0 | FS61: 0 | FX61: 0 | FY61: 0 | GA61: [549 / 1,2] | GD61: 0 | GF61: -1971647847 | GG61: 2 | GH61: 3 | GI61: -2 | GJ61: 0 | GK61: =ROUND(R61*(S12)/100,2) -> 0 | GL61: =ROUND(IF(AND(BH61=3,BI61=3,FS61<>0),P61,0),2) -> 0 | GM61: =ROUND(O61+X61+Y61+GK61,2)+GX61 -> 0 | GN61: =IF(OR(BI61=0,BI61=1),GM61-GX61,0) -> 0 | GO61: =IF(BI61=2,GM61-GX61,0) -> 0 | GP61: =IF(BI61=4,GM61-GX61,0) -> 0 | GR61: 1 | GS61: 1 | GT61: 0 | GV61: =ROUND((GT61),6) -> 0 | GW61: 1 | GX61: =ROUND(HC61*I61,2) -> 0 | HA61: 0 | HB61: 0 | HC61: =GV61*GW61 -> 0 | HE61: 0 | HF61: 0 | HS61: 0 | IK61: 0
A63: 51 | B63: =B24 -> 1 | C63: =A24 -> 4 | D63: =ROW(A24) -> 24 | F63: =IF(F24<>"",F24,"") -> Новый раздел | G63: =IF(G24<>"",G24,"") -> Строительные работы | H63: 0 | O63: =ROUND(AB63,2) -> 43246.29 | P63: =ROUND(AC63,2) -> 40597.03 | Q63: =ROUND(AD63,2) -> 1213.81 | R63: =ROUND(AE63,2) -> 121.1 | S63: =ROUND(AF63,2) -> 1435.45 | T63: =ROUND(AG63,2) -> 0 | U63: =AH63 -> 135.65221 | V63: =AI63 -> 0 | W63: =ROUND(AJ63,2) -> 0 | X63: =ROUND(AK63,2) -> 1549.74 | Y63: =ROUND(AL63,2) -> 1061.62 | AB63: =ROUND(SUMIF(AA28:AA61,"=56622586",O28:O61),2) -> 43246.29 | AC63: =ROUND(SUMIF(AA28:AA61,"=56622586",P28:P61),2) -> 40597.03 | AD63: =ROUND(SUMIF(AA28:AA61,"=56622586",Q28:Q61),2) -> 1213.81 | AE63: =ROUND(SUMIF(AA28:AA61,"=56622586",R28:R61),2) -> 121.1 | AF63: =ROUND(SUMIF(AA28:AA61,"=56622586",S28:S61),2) -> 1435.45 | AG63: =ROUND(SUMIF(AA28:AA61,"=56622586",T28:T61),2) -> 0 | AH63: =SUMIF(AA28:AA61,"=56622586",U28:U61) -> 135.65221 | AI63: =SUMIF(AA28:AA61,"=56622586",V28:V61) -> 0 | AJ63: =ROUND(SUMIF(AA28:AA61,"=56622586",W28:W61),2) -> 0 | AK63: =ROUND(SUMIF(AA28:AA61,"=56622586",X28:X61),2) -> 1549.74 | AL63: =ROUND(SUMIF(AA28:AA61,"=56622586",Y28:Y61),2) -> 1061.62 | AO63: =ROUND(BX63,2) -> 0 | AP63: =ROUND(BY63,2) -> 0 | AQ63: =ROUND(BZ63,2) -> 0 | AR63: =ROUND(CA63,2) -> 46069.59 | AS63: =ROUND(CB63,2) -> 46069.59 | AT63: =ROUND(CC63,2) -> 0 | AU63: =ROUND(CD63,2) -> 0 | AV63: =ROUND(CE63,2) -> 40597.03 | ... BD63: =ROUND(CM63,2) -> 0 | BX63: =ROUND(SUMIF(AA28:AA61,"=56622586",FQ28:FQ61),2) -> 0 | BY63: =ROUND(SUMIF(AA28:AA61,"=56622586",FR28:FR61),2) -> 0 | BZ63: =ROUND(SUMIF(AA28:AA61,"=56622586",GL28:GL61),2) -> 0 | CA63: =ROUND(SUMIF(AA28:AA61,"=56622586",GM28:GM61),2) -> 46069.59 | CB63: =ROUND(SUMIF(AA28:AA61,"=56622586",GN28:GN61),2) -> 46069.59 | CC63: =ROUND(SUMIF(AA28:AA61,"=56622586",GO28:GO61),2) -> 0 | CD63: =ROUND(SUMIF(AA28:AA61,"=56622586",GP28:GP61),2) -> 0 | CE63: =AC63-BX63 -> 40597.03 | CF63: =AC63-BY63 -> 40597.03 | CG63: =BX63-BZ63 -> 0 | CH63: =AC63-BX63-BY63+BZ63 -> 40597.03 | CI63: =BY63-BZ63 -> 0 | CJ63: =ROUND(SUMIF(AA28:AA61,"=56622586",GX28:GX61),2) -> 0 | CK63: =ROUND(SUMIF(AA28:AA61,"=56622586",GY28:GY61),2) -> 0 | CL63: =ROUND(SUMIF(AA28:AA61,"=56622586",GZ28:GZ61),2) -> 0 | CM63: =ROUND(SUMIF(AA28:AA61,"=56622586",HD28:HD61),2) -> 0 | DG63: =ROUND(DT63,2) -> 453752.88 | DH63: =ROUND(DU63,2) -> 389496.18 | DI63: =ROUND(DV63,2) -> 14719.31 | DJ63: =ROUND(DW63,2) -> 4179.17 | DK63: =ROUND(DX63,2) -> 49537.39 | DL63: =ROUND(DY63,2) -> 0 | DM63: =DZ63 -> 135.65221 | DN63: =EA63 -> 0 | DO63: =ROUND(EB63,2) -> 0 | DP63: =ROUND(EC63,2) -> 44214.02 | DQ63: =ROUND(ED63,2) -> 20367.31 | DT63: =ROUND(SUMIF(AA28:AA61,"=56616093",O28:O61),2) -> 453752.88 | DU63: =ROUND(SUMIF(AA28:AA61,"=56616093",P28:P61),2) -> 389496.18 | DV63: =ROUND(SUMIF(AA28:AA61,"=56616093",Q28:Q61),2) -> 14719.31 | DW63: =ROUND(SUMIF(AA28:AA61,"=56616093",R28:R61),2) -> 4179.17 | DX63: =ROUND(SUMIF(AA28:AA61,"=56616093",S28:S61),2) -> 49537.39 | DY63: =ROUND(SUMIF(AA28:AA61,"=56616093",T28:T61),2) -> 0 | DZ63: =SUMIF(AA28:AA61,"=56616093",U28:U61) -> 135.65221 | EA63: =SUMIF(AA28:AA61,"=56616093",V28:V61) -> 0 | EB63: =ROUND(SUMIF(AA28:AA61,"=56616093",W28:W61),2) -> 0 | EC63: =ROUND(SUMIF(AA28:AA61,"=56616093",X28:X61),2) -> 44214.02 | ED63: =ROUND(SUMIF(AA28:AA61,"=56616093",Y28:Y61),2) -> 20367.31 | EG63: =ROUND(FP63,2) -> 0 | EH63: =ROUND(FQ63,2) -> 0 | EI63: =ROUND(FR63,2) -> 0 | EJ63: =ROUND(FS63,2) -> 525020.89 | EK63: =ROUND(FT63,2) -> 525020.89 | EL63: =ROUND(FU63,2) -> 0 | EM63: =ROUND(FV63,2) -> 0 | EN63: =ROUND(FW63,2) -> 389496.18 | ... EV63: =ROUND(GE63,2) -> 0 | FP63: =ROUND(SUMIF(AA28:AA61,"=56616093",FQ28:FQ61),2) -> 0 | FQ63: =ROUND(SUMIF(AA28:AA61,"=56616093",FR28:FR61),2) -> 0 | FR63: =ROUND(SUMIF(AA28:AA61,"=56616093",GL28:GL61),2) -> 0 | FS63: =ROUND(SUMIF(AA28:AA61,"=56616093",GM28:GM61),2) -> 525020.89 | FT63: =ROUND(SUMIF(AA28:AA61,"=56616093",GN28:GN61),2) -> 525020.89 | FU63: =ROUND(SUMIF(AA28:AA61,"=56616093",GO28:GO61),2) -> 0 | FV63: =ROUND(SUMIF(AA28:AA61,"=56616093",GP28:GP61),2) -> 0 | FW63: =DU63-FP63 -> 389496.18 | FX63: =DU63-FQ63 -> 389496.18 | FY63: =FP63-FR63 -> 0 | FZ63: =DU63-FP63-FQ63+FR63 -> 389496.18 | GA63: =FQ63-FR63 -> 0 | GB63: =ROUND(SUMIF(AA28:AA61,"=56616093",GX28:GX61),2) -> 0 | GC63: =ROUND(SUMIF(AA28:AA61,"=56616093",GY28:GY61),2) -> 0 | GD63: =ROUND(SUMIF(AA28:AA61,"=56616093",GZ28:GZ61),2) -> 0 | GE63: =ROUND(SUMIF(AA28:AA61,"=56616093",HD28:HD61),2) -> 0 | GX63: 0
A65: 50 | B65: 0 | C65: 0 | D65: 1 | E65: 201 | F65: =ROUND(Source!O63,O65) -> 43246.29 | G65: ПЗ | H65: Прямые затраты | K65: 201 | L65: 1 | M65: 3 | O65: 2 | P65: =ROUND(Source!DG63,O65) -> 453752.88 | W65: 43246.29 | X65: 1 | Y65: 43246.29 | Z65: 453752.88 | AA65: 1 | AB65: 453752.88
A66: 50 | B66: 0 | C66: 0 | D66: 1 | E66: 202 | F66: =ROUND(Source!P63,O66) -> 40597.03 | G66: СтМатОб | H66: Стоимость материальных ресурсов (всего) | K66: 202 | L66: 2 | M66: 3 | O66: 2 | P66: =ROUND(Source!DH63,O66) -> 389496.18 | W66: 40597.03 | X66: 1 | Y66: 40597.03 | Z66: 389496.18 | AA66: 1 | AB66: 389496.18
A67: 50 | B67: 0 | C67: 0 | D67: 1 | E67: 222 | F67: =ROUND(Source!AO63,O67) -> 0 | G67: СтМатОбЗак | H67: Стоимость материалов и оборудования заказчика | K67: 222 | L67: 3 | M67: 3 | O67: 2 | P67: =ROUND(Source!EG63,O67) -> 0 | W67: 0 | X67: 1 | Y67: 0 | Z67: 0 | AA67: 1 | AB67: 0
A68: 50 | B68: 0 | C68: 0 | D68: 1 | E68: 225 | F68: =ROUND(Source!AV63,O68) -> 40597.03 | G68: СтМатОбПод | H68: Стоимость материалов и оборудования подрядчика | K68: 225 | L68: 4 | M68: 3 | O68: 2 | P68: =ROUND(Source!EN63,O68) -> 389496.18 | W68: 40597.03 | X68: 1 | Y68: 40597.03 | Z68: 389496.18 | AA68: 1 | AB68: 389496.18
A69: 50 | B69: 0 | C69: 0 | D69: 1 | E69: 226 | F69: =ROUND(Source!AW63,O69) -> 40597.03 | G69: СтМат | H69: Стоимость материалов (всего) | K69: 226 | L69: 5 | M69: 3 | O69: 2 | P69: =ROUND(Source!EO63,O69) -> 389496.18 | W69: 40597.03 | X69: 1 | Y69: 40597.03 | Z69: 389496.18 | AA69: 1 | AB69: 389496.18
A70: 50 | B70: 0 | C70: 0 | D70: 1 | E70: 227 | F70: =ROUND(Source!AX63,O70) -> 0 | G70: СтМатЗак | H70: Стоимость материалов заказчика | K70: 227 | L70: 6 | M70: 3 | O70: 2 | P70: =ROUND(Source!EP63,O70) -> 0 | W70: 0 | X70: 1 | Y70: 0 | Z70: 0 | AA70: 1 | AB70: 0
A71: 50 | B71: 0 | C71: 0 | D71: 1 | E71: 228 | F71: =ROUND(Source!AY63,O71) -> 40597.03 | G71: СтМатПод | H71: Стоимость материалов подрядчика | K71: 228 | L71: 7 | M71: 3 | O71: 2 | P71: =ROUND(Source!EQ63,O71) -> 389496.18 | W71: 40597.03 | X71: 1 | Y71: 40597.03 | Z71: 389496.18 | AA71: 1 | AB71: 389496.18
A72: 50 | B72: 0 | C72: 0 | D72: 1 | E72: 216 | F72: =ROUND(Source!AP63,O72) -> 0 | G72: Оборуд | H72: Стоимость оборудования (всего) | K72: 216 | L72: 8 | M72: 3 | O72: 2 | P72: =ROUND(Source!EH63,O72) -> 0 | W72: 0 | X72: 1 | Y72: 0 | Z72: 0 | AA72: 1 | AB72: 0
A73: 50 | B73: 0 | C73: 0 | D73: 1 | E73: 223 | F73: =ROUND(Source!AQ63,O73) -> 0 | G73: ОборудЗак | H73: Стоимость оборудования заказчика | K73: 223 | L73: 9 | M73: 3 | O73: 2 | P73: =ROUND(Source!EI63,O73) -> 0 | W73: 0 | X73: 1 | Y73: 0 | Z73: 0 | AA73: 1 | AB73: 0
A74: 50 | B74: 0 | C74: 0 | D74: 1 | E74: 229 | F74: =ROUND(Source!AZ63,O74) -> 0 | G74: ОборудПод | H74: Стоимость оборудования подрядчика | K74: 229 | L74: 10 | M74: 3 | O74: 2 | P74: =ROUND(Source!ER63,O74) -> 0 | W74: 0 | X74: 1 | Y74: 0 | Z74: 0 | AA74: 1 | AB74: 0
A75: 50 | B75: 0 | C75: 0 | D75: 1 | E75: 203 | F75: =ROUND(Source!Q63,O75) -> 1213.81 | G75: ЭММ | H75: Эксплуатация машин | K75: 203 | L75: 11 | M75: 3 | O75: 2 | P75: =ROUND(Source!DI63,O75) -> 14719.31 | W75: 1213.81 | X75: 1 | Y75: 1213.81 | Z75: 14719.31 | AA75: 1 | AB75: 14719.31
A76: 50 | B76: 0 | C76: 0 | D76: 1 | E76: 231 | F76: =ROUND(Source!BB63,O76) -> 0 | G76: ЭММсНРиСП | H76: Эксплуатация машин по ТСН-2001.16 | K76: 231 | L76: 12 | M76: 3 | O76: 2 | P76: =ROUND(Source!ET63,O76) -> 0 | W76: 0 | X76: 1 | Y76: 0 | Z76: 0 | AA76: 1 | AB76: 0
A77: 50 | B77: 0 | C77: 0 | D77: 1 | E77: 204 | F77: =ROUND(Source!R63,O77) -> 121.1 | G77: ЗПМ | H77: ЗП машинистов | K77: 204 | L77: 13 | M77: 3 | O77: 2 | P77: =ROUND(Source!DJ63,O77) -> 4179.17 | W77: 121.1 | X77: 1 | Y77: 121.1 | Z77: 4179.17 | AA77: 1 | AB77: 4179.17
A78: 50 | B78: 0 | C78: 0 | D78: 1 | E78: 205 | F78: =ROUND(Source!S63,O78) -> 1435.45 | G78: ОЗП | H78: Основная ЗП рабочих | K78: 205 | L78: 14 | M78: 3 | O78: 2 | P78: =ROUND(Source!DK63,O78) -> 49537.39 | W78: 1435.45 | X78: 1 | Y78: 1435.45 | Z78: 49537.39 | AA78: 1 | AB78: 49537.39
A79: 50 | B79: 0 | C79: 0 | D79: 1 | E79: 232 | F79: =ROUND(Source!BC63,O79) -> 0 | G79: ОЗПсНРиСП | H79: Основная ЗП рабочих по ТСН-2001.16 | K79: 232 | L79: 15 | M79: 3 | O79: 2 | P79: =ROUND(Source!EU63,O79) -> 0 | W79: 0 | X79: 1 | Y79: 0 | Z79: 0 | AA79: 1 | AB79: 0
A80: 50 | B80: 0 | C80: 0 | D80: 1 | E80: 214 | F80: =ROUND(Source!AS63,O80) -> 46069.59 | G80: Строит | H80: Строительные работы с НР и СП | K80: 214 | L80: 16 | M80: 3 | O80: 2 | P80: =ROUND(Source!EK63,O80) -> 525020.89 | W80: 46069.59 | X80: 1 | Y80: 46069.59 | Z80: 525020.89 | AA80: 1 | AB80: 525020.89
A81: 50 | B81: 0 | C81: 0 | D81: 1 | E81: 215 | F81: =ROUND(Source!AT63,O81) -> 0 | G81: Монтаж | H81: Монтажные работы с НР и СП | K81: 215 | L81: 17 | M81: 3 | O81: 2 | P81: =ROUND(Source!EL63,O81) -> 0 | W81: 0 | X81: 1 | Y81: 0 | Z81: 0 | AA81: 1 | AB81: 0
A82: 50 | B82: 0 | C82: 0 | D82: 1 | E82: 217 | F82: =ROUND(Source!AU63,O82) -> 0 | G82: Прочие | H82: Прочие работы с НР и СП | K82: 217 | L82: 18 | M82: 3 | O82: 2 | P82: =ROUND(Source!EM63,O82) -> 0 | W82: 0 | X82: 1 | Y82: 0 | Z82: 0 | AA82: 1 | AB82: 0
A83: 50 | B83: 0 | C83: 0 | D83: 1 | E83: 230 | F83: =ROUND(Source!BA63,O83) -> 0 | G83: ПрочиеЗатр | H83: Прочие затраты по ТСН-2001.16 | K83: 230 | L83: 19 | M83: 3 | O83: 2 | P83: =ROUND(Source!ES63,O83) -> 0 | W83: 0 | X83: 1 | Y83: 0 | Z83: 0 | AA83: 1 | AB83: 0
A84: 50 | B84: 0 | C84: 0 | D84: 1 | E84: 206 | F84: =ROUND(Source!T63,O84) -> 0 | G84: ВозврМат | H84: Возврат материалов | K84: 206 | L84: 20 | M84: 3 | O84: 2 | P84: =ROUND(Source!DL63,O84) -> 0 | W84: 0 | X84: 1 | Y84: 0 | Z84: 0 | AA84: 1 | AB84: 0
A85: 50 | B85: 0 | C85: 0 | D85: 1 | E85: 207 | F85: =Source!U63 -> 135.65221 | G85: ТрудСтр | H85: Трудозатраты строителей | K85: 207 | L85: 21 | M85: 3 | O85: -1 | P85: =Source!DM63 -> 135.65221 | W85: 135.65221 | X85: 1 | Y85: 135.65221 | Z85: 135.65221 | AA85: 1 | AB85: 135.65221
A86: 50 | B86: 0 | C86: 0 | D86: 1 | E86: 208 | F86: =Source!V63 -> 0 | G86: ТрудМаш | H86: Трудозатраты машинистов | K86: 208 | L86: 22 | M86: 3 | O86: -1 | P86: =Source!DN63 -> 0 | W86: 0 | X86: 1 | Y86: 0 | Z86: 0 | AA86: 1 | AB86: 0
A87: 50 | B87: 0 | C87: 0 | D87: 1 | E87: 209 | F87: =ROUND(Source!W63,O87) -> 0 | G87: ТранспМат | H87: Транспорт материалов | K87: 209 | L87: 23 | M87: 3 | O87: 2 | P87: =ROUND(Source!DO63,O87) -> 0 | W87: 0 | X87: 1 | Y87: 0 | Z87: 0 | AA87: 1 | AB87: 0
A88: 50 | B88: 0 | C88: 0 | D88: 1 | E88: 233 | F88: =ROUND(Source!BD63,O88) -> 0 | G88: Перевозка | H88: Перевозка грузов | K88: 233 | L88: 24 | M88: 3 | O88: 2 | P88: =ROUND(Source!EV63,O88) -> 0 | W88: 0 | X88: 1 | Y88: 0 | Z88: 0 | AA88: 1 | AB88: 0
A89: 50 | B89: 0 | C89: 0 | D89: 1 | E89: 210 | F89: =ROUND(Source!X63,O89) -> 1549.74 | G89: НР | H89: Накладные расходы | K89: 210 | L89: 25 | M89: 3 | O89: 2 | P89: =ROUND(Source!DP63,O89) -> 44214.02 | W89: 1549.74 | X89: 1 | Y89: 1549.74 | Z89: 44214.02 | AA89: 1 | AB89: 44214.02
A90: 50 | B90: 0 | C90: 0 | D90: 1 | E90: 211 | F90: =ROUND(Source!Y63,O90) -> 1061.62 | G90: СмПриб | H90: Сметная прибыль | K90: 211 | L90: 26 | M90: 3 | O90: 2 | P90: =ROUND(Source!DQ63,O90) -> 20367.31 | W90: 1061.62 | X90: 1 | Y90: 1061.62 | Z90: 20367.31 | AA90: 1 | AB90: 20367.31
A91: 50 | B91: 0 | C91: 0 | D91: 1 | E91: 224 | F91: =ROUND(Source!AR63,O91) -> 46069.59 | G91: Всего | H91: Всего с НР и СП | K91: 224 | L91: 27 | M91: 3 | O91: 2 | P91: =ROUND(Source!EJ63,O91) -> 525020.89 | W91: 46069.59 | X91: 1 | Y91: 46069.59 | Z91: 525020.89 | AA91: 1 | AB91: 525020.89
A93: 4 | B93: 1 | D93: =ROW(A174) -> 174 | F93: Новый раздел | G93: Электромонтажные работы | I93: 0 | K93: -1 | S93: 0 | T93: 0 | V93: 0 | BX93: 0 | CJ93: 0
A95: 52 | B95: =B174 -> 1 | C95: =C174 -> 4 | D95: =D174 -> 93 | E95: =E174 -> 0 | F95: =F174 -> Новый раздел | G95: =G174 -> Электромонтажные работы | O95: =O174 -> 4380.32 | P95: =P174 -> 554.35 | Q95: =Q174 -> 1054.54 | R95: =R174 -> 110.25 | S95: =S174 -> 2771.43 | T95: =T174 -> 0 | U95: =U174 -> 209.75535 | V95: =V174 -> 0 | ... GX95: =GX174 -> 0
A97: 17 | B97: 1 | C97: =ROW(SmtRes!A83) -> 83 | D97: =ROW(EtalonRes!A95) -> 95 | E97: 18 | F97: 4.8-74-1 | G97: Устройство постели при одном кабеле в траншее | H97: 100 М КАБЕЛЯ | I97: 0 | J97: 0 | K97: 0 | O97: =ROUND(CP97,2) -> 0 | P97: =ROUND((ROUND((AC97*AW97*I97),2)*BC97),2) -> 0 | Q97: =(ROUND((ROUND((((ET97*1.1))*AV97*I97),2)*BB97),2)+ROUND((ROUND(((AE97-((EU97*1.1)))*AV97*I97),2)*BS97),2)) -> 0 | R97: =ROUND((ROUND((AE97*AV97*I97),2)*BS97),2) -> 0 | S97: =ROUND((ROUND((AF97*AV97*I97),2)*BA97),2) -> 0 | T97: =ROUND(CU97*I97,2) -> 0 | U97: =CV97*I97 -> 0 | V97: =CW97*I97 -> 0 | W97: =ROUND(CX97*I97,2) -> 0 | X97: =ROUND(CY97,2) -> 0 | Y97: =ROUND(CZ97,2) -> 0 | AA97: 56622586 | AB97: =ROUND((AC97+AD97+AF97),6) -> 500.148 | AC97: =ROUND((ES97),6) -> 0 | AD97: =ROUND(((((ET97*1.1))-((EU97*1.1)))+AE97),6) -> 417.747 | AE97: =ROUND(((EU97*1.1)),6) -> 63.437 | AF97: =ROUND(((EV97*1.1)),6) -> 82.401 | AG97: =ROUND((AP97),6) -> 0 | AH97: =((EW97*1.1)) -> 6.688 | AI97: =((EX97*1.1)) -> 0 | AJ97: =(AS97) -> 0 | AK97: 454.68 | AL97: 0 | AM97: 379.77 | AN97: 57.67 | AO97: 74.91 | AP97: 0 | AQ97: 6.08 | AR97: 0 | AS97: 0 | AT97: 112 | AU97: 70 | AV97: 1.067 | AW97: 1.081 | AZ97: 1 | BA97: 1 | BB97: 1 | BC97: 1 | BH97: 0 | BI97: 2 | BJ97: ТСН-2001.4 Доп. 68, Сб. 8, т. 74, поз. 1 | BM97: 318 | BN97: 0 | BP97: 0 | BQ97: 40 | BR97: 0 | BS97: 1 | BT97: 1 | BU97: 1 | BV97: 1 | BW97: 1 | BX97: 1 | BZ97: 112 | CA97: 70 | CE97: 30 | CF97: 0 | CG97: 0 | CM97: 0 | CN97: Поправка: О.П. п.3.4.30.в Наименование: В отношении объектов, реализуемых с привлечением средств бюджета города Москвы, затраты, учитывающие усложненные условия производства работ (стесненность, сложность складирования и транспортной логистики, наличие в зоне производства работ действующего технологического оборудования или движения технологического транспорта и т.п.), определяются заказчиком в задании на проектирование при составлении локальных сметных расчетов (смет): для объектов, расположенных за пределами Третьего транспортного кольца города Москвы, но в пределах Московской кольцевой автомобильной дороги | CO97: 0 | CP97: =(P97+Q97+S97) -> 0 | CQ97: =ROUND((ROUND((AC97*AW97*1),2)*BC97),2) -> 0 | CR97: =(ROUND((ROUND((((ET97*1.1))*AV97*1),2)*BB97),2)+ROUND((ROUND(((AE97-((EU97*1.1)))*AV97*1),2)*BS97),2)) -> 445.74 | CS97: =ROUND((ROUND((AE97*AV97*1),2)*BS97),2) -> 67.69 | CT97: =ROUND((ROUND((AF97*AV97*1),2)*BA97),2) -> 87.92 | CU97: =AG97 -> 0 | CV97: =(AH97*AV97) -> 7.136096 | CW97: =AI97 -> 0 | CX97: =AJ97 -> 0 | CY97: =((S97*BZ97)/100) -> 0 | CZ97: =((S97*CA97)/100) -> 0 | DE97: )*1,1 | DF97: )*1,1 | DG97: )*1,1 | DI97: )*1,1 | DJ97: )*1,1 | DN97: 0 | DO97: 0 | DP97: 1 | DQ97: 1 | DU97: 1013 | DV97: 100 М КАБЕЛЯ | DW97: 100 М КАБЕЛЯ | DX97: 1 | EE97: 51696357 | EF97: 40 | EG97: Монтаж оборудования | EH97: 0 | EJ97: 2 | EK97: 318 | EL97: ТСН-2001.4-8. 8-73...8-80 | EM97: ТСН-2001.4-8-3 | EO97: Поправка: О.П. п.3.4.30.в | EQ97: 131072 | ER97: 454.68 | ES97: 0 | ET97: 379.77 | EU97: 57.67 | EV97: 74.91 | EW97: 6.08 | EX97: 0 | EY97: 0 | FQ97: 0 | FR97: 0 | FS97: 0 | FX97: 112 | FY97: 70 | GD97: 0 | GF97: 369100549 | GG97: 2 | GH97: 1 | GI97: -2 | GJ97: 0 | GK97: =ROUND(R97*(R12)/100,2) -> 0 | GL97: =ROUND(IF(AND(BH97=3,BI97=3,FS97<>0),P97,0),2) -> 0 | GM97: =ROUND(O97+X97+Y97+GK97,2)+GX97 -> 0 | GN97: =IF(OR(BI97=0,BI97=1),GM97-GX97,0) -> 0 | GO97: =IF(BI97=2,GM97-GX97,0) -> 0 | GP97: =IF(BI97=4,GM97-GX97,0) -> 0 | GR97: 0 | GS97: 0 | GT97: 0 | GV97: =ROUND((GT97),6) -> 0 | GW97: 1 | GX97: =ROUND(HC97*I97,2) -> 0 | HA97: 0 | HB97: 0 | HC97: =GV97*GW97 -> 0 | HS97: 0 | IK97: 0
A98: 17 | B98: 1 | C98: =ROW(SmtRes!A84) -> 84 | D98: =ROW(EtalonRes!A98) -> 98 | E98: 18 | F98: 4.8-74-1 | G98: Устройство постели при одном кабеле в траншее | H98: 100 М КАБЕЛЯ | I98: 0 | J98: 0 | K98: 0 | O98: =ROUND(CP98,2) -> 0 | P98: =ROUND((ROUND((AC98*AW98*I98),2)*BC98),2) -> 0 | Q98: =(ROUND((ROUND((((ET98*1.1))*AV98*I98),2)*BB98),2)+ROUND((ROUND(((AE98-((EU98*1.1)))*AV98*I98),2)*BS98),2)) -> 0 | R98: =ROUND((ROUND((AE98*AV98*I98),2)*BS98),2) -> 0 | S98: =ROUND((ROUND((AF98*AV98*I98),2)*BA98),2) -> 0 | T98: =ROUND(CU98*I98,2) -> 0 | U98: =CV98*I98 -> 0 | V98: =CW98*I98 -> 0 | W98: =ROUND(CX98*I98,2) -> 0 | X98: =ROUND(CY98,2) -> 0 | Y98: =ROUND(CZ98,2) -> 0 | AA98: 56616093 | AB98: =ROUND((AC98+AD98+AF98),6) -> 500.148 | AC98: =ROUND((ES98),6) -> 0 | AD98: =ROUND(((((ET98*1.1))-((EU98*1.1)))+AE98),6) -> 417.747 | AE98: =ROUND(((EU98*1.1)),6) -> 63.437 | AF98: =ROUND(((EV98*1.1)),6) -> 82.401 | AG98: =ROUND((AP98),6) -> 0 | AH98: =((EW98*1.1)) -> 6.688 | AI98: =((EX98*1.1)) -> 0 | AJ98: =(AS98) -> 0 | AK98: 454.68 | AL98: 0 | AM98: 379.77 | AN98: 57.67 | AO98: 74.91 | AP98: 0 | AQ98: 6.08 | AR98: 0 | AS98: 0 | AT98: 92 | AU98: 43 | AV98: 1.067 | AW98: 1.081 | AZ98: 1 | BA98: 34.51 | BB98: 12.86 | BC98: 1 | BH98: 0 | BI98: 2 | BJ98: ТСН-2001.4 Доп. 68, Сб. 8, т. 74, поз. 1 | BM98: 318 | BN98: 0 | BO98: 4.8-74-1 | BP98: 1 | BQ98: 40 | BR98: 0 | BS98: 34.51 | BT98: 1 | BU98: 1 | BV98: 1 | BW98: 1 | BX98: 1 | BZ98: 92 | CA98: 43 | CE98: 30 | CF98: 0 | CG98: 0 | CM98: 0 | CN98: Поправка: О.П. п.3.4.30.в Наименование: В отношении объектов, реализуемых с привлечением средств бюджета города Москвы, затраты, учитывающие усложненные условия производства работ (стесненность, сложность складирования и транспортной логистики, наличие в зоне производства работ действующего технологического оборудования или движения технологического транспорта и т.п.), определяются заказчиком в задании на проектирование при составлении локальных сметных расчетов (смет): для объектов, расположенных за пределами Третьего транспортного кольца города Москвы, но в пределах Московской кольцевой автомобильной дороги | CO98: 0 | CP98: =(P98+Q98+S98) -> 0 | CQ98: =ROUND((ROUND((AC98*AW98*1),2)*BC98),2) -> 0 | CR98: =(ROUND((ROUND((((ET98*1.1))*AV98*1),2)*BB98),2)+ROUND((ROUND(((AE98-((EU98*1.1)))*AV98*1),2)*BS98),2)) -> 5732.22 | CS98: =ROUND((ROUND((AE98*AV98*1),2)*BS98),2) -> 2335.98 | CT98: =ROUND((ROUND((AF98*AV98*1),2)*BA98),2) -> 3034.12 | CU98: =AG98 -> 0 | CV98: =(AH98*AV98) -> 7.136096 | CW98: =AI98 -> 0 | CX98: =AJ98 -> 0 | CY98: =S98*(BZ98/100) -> 0 | CZ98: =S98*(CA98/100) -> 0 | DE98: )*1,1 | DF98: )*1,1 | DG98: )*1,1 | DI98: )*1,1 | DJ98: )*1,1 | DN98: 112 | DO98: 70 | DP98: 1.067 | DQ98: 1.081 | DU98: 1013 | DV98: 100 М КАБЕЛЯ | DW98: 100 М КАБЕЛЯ | DX98: 1 | EE98: 51696357 | EF98: 40 | EG98: Монтаж оборудования | EH98: 0 | EJ98: 2 | EK98: 318 | EL98: ТСН-2001.4-8. 8-73...8-80 | EM98: ТСН-2001.4-8-3 | EO98: Поправка: О.П. п.3.4.30.в | EQ98: 131072 | ER98: 454.68 | ES98: 0 | ET98: 379.77 | EU98: 57.67 | EV98: 74.91 | EW98: 6.08 | EX98: 0 | EY98: 0 | FQ98: 0 | FR98: 0 | FS98: 0 | FX98: 112 | FY98: 70 | GD98: 0 | GF98: 369100549 | GG98: 2 | GH98: 1 | GI98: 2 | GJ98: 0 | GK98: =ROUND(R98*(S12)/100,2) -> 0 | GL98: =ROUND(IF(AND(BH98=3,BI98=3,FS98<>0),P98,0),2) -> 0 | GM98: =ROUND(O98+X98+Y98+GK98,2)+GX98 -> 0 | GN98: =IF(OR(BI98=0,BI98=1),GM98-GX98,0) -> 0 | GO98: =IF(BI98=2,GM98-GX98,0) -> 0 | GP98: =IF(BI98=4,GM98-GX98,0) -> 0 | GR98: 0 | GS98: 3 | GT98: 0 | GV98: =ROUND((GT98),6) -> 0 | GW98: 1 | GX98: =ROUND(HC98*I98,2) -> 0 | HA98: 0 | HB98: 0 | HC98: =GV98*GW98 -> 0 | HS98: 0 | IK98: 0
A99: 17 | B99: 1 | C99: =ROW(SmtRes!A85) -> 85 | D99: =ROW(EtalonRes!A101) -> 101 | E99: 19 | F99: 4.8-74-1 | G99: Устройство постели при одном кабеле в траншее | H99: 100 М КАБЕЛЯ | I99: 0 | J99: 0 | K99: 0 | O99: =ROUND(CP99,2) -> 0 | P99: =ROUND((ROUND((AC99*AW99*I99),2)*BC99),2) -> 0 | Q99: =(ROUND((ROUND((((ET99*1.1))*AV99*I99),2)*BB99),2)+ROUND((ROUND(((AE99-((EU99*1.1)))*AV99*I99),2)*BS99),2)) -> 0 | R99: =ROUND((ROUND((AE99*AV99*I99),2)*BS99),2) -> 0 | S99: =ROUND((ROUND((AF99*AV99*I99),2)*BA99),2) -> 0 | T99: =ROUND(CU99*I99,2) -> 0 | U99: =CV99*I99 -> 0 | V99: =CW99*I99 -> 0 | W99: =ROUND(CX99*I99,2) -> 0 | X99: =ROUND(CY99,2) -> 0 | Y99: =ROUND(CZ99,2) -> 0 | AA99: 56622586 | AB99: =ROUND((AC99+AD99+AF99),6) -> 500.148 | AC99: =ROUND((ES99),6) -> 0 | AD99: =ROUND(((((ET99*1.1))-((EU99*1.1)))+AE99),6) -> 417.747 | AE99: =ROUND(((EU99*1.1)),6) -> 63.437 | AF99: =ROUND(((EV99*1.1)),6) -> 82.401 | AG99: =ROUND((AP99),6) -> 0 | AH99: =((EW99*1.1)) -> 6.688 | AI99: =((EX99*1.1)) -> 0 | AJ99: =(AS99) -> 0 | AK99: 454.68 | AL99: 0 | AM99: 379.77 | AN99: 57.67 | AO99: 74.91 | AP99: 0 | AQ99: 6.08 | AR99: 0 | AS99: 0 | AT99: 112 | AU99: 70 | AV99: 1.067 | AW99: 1.081 | AZ99: 1 | BA99: 1 | BB99: 1 | BC99: 1 | BH99: 0 | BI99: 2 | BJ99: ТСН-2001.4 Доп. 68, Сб. 8, т. 74, поз. 1 | BM99: 318 | BN99: 0 | BP99: 0 | BQ99: 40 | BR99: 0 | BS99: 1 | BT99: 1 | BU99: 1 | BV99: 1 | BW99: 1 | BX99: 1 | BZ99: 112 | CA99: 70 | CE99: 30 | CF99: 0 | CG99: 0 | CM99: 0 | CN99: Поправка: О.П. п.3.4.30.в Наименование: В отношении объектов, реализуемых с привлечением средств бюджета города Москвы, затраты, учитывающие усложненные условия производства работ (стесненность, сложность складирования и транспортной логистики, наличие в зоне производства работ действующего технологического оборудования или движения технологического транспорта и т.п.), определяются заказчиком в задании на проектирование при составлении локальных сметных расчетов (смет): для объектов, расположенных за пределами Третьего транспортного кольца города Москвы, но в пределах Московской кольцевой автомобильной дороги | CO99: 0 | CP99: =(P99+Q99+S99) -> 0 | CQ99: =ROUND((ROUND((AC99*AW99*1),2)*BC99),2) -> 0 | CR99: =(ROUND((ROUND((((ET99*1.1))*AV99*1),2)*BB99),2)+ROUND((ROUND(((AE99-((EU99*1.1)))*AV99*1),2)*BS99),2)) -> 445.74 | CS99: =ROUND((ROUND((AE99*AV99*1),2)*BS99),2) -> 67.69 | CT99: =ROUND((ROUND((AF99*AV99*1),2)*BA99),2) -> 87.92 | CU99: =AG99 -> 0 | CV99: =(AH99*AV99) -> 7.136096 | CW99: =AI99 -> 0 | CX99: =AJ99 -> 0 | CY99: =((S99*BZ99)/100) -> 0 | CZ99: =((S99*CA99)/100) -> 0 | DE99: )*1,1 | DF99: )*1,1 | DG99: )*1,1 | DI99: )*1,1 | DJ99: )*1,1 | DN99: 0 | DO99: 0 | DP99: 1 | DQ99: 1 | DU99: 1013 | DV99: 100 М КАБЕЛЯ | DW99: 100 М КАБЕЛЯ | DX99: 1 | EE99: 51696357 | EF99: 40 | EG99: Монтаж оборудования | EH99: 0 | EJ99: 2 | EK99: 318 | EL99: ТСН-2001.4-8. 8-73...8-80 | EM99: ТСН-2001.4-8-3 | EO99: Поправка: О.П. п.3.4.30.в | EQ99: 131072 | ER99: 454.68 | ES99: 0 | ET99: 379.77 | EU99: 57.67 | EV99: 74.91 | EW99: 6.08 | EX99: 0 | EY99: 0 | FQ99: 0 | FR99: 0 | FS99: 0 | FX99: 112 | FY99: 70 | GD99: 0 | GF99: 369100549 | GG99: 2 | GH99: 1 | GI99: -2 | GJ99: 0 | GK99: =ROUND(R99*(R12)/100,2) -> 0 | GL99: =ROUND(IF(AND(BH99=3,BI99=3,FS99<>0),P99,0),2) -> 0 | GM99: =ROUND(O99+X99+Y99+GK99,2)+GX99 -> 0 | GN99: =IF(OR(BI99=0,BI99=1),GM99-GX99,0) -> 0 | GO99: =IF(BI99=2,GM99-GX99,0) -> 0 | GP99: =IF(BI99=4,GM99-GX99,0) -> 0 | GR99: 0 | GS99: 0 | GT99: 0 | GV99: =ROUND((GT99),6) -> 0 | GW99: 1 | GX99: =ROUND(HC99*I99,2) -> 0 | HA99: 0 | HB99: 0 | HC99: =GV99*GW99 -> 0 | HS99: 0 | IK99: 0
A100: 17 | B100: 1 | C100: =ROW(SmtRes!A86) -> 86 | D100: =ROW(EtalonRes!A104) -> 104 | E100: 19 | F100: 4.8-74-1 | G100: Устройство постели при одном кабеле в траншее | H100: 100 М КАБЕЛЯ | I100: 0 | J100: 0 | K100: 0 | O100: =ROUND(CP100,2) -> 0 | P100: =ROUND((ROUND((AC100*AW100*I100),2)*BC100),2) -> 0 | Q100: =(ROUND((ROUND((((ET100*1.1))*AV100*I100),2)*BB100),2)+ROUND((ROUND(((AE100-((EU100*1.1)))*AV100*I100),2)*BS100),2)) -> 0 | R100: =ROUND((ROUND((AE100*AV100*I100),2)*BS100),2) -> 0 | S100: =ROUND((ROUND((AF100*AV100*I100),2)*BA100),2) -> 0 | T100: =ROUND(CU100*I100,2) -> 0 | U100: =CV100*I100 -> 0 | V100: =CW100*I100 -> 0 | W100: =ROUND(CX100*I100,2) -> 0 | X100: =ROUND(CY100,2) -> 0 | Y100: =ROUND(CZ100,2) -> 0 | AA100: 56616093 | AB100: =ROUND((AC100+AD100+AF100),6) -> 500.148 | AC100: =ROUND((ES100),6) -> 0 | AD100: =ROUND(((((ET100*1.1))-((EU100*1.1)))+AE100),6) -> 417.747 | AE100: =ROUND(((EU100*1.1)),6) -> 63.437 | AF100: =ROUND(((EV100*1.1)),6) -> 82.401 | AG100: =ROUND((AP100),6) -> 0 | AH100: =((EW100*1.1)) -> 6.688 | AI100: =((EX100*1.1)) -> 0 | AJ100: =(AS100) -> 0 | AK100: 454.68 | AL100: 0 | AM100: 379.77 | AN100: 57.67 | AO100: 74.91 | AP100: 0 | AQ100: 6.08 | AR100: 0 | AS100: 0 | AT100: 92 | AU100: 43 | AV100: 1.067 | AW100: 1.081 | AZ100: 1 | BA100: 34.51 | BB100: 12.86 | BC100: 1 | BH100: 0 | BI100: 2 | BJ100: ТСН-2001.4 Доп. 68, Сб. 8, т. 74, поз. 1 | BM100: 318 | BN100: 0 | BO100: 4.8-74-1 | BP100: 1 | BQ100: 40 | BR100: 0 | BS100: 34.51 | BT100: 1 | BU100: 1 | BV100: 1 | BW100: 1 | BX100: 1 | BZ100: 92 | CA100: 43 | CE100: 30 | CF100: 0 | CG100: 0 | CM100: 0 | CN100: Поправка: О.П. п.3.4.30.в Наименование: В отношении объектов, реализуемых с привлечением средств бюджета города Москвы, затраты, учитывающие усложненные условия производства работ (стесненность, сложность складирования и транспортной логистики, наличие в зоне производства работ действующего технологического оборудования или движения технологического транспорта и т.п.), определяются заказчиком в задании на проектирование при составлении локальных сметных расчетов (смет): для объектов, расположенных за пределами Третьего транспортного кольца города Москвы, но в пределах Московской кольцевой автомобильной дороги | CO100: 0 | CP100: =(P100+Q100+S100) -> 0 | CQ100: =ROUND((ROUND((AC100*AW100*1),2)*BC100),2) -> 0 | CR100: =(ROUND((ROUND((((ET100*1.1))*AV100*1),2)*BB100),2)+ROUND((ROUND(((AE100-((EU100*1.1)))*AV100*1),2)*BS100),2)) -> 5732.22 | CS100: =ROUND((ROUND((AE100*AV100*1),2)*BS100),2) -> 2335.98 | CT100: =ROUND((ROUND((AF100*AV100*1),2)*BA100),2) -> 3034.12 | CU100: =AG100 -> 0 | CV100: =(AH100*AV100) -> 7.136096 | CW100: =AI100 -> 0 | CX100: =AJ100 -> 0 | CY100: =S100*(BZ100/100) -> 0 | CZ100: =S100*(CA100/100) -> 0 | DE100: )*1,1 | DF100: )*1,1 | DG100: )*1,1 | DI100: )*1,1 | DJ100: )*1,1 | DN100: 112 | DO100: 70 | DP100: 1.067 | DQ100: 1.081 | DU100: 1013 | DV100: 100 М КАБЕЛЯ | DW100: 100 М КАБЕЛЯ | DX100: 1 | EE100: 51696357 | EF100: 40 | EG100: Монтаж оборудования | EH100: 0 | EJ100: 2 | EK100: 318 | EL100: ТСН-2001.4-8. 8-73...8-80 | EM100: ТСН-2001.4-8-3 | EO100: Поправка: О.П. п.3.4.30.в | EQ100: 131072 | ER100: 454.68 | ES100: 0 | ET100: 379.77 | EU100: 57.67 | EV100: 74.91 | EW100: 6.08 | EX100: 0 | EY100: 0 | FQ100: 0 | FR100: 0 | FS100: 0 | FX100: 112 | FY100: 70 | GD100: 0 | GF100: 369100549 | GG100: 2 | GH100: 1 | GI100: 2 | GJ100: 0 | GK100: =ROUND(R100*(S12)/100,2) -> 0 | GL100: =ROUND(IF(AND(BH100=3,BI100=3,FS100<>0),P100,0),2) -> 0 | GM100: =ROUND(O100+X100+Y100+GK100,2)+GX100 -> 0 | GN100: =IF(OR(BI100=0,BI100=1),GM100-GX100,0) -> 0 | GO100: =IF(BI100=2,GM100-GX100,0) -> 0 | GP100: =IF(BI100=4,GM100-GX100,0) -> 0 | GR100: 0 | GS100: 3 | GT100: 0 | GV100: =ROUND((GT100),6) -> 0 | GW100: 1 | GX100: =ROUND(HC100*I100,2) -> 0 | HA100: 0 | HB100: 0 | HC100: =GV100*GW100 -> 0 | HS100: 0 | IK100: 0
A101: 17 | B101: 1 | C101: =ROW(SmtRes!A87) -> 87 | D101: =ROW(EtalonRes!A107) -> 107 | E101: 20 | F101: 4.8-74-2 | G101: Добавлять на каждый последующий кабель при устройстве постели (к норме и расценке 4.8-74-1) | H101: 100 М КАБЕЛЯ | I101: 0 | J101: 0 | K101: 0 | O101: =ROUND(CP101,2) -> 0 | P101: =ROUND((ROUND((AC101*AW101*I101),2)*BC101),2) -> 0 | Q101: =(ROUND((ROUND((((ET101*1.1))*AV101*I101),2)*BB101),2)+ROUND((ROUND(((AE101-((EU101*1.1)))*AV101*I101),2)*BS101),2)) -> 0 | R101: =ROUND((ROUND((AE101*AV101*I101),2)*BS101),2) -> 0 | S101: =ROUND((ROUND((AF101*AV101*I101),2)*BA101),2) -> 0 | T101: =ROUND(CU101*I101,2) -> 0 | U101: =CV101*I101 -> 0 | V101: =CW101*I101 -> 0 | W101: =ROUND(CX101*I101,2) -> 0 | X101: =ROUND(CY101,2) -> 0 | Y101: =ROUND(CZ101,2) -> 0 | AA101: 56622586 | AB101: =ROUND((AC101+AD101+AF101),6) -> 150.645 | AC101: =ROUND((ES101),6) -> 0 | AD101: =ROUND(((((ET101*1.1))-((EU101*1.1)))+AE101),6) -> 119.746 | AE101: =ROUND(((EU101*1.1)),6) -> 18.183 | AF101: =ROUND(((EV101*1.1)),6) -> 30.899 | AG101: =ROUND((AP101),6) -> 0 | AH101: =((EW101*1.1)) -> 2.508 | AI101: =((EX101*1.1)) -> 0 | AJ101: =(AS101) -> 0 | AK101: 136.95 | AL101: 0 | AM101: 108.86 | AN101: 16.53 | AO101: 28.09 | AP101: 0 | AQ101: 2.28 | AR101: 0 | AS101: 0 | AT101: 112 | AU101: 70 | AV101: 1.067 | AW101: 1.081 | AZ101: 1 | BA101: 1 | BB101: 1 | BC101: 1 | BH101: 0 | BI101: 2 | BJ101: ТСН-2001.4 Доп. 68, Сб. 8, т. 74, поз. 2 | BM101: 318 | BN101: 0 | BP101: 0 | BQ101: 40 | BR101: 0 | BS101: 1 | BT101: 1 | BU101: 1 | BV101: 1 | BW101: 1 | BX101: 1 | BZ101: 112 | CA101: 70 | CE101: 30 | CF101: 0 | CG101: 0 | CM101: 0 | CN101: Поправка: О.П. п.3.4.30.в Наименование: В отношении объектов, реализуемых с привлечением средств бюджета города Москвы, затраты, учитывающие усложненные условия производства работ (стесненность, сложность складирования и транспортной логистики, наличие в зоне производства работ действующего технологического оборудования или движения технологического транспорта и т.п.), определяются заказчиком в задании на проектирование при составлении локальных сметных расчетов (смет): для объектов, расположенных за пределами Третьего транспортного кольца города Москвы, но в пределах Московской кольцевой автомобильной дороги | CO101: 0 | CP101: =(P101+Q101+S101) -> 0 | CQ101: =ROUND((ROUND((AC101*AW101*1),2)*BC101),2) -> 0 | CR101: =(ROUND((ROUND((((ET101*1.1))*AV101*1),2)*BB101),2)+ROUND((ROUND(((AE101-((EU101*1.1)))*AV101*1),2)*BS101),2)) -> 127.77 | CS101: =ROUND((ROUND((AE101*AV101*1),2)*BS101),2) -> 19.4 | CT101: =ROUND((ROUND((AF101*AV101*1),2)*BA101),2) -> 32.97 | CU101: =AG101 -> 0 | CV101: =(AH101*AV101) -> 2.676036 | CW101: =AI101 -> 0 | CX101: =AJ101 -> 0 | CY101: =((S101*BZ101)/100) -> 0 | CZ101: =((S101*CA101)/100) -> 0 | DE101: )*1,1 | DF101: )*1,1 | DG101: )*1,1 | DI101: )*1,1 | DJ101: )*1,1 | DN101: 0 | DO101: 0 | DP101: 1 | DQ101: 1 | DU101: 1013 | DV101: 100 М КАБЕЛЯ | DW101: 100 М КАБЕЛЯ | DX101: 1 | EE101: 51696357 | EF101: 40 | EG101: Монтаж оборудования | EH101: 0 | EJ101: 2 | EK101: 318 | EL101: ТСН-2001.4-8. 8-73...8-80 | EM101: ТСН-2001.4-8-3 | EO101: Поправка: О.П. п.3.4.30.в | EQ101: 131072 | ER101: 136.95 | ES101: 0 | ET101: 108.86 | EU101: 16.53 | EV101: 28.09 | EW101: 2.28 | EX101: 0 | EY101: 0 | FQ101: 0 | FR101: 0 | FS101: 0 | FX101: 112 | FY101: 70 | GD101: 0 | GF101: -2050852561 | GG101: 2 | GH101: 1 | GI101: -2 | GJ101: 0 | GK101: =ROUND(R101*(R12)/100,2) -> 0 | GL101: =ROUND(IF(AND(BH101=3,BI101=3,FS101<>0),P101,0),2) -> 0 | GM101: =ROUND(O101+X101+Y101+GK101,2)+GX101 -> 0 | GN101: =IF(OR(BI101=0,BI101=1),GM101-GX101,0) -> 0 | GO101: =IF(BI101=2,GM101-GX101,0) -> 0 | GP101: =IF(BI101=4,GM101-GX101,0) -> 0 | GR101: 0 | GS101: 0 | GT101: 0 | GV101: =ROUND((GT101),6) -> 0 | GW101: 1 | GX101: =ROUND(HC101*I101,2) -> 0 | HA101: 0 | HB101: 0 | HC101: =GV101*GW101 -> 0 | HS101: 0 | IK101: 0
A102: 17 | B102: 1 | C102: =ROW(SmtRes!A88) -> 88 | D102: =ROW(EtalonRes!A110) -> 110 | E102: 20 | F102: 4.8-74-2 | G102: Добавлять на каждый последующий кабель при устройстве постели (к норме и расценке 4.8-74-1) | H102: 100 М КАБЕЛЯ | I102: 0 | J102: 0 | K102: 0 | O102: =ROUND(CP102,2) -> 0 | P102: =ROUND((ROUND((AC102*AW102*I102),2)*BC102),2) -> 0 | Q102: =(ROUND((ROUND((((ET102*1.1))*AV102*I102),2)*BB102),2)+ROUND((ROUND(((AE102-((EU102*1.1)))*AV102*I102),2)*BS102),2)) -> 0 | R102: =ROUND((ROUND((AE102*AV102*I102),2)*BS102),2) -> 0 | S102: =ROUND((ROUND((AF102*AV102*I102),2)*BA102),2) -> 0 | T102: =ROUND(CU102*I102,2) -> 0 | U102: =CV102*I102 -> 0 | V102: =CW102*I102 -> 0 | W102: =ROUND(CX102*I102,2) -> 0 | X102: =ROUND(CY102,2) -> 0 | Y102: =ROUND(CZ102,2) -> 0 | AA102: 56616093 | AB102: =ROUND((AC102+AD102+AF102),6) -> 150.645 | AC102: =ROUND((ES102),6) -> 0 | AD102: =ROUND(((((ET102*1.1))-((EU102*1.1)))+AE102),6) -> 119.746 | AE102: =ROUND(((EU102*1.1)),6) -> 18.183 | AF102: =ROUND(((EV102*1.1)),6) -> 30.899 | AG102: =ROUND((AP102),6) -> 0 | AH102: =((EW102*1.1)) -> 2.508 | AI102: =((EX102*1.1)) -> 0 | AJ102: =(AS102) -> 0 | AK102: 136.95 | AL102: 0 | AM102: 108.86 | AN102: 16.53 | AO102: 28.09 | AP102: 0 | AQ102: 2.28 | AR102: 0 | AS102: 0 | AT102: 92 | AU102: 43 | AV102: 1.067 | AW102: 1.081 | AZ102: 1 | BA102: 34.51 | BB102: 12.86 | BC102: 1 | BH102: 0 | BI102: 2 | BJ102: ТСН-2001.4 Доп. 68, Сб. 8, т. 74, поз. 2 | BM102: 318 | BN102: 0 | BO102: 4.8-74-2 | BP102: 1 | BQ102: 40 | BR102: 0 | BS102: 34.51 | BT102: 1 | BU102: 1 | BV102: 1 | BW102: 1 | BX102: 1 | BZ102: 92 | CA102: 43 | CE102: 30 | CF102: 0 | CG102: 0 | CM102: 0 | CN102: Поправка: О.П. п.3.4.30.в Наименование: В отношении объектов, реализуемых с привлечением средств бюджета города Москвы, затраты, учитывающие усложненные условия производства работ (стесненность, сложность складирования и транспортной логистики, наличие в зоне производства работ действующего технологического оборудования или движения технологического транспорта и т.п.), определяются заказчиком в задании на проектирование при составлении локальных сметных расчетов (смет): для объектов, расположенных за пределами Третьего транспортного кольца города Москвы, но в пределах Московской кольцевой автомобильной дороги | CO102: 0 | CP102: =(P102+Q102+S102) -> 0 | CQ102: =ROUND((ROUND((AC102*AW102*1),2)*BC102),2) -> 0 | CR102: =(ROUND((ROUND((((ET102*1.1))*AV102*1),2)*BB102),2)+ROUND((ROUND(((AE102-((EU102*1.1)))*AV102*1),2)*BS102),2)) -> 1643.12 | CS102: =ROUND((ROUND((AE102*AV102*1),2)*BS102),2) -> 669.49 | CT102: =ROUND((ROUND((AF102*AV102*1),2)*BA102),2) -> 1137.79 | CU102: =AG102 -> 0 | CV102: =(AH102*AV102) -> 2.676036 | CW102: =AI102 -> 0 | CX102: =AJ102 -> 0 | CY102: =S102*(BZ102/100) -> 0 | CZ102: =S102*(CA102/100) -> 0 | DE102: )*1,1 | DF102: )*1,1 | DG102: )*1,1 | DI102: )*1,1 | DJ102: )*1,1 | DN102: 112 | DO102: 70 | DP102: 1.067 | DQ102: 1.081 | DU102: 1013 | DV102: 100 М КАБЕЛЯ | DW102: 100 М КАБЕЛЯ | DX102: 1 | EE102: 51696357 | EF102: 40 | EG102: Монтаж оборудования | EH102: 0 | EJ102: 2 | EK102: 318 | EL102: ТСН-2001.4-8. 8-73...8-80 | EM102: ТСН-2001.4-8-3 | EO102: Поправка: О.П. п.3.4.30.в | EQ102: 131072 | ER102: 136.95 | ES102: 0 | ET102: 108.86 | EU102: 16.53 | EV102: 28.09 | EW102: 2.28 | EX102: 0 | EY102: 0 | FQ102: 0 | FR102: 0 | FS102: 0 | FX102: 112 | FY102: 70 | GD102: 0 | GF102: -2050852561 | GG102: 2 | GH102: 1 | GI102: 2 | GJ102: 0 | GK102: =ROUND(R102*(S12)/100,2) -> 0 | GL102: =ROUND(IF(AND(BH102=3,BI102=3,FS102<>0),P102,0),2) -> 0 | GM102: =ROUND(O102+X102+Y102+GK102,2)+GX102 -> 0 | GN102: =IF(OR(BI102=0,BI102=1),GM102-GX102,0) -> 0 | GO102: =IF(BI102=2,GM102-GX102,0) -> 0 | GP102: =IF(BI102=4,GM102-GX102,0) -> 0 | GR102: 0 | GS102: 3 | GT102: 0 | GV102: =ROUND((GT102),6) -> 0 | GW102: 1 | GX102: =ROUND(HC102*I102,2) -> 0 | HA102: 0 | HB102: 0 | HC102: =GV102*GW102 -> 0 | HS102: 0 | IK102: 0
A103: 17 | B103: 1 | C103: =ROW(SmtRes!A89) -> 89 | D103: =ROW(EtalonRes!A113) -> 113 | E103: 21 | F103: 4.8-74-2 | G103: Добавлять на каждый последующий кабель при устройстве постели (к норме и расценке 4.8-74-1) | H103: 100 М КАБЕЛЯ | I103: 0 | J103: 0 | K103: 0 | O103: =ROUND(CP103,2) -> 0 | P103: =ROUND((ROUND((AC103*AW103*I103),2)*BC103),2) -> 0 | Q103: =(ROUND((ROUND((((ET103*1.1))*AV103*I103),2)*BB103),2)+ROUND((ROUND(((AE103-((EU103*1.1)))*AV103*I103),2)*BS103),2)) -> 0 | R103: =ROUND((ROUND((AE103*AV103*I103),2)*BS103),2) -> 0 | S103: =ROUND((ROUND((AF103*AV103*I103),2)*BA103),2) -> 0 | T103: =ROUND(CU103*I103,2) -> 0 | U103: =CV103*I103 -> 0 | V103: =CW103*I103 -> 0 | W103: =ROUND(CX103*I103,2) -> 0 | X103: =ROUND(CY103,2) -> 0 | Y103: =ROUND(CZ103,2) -> 0 | AA103: 56622586 | AB103: =ROUND((AC103+AD103+AF103),6) -> 150.645 | AC103: =ROUND((ES103),6) -> 0 | AD103: =ROUND(((((ET103*1.1))-((EU103*1.1)))+AE103),6) -> 119.746 | AE103: =ROUND(((EU103*1.1)),6) -> 18.183 | AF103: =ROUND(((EV103*1.1)),6) -> 30.899 | AG103: =ROUND((AP103),6) -> 0 | AH103: =((EW103*1.1)) -> 2.508 | AI103: =((EX103*1.1)) -> 0 | AJ103: =(AS103) -> 0 | AK103: 136.95 | AL103: 0 | AM103: 108.86 | AN103: 16.53 | AO103: 28.09 | AP103: 0 | AQ103: 2.28 | AR103: 0 | AS103: 0 | AT103: 112 | AU103: 70 | AV103: 1.067 | AW103: 1.081 | AZ103: 1 | BA103: 1 | BB103: 1 | BC103: 1 | BH103: 0 | BI103: 2 | BJ103: ТСН-2001.4 Доп. 68, Сб. 8, т. 74, поз. 2 | BM103: 318 | BN103: 0 | BP103: 0 | BQ103: 40 | BR103: 0 | BS103: 1 | BT103: 1 | BU103: 1 | BV103: 1 | BW103: 1 | BX103: 1 | BZ103: 112 | CA103: 70 | CE103: 30 | CF103: 0 | CG103: 0 | CM103: 0 | CN103: Поправка: О.П. п.3.4.30.в Наименование: В отношении объектов, реализуемых с привлечением средств бюджета города Москвы, затраты, учитывающие усложненные условия производства работ (стесненность, сложность складирования и транспортной логистики, наличие в зоне производства работ действующего технологического оборудования или движения технологического транспорта и т.п.), определяются заказчиком в задании на проектирование при составлении локальных сметных расчетов (смет): для объектов, расположенных за пределами Третьего транспортного кольца города Москвы, но в пределах Московской кольцевой автомобильной дороги | CO103: 0 | CP103: =(P103+Q103+S103) -> 0 | CQ103: =ROUND((ROUND((AC103*AW103*1),2)*BC103),2) -> 0 | CR103: =(ROUND((ROUND((((ET103*1.1))*AV103*1),2)*BB103),2)+ROUND((ROUND(((AE103-((EU103*1.1)))*AV103*1),2)*BS103),2)) -> 127.77 | CS103: =ROUND((ROUND((AE103*AV103*1),2)*BS103),2) -> 19.4 | CT103: =ROUND((ROUND((AF103*AV103*1),2)*BA103),2) -> 32.97 | CU103: =AG103 -> 0 | CV103: =(AH103*AV103) -> 2.676036 | CW103: =AI103 -> 0 | CX103: =AJ103 -> 0 | CY103: =((S103*BZ103)/100) -> 0 | CZ103: =((S103*CA103)/100) -> 0 | DE103: )*1,1 | DF103: )*1,1 | DG103: )*1,1 | DI103: )*1,1 | DJ103: )*1,1 | DN103: 0 | DO103: 0 | DP103: 1 | DQ103: 1 | DU103: 1013 | DV103: 100 М КАБЕЛЯ | DW103: 100 М КАБЕЛЯ | DX103: 1 | EE103: 51696357 | EF103: 40 | EG103: Монтаж оборудования | EH103: 0 | EJ103: 2 | EK103: 318 | EL103: ТСН-2001.4-8. 8-73...8-80 | EM103: ТСН-2001.4-8-3 | EO103: Поправка: О.П. п.3.4.30.в | EQ103: 131072 | ER103: 136.95 | ES103: 0 | ET103: 108.86 | EU103: 16.53 | EV103: 28.09 | EW103: 2.28 | EX103: 0 | EY103: 0 | FQ103: 0 | FR103: 0 | FS103: 0 | FX103: 112 | FY103: 70 | GD103: 0 | GF103: -2050852561 | GG103: 2 | GH103: 1 | GI103: -2 | GJ103: 0 | GK103: =ROUND(R103*(R12)/100,2) -> 0 | GL103: =ROUND(IF(AND(BH103=3,BI103=3,FS103<>0),P103,0),2) -> 0 | GM103: =ROUND(O103+X103+Y103+GK103,2)+GX103 -> 0 | GN103: =IF(OR(BI103=0,BI103=1),GM103-GX103,0) -> 0 | GO103: =IF(BI103=2,GM103-GX103,0) -> 0 | GP103: =IF(BI103=4,GM103-GX103,0) -> 0 | GR103: 0 | GS103: 0 | GT103: 0 | GV103: =ROUND((GT103),6) -> 0 | GW103: 1 | GX103: =ROUND(HC103*I103,2) -> 0 | HA103: 0 | HB103: 0 | HC103: =GV103*GW103 -> 0 | HS103: 0 | IK103: 0
A104: 17 | B104: 1 | C104: =ROW(SmtRes!A90) -> 90 | D104: =ROW(EtalonRes!A116) -> 116 | E104: 21 | F104: 4.8-74-2 | G104: Добавлять на каждый последующий кабель при устройстве постели (к норме и расценке 4.8-74-1) | H104: 100 М КАБЕЛЯ | I104: 0 | J104: 0 | K104: 0 | O104: =ROUND(CP104,2) -> 0 | P104: =ROUND((ROUND((AC104*AW104*I104),2)*BC104),2) -> 0 | Q104: =(ROUND((ROUND((((ET104*1.1))*AV104*I104),2)*BB104),2)+ROUND((ROUND(((AE104-((EU104*1.1)))*AV104*I104),2)*BS104),2)) -> 0 | R104: =ROUND((ROUND((AE104*AV104*I104),2)*BS104),2) -> 0 | S104: =ROUND((ROUND((AF104*AV104*I104),2)*BA104),2) -> 0 | T104: =ROUND(CU104*I104,2) -> 0 | U104: =CV104*I104 -> 0 | V104: =CW104*I104 -> 0 | W104: =ROUND(CX104*I104,2) -> 0 | X104: =ROUND(CY104,2) -> 0 | Y104: =ROUND(CZ104,2) -> 0 | AA104: 56616093 | AB104: =ROUND((AC104+AD104+AF104),6) -> 150.645 | AC104: =ROUND((ES104),6) -> 0 | AD104: =ROUND(((((ET104*1.1))-((EU104*1.1)))+AE104),6) -> 119.746 | AE104: =ROUND(((EU104*1.1)),6) -> 18.183 | AF104: =ROUND(((EV104*1.1)),6) -> 30.899 | AG104: =ROUND((AP104),6) -> 0 | AH104: =((EW104*1.1)) -> 2.508 | AI104: =((EX104*1.1)) -> 0 | AJ104: =(AS104) -> 0 | AK104: 136.95 | AL104: 0 | AM104: 108.86 | AN104: 16.53 | AO104: 28.09 | AP104: 0 | AQ104: 2.28 | AR104: 0 | AS104: 0 | AT104: 92 | AU104: 43 | AV104: 1.067 | AW104: 1.081 | AZ104: 1 | BA104: 34.51 | BB104: 12.86 | BC104: 1 | BH104: 0 | BI104: 2 | BJ104: ТСН-2001.4 Доп. 68, Сб. 8, т. 74, поз. 2 | BM104: 318 | BN104: 0 | BO104: 4.8-74-2 | BP104: 1 | BQ104: 40 | BR104: 0 | BS104: 34.51 | BT104: 1 | BU104: 1 | BV104: 1 | BW104: 1 | BX104: 1 | BZ104: 92 | CA104: 43 | CE104: 30 | CF104: 0 | CG104: 0 | CM104: 0 | CN104: Поправка: О.П. п.3.4.30.в Наименование: В отношении объектов, реализуемых с привлечением средств бюджета города Москвы, затраты, учитывающие усложненные условия производства работ (стесненность, сложность складирования и транспортной логистики, наличие в зоне производства работ действующего технологического оборудования или движения технологического транспорта и т.п.), определяются заказчиком в задании на проектирование при составлении локальных сметных расчетов (смет): для объектов, расположенных за пределами Третьего транспортного кольца города Москвы, но в пределах Московской кольцевой автомобильной дороги | CO104: 0 | CP104: =(P104+Q104+S104) -> 0 | CQ104: =ROUND((ROUND((AC104*AW104*1),2)*BC104),2) -> 0 | CR104: =(ROUND((ROUND((((ET104*1.1))*AV104*1),2)*BB104),2)+ROUND((ROUND(((AE104-((EU104*1.1)))*AV104*1),2)*BS104),2)) -> 1643.12 | CS104: =ROUND((ROUND((AE104*AV104*1),2)*BS104),2) -> 669.49 | CT104: =ROUND((ROUND((AF104*AV104*1),2)*BA104),2) -> 1137.79 | CU104: =AG104 -> 0 | CV104: =(AH104*AV104) -> 2.676036 | CW104: =AI104 -> 0 | CX104: =AJ104 -> 0 | CY104: =S104*(BZ104/100) -> 0 | CZ104: =S104*(CA104/100) -> 0 | DE104: )*1,1 | DF104: )*1,1 | DG104: )*1,1 | DI104: )*1,1 | DJ104: )*1,1 | DN104: 112 | DO104: 70 | DP104: 1.067 | DQ104: 1.081 | DU104: 1013 | DV104: 100 М КАБЕЛЯ | DW104: 100 М КАБЕЛЯ | DX104: 1 | EE104: 51696357 | EF104: 40 | EG104: Монтаж оборудования | EH104: 0 | EJ104: 2 | EK104: 318 | EL104: ТСН-2001.4-8. 8-73...8-80 | EM104: ТСН-2001.4-8-3 | EO104: Поправка: О.П. п.3.4.30.в | EQ104: 131072 | ER104: 136.95 | ES104: 0 | ET104: 108.86 | EU104: 16.53 | EV104: 28.09 | EW104: 2.28 | EX104: 0 | EY104: 0 | FQ104: 0 | FR104: 0 | FS104: 0 | FX104: 112 | FY104: 70 | GD104: 0 | GF104: -2050852561 | GG104: 2 | GH104: 1 | GI104: 2 | GJ104: 0 | GK104: =ROUND(R104*(S12)/100,2) -> 0 | GL104: =ROUND(IF(AND(BH104=3,BI104=3,FS104<>0),P104,0),2) -> 0 | GM104: =ROUND(O104+X104+Y104+GK104,2)+GX104 -> 0 | GN104: =IF(OR(BI104=0,BI104=1),GM104-GX104,0) -> 0 | GO104: =IF(BI104=2,GM104-GX104,0) -> 0 | GP104: =IF(BI104=4,GM104-GX104,0) -> 0 | GR104: 0 | GS104: 3 | GT104: 0 | GV104: =ROUND((GT104),6) -> 0 | GW104: 1 | GX104: =ROUND(HC104*I104,2) -> 0 | HA104: 0 | HB104: 0 | HC104: =GV104*GW104 -> 0 | HS104: 0 | IK104: 0
A105: 17 | B105: 1 | C105: =ROW(SmtRes!A91) -> 91 | D105: =ROW(EtalonRes!A130) -> 130 | E105: 22 | F105: 4.8-73-2 | G105: Кабели до 35 кВ в готовых траншеях без покрытий, кабель массой до 2 кг (АПВББШПг 4х70) | H105: 100 М КАБЕЛЯ | I105: 0 | J105: 0 | K105: 0 | O105: =ROUND(CP105,2) -> 0 | P105: =ROUND((ROUND((AC105*AW105*I105),2)*BC105),2) -> 0 | Q105: =(ROUND((ROUND((((ET105*1.1))*AV105*I105),2)*BB105),2)+ROUND((ROUND(((AE105-((EU105*1.1)))*AV105*I105),2)*BS105),2)) -> 0 | R105: =ROUND((ROUND((AE105*AV105*I105),2)*BS105),2) -> 0 | S105: =ROUND((ROUND((AF105*AV105*I105),2)*BA105),2) -> 0 | T105: =ROUND(CU105*I105,2) -> 0 | U105: =CV105*I105 -> 0 | V105: =CW105*I105 -> 0 | W105: =ROUND(CX105*I105,2) -> 0 | X105: =ROUND(CY105,2) -> 0 | Y105: =ROUND(CZ105,2) -> 0 | AA105: 56622586 | AB105: =ROUND((AC105+AD105+AF105),6) -> 348.807 | AC105: =ROUND((ES105),6) -> 133.13 | AD105: =ROUND(((((ET105*1.1))-((EU105*1.1)))+AE105),6) -> 55.759 | AE105: =ROUND(((EU105*1.1)),6) -> 7.084 | AF105: =ROUND(((EV105*1.1)),6) -> 159.918 | AG105: =ROUND((AP105),6) -> 0 | AH105: =((EW105*1.1)) -> 12.98 | AI105: =((EX105*1.1)) -> 0 | AJ105: =(AS105) -> 0 | AK105: 329.2 | AL105: 133.13 | AM105: 50.69 | AN105: 6.44 | AO105: 145.38 | AP105: 0 | AQ105: 11.8 | AR105: 0 | AS105: 0 | AT105: 112 | AU105: 70 | AV105: 1.067 | AW105: 1.081 | AZ105: 1 | BA105: 1 | BB105: 1 | BC105: 1 | BH105: 0 | BI105: 2 | BJ105: ТСН-2001.4 Доп. 69, Сб. 8, т. 73, поз. 2 | BM105: 318 | BN105: 0 | BP105: 0 | BQ105: 40 | BR105: 0 | BS105: 1 | BT105: 1 | BU105: 1 | BV105: 1 | BW105: 1 | BX105: 1 | BZ105: 112 | CA105: 70 | CE105: 30 | CF105: 0 | CG105: 0 | CM105: 0 | CN105: Поправка: О.П. п.3.4.30.в Наименование: В отношении объектов, реализуемых с привлечением средств бюджета города Москвы, затраты, учитывающие усложненные условия производства работ (стесненность, сложность складирования и транспортной логистики, наличие в зоне производства работ действующего технологического оборудования или движения технологического транспорта и т.п.), определяются заказчиком в задании на проектирование при составлении локальных сметных расчетов (смет): для объектов, расположенных за пределами Третьего транспортного кольца города Москвы, но в пределах Московской кольцевой автомобильной дороги | CO105: 0 | CP105: =(P105+Q105+S105) -> 0 | CQ105: =ROUND((ROUND((AC105*AW105*1),2)*BC105),2) -> 143.91 | CR105: =(ROUND((ROUND((((ET105*1.1))*AV105*1),2)*BB105),2)+ROUND((ROUND(((AE105-((EU105*1.1)))*AV105*1),2)*BS105),2)) -> 59.49 | CS105: =ROUND((ROUND((AE105*AV105*1),2)*BS105),2) -> 7.56 | CT105: =ROUND((ROUND((AF105*AV105*1),2)*BA105),2) -> 170.63 | CU105: =AG105 -> 0 | CV105: =(AH105*AV105) -> 13.84966 | CW105: =AI105 -> 0 | CX105: =AJ105 -> 0 | CY105: =((S105*BZ105)/100) -> 0 | CZ105: =((S105*CA105)/100) -> 0 | DE105: )*1,1 | DF105: )*1,1 | DG105: )*1,1 | DI105: )*1,1 | DJ105: )*1,1 | DN105: 0 | DO105: 0 | DP105: 1 | DQ105: 1 | DU105: 1013 | DV105: 100 М КАБЕЛЯ | DW105: 100 М КАБЕЛЯ | DX105: 1 | EE105: 51696357 | EF105: 40 | EG105: Монтаж оборудования | EH105: 0 | EJ105: 2 | EK105: 318 | EL105: ТСН-2001.4-8. 8-73...8-80 | EM105: ТСН-2001.4-8-3 | EO105: Поправка: О.П. п.3.4.30.в | EQ105: 131072 | ER105: 329.2 | ES105: 133.13 | ET105: 50.69 | EU105: 6.44 | EV105: 145.38 | EW105: 11.8 | EX105: 0 | EY105: 0 | FQ105: 0 | FR105: 0 | FS105: 0 | FX105: 112 | FY105: 70 | GD105: 0 | GF105: 1315311286 | GG105: 2 | GH105: 1 | GI105: -2 | GJ105: 0 | GK105: =ROUND(R105*(R12)/100,2) -> 0 | GL105: =ROUND(IF(AND(BH105=3,BI105=3,FS105<>0),P105,0),2) -> 0 | GM105: =ROUND(O105+X105+Y105+GK105,2)+GX105 -> 0 | GN105: =IF(OR(BI105=0,BI105=1),GM105-GX105,0) -> 0 | GO105: =IF(BI105=2,GM105-GX105,0) -> 0 | GP105: =IF(BI105=4,GM105-GX105,0) -> 0 | GR105: 0 | GS105: 0 | GT105: 0 | GV105: =ROUND((GT105),6) -> 0 | GW105: 1 | GX105: =ROUND(HC105*I105,2) -> 0 | HA105: 0 | HB105: 0 | HC105: =GV105*GW105 -> 0 | HS105: 0 | IK105: 0
A106: 17 | B106: 1 | C106: =ROW(SmtRes!A92) -> 92 | D106: =ROW(EtalonRes!A144) -> 144 | E106: 22 | F106: 4.8-73-2 | G106: Кабели до 35 кВ в готовых траншеях без покрытий, кабель массой до 2 кг (АПВББШПг 4х70) | H106: 100 М КАБЕЛЯ | I106: 0 | J106: 0 | K106: 0 | O106: =ROUND(CP106,2) -> 0 | P106: =ROUND((ROUND((AC106*AW106*I106),2)*BC106),2) -> 0 | Q106: =(ROUND((ROUND((((ET106*1.1))*AV106*I106),2)*BB106),2)+ROUND((ROUND(((AE106-((EU106*1.1)))*AV106*I106),2)*BS106),2)) -> 0 | R106: =ROUND((ROUND((AE106*AV106*I106),2)*BS106),2) -> 0 | S106: =ROUND((ROUND((AF106*AV106*I106),2)*BA106),2) -> 0 | T106: =ROUND(CU106*I106,2) -> 0 | U106: =CV106*I106 -> 0 | V106: =CW106*I106 -> 0 | W106: =ROUND(CX106*I106,2) -> 0 | X106: =ROUND(CY106,2) -> 0 | Y106: =ROUND(CZ106,2) -> 0 | AA106: 56616093 | AB106: =ROUND((AC106+AD106+AF106),6) -> 348.807 | AC106: =ROUND((ES106),6) -> 133.13 | AD106: =ROUND(((((ET106*1.1))-((EU106*1.1)))+AE106),6) -> 55.759 | AE106: =ROUND(((EU106*1.1)),6) -> 7.084 | AF106: =ROUND(((EV106*1.1)),6) -> 159.918 | AG106: =ROUND((AP106),6) -> 0 | AH106: =((EW106*1.1)) -> 12.98 | AI106: =((EX106*1.1)) -> 0 | AJ106: =(AS106) -> 0 | AK106: 329.2 | AL106: 133.13 | AM106: 50.69 | AN106: 6.44 | AO106: 145.38 | AP106: 0 | AQ106: 11.8 | AR106: 0 | AS106: 0 | AT106: 92 | AU106: 43 | AV106: 1.067 | AW106: 1.081 | AZ106: 1 | BA106: 34.51 | BB106: 12.18 | BC106: 6.47 | BH106: 0 | BI106: 2 | BJ106: ТСН-2001.4 Доп. 69, Сб. 8, т. 73, поз. 2 | BM106: 318 | BN106: 0 | BO106: 4.8-73-2 | BP106: 1 | BQ106: 40 | BR106: 0 | BS106: 34.51 | BT106: 1 | BU106: 1 | BV106: 1 | BW106: 1 | BX106: 1 | BZ106: 92 | CA106: 43 | CE106: 30 | CF106: 0 | CG106: 0 | CM106: 0 | CN106: Поправка: О.П. п.3.4.30.в Наименование: В отношении объектов, реализуемых с привлечением средств бюджета города Москвы, затраты, учитывающие усложненные условия производства работ (стесненность, сложность складирования и транспортной логистики, наличие в зоне производства работ действующего технологического оборудования или движения технологического транспорта и т.п.), определяются заказчиком в задании на проектирование при составлении локальных сметных расчетов (смет): для объектов, расположенных за пределами Третьего транспортного кольца города Москвы, но в пределах Московской кольцевой автомобильной дороги | CO106: 0 | CP106: =(P106+Q106+S106) -> 0 | CQ106: =ROUND((ROUND((AC106*AW106*1),2)*BC106),2) -> 931.1 | CR106: =(ROUND((ROUND((((ET106*1.1))*AV106*1),2)*BB106),2)+ROUND((ROUND(((AE106-((EU106*1.1)))*AV106*1),2)*BS106),2)) -> 724.59 | CS106: =ROUND((ROUND((AE106*AV106*1),2)*BS106),2) -> 260.9 | CT106: =ROUND((ROUND((AF106*AV106*1),2)*BA106),2) -> 5888.44 | CU106: =AG106 -> 0 | CV106: =(AH106*AV106) -> 13.84966 | CW106: =AI106 -> 0 | CX106: =AJ106 -> 0 | CY106: =S106*(BZ106/100) -> 0 | CZ106: =S106*(CA106/100) -> 0 | DE106: )*1,1 | DF106: )*1,1 | DG106: )*1,1 | DI106: )*1,1 | DJ106: )*1,1 | DN106: 112 | DO106: 70 | DP106: 1.067 | DQ106: 1.081 | DU106: 1013 | DV106: 100 М КАБЕЛЯ | DW106: 100 М КАБЕЛЯ | DX106: 1 | EE106: 51696357 | EF106: 40 | EG106: Монтаж оборудования | EH106: 0 | EJ106: 2 | EK106: 318 | EL106: ТСН-2001.4-8. 8-73...8-80 | EM106: ТСН-2001.4-8-3 | EO106: Поправка: О.П. п.3.4.30.в | EQ106: 131072 | ER106: 329.2 | ES106: 133.13 | ET106: 50.69 | EU106: 6.44 | EV106: 145.38 | EW106: 11.8 | EX106: 0 | EY106: 0 | FQ106: 0 | FR106: 0 | FS106: 0 | FX106: 112 | FY106: 70 | GD106: 0 | GF106: 1315311286 | GG106: 2 | GH106: 1 | GI106: 2 | GJ106: 0 | GK106: =ROUND(R106*(S12)/100,2) -> 0 | GL106: =ROUND(IF(AND(BH106=3,BI106=3,FS106<>0),P106,0),2) -> 0 | GM106: =ROUND(O106+X106+Y106+GK106,2)+GX106 -> 0 | GN106: =IF(OR(BI106=0,BI106=1),GM106-GX106,0) -> 0 | GO106: =IF(BI106=2,GM106-GX106,0) -> 0 | GP106: =IF(BI106=4,GM106-GX106,0) -> 0 | GR106: 0 | GS106: 3 | GT106: 0 | GV106: =ROUND((GT106),6) -> 0 | GW106: 1 | GX106: =ROUND(HC106*I106,2) -> 0 | HA106: 0 | HB106: 0 | HC106: =GV106*GW106 -> 0 | HS106: 0 | IK106: 0
