Workbook

Sheet Смета по ТСН-2001(с доп.43
A1: =Source!B1 -> Smeta.RU (495) 974-1589
J2: Форма № 4б
A3: ПИР, СМР, ПНР, материалы, оборудование (за исключением замков, предоставляемых Заказчиком) по титулу: Строительство ТП-10/0,4кВ с тр-ми 2х400кВА, 4КЛ-10кВ от ТП-10/0,4кВ луч А,Б до КЛ-10кВ направлением ТП-10/0,4кВ № № 21782 - ТП-10/0,4кВ № 24478 луч А,Б, 8КЛ-0,4кВ от ТП-10/0,4кВ до ВРЩ-0,4кВ №1-3, в т.ч. ПИР: г.Москва, ул.Феодосийская, з/у 7 для нужд МКС – филиала ПАО «Россети Московский регион»
A4: (наименование стройки и/или объекта)
A6: ЛОКАЛЬНАЯ СМЕТА № 02-01-08
A8: Строительство закрытых переходов (2 этап)
A9: (наименование работ и затрат)
A11: =CONCATENATE( "Основание: чертежи № ", Source!J12) -> Основание: чертежи №
I13: В базисном уровне цен | J13: В текущем уровне цен
E14: Сметная стоимость | I14: =I15+I16+I17+I18 -> 973.4 | J14: =J15+J16+J17+J18 -> 8742.94 | K14: тыс.руб.
E15: Строительные работы | I15: =ROUND(SUM(X1:X155)/1000, 2) -> 852.04 | J15: =ROUND((Source!F191)/1000, 2) -> 7591.87 | K15: тыс.руб.
E16: Работы по монтажу оборудования | I16: =ROUND(SUM(Y1:Y155)/1000, 2) -> 121.36 | J16: =ROUND((Source!F192)/1000, 2) -> 1151.07 | K16: тыс.руб.
E17: Оборудование | I17: =ROUND(SUM(Z1:Z155)/1000, 2) -> 0 | J17: =ROUND((Source!F183)/1000, 2) -> 0 | K17: тыс.руб.
E18: Прочие работы и затраты | I18: =ROUND(SUM(AA1:AA155)/1000, 2) -> 0 | J18: =ROUND((Source!F193+Source!F194)/1000, 2) -> 0 | K18: тыс.руб.
E19: Средства на оплату труда | I19: =ROUND(SUM(W1:W155)/1000, 2) -> 21.84 | J19: =(Source!F189+ Source!F188)/1000 -> 753.82437 | K19: тыс.руб.
E20: Затраты труда | I20: =SUM(AB1:AB155) -> 748.80028 | K20: чел.-ч.
E21: Кроме того:
E22: Возврат материалов | I22: =ROUND(SUM(AE1:AE155)/1000, 2) -> 0 | J22: =SUM(AF1:AF155)/1000 -> 0 | K22: тыс.руб.
A24: Составлен(а) по ТСН-2001 с учетом Дополнения №: 73
A25: № и период сборника коэффициентов (индексов) пересчета: Коэффициенты к ТСН-2001 МГЭ №212 III квартал 2024 года | AP25: № и период сборника коэффициентов (индексов) пересчета: Коэффициенты к ТСН-2001 МГЭ №212 III квартал 2024 года
A26: № п/п | B26: Шифр расценки и коды ресурсов | C26: Наименование работ и затрат | D26: Ед. изм. | E26: Кол-во единиц | F26: Цена на ед. изм., руб. | G26: Попра- вочные коэффи- циенты | H26: Коэффи- циенты зимних удорожа- ний | I26: Всего затрат в базисном уровне цен, руб. | J26: Коэффи- циенты (индек- сы) пере- счета, нормы НР и СП | K26: ВСЕГО затрат в текущем уровне цен, руб.
A27: 1 | B27: 2 | C27: 3 | D27: 4 | E27: 5 | F27: 6 | G27: 7 | H27: 8 | I27: 9 | J27: 10 | K27: 11
A29: Раздел: Закрытый переход 2 сквх3тр (72,8м; 113,4м)
A31: =CONCATENATE("Подраздел: ",IF(Source!G28<>"Новый подраздел", Source!G28, "")) -> Подраздел: Строительные работы
A32: 1 | B32: 3.1-51-1 Поправка: О.П. п.3.4.30.г | C32: Разработка грунта вручную в траншеях глубиной до 2 м без креплений с откосами группа грунтов 1-3 | D32: =Source!DW32 -> 100 м3 грунта | E32: =Source!I32 -> 0.019155 | Q32: =ROUND((Source!DN32/100)*ROUND((ROUND((Source!AF32*Source!AV32*Source!I32),2)),2), 2) -> 53.83 | R32: =Source!X32 -> 1539.32 | S32: =ROUND((Source!DO32/100)*ROUND((ROUND((Source!AF32*Source!AV32*Source!I32),2)),2), 2) -> 39.48 | T32: =Source!Y32 -> 725.43 | U32: =ROUND((175/100)*ROUND((ROUND((Source!AE32*Source!AV32*Source!I32),2)),2), 2) -> 0 | V32: =ROUND((160/100)*ROUND(ROUND((ROUND((Source!AE32*Source!AV32*Source!I32),2)*Source!BS32),2), 2), 2) -> 0 | AI32: 0
C33: ЗП | F33: =Source!AO32 -> 2042.62 | G33: =Source!DG32 -> *1,05 | H33: =Source!AV32 -> 1.248 | I33: =ROUND((ROUND((Source!AF32*Source!AV32*Source!I32),2)),2) -> 51.27 | J33: =IF(Source!BA32<> 0, Source!BA32, 1) -> 34.51 | K33: =Source!S32 -> 1769.33 | W33: =I33 -> 51.27
C34: НР от ЗП | D34: % | E34: =Source!DN32 -> 105 | I34: =SUM(Q32:Q33) -> 53.83 | J34: =Source!BZ32 -> 87 | K34: =SUM(R32:R33) -> 1539.32
C35: СП от ЗП | D35: % | E35: =Source!DO32 -> 77 | I35: =SUM(S32:S34) -> 39.48 | J35: =Source!CA32 -> 41 | K35: =SUM(T32:T34) -> 725.43
C36: ЗТР | D36: чел-ч | E36: =Source!AQ32 -> 192.7 | G36: =Source!DI32 -> *1,05 | H36: =Source!AV32 -> 1.248 | I36: =Source!U32 -> 4.8369072 | AB36: =I36 -> 4.8369072
C37: Всего по позиции: | H37: =I33+I34+I35+0 -> 144.58 | J37: =K33+K34+K35+0 -> 4034.08 | O37: =I33+I34+I35+0 -> 144.58 | P37: =K33+K34+K35+0 -> 4034.08 | X37: =IF(Source!BI32<=1,I33+I34+I35-0, 0) -> 144.58 | Y37: =IF(Source!BI32=2,I33+I34+I35-0, 0) -> 0 | Z37: =IF(Source!BI32=3,I33+I34+I35-0, 0) -> 0 | AA37: =IF(Source!BI32=4,I33+I34+I35,0) -> 0
A39: 2 | B39: 3.1-53-1 Поправка: О.П. п.3.4.30.г | C39: Засыпка вручную траншей, пазух котлованов и ям группа грунтов 1-3 | D39: =Source!DW33 -> 100 м3 грунта | E39: =Source!I33 -> 0.04536 | Q39: =ROUND((Source!DN33/100)*ROUND((ROUND((Source!AF33*Source!AV33*Source!I33),2)),2), 2) -> 65.6 | R39: =Source!X33 -> 1875.88 | S39: =ROUND((Source!DO33/100)*ROUND((ROUND((Source!AF33*Source!AV33*Source!I33),2)),2), 2) -> 48.11 | T39: =Source!Y33 -> 884.03 | U39: =ROUND((175/100)*ROUND((ROUND((Source!AE33*Source!AV33*Source!I33),2)),2), 2) -> 0 | V39: =ROUND((160/100)*ROUND(ROUND((ROUND((Source!AE33*Source!AV33*Source!I33),2)*Source!BS33),2), 2), 2) -> 0 | AI39: 0
C40: ="Объем: "&Source!I33&"=4,536/"&"100" -> Объем: 0,04536=4,536/100
C41: ЗП | F41: =Source!AO33 -> 1051.13 | G41: =Source!DG33 -> *1,05 | H41: =Source!AV33 -> 1.248 | I41: =ROUND((ROUND((Source!AF33*Source!AV33*Source!I33),2)),2) -> 62.48 | J41: =IF(Source!BA33<> 0, Source!BA33, 1) -> 34.51 | K41: =Source!S33 -> 2156.18 | W41: =I41 -> 62.48
C42: НР от ЗП | D42: % | E42: =Source!DN33 -> 105 | I42: =SUM(Q39:Q41) -> 65.6 | J42: =Source!BZ33 -> 87 | K42: =SUM(R39:R41) -> 1875.88
C43: СП от ЗП | D43: % | E43: =Source!DO33 -> 77 | I43: =SUM(S39:S42) -> 48.11 | J43: =Source!CA33 -> 41 | K43: =SUM(T39:T42) -> 884.03
C44: ЗТР | D44: чел-ч | E44: =Source!AQ33 -> 107.04 | G44: =Source!DI33 -> *1,05 | H44: =Source!AV33 -> 1.248 | I44: =Source!U33 -> 6.3624302 | AB44: =I44 -> 6.3624302
C45: Всего по позиции: | H45: =I41+I42+I43+0 -> 176.19 | J45: =K41+K42+K43+0 -> 4916.09 | O45: =I41+I42+I43+0 -> 176.19 | P45: =K41+K42+K43+0 -> 4916.09 | X45: =IF(Source!BI33<=1,I41+I42+I43-0, 0) -> 176.19 | Y45: =IF(Source!BI33=2,I41+I42+I43-0, 0) -> 0 | Z45: =IF(Source!BI33=3,I41+I42+I43-0, 0) -> 0 | AA45: =IF(Source!BI33=4,I41+I42+I43,0) -> 0
A47: 3 | B47: 3.4-23-3 Поправка: О.П. п.3.4.30.г | C47: Устройство закрытого (подземного) перехода методом горизонтально направленного бурения с поэтапным расширением скважины для полиэтиленовых труб в грунтах I-III группы установками с тяговым усилием до 500 кН для труб Dy = 400 мм длиной до 400 м | D47: =Source!DW34 -> 1 М | E47: =Source!I34 -> 186.2 | Q47: =ROUND((Source!DN34/100)*ROUND((ROUND((Source!AF34*Source!AV34*Source!I34),2)),2), 2) -> 8857.25 | R47: =Source!X34 -> 244120.54 | S47: =ROUND((Source!DO34/100)*ROUND((ROUND((Source!AF34*Source!AV34*Source!I34),2)),2), 2) -> 9392.25 | T47: =Source!Y34 -> 114880.25 | U47: =ROUND((175/100)*ROUND((ROUND((Source!AE34*Source!AV34*Source!I34),2)),2), 2) -> 20526.19 | V47: =ROUND((160/100)*ROUND(ROUND((ROUND((Source!AE34*Source!AV34*Source!I34),2)*Source!BS34),2), 2), 2) -> 647642.27 | AI47: 0
C48: ="Объем: "&Source!I34&"=104,1+"&"113,4-"&"31,3" -> Объем: 186,2=104,1+113,4-31,3
C49: ЗП | F49: =Source!AO34 -> 29.04 | G49: =Source!DG34 -> *1,05 | H49: =Source!AV34 -> 1.047 | I49: =ROUND((ROUND((Source!AF34*Source!AV34*Source!I34),2)),2) -> 5944.46 | J49: =IF(Source!BA34<> 0, Source!BA34, 1) -> 34.51 | K49: =Source!S34 -> 205143.31 | W49: =I49 -> 5944.46
C50: ЭМ | F50: =Source!AM34 -> 1775.53 | G50: =Source!DE34 -> *1,05 | H50: =Source!AV34 -> 1.047 | I50: =(ROUND((ROUND((((Source!ET34*1.05))*Source!AV34*Source!I34),2)),2)+ROUND((ROUND(((Source!AE34-((Source!EU34*1.05)))*Source!AV34*Source!I34),2)),2)) -> 363449.16 | J50: =IF(Source!BB34<> 0, Source!BB34, 1) -> 9.71 | K50: =Source!Q34 -> 3529091.3
C51: в т.ч. ЗПМ | F51: =Source!AN34 -> 57.3 | G51: =Source!DF34 -> *1,05 | H51: =Source!AV34 -> 1.047 | I51: =ROUND((ROUND((Source!AE34*Source!AV34*Source!I34),2)),2) -> 11729.25 | J51: =IF(Source!BS34<> 0, Source!BS34, 1) -> 34.51 | K51: =Source!R34 -> 404776.42 | W51: =I51 -> 11729.25
C52: МР | F52: =Source!AL34 -> 22.45 | G52: =Source!DD34 | H52: =Source!AW34 -> 1.079 | I52: =ROUND((ROUND((Source!AC34*Source!AW34*Source!I34),2)),2) -> 4510.43 | J52: =IF(Source!BC34<> 0, Source!BC34, 1) -> 5.92 | K52: =Source!P34 -> 26701.75
A53: 3,1 | B53: =Source!F35 -> 1.1-1-1835 | C53: Бентонит натриевый тонкого помола с содержанием органических полимеров, для сгущения, увеличения объема и придания гелеобразующих свойств буровым растворам, укрепления, снижения просачивания воды в стенках каналов | D53: =Source!DW35 -> кг | E53: =Source!I35 -> 21748.16 | F53: =Source!AK35 -> 11.3 | H53: =Source!AW35 -> 1.079 | I53: =ROUND((ROUND((Source!AC35*Source!AW35*Source!I35),2)),2)+(ROUND((ROUND(((Source!ET35)*Source!AV35*Source!I35),2)),2)+ROUND((ROUND(((Source!AE35-(Source!EU35))*Source!AV35*Source!I35),2)),2))+ROUND((ROUND((Source!AF35*Source!AV35*Source!I35),2)),2) -> 265168.79 | J53: =IF(Source!BC35<> 0, Source!BC35, 1) -> 4.57 | K53: =Source!O35 -> 1211821.4 | Q53: =ROUND((Source!DN35/100)*ROUND((ROUND((Source!AF35*Source!AV35*Source!I35),2)),2), 2) -> 0 | R53: =Source!X35 -> 0 | S53: =ROUND((Source!DO35/100)*ROUND((ROUND((Source!AF35*Source!AV35*Source!I35),2)),2), 2) -> 0 | T53: =Source!Y35 -> 0 | U53: =ROUND((175/100)*ROUND((ROUND((Source!AE35*Source!AV35*Source!I35),2)),2), 2) -> 0 | V53: =ROUND((160/100)*ROUND(ROUND((ROUND((Source!AE35*Source!AV35*Source!I35),2)*Source!BS35),2), 2), 2) -> 0 | X53: =IF(Source!BI35<=1,I53, 0) -> 265168.79 | Y53: =IF(Source!BI35=2,I53, 0) -> 0 | Z53: =IF(Source!BI35=3,I53, 0) -> 0 | AA53: =IF(Source!BI35=4,I53, 0) -> 0 | AI53: 3
A54: 3,2 | B54: =Source!F36 -> 1.1-1-3290 | C54: Средство полимерное, жидкое, водородный показатель рН от 8,5 до 10,5, для кондиционирования грунтов при проходке тоннелей с использованием ТПМК с грунтопригрузом, улучшения рабочих характеристик пенных реагентов в сложных грунтовых условиях, модификации бентонитового раствора для ТПМК с гидропригрузом | D54: =Source!DW36 -> л | E54: =Source!I36 -> 1103.7936 | F54: =Source!AK36 -> 95.37 | H54: =Source!AW36 -> 1.079 | I54: =ROUND((ROUND((Source!AC36*Source!AW36*Source!I36),2)),2)+(ROUND((ROUND(((Source!ET36)*Source!AV36*Source!I36),2)),2)+ROUND((ROUND(((Source!AE36-(Source!EU36))*Source!AV36*Source!I36),2)),2))+ROUND((ROUND((Source!AF36*Source!AV36*Source!I36),2)),2) -> 113585.03 | J54: =IF(Source!BC36<> 0, Source!BC36, 1) -> 8.48 | K54: =Source!O36 -> 963201.05 | Q54: =ROUND((Source!DN36/100)*ROUND((ROUND((Source!AF36*Source!AV36*Source!I36),2)),2), 2) -> 0 | R54: =Source!X36 -> 0 | S54: =ROUND((Source!DO36/100)*ROUND((ROUND((Source!AF36*Source!AV36*Source!I36),2)),2), 2) -> 0 | T54: =Source!Y36 -> 0 | U54: =ROUND((175/100)*ROUND((ROUND((Source!AE36*Source!AV36*Source!I36),2)),2), 2) -> 0 | V54: =ROUND((160/100)*ROUND(ROUND((ROUND((Source!AE36*Source!AV36*Source!I36),2)*Source!BS36),2), 2), 2) -> 0 | X54: =IF(Source!BI36<=1,I54, 0) -> 113585.03 | Y54: =IF(Source!BI36=2,I54, 0) -> 0 | Z54: =IF(Source!BI36=3,I54, 0) -> 0 | AA54: =IF(Source!BI36=4,I54, 0) -> 0 | AI54: 3
C55: НР от ЗП | D55: % | E55: =Source!DN34 -> 149 | I55: =SUM(Q47:Q54) -> 8857.25 | J55: =Source!BZ34 -> 119 | K55: =SUM(R47:R54) -> 244120.54
C56: СП от ЗП | D56: % | E56: =Source!DO34 -> 158 | I56: =SUM(S47:S55) -> 9392.25 | J56: =Source!CA34 -> 56 | K56: =SUM(T47:T55) -> 114880.25
C57: НР и СП от ЗПМ | D57: % | E57: =175 -> 175 | I57: =SUM(U47:U56) -> 20526.19 | J57: =160 -> 160 | K57: =SUM(V47:V56) -> 647642.27
C58: ЗТР | D58: чел-ч | E58: =Source!AQ34 -> 2.08 | G58: =Source!DI34 -> *1,05 | H58: =Source!AV34 -> 1.047 | I58: =Source!U34 -> 425.77386 | AB58: =I58 -> 425.77386
C59: Всего по позиции: | H59: =I49+I50+I52+I55+I56+I57+SUM(I53:I54) -> 791433.56 | J59: =K49+K50+K52+K55+K56+K57+SUM(K53:K54) -> 6942601.9 | O59: =I49+I50+I52+I55+I56+I57+SUM(I53:I54) -> 791433.56 | P59: =K49+K50+K52+K55+K56+K57+SUM(K53:K54) -> 6942601.9 | X59: =IF(Source!BI34<=1,I49+I50+I52+I55+I56+I57-0, 0) -> 412679.74 | Y59: =IF(Source!BI34=2,I49+I50+I52+I55+I56+I57-0, 0) -> 0 | Z59: =IF(Source!BI34=3,I49+I50+I52+I55+I56+I57-0, 0) -> 0 | AA59: =IF(Source!BI34=4,I49+I50+I52+I55+I56+I57,0) -> 0
A61: 4 | B61: Цена поставщика Поправка: О.П. п.3.4.30.г | C61: Трубы из полиэтилена ТЗК Энергопласт ТСЗ 160*8,9 Sn 16 F3 96,46 = [939,56 / 9,74] | D61: =Source!DW37 -> м | E61: =Source!I37 -> 567.6 | F61: =Source!AL37 -> 96.46 | G61: =Source!DD37 | H61: =Source!AW37 -> 1 | I61: =ROUND((ROUND((Source!AC37*Source!AW37*Source!I37),2)),2) -> 54750.7 | J61: =IF(Source!BC37<> 0, Source!BC37, 1) -> 9.74 | K61: =Source!P37 -> 533271.82 | Q61: =ROUND((Source!DN37/100)*ROUND((ROUND((Source!AF37*Source!AV37*Source!I37),2)),2), 2) -> 0 | R61: =Source!X37 -> 0 | S61: =ROUND((Source!DO37/100)*ROUND((ROUND((Source!AF37*Source!AV37*Source!I37),2)),2), 2) -> 0 | T61: =Source!Y37 -> 0 | U61: =ROUND((175/100)*ROUND((ROUND((Source!AE37*Source!AV37*Source!I37),2)),2), 2) -> 0 | V61: =ROUND((160/100)*ROUND(ROUND((ROUND((Source!AE37*Source!AV37*Source!I37),2)*Source!BS37),2), 2), 2) -> 0 | AI61: 3
C62: ="Объем: "&Source!I37&"="&Source!I34&"*"&"3+"&"9" -> Объем: 567,6=186,2*3+9
C63: Всего по позиции: | H63: =I61+0 -> 54750.7 | J63: =K61+0 -> 533271.82 | O63: =I61+0 -> 54750.7 | P63: =K61+0 -> 533271.82 | X63: =IF(Source!BI37<=1,I61-0, 0) -> 54750.7 | Y63: =IF(Source!BI37=2,I61-0, 0) -> 0 | Z63: =IF(Source!BI37=3,I61-0, 0) -> 0 | AA63: =IF(Source!BI37=4,I61,0) -> 0
A65: 5 | B65: 3.4-21-2 Поправка: О.П. п.3.4.30.г | C65: Монтаж установки горизонтально направленного бурения с тяговым усилием до 500 кН | D65: =Source!DW38 -> 1 ШТ. | E65: =Source!I38 -> 1 | Q65: =ROUND((Source!DN38/100)*ROUND((ROUND((Source!AF38*Source!AV38*Source!I38),2)),2), 2) -> 12.4 | R65: =Source!X38 -> 341.67 | S65: =ROUND((Source!DO38/100)*ROUND((ROUND((Source!AF38*Source!AV38*Source!I38),2)),2), 2) -> 13.15 | T65: =Source!Y38 -> 160.79 | U65: =ROUND((175/100)*ROUND((ROUND((Source!AE38*Source!AV38*Source!I38),2)),2), 2) -> 61.18 | V65: =ROUND((160/100)*ROUND(ROUND((ROUND((Source!AE38*Source!AV38*Source!I38),2)*Source!BS38),2), 2), 2) -> 1930.35 | AI65: 0
C66: ="Объем: "&Source!I38&"=2*"&"0+"&"1" -> Объем: 1=2*0+1
C67: ЗП | F67: =Source!AO38 -> 7.57 | G67: =Source!DG38 -> *1,05 | H67: =Source!AV38 -> 1.047 | I67: =ROUND((ROUND((Source!AF38*Source!AV38*Source!I38),2)),2) -> 8.32 | J67: =IF(Source!BA38<> 0, Source!BA38, 1) -> 34.51 | K67: =Source!S38 -> 287.12 | W67: =I67 -> 8.32
C68: ЭМ | F68: =Source!AM38 -> 1202.64 | G68: =Source!DE38 -> *1,05 | H68: =Source!AV38 -> 1.047 | I68: =(ROUND((ROUND((((Source!ET38*1.05))*Source!AV38*Source!I38),2)),2)+ROUND((ROUND(((Source!AE38-((Source!EU38*1.05)))*Source!AV38*Source!I38),2)),2)) -> 1322.12 | J68: =IF(Source!BB38<> 0, Source!BB38, 1) -> 9.56 | K68: =Source!Q38 -> 12639.47
C69: в т.ч. ЗПМ | F69: =Source!AN38 -> 31.8 | G69: =Source!DF38 -> *1,05 | H69: =Source!AV38 -> 1.047 | I69: =ROUND((ROUND((Source!AE38*Source!AV38*Source!I38),2)),2) -> 34.96 | J69: =IF(Source!BS38<> 0, Source!BS38, 1) -> 34.51 | K69: =Source!R38 -> 1206.47 | W69: =I69 -> 34.96
C70: НР от ЗП | D70: % | E70: =Source!DN38 -> 149 | I70: =SUM(Q65:Q69) -> 12.4 | J70: =Source!BZ38 -> 119 | K70: =SUM(R65:R69) -> 341.67
C71: СП от ЗП | D71: % | E71: =Source!DO38 -> 158 | I71: =SUM(S65:S70) -> 13.15 | J71: =Source!CA38 -> 56 | K71: =SUM(T65:T70) -> 160.79
C72: НР и СП от ЗПМ | D72: % | E72: =175 -> 175 | I72: =SUM(U65:U71) -> 61.18 | J72: =160 -> 160 | K72: =SUM(V65:V71) -> 1930.35
C73: ЗТР | D73: чел-ч | E73: =Source!AQ38 -> 0.6 | G73: =Source!DI38 -> *1,05 | H73: =Source!AV38 -> 1.047 | I73: =Source!U38 -> 0.65961 | AB73: =I73 -> 0.65961
C74: Всего по позиции: | H74: =I67+I68+I70+I71+I72+0 -> 1417.17 | J74: =K67+K68+K70+K71+K72+0 -> 15359.4 | O74: =I67+I68+I70+I71+I72+0 -> 1417.17 | P74: =K67+K68+K70+K71+K72+0 -> 15359.4 | X74: =IF(Source!BI38<=1,I67+I68+I70+I71+I72-0, 0) -> 1417.17 | Y74: =IF(Source!BI38=2,I67+I68+I70+I71+I72-0, 0) -> 0 | Z74: =IF(Source!BI38=3,I67+I68+I70+I71+I72-0, 0) -> 0 | AA74: =IF(Source!BI38=4,I67+I68+I70+I71+I72,0) -> 0
A76: 6 | B76: 3.4-21-4 Поправка: О.П. п.3.4.30.г | C76: Демонтаж установки горизонтального направленного бурения с тяговым усилием до 500 кН | D76: =Source!DW39 -> 1 ШТ. | E76: =Source!I39 -> 2 | Q76: =ROUND((Source!DN39/100)*ROUND((ROUND((Source!AF39*Source!AV39*Source!I39),2)),2), 2) -> 10.74 | R76: =Source!X39 -> 296.1 | S76: =ROUND((Source!DO39/100)*ROUND((ROUND((Source!AF39*Source!AV39*Source!I39),2)),2), 2) -> 11.39 | T76: =Source!Y39 -> 139.34 | U76: =ROUND((175/100)*ROUND((ROUND((Source!AE39*Source!AV39*Source!I39),2)),2), 2) -> 38.94 | V76: =ROUND((160/100)*ROUND(ROUND((ROUND((Source!AE39*Source!AV39*Source!I39),2)*Source!BS39),2), 2), 2) -> 1228.56 | AI76: 0
C77: ЗП | F77: =Source!AO39 -> 3.28 | G77: =Source!DG39 -> *1,05 | H77: =Source!AV39 -> 1.047 | I77: =ROUND((ROUND((Source!AF39*Source!AV39*Source!I39),2)),2) -> 7.21 | J77: =IF(Source!BA39<> 0, Source!BA39, 1) -> 34.51 | K77: =Source!S39 -> 248.82 | W77: =I77 -> 7.21
C78: ЭМ | F78: =Source!AM39 -> 479.26 | G78: =Source!DE39 -> *1,05 | H78: =Source!AV39 -> 1.047 | I78: =(ROUND((ROUND((((Source!ET39*1.05))*Source!AV39*Source!I39),2)),2)+ROUND((ROUND(((Source!AE39-((Source!EU39*1.05)))*Source!AV39*Source!I39),2)),2)) -> 1053.75 | J78: =IF(Source!BB39<> 0, Source!BB39, 1) -> 9.36 | K78: =Source!Q39 -> 9863.1
C79: в т.ч. ЗПМ | F79: =Source!AN39 -> 10.12 | G79: =Source!DF39 -> *1,05 | H79: =Source!AV39 -> 1.047 | I79: =ROUND((ROUND((Source!AE39*Source!AV39*Source!I39),2)),2) -> 22.25 | J79: =IF(Source!BS39<> 0, Source!BS39, 1) -> 34.51 | K79: =Source!R39 -> 767.85 | W79: =I79 -> 22.25
C80: НР от ЗП | D80: % | E80: =Source!DN39 -> 149 | I80: =SUM(Q76:Q79) -> 10.74 | J80: =Source!BZ39 -> 119 | K80: =SUM(R76:R79) -> 296.1
C81: СП от ЗП | D81: % | E81: =Source!DO39 -> 158 | I81: =SUM(S76:S80) -> 11.39 | J81: =Source!CA39 -> 56 | K81: =SUM(T76:T80) -> 139.34
C82: НР и СП от ЗПМ | D82: % | E82: =175 -> 175 | I82: =SUM(U76:U81) -> 38.94 | J82: =160 -> 160 | K82: =SUM(V76:V81) -> 1228.56
C83: ЗТР | D83: чел-ч | E83: =Source!AQ39 -> 0.26 | G83: =Source!DI39 -> *1,05 | H83: =Source!AV39 -> 1.047 | I83: =Source!U39 -> 0.571662 | AB83: =I83 -> 0.571662
C84: Всего по позиции: | H84: =I77+I78+I80+I81+I82+0 -> 1122.03 | J84: =K77+K78+K80+K81+K82+0 -> 11775.92 | O84: =I77+I78+I80+I81+I82+0 -> 1122.03 | P84: =K77+K78+K80+K81+K82+0 -> 11775.92 | X84: =IF(Source!BI39<=1,I77+I78+I80+I81+I82-0, 0) -> 1122.03 | Y84: =IF(Source!BI39=2,I77+I78+I80+I81+I82-0, 0) -> 0 | Z84: =IF(Source!BI39=3,I77+I78+I80+I81+I82-0, 0) -> 0 | AA84: =IF(Source!BI39=4,I77+I78+I80+I81+I82,0) -> 0
A86: 7 | B86: 3.22-73-2 Поправка: О.П. п.3.4.30.г | C86: Сварка полиэтиленовых труб номинальным наружным диаметром 140 мм - 160 мм | D86: =Source!DW40 -> 1 стык | E86: =Source!I40 -> 49 | Q86: =ROUND((Source!DN40/100)*ROUND((ROUND((Source!AF40*Source!AV40*Source!I40),2)),2), 2) -> 1082.78 | R86: =Source!X40 -> 30623.86 | S86: =ROUND((Source!DO40/100)*ROUND((ROUND((Source!AF40*Source!AV40*Source!I40),2)),2), 2) -> 919.96 | T86: =Source!Y40 -> 15171.45 | U86: =ROUND((175/100)*ROUND((ROUND((Source!AE40*Source!AV40*Source!I40),2)),2), 2) -> 0 | V86: =ROUND((160/100)*ROUND(ROUND((ROUND((Source!AE40*Source!AV40*Source!I40),2)*Source!BS40),2), 2), 2) -> 0 | AI86: 0
C87: ="Объем: "&Source!I40&"=55-"&"6" -> Объем: 49=55-6
C88: ЗП | F88: =Source!AO40 -> 14.83 | G88: =Source!DG40 -> *1,05 | H88: =Source!AV40 -> 1.067 | I88: =ROUND((ROUND((Source!AF40*Source!AV40*Source!I40),2)),2) -> 814.12 | J88: =IF(Source!BA40<> 0, Source!BA40, 1) -> 34.51 | K88: =Source!S40 -> 28095.28 | W88: =I88 -> 814.12
C89: ЭМ | F89: =Source!AM40 -> 2.25 | G89: =Source!DE40 -> *1,05 | H89: =Source!AV40 -> 1.067 | I89: =(ROUND((ROUND((((Source!ET40*1.05))*Source!AV40*Source!I40),2)),2)+ROUND((ROUND(((Source!AE40-((Source!EU40*1.05)))*Source!AV40*Source!I40),2)),2)) -> 123.52 | J89: =IF(Source!BB40<> 0, Source!BB40, 1) -> 8.85 | K89: =Source!Q40 -> 1093.15
C90: МР | F90: =Source!AL40 -> 0.91 | G90: =Source!DD40 | H90: =Source!AW40 -> 1.003 | I90: =ROUND((ROUND((Source!AC40*Source!AW40*Source!I40),2)),2) -> 44.72 | J90: =IF(Source!BC40<> 0, Source!BC40, 1) -> 105.24 | K90: =Source!P40 -> 4706.33
C91: НР от ЗП | D91: % | E91: =Source!DN40 -> 133 | I91: =SUM(Q86:Q90) -> 1082.78 | J91: =Source!BZ40 -> 109 | K91: =SUM(R86:R90) -> 30623.86
C92: СП от ЗП | D92: % | E92: =Source!DO40 -> 113 | I92: =SUM(S86:S91) -> 919.96 | J92: =Source!CA40 -> 54 | K92: =SUM(T86:T91) -> 15171.45
C93: ЗТР | D93: чел-ч | E93: =Source!AQ40 -> 1.15 | G93: =Source!DI40 -> *1,05 | H93: =Source!AV40 -> 1.067 | I93: =Source!U40 -> 63.131722 | AB93: =I93 -> 63.131722
C94: Всего по позиции: | H94: =I88+I89+I90+I91+I92+0 -> 2985.1 | J94: =K88+K89+K90+K91+K92+0 -> 79690.07 | O94: =I88+I89+I90+I91+I92+0 -> 2985.1 | P94: =K88+K89+K90+K91+K92+0 -> 79690.07 | X94: =IF(Source!BI40<=1,I88+I89+I90+I91+I92-0, 0) -> 2985.1 | Y94: =IF(Source!BI40=2,I88+I89+I90+I91+I92-0, 0) -> 0 | Z94: =IF(Source!BI40=3,I88+I89+I90+I91+I92-0, 0) -> 0 | AA94: =IF(Source!BI40=4,I88+I89+I90+I91+I92,0) -> 0
A96: 8 | B96: 4.10-115-29 Поправка: О.П. п.3.4.30.г | C96: Разные работы, герметизация свободного канала кабельной канализации | D96: =Source!DW41 -> канал | E96: =Source!I41 -> 4 | Q96: =ROUND((Source!DN41/100)*ROUND((ROUND((Source!AF41*Source!AV41*Source!I41),2)),2), 2) -> 6.2 | R96: =Source!X41 -> 175.89 | S96: =ROUND((Source!DO41/100)*ROUND((ROUND((Source!AF41*Source!AV41*Source!I41),2)),2), 2) -> 3.88 | T96: =Source!Y41 -> 82.21 | U96: =ROUND((175/100)*ROUND((ROUND((Source!AE41*Source!AV41*Source!I41),2)),2), 2) -> 0 | V96: =ROUND((160/100)*ROUND(ROUND((ROUND((Source!AE41*Source!AV41*Source!I41),2)*Source!BS41),2), 2), 2) -> 0 | AI96: 0
C97: ЗП | F97: =Source!AO41 -> 1.26 | G97: =Source!DG41 -> *1,05 | H97: =Source!AV41 -> 1.047 | I97: =ROUND((ROUND((Source!AF41*Source!AV41*Source!I41),2)),2) -> 5.54 | J97: =IF(Source!BA41<> 0, Source!BA41, 1) -> 34.51 | K97: =Source!S41 -> 191.19 | W97: =I97 -> 5.54
C98: МР | F98: =Source!AL41 -> 11.3 | G98: =Source!DD41 | H98: =Source!AW41 -> 1 | I98: =ROUND((ROUND((Source!AC41*Source!AW41*Source!I41),2)),2) -> 45.2 | J98: =IF(Source!BC41<> 0, Source!BC41, 1) -> 9.74 | K98: =Source!P41 -> 440.25
C99: НР от ЗП | D99: % | E99: =Source!DN41 -> 112 | I99: =SUM(Q96:Q98) -> 6.2 | J99: =Source!BZ41 -> 92 | K99: =SUM(R96:R98) -> 175.89
C100: СП от ЗП | D100: % | E100: =Source!DO41 -> 70 | I100: =SUM(S96:S99) -> 3.88 | J100: =Source!CA41 -> 43 | K100: =SUM(T96:T99) -> 82.21
C101: ЗТР | D101: чел-ч | E101: =Source!AQ41 -> 0.1 | G101: =Source!DI41 -> *1,05 | H101: =Source!AV41 -> 1.047 | I101: =Source!U41 -> 0.43974 | AB101: =I101 -> 0.43974
C102: Всего по позиции: | H102: =I97+I98+I99+I100+0 -> 60.82 | J102: =K97+K98+K99+K100+0 -> 889.54 | O102: =I97+I98+I99+I100+0 -> 60.82 | P102: =K97+K98+K99+K100+0 -> 889.54 | X102: =IF(Source!BI41<=1,I97+I98+I99+I100-0, 0) -> 0 | Y102: =IF(Source!BI41=2,I97+I98+I99+I100-0, 0) -> 60.82 | Z102: =IF(Source!BI41=3,I97+I98+I99+I100-0, 0) -> 0 | AA102: =IF(Source!BI41=4,I97+I98+I99+I100,0) -> 0
A104: 9 | B104: 1.12-3-62 Поправка: О.П. п.3.4.30.г | C104: Заглушки (пробки) полиэтиленовые для каналов кабельной канализации из хризотилцементных труб внутренним диаметром 150 мм | D104: =Source!DW42 -> шт. | E104: =Source!I42 -> 4 | F104: =Source!AL42 -> 3.9 | G104: =Source!DD42 | H104: =Source!AW42 -> 1 | I104: =ROUND((ROUND((Source!AC42*Source!AW42*Source!I42),2)),2) -> 15.6 | J104: =IF(Source!BC42<> 0, Source!BC42, 1) -> 13.93 | K104: =Source!P42 -> 217.31 | Q104: =ROUND((Source!DN42/100)*ROUND((ROUND((Source!AF42*Source!AV42*Source!I42),2)),2), 2) -> 0 | R104: =Source!X42 -> 0 | S104: =ROUND((Source!DO42/100)*ROUND((ROUND((Source!AF42*Source!AV42*Source!I42),2)),2), 2) -> 0 | T104: =Source!Y42 -> 0 | U104: =ROUND((175/100)*ROUND((ROUND((Source!AE42*Source!AV42*Source!I42),2)),2), 2) -> 0 | V104: =ROUND((160/100)*ROUND(ROUND((ROUND((Source!AE42*Source!AV42*Source!I42),2)*Source!BS42),2), 2), 2) -> 0 | AI104: 3
C105: Всего по позиции: | H105: =I104+0 -> 15.6 | J105: =K104+0 -> 217.31 | O105: =I104+0 -> 15.6 | P105: =K104+0 -> 217.31 | X105: =IF(Source!BI42<=1,I104-0, 0) -> 15.6 | Y105: =IF(Source!BI42=2,I104-0, 0) -> 0 | Z105: =IF(Source!BI42=3,I104-0, 0) -> 0 | AA105: =IF(Source!BI42=4,I104,0) -> 0
A108: =CONCATENATE("Итого по подразделу: ",IF(Source!G44<>"Новый подраздел", Source!G44, "")) -> Итого по подразделу: Строительные работы | H108: =SUM(O31:O107) -> 852105.75 | J108: =SUM(P31:P107) -> 7592756.1
A109: Итого по ТСН-2001.16 | H109: =SUM(AC31:AC108) -> 0 | J109: =SUM(AD31:AD108) -> 0
A110: Итого возвратных сумм | H110: =SUM(AE31:AE109) -> 0 | J110: =SUM(AF31:AF109) -> 0
A112: =CONCATENATE("Подраздел: ",IF(Source!G74<>"Новый подраздел", Source!G74, "")) -> Подраздел: Монтажные работы
A113: 10 | B113: 4.8-80-2 Поправка: О.П. п.3.4.30.г | C113: Прокладка кабеля напряжением до 35 кВ в проложенных трубах, блоках и коробах, при массе 1 м до 2 кг | D113: =Source!DW78 -> 100 М КАБЕЛЯ | E113: =Source!I78 -> 13.1805 | Q113: =ROUND((Source!DN78/100)*ROUND((ROUND((Source!AF78*Source!AV78*Source!I78),2)),2), 2) -> 3219.44 | R113: =Source!X78 -> 91263.08 | S113: =ROUND((Source!DO78/100)*ROUND((ROUND((Source!AF78*Source!AV78*Source!I78),2)),2), 2) -> 2012.15 | T113: =Source!Y78 -> 42655.57 | U113: =ROUND((175/100)*ROUND((ROUND((Source!AE78*Source!AV78*Source!I78),2)),2), 2) -> 166.43 | V113: =ROUND((160/100)*ROUND(ROUND((ROUND((Source!AE78*Source!AV78*Source!I78),2)*Source!BS78),2), 2), 2) -> 5251.04 | AI113: 0
C114: ="Объем: "&Source!I78&"=1318,05/"&"100" -> Объем: 13,1805=1318,05/100
C115: ЗП | F115: =Source!AO78 -> 194.66 | G115: =Source!DG78 -> *1,05 | H115: =Source!AV78 -> 1.067 | I115: =ROUND((ROUND((Source!AF78*Source!AV78*Source!I78),2)),2) -> 2874.5 | J115: =IF(Source!BA78<> 0, Source!BA78, 1) -> 34.51 | K115: =Source!S78 -> 99199 | W115: =I115 -> 2874.5
C116: ЭМ | F116: =Source!AM78 -> 52.8 | G116: =Source!DE78 -> *1,05 | H116: =Source!AV78 -> 1.067 | I116: =(ROUND((ROUND((((Source!ET78*1.05))*Source!AV78*Source!I78),2)),2)+ROUND((ROUND(((Source!AE78-((Source!EU78*1.05)))*Source!AV78*Source!I78),2)),2)) -> 779.69 | J116: =IF(Source!BB78<> 0, Source!BB78, 1) -> 12.04 | K116: =Source!Q78 -> 9387.47
C117: в т.ч. ЗПМ | F117: =Source!AN78 -> 6.44 | G117: =Source!DF78 -> *1,05 | H117: =Source!AV78 -> 1.067 | I117: =ROUND((ROUND((Source!AE78*Source!AV78*Source!I78),2)),2) -> 95.1 | J117: =IF(Source!BS78<> 0, Source!BS78, 1) -> 34.51 | K117: =Source!R78 -> 3281.9 | W117: =I117 -> 95.1
C118: МР | F118: =Source!AL78 -> 52.94 | G118: =Source!DD78 | H118: =Source!AW78 -> 1.081 | I118: =ROUND((ROUND((Source!AC78*Source!AW78*Source!I78),2)),2) -> 754.3 | J118: =IF(Source!BC78<> 0, Source!BC78, 1) -> 17.38 | K118: =Source!P78 -> 13109.73
...

Sheet Source
A1: 0 | B1: Smeta.RU (495) 974-1589 | D1: _PS_ | F1: 0 | G1: 0 | H1: 0 | I1: Smeta.RU | K1: 1 | L1: 75112 | M1: 10 | N1: 11 | O1: 15 | P1: 0 | Q1: 1
A12: 1 | B12: 210 | C12: 1 | D12: =ROW(A174) -> 174 | E12: 0 | F12: 02-01-08 Закрытый переход_(2 этап) | G12: 02-01-08 Закрытый переход | I12: 0 | K12: 0 | L12: 0 | M12: 4098 | O12: 0 | P12: 0 | Q12: 0 | R12: 160 | T12: 1 | V12: 0 | BB12: 0 | BH12: Сметные нормы списания | BI12: Коды ОКП для ТСН-2001 МГЭ (История развития) | BJ12: 1 | BK12: 1 | BL12: 0 | BM12: 0 | BN12: 1 | BO12: 0 | BP12: 6 | BQ12: 2 | BR12: 1 | BS12: 1 | BT12: 0 | BU12: 0 | BV12: 0 | BW12: 0 | BX12: 0 | BZ12: Типовой расчет для ТСН-2001 МГЭ, Новая методика с выпуска доп. 43 (Строительство), Доп 73 | CA12: История развития для ТСН-2001 (МГЭ) 73 доп от 17.07.2024 | CB12: История развития для ТСН-2001 (МГЭ) 73 доп от 17.07.2024 | CC12: История развития для ТСН-2001 (МГЭ) 73 доп от 17.07.2024 | CD12: История развития для ТСН-2001 (МГЭ) 73 доп от 17.07.2024 | CE12: Поправки для ТСН-2001 от 16.04.2024 г. доп.72 | CF12: 0 | CG12: 0 | CH12: 8 | CK12: 79 | CQ12: Территориальные сметные нормативы для Москвы (ТСН-2001) | CR12: ТЕР | CS12: 41660 | CT12: 1 | CU12: 73 | CY12: 0 | EC12: 0
A15: 15 | B15: 1
A18: 52 | B18: =B174 -> 210 | C18: =C174 -> 1 | D18: =D174 -> 12 | E18: =E174 -> 0 | F18: =F174 -> 02-01-08 Закрытый переход_(2 этап) | G18: =G174 -> 02-01-08 Закрытый переход | O18: =O174 -> 7532850.3 | P18: =P174 -> 3626729 | Q18: =Q174 -> 3562517 | R18: =R174 -> 410220.03 | S18: =S174 -> 343604.34 | T18: =T174 -> 0 | U18: =U174 -> 748.80028 | V18: =V174 -> 0 | ... GX18: =GX174 -> 0
A20: 3 | B20: 1 | D20: =ROW(A144) -> 144 | F20: Новая локальная смета | G20: Закрытые переходы | I20: 0 | K20: -1 | L20: Новая локальная смета | S20: 0 | V20: 0 | BX20: 0 | CF20: 0 | CG20: 0
A22: 52 | B22: =B144 -> 1 | C22: =C144 -> 3 | D22: =D144 -> 20 | E22: =E144 -> 0 | F22: =F144 -> Новая локальная смета | G22: =G144 -> Закрытые переходы | O22: =O144 -> 7532850.3 | P22: =P144 -> 3626729 | Q22: =Q144 -> 3562517 | R22: =R144 -> 410220.03 | S22: =S144 -> 343604.34 | T22: =T144 -> 0 | U22: =U144 -> 748.80028 | V22: =V144 -> 0 | ... GX22: =GX144 -> 0
A24: 4 | B24: 1 | D24: =ROW(A114) -> 114 | F24: Новый раздел | G24: Закрытый переход 2 сквх3тр (104,1м; 113,4м) | I24: 0 | K24: -1 | S24: 0 | V24: 0 | BX24: 0 | CJ24: 0
A26: 52 | B26: =B114 -> 1 | C26: =C114 -> 4 | D26: =D114 -> 24 | E26: =E114 -> 0 | F26: =F114 -> Новый раздел | G26: =G114 -> Закрытый переход 2 сквх3тр (104,1м; 113,4м) | O26: =O114 -> 7532850.3 | P26: =P114 -> 3626729 | Q26: =Q114 -> 3562517 | R26: =R114 -> 410220.03 | S26: =S114 -> 343604.34 | T26: =T114 -> 0 | U26: =U114 -> 748.80028 | V26: =V114 -> 0 | ... GX26: =GX114 -> 0
A28: 5 | B28: 1 | D28: =ROW(A44) -> 44 | F28: Новый подраздел | G28: Строительные работы | I28: 0 | K28: 0 | S28: 0 | V28: 0 | BX28: 0 | CJ28: 0
A30: 52 | B30: =B44 -> 1 | C30: =C44 -> 5 | D30: =D44 -> 28 | E30: =E44 -> 0 | F30: =F44 -> Новый подраздел | G30: =G44 -> Строительные работы | O30: =O44 -> 6530938.2 | P30: =P44 -> 2740359.9 | Q30: =Q44 -> 3552687.1 | R30: =R44 -> 406750.74 | S30: =S44 -> 237891.23 | T30: =T44 -> 0 | U30: =U44 -> 501.77593 | V30: =V44 -> 0 | ... GX30: =GX44 -> 0
A32: 17 | B32: 1 | C32: =ROW(SmtRes!A1) -> 1 | D32: =ROW(EtalonRes!A1) -> 1 | E32: 1 | F32: 3.1-51-1 | G32: Разработка грунта вручную в траншеях глубиной до 2 м без креплений с откосами группа грунтов 1-3 | H32: 100 м3 грунта | I32: =ROUND(0.019155,9) -> 0.019155 | J32: 0 | K32: =ROUND(0.019155,9) -> 0.019155 | O32: =ROUND(CP32,2) -> 1769.33 | P32: =ROUND((ROUND((AC32*AW32*I32),2)*BC32),2) -> 0 | Q32: =(ROUND((ROUND((((ET32*1.05))*AV32*I32),2)*BB32),2)+ROUND((ROUND(((AE32-((EU32*1.05)))*AV32*I32),2)*BS32),2)) -> 0 | R32: =ROUND((ROUND((AE32*AV32*I32),2)*BS32),2) -> 0 | S32: =ROUND((ROUND((AF32*AV32*I32),2)*BA32),2) -> 1769.33 | T32: =ROUND(CU32*I32,2) -> 0 | U32: =CV32*I32 -> 4.8369072 | V32: =CW32*I32 -> 0 | W32: =ROUND(CX32*I32,2) -> 0 | X32: =ROUND(CY32,2) -> 1539.32 | Y32: =ROUND(CZ32,2) -> 725.43 | AA32: 57737055 | AB32: =ROUND((AC32+AD32+AF32),6) -> 2144.751 | AC32: =ROUND((ES32),6) -> 0 | AD32: =ROUND(((((ET32*1.05))-((EU32*1.05)))+AE32),6) -> 0 | AE32: =ROUND(((EU32*1.05)),6) -> 0 | AF32: =ROUND(((EV32*1.05)),6) -> 2144.751 | AG32: =ROUND((AP32),6) -> 0 | AH32: =((EW32*1.05)) -> 202.335 | AI32: =((EX32*1.05)) -> 0 | AJ32: =(AS32) -> 0 | AK32: 2042.62 | AL32: 0 | AM32: 0 | AN32: 0 | AO32: 2042.62 | AP32: 0 | AQ32: 192.7 | AR32: 0 | AS32: 0 | AT32: 87 | AU32: 41 | AV32: 1.248 | AW32: 1 | AZ32: 1 | BA32: 34.51 | BB32: 1 | BC32: 1 | BH32: 0 | BI32: 1 | BJ32: ТСН-2001.3. Доп. 1-42. Сб. 1, т. 51, поз. 1 | BM32: 16 | BN32: 0 | BO32: 3.1-51-1 | BP32: 1 | BQ32: 30 | BR32: 0 | BS32: 34.51 | BT32: 1 | BU32: 1 | BV32: 1 | BW32: 1 | BX32: 1 | BZ32: 87 | CA32: 41 | CE32: 30 | CF32: 0 | CG32: 0 | CM32: 0 | CN32: Поправка: О.П. п.3.4.30.г Наименование: В отношении объектов, реализуемых с привлечением средств бюджета города Москвы, затраты, учитывающие усложненные условия производства работ (стесненность, сложность складирования и транспортной логистики, наличие в зоне производства работ действующего технологического оборудования или движения технологического транспорта и т.п.), определяются заказчиком в задании на проектирование при составлении локальных сметных расчетов (смет): для объектов города Москвы, расположенных за пределами Московской кольцевой автомобильной дороги | CO32: 0 | CP32: =(P32+Q32+S32) -> 1769.33 | CQ32: =ROUND((ROUND((AC32*AW32*1),2)*BC32),2) -> 0 | CR32: =(ROUND((ROUND((((ET32*1.05))*AV32*1),2)*BB32),2)+ROUND((ROUND(((AE32-((EU32*1.05)))*AV32*1),2)*BS32),2)) -> 0 | CS32: =ROUND((ROUND((AE32*AV32*1),2)*BS32),2) -> 0 | CT32: =ROUND((ROUND((AF32*AV32*1),2)*BA32),2) -> 92371.19 | CU32: =AG32 -> 0 | CV32: =(AH32*AV32) -> 252.51408 | CW32: =AI32 -> 0 | CX32: =AJ32 -> 0 | CY32: =S32*(BZ32/100) -> 1539.3171 | CZ32: =S32*(CA32/100) -> 725.4253 | DB32: 1 | DE32: *1,05 | DF32: *1,05 | DG32: *1,05 | DI32: *1,05 | DJ32: *1,05 | DN32: 105 | DO32: 77 | DP32: 1.248 | DQ32: 1 | DU32: 1013 | DV32: 100 м3 грунта | DW32: 100 м3 грунта | DX32: 1 | EE32: 51696099 | EF32: 30 | EG32: Строительные работы | EH32: 0 | EJ32: 1 | EK32: 16 | EL32: ТСН-2001.3-1. 1-49...1-55 | EM32: ТСН-2001.3-1-15 | EO32: Поправка: О.П. п.3.4.30.г | EQ32: 131072 | ER32: 2042.62 | ES32: 0 | ET32: 0 | EU32: 0 | EV32: 2042.62 | EW32: 192.7 | EX32: 0 | EY32: 0 | FQ32: 0 | FR32: 0 | FS32: 0 | FX32: 105 | FY32: 77 | GD32: 0 | GF32: -2104602307 | GG32: 2 | GH32: 1 | GI32: 2 | GJ32: 0 | GK32: =ROUND(R32*(R12)/100,2) -> 0 | GL32: =ROUND(IF(AND(BH32=3,BI32=3,FS32<>0),P32,0),2) -> 0 | GM32: =ROUND(O32+X32+Y32+GK32,2)+GX32 -> 4034.08 | GN32: =IF(OR(BI32=0,BI32=1),GM32-GX32,0) -> 4034.08 | GO32: =IF(BI32=2,GM32-GX32,0) -> 0 | GP32: =IF(BI32=4,GM32-GX32,0) -> 0 | GR32: 0 | GS32: 3 | GT32: 0 | GV32: =ROUND((GT32),6) -> 0 | GW32: 1 | GX32: =ROUND(HC32*I32,2) -> 0 | HA32: 0 | HB32: 0 | HC32: =GV32*GW32 -> 0 | HS32: 0 | IK32: 0
A33: 17 | B33: 1 | C33: =ROW(SmtRes!A2) -> 2 | D33: =ROW(EtalonRes!A2) -> 2 | E33: 2 | F33: 3.1-53-1 | G33: Засыпка вручную траншей, пазух котлованов и ям группа грунтов 1-3 | H33: 100 м3 грунта | I33: =ROUND(4.536/100,9) -> 0.04536 | J33: 0 | K33: =ROUND(4.536/100,9) -> 0.04536 | O33: =ROUND(CP33,2) -> 2156.18 | P33: =ROUND((ROUND((AC33*AW33*I33),2)*BC33),2) -> 0 | Q33: =(ROUND((ROUND((((ET33*1.05))*AV33*I33),2)*BB33),2)+ROUND((ROUND(((AE33-((EU33*1.05)))*AV33*I33),2)*BS33),2)) -> 0 | R33: =ROUND((ROUND((AE33*AV33*I33),2)*BS33),2) -> 0 | S33: =ROUND((ROUND((AF33*AV33*I33),2)*BA33),2) -> 2156.18 | T33: =ROUND(CU33*I33,2) -> 0 | U33: =CV33*I33 -> 6.3624302 | V33: =CW33*I33 -> 0 | W33: =ROUND(CX33*I33,2) -> 0 | X33: =ROUND(CY33,2) -> 1875.88 | Y33: =ROUND(CZ33,2) -> 884.03 | AA33: 57737055 | AB33: =ROUND((AC33+AD33+AF33),6) -> 1103.6865 | AC33: =ROUND((ES33),6) -> 0 | AD33: =ROUND(((((ET33*1.05))-((EU33*1.05)))+AE33),6) -> 0 | AE33: =ROUND(((EU33*1.05)),6) -> 0 | AF33: =ROUND(((EV33*1.05)),6) -> 1103.6865 | AG33: =ROUND((AP33),6) -> 0 | AH33: =((EW33*1.05)) -> 112.392 | AI33: =((EX33*1.05)) -> 0 | AJ33: =(AS33) -> 0 | AK33: 1051.13 | AL33: 0 | AM33: 0 | AN33: 0 | AO33: 1051.13 | AP33: 0 | AQ33: 107.04 | AR33: 0 | AS33: 0 | AT33: 87 | AU33: 41 | AV33: 1.248 | AW33: 1 | AZ33: 1 | BA33: 34.51 | BB33: 1 | BC33: 1 | BH33: 0 | BI33: 1 | BJ33: ТСН-2001.3. Доп. 1-42. Сб. 1, т. 53, поз. 1 | BM33: 16 | BN33: 0 | BO33: 3.1-53-1 | BP33: 1 | BQ33: 30 | BR33: 0 | BS33: 34.51 | BT33: 1 | BU33: 1 | BV33: 1 | BW33: 1 | BX33: 1 | BZ33: 87 | CA33: 41 | CE33: 30 | CF33: 0 | CG33: 0 | CM33: 0 | CN33: Поправка: О.П. п.3.4.30.г Наименование: В отношении объектов, реализуемых с привлечением средств бюджета города Москвы, затраты, учитывающие усложненные условия производства работ (стесненность, сложность складирования и транспортной логистики, наличие в зоне производства работ действующего технологического оборудования или движения технологического транспорта и т.п.), определяются заказчиком в задании на проектирование при составлении локальных сметных расчетов (смет): для объектов города Москвы, расположенных за пределами Московской кольцевой автомобильной дороги | CO33: 0 | CP33: =(P33+Q33+S33) -> 2156.18 | CQ33: =ROUND((ROUND((AC33*AW33*1),2)*BC33),2) -> 0 | CR33: =(ROUND((ROUND((((ET33*1.05))*AV33*1),2)*BB33),2)+ROUND((ROUND(((AE33-((EU33*1.05)))*AV33*1),2)*BS33),2)) -> 0 | CS33: =ROUND((ROUND((AE33*AV33*1),2)*BS33),2) -> 0 | CT33: =ROUND((ROUND((AF33*AV33*1),2)*BA33),2) -> 47534.07 | CU33: =AG33 -> 0 | CV33: =(AH33*AV33) -> 140.26522 | CW33: =AI33 -> 0 | CX33: =AJ33 -> 0 | CY33: =S33*(BZ33/100) -> 1875.8766 | CZ33: =S33*(CA33/100) -> 884.0338 | DB33: 2 | DE33: *1,05 | DF33: *1,05 | DG33: *1,05 | DI33: *1,05 | DJ33: *1,05 | DN33: 105 | DO33: 77 | DP33: 1.248 | DQ33: 1 | DU33: 1013 | DV33: 100 м3 грунта | DW33: 100 м3 грунта | DX33: 1 | EE33: 51696099 | EF33: 30 | EG33: Строительные работы | EH33: 0 | EJ33: 1 | EK33: 16 | EL33: ТСН-2001.3-1. 1-49...1-55 | EM33: ТСН-2001.3-1-15 | EO33: Поправка: О.П. п.3.4.30.г | EQ33: 131072 | ER33: 1051.13 | ES33: 0 | ET33: 0 | EU33: 0 | EV33: 1051.13 | EW33: 107.04 | EX33: 0 | EY33: 0 | FQ33: 0 | FR33: 0 | FS33: 0 | FX33: 105 | FY33: 77 | GD33: 0 | GF33: 1725378853 | GG33: 2 | GH33: 1 | GI33: 2 | GJ33: 0 | GK33: =ROUND(R33*(R12)/100,2) -> 0 | GL33: =ROUND(IF(AND(BH33=3,BI33=3,FS33<>0),P33,0),2) -> 0 | GM33: =ROUND(O33+X33+Y33+GK33,2)+GX33 -> 4916.09 | GN33: =IF(OR(BI33=0,BI33=1),GM33-GX33,0) -> 4916.09 | GO33: =IF(BI33=2,GM33-GX33,0) -> 0 | GP33: =IF(BI33=4,GM33-GX33,0) -> 0 | GR33: 0 | GS33: 3 | GT33: 0 | GV33: =ROUND((GT33),6) -> 0 | GW33: 1 | GX33: =ROUND(HC33*I33,2) -> 0 | HA33: 0 | HB33: 0 | HC33: =GV33*GW33 -> 0 | HS33: 0 | IK33: 0
A34: 17 | B34: 1 | C34: =ROW(SmtRes!A15) -> 15 | D34: =ROW(EtalonRes!A16) -> 16 | E34: 3 | F34: 3.4-23-3 | G34: Устройство закрытого (подземного) перехода методом горизонтально направленного бурения с поэтапным расширением скважины для полиэтиленовых труб в грунтах I-III группы установками с тяговым усилием до 500 кН для труб Dy = 400 мм длиной до 400 м | H34: 1 М | I34: =ROUND(104.1+113.4-31.3,9) -> 186.2 | J34: 0 | K34: =ROUND(104.1+113.4-31.3,9) -> 186.2 | O34: =ROUND(CP34,2) -> 3760936.4 | P34: =ROUND((ROUND((AC34*AW34*I34),2)*BC34),2) -> 26701.75 | Q34: =(ROUND((ROUND((((ET34*1.05))*AV34*I34),2)*BB34),2)+ROUND((ROUND(((AE34-((EU34*1.05)))*AV34*I34),2)*BS34),2)) -> 3529091.3 | R34: =ROUND((ROUND((AE34*AV34*I34),2)*BS34),2) -> 404776.42 | S34: =ROUND((ROUND((AF34*AV34*I34),2)*BA34),2) -> 205143.31 | T34: =ROUND(CU34*I34,2) -> 0 | U34: =CV34*I34 -> 425.77386 | V34: =CW34*I34 -> 0 | W34: =ROUND(CX34*I34,2) -> 0 | X34: =ROUND(CY34,2) -> 244120.54 | Y34: =ROUND(CZ34,2) -> 114880.25 | AA34: 57737055 | AB34: =ROUND((AC34+AD34+AF34),6) -> 1917.2485 | AC34: =ROUND((ES34),6) -> 22.45 | AD34: =ROUND(((((ET34*1.05))-((EU34*1.05)))+AE34),6) -> 1864.3065 | AE34: =ROUND(((EU34*1.05)),6) -> 60.165 | AF34: =ROUND(((EV34*1.05)),6) -> 30.492 | AG34: =ROUND((AP34),6) -> 0 | AH34: =((EW34*1.05)) -> 2.184 | AI34: =((EX34*1.05)) -> 0 | AJ34: =(AS34) -> 0 | AK34: 1827.02 | AL34: 22.45 | AM34: 1775.53 | AN34: 57.3 | AO34: 29.04 | AP34: 0 | AQ34: 2.08 | AR34: 0 | AS34: 0 | AT34: 119 | AU34: 56 | AV34: 1.047 | AW34: 1.079 | AZ34: 1 | BA34: 34.51 | BB34: 9.71 | BC34: 5.92 | BH34: 0 | BI34: 1 | BJ34: ТСН-2001.3 Доп. 69, Сб. 4, т. 23, поз. 3 | BM34: 1989 | BN34: 0 | BO34: 3.4-23-3 | BP34: 1 | BQ34: 30 | BR34: 0 | BS34: 34.51 | BT34: 1 | BU34: 1 | BV34: 1 | BW34: 1 | BX34: 1 | BZ34: 119 | CA34: 56 | CE34: 30 | CF34: 0 | CG34: 0 | CM34: 0 | CN34: Поправка: О.П. п.3.4.30.г Наименование: В отношении объектов, реализуемых с привлечением средств бюджета города Москвы, затраты, учитывающие усложненные условия производства работ (стесненность, сложность складирования и транспортной логистики, наличие в зоне производства работ действующего технологического оборудования или движения технологического транспорта и т.п.), определяются заказчиком в задании на проектирование при составлении локальных сметных расчетов (смет): для объектов города Москвы, расположенных за пределами Московской кольцевой автомобильной дороги | CO34: 0 | CP34: =(P34+Q34+S34) -> 3760936.4 | CQ34: =ROUND((ROUND((AC34*AW34*1),2)*BC34),2) -> 143.38 | CR34: =(ROUND((ROUND((((ET34*1.05))*AV34*1),2)*BB34),2)+ROUND((ROUND(((AE34-((EU34*1.05)))*AV34*1),2)*BS34),2)) -> 18953.24 | CS34: =ROUND((ROUND((AE34*AV34*1),2)*BS34),2) -> 2173.78 | CT34: =ROUND((ROUND((AF34*AV34*1),2)*BA34),2) -> 1101.9 | CU34: =AG34 -> 0 | CV34: =(AH34*AV34) -> 2.286648 | CW34: =AI34 -> 0 | CX34: =AJ34 -> 0 | CY34: =S34*(BZ34/100) -> 244120.54 | CZ34: =S34*(CA34/100) -> 114880.25 | DB34: 3 | DE34: *1,05 | DF34: *1,05 | DG34: *1,05 | DI34: *1,05 | DJ34: *1,05 | DN34: 149 | DO34: 158 | DP34: 1.047 | DQ34: 1.079 | DU34: 1013 | DV34: 1 М | DW34: 1 М | DX34: 1 | EE34: 51698030 | EF34: 30 | EG34: Строительные работы | EH34: 0 | EJ34: 1 | EK34: 1989 | EL34: ТСН-2001.3-4. 4-23-1...4-23-5 (доп. 47) | EM34: ТСН-2001.3-4-4 | EO34: Поправка: О.П. п.3.4.30.г | EQ34: 131072 | ER34: 1827.02 | ES34: 22.45 | ET34: 1775.53 | EU34: 57.3 | EV34: 29.04 | EW34: 2.08 | EX34: 0 | EY34: 0 | FQ34: 0 | FR34: 0 | FS34: 0 | FX34: 149 | FY34: 158 | GD34: 0 | GF34: 925277583 | GG34: 2 | GH34: 1 | GI34: 2 | GJ34: 0 | GK34: =ROUND(R34*(R12)/100,2) -> 647642.27 | GL34: =ROUND(IF(AND(BH34=3,BI34=3,FS34<>0),P34,0),2) -> 0 | GM34: =ROUND(O34+X34+Y34+GK34,2)+GX34 -> 4767579.5 | GN34: =IF(OR(BI34=0,BI34=1),GM34-GX34,0) -> 4767579.5 | GO34: =IF(BI34=2,GM34-GX34,0) -> 0 | GP34: =IF(BI34=4,GM34-GX34,0) -> 0 | GR34: 0 | GS34: 3 | GT34: 0 | GV34: =ROUND((GT34),6) -> 0 | GW34: 1 | GX34: =ROUND(HC34*I34,2) -> 0 | HA34: 0 | HB34: 0 | HC34: =GV34*GW34 -> 0 | HS34: 0 | IK34: 0
A35: 18 | B35: 1 | C35: 13 | E35: 3,1 | F35: 1.1-1-1835 | G35: Бентонит натриевый тонкого помола с содержанием органических полимеров, для сгущения, увеличения объема и придания гелеобразующих свойств буровым растворам, укрепления, снижения просачивания воды в стенках каналов | H35: кг | I35: =I34*J35 -> 21748.16 | J35: 116.8 | K35: 116.8 | O35: =ROUND(CP35,2) -> 1211821.4 | P35: =ROUND((ROUND((AC35*AW35*I35),2)*BC35),2) -> 1211821.4 | Q35: =(ROUND((ROUND(((ET35)*AV35*I35),2)*BB35),2)+ROUND((ROUND(((AE35-(EU35))*AV35*I35),2)*BS35),2)) -> 0 | R35: =ROUND((ROUND((AE35*AV35*I35),2)*BS35),2) -> 0 | S35: =ROUND((ROUND((AF35*AV35*I35),2)*BA35),2) -> 0 | T35: =ROUND(CU35*I35,2) -> 0 | U35: =CV35*I35 -> 0 | V35: =CW35*I35 -> 0 | W35: =ROUND(CX35*I35,2) -> 0 | X35: =ROUND(CY35,2) -> 0 | Y35: =ROUND(CZ35,2) -> 0 | AA35: 57737055 | AB35: =ROUND((AC35+AD35+AF35),6) -> 11.3 | AC35: =ROUND((ES35),6) -> 11.3 | AD35: =ROUND((((ET35)-(EU35))+AE35),6) -> 0 | AE35: =ROUND((EU35),6) -> 0 | AF35: =ROUND((EV35),6) -> 0 | AG35: =ROUND((AP35),6) -> 0 | AH35: =(EW35) -> 0 | AI35: =(EX35) -> 0 | AJ35: =(AS35) -> 0 | AK35: 11.3 | AL35: 11.3 | AM35: 0 | AN35: 0 | AO35: 0 | AP35: 0 | AQ35: 0 | AR35: 0 | AS35: 0 | AT35: 0 | AU35: 0 | AV35: 1 | AW35: 1.079 | AZ35: 1 | BA35: 1 | BB35: 1 | BC35: 4.57 | BH35: 3 | BI35: 1 | BJ35: ТСН-2001.1 Доп. 49, Р. 1, о. 1, поз. 1835 | BM35: 1989 | BN35: 0 | BO35: 1.1-1-1835 | BP35: 1 | BQ35: 30 | BR35: 0 | BS35: 1 | BT35: 1 | BU35: 1 | BV35: 1 | BW35: 1 | BX35: 1 | BZ35: 0 | CA35: 0 | CE35: 30 | CF35: 0 | CG35: 0 | CM35: 0 | CO35: 0 | CP35: =(P35+Q35+S35) -> 1211821.4 | CQ35: =ROUND((ROUND((AC35*AW35*1),2)*BC35),2) -> 55.71 | CR35: =(ROUND((ROUND(((ET35)*AV35*1),2)*BB35),2)+ROUND((ROUND(((AE35-(EU35))*AV35*1),2)*BS35),2)) -> 0 | CS35: =ROUND((ROUND((AE35*AV35*1),2)*BS35),2) -> 0 | CT35: =ROUND((ROUND((AF35*AV35*1),2)*BA35),2) -> 0 | CU35: =AG35 -> 0 | CV35: =(AH35*AV35) -> 0 | CW35: =AI35 -> 0 | CX35: =AJ35 -> 0 | CY35: =S35*(BZ35/100) -> 0 | CZ35: =S35*(CA35/100) -> 0 | DN35: 149 | DO35: 158 | DP35: 1.047 | DQ35: 1.079 | DU35: 1009 | DV35: кг | DW35: кг | DX35: 1 | EE35: 51698030 | EF35: 30 | EG35: Строительные работы | EH35: 0 | EJ35: 1 | EK35: 1989 | EL35: ТСН-2001.3-4. 4-23-1...4-23-5 (доп. 47) | EM35: ТСН-2001.3-4-4 | EQ35: 0 | ER35: 11.3 | ES35: 11.3 | ET35: 0 | EU35: 0 | EV35: 0 | EW35: 0 | EX35: 0 | FQ35: 0 | FR35: 0 | FS35: 0 | FX35: 149 | FY35: 158 | GD35: 0 | GF35: -936542528 | GG35: 2 | GH35: 1 | GI35: 2 | GJ35: 0 | GK35: =ROUND(R35*(R12)/100,2) -> 0 | GL35: =ROUND(IF(AND(BH35=3,BI35=3,FS35<>0),P35,0),2) -> 0 | GM35: =ROUND(O35+X35+Y35+GK35,2)+GX35 -> 1211821.4 | GN35: =IF(OR(BI35=0,BI35=1),GM35-GX35,0) -> 1211821.4 | GO35: =IF(BI35=2,GM35-GX35,0) -> 0 | GP35: =IF(BI35=4,GM35-GX35,0) -> 0 | GR35: 0 | GS35: 3 | GT35: 0 | GV35: =ROUND((GT35),6) -> 0 | GW35: 1 | GX35: =ROUND(HC35*I35,2) -> 0 | HA35: 0 | HB35: 0 | HC35: =GV35*GW35 -> 0 | HS35: 0 | IK35: 0
A36: 18 | B36: 1 | C36: 15 | E36: 3,2 | F36: 1.1-1-3290 | G36: Средство полимерное, жидкое, водородный показатель рН от 8,5 до 10,5, для кондиционирования грунтов при проходке тоннелей с использованием ТПМК с грунтопригрузом, улучшения рабочих характеристик пенных реагентов в сложных грунтовых условиях, модификации бентонитового раствора для ТПМК с гидропригрузом | H36: л | I36: =I34*J36 -> 1103.7936 | J36: 5.928 | K36: 5.928 | O36: =ROUND(CP36,2) -> 963201.05 | P36: =ROUND((ROUND((AC36*AW36*I36),2)*BC36),2) -> 963201.05 | Q36: =(ROUND((ROUND(((ET36)*AV36*I36),2)*BB36),2)+ROUND((ROUND(((AE36-(EU36))*AV36*I36),2)*BS36),2)) -> 0 | R36: =ROUND((ROUND((AE36*AV36*I36),2)*BS36),2) -> 0 | S36: =ROUND((ROUND((AF36*AV36*I36),2)*BA36),2) -> 0 | T36: =ROUND(CU36*I36,2) -> 0 | U36: =CV36*I36 -> 0 | V36: =CW36*I36 -> 0 | W36: =ROUND(CX36*I36,2) -> 0 | X36: =ROUND(CY36,2) -> 0 | Y36: =ROUND(CZ36,2) -> 0 | AA36: 57737055 | AB36: =ROUND((AC36+AD36+AF36),6) -> 95.37 | AC36: =ROUND((ES36),6) -> 95.37 | AD36: =ROUND((((ET36)-(EU36))+AE36),6) -> 0 | AE36: =ROUND((EU36),6) -> 0 | AF36: =ROUND((EV36),6) -> 0 | AG36: =ROUND((AP36),6) -> 0 | AH36: =(EW36) -> 0 | AI36: =(EX36) -> 0 | AJ36: =(AS36) -> 0 | AK36: 95.37 | AL36: 95.37 | AM36: 0 | AN36: 0 | AO36: 0 | AP36: 0 | AQ36: 0 | AR36: 0 | AS36: 0 | AT36: 0 | AU36: 0 | AV36: 1 | AW36: 1.079 | AZ36: 1 | BA36: 1 | BB36: 1 | BC36: 8.48 | BH36: 3 | BI36: 1 | BJ36: ТСН-2001.1 Доп. 67, Р. 1, о. 1, поз. 3290 | BM36: 1989 | BN36: 0 | BO36: 1.1-1-3290 | BP36: 1 | BQ36: 30 | BR36: 0 | BS36: 1 | BT36: 1 | BU36: 1 | BV36: 1 | BW36: 1 | BX36: 1 | BZ36: 0 | CA36: 0 | CE36: 30 | CF36: 0 | CG36: 0 | CM36: 0 | CO36: 0 | CP36: =(P36+Q36+S36) -> 963201.05 | CQ36: =ROUND((ROUND((AC36*AW36*1),2)*BC36),2) -> 872.59 | CR36: =(ROUND((ROUND(((ET36)*AV36*1),2)*BB36),2)+ROUND((ROUND(((AE36-(EU36))*AV36*1),2)*BS36),2)) -> 0 | CS36: =ROUND((ROUND((AE36*AV36*1),2)*BS36),2) -> 0 | CT36: =ROUND((ROUND((AF36*AV36*1),2)*BA36),2) -> 0 | CU36: =AG36 -> 0 | CV36: =(AH36*AV36) -> 0 | CW36: =AI36 -> 0 | CX36: =AJ36 -> 0 | CY36: =S36*(BZ36/100) -> 0 | CZ36: =S36*(CA36/100) -> 0 | DN36: 149 | DO36: 158 | DP36: 1.047 | DQ36: 1.079 | DU36: 1013 | DV36: л | DW36: л | DX36: 1 | EE36: 51698030 | EF36: 30 | EG36: Строительные работы | EH36: 0 | EJ36: 1 | EK36: 1989 | EL36: ТСН-2001.3-4. 4-23-1...4-23-5 (доп. 47) | EM36: ТСН-2001.3-4-4 | EQ36: 0 | ER36: 95.37 | ES36: 95.37 | ET36: 0 | EU36: 0 | EV36: 0 | EW36: 0 | EX36: 0 | FQ36: 0 | FR36: 0 | FS36: 0 | FX36: 149 | FY36: 158 | GD36: 0 | GF36: 1548396739 | GG36: 2 | GH36: 1 | GI36: 2 | GJ36: 0 | GK36: =ROUND(R36*(R12)/100,2) -> 0 | GL36: =ROUND(IF(AND(BH36=3,BI36=3,FS36<>0),P36,0),2) -> 0 | GM36: =ROUND(O36+X36+Y36+GK36,2)+GX36 -> 963201.05 | GN36: =IF(OR(BI36=0,BI36=1),GM36-GX36,0) -> 963201.05 | GO36: =IF(BI36=2,GM36-GX36,0) -> 0 | GP36: =IF(BI36=4,GM36-GX36,0) -> 0 | GR36: 0 | GS36: 3 | GT36: 0 | GV36: =ROUND((GT36),6) -> 0 | GW36: 1 | GX36: =ROUND(HC36*I36,2) -> 0 | HA36: 0 | HB36: 0 | HC36: =GV36*GW36 -> 0 | HS36: 0 | IK36: 0
A37: 17 | B37: 1 | E37: 4 | F37: Цена поставщика | G37: Трубы из полиэтилена ТЗК Энергопласт ТСЗ 160*8,9 Sn 16 F3 | H37: м | I37: =ROUND(I34*3+9,9) -> 567.6 | J37: 0 | K37: =ROUND(I34*3+9,9) -> 567.6 | O37: =ROUND(CP37,2) -> 533271.82 | P37: =ROUND((ROUND((AC37*AW37*I37),2)*BC37),2) -> 533271.82 | Q37: =(ROUND((ROUND((((ET37*1.05))*AV37*I37),2)*BB37),2)+ROUND((ROUND(((AE37-((EU37*1.05)))*AV37*I37),2)*BS37),2)) -> 0 | R37: =ROUND((ROUND((AE37*AV37*I37),2)*BS37),2) -> 0 | S37: =ROUND((ROUND((AF37*AV37*I37),2)*BA37),2) -> 0 | T37: =ROUND(CU37*I37,2) -> 0 | U37: =CV37*I37 -> 0 | V37: =CW37*I37 -> 0 | W37: =ROUND(CX37*I37,2) -> 0 | X37: =ROUND(CY37,2) -> 0 | Y37: =ROUND(CZ37,2) -> 0 | AA37: 57737055 | AB37: =ROUND((AC37+AD37+AF37),6) -> 96.46 | AC37: =ROUND((ES37),6) -> 96.46 | AD37: =ROUND(((((ET37*1.05))-((EU37*1.05)))+AE37),6) -> 0 | AE37: =ROUND(((EU37*1.05)),6) -> 0 | AF37: =ROUND(((EV37*1.05)),6) -> 0 | AG37: =ROUND((AP37),6) -> 0 | AH37: =((EW37*1.05)) -> 0 | AI37: =((EX37*1.05)) -> 0 | AJ37: =(AS37) -> 0 | AK37: 96.46 | AL37: 96.46 | AM37: 0 | AN37: 0 | AO37: 0 | AP37: 0 | AQ37: 0 | AR37: 0 | AS37: 0 | AT37: 0 | AU37: 0 | AV37: 1 | AW37: 1 | AZ37: 1 | BA37: 1 | BB37: 1 | BC37: 9.74 | BH37: 3 | BI37: 1 | BM37: 400002 | BN37: 0 | BP37: 0 | BQ37: 202 | BR37: 0 | BS37: 1 | BT37: 1 | BU37: 1 | BV37: 1 | BW37: 1 | BX37: 1 | BZ37: 0 | CA37: 0 | CE37: 30 | CF37: 0 | CG37: 0 | CM37: 0 | CN37: Поправка: О.П. п.3.4.30.г Наименование: В отношении объектов, реализуемых с привлечением средств бюджета города Москвы, затраты, учитывающие усложненные условия производства работ (стесненность, сложность складирования и транспортной логистики, наличие в зоне производства работ действующего технологического оборудования или движения технологического транспорта и т.п.), определяются заказчиком в задании на проектирование при составлении локальных сметных расчетов (смет): для объектов города Москвы, расположенных за пределами Московской кольцевой автомобильной дороги | CO37: 0 | CP37: =(P37+Q37+S37) -> 533271.82 | CQ37: =ROUND((ROUND((AC37*AW37*1),2)*BC37),2) -> 939.52 | CR37: =(ROUND((ROUND((((ET37*1.05))*AV37*1),2)*BB37),2)+ROUND((ROUND(((AE37-((EU37*1.05)))*AV37*1),2)*BS37),2)) -> 0 | CS37: =ROUND((ROUND((AE37*AV37*1),2)*BS37),2) -> 0 | CT37: =ROUND((ROUND((AF37*AV37*1),2)*BA37),2) -> 0 | CU37: =AG37 -> 0 | CV37: =(AH37*AV37) -> 0 | CW37: =AI37 -> 0 | CX37: =AJ37 -> 0 | CY37: =S37*(BZ37/100) -> 0 | CZ37: =S37*(CA37/100) -> 0 | DB37: 4 | DE37: *1,05 | DF37: *1,05 | DG37: *1,05 | DI37: *1,05 | DJ37: *1,05 | DN37: 0 | DO37: 0 | DP37: 1 | DQ37: 1 | DU37: 1003 | DV37: м | DW37: м | DX37: 1 | EE37: 51698006 | EF37: 202 | EG37: Материалы | EH37: 0 | EJ37: 1 | EK37: 400002 | EL37: Материалы, изделия и конструкции | EM37: Материалы | EO37: Поправка: О.П. п.3.4.30.г | EQ37: 131072 | ER37: 96.46 | ES37: 96.46 | ET37: 0 | EU37: 0 | EV37: 0 | EW37: 0 | EX37: 0 | EY37: 0 | EZ37: 5 | FC37: 0 | FD37: 18 | FF37: 939.56 | FQ37: 0 | FR37: 0 | FS37: 0 | FX37: 0 | FY37: 0 | GA37: [939,56 / 9,74] | GD37: 0 | GF37: -2093484384 | GG37: 2 | GH37: 3 | GI37: 3 | GJ37: 0 | GK37: =ROUND(R37*(R12)/100,2) -> 0 | GL37: =ROUND(IF(AND(BH37=3,BI37=3,FS37<>0),P37,0),2) -> 0 | GM37: =ROUND(O37+X37+Y37+GK37,2)+GX37 -> 533271.82 | GN37: =IF(OR(BI37=0,BI37=1),GM37-GX37,0) -> 533271.82 | GO37: =IF(BI37=2,GM37-GX37,0) -> 0 | GP37: =IF(BI37=4,GM37-GX37,0) -> 0 | GR37: 1 | GS37: 1 | GT37: 0 | GV37: =ROUND((GT37),6) -> 0 | GW37: 1 | GX37: =ROUND(HC37*I37,2) -> 0 | HA37: 0 | HB37: 0 | HC37: =GV37*GW37 -> 0 | HE37: 0 | HF37: 0 | HS37: 0 | IK37: 0
A38: 17 | B38: 1 | C38: =ROW(SmtRes!A18) -> 18 | D38: =ROW(EtalonRes!A19) -> 19 | E38: 5 | F38: 3.4-21-2 | G38: Монтаж установки горизонтально направленного бурения с тяговым усилием до 500 кН | H38: 1 ШТ. | I38: =ROUND(2*0+1,9) -> 1 | J38: 0 | K38: =ROUND(2*0+1,9) -> 1 | O38: =ROUND(CP38,2) -> 12926.59 | P38: =ROUND((ROUND((AC38*AW38*I38),2)*BC38),2) -> 0 | Q38: =(ROUND((ROUND((((ET38*1.05))*AV38*I38),2)*BB38),2)+ROUND((ROUND(((AE38-((EU38*1.05)))*AV38*I38),2)*BS38),2)) -> 12639.47 | R38: =ROUND((ROUND((AE38*AV38*I38),2)*BS38),2) -> 1206.47 | S38: =ROUND((ROUND((AF38*AV38*I38),2)*BA38),2) -> 287.12 | T38: =ROUND(CU38*I38,2) -> 0 | U38: =CV38*I38 -> 0.65961 | V38: =CW38*I38 -> 0 | W38: =ROUND(CX38*I38,2) -> 0 | X38: =ROUND(CY38,2) -> 341.67 | Y38: =ROUND(CZ38,2) -> 160.79 | AA38: 57737055 | AB38: =ROUND((AC38+AD38+AF38),6) -> 1270.7205 | AC38: =ROUND((ES38),6) -> 0 | AD38: =ROUND(((((ET38*1.05))-((EU38*1.05)))+AE38),6) -> 1262.772 | AE38: =ROUND(((EU38*1.05)),6) -> 33.39 | AF38: =ROUND(((EV38*1.05)),6) -> 7.9485 | AG38: =ROUND((AP38),6) -> 0 | AH38: =((EW38*1.05)) -> 0.63 | AI38: =((EX38*1.05)) -> 0 | AJ38: =(AS38) -> 0 | AK38: 1210.21 | AL38: 0 | AM38: 1202.64 | AN38: 31.8 | AO38: 7.57 | AP38: 0 | AQ38: 0.6 | AR38: 0 | AS38: 0 | AT38: 119 | AU38: 56 | AV38: 1.047 | AW38: 1.079 | AZ38: 1 | BA38: 34.51 | BB38: 9.56 | BC38: 1 | BH38: 0 | BI38: 1 | BJ38: ТСН-2001.3 Доп. 68, Сб. 4, т. 21, поз. 2 | BM38: 1987 | BN38: 0 | BO38: 3.4-21-2 | BP38: 1 | BQ38: 30 | BR38: 0 | BS38: 34.51 | BT38: 1 | BU38: 1 | BV38: 1 | BW38: 1 | BX38: 1 | BZ38: 119 | CA38: 56 | CE38: 30 | CF38: 0 | CG38: 0 | CM38: 0 | CN38: Поправка: О.П. п.3.4.30.г Наименование: В отношении объектов, реализуемых с привлечением средств бюджета города Москвы, затраты, учитывающие усложненные условия производства работ (стесненность, сложность складирования и транспортной логистики, наличие в зоне производства работ действующего технологического оборудования или движения технологического транспорта и т.п.), определяются заказчиком в задании на проектирование при составлении локальных сметных расчетов (смет): для объектов города Москвы, расположенных за пределами Московской кольцевой автомобильной дороги | CO38: 0 | CP38: =(P38+Q38+S38) -> 12926.59 | CQ38: =ROUND((ROUND((AC38*AW38*1),2)*BC38),2) -> 0 | CR38: =(ROUND((ROUND((((ET38*1.05))*AV38*1),2)*BB38),2)+ROUND((ROUND(((AE38-((EU38*1.05)))*AV38*1),2)*BS38),2)) -> 12639.47 | CS38: =ROUND((ROUND((AE38*AV38*1),2)*BS38),2) -> 1206.47 | CT38: =ROUND((ROUND((AF38*AV38*1),2)*BA38),2) -> 287.12 | CU38: =AG38 -> 0 | CV38: =(AH38*AV38) -> 0.65961 | CW38: =AI38 -> 0 | CX38: =AJ38 -> 0 | CY38: =S38*(BZ38/100) -> 341.6728 | CZ38: =S38*(CA38/100) -> 160.7872 | DB38: 5 | DE38: *1,05 | DF38: *1,05 | DG38: *1,05 | DI38: *1,05 | DJ38: *1,05 | DN38: 149 | DO38: 158 | DP38: 1.047 | DQ38: 1.079 | DU38: 1013 | DV38: 1 ШТ. | DW38: 1 ШТ. | DX38: 1 | EE38: 51698028 | EF38: 30 | EG38: Строительные работы | EH38: 0 | EJ38: 1 | EK38: 1987 | EL38: ТСН-2001.3-4. 4-21-1...4-21-4 (доп. 47) | EM38: ТСН-2001.3-4-2 | EO38: Поправка: О.П. п.3.4.30.г | EQ38: 131072 | ER38: 1210.21 | ES38: 0 | ET38: 1202.64 | EU38: 31.8 | EV38: 7.57 | EW38: 0.6 | EX38: 0 | EY38: 0 | FQ38: 0 | FR38: 0 | FS38: 0 | FX38: 149 | FY38: 158 | GD38: 0 | GF38: 1434979114 | GG38: 2 | GH38: 1 | GI38: 2 | GJ38: 0 | GK38: =ROUND(R38*(R12)/100,2) -> 1930.35 | GL38: =ROUND(IF(AND(BH38=3,BI38=3,FS38<>0),P38,0),2) -> 0 | GM38: =ROUND(O38+X38+Y38+GK38,2)+GX38 -> 15359.4 | GN38: =IF(OR(BI38=0,BI38=1),GM38-GX38,0) -> 15359.4 | GO38: =IF(BI38=2,GM38-GX38,0) -> 0 | GP38: =IF(BI38=4,GM38-GX38,0) -> 0 | GR38: 0 | GS38: 3 | GT38: 0 | GV38: =ROUND((GT38),6) -> 0 | GW38: 1 | GX38: =ROUND(HC38*I38,2) -> 0 | HA38: 0 | HB38: 0 | HC38: =GV38*GW38 -> 0 | HS38: 0 | IK38: 0
A39: 17 | B39: 1 | C39: =ROW(SmtRes!A20) -> 20 | D39: =ROW(EtalonRes!A21) -> 21 | E39: 6 | F39: 3.4-21-4 | G39: Демонтаж установки горизонтального направленного бурения с тяговым усилием до 500 кН | H39: 1 ШТ. | I39: 2 | J39: 0 | K39: 2 | O39: =ROUND(CP39,2) -> 10111.92 | P39: =ROUND((ROUND((AC39*AW39*I39),2)*BC39),2) -> 0 | Q39: =(ROUND((ROUND((((ET39*1.05))*AV39*I39),2)*BB39),2)+ROUND((ROUND(((AE39-((EU39*1.05)))*AV39*I39),2)*BS39),2)) -> 9863.1 | R39: =ROUND((ROUND((AE39*AV39*I39),2)*BS39),2) -> 767.85 | S39: =ROUND((ROUND((AF39*AV39*I39),2)*BA39),2) -> 248.82 | T39: =ROUND(CU39*I39,2) -> 0 | U39: =CV39*I39 -> 0.571662 | V39: =CW39*I39 -> 0 | W39: =ROUND(CX39*I39,2) -> 0 | X39: =ROUND(CY39,2) -> 296.1 | Y39: =ROUND(CZ39,2) -> 139.34 | AA39: 57737055 | AB39: =ROUND((AC39+AD39+AF39),6) -> 506.667 | AC39: =ROUND((ES39),6) -> 0 | AD39: =ROUND(((((ET39*1.05))-((EU39*1.05)))+AE39),6) -> 503.223 | AE39: =ROUND(((EU39*1.05)),6) -> 10.626 | AF39: =ROUND(((EV39*1.05)),6) -> 3.444 | AG39: =ROUND((AP39),6) -> 0 | AH39: =((EW39*1.05)) -> 0.273 | AI39: =((EX39*1.05)) -> 0 | AJ39: =(AS39) -> 0 | AK39: 482.54 | AL39: 0 | AM39: 479.26 | AN39: 10.12 | AO39: 3.28 | AP39: 0 | AQ39: 0.26 | AR39: 0 | AS39: 0 | AT39: 119 | AU39: 56 | AV39: 1.047 | AW39: 1.079 | AZ39: 1 | BA39: 34.51 | BB39: 9.36 | BC39: 1 | BH39: 0 | BI39: 1 | BJ39: ТСН-2001.3 Доп. 68, Сб. 4, т. 21, поз. 4 | BM39: 1987 | BN39: 0 | BO39: 3.4-21-4 | BP39: 1 | BQ39: 30 | BR39: 0 | BS39: 34.51 | BT39: 1 | BU39: 1 | BV39: 1 | BW39: 1 | BX39: 1 | BZ39: 119 | CA39: 56 | CE39: 30 | CF39: 0 | CG39: 0 | CM39: 0 | CN39: Поправка: О.П. п.3.4.30.г Наименование: В отношении объектов, реализуемых с привлечением средств бюджета города Москвы, затраты, учитывающие усложненные условия производства работ (стесненность, сложность складирования и транспортной логистики, наличие в зоне производства работ действующего технологического оборудования или движения технологического транспорта и т.п.), определяются заказчиком в задании на проектирование при составлении локальных сметных расчетов (смет): для объектов города Москвы, расположенных за пределами Московской кольцевой автомобильной дороги | CO39: 0 | CP39: =(P39+Q39+S39) -> 10111.92 | CQ39: =ROUND((ROUND((AC39*AW39*1),2)*BC39),2) -> 0 | CR39: =(ROUND((ROUND((((ET39*1.05))*AV39*1),2)*BB39),2)+ROUND((ROUND(((AE39-((EU39*1.05)))*AV39*1),2)*BS39),2)) -> 4931.5 | CS39: =ROUND((ROUND((AE39*AV39*1),2)*BS39),2) -> 384.1 | CT39: =ROUND((ROUND((AF39*AV39*1),2)*BA39),2) -> 124.58 | CU39: =AG39 -> 0 | CV39: =(AH39*AV39) -> 0.285831 | CW39: =AI39 -> 0 | CX39: =AJ39 -> 0 | CY39: =S39*(BZ39/100) -> 296.0958 | CZ39: =S39*(CA39/100) -> 139.3392 | DB39: 6 | DE39: *1,05 | DF39: *1,05 | DG39: *1,05 | DI39: *1,05 | DJ39: *1,05 | DN39: 149 | DO39: 158 | DP39: 1.047 | DQ39: 1.079 | DU39: 1013 | DV39: 1 ШТ. | DW39: 1 ШТ. | DX39: 1 | EE39: 51698028 | EF39: 30 | EG39: Строительные работы | EH39: 0 | EJ39: 1 | EK39: 1987 | EL39: ТСН-2001.3-4. 4-21-1...4-21-4 (доп. 47) | EM39: ТСН-2001.3-4-2 | EO39: Поправка: О.П. п.3.4.30.г | EQ39: 131072 | ER39: 482.54 | ES39: 0 | ET39: 479.26 | EU39: 10.12 | EV39: 3.28 | EW39: 0.26 | EX39: 0 | EY39: 0 | FQ39: 0 | FR39: 0 | FS39: 0 | FX39: 149 | FY39: 158 | GD39: 0 | GF39: 2045322088 | GG39: 2 | GH39: 1 | GI39: 2 | GJ39: 0 | GK39: =ROUND(R39*(R12)/100,2) -> 1228.56 | GL39: =ROUND(IF(AND(BH39=3,BI39=3,FS39<>0),P39,0),2) -> 0 | GM39: =ROUND(O39+X39+Y39+GK39,2)+GX39 -> 11775.92 | GN39: =IF(OR(BI39=0,BI39=1),GM39-GX39,0) -> 11775.92 | GO39: =IF(BI39=2,GM39-GX39,0) -> 0 | GP39: =IF(BI39=4,GM39-GX39,0) -> 0 | GR39: 0 | GS39: 3 | GT39: 0 | GV39: =ROUND((GT39),6) -> 0 | GW39: 1 | GX39: =ROUND(HC39*I39,2) -> 0 | HA39: 0 | HB39: 0 | HC39: =GV39*GW39 -> 0 | HS39: 0 | IK39: 0
A40: 17 | B40: 1 | C40: =ROW(SmtRes!A24) -> 24 | D40: =ROW(EtalonRes!A25) -> 25 | E40: 7 | F40: 3.22-73-2 | G40: Сварка полиэтиленовых труб номинальным наружным диаметром 140 мм - 160 мм | H40: 1 стык | I40: =ROUND(55-6,9) -> 49 | J40: 0 | K40: =ROUND(55-6,9) -> 49 | O40: =ROUND(CP40,2) -> 33894.76 | P40: =ROUND((ROUND((AC40*AW40*I40),2)*BC40),2) -> 4706.33 | Q40: =(ROUND((ROUND((((ET40*1.05))*AV40*I40),2)*BB40),2)+ROUND((ROUND(((AE40-((EU40*1.05)))*AV40*I40),2)*BS40),2)) -> 1093.15 | R40: =ROUND((ROUND((AE40*AV40*I40),2)*BS40),2) -> 0 | S40: =ROUND((ROUND((AF40*AV40*I40),2)*BA40),2) -> 28095.28 | T40: =ROUND(CU40*I40,2) -> 0 | U40: =CV40*I40 -> 63.131722 | V40: =CW40*I40 -> 0 | W40: =ROUND(CX40*I40,2) -> 0 | X40: =ROUND(CY40,2) -> 30623.86 | Y40: =ROUND(CZ40,2) -> 15171.45 | AA40: 57737055 | AB40: =ROUND((AC40+AD40+AF40),6) -> 18.844 | AC40: =ROUND((ES40),6) -> 0.91 | AD40: =ROUND(((((ET40*1.05))-((EU40*1.05)))+AE40),6) -> 2.3625 | AE40: =ROUND(((EU40*1.05)),6) -> 0 | AF40: =ROUND(((EV40*1.05)),6) -> 15.5715 | AG40: =ROUND((AP40),6) -> 0 | AH40: =((EW40*1.05)) -> 1.2075 | AI40: =((EX40*1.05)) -> 0 | AJ40: =(AS40) -> 0 | AK40: 17.99 | AL40: 0.91 | AM40: 2.25 | AN40: 0 | AO40: 14.83 | AP40: 0 | AQ40: 1.15 | AR40: 0 | AS40: 0 | AT40: 109 | AU40: 54 | AV40: 1.067 | AW40: 1.003 | AZ40: 1 | BA40: 34.51 | BB40: 8.85 | BC40: 105.24 | BH40: 0 | BI40: 1 | BJ40: ТСН-2001.3 Доп. 68, Сб. 22, т. 73, поз. 2 | BM40: 2167 | BN40: 0 | BO40: 3.22-73-2 | BP40: 1 | BQ40: 30 | BR40: 0 | BS40: 34.51 | BT40: 1 | BU40: 1 | BV40: 1 | BW40: 1 | BX40: 1 | BZ40: 109 | CA40: 54 | CE40: 30 | CF40: 0 | CG40: 0 | CM40: 0 | CN40: Поправка: О.П. п.3.4.30.г Наименование: В отношении объектов, реализуемых с привлечением средств бюджета города Москвы, затраты, учитывающие усложненные условия производства работ (стесненность, сложность складирования и транспортной логистики, наличие в зоне производства работ действующего технологического оборудования или движения технологического транспорта и т.п.), определяются заказчиком в задании на проектирование при составлении локальных сметных расчетов (смет): для объектов города Москвы, расположенных за пределами Московской кольцевой автомобильной дороги | CO40: 0 | CP40: =(P40+Q40+S40) -> 33894.76 | CQ40: =ROUND((ROUND((AC40*AW40*1),2)*BC40),2) -> 95.77 | CR40: =(ROUND((ROUND((((ET40*1.05))*AV40*1),2)*BB40),2)+ROUND((ROUND(((AE40-((EU40*1.05)))*AV40*1),2)*BS40),2)) -> 22.3 | CS40: =ROUND((ROUND((AE40*AV40*1),2)*BS40),2) -> 0 | CT40: =ROUND((ROUND((AF40*AV40*1),2)*BA40),2) -> 573.21 | CU40: =AG40 -> 0 | CV40: =(AH40*AV40) -> 1.2884025 | CW40: =AI40 -> 0 | CX40: =AJ40 -> 0 | CY40: =S40*(BZ40/100) -> 30623.855 | CZ40: =S40*(CA40/100) -> 15171.451 | DB40: 7 | DE40: *1,05 | DF40: *1,05 | DG40: *1,05 | DI40: *1,05 | DJ40: *1,05 | DN40: 133 | DO40: 113 | DP40: 1.067 | DQ40: 1.003 | DU40: 1013 | DV40: 1 стык | DW40: 1 стык | DX40: 1 | EE40: 51698212 | EF40: 30 | EG40: Строительные работы | EH40: 0 | EJ40: 1 | EK40: 2167 | EL40: ТСН-2001.3-22. 22-73-1...22-73-16 (доп. 60) | EM40: ТСН-2001.3-22-9 | EO40: Поправка: О.П. п.3.4.30.г | EQ40: 131072 | ER40: 17.99 | ES40: 0.91 | ET40: 2.25 | EU40: 0 | EV40: 14.83 | EW40: 1.15 | EX40: 0 | EY40: 0 | FQ40: 0 | FR40: 0 | FS40: 0 | FX40: 133 | FY40: 113 | GD40: 0 | GF40: -503870478 | GG40: 2 | GH40: 1 | GI40: 2 | GJ40: 0 | GK40: =ROUND(R40*(R12)/100,2) -> 0 | GL40: =ROUND(IF(AND(BH40=3,BI40=3,FS40<>0),P40,0),2) -> 0 | GM40: =ROUND(O40+X40+Y40+GK40,2)+GX40 -> 79690.07 | GN40: =IF(OR(BI40=0,BI40=1),GM40-GX40,0) -> 79690.07 | GO40: =IF(BI40=2,GM40-GX40,0) -> 0 | GP40: =IF(BI40=4,GM40-GX40,0) -> 0 | GR40: 0 | GS40: 3 | GT40: 0 | GV40: =ROUND((GT40),6) -> 0 | GW40: 1 | GX40: =ROUND(HC40*I40,2) -> 0 | HA40: 0 | HB40: 0 | HC40: =GV40*GW40 -> 0 | HS40: 0 | IK40: 0
A41: 17 | B41: 1 | C41: =ROW(SmtRes!A25) -> 25 | D41: =ROW(EtalonRes!A26) -> 26 | E41: 8 | F41: 4.10-115-29 | G41: Разные работы, герметизация свободного канала кабельной канализации | H41: канал | I41: =ROUND(4,9) -> 4 | J41: 0 | K41: =ROUND(4,9) -> 4 | O41: =ROUND(CP41,2) -> 631.44 | P41: =ROUND((ROUND((AC41*AW41*I41),2)*BC41),2) -> 440.25 | Q41: =(ROUND((ROUND((((ET41*1.05))*AV41*I41),2)*BB41),2)+ROUND((ROUND(((AE41-((EU41*1.05)))*AV41*I41),2)*BS41),2)) -> 0 | R41: =ROUND((ROUND((AE41*AV41*I41),2)*BS41),2) -> 0 | S41: =ROUND((ROUND((AF41*AV41*I41),2)*BA41),2) -> 191.19 | T41: =ROUND(CU41*I41,2) -> 0 | U41: =CV41*I41 -> 0.43974 | V41: =CW41*I41 -> 0 | W41: =ROUND(CX41*I41,2) -> 0 | X41: =ROUND(CY41,2) -> 175.89 | Y41: =ROUND(CZ41,2) -> 82.21 | AA41: 57737055 | AB41: =ROUND((AC41+AD41+AF41),6) -> 12.623 | AC41: =ROUND((ES41),6) -> 11.3 | AD41: =ROUND(((((ET41*1.05))-((EU41*1.05)))+AE41),6) -> 0 | AE41: =ROUND(((EU41*1.05)),6) -> 0 | AF41: =ROUND(((EV41*1.05)),6) -> 1.323 | AG41: =ROUND((AP41),6) -> 0 | AH41: =((EW41*1.05)) -> 0.105 | AI41: =((EX41*1.05)) -> 0 | AJ41: =(AS41) -> 0 | AK41: 12.56 | AL41: 11.3 | AM41: 0 | AN41: 0 | AO41: 1.26 | AP41: 0 | AQ41: 0.1 | AR41: 0 | AS41: 0 | AT41: 92 | AU41: 43 | AV41: 1.047 | AW41: 1 | AZ41: 1 | BA41: 34.51 | BB41: 1 | BC41: 9.74 | BH41: 0 | BI41: 2 | BJ41: ТСН-2001.4. Доп. 1-42. Сб. 10, т. 115, поз. 29 | BM41: 338 | BN41: 0 | BO41: 4.10-115-29 | BP41: 1 | BQ41: 40 | BR41: 0 | BS41: 34.51 | BT41: 1 | BU41: 1 | BV41: 1 | BW41: 1 | BX41: 1 | BZ41: 92 | CA41: 43 | CE41: 30 | CF41: 0 | CG41: 0 | CM41: 0 | CN41: Поправка: О.П. п.3.4.30.г Наименование: В отношении объектов, реализуемых с привлечением средств бюджета города Москвы, затраты, учитывающие усложненные условия производства работ (стесненность, сложность складирования и транспортной логистики, наличие в зоне производства работ действующего технологического оборудования или движения технологического транспорта и т.п.), определяются заказчиком в задании на проектирование при составлении локальных сметных расчетов (смет): для объектов города Москвы, расположенных за пределами Московской кольцевой автомобильной дороги | CO41: 0 | CP41: =(P41+Q41+S41) -> 631.44 | CQ41: =ROUND((ROUND((AC41*AW41*1),2)*BC41),2) -> 110.06 | CR41: =(ROUND((ROUND((((ET41*1.05))*AV41*1),2)*BB41),2)+ROUND((ROUND(((AE41-((EU41*1.05)))*AV41*1),2)*BS41),2)) -> 0 | CS41: =ROUND((ROUND((AE41*AV41*1),2)*BS41),2) -> 0 | CT41: =ROUND((ROUND((AF41*AV41*1),2)*BA41),2) -> 47.97 | CU41: =AG41 -> 0 | CV41: =(AH41*AV41) -> 0.109935 | CW41: =AI41 -> 0 | CX41: =AJ41 -> 0 | CY41: =S41*(BZ41/100) -> 175.8948 | CZ41: =S41*(CA41/100) -> 82.2117 | DB41: 8 | DE41: *1,05 | DF41: *1,05 | DG41: *1,05 | DI41: *1,05 | DJ41: *1,05 | DN41: 112 | DO41: 70 | DP41: 1.047 | DQ41: 1 | DU41: 1013 | DV41: канал | DW41: канал | DX41: 1 | EE41: 51696377 | EF41: 40 | EG41: Монтаж оборудования | EH41: 0 | EJ41: 2 | EK41: 338 | EL41: ТСН-2001.4-10. 10-115-26...10-115-33 | EM41: ТСН-2001.4-10-3 | EO41: Поправка: О.П. п.3.4.30.г | EQ41: 131072 | ER41: 12.56 | ES41: 11.3 | ET41: 0 | EU41: 0 | EV41: 1.26 | EW41: 0.1 | EX41: 0 | EY41: 0 | FQ41: 0 | FR41: 0 | FS41: 0 | FX41: 112 | FY41: 70 | GD41: 0 | GF41: -253925426 | GG41: 2 | GH41: 1 | GI41: 2 | GJ41: 0 | GK41: =ROUND(R41*(R12)/100,2) -> 0 | GL41: =ROUND(IF(AND(BH41=3,BI41=3,FS41<>0),P41,0),2) -> 0 | GM41: =ROUND(O41+X41+Y41+GK41,2)+GX41 -> 889.54 | GN41: =IF(OR(BI41=0,BI41=1),GM41-GX41,0) -> 0 | GO41: =IF(BI41=2,GM41-GX41,0) -> 889.54 | GP41: =IF(BI41=4,GM41-GX41,0) -> 0 | GR41: 0 | GS41: 3 | GT41: 0 | GV41: =ROUND((GT41),6) -> 0 | GW41: 1 | GX41: =ROUND(HC41*I41,2) -> 0 | HA41: 0 | HB41: 0 | HC41: =GV41*GW41 -> 0 | HS41: 0 | IK41: 0
A42: 17 | B42: 1 | E42: 9 | F42: 1.12-3-62 | G42: Заглушки (пробки) полиэтиленовые для каналов кабельной канализации из хризотилцементных труб внутренним диаметром 150 мм | H42: шт. | I42: =ROUND(4,9) -> 4 | J42: 0 | K42: =ROUND(4,9) -> 4 | O42: =ROUND(CP42,2) -> 217.31 | P42: =ROUND((ROUND((AC42*AW42*I42),2)*BC42),2) -> 217.31 | Q42: =(ROUND((ROUND((((ET42*1.05))*AV42*I42),2)*BB42),2)+ROUND((ROUND(((AE42-((EU42*1.05)))*AV42*I42),2)*BS42),2)) -> 0 | R42: =ROUND((ROUND((AE42*AV42*I42),2)*BS42),2) -> 0 | S42: =ROUND((ROUND((AF42*AV42*I42),2)*BA42),2) -> 0 | T42: =ROUND(CU42*I42,2) -> 0 | U42: =CV42*I42 -> 0 | V42: =CW42*I42 -> 0 | W42: =ROUND(CX42*I42,2) -> 0 | X42: =ROUND(CY42,2) -> 0 | Y42: =ROUND(CZ42,2) -> 0 | AA42: 57737055 | AB42: =ROUND((AC42+AD42+AF42),6) -> 3.9 | AC42: =ROUND((ES42),6) -> 3.9 | AD42: =ROUND(((((ET42*1.05))-((EU42*1.05)))+AE42),6) -> 0 | AE42: =ROUND(((EU42*1.05)),6) -> 0 | AF42: =ROUND(((EV42*1.05)),6) -> 0 | AG42: =ROUND((AP42),6) -> 0 | AH42: =((EW42*1.05)) -> 0 | AI42: =((EX42*1.05)) -> 0 | AJ42: =(AS42) -> 0 | AK42: 3.9 | AL42: 3.9 | AM42: 0 | AN42: 0 | AO42: 0 | AP42: 0 | AQ42: 0 | AR42: 0 | AS42: 0 | AT42: 0 | AU42: 0 | AV42: 1 | AW42: 1 | AZ42: 1 | BA42: 1 | BB42: 1 | BC42: 13.93 | BH42: 3 | BI42: 1 | BJ42: ТСН-2001.1 Доп. 70, Р. 12, о. 3, поз. 62 | BM42: 1617 | BN42: 0 | BO42: 1.12-3-62 | BP42: 1 | BQ42: 200 | BR42: 0 | BS42: 1 | BT42: 1 | BU42: 1 | BV42: 1 | BW42: 1 | BX42: 1 | BZ42: 0 | CA42: 0 | CE42: 30 | CF42: 0 | CG42: 0 | CM42: 0 | CN42: Поправка: О.П. п.3.4.30.г Наименование: В отношении объектов, реализуемых с привлечением средств бюджета города Москвы, затраты, учитывающие усложненные условия производства работ (стесненность, сложность складирования и транспортной логистики, наличие в зоне производства работ действующего технологического оборудования или движения технологического транспорта и т.п.), определяются заказчиком в задании на проектирование при составлении локальных сметных расчетов (смет): для объектов города Москвы, расположенных за пределами Московской кольцевой автомобильной дороги | CO42: 0 | CP42: =(P42+Q42+S42) -> 217.31 | CQ42: =ROUND((ROUND((AC42*AW42*1),2)*BC42),2) -> 54.33 | CR42: =(ROUND((ROUND((((ET42*1.05))*AV42*1),2)*BB42),2)+ROUND((ROUND(((AE42-((EU42*1.05)))*AV42*1),2)*BS42),2)) -> 0 | CS42: =ROUND((ROUND((AE42*AV42*1),2)*BS42),2) -> 0 | CT42: =ROUND((ROUND((AF42*AV42*1),2)*BA42),2) -> 0 | CU42: =AG42 -> 0 | CV42: =(AH42*AV42) -> 0 | CW42: =AI42 -> 0 | CX42: =AJ42 -> 0 | CY42: =S42*(BZ42/100) -> 0 | CZ42: =S42*(CA42/100) -> 0 | DB42: 9 | DE42: *1,05 | DF42: *1,05 | DG42: *1,05 | DI42: *1,05 | DJ42: *1,05 | DN42: 0 | DO42: 0 | DP42: 1 | DQ42: 1 | DU42: 1010 | DV42: шт. | DW42: шт. | DX42: 1 | EE42: 51697656 | EF42: 200 | EG42: Материалы строительные | EH42: 0 | EJ42: 1 | EK42: 1617 | EL42: ТСН-2001.1 Материалы строительные | EM42: ТСН-2001.1-1 | EO42: Поправка: О.П. п.3.4.30.г | EQ42: 131072 | ER42: 3.9 | ES42: 3.9 | ET42: 0 | EU42: 0 | EV42: 0 | EW42: 0 | EX42: 0 | EY42: 0 | FQ42: 0 | FR42: 0 | FS42: 0 | FX42: 0 | FY42: 0 | GD42: 0 | GF42: 1553567620 | GG42: 2 | GH42: 1 | GI42: 2 | GJ42: 0 | GK42: =ROUND(R42*(R12)/100,2) -> 0 | GL42: =ROUND(IF(AND(BH42=3,BI42=3,FS42<>0),P42,0),2) -> 0 | GM42: =ROUND(O42+X42+Y42+GK42,2)+GX42 -> 217.31 | GN42: =IF(OR(BI42=0,BI42=1),GM42-GX42,0) -> 217.31 | GO42: =IF(BI42=2,GM42-GX42,0) -> 0 | GP42: =IF(BI42=4,GM42-GX42,0) -> 0 | GR42: 0 | GS42: 3 | GT42: 0 | GV42: =ROUND((GT42),6) -> 0 | GW42: 1 | GX42: =ROUND(HC42*I42,2) -> 0 | HA42: 0 | HB42: 0 | HC42: =GV42*GW42 -> 0 | HS42: 0 | IK42: 0
A44: 51 | B44: =B28 -> 1 | C44: =A28 -> 5 | D44: =ROW(A28) -> 28 | F44: =IF(F28<>"",F28,"") -> Новый подраздел | G44: =IF(G28<>"",G28,"") -> Строительные работы | H44: 0 | O44: =ROUND(AB44,2) -> 6530938.2 | P44: =ROUND(AC44,2) -> 2740359.9 | Q44: =ROUND(AD44,2) -> 3552687.1 | R44: =ROUND(AE44,2) -> 406750.74 | S44: =ROUND(AF44,2) -> 237891.23 | T44: =ROUND(AG44,2) -> 0 | U44: =AH44 -> 501.77593 | V44: =AI44 -> 0 | W44: =ROUND(AJ44,2) -> 0 | X44: =ROUND(AK44,2) -> 278973.26 | Y44: =ROUND(AL44,2) -> 132043.5 | AB44: =ROUND(SUMIF(AA32:AA42,"=57737055",O32:O42),2) -> 6530938.2 | AC44: =ROUND(SUMIF(AA32:AA42,"=57737055",P32:P42),2) -> 2740359.9 | AD44: =ROUND(SUMIF(AA32:AA42,"=57737055",Q32:Q42),2) -> 3552687.1 | AE44: =ROUND(SUMIF(AA32:AA42,"=57737055",R32:R42),2) -> 406750.74 | AF44: =ROUND(SUMIF(AA32:AA42,"=57737055",S32:S42),2) -> 237891.23 | AG44: =ROUND(SUMIF(AA32:AA42,"=57737055",T32:T42),2) -> 0 | AH44: =SUMIF(AA32:AA42,"=57737055",U32:U42) -> 501.77593 | AI44: =SUMIF(AA32:AA42,"=57737055",V32:V42) -> 0 | AJ44: =ROUND(SUMIF(AA32:AA42,"=57737055",W32:W42),2) -> 0 | AK44: =ROUND(SUMIF(AA32:AA42,"=57737055",X32:X42),2) -> 278973.26 | AL44: =ROUND(SUMIF(AA32:AA42,"=57737055",Y32:Y42),2) -> 132043.5 | AO44: =ROUND(BX44,2) -> 0 | AP44: =ROUND(BY44,2) -> 0 | AQ44: =ROUND(BZ44,2) -> 0 | AR44: =ROUND(CA44,2) -> 7592756.1 | AS44: =ROUND(CB44,2) -> 7591866.6 | AT44: =ROUND(CC44,2) -> 889.54 | AU44: =ROUND(CD44,2) -> 0 | AV44: =ROUND(CE44,2) -> 2740359.9 | ... BD44: =ROUND(CM44,2) -> 0 | BX44: =ROUND(SUMIF(AA32:AA42,"=57737055",FQ32:FQ42),2) -> 0 | BY44: =ROUND(SUMIF(AA32:AA42,"=57737055",FR32:FR42),2) -> 0 | BZ44: =ROUND(SUMIF(AA32:AA42,"=57737055",GL32:GL42),2) -> 0 | CA44: =ROUND(SUMIF(AA32:AA42,"=57737055",GM32:GM42),2) -> 7592756.1 | CB44: =ROUND(SUMIF(AA32:AA42,"=57737055",GN32:GN42),2) -> 7591866.6 | CC44: =ROUND(SUMIF(AA32:AA42,"=57737055",GO32:GO42),2) -> 889.54 | CD44: =ROUND(SUMIF(AA32:AA42,"=57737055",GP32:GP42),2) -> 0 | CE44: =AC44-BX44 -> 2740359.9 | CF44: =AC44-BY44 -> 2740359.9 | CG44: =BX44-BZ44 -> 0 | CH44: =AC44-BX44-BY44+BZ44 -> 2740359.9 | CI44: =BY44-BZ44 -> 0 | CJ44: =ROUND(SUMIF(AA32:AA42,"=57737055",GX32:GX42),2) -> 0 | CK44: =ROUND(SUMIF(AA32:AA42,"=57737055",GY32:GY42),2) -> 0 | CL44: =ROUND(SUMIF(AA32:AA42,"=57737055",GZ32:GZ42),2) -> 0 | CM44: =ROUND(SUMIF(AA32:AA42,"=57737055",HD32:HD42),2) -> 0 | GX44: 0
A46: 50 | B46: 0 | C46: 0 | D46: 1 | E46: 201 | F46: =ROUND(Source!O44,O46) -> 6530938.2 | G46: ПЗ | H46: Прямые затраты | K46: 201 | L46: 1 | M46: 3 | O46: 2 | W46: 6530938.2 | X46: 1 | Y46: 6530938.2
A47: 50 | B47: 0 | C47: 0 | D47: 1 | E47: 202 | F47: =ROUND(Source!P44,O47) -> 2740359.9 | G47: СтМатОб | H47: Стоимость материальных ресурсов (всего) | K47: 202 | L47: 2 | M47: 3 | O47: 2 | W47: 2740359.9 | X47: 1 | Y47: 2740359.9
A48: 50 | B48: 0 | C48: 0 | D48: 1 | E48: 222 | F48: =ROUND(Source!AO44,O48) -> 0 | G48: СтМатОбЗак | H48: Стоимость материалов и оборудования заказчика | K48: 222 | L48: 3 | M48: 3 | O48: 2 | W48: 0 | X48: 1 | Y48: 0
A49: 50 | B49: 0 | C49: 0 | D49: 1 | E49: 225 | F49: =ROUND(Source!AV44,O49) -> 2740359.9 | G49: СтМатОбПод | H49: Стоимость материалов и оборудования подрядчика | K49: 225 | L49: 4 | M49: 3 | O49: 2 | W49: 2740359.9 | X49: 1 | Y49: 2740359.9
A50: 50 | B50: 0 | C50: 0 | D50: 1 | E50: 226 | F50: =ROUND(Source!AW44,O50) -> 2740359.9 | G50: СтМат | H50: Стоимость материалов (всего) | K50: 226 | L50: 5 | M50: 3 | O50: 2 | W50: 2740359.9 | X50: 1 | Y50: 2740359.9
A51: 50 | B51: 0 | C51: 0 | D51: 1 | E51: 227 | F51: =ROUND(Source!AX44,O51) -> 0 | G51: СтМатЗак | H51: Стоимость материалов заказчика | K51: 227 | L51: 6 | M51: 3 | O51: 2 | W51: 0 | X51: 1 | Y51: 0
A52: 50 | B52: 0 | C52: 0 | D52: 1 | E52: 228 | F52: =ROUND(Source!AY44,O52) -> 2740359.9 | G52: СтМатПод | H52: Стоимость материалов подрядчика | K52: 228 | L52: 7 | M52: 3 | O52: 2 | W52: 2740359.9 | X52: 1 | Y52: 2740359.9
A53: 50 | B53: 0 | C53: 0 | D53: 1 | E53: 216 | F53: =ROUND(Source!AP44,O53) -> 0 | G53: Оборуд | H53: Стоимость оборудования (всего) | K53: 216 | L53: 8 | M53: 3 | O53: 2 | W53: 0 | X53: 1 | Y53: 0
A54: 50 | B54: 0 | C54: 0 | D54: 1 | E54: 223 | F54: =ROUND(Source!AQ44,O54) -> 0 | G54: ОборудЗак | H54: Стоимость оборудования заказчика | K54: 223 | L54: 9 | M54: 3 | O54: 2 | W54: 0 | X54: 1 | Y54: 0
A55: 50 | B55: 0 | C55: 0 | D55: 1 | E55: 229 | F55: =ROUND(Source!AZ44,O55) -> 0 | G55: ОборудПод | H55: Стоимость оборудования подрядчика | K55: 229 | L55: 10 | M55: 3 | O55: 2 | W55: 0 | X55: 1 | Y55: 0
A56: 50 | B56: 0 | C56: 0 | D56: 1 | E56: 203 | F56: =ROUND(Source!Q44,O56) -> 3552687.1 | G56: ЭММ | H56: Эксплуатация машин | K56: 203 | L56: 11 | M56: 3 | O56: 2 | W56: 3552687.1 | X56: 1 | Y56: 3552687.1
A57: 50 | B57: 0 | C57: 0 | D57: 1 | E57: 231 | F57: =ROUND(Source!BB44,O57) -> 0 | G57: ЭММсНРиСП | H57: Эксплуатация машин по ТСН-2001.16 | K57: 231 | L57: 12 | M57: 3 | O57: 2 | W57: 0 | X57: 1 | Y57: 0
A58: 50 | B58: 0 | C58: 0 | D58: 1 | E58: 204 | F58: =ROUND(Source!R44,O58) -> 406750.74 | G58: ЗПМ | H58: ЗП машинистов | K58: 204 | L58: 13 | M58: 3 | O58: 2 | W58: 406750.74 | X58: 1 | Y58: 406750.74
A59: 50 | B59: 0 | C59: 0 | D59: 1 | E59: 205 | F59: =ROUND(Source!S44,O59) -> 237891.23 | G59: ОЗП | H59: Основная ЗП рабочих | K59: 205 | L59: 14 | M59: 3 | O59: 2 | W59: 237891.23 | X59: 1 | Y59: 237891.23
A60: 50 | B60: 0 | C60: 0 | D60: 1 | E60: 232 | F60: =ROUND(Source!BC44,O60) -> 0 | G60: ОЗПсНРиСП | H60: Основная ЗП рабочих по ТСН-2001.16 | K60: 232 | L60: 15 | M60: 3 | O60: 2 | W60: 0 | X60: 1 | Y60: 0
A61: 50 | B61: 0 | C61: 0 | D61: 1 | E61: 214 | F61: =ROUND(Source!AS44,O61) -> 7591866.6 | G61: Строит | H61: Строительные работы с НР и СП | K61: 214 | L61: 16 | M61: 3 | O61: 2 | W61: 7591866.6 | X61: 1 | Y61: 7591866.6
A62: 50 | B62: 0 | C62: 0 | D62: 1 | E62: 215 | F62: =ROUND(Source!AT44,O62) -> 889.54 | G62: Монтаж | H62: Монтажные работы с НР и СП | K62: 215 | L62: 17 | M62: 3 | O62: 2 | W62: 889.54 | X62: 1 | Y62: 889.54
A63: 50 | B63: 0 | C63: 0 | D63: 1 | E63: 217 | F63: =ROUND(Source!AU44,O63) -> 0 | G63: Прочие | H63: Прочие работы с НР и СП | K63: 217 | L63: 18 | M63: 3 | O63: 2 | W63: 0 | X63: 1 | Y63: 0
A64: 50 | B64: 0 | C64: 0 | D64: 1 | E64: 230 | F64: =ROUND(Source!BA44,O64) -> 0 | G64: ПрочиеЗатр | H64: Прочие затраты по ТСН-2001.16 | K64: 230 | L64: 19 | M64: 3 | O64: 2 | W64: 0 | X64: 1 | Y64: 0
A65: 50 | B65: 0 | C65: 0 | D65: 1 | E65: 206 | F65: =ROUND(Source!T44,O65) -> 0 | G65: ВозврМат | H65: Возврат материалов | K65: 206 | L65: 20 | M65: 3 | O65: 2 | W65: 0 | X65: 1 | Y65: 0
A66: 50 | B66: 0 | C66: 0 | D66: 1 | E66: 207 | F66: =Source!U44 -> 501.77593 | G66: ТрудСтр | H66: Трудозатраты строителей | K66: 207 | L66: 21 | M66: 3 | O66: -1 | W66: 501.77593 | X66: 1 | Y66: 501.77593
A67: 50 | B67: 0 | C67: 0 | D67: 1 | E67: 208 | F67: =Source!V44 -> 0 | G67: ТрудМаш | H67: Трудозатраты машинистов | K67: 208 | L67: 22 | M67: 3 | O67: -1 | W67: 0 | X67: 1 | Y67: 0
A68: 50 | B68: 0 | C68: 0 | D68: 1 | E68: 209 | F68: =ROUND(Source!W44,O68) -> 0 | G68: ТранспМат | H68: Транспорт материалов | K68: 209 | L68: 23 | M68: 3 | O68: 2 | W68: 0 | X68: 1 | Y68: 0
A69: 50 | B69: 0 | C69: 0 | D69: 1 | E69: 233 | F69: =ROUND(Source!BD44,O69) -> 0 | G69: Перевозка | H69: Перевозка грузов | K69: 233 | L69: 24 | M69: 3 | O69: 2 | W69: 0 | X69: 1 | Y69: 0
A70: 50 | B70: 0 | C70: 0 | D70: 1 | E70: 210 | F70: =ROUND(Source!X44,O70) -> 278973.26 | G70: НР | H70: Накладные расходы | K70: 210 | L70: 25 | M70: 3 | O70: 2 | W70: 278973.26 | X70: 1 | Y70: 278973.26
A71: 50 | B71: 0 | C71: 0 | D71: 1 | E71: 211 | F71: =ROUND(Source!Y44,O71) -> 132043.5 | G71: СмПриб | H71: Сметная прибыль | K71: 211 | L71: 26 | M71: 3 | O71: 2 | W71: 132043.5 | X71: 1 | Y71: 132043.5
A72: 50 | B72: 0 | C72: 0 | D72: 1 | E72: 224 | F72: =ROUND(Source!AR44,O72) -> 7592756.1 | G72: Всего | H72: Всего с НР и СП | K72: 224 | L72: 27 | M72: 3 | O72: 2 | W72: 7592756.1 | X72: 1 | Y72: 7592756.1
A74: 5 | B74: 1 | D74: =ROW(A84) -> 84 | F74: Новый подраздел | G74: Монтажные работы | I74: 0 | K74: 0 | S74: 0 | V74: 0 | BX74: 0 | CJ74: 0
A76: 52 | B76: =B84 -> 1 | C76: =C84 -> 5 | D76: =D84 -> 74 | E76: =E84 -> 0 | F76: =F84 -> Новый подраздел | G76: =G84 -> Монтажные работы | O76: =O84 -> 1001912.2 | P76: =P84 -> 886369.1 | Q76: =Q84 -> 9829.94 | R76: =R84 -> 3469.29 | S76: =S84 -> 105713.11 | T76: =T84 -> 0 | U76: =U84 -> 247.02435 | V76: =V84 -> 0 | ... GX76: =GX84 -> 0
A78: 17 | B78: 1 | C78: =ROW(SmtRes!A37) -> 37 | D78: =ROW(EtalonRes!A39) -> 39 | E78: 10 | F78: 4.8-80-2 | G78: Прокладка кабеля напряжением до 35 кВ в проложенных трубах, блоках и коробах, при массе 1 м до 2 кг | H78: 100 М КАБЕЛЯ | I78: =ROUND(1318.05/100,9) -> 13.1805 | J78: 0 | K78: =ROUND(1318.05/100,9) -> 13.1805 | O78: =ROUND(CP78,2) -> 121696.2 | P78: =ROUND((ROUND((AC78*AW78*I78),2)*BC78),2) -> 13109.73 | Q78: =(ROUND((ROUND((((ET78*1.05))*AV78*I78),2)*BB78),2)+ROUND((ROUND(((AE78-((EU78*1.05)))*AV78*I78),2)*BS78),2)) -> 9387.47 | R78: =ROUND((ROUND((AE78*AV78*I78),2)*BS78),2) -> 3281.9 | S78: =ROUND((ROUND((AF78*AV78*I78),2)*BA78),2) -> 99199 | T78: =ROUND(CU78*I78,2) -> 0 | U78: =CV78*I78 -> 233.31502 | V78: =CW78*I78 -> 0 | W78: =ROUND(CX78*I78,2) -> 0 | X78: =ROUND(CY78,2) -> 91263.08 | Y78: =ROUND(CZ78,2) -> 42655.57 | AA78: 57737055 | AB78: =ROUND((AC78+AD78+AF78),6) -> 312.773 | AC78: =ROUND((ES78),6) -> 52.94 | AD78: =ROUND(((((ET78*1.05))-((EU78*1.05)))+AE78),6) -> 55.44 | AE78: =ROUND(((EU78*1.05)),6) -> 6.762 | AF78: =ROUND(((EV78*1.05)),6) -> 204.393 | AG78: =ROUND((AP78),6) -> 0 | AH78: =((EW78*1.05)) -> 16.59 | AI78: =((EX78*1.05)) -> 0 | AJ78: =(AS78) -> 0 | AK78: 300.4 | AL78: 52.94 | AM78: 52.8 | AN78: 6.44 | AO78: 194.66 | AP78: 0 | AQ78: 15.8 | AR78: 0 | AS78: 0 | AT78: 92 | AU78: 43 | AV78: 1.067 | AW78: 1.081 | AZ78: 1 | BA78: 34.51 | BB78: 12.04 | BC78: 17.38 | BH78: 0 | BI78: 2 | BJ78: ТСН-2001.4 Доп. 69, Сб. 8, т. 80, поз. 2 | BM78: 318 | BN78: 0 | BO78: 4.8-80-2 | BP78: 1 | BQ78: 40 | BR78: 0 | BS78: 34.51 | BT78: 1 | BU78: 1 | BV78: 1 | BW78: 1 | BX78: 1 | BZ78: 92 | CA78: 43 | CE78: 30 | CF78: 0 | CG78: 0 | CM78: 0 | CN78: Поправка: О.П. п.3.4.30.г Наименование: В отношении объектов, реализуемых с привлечением средств бюджета города Москвы, затраты, учитывающие усложненные условия производства работ (стесненность, сложность складирования и транспортной логистики, наличие в зоне производства работ действующего технологического оборудования или движения технологического транспорта и т.п.), определяются заказчиком в задании на проектирование при составлении локальных сметных расчетов (смет): для объектов города Москвы, расположенных за пределами Московской кольцевой автомобильной дороги | CO78: 0 | CP78: =(P78+Q78+S78) -> 121696.2 | CQ78: =ROUND((ROUND((AC78*AW78*1),2)*BC78),2) -> 994.66 | CR78: =(ROUND((ROUND((((ET78*1.05))*AV78*1),2)*BB78),2)+ROUND((ROUND(((AE78-((EU78*1.05)))*AV78*1),2)*BS78),2)) -> 712.17 | CS78: =ROUND((ROUND((AE78*AV78*1),2)*BS78),2) -> 249.16 | CT78: =ROUND((ROUND((AF78*AV78*1),2)*BA78),2) -> 7526.29 | CU78: =AG78 -> 0 | CV78: =(AH78*AV78) -> 17.70153 | CW78: =AI78 -> 0 | CX78: =AJ78 -> 0 | CY78: =S78*(BZ78/100) -> 91263.08 | CZ78: =S78*(CA78/100) -> 42655.57 | DB78: 10 | DE78: *1,05 | DF78: *1,05 | DG78: *1,05 | DI78: *1,05 | DJ78: *1,05 | DN78: 112 | DO78: 70 | DP78: 1.067 | DQ78: 1.081 | DU78: 1013 | DV78: 100 М КАБЕЛЯ | DW78: 100 М КАБЕЛЯ | DX78: 1 | EE78: 51696357 | EF78: 40 | EG78: Монтаж оборудования | EH78: 0 | EJ78: 2 | EK78: 318 | EL78: ТСН-2001.4-8. 8-73...8-80 | EM78: ТСН-2001.4-8-3 | EO78: Поправка: О.П. п.3.4.30.г | EQ78: 131072 | ER78: 300.4 | ES78: 52.94 | ET78: 52.8 | EU78: 6.44 | EV78: 194.66 | EW78: 15.8 | EX78: 0 | EY78: 0 | FQ78: 0 | FR78: 0 | FS78: 2 | FX78: 112 | FY78: 70 | GD78: 0 | GF78: 2013852604 | GG78: 2 | GH78: 1 | GI78: 2 | GJ78: 0 | GK78: =ROUND(R78*(R12)/100,2) -> 5251.04 | GL78: =ROUND(IF(AND(BH78=3,BI78=3,FS78<>0),P78,0),2) -> 0 | GM78: =ROUND(O78+X78+Y78+GK78,2)+GX78 -> 260865.89 | GN78: =IF(OR(BI78=0,BI78=1),GM78-GX78,0) -> 0 | GO78: =IF(BI78=2,GM78-GX78,0) -> 260865.89 | GP78: =IF(BI78=4,GM78-GX78,0) -> 0 | GR78: 0 | GS78: 3 | GT78: 0 | GV78: =ROUND((GT78),6) -> 0 | GW78: 1 | GX78: =ROUND(HC78*I78,2) -> 0 | HA78: 0 | HB78: 0 | HC78: =GV78*GW78 -> 0 | HS78: 0 | IK78: 0
A79: 18 | B79: 1 | C79: 37 | E79: 10,1 | F79: 1.23-7-391 | G79: Кабель силовой с алюминиевой многопроволочной жилой, с изоляцией из сшитого полиэтилена, с медным экраном, с водоблокирующей лентой под металлическим экраном, марка АПвПуг, напряжение 10000 В, число жил, сечение жилы, экран 1х120/35 мм2 | H79: км | I79: =I78*J79 -> 1.344411 | J79: 0.102 | K79: 0.102 | O79: =ROUND(CP79,2) -> 870348.66 | P79: =ROUND((ROUND((AC79*AW79*I79),2)*BC79),2) -> 870348.66 | Q79: =(ROUND((ROUND(((ET79)*AV79*I79),2)*BB79),2)+ROUND((ROUND(((AE79-(EU79))*AV79*I79),2)*BS79),2)) -> 0 | R79: =ROUND((ROUND((AE79*AV79*I79),2)*BS79),2) -> 0 | S79: =ROUND((ROUND((AF79*AV79*I79),2)*BA79),2) -> 0 | T79: =ROUND(CU79*I79,2) -> 0 | U79: =CV79*I79 -> 0 | V79: =CW79*I79 -> 0 | W79: =ROUND(CX79*I79,2) -> 0 | X79: =ROUND(CY79,2) -> 0 | Y79: =ROUND(CZ79,2) -> 0 | AA79: 57737055 | AB79: =ROUND((AC79+AD79+AF79),6) -> 81534.37 | AC79: =ROUND((ES79),6) -> 81534.37 | AD79: =ROUND((((ET79)-(EU79))+AE79),6) -> 0 | AE79: =ROUND((EU79),6) -> 0 | AF79: =ROUND((EV79),6) -> 0 | AG79: =ROUND((AP79),6) -> 0 | AH79: =(EW79) -> 0 | AI79: =(EX79) -> 0 | AJ79: =(AS79) -> 0 | AK79: 81534.37 | AL79: 81534.37 | AM79: 0 | AN79: 0 | AO79: 0 | AP79: 0 | AQ79: 0 | AR79: 0 | AS79: 0 | AT79: 0 | AU79: 0 | AV79: 1 | AW79: 1 | AZ79: 1 | BA79: 1 | BB79: 1 | BC79: 7.94 | BH79: 3 | BI79: 2 | BJ79: ТСН-2001.1 Доп. 73, Р. 23, о. 7, поз. 391 | BM79: 318 | BN79: 0 | BO79: 1.23-7-391 | BP79: 1 | BQ79: 40 | BR79: 0 | BS79: 1 | BT79: 1 | BU79: 1 | BV79: 1 | BW79: 1 | BX79: 1 | BZ79: 0 | CA79: 0 | CE79: 30 | CF79: 0 | CG79: 0 | CM79: 0 | CO79: 0 | CP79: =(P79+Q79+S79) -> 870348.66 | CQ79: =ROUND((ROUND((AC79*AW79*1),2)*BC79),2) -> 647382.9 | CR79: =(ROUND((ROUND(((ET79)*AV79*1),2)*BB79),2)+ROUND((ROUND(((AE79-(EU79))*AV79*1),2)*BS79),2)) -> 0 | CS79: =ROUND((ROUND((AE79*AV79*1),2)*BS79),2) -> 0 | CT79: =ROUND((ROUND((AF79*AV79*1),2)*BA79),2) -> 0 | CU79: =AG79 -> 0 | CV79: =(AH79*AV79) -> 0 | CW79: =AI79 -> 0 | CX79: =AJ79 -> 0 | CY79: =S79*(BZ79/100) -> 0 | CZ79: =S79*(CA79/100) -> 0 | DN79: 112 | DO79: 70 | DP79: 1.067 | DQ79: 1 | DU79: 1003 | DV79: км | DW79: км | DX79: 1000 | EE79: 51696357 | EF79: 40 | EG79: Монтаж оборудования | EH79: 0 | EJ79: 2 | EK79: 318 | EL79: ТСН-2001.4-8. 8-73...8-80 | EM79: ТСН-2001.4-8-3 | EQ79: 0 | ER79: 81534.37 | ES79: 81534.37 | ET79: 0 | EU79: 0 | EV79: 0 | EW79: 0 | EX79: 0 | FQ79: 0 | FR79: 0 | FS79: 0 | FX79: 112 | FY79: 70 | GD79: 0 | GF79: 61579043 | GG79: 2 | GH79: 1 | GI79: 2 | GJ79: 0 | GK79: =ROUND(R79*(R12)/100,2) -> 0 | GL79: =ROUND(IF(AND(BH79=3,BI79=3,FS79<>0),P79,0),2) -> 0 | GM79: =ROUND(O79+X79+Y79+GK79,2)+GX79 -> 870348.66 | GN79: =IF(OR(BI79=0,BI79=1),GM79-GX79,0) -> 0 | GO79: =IF(BI79=2,GM79-GX79,0) -> 870348.66 | GP79: =IF(BI79=4,GM79-GX79,0) -> 0 | GR79: 0 | GS79: 3 | GT79: 0 | GV79: =ROUND((GT79),6) -> 0 | GW79: 1 | GX79: =ROUND(HC79*I79,2) -> 0 | HA79: 0 | HB79: 0 | HC79: =GV79*GW79 -> 0 | HS79: 0 | IK79: 0
A80: 17 | B80: 1 | E80: 11 | F80: 1.23-7-391 | G80: Кабель силовой с алюминиевой многопроволочной жилой, с изоляцией из сшитого полиэтилена, с медным экраном, с водоблокирующей лентой под металлическим экраном, марка АПвПуг, напряжение 10000 В, число жил, сечение жилы, экран 1х120/35 мм2 | H80: км | I80: 0 | J80: 0 | K80: 0 | O80: =ROUND(CP80,2) -> 0 | P80: =ROUND((ROUND((AC80*AW80*I80),2)*BC80),2) -> 0 | Q80: =(ROUND((ROUND((((ET80*1.05))*AV80*I80),2)*BB80),2)+ROUND((ROUND(((AE80-((EU80*1.05)))*AV80*I80),2)*BS80),2)) -> 0 | R80: =ROUND((ROUND((AE80*AV80*I80),2)*BS80),2) -> 0 | S80: =ROUND((ROUND((AF80*AV80*I80),2)*BA80),2) -> 0 | T80: =ROUND(CU80*I80,2) -> 0 | U80: =CV80*I80 -> 0 | V80: =CW80*I80 -> 0 | W80: =ROUND(CX80*I80,2) -> 0 | X80: =ROUND(CY80,2) -> 0 | Y80: =ROUND(CZ80,2) -> 0 | AA80: 57737055 | AB80: =ROUND((AC80+AD80+AF80),6) -> 81534.37 | AC80: =ROUND((ES80),6) -> 81534.37 | AD80: =ROUND(((((ET80*1.05))-((EU80*1.05)))+AE80),6) -> 0 | AE80: =ROUND(((EU80*1.05)),6) -> 0 | AF80: =ROUND(((EV80*1.05)),6) -> 0 | AG80: =ROUND((AP80),6) -> 0 | AH80: =((EW80*1.05)) -> 0 | AI80: =((EX80*1.05)) -> 0 | AJ80: =(AS80) -> 0 | AK80: 81534.37 | AL80: 81534.37 | AM80: 0 | AN80: 0 | AO80: 0 | AP80: 0 | AQ80: 0 | AR80: 0 | AS80: 0 | AT80: 0 | AU80: 0 | AV80: 1 | AW80: 1 | AZ80: 1 | BA80: 1 | BB80: 1 | BC80: 7.94 | BH80: 3 | BI80: 2 | BJ80: ТСН-2001.1 Доп. 73, Р. 23, о. 7, поз. 391 | BM80: 1618 | BN80: 0 | BO80: 1.23-7-391 | BP80: 1 | BQ80: 201 | BR80: 0 | BS80: 1 | BT80: 1 | BU80: 1 | BV80: 1 | BW80: 1 | BX80: 1 | BZ80: 0 | CA80: 0 | CE80: 30 | CF80: 0 | CG80: 0 | CM80: 0 | CN80: Поправка: О.П. п.3.4.30.г Наименование: В отношении объектов, реализуемых с привлечением средств бюджета города Москвы, затраты, учитывающие усложненные условия производства работ (стесненность, сложность складирования и транспортной логистики, наличие в зоне производства работ действующего технологического оборудования или движения технологического транспорта и т.п.), определяются заказчиком в задании на проектирование при составлении локальных сметных расчетов (смет): для объектов города Москвы, расположенных за пределами Московской кольцевой автомобильной дороги | CO80: 0 | CP80: =(P80+Q80+S80) -> 0 | CQ80: =ROUND((ROUND((AC80*AW80*1),2)*BC80),2) -> 647382.9 | CR80: =(ROUND((ROUND((((ET80*1.05))*AV80*1),2)*BB80),2)+ROUND((ROUND(((AE80-((EU80*1.05)))*AV80*1),2)*BS80),2)) -> 0 | CS80: =ROUND((ROUND((AE80*AV80*1),2)*BS80),2) -> 0 | CT80: =ROUND((ROUND((AF80*AV80*1),2)*BA80),2) -> 0 | CU80: =AG80 -> 0 | CV80: =(AH80*AV80) -> 0 | CW80: =AI80 -> 0 | CX80: =AJ80 -> 0 | CY80: =S80*(BZ80/100) -> 0 | CZ80: =S80*(CA80/100) -> 0 | DB80: 11 | DE80: *1,05 | DF80: *1,05 | DG80: *1,05 | DI80: *1,05 | DJ80: *1,05 | DN80: 0 | DO80: 0 | DP80: 1 | DQ80: 1 | DU80: 1003 | DV80: км | DW80: км | DX80: 1000 | EE80: 51697657 | EF80: 201 | EG80: Материалы монтажные | EH80: 0 | EJ80: 2 | EK80: 1618 | EL80: ТСН-2001.1 Материалы монтажные | EM80: ТСН-2001.1-2 | EO80: Поправка: О.П. п.3.4.30.г | EQ80: 131072 | ER80: 81534.37 | ES80: 81534.37 | ET80: 0 | EU80: 0 | EV80: 0 | EW80: 0 | EX80: 0 | EY80: 0 | FQ80: 0 | FR80: 0 | FS80: 0 | FX80: 0 | FY80: 0 | GD80: 0 | GF80: 61579043 | GG80: 2 | GH80: 1 | GI80: 2 | GJ80: 0 | GK80: =ROUND(R80*(R12)/100,2) -> 0 | GL80: =ROUND(IF(AND(BH80=3,BI80=3,FS80<>0),P80,0),2) -> 0 | GM80: =ROUND(O80+X80+Y80+GK80,2)+GX80 -> 0 | GN80: =IF(OR(BI80=0,BI80=1),GM80-GX80,0) -> 0 | GO80: =IF(BI80=2,GM80-GX80,0) -> 0 | GP80: =IF(BI80=4,GM80-GX80,0) -> 0 | GR80: 0 | GS80: 3 | GT80: 0 | GV80: =ROUND((GT80),6) -> 0 | GW80: 1 | GX80: =ROUND(HC80*I80,2) -> 0 | HA80: 0 | HB80: 0 | HC80: =GV80*GW80 -> 0 | HS80: 0 | IK80: 0
A81: 17 | B81: 1 | D81: =ROW(EtalonRes!A48) -> 48 | E81: 12 | F81: 4.8-301-1 | G81: Монтаж уплотнителя кабельного прохода термоусаживаемого | H81: 100 компл. | I81: =ROUND(8/100,9) -> 0.08 | J81: 0 | K81: =ROUND(8/100,9) -> 0.08 | O81: =ROUND(CP81,2) -> 7274.02 | P81: =ROUND((ROUND((AC81*AW81*I81),2)*BC81),2) -> 317.44 | Q81: =(ROUND((ROUND((((ET81*1.05))*AV81*I81),2)*BB81),2)+ROUND((ROUND(((AE81-((EU81*1.05)))*AV81*I81),2)*BS81),2)) -> 442.47 | R81: =ROUND((ROUND((AE81*AV81*I81),2)*BS81),2) -> 187.39 | S81: =ROUND((ROUND((AF81*AV81*I81),2)*BA81),2) -> 6514.11 | T81: =ROUND(CU81*I81,2) -> 0 | U81: =CV81*I81 -> 13.709334 | V81: =CW81*I81 -> 0 | W81: =ROUND(CX81*I81,2) -> 0 | X81: =ROUND(CY81,2) -> 5992.98 | Y81: =ROUND(CZ81,2) -> 2801.07 | AA81: 57737055 | AB81: =ROUND((AC81+AD81+AF81),6) -> 3540.525 | AC81: =ROUND((ES81),6) -> 535.53 | AD81: =ROUND(((((ET81*1.05))-((EU81*1.05)))+AE81),6) -> 751.4535 | AE81: =ROUND(((EU81*1.05)),6) -> 64.848 | AF81: =ROUND(((EV81*1.05)),6) -> 2253.5415 | AG81: =ROUND((AP81),6) -> 0 | AH81: =((EW81*1.05)) -> 163.674 | AI81: =((EX81*1.05)) -> 0 | AJ81: =(AS81) -> 0 | AK81: 3397.43 | AL81: 535.53 | AM81: 715.67 | AN81: 61.76 | AO81: 2146.23 | AP81: 0 | AQ81: 155.88 | AR81: 0 | AS81: 0 | AT81: 92 | AU81: 43 | AV81: 1.047 | AW81: 1 | AZ81: 1 | BA81: 34.51 | BB81: 7.03 | BC81: 7.41 | BH81: 0 | BI81: 2 | BJ81: ТСН-2001.4 Доп. 68, Сб. 8, т. 301, поз. 1 | BM81: 1726 | BN81: 0 | BO81: 4.8-301-1 | BP81: 1 | BQ81: 40 | BR81: 0 | BS81: 34.51 | BT81: 1 | BU81: 1 | BV81: 1 | BW81: 1 | BX81: 1 | BZ81: 92 | CA81: 43 | CE81: 30 | CF81: 0 | CG81: 0 | CM81: 0 | CN81: Поправка: О.П. п.3.4.30.г Наименование: В отношении объектов, реализуемых с привлечением средств бюджета города Москвы, затраты, учитывающие усложненные условия производства работ (стесненность, сложность складирования и транспортной логистики, наличие в зоне производства работ действующего технологического оборудования или движения технологического транспорта и т.п.), определяются заказчиком в задании на проектирование при составлении локальных сметных расчетов (смет): для объектов города Москвы, расположенных за пределами Московской кольцевой автомобильной дороги | CO81: 0 | CP81: =(P81+Q81+S81) -> 7274.02 | CQ81: =ROUND((ROUND((AC81*AW81*1),2)*BC81),2) -> 3968.28 | CR81: =(ROUND((ROUND((((ET81*1.05))*AV81*1),2)*BB81),2)+ROUND((ROUND(((AE81-((EU81*1.05)))*AV81*1),2)*BS81),2)) -> 5530.99 | CS81: =ROUND((ROUND((AE81*AV81*1),2)*BS81),2) -> 2343.23 | CT81: =ROUND((ROUND((AF81*AV81*1),2)*BA81),2) -> 81424.96 | CU81: =AG81 -> 0 | CV81: =(AH81*AV81) -> 171.36668 | CW81: =AI81 -> 0 | CX81: =AJ81 -> 0 | CY81: =S81*(BZ81/100) -> 5992.9812 | CZ81: =S81*(CA81/100) -> 2801.0673 | DB81: 12 | DE81: *1,05 | DF81: *1,05 | DG81: *1,05 | DI81: *1,05 | DJ81: *1,05 | DN81: 112 | DO81: 70 | DP81: 1.047 | DQ81: 1 | DU81: 1013 | DV81: 100 компл. | DW81: 100 компл. | DX81: 1 | EE81: 51697765 | EF81: 40 | EG81: Монтаж оборудования | EH81: 0 | EJ81: 2 | EK81: 1726 | EL81: ТСН-2001.4-8. 8-301…8-309 (доп. 30) | EM81: ТСН-2001.4-8-34 | EO81: Поправка: О.П. п.3.4.30.г | EQ81: 131072 | ER81: 3397.43 | ES81: 535.53 | ET81: 715.67 | EU81: 61.76 | EV81: 2146.23 | EW81: 155.88 | EX81: 0 | EY81: 0 | FQ81: 0 | FR81: 0 | FS81: 0 | FX81: 112 | FY81: 70 | GD81: 0 | GF81: 957162054 | GG81: 2 | GH81: 1 | GI81: 2 | GJ81: 0 | GK81: =ROUND(R81*(R12)/100,2) -> 299.82 | GL81: =ROUND(IF(AND(BH81=3,BI81=3,FS81<>0),P81,0),2) -> 0 | GM81: =ROUND(O81+X81+Y81+GK81,2)+GX81 -> 16367.89 | GN81: =IF(OR(BI81=0,BI81=1),GM81-GX81,0) -> 0 | GO81: =IF(BI81=2,GM81-GX81,0) -> 16367.89 | GP81: =IF(BI81=4,GM81-GX81,0) -> 0 | GR81: 0 | GS81: 3 | GT81: 0 | GV81: =ROUND((GT81),6) -> 0 | GW81: 1 | GX81: =ROUND(HC81*I81,2) -> 0 | HA81: 0 | HB81: 0 | HC81: =GV81*GW81 -> 0 | HS81: 0 | IK81: 0
A82: 17 | B82: 1 | E82: 13 | F82: 1.21-5-1069 | G82: Уплотнитель кабельных проходов, типа УКПТ | H82: КОМПЛЕКТ | I82: 8 | J82: 0 | K82: 8 | O82: =ROUND(CP82,2) -> 2593.27 | P82: =ROUND((ROUND((AC82*AW82*I82),2)*BC82),2) -> 2593.27 | Q82: =(ROUND((ROUND((((ET82*1.05))*AV82*I82),2)*BB82),2)+ROUND((ROUND(((AE82-((EU82*1.05)))*AV82*I82),2)*BS82),2)) -> 0 | R82: =ROUND((ROUND((AE82*AV82*I82),2)*BS82),2) -> 0 | S82: =ROUND((ROUND((AF82*AV82*I82),2)*BA82),2) -> 0 | T82: =ROUND(CU82*I82,2) -> 0 | U82: =CV82*I82 -> 0 | V82: =CW82*I82 -> 0 | W82: =ROUND(CX82*I82,2) -> 0 | X82: =ROUND(CY82,2) -> 0 | Y82: =ROUND(CZ82,2) -> 0 | AA82: 57737055 | AB82: =ROUND((AC82+AD82+AF82),6) -> 153.63 | AC82: =ROUND((ES82),6) -> 153.63 | AD82: =ROUND(((((ET82*1.05))-((EU82*1.05)))+AE82),6) -> 0 | AE82: =ROUND(((EU82*1.05)),6) -> 0 | AF82: =ROUND(((EV82*1.05)),6) -> 0 | AG82: =ROUND((AP82),6) -> 0 | AH82: =((EW82*1.05)) -> 0 | AI82: =((EX82*1.05)) -> 0 | AJ82: =(AS82) -> 0 | AK82: 153.63 | AL82: 153.63 | AM82: 0 | AN82: 0 | AO82: 0 | AP82: 0 | AQ82: 0 | AR82: 0 | AS82: 0 | AT82: 0 | AU82: 0 | AV82: 1 | AW82: 1 | AZ82: 1 | BA82: 1 | BB82: 1 | BC82: 2.11 | BH82: 3 | BI82: 2 | BJ82: ТСН-2001.1 Доп. 73, Р. 21, о. 5, поз. 1069 | BM82: 1618 | BN82: 0 | BO82: 1.21-5-1069 | BP82: 1 | BQ82: 201 | BR82: 0 | BS82: 1 | BT82: 1 | BU82: 1 | BV82: 1 | BW82: 1 | BX82: 1 | BZ82: 0 | CA82: 0 | CE82: 30 | CF82: 0 | CG82: 0 | CM82: 0 | CN82: Поправка: О.П. п.3.4.30.г Наименование: В отношении объектов, реализуемых с привлечением средств бюджета города Москвы, затраты, учитывающие усложненные условия производства работ (стесненность, сложность складирования и транспортной логистики, наличие в зоне производства работ действующего технологического оборудования или движения технологического транспорта и т.п.), определяются заказчиком в задании на проектирование при составлении локальных сметных расчетов (смет): для объектов города Москвы, расположенных за пределами Московской кольцевой автомобильной дороги | CO82: 0 | CP82: =(P82+Q82+S82) -> 2593.27 | CQ82: =ROUND((ROUND((AC82*AW82*1),2)*BC82),2) -> 324.16 | CR82: =(ROUND((ROUND((((ET82*1.05))*AV82*1),2)*BB82),2)+ROUND((ROUND(((AE82-((EU82*1.05)))*AV82*1),2)*BS82),2)) -> 0 | CS82: =ROUND((ROUND((AE82*AV82*1),2)*BS82),2) -> 0 | CT82: =ROUND((ROUND((AF82*AV82*1),2)*BA82),2) -> 0 | CU82: =AG82 -> 0 | CV82: =(AH82*AV82) -> 0 | CW82: =AI82 -> 0 | CX82: =AJ82 -> 0 | CY82: =S82*(BZ82/100) -> 0 | CZ82: =S82*(CA82/100) -> 0 | DB82: 13 | DE82: *1,05 | DF82: *1,05 | DG82: *1,05 | DI82: *1,05 | DJ82: *1,05 | DN82: 0 | DO82: 0 | DP82: 1 | DQ82: 1 | DU82: 1013 | DV82: КОМПЛЕКТ | DW82: КОМПЛЕКТ | DX82: 1 | EE82: 51697657 | EF82: 201 | EG82: Материалы монтажные | EH82: 0 | EJ82: 2 | EK82: 1618 | EL82: ТСН-2001.1 Материалы монтажные | EM82: ТСН-2001.1-2 | EO82: Поправка: О.П. п.3.4.30.г | EQ82: 131072 | ER82: 153.63 | ES82: 153.63 | ET82: 0 | EU82: 0 | EV82: 0 | EW82: 0 | EX82: 0 | EY82: 0 | FQ82: 0 | FR82: 0 | FS82: 0 | FX82: 0 | FY82: 0 | GD82: 0 | GF82: 1544174678 | GG82: 2 | GH82: 1 | GI82: 2 | GJ82: 0 | GK82: =ROUND(R82*(R12)/100,2) -> 0 | GL82: =ROUND(IF(AND(BH82=3,BI82=3,FS82<>0),P82,0),2) -> 0 | GM82: =ROUND(O82+X82+Y82+GK82,2)+GX82 -> 2593.27 | GN82: =IF(OR(BI82=0,BI82=1),GM82-GX82,0) -> 0 | GO82: =IF(BI82=2,GM82-GX82,0) -> 2593.27 | GP82: =IF(BI82=4,GM82-GX82,0) -> 0 | GR82: 0 | GS82: 3 | GT82: 0 | GV82: =ROUND((GT82),6) -> 0 | GW82: 1 | GX82: =ROUND(HC82*I82,2) -> 0 | HA82: 0 | HB82: 0 | HC82: =GV82*GW82 -> 0 | HS82: 0 | IK82: 0
A84: 51 | B84: =B74 -> 1 | C84: =A74 -> 5 | D84: =ROW(A74) -> 74 | F84: =IF(F74<>"",F74,"") -> Новый подраздел | G84: =IF(G74<>"",G74,"") -> Монтажные работы | H84: 0 | O84: =ROUND(AB84,2) -> 1001912.2 | P84: =ROUND(AC84,2) -> 886369.1 | Q84: =ROUND(AD84,2) -> 9829.94 | R84: =ROUND(AE84,2) -> 3469.29 | S84: =ROUND(AF84,2) -> 105713.11 | T84: =ROUND(AG84,2) -> 0 | U84: =AH84 -> 247.02435 | V84: =AI84 -> 0 | W84: =ROUND(AJ84,2) -> 0 | X84: =ROUND(AK84,2) -> 97256.06 | Y84: =ROUND(AL84,2) -> 45456.64 | AB84: =ROUND(SUMIF(AA78:AA82,"=57737055",O78:O82),2) -> 1001912.2 | AC84: =ROUND(SUMIF(AA78:AA82,"=57737055",P78:P82),2) -> 886369.1 | AD84: =ROUND(SUMIF(AA78:AA82,"=57737055",Q78:Q82),2) -> 9829.94 | AE84: =ROUND(SUMIF(AA78:AA82,"=57737055",R78:R82),2) -> 3469.29 | AF84: =ROUND(SUMIF(AA78:AA82,"=57737055",S78:S82),2) -> 105713.11 | AG84: =ROUND(SUMIF(AA78:AA82,"=57737055",T78:T82),2) -> 0 | AH84: =SUMIF(AA78:AA82,"=57737055",U78:U82) -> 247.02435 | AI84: =SUMIF(AA78:AA82,"=57737055",V78:V82) -> 0 | AJ84: =ROUND(SUMIF(AA78:AA82,"=57737055",W78:W82),2) -> 0 | AK84: =ROUND(SUMIF(AA78:AA82,"=57737055",X78:X82),2) -> 97256.06 | AL84: =ROUND(SUMIF(AA78:AA82,"=57737055",Y78:Y82),2) -> 45456.64 | AO84: =ROUND(BX84,2) -> 0 | AP84: =ROUND(BY84,2) -> 0 | AQ84: =ROUND(BZ84,2) -> 0 | AR84: =ROUND(CA84,2) -> 1150175.7 | AS84: =ROUND(CB84,2) -> 0 | AT84: =ROUND(CC84,2) -> 1150175.7 | AU84: =ROUND(CD84,2) -> 0 | AV84: =ROUND(CE84,2) -> 886369.1 | ... BD84: =ROUND(CM84,2) -> 0 | BX84: =ROUND(SUMIF(AA78:AA82,"=57737055",FQ78:FQ82),2) -> 0 | BY84: =ROUND(SUMIF(AA78:AA82,"=57737055",FR78:FR82),2) -> 0 | BZ84: =ROUND(SUMIF(AA78:AA82,"=57737055",GL78:GL82),2) -> 0 | CA84: =ROUND(SUMIF(AA78:AA82,"=57737055",GM78:GM82),2) -> 1150175.7 | CB84: =ROUND(SUMIF(AA78:AA82,"=57737055",GN78:GN82),2) -> 0 | CC84: =ROUND(SUMIF(AA78:AA82,"=57737055",GO78:GO82),2) -> 1150175.7 | CD84: =ROUND(SUMIF(AA78:AA82,"=57737055",GP78:GP82),2) -> 0 | CE84: =AC84-BX84 -> 886369.1 | CF84: =AC84-BY84 -> 886369.1 | CG84: =BX84-BZ84 -> 0 | CH84: =AC84-BX84-BY84+BZ84 -> 886369.1 | CI84: =BY84-BZ84 -> 0 | CJ84: =ROUND(SUMIF(AA78:AA82,"=57737055",GX78:GX82),2) -> 0 | CK84: =ROUND(SUMIF(AA78:AA82,"=57737055",GY78:GY82),2) -> 0 | CL84: =ROUND(SUMIF(AA78:AA82,"=57737055",GZ78:GZ82),2) -> 0 | CM84: =ROUND(SUMIF(AA78:AA82,"=57737055",HD78:HD82),2) -> 0 | GX84: 0
A86: 50 | B86: 0 | C86: 0 | D86: 1 | E86: 201 | F86: =ROUND(Source!O84,O86) -> 1001912.2 | G86: ПЗ | H86: Прямые затраты | K86: 201 | L86: 1 | M86: 3 | O86: 2 | W86: 1001912.2 | X86: 1 | Y86: 1001912.2
A87: 50 | B87: 0 | C87: 0 | D87: 1 | E87: 202 | F87: =ROUND(Source!P84,O87) -> 886369.1 | G87: СтМатОб | H87: Стоимость материальных ресурсов (всего) | K87: 202 | L87: 2 | M87: 3 | O87: 2 | W87: 886369.1 | X87: 1 | Y87: 886369.1
A88: 50 | B88: 0 | C88: 0 | D88: 1 | E88: 222 | F88: =ROUND(Source!AO84,O88) -> 0 | G88: СтМатОбЗак | H88: Стоимость материалов и оборудования заказчика | K88: 222 | L88: 3 | M88: 3 | O88: 2 | W88: 0 | X88: 1 | Y88: 0
A89: 50 | B89: 0 | C89: 0 | D89: 1 | E89: 225 | F89: =ROUND(Source!AV84,O89) -> 886369.1 | G89: СтМатОбПод | H89: Стоимость материалов и оборудования подрядчика | K89: 225 | L89: 4 | M89: 3 | O89: 2 | W89: 886369.1 | X89: 1 | Y89: 886369.1
A90: 50 | B90: 0 | C90: 0 | D90: 1 | E90: 226 | F90: =ROUND(Source!AW84,O90) -> 886369.1 | G90: СтМат | H90: Стоимость материалов (всего) | K90: 226 | L90: 5 | M90: 3 | O90: 2 | W90: 886369.1 | X90: 1 | Y90: 886369.1
A91: 50 | B91: 0 | C91: 0 | D91: 1 | E91: 227 | F91: =ROUND(Source!AX84,O91) -> 0 | G91: СтМатЗак | H91: Стоимость материалов заказчика | K91: 227 | L91: 6 | M91: 3 | O91: 2 | W91: 0 | X91: 1 | Y91: 0
A92: 50 | B92: 0 | C92: 0 | D92: 1 | E92: 228 | F92: =ROUND(Source!AY84,O92) -> 886369.1 | G92: СтМатПод | H92: Стоимость материалов подрядчика | K92: 228 | L92: 7 | M92: 3 | O92: 2 | W92: 886369.1 | X92: 1 | Y92: 886369.1
A93: 50 | B93: 0 | C93: 0 | D93: 1 | E93: 216 | F93: =ROUND(Source!AP84,O93) -> 0 | G93: Оборуд | H93: Стоимость оборудования (всего) | K93: 216 | L93: 8 | M93: 3 | O93: 2 | W93: 0 | X93: 1 | Y93: 0
A94: 50 | B94: 0 | C94: 0 | D94: 1 | E94: 223 | F94: =ROUND(Source!AQ84,O94) -> 0 | G94: ОборудЗак | H94: Стоимость оборудования заказчика | K94: 223 | L94: 9 | M94: 3 | O94: 2 | W94: 0 | X94: 1 | Y94: 0
A95: 50 | B95: 0 | C95: 0 | D95: 1 | E95: 229 | F95: =ROUND(Source!AZ84,O95) -> 0 | G95: ОборудПод | H95: Стоимость оборудования подрядчика | K95: 229 | L95: 10 | M95: 3 | O95: 2 | W95: 0 | X95: 1 | Y95: 0
A96: 50 | B96: 0 | C96: 0 | D96: 1 | E96: 203 | F96: =ROUND(Source!Q84,O96) -> 9829.94 | G96: ЭММ | H96: Эксплуатация машин | K96: 203 | L96: 11 | M96: 3 | O96: 2 | W96: 9829.94 | X96: 1 | Y96: 9829.94
A97: 50 | B97: 0 | C97: 0 | D97: 1 | E97: 231 | F97: =ROUND(Source!BB84,O97) -> 0 | G97: ЭММсНРиСП | H97: Эксплуатация машин по ТСН-2001.16 | K97: 231 | L97: 12 | M97: 3 | O97: 2 | W97: 0 | X97: 1 | Y97: 0
A98: 50 | B98: 0 | C98: 0 | D98: 1 | E98: 204 | F98: =ROUND(Source!R84,O98) -> 3469.29 | G98: ЗПМ | H98: ЗП машинистов | K98: 204 | L98: 13 | M98: 3 | O98: 2 | W98: 3469.29 | X98: 1 | Y98: 3469.29
A99: 50 | B99: 0 | C99: 0 | D99: 1 | E99: 205 | F99: =ROUND(Source!S84,O99) -> 105713.11 | G99: ОЗП | H99: Основная ЗП рабочих | K99: 205 | L99: 14 | M99: 3 | O99: 2 | W99: 105713.11 | X99: 1 | Y99: 105713.11
A100: 50 | B100: 0 | C100: 0 | D100: 1 | E100: 232 | F100: =ROUND(Source!BC84,O100) -> 0 | G100: ОЗПсНРиСП | H100: Основная ЗП рабочих по ТСН-2001.16 | K100: 232 | L100: 15 | M100: 3 | O100: 2 | W100: 0 | X100: 1 | Y100: 0
A101: 50 | B101: 0 | C101: 0 | D101: 1 | E101: 214 | F101: =ROUND(Source!AS84,O101) -> 0 | G101: Строит | H101: Строительные работы с НР и СП | K101: 214 | L101: 16 | M101: 3 | O101: 2 | W101: 0 | X101: 1 | Y101: 0
A102: 50 | B102: 0 | C102: 0 | D102: 1 | E102: 215 | F102: =ROUND(Source!AT84,O102) -> 1150175.7 | G102: Монтаж | H102: Монтажные работы с НР и СП | K102: 215 | L102: 17 | M102: 3 | O102: 2 | W102: 1150175.7 | X102: 1 | Y102: 1150175.7
A103: 50 | B103: 0 | C103: 0 | D103: 1 | E103: 217 | F103: =ROUND(Source!AU84,O103) -> 0 | G103: Прочие | H103: Прочие работы с НР и СП | K103: 217 | L103: 18 | M103: 3 | O103: 2 | W103: 0 | X103: 1 | Y103: 0
A104: 50 | B104: 0 | C104: 0 | D104: 1 | E104: 230 | F104: =ROUND(Source!BA84,O104) -> 0 | G104: ПрочиеЗатр | H104: Прочие затраты по ТСН-2001.16 | K104: 230 | L104: 19 | M104: 3 | O104: 2 | W104: 0 | X104: 1 | Y104: 0
A105: 50 | B105: 0 | C105: 0 | D105: 1 | E105: 206 | F105: =ROUND(Source!T84,O105) -> 0 | G105: ВозврМат | H105: Возврат материалов | K105: 206 | L105: 20 | M105: 3 | O105: 2 | W105: 0 | X105: 1 | Y105: 0
A106: 50 | B106: 0 | C106: 0 | D106: 1 | E106: 207 | F106: =Source!U84 -> 247.02435 | G106: ТрудСтр | H106: Трудозатраты строителей | K106: 207 | L106: 21 | M106: 3 | O106: -1 | W106: 247.02435 | X106: 1 | Y106: 247.02435
A107: 50 | B107: 0 | C107: 0 | D107: 1 | E107: 208 | F107: =Source!V84 -> 0 | G107: ТрудМаш | H107: Трудозатраты машинистов | K107: 208 | L107: 22 | M107: 3 | O107: -1 | W107: 0 | X107: 1 | Y107: 0
A108: 50 | B108: 0 | C108: 0 | D108: 1 | E108: 209 | F108: =ROUND(Source!W84,O108) -> 0 | G108: ТранспМат | H108: Транспорт материалов | K108: 209 | L108: 23 | M108: 3 | O108: 2 | W108: 0 | X108: 1 | Y108: 0
A109: 50 | B109: 0 | C109: 0 | D109: 1 | E109: 233 | F109: =ROUND(Source!BD84,O109) -> 0 | G109: Перевозка | H109: Перевозка грузов | K109: 233 | L109: 24 | M109: 3 | O109: 2 | W109: 0 | X109: 1 | Y109: 0
A110: 50 | B110: 0 | C110: 0 | D110: 1 | E110: 210 | F110: =ROUND(Source!X84,O110) -> 97256.06 | G110: НР | H110: Накладные расходы | K110: 210 | L110: 25 | M110: 3 | O110: 2 | W110: 97256.06 | X110: 1 | Y110: 97256.06
A111: 50 | B111: 0 | C111: 0 | D111: 1 | E111: 211 | F111: =ROUND(Source!Y84,O111) -> 45456.64 | G111: СмПриб | H111: Сметная прибыль | K111: 211 | L111: 26 | M111: 3 | O111: 2 | W111: 45456.64 | X111: 1 | Y111: 45456.64
A112: 50 | B112: 0 | C112: 0 | D112: 1 | E112: 224 | F112: =ROUND(Source!AR84,O112) -> 1150175.7 | G112: Всего | H112: Всего с НР и СП | K112: 224 | L112: 27 | M112: 3 | O112: 2 | W112: 1150175.7 | X112: 1 | Y112: 1150175.7
A114: 51 | B114: =B24 -> 1 | C114: =A24 -> 4 | D114: =ROW(A24) -> 24 | F114: =IF(F24<>"",F24,"") -> Новый раздел | G114: =IF(G24<>"",G24,"") -> Закрытый переход 2 сквх3тр (104,1м; 113,4м) | H114: 0 | O114: =ROUND(O44+O84+AB114,2) -> 7532850.3 | P114: =ROUND(P44+P84+AC114,2) -> 3626729 | Q114: =ROUND(Q44+Q84+AD114,2) -> 3562517 | R114: =ROUND(R44+R84+AE114,2) -> 410220.03 | S114: =ROUND(S44+S84+AF114,2) -> 343604.34 | T114: =ROUND(T44+T84+AG114,2) -> 0 | U114: =U44+U84+AH114 -> 748.80028 | V114: =V44+V84+AI114 -> 0 | W114: =ROUND(W44+W84+AJ114,2) -> 0 | X114: =ROUND(X44+X84+AK114,2) -> 376229.32 | Y114: =ROUND(Y44+Y84+AL114,2) -> 177500.14 | AO114: =ROUND(AO44+AO84+BX114,2) -> 0 | AP114: =ROUND(AP44+AP84+BY114,2) -> 0 | AQ114: =ROUND(AQ44+AQ84+BZ114,2) -> 0 | AR114: =ROUND(AR44+AR84+CA114,2) -> 8742931.8 | AS114: =ROUND(AS44+AS84+CB114,2) -> 7591866.6 | AT114: =ROUND(AT44+AT84+CC114,2) -> 1151065.2 | AU114: =ROUND(AU44+AU84+CD114,2) -> 0 | AV114: =ROUND(AV44+AV84+CE114,2) -> 3626729 | ... BD114: =ROUND(BD44+BD84+CM114,2) -> 0 | GX114: 0
A116: 50 | B116: 0 | C116: 0 | D116: 1 | E116: 201 | F116: =ROUND(Source!O114,O116) -> 7532850.3 | G116: ПЗ | H116: Прямые затраты | K116: 201 | L116: 1 | M116: 3 | O116: 2 | W116: 7532850.3 | X116: 1 | Y116: 7532850.3
A117: 50 | B117: 0 | C117: 0 | D117: 1 | E117: 202 | F117: =ROUND(Source!P114,O117) -> 3626729 | G117: СтМатОб | H117: Стоимость материальных ресурсов (всего) | K117: 202 | L117: 2 | M117: 3 | O117: 2 | W117: 3626729 | X117: 1 | Y117: 3626729
A118: 50 | B118: 0 | C118: 0 | D118: 1 | E118: 222 | F118: =ROUND(Source!AO114,O118) -> 0 | G118: СтМатОбЗак | H118: Стоимость материалов и оборудования заказчика | K118: 222 | L118: 3 | M118: 3 | O118: 2 | W118: 0 | X118: 1 | Y118: 0
A119: 50 | B119: 0 | C119: 0 | D119: 1 | E119: 225 | F119: =ROUND(Source!AV114,O119) -> 3626729 | G119: СтМатОбПод | H119: Стоимость материалов и оборудования подрядчика | K119: 225 | L119: 4 | M119: 3 | O119: 2 | W119: 3626729 | X119: 1 | Y119: 3626729
A120: 50 | B120: 0 | C120: 0 | D120: 1 | E120: 226 | F120: =ROUND(Source!AW114,O120) -> 3626729 | G120: СтМат | H120: Стоимость материалов (всего) | K120: 226 | L120: 5 | M120: 3 | O120: 2 | W120: 3626729 | X120: 1 | Y120: 3626729
A121: 50 | B121: 0 | C121: 0 | D121: 1 | E121: 227 | F121: =ROUND(Source!AX114,O121) -> 0 | G121: СтМатЗак | H121: Стоимость материалов заказчика | K121: 227 | L121: 6 | M121: 3 | O121: 2 | W121: 0 | X121: 1 | Y121: 0
A122: 50 | B122: 0 | C122: 0 | D122: 1 | E122: 228 | F122: =ROUND(Source!AY114,O122) -> 3626729 | G122: СтМатПод | H122: Стоимость материалов подрядчика | K122: 228 | L122: 7 | M122: 3 | O122: 2 | W122: 3626729 | X122: 1 | Y122: 3626729
A123: 50 | B123: 0 | C123: 0 | D123: 1 | E123: 216 | F123: =ROUND(Source!AP114,O123) -> 0 | G123: Оборуд | H123: Стоимость оборудования (всего) | K123: 216 | L123: 8 | M123: 3 | O123: 2 | W123: 0 | X123: 1 | Y123: 0
A124: 50 | B124: 0 | C124: 0 | D124: 1 | E124: 223 | F124: =ROUND(Source!AQ114,O124) -> 0 | G124: ОборудЗак | H124: Стоимость оборудования заказчика | K124: 223 | L124: 9 | M124: 3 | O124: 2 | W124: 0 | X124: 1 | Y124: 0
A125: 50 | B125: 0 | C125: 0 | D125: 1 | E125: 229 | F125: =ROUND(Source!AZ114,O125) -> 0 | G125: ОборудПод | H125: Стоимость оборудования подрядчика | K125: 229 | L125: 10 | M125: 3 | O125: 2 | W125: 0 | X125: 1 | Y125: 0
A126: 50 | B126: 0 | C126: 0 | D126: 1 | E126: 203 | F126: =ROUND(Source!Q114,O126) -> 3562517 | G126: ЭММ | H126: Эксплуатация машин | K126: 203 | L126: 11 | M126: 3 | O126: 2 | W126: 3562517 | X126: 1 | Y126: 3562517
A127: 50 | B127: 0 | C127: 0 | D127: 1 | E127: 231 | F127: =ROUND(Source!BB114,O127) -> 0 | G127: ЭММсНРиСП | H127: Эксплуатация машин по ТСН-2001.16 | K127: 231 | L127: 12 | M127: 3 | O127: 2 | W127: 0 | X127: 1 | Y127: 0
A128: 50 | B128: 0 | C128: 0 | D128: 1 | E128: 204 | F128: =ROUND(Source!R114,O128) -> 410220.03 | G128: ЗПМ | H128: ЗП машинистов | K128: 204 | L128: 13 | M128: 3 | O128: 2 | W128: 410220.03 | X128: 1 | Y128: 410220.03
A129: 50 | B129: 0 | C129: 0 | D129: 1 | E129: 205 | F129: =ROUND(Source!S114,O129) -> 343604.34 | G129: ОЗП | H129: Основная ЗП рабочих | K129: 205 | L129: 14 | M129: 3 | O129: 2 | W129: 343604.34 | X129: 1 | Y129: 343604.34
A130: 50 | B130: 0 | C130: 0 | D130: 1 | E130: 232 | F130: =ROUND(Source!BC114,O130) -> 0 | G130: ОЗПсНРиСП | H130: Основная ЗП рабочих по ТСН-2001.16 | K130: 232 | L130: 15 | M130: 3 | O130: 2 | W130: 0 | X130: 1 | Y130: 0
...

Sheet SourceObSm
A1: 0 | B1: Smeta.RU (495) 974-1589 | D1: _OBSM_ | F1: 0 | G1: 0 | H1: 0 | I1: Smeta.RU | K1: 1 | L1: 75112 | M1: 10 | N1: 11 | O1: 15 | P1: 0 | Q1: 1
A12: 1 | B12: 52 | C12: 1 | E12: 0 | F12: 02-01-08 Закрытый переход_(2 этап) | G12: 02-01-08 Закрытый переход | I12: 0 | K12: 0 | L12: 0 | M12: 4098 | O12: 0 | P12: 0 | Q12: 0 | R12: 160 | T12: 1 | V12: 0 | BB12: 0 | BH12: Сметные нормы списания | BI12: Коды ОКП для ТСН-2001 МГЭ (История развития) | BJ12: 1 | BK12: 1 | BL12: 0 | BM12: 0 | BN12: 1 | BO12: 0 | BP12: 6 | BQ12: 2 | BR12: 1 | BS12: 1 | BT12: 0 | BU12: 0 | BV12: 0 | BW12: 0 | BX12: 0 | BZ12: Типовой расчет для ТСН-2001 МГЭ, Новая методика с выпуска доп. 43 (Строительство), Доп 73 | CA12: История развития для ТСН-2001 (МГЭ) 73 доп от 17.07.2024 | CB12: История развития для ТСН-2001 (МГЭ) 73 доп от 17.07.2024 | CC12: История развития для ТСН-2001 (МГЭ) 73 доп от 17.07.2024 | CD12: История развития для ТСН-2001 (МГЭ) 73 доп от 17.07.2024 | CE12: Поправки для ТСН-2001 от 16.04.2024 г. доп.72 | CF12: 0 | CG12: 0 | CH12: 8 | CK12: 79 | CQ12: Территориальные сметные нормативы для Москвы (ТСН-2001) | CR12: ТЕР | CS12: 41660 | CT12: 1 | CU12: 73 | CY12: 0 | EC12: 0
A14: 22 | B14: 1 | C14: 0 | D14: 57737055 | E14: 0 | F14: 2 | G14: 1
A16: 3 | B16: 1 | C16: Новая локальная смета | D16: Закрытые переходы | E16: =ROUND((Source!F161)/1000,2) -> 7591.87 | F16: =ROUND((Source!F162)/1000,2) -> 1151.07 | G16: =ROUND((Source!F153)/1000,2) -> 0 | H16: =ROUND((Source!F163)/1000+(Source!F164)/1000,2) -> 0 | I16: =E16+F16+G16+H16 -> 8742.94 | J16: =ROUND((Source!F159+Source!F158)/1000,2) -> 753.82 | K16: 11159.58 | L16: 0 | M16: 0 | N16: =I16+L16+M16 -> 8742.94 | AI16: 0 | AJ16: -1 | AN16: 0 | AT16: 7532850.3 | AU16: 3626729 | AV16: 0 | AW16: 0 | AX16: 0 | AY16: 3562517 | AZ16: 410220.03 | BA16: 343604.34 | BB16: 7591866.6 | BC16: 1151065.2 | BD16: 0 | BE16: 0 | BF16: 748.80028 | BG16: 0 | BH16: 0 | BI16: 376229.32 | BJ16: 177500.14 | BK16: 8742931.8
A18: 51 | E18: 7591.87 | F18: 1151.07 | G18: 0 | H18: 0 | I18: 8742.94 | J18: 753.82 | K18: 11159.58 | L18: 0 | M18: 0 | N18: 8742.94
A20: 50 | B20: 0 | C20: 0 | D20: 1 | E20: 201 | F20: 7532850.3 | G20: ПЗ | H20: Прямые затраты | K20: 201 | L20: 1 | M20: 3 | O20: 2
A21: 50 | B21: 0 | C21: 0 | D21: 1 | E21: 202 | F21: 3626729 | G21: СтМатОб | H21: Стоимость материальных ресурсов (всего) | K21: 202 | L21: 2 | M21: 3 | O21: 2
A22: 50 | B22: 0 | C22: 0 | D22: 1 | E22: 222 | F22: 0 | G22: СтМатОбЗак | H22: Стоимость материалов и оборудования заказчика | K22: 222 | L22: 3 | M22: 3 | O22: 2
A23: 50 | B23: 0 | C23: 0 | D23: 1 | E23: 225 | F23: 3626729 | G23: СтМатОбПод | H23: Стоимость материалов и оборудования подрядчика | K23: 225 | L23: 4 | M23: 3 | O23: 2
A24: 50 | B24: 0 | C24: 0 | D24: 1 | E24: 226 | F24: 3626729 | G24: СтМат | H24: Стоимость материалов (всего) | K24: 226 | L24: 5 | M24: 3 | O24: 2
A25: 50 | B25: 0 | C25: 0 | D25: 1 | E25: 227 | F25: 0 | G25: СтМатЗак | H25: Стоимость материалов заказчика | K25: 227 | L25: 6 | M25: 3 | O25: 2
A26: 50 | B26: 0 | C26: 0 | D26: 1 | E26: 228 | F26: 3626729 | G26: СтМатПод | H26: Стоимость материалов подрядчика | K26: 228 | L26: 7 | M26: 3 | O26: 2
A27: 50 | B27: 0 | C27: 0 | D27: 1 | E27: 216 | F27: 0 | G27: Оборуд | H27: Стоимость оборудования (всего) | K27: 216 | L27: 8 | M27: 3 | O27: 2
A28: 50 | B28: 0 | C28: 0 | D28: 1 | E28: 223 | F28: 0 | G28: ОборудЗак | H28: Стоимость оборудования заказчика | K28: 223 | L28: 9 | M28: 3 | O28: 2
A29: 50 | B29: 0 | C29: 0 | D29: 1 | E29: 229 | F29: 0 | G29: ОборудПод | H29: Стоимость оборудования подрядчика | K29: 229 | L29: 10 | M29: 3 | O29: 2
A30: 50 | B30: 0 | C30: 0 | D30: 1 | E30: 203 | F30: 3562517 | G30: ЭММ | H30: Эксплуатация машин | K30: 203 | L30: 11 | M30: 3 | O30: 2
A31: 50 | B31: 0 | C31: 0 | D31: 1 | E31: 231 | F31: 0 | G31: ЭММсНРиСП | H31: Эксплуатация машин по ТСН-2001.16 | K31: 231 | L31: 12 | M31: 3 | O31: 2
... A47: 50 | B47: 1 | C47: 0 | D47: 2 | E47: 0 | F47: 8742931.8 | G47: и1 | H47: Итого: | K47: 212 | L47: 28 | M47: 0 | O47: 2
A49: -1
A52: 75 | B52: Текущий уровень цен | C52: 2024 | D52: 0 | E52: 4 | G52: 0 | H52: 2 | I52: 1 | J52: 1 | K52: 95 | L52: 65 | M52: 0 | N52: 57737055 | O52: 1
A53: 1 | B53: Сборник индексов | C53: Коэффициенты к ТСН-2001 МГЭ | D53: 2024 | E53: 7 | F53: 1 | G53: 1 | H53: 0 | I53: 2 | J53: 1 | K53: 1 | L53: 1 | M53: 1 | N53: 1 | O53: 1 | P53: 1 | Q53: 1 | AA53: 212 | AN53: 57737056

Sheet SmtRes
A1: =ROW(Source!A32) -> 32 | B1: 57737055 | C1: 57737291 | D1: 47634407 | E1: 27786564 | F1: 1 | G1: 27786564 | H1: 1 | I1: 9999990008 | K1: Трудозатраты рабочих | L1: 1191 | N1: 1013 | O1: чел.-ч. | P1: чел.-ч. | Q1: 1 | W1: 0 | X1: 476480486 | Y1: =(AT1*1.05) -> 202.335 | AA1: 0 | AB1: 0 | AC1: 0 | AD1: 0 | AE1: 0 | AF1: 0 | AG1: 0 | AH1: 0 | AI1: 1 | AJ1: 1 | AK1: 1 | AL1: 1 | AM1: -2 | AN1: 0 | AO1: 1 | AP1: 1 | AQ1: 0 | AR1: 0 | AT1: 192.7 | AU1: *1,05 | AV1: 1 | AW1: 2 | AX1: 57737293 | AY1: 1 | AZ1: 0 | BA1: 1 | BB1: 0 | BC1: 0 | BD1: 0 | BE1: 0 | BF1: 0 | BG1: 0 | BH1: 0 | BI1: 0 | BJ1: 0 | BK1: 0 | BL1: 0 | BM1: 0 | BN1: 0 | BO1: 0 | BP1: 0 | BQ1: 0 | BR1: 0 | BS1: 0 | BT1: 0 | BU1: 0 | BV1: 0 | BW1: 0 | CU1: =ROUND(AT1*Source!I32*AH1*AL1,2) -> 0 | CV1: =ROUND(Y1*Source!I32,9) -> 3.8757269 | CW1: 0 | CX1: =ROUND(Y1*Source!I32,9) -> 3.8757269 | CY1: =AD1 -> 0 | CZ1: =AH1 -> 0 | DA1: =AL1 -> 1 | DB1: =ROUND((ROUND(AT1*CZ1,2)*1.05),6) -> 0 | DC1: =ROUND((ROUND(AT1*AG1,2)*1.05),6) -> 0 | DF1: =ROUND(ROUND(AE1,2)*CX1,2) -> 0 | DG1: =ROUND(ROUND(AF1,2)*CX1,2) -> 0 | DH1: =ROUND(ROUND(AG1,2)*CX1,2) -> 0 | DI1: =ROUND(ROUND(AH1,2)*CX1,2) -> 0 | DJ1: =DI1 -> 0 | DK1: 0 | DM1: 0 | DO1: 0
A2: =ROW(Source!A33) -> 33 | B2: 57737055 | C2: 57737294 | D2: 47634407 | E2: 27786564 | F2: 1 | G2: 27786564 | H2: 1 | I2: 9999990008 | K2: Трудозатраты рабочих | L2: 1191 | N2: 1013 | O2: чел.-ч. | P2: чел.-ч. | Q2: 1 | W2: 0 | X2: 476480486 | Y2: =(AT2*1.05) -> 112.392 | AA2: 0 | AB2: 0 | AC2: 0 | AD2: 0 | AE2: 0 | AF2: 0 | AG2: 0 | AH2: 0 | AI2: 1 | AJ2: 1 | AK2: 1 | AL2: 1 | AM2: -2 | AN2: 0 | AO2: 1 | AP2: 1 | AQ2: 0 | AR2: 0 | AT2: 107.04 | AU2: *1,05 | AV2: 1 | AW2: 2 | AX2: 57737296 | AY2: 1 | AZ2: 0 | BA2: 2 | BB2: 0 | BC2: 0 | BD2: 0 | BE2: 0 | BF2: 0 | BG2: 0 | BH2: 0 | BI2: 0 | BJ2: 0 | BK2: 0 | BL2: 0 | BM2: 0 | BN2: 0 | BO2: 0 | BP2: 0 | BQ2: 0 | BR2: 0 | BS2: 0 | BT2: 0 | BU2: 0 | BV2: 0 | BW2: 0 | CU2: =ROUND(AT2*Source!I33*AH2*AL2,2) -> 0 | CV2: =ROUND(Y2*Source!I33,9) -> 5.0981011 | CW2: 0 | CX2: =ROUND(Y2*Source!I33,9) -> 5.0981011 | CY2: =AD2 -> 0 | CZ2: =AH2 -> 0 | DA2: =AL2 -> 1 | DB2: =ROUND((ROUND(AT2*CZ2,2)*1.05),6) -> 0 | DC2: =ROUND((ROUND(AT2*AG2,2)*1.05),6) -> 0 | DF2: =ROUND(ROUND(AE2,2)*CX2,2) -> 0 | DG2: =ROUND(ROUND(AF2,2)*CX2,2) -> 0 | DH2: =ROUND(ROUND(AG2,2)*CX2,2) -> 0 | DI2: =ROUND(ROUND(AH2,2)*CX2,2) -> 0 | DJ2: =DI2 -> 0 | DK2: 0 | DM2: 0 | DO2: 0
A3: =ROW(Source!A34) -> 34 | B3: 57737055 | C3: 57737297 | D3: 47634407 | E3: 27786564 | F3: 1 | G3: 27786564 | H3: 1 | I3: 9999990008 | K3: Трудозатраты рабочих | L3: 1191 | N3: 1013 | O3: чел.-ч. | P3: чел.-ч. | Q3: 1 | W3: 0 | X3: 476480486 | Y3: =(AT3*1.05) -> 2.184 | AA3: 0 | AB3: 0 | AC3: 0 | AD3: 0 | AE3: 0 | AF3: 0 | AG3: 0 | AH3: 0 | AI3: 1 | AJ3: 1 | AK3: 1 | AL3: 1 | AM3: -2 | AN3: 0 | AO3: 1 | AP3: 1 | AQ3: 0 | AR3: 0 | AT3: 2.08 | AU3: *1,05 | AV3: 1 | AW3: 2 | AX3: 57737311 | AY3: 1 | AZ3: 0 | BA3: 3 | BB3: 0 | BC3: 0 | BD3: 0 | BE3: 0 | BF3: 0 | BG3: 0 | BH3: 0 | BI3: 0 | BJ3: 0 | BK3: 0 | BL3: 0 | BM3: 0 | BN3: 0 | BO3: 0 | BP3: 0 | BQ3: 0 | BR3: 0 | BS3: 0 | BT3: 0 | BU3: 0 | BV3: 0 | BW3: 0 | CU3: =ROUND(AT3*Source!I34*AH3*AL3,2) -> 0 | CV3: =ROUND(Y3*Source!I34,9) -> 406.6608 | CW3: 0 | CX3: =ROUND(Y3*Source!I34,9) -> 406.6608 | CY3: =AD3 -> 0 | CZ3: =AH3 -> 0 | DA3: =AL3 -> 1 | DB3: =ROUND((ROUND(AT3*CZ3,2)*1.05),6) -> 0 | DC3: =ROUND((ROUND(AT3*AG3,2)*1.05),6) -> 0 | DF3: =ROUND(ROUND(AE3,2)*CX3,2) -> 0 | DG3: =ROUND(ROUND(AF3,2)*CX3,2) -> 0 | DH3: =ROUND(ROUND(AG3,2)*CX3,2) -> 0 | DI3: =ROUND(ROUND(AH3,2)*CX3,2) -> 0 | DJ3: =DI3 -> 0 | DK3: 0 | DM3: 0 | DO3: 0
A4: =ROW(Source!A34) -> 34 | B4: 57737055 | C4: 57737297 | D4: 47766829 | E4: 1 | F4: 1 | G4: 27786564 | H4: 2 | I4: 2.1-11-91 | J4: ТСН-2001.2. Доп. 68. п.1-11-91 (110701) | K4: Насосы водоотливные, производительность до 54 м3/ч, мощность до 3,2 кВт (4,8 л.с) | L4: 1368 | N4: 1011 | O4: маш.-ч | P4: маш.-ч | Q4: 1 | W4: 0 | X4: 476320882 | Y4: =(AT4*1.05) -> 0.126 | AA4: 0 | AB4: 231.57 | AC4: 121.76 | AD4: 0 | AE4: 0 | AF4: 12.98 | AG4: 3.37 | AH4: 0 | AI4: 1 | AJ4: 17.04 | AK4: 34.51 | AL4: 1 | AM4: 2 | AN4: 0 | AO4: 1 | AP4: 1 | AQ4: 0 | AR4: 0 | AT4: 0.12 | AU4: *1,05 | AV4: 0 | AW4: 2 | AX4: 57737312 | AY4: 1 | AZ4: 0 | BA4: 4 | BB4: 0 | BC4: 0 | BD4: 0 | BE4: 0 | BF4: 0 | BG4: 0 | BH4: 0 | BI4: 0 | BJ4: 0 | BK4: 0 | BL4: 0 | BM4: 0 | BN4: 0 | BO4: 0 | BP4: 0 | BQ4: 0 | BR4: 0 | BS4: 0 | BT4: 0 | BU4: 0 | BV4: 0 | BW4: 0 | CV4: 0 | CW4: =ROUND(Y4*Source!I34*DO4,9) -> 0 | CX4: =ROUND(Y4*Source!I34,9) -> 23.4612 | CY4: =AB4 -> 231.57 | CZ4: =AF4 -> 12.98 | DA4: =AJ4 -> 17.04 | DB4: =ROUND((ROUND(AT4*CZ4,2)*1.05),6) -> 1.638 | DC4: =ROUND((ROUND(AT4*AG4,2)*1.05),6) -> 0.42 | DF4: =ROUND(ROUND(AE4,2)*CX4,2) -> 0 | DG4: =ROUND(ROUND(AF4*AJ4,2)*CX4,2) -> 5189.15 | DH4: =ROUND(ROUND(AG4*AK4,2)*CX4,2) -> 2728.54 | DI4: =ROUND(ROUND(AH4,2)*CX4,2) -> 0 | DJ4: =DG4 -> 5189.15 | DK4: 0 | DM4: 0 | DO4: 0
A5: =ROW(Source!A34) -> 34 | B5: 57737055 | C5: 57737297 | D5: 47767072 | E5: 1 | F5: 1 | G5: 27786564 | H5: 2 | I5: 2.1-17-203 | J5: ТСН-2001.2. Доп. 68. п.1-17-203 (172706) | K5: Установки направленного бурения, тяговое усилие до 500 кН | L5: 1368 | N5: 1011 | O5: маш.-ч | P5: маш.-ч | Q5: 1 | W5: 0 | X5: -491204050 | Y5: =(AT5*1.05) -> 0.924 | AA5: 0 | AB5: 18064.39 | AC5: 1406.98 | AD5: 0 | AE5: 0 | AF5: 1843.32 | AG5: 38.94 | AH5: 0 | AI5: 1 | AJ5: 9.36 | AK5: 34.51 | AL5: 1 | AM5: 2 | AN5: 0 | AO5: 1 | AP5: 1 | AQ5: 0 | AR5: 0 | AT5: 0.88 | AU5: *1,05 | AV5: 0 | AW5: 2 | AX5: 57737313 | AY5: 1 | AZ5: 0 | BA5: 5 | BB5: 0 | BC5: 0 | BD5: 0 | BE5: 0 | BF5: 0 | BG5: 0 | BH5: 0 | BI5: 0 | BJ5: 0 | BK5: 0 | BL5: 0 | BM5: 0 | BN5: 0 | BO5: 0 | BP5: 0 | BQ5: 0 | BR5: 0 | BS5: 0 | BT5: 0 | BU5: 0 | BV5: 0 | BW5: 0 | CV5: 0 | CW5: =ROUND(Y5*Source!I34*DO5,9) -> 0 | CX5: =ROUND(Y5*Source!I34,9) -> 172.0488 | CY5: =AB5 -> 18064.39 | CZ5: =AF5 -> 1843.32 | DA5: =AJ5 -> 9.36 | DB5: =ROUND((ROUND(AT5*CZ5,2)*1.05),6) -> 1703.226 | DC5: =ROUND((ROUND(AT5*AG5,2)*1.05),6) -> 35.9835 | DF5: =ROUND(ROUND(AE5,2)*CX5,2) -> 0 | DG5: =ROUND(ROUND(AF5*AJ5,2)*CX5,2) -> 2968440.5 | DH5: =ROUND(ROUND(AG5*AK5,2)*CX5,2) -> 231202.62 | DI5: =ROUND(ROUND(AH5,2)*CX5,2) -> 0 | DJ5: =DG5 -> 2968440.5 | DK5: 0 | DM5: 0 | DO5: 0
A6: =ROW(Source!A34) -> 34 | B6: 57737055 | C6: 57737297 | D6: 47766980 | E6: 1 | F6: 1 | G6: 27786564 | H6: 2 | I6: 2.1-17-49 | J6: ТСН-2001.2. Доп. 68. п.1-17-49 (176802) | K6: Машины комбинированные илососные промывочные на базе автомобиля, объем цистерн до 10 м3, производительность до 720 м3/ч | L6: 1368 | N6: 1011 | O6: маш.-ч | P6: маш.-ч | Q6: 1 | W6: 0 | X6: 1811835874 | Y6: =(AT6*1.05) -> 0.1155 | AA6: 0 | AB6: 2140.69 | AC6: 525.36 | AD6: 0 | AE6: 0 | AF6: 181.58 | AG6: 14.54 | AH6: 0 | AI6: 1 | AJ6: 11.26 | AK6: 34.51 | AL6: 1 | AM6: 2 | AN6: 0 | AO6: 1 | AP6: 1 | AQ6: 0 | AR6: 0 | AT6: 0.11 | AU6: *1,05 | AV6: 0 | AW6: 2 | AX6: 57737314 | AY6: 1 | AZ6: 0 | BA6: 6 | BB6: 0 | BC6: 0 | BD6: 0 | BE6: 0 | BF6: 0 | BG6: 0 | BH6: 0 | BI6: 0 | BJ6: 0 | BK6: 0 | BL6: 0 | BM6: 0 | BN6: 0 | BO6: 0 | BP6: 0 | BQ6: 0 | BR6: 0 | BS6: 0 | BT6: 0 | BU6: 0 | BV6: 0 | BW6: 0 | CV6: 0 | CW6: =ROUND(Y6*Source!I34*DO6,9) -> 0 | CX6: =ROUND(Y6*Source!I34,9) -> 21.5061 | CY6: =AB6 -> 2140.69 | CZ6: =AF6 -> 181.58 | DA6: =AJ6 -> 11.26 | DB6: =ROUND((ROUND(AT6*CZ6,2)*1.05),6) -> 20.9685 | DC6: =ROUND((ROUND(AT6*AG6,2)*1.05),6) -> 1.68 | DF6: =ROUND(ROUND(AE6,2)*CX6,2) -> 0 | DG6: =ROUND(ROUND(AF6*AJ6,2)*CX6,2) -> 43971.16 | DH6: =ROUND(ROUND(AG6*AK6,2)*CX6,2) -> 10791.33 | DI6: =ROUND(ROUND(AH6,2)*CX6,2) -> 0 | DJ6: =DG6 -> 43971.16 | DK6: 0 | DM6: 0 | DO6: 0
A7: =ROW(Source!A34) -> 34 | B7: 57737055 | C7: 57737297 | D7: 47767117 | E7: 1 | F7: 1 | G7: 27786564 | H7: 2 | I7: 2.1-18-23 | J7: ТСН-2001.2. Доп. 68. п.1-18-23 (183201) | K7: Автомобили бортовые с краном-манипулятором, грузоподъемность до 6 т | L7: 1368 | N7: 1011 | O7: маш.-ч | P7: маш.-ч | Q7: 1 | W7: 0 | X7: 2005480434 | Y7: =(AT7*1.05) -> 0.021 | AA7: 0 | AB7: 1529.33 | AC7: 455.99 | AD7: 0 | AE7: 0 | AF7: 125.38 | AG7: 12.62 | AH7: 0 | AI7: 1 | AJ7: 11.65 | AK7: 34.51 | AL7: 1 | AM7: 2 | AN7: 0 | AO7: 1 | AP7: 1 | AQ7: 0 | AR7: 0 | AT7: 0.02 | AU7: *1,05 | AV7: 0 | AW7: 2 | AX7: 57737315 | AY7: 1 | AZ7: 0 | BA7: 7 | BB7: 0 | BC7: 0 | BD7: 0 | BE7: 0 | BF7: 0 | BG7: 0 | BH7: 0 | BI7: 0 | BJ7: 0 | BK7: 0 | BL7: 0 | BM7: 0 | BN7: 0 | BO7: 0 | BP7: 0 | BQ7: 0 | BR7: 0 | BS7: 0 | BT7: 0 | BU7: 0 | BV7: 0 | BW7: 0 | CV7: 0 | CW7: =ROUND(Y7*Source!I34*DO7,9) -> 0 | CX7: =ROUND(Y7*Source!I34,9) -> 3.9102 | CY7: =AB7 -> 1529.33 | CZ7: =AF7 -> 125.38 | DA7: =AJ7 -> 11.65 | DB7: =ROUND((ROUND(AT7*CZ7,2)*1.05),6) -> 2.6355 | DC7: =ROUND((ROUND(AT7*AG7,2)*1.05),6) -> 0.2625 | DF7: =ROUND(ROUND(AE7,2)*CX7,2) -> 0 | DG7: =ROUND(ROUND(AF7*AJ7,2)*CX7,2) -> 5711.55 | DH7: =ROUND(ROUND(AG7*AK7,2)*CX7,2) -> 1702.97 | DI7: =ROUND(ROUND(AH7,2)*CX7,2) -> 0 | DJ7: =DG7 -> 5711.55 | DK7: 0 | DM7: 0 | DO7: 0
A8: =ROW(Source!A34) -> 34 | B8: 57737055 | C8: 57737297 | D8: 47766471 | E8: 1 | F8: 1 | G8: 27786564 | H8: 2 | I8: 2.1-3-69 | J8: ТСН-2001.2. Доп. 68. п.1-3-69 (038003) | K8: Трубоукладчики, диаметр труб до 400 мм | L8: 1368 | N8: 1011 | O8: маш.-ч | P8: маш.-ч | Q8: 1 | W8: 0 | X8: -2113632580 | Y8: =(AT8*1.05) -> 0.315 | AA8: 0 | AB8: 1754.44 | AC8: 525.36 | AD8: 0 | AE8: 0 | AF8: 139.99 | AG8: 14.54 | AH8: 0 | AI8: 1 | AJ8: 11.97 | AK8: 34.51 | AL8: 1 | AM8: 2 | AN8: 0 | AO8: 1 | AP8: 1 | AQ8: 0 | AR8: 0 | AT8: 0.3 | AU8: *1,05 | AV8: 0 | AW8: 2 | AX8: 57737316 | AY8: 1 | AZ8: 0 | BA8: 8 | BB8: 0 | BC8: 0 | BD8: 0 | BE8: 0 | BF8: 0 | BG8: 0 | BH8: 0 | BI8: 0 | BJ8: 0 | BK8: 0 | BL8: 0 | BM8: 0 | BN8: 0 | BO8: 0 | BP8: 0 | BQ8: 0 | BR8: 0 | BS8: 0 | BT8: 0 | BU8: 0 | BV8: 0 | BW8: 0 | CV8: 0 | CW8: =ROUND(Y8*Source!I34*DO8,9) -> 0 | CX8: =ROUND(Y8*Source!I34,9) -> 58.653 | CY8: =AB8 -> 1754.44 | CZ8: =AF8 -> 139.99 | DA8: =AJ8 -> 11.97 | DB8: =ROUND((ROUND(AT8*CZ8,2)*1.05),6) -> 44.1 | DC8: =ROUND((ROUND(AT8*AG8,2)*1.05),6) -> 4.578 | DF8: =ROUND(ROUND(AE8,2)*CX8,2) -> 0 | DG8: =ROUND(ROUND(AF8*AJ8,2)*CX8,2) -> 98283.66 | DH8: =ROUND(ROUND(AG8*AK8,2)*CX8,2) -> 29430.9 | DI8: =ROUND(ROUND(AH8,2)*CX8,2) -> 0 | DJ8: =DG8 -> 98283.66 | DK8: 0 | DM8: 0 | DO8: 0
A9: =ROW(Source!A34) -> 34 | B9: 57737055 | C9: 57737297 | D9: 47766605 | E9: 1 | F9: 1 | G9: 27786564 | H9: 2 | I9: 2.1-5-18 | J9: ТСН-2001.2. Доп. 68. п.1-5-18 (050902) | K9: Машины поливомоечные, емкость цистерны до 8 м3 | L9: 1368 | N9: 1011 | O9: маш.-ч | P9: маш.-ч | Q9: 1 | W9: 0 | X9: 1034498840 | Y9: =(AT9*1.05) -> 0.126 | AA9: 0 | AB9: 1700.53 | AC9: 455.99 | AD9: 0 | AE9: 0 | AF9: 140.38 | AG9: 12.62 | AH9: 0 | AI9: 1 | AJ9: 11.57 | AK9: 34.51 | AL9: 1 | AM9: 2 | AN9: 0 | AO9: 1 | AP9: 1 | AQ9: 0 | AR9: 0 | AT9: 0.12 | AU9: *1,05 | AV9: 0 | AW9: 2 | AX9: 57737317 | AY9: 1 | AZ9: 0 | BA9: 9 | BB9: 0 | BC9: 0 | BD9: 0 | BE9: 0 | BF9: 0 | BG9: 0 | BH9: 0 | BI9: 0 | BJ9: 0 | BK9: 0 | BL9: 0 | BM9: 0 | BN9: 0 | BO9: 0 | BP9: 0 | BQ9: 0 | BR9: 0 | BS9: 0 | BT9: 0 | BU9: 0 | BV9: 0 | BW9: 0 | CV9: 0 | CW9: =ROUND(Y9*Source!I34*DO9,9) -> 0 | CX9: =ROUND(Y9*Source!I34,9) -> 23.4612 | CY9: =AB9 -> 1700.53 | CZ9: =AF9 -> 140.38 | DA9: =AJ9 -> 11.57 | DB9: =ROUND((ROUND(AT9*CZ9,2)*1.05),6) -> 17.6925 | DC9: =ROUND((ROUND(AT9*AG9,2)*1.05),6) -> 1.5855 | DF9: =ROUND(ROUND(AE9,2)*CX9,2) -> 0 | DG9: =ROUND(ROUND(AF9*AJ9,2)*CX9,2) -> 38105.68 | DH9: =ROUND(ROUND(AG9*AK9,2)*CX9,2) -> 10217.82 | DI9: =ROUND(ROUND(AH9,2)*CX9,2) -> 0 | DJ9: =DG9 -> 38105.68 | DK9: 0 | DM9: 0 | DO9: 0
A10: =ROW(Source!A34) -> 34 | B10: 57737055 | C10: 57737297 | D10: 47766703 | E10: 1 | F10: 1 | G10: 27786564 | H10: 2 | I10: 2.1-6-79 | J10: ТСН-2001.2. Доп. 68. п.1-6-79 (061105) | K10: Установки смесительные стационарные для приготовления бентонитового раствора, емкость до 4000 л | L10: 1368 | N10: 1011 | O10: маш.-ч | P10: маш.-ч | Q10: 1 | W10: 0 | X10: -1720189102 | Y10: =(AT10*1.05) -> 0.924 | AA10: 0 | AB10: 1282.93 | AC10: 611.71 | AD10: 0 | AE10: 0 | AF10: 80.14 | AG10: 16.93 | AH10: 0 | AI10: 1 | AJ10: 15.29 | AK10: 34.51 | AL10: 1 | AM10: 2 | AN10: 0 | AO10: 1 | AP10: 1 | AQ10: 0 | AR10: 0 | AT10: 0.88 | AU10: *1,05 | AV10: 0 | AW10: 2 | AX10: 57737318 | AY10: 1 | AZ10: 0 | BA10: 10 | BB10: 0 | BC10: 0 | BD10: 0 | BE10: 0 | BF10: 0 | BG10: 0 | BH10: 0 | BI10: 0 | BJ10: 0 | BK10: 0 | BL10: 0 | BM10: 0 | BN10: 0 | BO10: 0 | BP10: 0 | BQ10: 0 | BR10: 0 | BS10: 0 | BT10: 0 | BU10: 0 | BV10: 0 | BW10: 0 | CV10: 0 | CW10: =ROUND(Y10*Source!I34*DO10,9) -> 0 | CX10: =ROUND(Y10*Source!I34,9) -> 172.0488 | CY10: =AB10 -> 1282.93 | CZ10: =AF10 -> 80.14 | DA10: =AJ10 -> 15.29 | DB10: =ROUND((ROUND(AT10*CZ10,2)*1.05),6) -> 74.046 | DC10: =ROUND((ROUND(AT10*AG10,2)*1.05),6) -> 15.645 | DF10: =ROUND(ROUND(AE10,2)*CX10,2) -> 0 | DG10: =ROUND(ROUND(AF10*AJ10,2)*CX10,2) -> 210818.28 | DH10: =ROUND(ROUND(AG10*AK10,2)*CX10,2) -> 100519.51 | DI10: =ROUND(ROUND(AH10,2)*CX10,2) -> 0 | DJ10: =DG10 -> 210818.28 | DK10: 0 | DM10: 0 | DO10: 0
A11: =ROW(Source!A34) -> 34 | B11: 57737055 | C11: 57737297 | D11: 46723741 | E11: 1 | F11: 1 | G11: 27786564 | H11: 3 | I11: 1.1-1-1049 | J11: ТСН-2001.1 Доп. 67, Р. 1, о. 1, поз. 1049 | K11: Сода кальцинированная, техническая | L11: 1348 | N11: 1009 | O11: т | P11: т | Q11: 1000 | W11: 0 | X11: -301894024 | Y11: =AT11 -> 0.001505 | AA11: 24939.14 | AB11: 0 | AC11: 0 | AD11: 0 | AE11: 5778.3 | AF11: 0 | AG11: 0 | AH11: 0 | AI11: 4 | AJ11: 1 | AK11: 1 | AL11: 1 | AM11: 2 | AN11: 0 | AO11: 1 | AP11: 1 | AQ11: 0 | AR11: 0 | AT11: 0.001505 | AV11: 0 | AW11: 2 | AX11: 57737319 | AY11: 1 | AZ11: 0 | BA11: 11 | BB11: 0 | BC11: 0 | BD11: 0 | BE11: 0 | BF11: 0 | BG11: 0 | BH11: 0 | BI11: 0 | BJ11: 0 | BK11: 0 | BL11: 0 | BM11: 0 | BN11: 0 | BO11: 0 | BP11: 0 | BQ11: 0 | BR11: 0 | BS11: 0 | BT11: 0 | BU11: 0 | BV11: 0 | BW11: 0 | CV11: 0 | CW11: 0 | CX11: =ROUND(Y11*Source!I34,9) -> 0.280231 | CY11: =AA11 -> 24939.14 | CZ11: =AE11 -> 5778.3 | DA11: =AI11 -> 4 | DB11: =ROUND(ROUND(AT11*CZ11,2),6) -> 8.7 | DC11: =ROUND(ROUND(AT11*AG11,2),6) -> 0 | DF11: =ROUND(ROUND(AE11*AI11,2)*CX11,2) -> 6477.04 | DG11: =ROUND(ROUND(AF11,2)*CX11,2) -> 0 | DH11: =ROUND(ROUND(AG11,2)*CX11,2) -> 0 | DI11: =ROUND(ROUND(AH11,2)*CX11,2) -> 0 | DJ11: =DF11 -> 6477.04 | DK11: 0 | DM11: 0 | DO11: 0
A12: =ROW(Source!A34) -> 34 | B12: 57737055 | C12: 57737297 | D12: 30390465 | E12: 1 | F12: 1 | G12: 27786564 | H12: 3 | I12: 1.1-1-118 | J12: ТСН-2001.1. Доп. 1-42. Р. 1, о. 1, поз. 118 | K12: Вода | L12: 1339 | N12: 1007 | O12: м3 | P12: м3 | Q12: 1 | W12: 0 | X12: 1942501623 | Y12: =AT12 -> 1.9 | AA12: 53.78 | AB12: 0 | AC12: 0 | AD12: 0 | AE12: 7.07 | AF12: 0 | AG12: 0 | AH12: 0 | AI12: 7.05 | AJ12: 1 | AK12: 1 | AL12: 1 | AM12: 2 | AN12: 0 | AO12: 1 | AP12: 1 | AQ12: 0 | AR12: 0 | AT12: 1.9 | AV12: 0 | AW12: 2 | AX12: 57737320 | AY12: 1 | AZ12: 0 | BA12: 12 | BB12: 0 | BC12: 0 | BD12: 0 | BE12: 0 | BF12: 0 | BG12: 0 | BH12: 0 | BI12: 0 | BJ12: 0 | BK12: 0 | BL12: 0 | BM12: 0 | BN12: 0 | BO12: 0 | BP12: 0 | BQ12: 0 | BR12: 0 | BS12: 0 | BT12: 0 | BU12: 0 | BV12: 0 | BW12: 0 | CV12: 0 | CW12: 0 | CX12: =ROUND(Y12*Source!I34,9) -> 353.78 | CY12: =AA12 -> 53.78 | CZ12: =AE12 -> 7.07 | DA12: =AI12 -> 7.05 | DB12: =ROUND(ROUND(AT12*CZ12,2),6) -> 13.43 | DC12: =ROUND(ROUND(AT12*AG12,2),6) -> 0 | DF12: =ROUND(ROUND(AE12*AI12,2)*CX12,2) -> 17632.4 | DG12: =ROUND(ROUND(AF12,2)*CX12,2) -> 0 | DH12: =ROUND(ROUND(AG12,2)*CX12,2) -> 0 | DI12: =ROUND(ROUND(AH12,2)*CX12,2) -> 0 | DJ12: =DF12 -> 17632.4 | DK12: 0 | DM12: 0 | DO12: 0
A13: =ROW(Source!A34) -> 34 | B13: 57737055 | C13: 57737297 | D13: 32918763 | E13: 1 | F13: 1 | G13: 27786564 | H13: 3 | I13: 1.1-1-1835 | J13: ТСН-2001.1 Доп. 49, Р. 1, о. 1, поз. 1835 | K13: Бентонит натриевый тонкого помола с содержанием органических полимеров, для сгущения, увеличения объема и придания гелеобразующих свойств буровым растворам, укрепления, снижения просачивания воды в стенках каналов | L13: 1346 | N13: 1009 | O13: кг | P13: кг | Q13: 1 | W13: 0 | X13: -936542528 | Y13: =AT13 -> 116.8 | AA13: 55.72 | AB13: 0 | AC13: 0 | AD13: 0 | AE13: 11.3 | AF13: 0 | AG13: 0 | AH13: 0 | AI13: 4.57 | AJ13: 1 | AK13: 1 | AL13: 1 | AM13: 0 | AN13: 0 | AO13: 0 | AP13: 1 | AQ13: 0 | AR13: 0 | AT13: 116.8 | AV13: 0 | AW13: 1 | AX13: -1 | AY13: 0 | AZ13: 0 | BB13: 0 | BC13: 0 | BD13: 0 | BE13: 0 | BF13: 0 | BG13: 0 | BH13: 0 | BI13: 0 | BJ13: 0 | BK13: 0 | BL13: 0 | BM13: 0 | BN13: 0 | BO13: 0 | BP13: 0 | BQ13: 0 | BR13: 0 | BS13: 0 | BT13: 0 | BU13: 0 | BV13: 0 | BW13: 0 | CV13: 0 | CW13: 0 | CX13: =ROUND(Y13*Source!I34,9) -> 21748.16 | CY13: =AA13 -> 55.72 | CZ13: =AE13 -> 11.3 | DA13: =AI13 -> 4.57 | DB13: =ROUND(ROUND(AT13*CZ13,2),6) -> 1319.84 | DC13: =ROUND(ROUND(AT13*AG13,2),6) -> 0 | DF13: =ROUND(ROUND(AE13*AI13,2)*CX13,2) -> 1123075 | DG13: =ROUND(ROUND(AF13,2)*CX13,2) -> 0 | DH13: =ROUND(ROUND(AG13,2)*CX13,2) -> 0 | DI13: =ROUND(ROUND(AH13,2)*CX13,2) -> 0 | DJ13: =DF13 -> 1123075 | DK13: 0 | DM13: 0 | DO13: 0
A14: =ROW(Source!A34) -> 34 | B14: 57737055 | C14: 57737297 | D14: 47765707 | E14: 1 | F14: 1 | G14: 27786564 | H14: 3 | I14: 1.1-1-2948 | J14: ТСН-2001.1 Доп. 68, Р. 1, о. 1, поз. 2948 | K14: Смазка графитная | L14: 1346 | N14: 1009 | O14: кг | P14: кг | Q14: 1 | W14: 0 | X14: -1961732728 | Y14: =AT14 -> 0.0432 | AA14: 86.84 | AB14: 0 | AC14: 0 | AD14: 0 | AE14: 7.48 | AF14: 0 | AG14: 0 | AH14: 0 | AI14: 10.76 | AJ14: 1 | AK14: 1 | AL14: 1 | AM14: 2 | AN14: 0 | AO14: 1 | AP14: 1 | AQ14: 0 | AR14: 0 | AT14: 0.0432 | AV14: 0 | AW14: 2 | AX14: 57737321 | AY14: 1 | AZ14: 0 | BA14: 13 | BB14: 0 | BC14: 0 | BD14: 0 | BE14: 0 | BF14: 0 | BG14: 0 | BH14: 0 | BI14: 0 | BJ14: 0 | BK14: 0 | BL14: 0 | BM14: 0 | BN14: 0 | BO14: 0 | BP14: 0 | BQ14: 0 | BR14: 0 | BS14: 0 | BT14: 0 | BU14: 0 | BV14: 0 | BW14: 0 | CV14: 0 | CW14: 0 | CX14: =ROUND(Y14*Source!I34,9) -> 8.04384 | CY14: =AA14 -> 86.84 | CZ14: =AE14 -> 7.48 | DA14: =AI14 -> 10.76 | DB14: =ROUND(ROUND(AT14*CZ14,2),6) -> 0.32 | DC14: =ROUND(ROUND(AT14*AG14,2),6) -> 0 | DF14: =ROUND(ROUND(AE14*AI14,2)*CX14,2) -> 647.37 | DG14: =ROUND(ROUND(AF14,2)*CX14,2) -> 0 | DH14: =ROUND(ROUND(AG14,2)*CX14,2) -> 0 | DI14: =ROUND(ROUND(AH14,2)*CX14,2) -> 0 | DJ14: =DF14 -> 647.37 | DK14: 0 | DM14: 0 | DO14: 0
A15: =ROW(Source!A34) -> 34 | B15: 57737055 | C15: 57737297 | D15: 46724841 | E15: 1 | F15: 1 | G15: 27786564 | H15: 3 | I15: 1.1-1-3290 | J15: ТСН-2001.1 Доп. 67, Р. 1, о. 1, поз. 3290 | K15: Средство полимерное, жидкое, водородный показатель рН от 8,5 до 10,5, для кондиционирования грунтов при проходке тоннелей с использованием ТПМК с грунтопригрузом, улучшения рабочих характеристик пенных реагентов в сложных грунтовых условиях, модификации бентонитового раствора для ТПМК с гидропригрузом | L15: 1296 | N15: 1013 | O15: л | P15: л | Q15: 1 | W15: 0 | X15: 1548396739 | Y15: =AT15 -> 5.928 | AA15: 872.63 | AB15: 0 | AC15: 0 | AD15: 0 | AE15: 95.37 | AF15: 0 | AG15: 0 | AH15: 0 | AI15: 8.48 | AJ15: 1 | AK15: 1 | AL15: 1 | AM15: 0 | AN15: 0 | AO15: 0 | AP15: 1 | AQ15: 0 | AR15: 0 | AT15: 5.928 | AV15: 0 | AW15: 1 | AX15: -1 | AY15: 0 | AZ15: 0 | BB15: 0 | BC15: 0 | BD15: 0 | BE15: 0 | BF15: 0 | BG15: 0 | BH15: 0 | BI15: 0 | BJ15: 0 | BK15: 0 | BL15: 0 | BM15: 0 | BN15: 0 | BO15: 0 | BP15: 0 | BQ15: 0 | BR15: 0 | BS15: 0 | BT15: 0 | BU15: 0 | BV15: 0 | BW15: 0 | CV15: 0 | CW15: 0 | CX15: =ROUND(Y15*Source!I34,9) -> 1103.7936 | CY15: =AA15 -> 872.63 | CZ15: =AE15 -> 95.37 | DA15: =AI15 -> 8.48 | DB15: =ROUND(ROUND(AT15*CZ15,2),6) -> 565.35 | DC15: =ROUND(ROUND(AT15*AG15,2),6) -> 0 | DF15: =ROUND(ROUND(AE15*AI15,2)*CX15,2) -> 892682.04 | DG15: =ROUND(ROUND(AF15,2)*CX15,2) -> 0 | DH15: =ROUND(ROUND(AG15,2)*CX15,2) -> 0 | DI15: =ROUND(ROUND(AH15,2)*CX15,2) -> 0 | DJ15: =DF15 -> 892682.04 | DK15: 0 | DM15: 0 | DO15: 0
A16: =ROW(Source!A38) -> 38 | B16: 57737055 | C16: 57737328 | D16: 47634407 | E16: 27786564 | F16: 1 | G16: 27786564 | H16: 1 | I16: 9999990008 | K16: Трудозатраты рабочих | L16: 1191 | N16: 1013 | O16: чел.-ч. | P16: чел.-ч. | Q16: 1 | W16: 0 | X16: 476480486 | Y16: =(AT16*1.05) -> 0.63 | AA16: 0 | AB16: 0 | AC16: 0 | AD16: 0 | AE16: 0 | AF16: 0 | AG16: 0 | AH16: 0 | AI16: 1 | AJ16: 1 | AK16: 1 | AL16: 1 | AM16: -2 | AN16: 0 | AO16: 1 | AP16: 1 | AQ16: 0 | AR16: 0 | AT16: 0.6 | AU16: *1,05 | AV16: 1 | AW16: 2 | AX16: 57737332 | AY16: 1 | AZ16: 0 | BA16: 17 | BB16: 0 | BC16: 0 | BD16: 0 | BE16: 0 | BF16: 0 | BG16: 0 | BH16: 0 | BI16: 0 | BJ16: 0 | BK16: 0 | BL16: 0 | BM16: 0 | BN16: 0 | BO16: 0 | BP16: 0 | BQ16: 0 | BR16: 0 | BS16: 0 | BT16: 0 | BU16: 0 | BV16: 0 | BW16: 0 | CU16: =ROUND(AT16*Source!I38*AH16*AL16,2) -> 0 | CV16: =ROUND(Y16*Source!I38,9) -> 0.63 | CW16: 0 | CX16: =ROUND(Y16*Source!I38,9) -> 0.63 | CY16: =AD16 -> 0 | CZ16: =AH16 -> 0 | DA16: =AL16 -> 1 | DB16: =ROUND((ROUND(AT16*CZ16,2)*1.05),6) -> 0 | DC16: =ROUND((ROUND(AT16*AG16,2)*1.05),6) -> 0 | DF16: =ROUND(ROUND(AE16,2)*CX16,2) -> 0 | DG16: =ROUND(ROUND(AF16,2)*CX16,2) -> 0 | DH16: =ROUND(ROUND(AG16,2)*CX16,2) -> 0 | DI16: =ROUND(ROUND(AH16,2)*CX16,2) -> 0 | DJ16: =DI16 -> 0 | DK16: 0 | DM16: 0 | DO16: 0
A17: =ROW(Source!A38) -> 38 | B17: 57737055 | C17: 57737328 | D17: 47767072 | E17: 1 | F17: 1 | G17: 27786564 | H17: 2 | I17: 2.1-17-203 | J17: ТСН-2001.2. Доп. 68. п.1-17-203 (172706) | K17: Установки направленного бурения, тяговое усилие до 500 кН | L17: 1368 | N17: 1011 | O17: маш.-ч | P17: маш.-ч | Q17: 1 | W17: 0 | X17: -491204050 | Y17: =(AT17*1.05) -> 0.63 | AA17: 0 | AB17: 18064.39 | AC17: 1406.98 | AD17: 0 | AE17: 0 | AF17: 1843.32 | AG17: 38.94 | AH17: 0 | AI17: 1 | AJ17: 9.36 | AK17: 34.51 | AL17: 1 | AM17: 2 | AN17: 0 | AO17: 1 | AP17: 1 | AQ17: 0 | AR17: 0 | AT17: 0.6 | AU17: *1,05 | AV17: 0 | AW17: 2 | AX17: 57737333 | AY17: 1 | AZ17: 0 | BA17: 18 | BB17: 0 | BC17: 0 | BD17: 0 | BE17: 0 | BF17: 0 | BG17: 0 | BH17: 0 | BI17: 0 | BJ17: 0 | BK17: 0 | BL17: 0 | BM17: 0 | BN17: 0 | BO17: 0 | BP17: 0 | BQ17: 0 | BR17: 0 | BS17: 0 | BT17: 0 | BU17: 0 | BV17: 0 | BW17: 0 | CV17: 0 | CW17: =ROUND(Y17*Source!I38*DO17,9) -> 0 | CX17: =ROUND(Y17*Source!I38,9) -> 0.63 | CY17: =AB17 -> 18064.39 | CZ17: =AF17 -> 1843.32 | DA17: =AJ17 -> 9.36 | DB17: =ROUND((ROUND(AT17*CZ17,2)*1.05),6) -> 1161.2895 | DC17: =ROUND((ROUND(AT17*AG17,2)*1.05),6) -> 24.528 | DF17: =ROUND(ROUND(AE17,2)*CX17,2) -> 0 | DG17: =ROUND(ROUND(AF17*AJ17,2)*CX17,2) -> 10869.69 | DH17: =ROUND(ROUND(AG17*AK17,2)*CX17,2) -> 846.61 | DI17: =ROUND(ROUND(AH17,2)*CX17,2) -> 0 | DJ17: =DG17 -> 10869.69 | DK17: 0 | DM17: 0 | DO17: 0
A18: =ROW(Source!A38) -> 38 | B18: 57737055 | C18: 57737328 | D18: 47766748 | E18: 1 | F18: 1 | G18: 27786564 | H18: 2 | I18: 2.1-9-2 | J18: ТСН-2001.2. Доп. 68. п.1-9-2 (090201) | K18: Машины бурильно-крановые на базе автомобиля, глубина бурения до 5 м | L18: 1368 | N18: 1011 | O18: маш.-ч | P18: маш.-ч | Q18: 1 | W18: 0 | X18: 2120447496 | Y18: =(AT18*1.05) -> 0.609 | AA18: 0 | AB18: 2072.6 | AC18: 525.36 | AD18: 0 | AE18: 0 | AF18: 166.63 | AG18: 14.54 | AH18: 0 | AI18: 1 | AJ18: 11.88 | AK18: 34.51 | AL18: 1 | AM18: 2 | AN18: 0 | AO18: 1 | AP18: 1 | AQ18: 0 | AR18: 0 | AT18: 0.58 | AU18: *1,05 | AV18: 0 | AW18: 2 | AX18: 57737334 | AY18: 1 | AZ18: 0 | BA18: 19 | BB18: 0 | BC18: 0 | BD18: 0 | BE18: 0 | BF18: 0 | BG18: 0 | BH18: 0 | BI18: 0 | BJ18: 0 | BK18: 0 | BL18: 0 | BM18: 0 | BN18: 0 | BO18: 0 | BP18: 0 | BQ18: 0 | BR18: 0 | BS18: 0 | BT18: 0 | BU18: 0 | BV18: 0 | BW18: 0 | CV18: 0 | CW18: =ROUND(Y18*Source!I38*DO18,9) -> 0 | CX18: =ROUND(Y18*Source!I38,9) -> 0.609 | CY18: =AB18 -> 2072.6 | CZ18: =AF18 -> 166.63 | DA18: =AJ18 -> 11.88 | DB18: =ROUND((ROUND(AT18*CZ18,2)*1.05),6) -> 101.4825 | DC18: =ROUND((ROUND(AT18*AG18,2)*1.05),6) -> 8.8515 | DF18: =ROUND(ROUND(AE18,2)*CX18,2) -> 0 | DG18: =ROUND(ROUND(AF18*AJ18,2)*CX18,2) -> 1205.55 | DH18: =ROUND(ROUND(AG18*AK18,2)*CX18,2) -> 305.58 | DI18: =ROUND(ROUND(AH18,2)*CX18,2) -> 0 | DJ18: =DG18 -> 1205.55 | DK18: 0 | DM18: 0 | DO18: 0
A19: =ROW(Source!A39) -> 39 | B19: 57737055 | C19: 57737335 | D19: 47634407 | E19: 27786564 | F19: 1 | G19: 27786564 | H19: 1 | I19: 9999990008 | K19: Трудозатраты рабочих | L19: 1191 | N19: 1013 | O19: чел.-ч. | P19: чел.-ч. | Q19: 1 | W19: 0 | X19: 476480486 | Y19: =(AT19*1.05) -> 0.273 | AA19: 0 | AB19: 0 | AC19: 0 | AD19: 0 | AE19: 0 | AF19: 0 | AG19: 0 | AH19: 0 | AI19: 1 | AJ19: 1 | AK19: 1 | AL19: 1 | AM19: -2 | AN19: 0 | AO19: 1 | AP19: 1 | AQ19: 0 | AR19: 0 | AT19: 0.26 | AU19: *1,05 | AV19: 1 | AW19: 2 | AX19: 57737338 | AY19: 1 | AZ19: 0 | BA19: 20 | BB19: 0 | BC19: 0 | BD19: 0 | BE19: 0 | BF19: 0 | BG19: 0 | BH19: 0 | BI19: 0 | BJ19: 0 | BK19: 0 | BL19: 0 | BM19: 0 | BN19: 0 | BO19: 0 | BP19: 0 | BQ19: 0 | BR19: 0 | BS19: 0 | BT19: 0 | BU19: 0 | BV19: 0 | BW19: 0 | CU19: =ROUND(AT19*Source!I39*AH19*AL19,2) -> 0 | CV19: =ROUND(Y19*Source!I39,9) -> 0.546 | CW19: 0 | CX19: =ROUND(Y19*Source!I39,9) -> 0.546 | CY19: =AD19 -> 0 | CZ19: =AH19 -> 0 | DA19: =AL19 -> 1 | DB19: =ROUND((ROUND(AT19*CZ19,2)*1.05),6) -> 0 | DC19: =ROUND((ROUND(AT19*AG19,2)*1.05),6) -> 0 | DF19: =ROUND(ROUND(AE19,2)*CX19,2) -> 0 | DG19: =ROUND(ROUND(AF19,2)*CX19,2) -> 0 | DH19: =ROUND(ROUND(AG19,2)*CX19,2) -> 0 | DI19: =ROUND(ROUND(AH19,2)*CX19,2) -> 0 | DJ19: =DI19 -> 0 | DK19: 0 | DM19: 0 | DO19: 0
A20: =ROW(Source!A39) -> 39 | B20: 57737055 | C20: 57737335 | D20: 47767072 | E20: 1 | F20: 1 | G20: 27786564 | H20: 2 | I20: 2.1-17-203 | J20: ТСН-2001.2. Доп. 68. п.1-17-203 (172706) | K20: Установки направленного бурения, тяговое усилие до 500 кН | L20: 1368 | N20: 1011 | O20: маш.-ч | P20: маш.-ч | Q20: 1 | W20: 0 | X20: -491204050 | Y20: =(AT20*1.05) -> 0.273 | AA20: 0 | AB20: 18064.39 | AC20: 1406.98 | AD20: 0 | AE20: 0 | AF20: 1843.32 | AG20: 38.94 | AH20: 0 | AI20: 1 | AJ20: 9.36 | AK20: 34.51 | AL20: 1 | AM20: 2 | AN20: 0 | AO20: 1 | AP20: 1 | AQ20: 0 | AR20: 0 | AT20: 0.26 | AU20: *1,05 | AV20: 0 | AW20: 2 | AX20: 57737339 | AY20: 1 | AZ20: 0 | BA20: 21 | BB20: 0 | BC20: 0 | BD20: 0 | BE20: 0 | BF20: 0 | BG20: 0 | BH20: 0 | BI20: 0 | BJ20: 0 | BK20: 0 | BL20: 0 | BM20: 0 | BN20: 0 | BO20: 0 | BP20: 0 | BQ20: 0 | BR20: 0 | BS20: 0 | BT20: 0 | BU20: 0 | BV20: 0 | BW20: 0 | CV20: 0 | CW20: =ROUND(Y20*Source!I39*DO20,9) -> 0 | CX20: =ROUND(Y20*Source!I39,9) -> 0.546 | CY20: =AB20 -> 18064.39 | CZ20: =AF20 -> 1843.32 | DA20: =AJ20 -> 9.36 | DB20: =ROUND((ROUND(AT20*CZ20,2)*1.05),6) -> 503.223 | DC20: =ROUND((ROUND(AT20*AG20,2)*1.05),6) -> 10.626 | DF20: =ROUND(ROUND(AE20,2)*CX20,2) -> 0 | DG20: =ROUND(ROUND(AF20*AJ20,2)*CX20,2) -> 9420.4 | DH20: =ROUND(ROUND(AG20*AK20,2)*CX20,2) -> 733.73 | DI20: =ROUND(ROUND(AH20,2)*CX20,2) -> 0 | DJ20: =DG20 -> 9420.4 | DK20: 0 | DM20: 0 | DO20: 0
A21: =ROW(Source!A40) -> 40 | B21: 57737055 | C21: 57737340 | D21: 47634407 | E21: 27786564 | F21: 1 | G21: 27786564 | H21: 1 | I21: 9999990008 | K21: Трудозатраты рабочих | L21: 1191 | N21: 1013 | O21: чел.-ч. | P21: чел.-ч. | Q21: 1 | W21: 0 | X21: 476480486 | Y21: =(AT21*1.05) -> 1.2075 | AA21: 0 | AB21: 0 | AC21: 0 | AD21: 0 | AE21: 0 | AF21: 0 | AG21: 0 | AH21: 0 | AI21: 1 | AJ21: 1 | AK21: 1 | AL21: 1 | AM21: -2 | AN21: 0 | AO21: 1 | AP21: 1 | AQ21: 0 | AR21: 0 | AT21: 1.15 | AU21: *1,05 | AV21: 1 | AW21: 2 | AX21: 57737345 | AY21: 1 | AZ21: 0 | BA21: 22 | BB21: 0 | BC21: 0 | BD21: 0 | BE21: 0 | BF21: 0 | BG21: 0 | BH21: 0 | BI21: 0 | BJ21: 0 | BK21: 0 | BL21: 0 | BM21: 0 | BN21: 0 | BO21: 0 | BP21: 0 | BQ21: 0 | BR21: 0 | BS21: 0 | BT21: 0 | BU21: 0 | BV21: 0 | BW21: 0 | CU21: =ROUND(AT21*Source!I40*AH21*AL21,2) -> 0 | CV21: =ROUND(Y21*Source!I40,9) -> 59.1675 | CW21: 0 | CX21: =ROUND(Y21*Source!I40,9) -> 59.1675 | CY21: =AD21 -> 0 | CZ21: =AH21 -> 0 | DA21: =AL21 -> 1 | DB21: =ROUND((ROUND(AT21*CZ21,2)*1.05),6) -> 0 | DC21: =ROUND((ROUND(AT21*AG21,2)*1.05),6) -> 0 | DF21: =ROUND(ROUND(AE21,2)*CX21,2) -> 0 | DG21: =ROUND(ROUND(AF21,2)*CX21,2) -> 0 | DH21: =ROUND(ROUND(AG21,2)*CX21,2) -> 0 | DI21: =ROUND(ROUND(AH21,2)*CX21,2) -> 0 | DJ21: =DI21 -> 0 | DK21: 0 | DM21: 0 | DO21: 0
A22: =ROW(Source!A40) -> 40 | B22: 57737055 | C22: 57737340 | D22: 47766881 | E22: 1 | F22: 1 | G22: 27786564 | H22: 2 | I22: 2.1-13-40 | J22: ТСН-2001.2. Доп. 68. п.1-13-40 (135505) | K22: Аппараты для стыковой сварки труб из термопластов диаметром от 40 до 160 мм | L22: 1368 | N22: 1011 | O22: маш.-ч | P22: маш.-ч | Q22: 1 | W22: 0 | X22: 1322430240 | Y22: =(AT22*1.05) -> 0.588 | AA22: 0 | AB22: 37.95 | AC22: 0 | AD22: 0 | AE22: 0 | AF22: 4.01 | AG22: 0 | AH22: 0 | AI22: 1 | AJ22: 8.87 | AK22: 34.51 | AL22: 1 | AM22: 2 | AN22: 0 | AO22: 1 | AP22: 1 | AQ22: 0 | AR22: 0 | AT22: 0.56 | AU22: *1,05 | AV22: 0 | AW22: 2 | AX22: 57737346 | AY22: 1 | AZ22: 0 | BA22: 23 | BB22: 0 | BC22: 0 | BD22: 0 | BE22: 0 | BF22: 0 | BG22: 0 | BH22: 0 | BI22: 0 | BJ22: 0 | BK22: 0 | BL22: 0 | BM22: 0 | BN22: 0 | BO22: 0 | BP22: 0 | BQ22: 0 | BR22: 0 | BS22: 0 | BT22: 0 | BU22: 0 | BV22: 0 | BW22: 0 | CV22: 0 | CW22: =ROUND(Y22*Source!I40*DO22,9) -> 0 | CX22: =ROUND(Y22*Source!I40,9) -> 28.812 | CY22: =AB22 -> 37.95 | CZ22: =AF22 -> 4.01 | DA22: =AJ22 -> 8.87 | DB22: =ROUND((ROUND(AT22*CZ22,2)*1.05),6) -> 2.3625 | DC22: =ROUND((ROUND(AT22*AG22,2)*1.05),6) -> 0 | DF22: =ROUND(ROUND(AE22,2)*CX22,2) -> 0 | DG22: =ROUND(ROUND(AF22*AJ22,2)*CX22,2) -> 1024.84 | DH22: =ROUND(ROUND(AG22*AK22,2)*CX22,2) -> 0 | DI22: =ROUND(ROUND(AH22,2)*CX22,2) -> 0 | DJ22: =DG22 -> 1024.84 | DK22: 0 | DM22: 0 | DO22: 0
A23: =ROW(Source!A40) -> 40 | B23: 57737055 | C23: 57737340 | D23: 44217275 | E23: 1 | F23: 1 | G23: 27786564 | H23: 3 | I23: 1.1-1-1064 | J23: ТСН-2001.1 Доп. 65, Р. 1, о. 1, поз. 1064 | K23: Спирт этиловый технический | L23: 1346 | N23: 1009 | O23: кг | P23: кг | Q23: 1 | W23: 0 | X23: 404283604 | Y23: =AT23 -> 0.0667 | AA23: 1359.47 | AB23: 0 | AC23: 0 | AD23: 0 | AE23: 11.25 | AF23: 0 | AG23: 0 | AH23: 0 | AI23: 120.48 | AJ23: 1 | AK23: 1 | AL23: 1 | AM23: 2 | AN23: 0 | AO23: 1 | AP23: 1 | AQ23: 0 | AR23: 0 | AT23: 0.0667 | AV23: 0 | AW23: 2 | AX23: 57737347 | AY23: 1 | AZ23: 0 | BA23: 24 | BB23: 0 | BC23: 0 | BD23: 0 | BE23: 0 | BF23: 0 | BG23: 0 | BH23: 0 | BI23: 0 | BJ23: 0 | BK23: 0 | BL23: 0 | BM23: 0 | BN23: 0 | BO23: 0 | BP23: 0 | BQ23: 0 | BR23: 0 | BS23: 0 | BT23: 0 | BU23: 0 | BV23: 0 | BW23: 0 | CV23: 0 | CW23: 0 | CX23: =ROUND(Y23*Source!I40,9) -> 3.2683 | CY23: =AA23 -> 1359.47 | CZ23: =AE23 -> 11.25 | DA23: =AI23 -> 120.48 | DB23: =ROUND(ROUND(AT23*CZ23,2),6) -> 0.75 | DC23: =ROUND(ROUND(AT23*AG23,2),6) -> 0 | DF23: =ROUND(ROUND(AE23*AI23,2)*CX23,2) -> 4429.85 | DG23: =ROUND(ROUND(AF23,2)*CX23,2) -> 0 | DH23: =ROUND(ROUND(AG23,2)*CX23,2) -> 0 | DI23: =ROUND(ROUND(AH23,2)*CX23,2) -> 0 | DJ23: =DF23 -> 4429.85 | DK23: 0 | DM23: 0 | DO23: 0
A24: =ROW(Source!A40) -> 40 | B24: 57737055 | C24: 57737340 | D24: 30390462 | E24: 1 | F24: 1 | G24: 27786564 | H24: 3 | I24: 1.1-1-115 | J24: ТСН-2001.1. Доп. 1-42. Р. 1, о. 1, поз. 115 | K24: Ветошь | L24: 1346 | N24: 1009 | O24: кг | P24: кг | Q24: 1 | W24: 0 | X24: -1299596119 | Y24: =AT24 -> 0.1 | AA24: 53.77 | AB24: 0 | AC24: 0 | AD24: 0 | AE24: 1.61 | AF24: 0 | AG24: 0 | AH24: 0 | AI24: 33.3 | AJ24: 1 | AK24: 1 | AL24: 1 | AM24: 2 | AN24: 0 | AO24: 1 | AP24: 1 | AQ24: 0 | AR24: 0 | AT24: 0.1 | AV24: 0 | AW24: 2 | AX24: 57737348 | AY24: 1 | AZ24: 0 | BA24: 25 | BB24: 0 | BC24: 0 | BD24: 0 | BE24: 0 | BF24: 0 | BG24: 0 | BH24: 0 | BI24: 0 | BJ24: 0 | BK24: 0 | BL24: 0 | BM24: 0 | BN24: 0 | BO24: 0 | BP24: 0 | BQ24: 0 | BR24: 0 | BS24: 0 | BT24: 0 | BU24: 0 | BV24: 0 | BW24: 0 | CV24: 0 | CW24: 0 | CX24: =ROUND(Y24*Source!I40,9) -> 4.9 | CY24: =AA24 -> 53.77 | CZ24: =AE24 -> 1.61 | DA24: =AI24 -> 33.3 | DB24: =ROUND(ROUND(AT24*CZ24,2),6) -> 0.16 | DC24: =ROUND(ROUND(AT24*AG24,2),6) -> 0 | DF24: =ROUND(ROUND(AE24*AI24,2)*CX24,2) -> 262.69 | DG24: =ROUND(ROUND(AF24,2)*CX24,2) -> 0 | DH24: =ROUND(ROUND(AG24,2)*CX24,2) -> 0 | DI24: =ROUND(ROUND(AH24,2)*CX24,2) -> 0 | DJ24: =DF24 -> 262.69 | DK24: 0 | DM24: 0 | DO24: 0
A25: =ROW(Source!A41) -> 41 | B25: 57737055 | C25: 57737349 | D25: 47634407 | E25: 27786564 | F25: 1 | G25: 27786564 | H25: 1 | I25: 9999990008 | K25: Трудозатраты рабочих | L25: 1191 | N25: 1013 | O25: чел.-ч. | P25: чел.-ч. | Q25: 1 | W25: 0 | X25: 476480486 | Y25: =(AT25*1.05) -> 0.105 | AA25: 0 | AB25: 0 | AC25: 0 | AD25: 0 | AE25: 0 | AF25: 0 | AG25: 0 | AH25: 0 | AI25: 1 | AJ25: 1 | AK25: 1 | AL25: 1 | AM25: -2 | AN25: 0 | AO25: 1 | AP25: 1 | AQ25: 0 | AR25: 0 | AT25: 0.1 | AU25: *1,05 | AV25: 1 | AW25: 2 | AX25: 57737351 | AY25: 1 | AZ25: 0 | BA25: 26 | BB25: 0 | BC25: 0 | BD25: 0 | BE25: 0 | BF25: 0 | BG25: 0 | BH25: 0 | BI25: 0 | BJ25: 0 | BK25: 0 | BL25: 0 | BM25: 0 | BN25: 0 | BO25: 0 | BP25: 0 | BQ25: 0 | BR25: 0 | BS25: 0 | BT25: 0 | BU25: 0 | BV25: 0 | BW25: 0 | CU25: =ROUND(AT25*Source!I41*AH25*AL25,2) -> 0 | CV25: =ROUND(Y25*Source!I41,9) -> 0.42 | CW25: 0 | CX25: =ROUND(Y25*Source!I41,9) -> 0.42 | CY25: =AD25 -> 0 | CZ25: =AH25 -> 0 | DA25: =AL25 -> 1 | DB25: =ROUND((ROUND(AT25*CZ25,2)*1.05),6) -> 0 | DC25: =ROUND((ROUND(AT25*AG25,2)*1.05),6) -> 0 | DF25: =ROUND(ROUND(AE25,2)*CX25,2) -> 0 | DG25: =ROUND(ROUND(AF25,2)*CX25,2) -> 0 | DH25: =ROUND(ROUND(AG25,2)*CX25,2) -> 0 | DI25: =ROUND(ROUND(AH25,2)*CX25,2) -> 0 | DJ25: =DI25 -> 0 | DK25: 0 | DM25: 0 | DO25: 0
A26: =ROW(Source!A78) -> 78 | B26: 57737055 | C26: 57737353 | D26: 47634407 | E26: 27786564 | F26: 1 | G26: 27786564 | H26: 1 | I26: 9999990008 | K26: Трудозатраты рабочих | L26: 1191 | N26: 1013 | O26: чел.-ч. | P26: чел.-ч. | Q26: 1 | W26: 0 | X26: 476480486 | Y26: =(AT26*1.05) -> 16.59 | AA26: 0 | AB26: 0 | AC26: 0 | AD26: 0 | AE26: 0 | AF26: 0 | AG26: 0 | AH26: 0 | AI26: 1 | AJ26: 1 | AK26: 1 | AL26: 1 | AM26: -2 | AN26: 0 | AO26: 1 | AP26: 1 | AQ26: 0 | AR26: 0 | AT26: 15.8 | AU26: *1,05 | AV26: 1 | AW26: 2 | AX26: 57737366 | AY26: 1 | AZ26: 0 | BA26: 27 | BB26: 0 | BC26: 0 | BD26: 0 | BE26: 0 | BF26: 0 | BG26: 0 | BH26: 0 | BI26: 0 | BJ26: 0 | BK26: 0 | BL26: 0 | BM26: 0 | BN26: 0 | BO26: 0 | BP26: 0 | BQ26: 0 | BR26: 0 | BS26: 0 | BT26: 0 | BU26: 0 | BV26: 0 | BW26: 0 | CU26: =ROUND(AT26*Source!I78*AH26*AL26,2) -> 0 | CV26: =ROUND(Y26*Source!I78,9) -> 218.66449 | CW26: 0 | CX26: =ROUND(Y26*Source!I78,9) -> 218.66449 | CY26: =AD26 -> 0 | CZ26: =AH26 -> 0 | DA26: =AL26 -> 1 | DB26: =ROUND((ROUND(AT26*CZ26,2)*1.05),6) -> 0 | DC26: =ROUND((ROUND(AT26*AG26,2)*1.05),6) -> 0 | DF26: =ROUND(ROUND(AE26,2)*CX26,2) -> 0 | DG26: =ROUND(ROUND(AF26,2)*CX26,2) -> 0 | DH26: =ROUND(ROUND(AG26,2)*CX26,2) -> 0 | DI26: =ROUND(ROUND(AH26,2)*CX26,2) -> 0 | DJ26: =DI26 -> 0 | DK26: 0 | DM26: 0 | DO26: 0
A27: =ROW(Source!A78) -> 78 | B27: 57737055 | C27: 57737353 | D27: 47767106 | E27: 1 | F27: 1 | G27: 27786564 | H27: 2 | I27: 2.1-18-7 | J27: ТСН-2001.2. Доп. 68. п.1-18-7 (183001) | K27: Автомобили грузовые бортовые, грузоподъемность до 5 т | L27: 1368 | N27: 1011 | O27: маш.-ч | P27: маш.-ч | Q27: 1 | W27: 0 | X27: -7781208 | Y27: =(AT27*1.05) -> 0.5355 | AA27: 0 | AB27: 1140.27 | AC27: 464.7 | AD27: 0 | AE27: 0 | AF27: 83.1 | AG27: 12.62 | AH27: 0 | AI27: 1 | AJ27: 12.86 | AK27: 34.51 | AL27: 1 | AM27: 2 | AN27: 0 | AO27: 1 | AP27: 1 | AQ27: 0 | AR27: 0 | AT27: 0.51 | AU27: *1,05 | AV27: 0 | AW27: 2 | AX27: 57737367 | AY27: 1 | AZ27: 0 | BA27: 28 | BB27: 0 | BC27: 0 | BD27: 0 | BE27: 0 | BF27: 0 | BG27: 0 | BH27: 0 | BI27: 0 | BJ27: 0 | BK27: 0 | BL27: 0 | BM27: 0 | BN27: 0 | BO27: 0 | BP27: 0 | BQ27: 0 | BR27: 0 | BS27: 0 | BT27: 0 | BU27: 0 | BV27: 0 | BW27: 0 | CV27: 0 | CW27: =ROUND(Y27*Source!I78*DO27,9) -> 0 | CX27: =ROUND(Y27*Source!I78,9) -> 7.0581578 | CY27: =AB27 -> 1140.27 | CZ27: =AF27 -> 83.1 | DA27: =AJ27 -> 12.86 | DB27: =ROUND((ROUND(AT27*CZ27,2)*1.05),6) -> 44.499 | DC27: =ROUND((ROUND(AT27*AG27,2)*1.05),6) -> 6.762 | DF27: =ROUND(ROUND(AE27,2)*CX27,2) -> 0 | DG27: =ROUND(ROUND(AF27*AJ27,2)*CX27,2) -> 7542.84 | DH27: =ROUND(ROUND(AG27*AK27,2)*CX27,2) -> 3073.97 | DI27: =ROUND(ROUND(AH27,2)*CX27,2) -> 0 | DJ27: =DG27 -> 7542.84 | DK27: 0 | DM27: 0 | DO27: 0
A28: =ROW(Source!A78) -> 78 | B28: 57737055 | C28: 57737353 | D28: 47766535 | E28: 1 | F28: 1 | G28: 27786564 | H28: 2 | I28: 2.1-4-31 | J28: ТСН-2001.2. Доп. 68. п.1-4-31 (042903) | K28: Лебедки электрические, тяговое усилие до 14,71 кН (1,5 тс) | L28: 1368 | N28: 1011 | O28: маш.-ч | P28: маш.-ч | Q28: 1 | W28: 0 | X28: -1386352920 | Y28: =(AT28*1.05) -> 3.5805 | AA28: 0 | AB28: 21.34 | AC28: 0 | AD28: 0 | AE28: 0 | AF28: 2.27 | AG28: 0 | AH28: 0 | AI28: 1 | AJ28: 8.81 | AK28: 34.51 | AL28: 1 | AM28: 2 | AN28: 0 | AO28: 1 | AP28: 1 | AQ28: 0 | AR28: 0 | AT28: 3.41 | AU28: *1,05 | AV28: 0 | AW28: 2 | AX28: 57737368 | AY28: 1 | AZ28: 0 | BA28: 29 | BB28: 0 | BC28: 0 | BD28: 0 | BE28: 0 | BF28: 0 | BG28: 0 | BH28: 0 | BI28: 0 | BJ28: 0 | BK28: 0 | BL28: 0 | BM28: 0 | BN28: 0 | BO28: 0 | BP28: 0 | BQ28: 0 | BR28: 0 | BS28: 0 | BT28: 0 | BU28: 0 | BV28: 0 | BW28: 0 | CV28: 0 | CW28: =ROUND(Y28*Source!I78*DO28,9) -> 0 | CX28: =ROUND(Y28*Source!I78,9) -> 47.19278 | CY28: =AB28 -> 21.34 | CZ28: =AF28 -> 2.27 | DA28: =AJ28 -> 8.81 | DB28: =ROUND((ROUND(AT28*CZ28,2)*1.05),6) -> 8.127 | DC28: =ROUND((ROUND(AT28*AG28,2)*1.05),6) -> 0 | DF28: =ROUND(ROUND(AE28,2)*CX28,2) -> 0 | DG28: =ROUND(ROUND(AF28*AJ28,2)*CX28,2) -> 943.86 | DH28: =ROUND(ROUND(AG28*AK28,2)*CX28,2) -> 0 | DI28: =ROUND(ROUND(AH28,2)*CX28,2) -> 0 | DJ28: =DG28 -> 943.86 | DK28: 0 | DM28: 0 | DO28: 0
A29: =ROW(Source!A78) -> 78 | B29: 57737055 | C29: 57737353 | D29: 47766545 | E29: 1 | F29: 1 | G29: 27786564 | H29: 2 | I29: 2.1-4-45 | J29: ТСН-2001.2. Доп. 68. п.1-4-45 (043403) | K29: Домкраты гидравлические, грузоподъемность до 100 т | L29: 1368 | N29: 1011 | O29: маш.-ч | P29: маш.-ч | Q29: 1 | W29: 0 | X29: 1766156404 | Y29: =(AT29*1.05) -> 3.8535 | AA29: 0 | AB29: 6.51 | AC29: 0 | AD29: 0 | AE29: 0 | AF29: 0.73 | AG29: 0 | AH29: 0 | AI29: 1 | AJ29: 8.36 | AK29: 34.51 | AL29: 1 | AM29: 2 | AN29: 0 | AO29: 1 | AP29: 1 | AQ29: 0 | AR29: 0 | AT29: 3.67 | AU29: *1,05 | AV29: 0 | AW29: 2 | AX29: 57737369 | AY29: 1 | AZ29: 0 | BA29: 30 | BB29: 0 | BC29: 0 | BD29: 0 | BE29: 0 | BF29: 0 | BG29: 0 | BH29: 0 | BI29: 0 | BJ29: 0 | BK29: 0 | BL29: 0 | BM29: 0 | BN29: 0 | BO29: 0 | BP29: 0 | BQ29: 0 | BR29: 0 | BS29: 0 | BT29: 0 | BU29: 0 | BV29: 0 | BW29: 0 | CV29: 0 | CW29: =ROUND(Y29*Source!I78*DO29,9) -> 0 | CX29: =ROUND(Y29*Source!I78,9) -> 50.791057 | CY29: =AB29 -> 6.51 | CZ29: =AF29 -> 0.73 | DA29: =AJ29 -> 8.36 | DB29: =ROUND((ROUND(AT29*CZ29,2)*1.05),6) -> 2.814 | DC29: =ROUND((ROUND(AT29*AG29,2)*1.05),6) -> 0 | DF29: =ROUND(ROUND(AE29,2)*CX29,2) -> 0 | DG29: =ROUND(ROUND(AF29*AJ29,2)*CX29,2) -> 309.83 | DH29: =ROUND(ROUND(AG29*AK29,2)*CX29,2) -> 0 | DI29: =ROUND(ROUND(AH29,2)*CX29,2) -> 0 | DJ29: =DG29 -> 309.83 | DK29: 0 | DM29: 0 | DO29: 0
A30: =ROW(Source!A78) -> 78 | B30: 57737055 | C30: 57737353 | D30: 46723498 | E30: 1 | F30: 1 | G30: 27786564 | H30: 3 | I30: 1.1-1-491 | J30: ТСН-2001.1 Доп. 67, Р. 1, о. 1, поз. 491 | K30: Лак битумный, типа БТ-123 | L30: 1348 | N30: 1009 | O30: т | P30: т | Q30: 1000 | W30: 0 | X30: 975641442 | Y30: =AT30 -> 6e-05 | AA30: 83856.09 | AB30: 0 | AC30: 0 | AD30: 0 | AE30: 11242.42 | AF30: 0 | AG30: 0 | AH30: 0 | AI30: 6.9 | AJ30: 1 | AK30: 1 | AL30: 1 | AM30: 2 | AN30: 0 | AO30: 1 | AP30: 1 | AQ30: 0 | AR30: 0 | AT30: 6e-05 | AV30: 0 | AW30: 2 | AX30: 57737370 | AY30: 1 | AZ30: 0 | BA30: 31 | BB30: 0 | BC30: 0 | BD30: 0 | BE30: 0 | BF30: 0 | BG30: 0 | BH30: 0 | BI30: 0 | BJ30: 0 | BK30: 0 | BL30: 0 | BM30: 0 | BN30: 0 | BO30: 0 | BP30: 0 | BQ30: 0 | BR30: 0 | BS30: 0 | BT30: 0 | BU30: 0 | BV30: 0 | BW30: 0 | CV30: 0 | CW30: 0 | CX30: =ROUND(Y30*Source!I78,9) -> 0.00079083 | CY30: =AA30 -> 83856.09 | CZ30: =AE30 -> 11242.42 | DA30: =AI30 -> 6.9 | DB30: =ROUND(ROUND(AT30*CZ30,2),6) -> 0.67 | DC30: =ROUND(ROUND(AT30*AG30,2),6) -> 0 | DF30: =ROUND(ROUND(AE30*AI30,2)*CX30,2) -> 61.35 | DG30: =ROUND(ROUND(AF30,2)*CX30,2) -> 0 | DH30: =ROUND(ROUND(AG30,2)*CX30,2) -> 0 | DI30: =ROUND(ROUND(AH30,2)*CX30,2) -> 0 | DJ30: =DF30 -> 61.35 | DK30: 0 | DM30: 0 | DO30: 0
A31: =ROW(Source!A78) -> 78 | B31: 57737055 | C31: 57737353 | D31: 45796980 | E31: 1 | F31: 1 | G31: 27786564 | H31: 3 | I31: 1.1-1-8031 | J31: ТСН-2001.1 Доп. 66, Р. 1, о. 1, поз. 8031 | K31: Роль свинцовая, марка С1, толщина от 1 до 1,5 мм | L31: 1346 | N31: 1009 | O31: кг | P31: кг | Q31: 1 | W31: 0 | X31: 1533725368 | Y31: =AT31 -> 0.8 | AA31: 211.96 | AB31: 0 | AC31: 0 | AD31: 0 | AE31: 25.8 | AF31: 0 | AG31: 0 | AH31: 0 | AI31: 7.6 | AJ31: 1 | AK31: 1 | AL31: 1 | AM31: 2 | AN31: 0 | AO31: 1 | AP31: 1 | AQ31: 0 | AR31: 0 | AT31: 0.8 | AV31: 0 | AW31: 2 | AX31: 57737371 | AY31: 1 | AZ31: 0 | BA31: 32 | BB31: 0 | BC31: 0 | BD31: 0 | BE31: 0 | BF31: 0 | BG31: 0 | BH31: 0 | BI31: 0 | BJ31: 0 | BK31: 0 | BL31: 0 | BM31: 0 | BN31: 0 | BO31: 0 | BP31: 0 | BQ31: 0 | BR31: 0 | BS31: 0 | BT31: 0 | BU31: 0 | BV31: 0 | BW31: 0 | CV31: 0 | CW31: 0 | CX31: =ROUND(Y31*Source!I78,9) -> 10.5444 | CY31: =AA31 -> 211.96 | CZ31: =AE31 -> 25.8 | DA31: =AI31 -> 7.6 | DB31: =ROUND(ROUND(AT31*CZ31,2),6) -> 20.64 | DC31: =ROUND(ROUND(AT31*AG31,2),6) -> 0 | DF31: =ROUND(ROUND(AE31*AI31,2)*CX31,2) -> 2067.55 | DG31: =ROUND(ROUND(AF31,2)*CX31,2) -> 0 | DH31: =ROUND(ROUND(AG31,2)*CX31,2) -> 0 | DI31: =ROUND(ROUND(AH31,2)*CX31,2) -> 0 | DJ31: =DF31 -> 2067.55 | DK31: 0 | DM31: 0 | DO31: 0
A32: =ROW(Source!A78) -> 78 | B32: 57737055 | C32: 57737353 | D32: 46723689 | E32: 1 | F32: 1 | G32: 27786564 | H32: 3 | I32: 1.1-1-944 | J32: ТСН-2001.1 Доп. 67, Р. 1, о. 1, поз. 944 | K32: Припой оловянно-свинцовый, в прутках, диаметр 8 мм, типа ПОС-30 | L32: 1348 | N32: 1009 | O32: т | P32: т | Q32: 1000 | W32: 0 | X32: -1817633629 | Y32: =AT32 -> 0.0005 | AA32: 1617949.2 | AB32: 0 | AC32: 0 | AD32: 0 | AE32: 60966 | AF32: 0 | AG32: 0 | AH32: 0 | AI32: 24.55 | AJ32: 1 | AK32: 1 | AL32: 1 | AM32: 2 | AN32: 0 | AO32: 1 | AP32: 1 | AQ32: 0 | AR32: 0 | AT32: 0.0005 | AV32: 0 | AW32: 2 | AX32: 57737372 | AY32: 1 | AZ32: 0 | BA32: 33 | BB32: 0 | BC32: 0 | BD32: 0 | BE32: 0 | BF32: 0 | BG32: 0 | BH32: 0 | BI32: 0 | BJ32: 0 | BK32: 0 | BL32: 0 | BM32: 0 | BN32: 0 | BO32: 0 | BP32: 0 | BQ32: 0 | BR32: 0 | BS32: 0 | BT32: 0 | BU32: 0 | BV32: 0 | BW32: 0 | CV32: 0 | CW32: 0 | CX32: =ROUND(Y32*Source!I78,9) -> 0.00659025 | CY32: =AA32 -> 1617949.2 | CZ32: =AE32 -> 60966 | DA32: =AI32 -> 24.55 | DB32: =ROUND(ROUND(AT32*CZ32,2),6) -> 30.48 | DC32: =ROUND(ROUND(AT32*AG32,2),6) -> 0 | DF32: =ROUND(ROUND(AE32*AI32,2)*CX32,2) -> 9863.73 | DG32: =ROUND(ROUND(AF32,2)*CX32,2) -> 0 | DH32: =ROUND(ROUND(AG32,2)*CX32,2) -> 0 | DI32: =ROUND(ROUND(AH32,2)*CX32,2) -> 0 | DJ32: =DF32 -> 9863.73 | DK32: 0 | DM32: 0 | DO32: 0
A33: =ROW(Source!A78) -> 78 | B33: 57737055 | C33: 57737353 | D33: 46723704 | E33: 1 | F33: 1 | G33: 27786564 | H33: 3 | I33: 1.1-1-967 | J33: ТСН-2001.1 Доп. 67, Р. 1, о. 1, поз. 967 | K33: Проволока стальная низкоуглеродистая общего назначения оцинкованная, диаметр от 1,6 до 3,0 мм | L33: 1348 | N33: 1009 | O33: т | P33: т | Q33: 1000 | W33: 0 | X33: 1862018911 | Y33: =AT33 -> 4e-05 | AA33: 94661.04 | AB33: 0 | AC33: 0 | AD33: 0 | AE33: 7982.5 | AF33: 0 | AG33: 0 | AH33: 0 | AI33: 10.97 | AJ33: 1 | AK33: 1 | AL33: 1 | AM33: 2 | AN33: 0 | AO33: 1 | AP33: 1 | AQ33: 0 | AR33: 0 | AT33: 4e-05 | AV33: 0 | AW33: 2 | AX33: 57737373 | AY33: 1 | AZ33: 0 | BA33: 34 | BB33: 0 | BC33: 0 | BD33: 0 | BE33: 0 | BF33: 0 | BG33: 0 | BH33: 0 | BI33: 0 | BJ33: 0 | BK33: 0 | BL33: 0 | BM33: 0 | BN33: 0 | BO33: 0 | BP33: 0 | BQ33: 0 | BR33: 0 | BS33: 0 | BT33: 0 | BU33: 0 | BV33: 0 | BW33: 0 | CV33: 0 | CW33: 0 | CX33: =ROUND(Y33*Source!I78,9) -> 0.00052722 | CY33: =AA33 -> 94661.04 | CZ33: =AE33 -> 7982.5 | DA33: =AI33 -> 10.97 | DB33: =ROUND(ROUND(AT33*CZ33,2),6) -> 0.32 | DC33: =ROUND(ROUND(AT33*AG33,2),6) -> 0 | DF33: =ROUND(ROUND(AE33*AI33,2)*CX33,2) -> 46.17 | DG33: =ROUND(ROUND(AF33,2)*CX33,2) -> 0 | DH33: =ROUND(ROUND(AG33,2)*CX33,2) -> 0 | DI33: =ROUND(ROUND(AH33,2)*CX33,2) -> 0 | DJ33: =DF33 -> 46.17 | DK33: 0 | DM33: 0 | DO33: 0
A34: =ROW(Source!A78) -> 78 | B34: 57737055 | C34: 57737353 | D34: 52048144 | E34: 1 | F34: 1 | G34: 27786564 | H34: 3 | I34: 1.21-5-1180 | J34: ТСН-2001.1 Доп. 73, Р. 21, о. 5, поз. 1180 | K34: Бирка маркировочная для кабелей и проводов, типа У134 У3,5 | L34: 1356 | N34: 1010 | O34: 1000 шт. | P34: 1000 шт. | Q34: 1000 | W34: 0 | X34: 1183006993 | Y34: =AT34 -> 0.00041 | AA34: 1470.25 | AB34: 0 | AC34: 0 | AD34: 0 | AE34: 226.68 | AF34: 0 | AG34: 0 | AH34: 0 | AI34: 6 | AJ34: 1 | AK34: 1 | AL34: 1 | AM34: 2 | AN34: 0 | AO34: 1 | AP34: 1 | AQ34: 0 | AR34: 0 | AT34: 0.00041 | AV34: 0 | AW34: 2 | AX34: 57737374 | AY34: 1 | AZ34: 0 | BA34: 35 | BB34: 0 | BC34: 0 | BD34: 0 | BE34: 0 | BF34: 0 | BG34: 0 | BH34: 0 | BI34: 0 | BJ34: 0 | BK34: 0 | BL34: 0 | BM34: 0 | BN34: 0 | BO34: 0 | BP34: 0 | BQ34: 0 | BR34: 0 | BS34: 0 | BT34: 0 | BU34: 0 | BV34: 0 | BW34: 0 | CV34: 0 | CW34: 0 | CX34: =ROUND(Y34*Source!I78,9) -> 0.005404005 | CY34: =AA34 -> 1470.25 | CZ34: =AE34 -> 226.68 | DA34: =AI34 -> 6 | DB34: =ROUND(ROUND(AT34*CZ34,2),6) -> 0.09 | DC34: =ROUND(ROUND(AT34*AG34,2),6) -> 0 | DF34: =ROUND(ROUND(AE34*AI34,2)*CX34,2) -> 7.35 | DG34: =ROUND(ROUND(AF34,2)*CX34,2) -> 0 | DH34: =ROUND(ROUND(AG34,2)*CX34,2) -> 0 | DI34: =ROUND(ROUND(AH34,2)*CX34,2) -> 0 | DJ34: =DF34 -> 7.35 | DK34: 0 | DM34: 0 | DO34: 0
A35: =ROW(Source!A78) -> 78 | B35: 57737055 | C35: 57737353 | D35: 46735506 | E35: 1 | F35: 1 | G35: 27786564 | H35: 3 | I35: 1.21-5-798 | J35: ТСН-2001.1 Доп. 67, Р. 21, о. 5, поз. 798 | K35: Лента монтажная, типа ЛМ-5 | L35: 1301 | N35: 1003 | O35: м | P35: м | Q35: 1 | W35: 0 | X35: 1159735927 | Y35: =AT35 -> 0.96 | AA35: 5.1 | AB35: 0 | AC35: 0 | AD35: 0 | AE35: 0.7 | AF35: 0 | AG35: 0 | AH35: 0 | AI35: 6.74 | AJ35: 1 | AK35: 1 | AL35: 1 | AM35: 2 | AN35: 0 | AO35: 1 | AP35: 1 | AQ35: 0 | AR35: 0 | AT35: 0.96 | AV35: 0 | AW35: 2 | AX35: 57737375 | AY35: 1 | AZ35: 0 | BA35: 36 | BB35: 0 | BC35: 0 | BD35: 0 | BE35: 0 | BF35: 0 | BG35: 0 | BH35: 0 | BI35: 0 | BJ35: 0 | BK35: 0 | BL35: 0 | BM35: 0 | BN35: 0 | BO35: 0 | BP35: 0 | BQ35: 0 | BR35: 0 | BS35: 0 | BT35: 0 | BU35: 0 | BV35: 0 | BW35: 0 | CV35: 0 | CW35: 0 | CX35: =ROUND(Y35*Source!I78,9) -> 12.65328 | CY35: =AA35 -> 5.1 | CZ35: =AE35 -> 0.7 | DA35: =AI35 -> 6.74 | DB35: =ROUND(ROUND(AT35*CZ35,2),6) -> 0.67 | DC35: =ROUND(ROUND(AT35*AG35,2),6) -> 0 | DF35: =ROUND(ROUND(AE35*AI35,2)*CX35,2) -> 59.72 | DG35: =ROUND(ROUND(AF35,2)*CX35,2) -> 0 | DH35: =ROUND(ROUND(AG35,2)*CX35,2) -> 0 | DI35: =ROUND(ROUND(AH35,2)*CX35,2) -> 0 | DJ35: =DF35 -> 59.72 | DK35: 0 | DM35: 0 | DO35: 0
A36: =ROW(Source!A78) -> 78 | B36: 57737055 | C36: 57737353 | D36: 46735508 | E36: 1 | F36: 1 | G36: 27786564 | H36: 3 | I36: 1.21-5-800 | J36: ТСН-2001.1 Доп. 67, Р. 21, о. 5, поз. 800 | K36: Кнопка для ленты ЛМ, типа 3,5 | L36: 1356 | N36: 1010 | O36: 1000 шт. | P36: 1000 шт. | Q36: 1000 | W36: 0 | X36: 1674776227 | Y36: =AT36 -> 0.00832 | AA36: 229.8 | AB36: 0 | AC36: 0 | AD36: 0 | AE36: 6.44 | AF36: 0 | AG36: 0 | AH36: 0 | AI36: 33.01 | AJ36: 1 | AK36: 1 | AL36: 1 | AM36: 2 | AN36: 0 | AO36: 1 | AP36: 1 | AQ36: 0 | AR36: 0 | AT36: 0.00832 | AV36: 0 | AW36: 2 | AX36: 57737376 | AY36: 1 | AZ36: 0 | BA36: 37 | BB36: 0 | BC36: 0 | BD36: 0 | BE36: 0 | BF36: 0 | BG36: 0 | BH36: 0 | BI36: 0 | BJ36: 0 | BK36: 0 | BL36: 0 | BM36: 0 | BN36: 0 | BO36: 0 | BP36: 0 | BQ36: 0 | BR36: 0 | BS36: 0 | BT36: 0 | BU36: 0 | BV36: 0 | BW36: 0 | CV36: 0 | CW36: 0 | CX36: =ROUND(Y36*Source!I78,9) -> 0.10966176 | CY36: =AA36 -> 229.8 | CZ36: =AE36 -> 6.44 | DA36: =AI36 -> 33.01 | DB36: =ROUND(ROUND(AT36*CZ36,2),6) -> 0.05 | DC36: =ROUND(ROUND(AT36*AG36,2),6) -> 0 | DF36: =ROUND(ROUND(AE36*AI36,2)*CX36,2) -> 23.31 | DG36: =ROUND(ROUND(AF36,2)*CX36,2) -> 0 | DH36: =ROUND(ROUND(AG36,2)*CX36,2) -> 0 | DI36: =ROUND(ROUND(AH36,2)*CX36,2) -> 0 | DJ36: =DF36 -> 23.31 | DK36: 0 | DM36: 0 | DO36: 0
A37: =ROW(Source!A78) -> 78 | B37: 57737055 | C37: 57737353 | D37: 52049651 | E37: 1 | F37: 1 | G37: 27786564 | H37: 3 | I37: 1.23-7-391 | J37: ТСН-2001.1 Доп. 73, Р. 23, о. 7, поз. 391 | K37: Кабель силовой с алюминиевой многопроволочной жилой, с изоляцией из сшитого полиэтилена, с медным экраном, с водоблокирующей лентой под металлическим экраном, марка АПвПуг, напряжение 10000 В, число жил, сечение жилы, экран 1х120/35 мм2 | L37: 1303 | N37: 1003 | O37: км | P37: км | Q37: 1000 | W37: 0 | X37: 61579043 | Y37: =AT37 -> 0.102 | AA37: 647382.9 | AB37: 0 | AC37: 0 | AD37: 0 | AE37: 81534.37 | AF37: 0 | AG37: 0 | AH37: 0 | AI37: 7.94 | AJ37: 1 | AK37: 1 | AL37: 1 | AM37: 0 | AN37: 0 | AO37: 0 | AP37: 1 | AQ37: 0 | AR37: 0 | AT37: 0.102 | AV37: 0 | AW37: 1 | AX37: -1 | AY37: 0 | AZ37: 0 | BB37: 0 | BC37: 0 | BD37: 0 | BE37: 0 | BF37: 0 | BG37: 0 | BH37: 0 | BI37: 0 | BJ37: 0 | BK37: 0 | BL37: 0 | BM37: 0 | BN37: 0 | BO37: 0 | BP37: 0 | BQ37: 0 | BR37: 0 | BS37: 0 | BT37: 0 | BU37: 0 | BV37: 0 | BW37: 0 | CV37: 0 | CW37: 0 | CX37: =ROUND(Y37*Source!I78,9) -> 1.344411 | CY37: =AA37 -> 647382.9 | CZ37: =AE37 -> 81534.37 | DA37: =AI37 -> 7.94 | DB37: =ROUND(ROUND(AT37*CZ37,2),6) -> 8316.51 | DC37: =ROUND(ROUND(AT37*AG37,2),6) -> 0 | DF37: =ROUND(ROUND(AE37*AI37,2)*CX37,2) -> 870348.69 | DG37: =ROUND(ROUND(AF37,2)*CX37,2) -> 0 | DH37: =ROUND(ROUND(AG37,2)*CX37,2) -> 0 | DI37: =ROUND(ROUND(AH37,2)*CX37,2) -> 0 | DJ37: =DF37 -> 870348.69 | DK37: 0 | DM37: 0 | DO37: 0

Sheet EtalonRes
A1: =ROW(Source!A32) -> 32 | B1: 57737293 | C1: 57737291 | D1: 47634407 | E1: 27786564 | F1: 1 | G1: 27786564 | H1: 1 | I1: 9999990008 | K1: Трудозатраты рабочих | L1: 1191 | N1: 1013 | O1: чел.-ч. | P1: чел.-ч. | Q1: 1 | X1: 192.7 | Y1: 0 | Z1: 0 | AA1: 0 | AB1: 0 | AC1: 0 | AD1: 1 | AE1: 1 | AF1: *1,05 | AG1: 202.335 | AH1: 2 | AI1: 57737292 | AJ1: 1 | AK1: 0 | AL1: 0 | AM1: 0 | AN1: 0 | AO1: 0 | AP1: 0 | AQ1: 0 | AR1: 0
A2: =ROW(Source!A33) -> 33 | B2: 57737296 | C2: 57737294 | D2: 47634407 | E2: 27786564 | F2: 1 | G2: 27786564 | H2: 1 | I2: 9999990008 | K2: Трудозатраты рабочих | L2: 1191 | N2: 1013 | O2: чел.-ч. | P2: чел.-ч. | Q2: 1 | X2: 107.04 | Y2: 0 | Z2: 0 | AA2: 0 | AB2: 0 | AC2: 0 | AD2: 1 | AE2: 1 | AF2: *1,05 | AG2: 112.392 | AH2: 2 | AI2: 57737295 | AJ2: 2 | AK2: 0 | AL2: 0 | AM2: 0 | AN2: 0 | AO2: 0 | AP2: 0 | AQ2: 0 | AR2: 0
A3: =ROW(Source!A34) -> 34 | B3: 57737311 | C3: 57737297 | D3: 47634407 | E3: 27786564 | F3: 1 | G3: 27786564 | H3: 1 | I3: 9999990008 | K3: Трудозатраты рабочих | L3: 1191 | N3: 1013 | O3: чел.-ч. | P3: чел.-ч. | Q3: 1 | X3: 2.08 | Y3: 0 | Z3: 0 | AA3: 0 | AB3: 0 | AC3: 0 | AD3: 1 | AE3: 1 | AF3: *1,05 | AG3: 2.184 | AH3: 2 | AI3: 57737310 | AJ3: 3 | AK3: 0 | AL3: 0 | AM3: 0 | AN3: 0 | AO3: 0 | AP3: 0 | AQ3: 0 | AR3: 0
A4: =ROW(Source!A34) -> 34 | B4: 57737312 | C4: 57737297 | D4: 47766829 | E4: 1 | F4: 1 | G4: 27786564 | H4: 2 | I4: 2.1-11-91 | J4: ТСН-2001.2. Доп. 68. п.1-11-91 (110701) | K4: Насосы водоотливные, производительность до 54 м3/ч, мощность до 3,2 кВт (4,8 л.с) | L4: 1368 | N4: 1011 | O4: маш.-ч | P4: маш.-ч | Q4: 1 | X4: 0.12 | Y4: 0 | Z4: 12.98 | AA4: 3.37 | AB4: 0 | AC4: 0 | AD4: 1 | AE4: 0 | AF4: *1,05 | AG4: 0.126 | AH4: 2 | AI4: 57737298 | AJ4: 4 | AK4: 0 | AL4: 0 | AM4: 0 | AN4: 0 | AO4: 0 | AP4: 0 | AQ4: 0 | AR4: 0
A5: =ROW(Source!A34) -> 34 | B5: 57737313 | C5: 57737297 | D5: 47767072 | E5: 1 | F5: 1 | G5: 27786564 | H5: 2 | I5: 2.1-17-203 | J5: ТСН-2001.2. Доп. 68. п.1-17-203 (172706) | K5: Установки направленного бурения, тяговое усилие до 500 кН | L5: 1368 | N5: 1011 | O5: маш.-ч | P5: маш.-ч | Q5: 1 | X5: 0.88 | Y5: 0 | Z5: 1843.32 | AA5: 38.94 | AB5: 0 | AC5: 0 | AD5: 1 | AE5: 0 | AF5: *1,05 | AG5: 0.924 | AH5: 2 | AI5: 57737299 | AJ5: 5 | AK5: 0 | AL5: 0 | AM5: 0 | AN5: 0 | AO5: 0 | AP5: 0 | AQ5: 0 | AR5: 0
A6: =ROW(Source!A34) -> 34 | B6: 57737314 | C6: 57737297 | D6: 47766980 | E6: 1 | F6: 1 | G6: 27786564 | H6: 2 | I6: 2.1-17-49 | J6: ТСН-2001.2. Доп. 68. п.1-17-49 (176802) | K6: Машины комбинированные илососные промывочные на базе автомобиля, объем цистерн до 10 м3, производительность до 720 м3/ч | L6: 1368 | N6: 1011 | O6: маш.-ч | P6: маш.-ч | Q6: 1 | X6: 0.11 | Y6: 0 | Z6: 181.58 | AA6: 14.54 | AB6: 0 | AC6: 0 | AD6: 1 | AE6: 0 | AF6: *1,05 | AG6: 0.1155 | AH6: 2 | AI6: 57737300 | AJ6: 6 | AK6: 0 | AL6: 0 | AM6: 0 | AN6: 0 | AO6: 0 | AP6: 0 | AQ6: 0 | AR6: 0
A7: =ROW(Source!A34) -> 34 | B7: 57737315 | C7: 57737297 | D7: 47767117 | E7: 1 | F7: 1 | G7: 27786564 | H7: 2 | I7: 2.1-18-23 | J7: ТСН-2001.2. Доп. 68. п.1-18-23 (183201) | K7: Автомобили бортовые с краном-манипулятором, грузоподъемность до 6 т | L7: 1368 | N7: 1011 | O7: маш.-ч | P7: маш.-ч | Q7: 1 | X7: 0.02 | Y7: 0 | Z7: 125.38 | AA7: 12.62 | AB7: 0 | AC7: 0 | AD7: 1 | AE7: 0 | AF7: *1,05 | AG7: 0.021 | AH7: 2 | AI7: 57737301 | AJ7: 7 | AK7: 0 | AL7: 0 | AM7: 0 | AN7: 0 | AO7: 0 | AP7: 0 | AQ7: 0 | AR7: 0
A8: =ROW(Source!A34) -> 34 | B8: 57737316 | C8: 57737297 | D8: 47766471 | E8: 1 | F8: 1 | G8: 27786564 | H8: 2 | I8: 2.1-3-69 | J8: ТСН-2001.2. Доп. 68. п.1-3-69 (038003) | K8: Трубоукладчики, диаметр труб до 400 мм | L8: 1368 | N8: 1011 | O8: маш.-ч | P8: маш.-ч | Q8: 1 | X8: 0.3 | Y8: 0 | Z8: 139.99 | AA8: 14.54 | AB8: 0 | AC8: 0 | AD8: 1 | AE8: 0 | AF8: *1,05 | AG8: 0.315 | AH8: 2 | AI8: 57737302 | AJ8: 8 | AK8: 0 | AL8: 0 | AM8: 0 | AN8: 0 | AO8: 0 | AP8: 0 | AQ8: 0 | AR8: 0
A9: =ROW(Source!A34) -> 34 | B9: 57737317 | C9: 57737297 | D9: 47766605 | E9: 1 | F9: 1 | G9: 27786564 | H9: 2 | I9: 2.1-5-18 | J9: ТСН-2001.2. Доп. 68. п.1-5-18 (050902) | K9: Машины поливомоечные, емкость цистерны до 8 м3 | L9: 1368 | N9: 1011 | O9: маш.-ч | P9: маш.-ч | Q9: 1 | X9: 0.12 | Y9: 0 | Z9: 140.38 | AA9: 12.62 | AB9: 0 | AC9: 0 | AD9: 1 | AE9: 0 | AF9: *1,05 | AG9: 0.126 | AH9: 2 | AI9: 57737303 | AJ9: 9 | AK9: 0 | AL9: 0 | AM9: 0 | AN9: 0 | AO9: 0 | AP9: 0 | AQ9: 0 | AR9: 0
A10: =ROW(Source!A34) -> 34 | B10: 57737318 | C10: 57737297 | D10: 47766703 | E10: 1 | F10: 1 | G10: 27786564 | H10: 2 | I10: 2.1-6-79 | J10: ТСН-2001.2. Доп. 68. п.1-6-79 (061105) | K10: Установки смесительные стационарные для приготовления бентонитового раствора, емкость до 4000 л | L10: 1368 | N10: 1011 | O10: маш.-ч | P10: маш.-ч | Q10: 1 | X10: 0.88 | Y10: 0 | Z10: 80.14 | AA10: 16.93 | AB10: 0 | AC10: 0 | AD10: 1 | AE10: 0 | AF10: *1,05 | AG10: 0.924 | AH10: 2 | AI10: 57737304 | AJ10: 10 | AK10: 0 | AL10: 0 | AM10: 0 | AN10: 0 | AO10: 0 | AP10: 0 | AQ10: 0 | AR10: 0
A11: =ROW(Source!A34) -> 34 | B11: 57737319 | C11: 57737297 | D11: 46723741 | E11: 1 | F11: 1 | G11: 27786564 | H11: 3 | I11: 1.1-1-1049 | J11: ТСН-2001.1 Доп. 67, Р. 1, о. 1, поз. 1049 | K11: Сода кальцинированная, техническая | L11: 1348 | N11: 1009 | O11: т | P11: т | Q11: 1000 | X11: 0.001505 | Y11: 5778.3 | Z11: 0 | AA11: 0 | AB11: 0 | AC11: 0 | AD11: 1 | AE11: 0 | AG11: 0.001505 | AH11: 2 | AI11: 57737305 | AJ11: 11 | AK11: 0 | AL11: 0 | AM11: 0 | AN11: 0 | AO11: 0 | AP11: 0 | AQ11: 0 | AR11: 0
A12: =ROW(Source!A34) -> 34 | B12: 57737320 | C12: 57737297 | D12: 30390465 | E12: 1 | F12: 1 | G12: 27786564 | H12: 3 | I12: 1.1-1-118 | J12: ТСН-2001.1. Доп. 1-42. Р. 1, о. 1, поз. 118 | K12: Вода | L12: 1339 | N12: 1007 | O12: м3 | P12: м3 | Q12: 1 | X12: 1.9 | Y12: 7.07 | Z12: 0 | AA12: 0 | AB12: 0 | AC12: 0 | AD12: 1 | AE12: 0 | AG12: 1.9 | AH12: 2 | AI12: 57737306 | AJ12: 12 | AK12: 0 | AL12: 0 | AM12: 0 | AN12: 0 | AO12: 0 | AP12: 0 | AQ12: 0 | AR12: 0
A13: =ROW(Source!A34) -> 34 | B13: 57737321 | C13: 57737297 | D13: 47765707 | E13: 1 | F13: 1 | G13: 27786564 | H13: 3 | I13: 1.1-1-2948 | J13: ТСН-2001.1 Доп. 68, Р. 1, о. 1, поз. 2948 | K13: Смазка графитная | L13: 1346 | N13: 1009 | O13: кг | P13: кг | Q13: 1 | X13: 0.0432 | Y13: 7.48 | Z13: 0 | AA13: 0 | AB13: 0 | AC13: 0 | AD13: 1 | AE13: 0 | AG13: 0.0432 | AH13: 2 | AI13: 57737307 | AJ13: 14 | AK13: 0 | AL13: 0 | AM13: 0 | AN13: 0 | AO13: 0 | AP13: 0 | AQ13: 0 | AR13: 0
A14: =ROW(Source!A34) -> 34 | B14: 57737322 | C14: 57737297 | D14: 32158535 | E14: 27786564 | F14: 1 | G14: 27786564 | H14: 3 | I14: 2164500000 | K14: Бентониты | L14: 1346 | N14: 1009 | O14: кг | P14: кг | Q14: 1 | X14: 116.8 | Y14: 0 | Z14: 0 | AA14: 0 | AB14: 0 | AC14: 0 | AD14: 0 | AE14: 0 | AG14: 116.8 | AH14: 3 | AI14: -1 | AK14: 0 | AL14: 0 | AM14: 0 | AN14: 0 | AO14: 0 | AP14: 0 | AQ14: 0 | AR14: 0
A15: =ROW(Source!A34) -> 34 | B15: 57737323 | C15: 57737297 | D15: 30365725 | E15: 27786564 | F15: 1 | G15: 27786564 | H15: 3 | I15: 2248110000 | K15: Трубы из полиэтилена | L15: 1301 | N15: 1003 | O15: м | P15: м | Q15: 1 | X15: 0 | Y15: 0 | Z15: 0 | AA15: 0 | AB15: 0 | AC15: 0 | AD15: 0 | AE15: 0 | AG15: 0 | AH15: 3 | AI15: -1 | AK15: 0 | AL15: 0 | AM15: 0 | AN15: 0 | AO15: 0 | AP15: 0 | AQ15: 0 | AR15: 0
A16: =ROW(Source!A34) -> 34 | B16: 57737324 | C16: 57737297 | D16: 32158874 | E16: 27786564 | F16: 1 | G16: 27786564 | H16: 3 | I16: 2452910000 | K16: Полимеры для флотации | L16: 1296 | N16: 1013 | O16: л | P16: л | Q16: 1 | X16: 5.928 | Y16: 0 | Z16: 0 | AA16: 0 | AB16: 0 | AC16: 0 | AD16: 0 | AE16: 0 | AG16: 5.928 | AH16: 3 | AI16: -1 | AK16: 0 | AL16: 0 | AM16: 0 | AN16: 0 | AO16: 0 | AP16: 0 | AQ16: 0 | AR16: 0
A17: =ROW(Source!A38) -> 38 | B17: 57737332 | C17: 57737328 | D17: 47634407 | E17: 27786564 | F17: 1 | G17: 27786564 | H17: 1 | I17: 9999990008 | K17: Трудозатраты рабочих | L17: 1191 | N17: 1013 | O17: чел.-ч. | P17: чел.-ч. | Q17: 1 | X17: 0.6 | Y17: 0 | Z17: 0 | AA17: 0 | AB17: 0 | AC17: 0 | AD17: 1 | AE17: 1 | AF17: *1,05 | AG17: 0.63 | AH17: 2 | AI17: 57737329 | AJ17: 16 | AK17: 0 | AL17: 0 | AM17: 0 | AN17: 0 | AO17: 0 | AP17: 0 | AQ17: 0 | AR17: 0
A18: =ROW(Source!A38) -> 38 | B18: 57737333 | C18: 57737328 | D18: 47767072 | E18: 1 | F18: 1 | G18: 27786564 | H18: 2 | I18: 2.1-17-203 | J18: ТСН-2001.2. Доп. 68. п.1-17-203 (172706) | K18: Установки направленного бурения, тяговое усилие до 500 кН | L18: 1368 | N18: 1011 | O18: маш.-ч | P18: маш.-ч | Q18: 1 | X18: 0.6 | Y18: 0 | Z18: 1843.32 | AA18: 38.94 | AB18: 0 | AC18: 0 | AD18: 1 | AE18: 0 | AF18: *1,05 | AG18: 0.63 | AH18: 2 | AI18: 57737330 | AJ18: 17 | AK18: 0 | AL18: 0 | AM18: 0 | AN18: 0 | AO18: 0 | AP18: 0 | AQ18: 0 | AR18: 0
A19: =ROW(Source!A38) -> 38 | B19: 57737334 | C19: 57737328 | D19: 47766748 | E19: 1 | F19: 1 | G19: 27786564 | H19: 2 | I19: 2.1-9-2 | J19: ТСН-2001.2. Доп. 68. п.1-9-2 (090201) | K19: Машины бурильно-крановые на базе автомобиля, глубина бурения до 5 м | L19: 1368 | N19: 1011 | O19: маш.-ч | P19: маш.-ч | Q19: 1 | X19: 0.58 | Y19: 0 | Z19: 166.63 | AA19: 14.54 | AB19: 0 | AC19: 0 | AD19: 1 | AE19: 0 | AF19: *1,05 | AG19: 0.609 | AH19: 2 | AI19: 57737331 | AJ19: 18 | AK19: 0 | AL19: 0 | AM19: 0 | AN19: 0 | AO19: 0 | AP19: 0 | AQ19: 0 | AR19: 0
A20: =ROW(Source!A39) -> 39 | B20: 57737338 | C20: 57737335 | D20: 47634407 | E20: 27786564 | F20: 1 | G20: 27786564 | H20: 1 | I20: 9999990008 | K20: Трудозатраты рабочих | L20: 1191 | N20: 1013 | O20: чел.-ч. | P20: чел.-ч. | Q20: 1 | X20: 0.26 | Y20: 0 | Z20: 0 | AA20: 0 | AB20: 0 | AC20: 0 | AD20: 1 | AE20: 1 | AF20: *1,05 | AG20: 0.273 | AH20: 2 | AI20: 57737336 | AJ20: 19 | AK20: 0 | AL20: 0 | AM20: 0 | AN20: 0 | AO20: 0 | AP20: 0 | AQ20: 0 | AR20: 0
A21: =ROW(Source!A39) -> 39 | B21: 57737339 | C21: 57737335 | D21: 47767072 | E21: 1 | F21: 1 | G21: 27786564 | H21: 2 | I21: 2.1-17-203 | J21: ТСН-2001.2. Доп. 68. п.1-17-203 (172706) | K21: Установки направленного бурения, тяговое усилие до 500 кН | L21: 1368 | N21: 1011 | O21: маш.-ч | P21: маш.-ч | Q21: 1 | X21: 0.26 | Y21: 0 | Z21: 1843.32 | AA21: 38.94 | AB21: 0 | AC21: 0 | AD21: 1 | AE21: 0 | AF21: *1,05 | AG21: 0.273 | AH21: 2 | AI21: 57737337 | AJ21: 20 | AK21: 0 | AL21: 0 | AM21: 0 | AN21: 0 | AO21: 0 | AP21: 0 | AQ21: 0 | AR21: 0
A22: =ROW(Source!A40) -> 40 | B22: 57737345 | C22: 57737340 | D22: 47634407 | E22: 27786564 | F22: 1 | G22: 27786564 | H22: 1 | I22: 9999990008 | K22: Трудозатраты рабочих | L22: 1191 | N22: 1013 | O22: чел.-ч. | P22: чел.-ч. | Q22: 1 | X22: 1.15 | Y22: 0 | Z22: 0 | AA22: 0 | AB22: 0 | AC22: 0 | AD22: 1 | AE22: 1 | AF22: *1,05 | AG22: 1.2075 | AH22: 2 | AI22: 57737341 | AJ22: 21 | AK22: 0 | AL22: 0 | AM22: 0 | AN22: 0 | AO22: 0 | AP22: 0 | AQ22: 0 | AR22: 0
A23: =ROW(Source!A40) -> 40 | B23: 57737346 | C23: 57737340 | D23: 47766881 | E23: 1 | F23: 1 | G23: 27786564 | H23: 2 | I23: 2.1-13-40 | J23: ТСН-2001.2. Доп. 68. п.1-13-40 (135505) | K23: Аппараты для стыковой сварки труб из термопластов диаметром от 40 до 160 мм | L23: 1368 | N23: 1011 | O23: маш.-ч | P23: маш.-ч | Q23: 1 | X23: 0.56 | Y23: 0 | Z23: 4.01 | AA23: 0 | AB23: 0 | AC23: 0 | AD23: 1 | AE23: 0 | AF23: *1,05 | AG23: 0.588 | AH23: 2 | AI23: 57737342 | AJ23: 22 | AK23: 0 | AL23: 0 | AM23: 0 | AN23: 0 | AO23: 0 | AP23: 0 | AQ23: 0 | AR23: 0
A24: =ROW(Source!A40) -> 40 | B24: 57737347 | C24: 57737340 | D24: 44217275 | E24: 1 | F24: 1 | G24: 27786564 | H24: 3 | I24: 1.1-1-1064 | J24: ТСН-2001.1 Доп. 65, Р. 1, о. 1, поз. 1064 | K24: Спирт этиловый технический | L24: 1346 | N24: 1009 | O24: кг | P24: кг | Q24: 1 | X24: 0.0667 | Y24: 11.25 | Z24: 0 | AA24: 0 | AB24: 0 | AC24: 0 | AD24: 1 | AE24: 0 | AG24: 0.0667 | AH24: 2 | AI24: 57737343 | AJ24: 23 | AK24: 0 | AL24: 0 | AM24: 0 | AN24: 0 | AO24: 0 | AP24: 0 | AQ24: 0 | AR24: 0
A25: =ROW(Source!A40) -> 40 | B25: 57737348 | C25: 57737340 | D25: 30390462 | E25: 1 | F25: 1 | G25: 27786564 | H25: 3 | I25: 1.1-1-115 | J25: ТСН-2001.1. Доп. 1-42. Р. 1, о. 1, поз. 115 | K25: Ветошь | L25: 1346 | N25: 1009 | O25: кг | P25: кг | Q25: 1 | X25: 0.1 | Y25: 1.61 | Z25: 0 | AA25: 0 | AB25: 0 | AC25: 0 | AD25: 1 | AE25: 0 | AG25: 0.1 | AH25: 2 | AI25: 57737344 | AJ25: 24 | AK25: 0 | AL25: 0 | AM25: 0 | AN25: 0 | AO25: 0 | AP25: 0 | AQ25: 0 | AR25: 0
A26: =ROW(Source!A41) -> 41 | B26: 57737351 | C26: 57737349 | D26: 47634407 | E26: 27786564 | F26: 1 | G26: 27786564 | H26: 1 | I26: 9999990008 | K26: Трудозатраты рабочих | L26: 1191 | N26: 1013 | O26: чел.-ч. | P26: чел.-ч. | Q26: 1 | X26: 0.1 | Y26: 0 | Z26: 0 | AA26: 0 | AB26: 0 | AC26: 0 | AD26: 1 | AE26: 1 | AF26: *1,05 | AG26: 0.105 | AH26: 2 | AI26: 57737350 | AJ26: 25 | AK26: 0 | AL26: 0 | AM26: 0 | AN26: 0 | AO26: 0 | AP26: 0 | AQ26: 0 | AR26: 0
A27: =ROW(Source!A78) -> 78 | B27: 57737366 | C27: 57737353 | D27: 47634407 | E27: 27786564 | F27: 1 | G27: 27786564 | H27: 1 | I27: 9999990008 | K27: Трудозатраты рабочих | L27: 1191 | N27: 1013 | O27: чел.-ч. | P27: чел.-ч. | Q27: 1 | X27: 15.8 | Y27: 0 | Z27: 0 | AA27: 0 | AB27: 0 | AC27: 0 | AD27: 1 | AE27: 1 | AF27: *1,05 | AG27: 16.59 | AH27: 2 | AI27: 57737354 | AJ27: 26 | AK27: 0 | AL27: 0 | AM27: 0 | AN27: 0 | AO27: 0 | AP27: 0 | AQ27: 0 | AR27: 0
A28: =ROW(Source!A78) -> 78 | B28: 57737367 | C28: 57737353 | D28: 47767106 | E28: 1 | F28: 1 | G28: 27786564 | H28: 2 | I28: 2.1-18-7 | J28: ТСН-2001.2. Доп. 68. п.1-18-7 (183001) | K28: Автомобили грузовые бортовые, грузоподъемность до 5 т | L28: 1368 | N28: 1011 | O28: маш.-ч | P28: маш.-ч | Q28: 1 | X28: 0.51 | Y28: 0 | Z28: 83.1 | AA28: 12.62 | AB28: 0 | AC28: 0 | AD28: 1 | AE28: 0 | AF28: *1,05 | AG28: 0.5355 | AH28: 2 | AI28: 57737355 | AJ28: 27 | AK28: 0 | AL28: 0 | AM28: 0 | AN28: 0 | AO28: 0 | AP28: 0 | AQ28: 0 | AR28: 0
A29: =ROW(Source!A78) -> 78 | B29: 57737368 | C29: 57737353 | D29: 47766535 | E29: 1 | F29: 1 | G29: 27786564 | H29: 2 | I29: 2.1-4-31 | J29: ТСН-2001.2. Доп. 68. п.1-4-31 (042903) | K29: Лебедки электрические, тяговое усилие до 14,71 кН (1,5 тс) | L29: 1368 | N29: 1011 | O29: маш.-ч | P29: маш.-ч | Q29: 1 | X29: 3.41 | Y29: 0 | Z29: 2.27 | AA29: 0 | AB29: 0 | AC29: 0 | AD29: 1 | AE29: 0 | AF29: *1,05 | AG29: 3.5805 | AH29: 2 | AI29: 57737356 | AJ29: 28 | AK29: 0 | AL29: 0 | AM29: 0 | AN29: 0 | AO29: 0 | AP29: 0 | AQ29: 0 | AR29: 0
A30: =ROW(Source!A78) -> 78 | B30: 57737369 | C30: 57737353 | D30: 47766545 | E30: 1 | F30: 1 | G30: 27786564 | H30: 2 | I30: 2.1-4-45 | J30: ТСН-2001.2. Доп. 68. п.1-4-45 (043403) | K30: Домкраты гидравлические, грузоподъемность до 100 т | L30: 1368 | N30: 1011 | O30: маш.-ч | P30: маш.-ч | Q30: 1 | X30: 3.67 | Y30: 0 | Z30: 0.73 | AA30: 0 | AB30: 0 | AC30: 0 | AD30: 1 | AE30: 0 | AF30: *1,05 | AG30: 3.8535 | AH30: 2 | AI30: 57737357 | AJ30: 29 | AK30: 0 | AL30: 0 | AM30: 0 | AN30: 0 | AO30: 0 | AP30: 0 | AQ30: 0 | AR30: 0
A31: =ROW(Source!A78) -> 78 | B31: 57737370 | C31: 57737353 | D31: 46723498 | E31: 1 | F31: 1 | G31: 27786564 | H31: 3 | I31: 1.1-1-491 | J31: ТСН-2001.1 Доп. 67, Р. 1, о. 1, поз. 491 | K31: Лак битумный, типа БТ-123 | L31: 1348 | N31: 1009 | O31: т | P31: т | Q31: 1000 | X31: 6e-05 | Y31: 11242.42 | Z31: 0 | AA31: 0 | AB31: 0 | AC31: 0 | AD31: 1 | AE31: 0 | AG31: 6e-05 | AH31: 2 | AI31: 57737358 | AJ31: 30 | AK31: 0 | AL31: 0 | AM31: 0 | AN31: 0 | AO31: 0 | AP31: 0 | AQ31: 0 | AR31: 0
A32: =ROW(Source!A78) -> 78 | B32: 57737371 | C32: 57737353 | D32: 45796980 | E32: 1 | F32: 1 | G32: 27786564 | H32: 3 | I32: 1.1-1-8031 | J32: ТСН-2001.1 Доп. 66, Р. 1, о. 1, поз. 8031 | K32: Роль свинцовая, марка С1, толщина от 1 до 1,5 мм | L32: 1346 | N32: 1009 | O32: кг | P32: кг | Q32: 1 | X32: 0.8 | Y32: 25.8 | Z32: 0 | AA32: 0 | AB32: 0 | AC32: 0 | AD32: 1 | AE32: 0 | AG32: 0.8 | AH32: 2 | AI32: 57737359 | AJ32: 31 | AK32: 0 | AL32: 0 | AM32: 0 | AN32: 0 | AO32: 0 | AP32: 0 | AQ32: 0 | AR32: 0
A33: =ROW(Source!A78) -> 78 | B33: 57737372 | C33: 57737353 | D33: 46723689 | E33: 1 | F33: 1 | G33: 27786564 | H33: 3 | I33: 1.1-1-944 | J33: ТСН-2001.1 Доп. 67, Р. 1, о. 1, поз. 944 | K33: Припой оловянно-свинцовый, в прутках, диаметр 8 мм, типа ПОС-30 | L33: 1348 | N33: 1009 | O33: т | P33: т | Q33: 1000 | X33: 0.0005 | Y33: 60966 | Z33: 0 | AA33: 0 | AB33: 0 | AC33: 0 | AD33: 1 | AE33: 0 | AG33: 0.0005 | AH33: 2 | AI33: 57737360 | AJ33: 32 | AK33: 0 | AL33: 0 | AM33: 0 | AN33: 0 | AO33: 0 | AP33: 0 | AQ33: 0 | AR33: 0
A34: =ROW(Source!A78) -> 78 | B34: 57737373 | C34: 57737353 | D34: 46723704 | E34: 1 | F34: 1 | G34: 27786564 | H34: 3 | I34: 1.1-1-967 | J34: ТСН-2001.1 Доп. 67, Р. 1, о. 1, поз. 967 | K34: Проволока стальная низкоуглеродистая общего назначения оцинкованная, диаметр от 1,6 до 3,0 мм | L34: 1348 | N34: 1009 | O34: т | P34: т | Q34: 1000 | X34: 4e-05 | Y34: 7982.5 | Z34: 0 | AA34: 0 | AB34: 0 | AC34: 0 | AD34: 1 | AE34: 0 | AG34: 4e-05 | AH34: 2 | AI34: 57737361 | AJ34: 33 | AK34: 0 | AL34: 0 | AM34: 0 | AN34: 0 | AO34: 0 | AP34: 0 | AQ34: 0 | AR34: 0
A35: =ROW(Source!A78) -> 78 | B35: 57737374 | C35: 57737353 | D35: 46735845 | E35: 1 | F35: 1 | G35: 27786564 | H35: 3 | I35: 1.21-5-1180 | J35: ТСН-2001.1 Доп. 67, Р. 21, о. 5, поз. 1180 | K35: Бирка маркировочная для кабелей и проводов, типа У134 У3,5 | L35: 1356 | N35: 1010 | O35: 1000 шт. | P35: 1000 шт. | Q35: 1000 | X35: 0.00041 | Y35: 226.68 | Z35: 0 | AA35: 0 | AB35: 0 | AC35: 0 | AD35: 1 | AE35: 0 | AG35: 0.00041 | AH35: 2 | AI35: 57737362 | AJ35: 34 | AK35: 0 | AL35: 0 | AM35: 0 | AN35: 0 | AO35: 0 | AP35: 0 | AQ35: 0 | AR35: 0
A36: =ROW(Source!A78) -> 78 | B36: 57737375 | C36: 57737353 | D36: 46735506 | E36: 1 | F36: 1 | G36: 27786564 | H36: 3 | I36: 1.21-5-798 | J36: ТСН-2001.1 Доп. 67, Р. 21, о. 5, поз. 798 | K36: Лента монтажная, типа ЛМ-5 | L36: 1301 | N36: 1003 | O36: м | P36: м | Q36: 1 | X36: 0.96 | Y36: 0.7 | Z36: 0 | AA36: 0 | AB36: 0 | AC36: 0 | AD36: 1 | AE36: 0 | AG36: 0.96 | AH36: 2 | AI36: 57737363 | AJ36: 35 | AK36: 0 | AL36: 0 | AM36: 0 | AN36: 0 | AO36: 0 | AP36: 0 | AQ36: 0 | AR36: 0
A37: =ROW(Source!A78) -> 78 | B37: 57737376 | C37: 57737353 | D37: 46735508 | E37: 1 | F37: 1 | G37: 27786564 | H37: 3 | I37: 1.21-5-800 | J37: ТСН-2001.1 Доп. 67, Р. 21, о. 5, поз. 800 | K37: Кнопка для ленты ЛМ, типа 3,5 | L37: 1356 | N37: 1010 | O37: 1000 шт. | P37: 1000 шт. | Q37: 1000 | X37: 0.00832 | Y37: 6.44 | Z37: 0 | AA37: 0 | AB37: 0 | AC37: 0 | AD37: 1 | AE37: 0 | AG37: 0.00832 | AH37: 2 | AI37: 57737364 | AJ37: 36 | AK37: 0 | AL37: 0 | AM37: 0 | AN37: 0 | AO37: 0 | AP37: 0 | AQ37: 0 | AR37: 0
A38: =ROW(Source!A78) -> 78 | B38: 57737377 | C38: 57737353 | D38: 49717618 | E38: 27786564 | F38: 1 | G38: 27786564 | H38: 3 | I38: 3500000000 | K38: Кабели напряжением до 35 кВ | L38: 1303 | N38: 1003 | O38: км | P38: км | Q38: 1000 | X38: 0.102 | Y38: 0 | Z38: 0 | AA38: 0 | AB38: 0 | AC38: 0 | AD38: 0 | AE38: 0 | AG38: 0.102 | AH38: 3 | AI38: -1 | AK38: 0 | AL38: 0 | AM38: 0 | AN38: 0 | AO38: 0 | AP38: 0 | AQ38: 0 | AR38: 0
A39: =ROW(Source!A78) -> 78 | B39: 57737378 | C39: 57737353 | D39: 46556476 | E39: 27786564 | F39: 1 | G39: 27786564 | H39: 3 | I39: 3599190000 | K39: Оконцеватели (капы) термоусаживаемые | L39: 1354 | N39: 1010 | O39: шт. | P39: шт. | Q39: 1 | X39: 0 | Y39: 0 | Z39: 0 | AA39: 0 | AB39: 0 | AC39: 0 | AD39: 0 | AE39: 0 | AG39: 0 | AH39: 3 | AI39: -1 | AK39: 0 | AL39: 0 | AM39: 0 | AN39: 0 | AO39: 0 | AP39: 0 | AQ39: 0 | AR39: 0
A40: =ROW(Source!A81) -> 81 | B40: 57737382 | C40: 57737381 | D40: 47634407 | E40: 27786564 | F40: 1 | G40: 27786564 | H40: 1 | I40: 9999990008 | K40: Трудозатраты рабочих | L40: 1191 | N40: 1013 | O40: чел.-ч. | P40: чел.-ч. | Q40: 1 | X40: 155.88 | Y40: 0 | Z40: 0 | AA40: 0 | AB40: 0 | AC40: 0 | AD40: 1 | AE40: 1 | AF40: *1,05 | AG40: 163.674 | AH40: 3 | AI40: -1 | AK40: 0 | AL40: 0 | AM40: 0 | AN40: 0 | AO40: 0 | AP40: 0 | AQ40: 0 | AR40: 0
A41: =ROW(Source!A81) -> 81 | B41: 57737383 | C41: 57737381 | D41: 30415180 | E41: 1 | F41: 1 | G41: 27786564 | H41: 2 | I41: 2.1-17-24 | J41: ТСН-2001.2. Доп. 1-42, п. 1-17-24 (174302) | K41: Инжекторные газовые горелки | L41: 1367 | N41: 1011 | O41: маш.-ч. | P41: маш.-ч. | Q41: 1 | X41: 19.72 | Y41: 0 | Z41: 36.08 | AA41: 3.1 | AB41: 0 | AC41: 0 | AD41: 1 | AE41: 0 | AF41: *1,05 | AG41: 20.706 | AH41: 3 | AI41: -1 | AK41: 0 | AL41: 0 | AM41: 0 | AN41: 0 | AO41: 0 | AP41: 0 | AQ41: 0 | AR41: 0
A42: =ROW(Source!A81) -> 81 | B42: 57737384 | C42: 57737381 | D42: 47767106 | E42: 1 | F42: 1 | G42: 27786564 | H42: 2 | I42: 2.1-18-7 | J42: ТСН-2001.2. Доп. 68. п.1-18-7 (183001) | K42: Автомобили грузовые бортовые, грузоподъемность до 5 т | L42: 1368 | N42: 1011 | O42: маш.-ч | P42: маш.-ч | Q42: 1 | X42: 0.05 | Y42: 0 | Z42: 83.1 | AA42: 12.62 | AB42: 0 | AC42: 0 | AD42: 1 | AE42: 0 | AF42: *1,05 | AG42: 0.0525 | AH42: 3 | AI42: -1 | AK42: 0 | AL42: 0 | AM42: 0 | AN42: 0 | AO42: 0 | AP42: 0 | AQ42: 0 | AR42: 0
A43: =ROW(Source!A81) -> 81 | B43: 57737385 | C43: 57737381 | D43: 30390462 | E43: 1 | F43: 1 | G43: 27786564 | H43: 3 | I43: 1.1-1-115 | J43: ТСН-2001.1. Доп. 1-42. Р. 1, о. 1, поз. 115 | K43: Ветошь | L43: 1346 | N43: 1009 | O43: кг | P43: кг | Q43: 1 | X43: 10 | Y43: 1.61 | Z43: 0 | AA43: 0 | AB43: 0 | AC43: 0 | AD43: 1 | AE43: 0 | AG43: 10 | AH43: 3 | AI43: -1 | AK43: 0 | AL43: 0 | AM43: 0 | AN43: 0 | AO43: 0 | AP43: 0 | AQ43: 0 | AR43: 0
A44: =ROW(Source!A81) -> 81 | B44: 57737386 | C44: 57737381 | D44: 46724002 | E44: 1 | F44: 1 | G44: 27786564 | H44: 3 | I44: 1.1-1-1464 | J44: ТСН-2001.1 Доп. 67, Р. 1, о. 1, поз. 1464 | K44: Бумага наждачная шлифовальная, на тканевой основе, водостойкая | L44: 1327 | N44: 1005 | O44: м2 | P44: м2 | Q44: 1 | X44: 1 | Y44: 127.33 | Z44: 0 | AA44: 0 | AB44: 0 | AC44: 0 | AD44: 1 | AE44: 0 | AG44: 1 | AH44: 3 | AI44: -1 | AK44: 0 | AL44: 0 | AM44: 0 | AN44: 0 | AO44: 0 | AP44: 0 | AQ44: 0 | AR44: 0
A45: =ROW(Source!A81) -> 81 | B45: 57737387 | C45: 57737381 | D45: 37620224 | E45: 1 | F45: 1 | G45: 27786564 | H45: 3 | I45: 1.1-1-2613 | J45: ТСН-2001.1 Доп. 56, Р. 1, о. 1, поз. 2613 | K45: Пропан-бутан, сжиженный газ | L45: 1346 | N45: 1009 | O45: кг | P45: кг | Q45: 1 | X45: 30.6 | Y45: 6.27 | Z45: 0 | AA45: 0 | AB45: 0 | AC45: 0 | AD45: 1 | AE45: 0 | AG45: 30.6 | AH45: 3 | AI45: -1 | AK45: 0 | AL45: 0 | AM45: 0 | AN45: 0 | AO45: 0 | AP45: 0 | AQ45: 0 | AR45: 0
A46: =ROW(Source!A81) -> 81 | B46: 57737388 | C46: 57737381 | D46: 30394098 | E46: 1 | F46: 1 | G46: 27786564 | H46: 3 | I46: 1.1-2-158 | J46: ТСН-2001.1. Доп. 1-42. Р. 1, о. 2, поз. 158 | K46: Бензин авиационный, марка Б-70 | L46: 1296 | N46: 1013 | O46: л | P46: л | Q46: 1 | X46: 5 | Y46: 16.26 | Z46: 0 | AA46: 0 | AB46: 0 | AC46: 0 | AD46: 1 | AE46: 0 | AG46: 5 | AH46: 3 | AI46: -1 | AK46: 0 | AL46: 0 | AM46: 0 | AN46: 0 | AO46: 0 | AP46: 0 | AQ46: 0 | AR46: 0
A47: =ROW(Source!A81) -> 81 | B47: 57737389 | C47: 57737381 | D47: 46735801 | E47: 1 | F47: 1 | G47: 27786564 | H47: 3 | I47: 1.21-5-1134 | J47: ТСН-2001.1 Доп. 67, Р. 21, о. 5, поз. 1134 | K47: Хомут (стяжка) кабельный из полиамида, размеры 4,8х300 мм | L47: 1355 | N47: 1010 | O47: 100 шт. | P47: 100 шт. | Q47: 100 | X47: 2 | Y47: 59.47 | Z47: 0 | AA47: 0 | AB47: 0 | AC47: 0 | AD47: 1 | AE47: 0 | AG47: 2 | AH47: 3 | AI47: -1 | AK47: 0 | AL47: 0 | AM47: 0 | AN47: 0 | AO47: 0 | AP47: 0 | AQ47: 0 | AR47: 0
A48: =ROW(Source!A81) -> 81 | B48: 57737390 | C48: 57737381 | D48: 30382931 | E48: 27786564 | F48: 1 | G48: 27786564 | H48: 3 | I48: 5296335000 | K48: Уплотнители кабельных проходов термоусаживаемые | L48: 1391 | N48: 1013 | O48: КОМПЛЕКТ | P48: КОМПЛЕКТ | Q48: 1 | X48: 100 | Y48: 0 | Z48: 0 | AA48: 0 | AB48: 0 | AC48: 0 | AD48: 0 | AE48: 0 | AG48: 100 | AH48: 3 | AI48: -1 | AK48: 0 | AL48: 0 | AM48: 0 | AN48: 0 | AO48: 0 | AP48: 0 | AQ48: 0 | AR48: 0

Sheet SrcPoprs
A1: 32 | B1: 1 | E1: *1,05 | F1: *1,05 | G1: *1,05 | I1: *1,05 | J1: *1,05 | O1: *1,05 | S1: О.П. п.3.4.30.г | T1: В отношении объектов, реализуемых с привлечением средств бюджета города Москвы, затраты, учитывающие усложненные условия производства работ (стесненность, сложность складирования и транспортной логистики, наличие в зоне производства работ действующего технологического оборудования или движения технологического транспорта и т.п.), определяются заказчиком в задании на проектирование при составлении локальных сметных расчетов (смет): для объектов города Москвы, расположенных за пределами Московской кольцевой автомобильной дороги | U1: Глава 12
A2: 33 | B2: 1 | E2: *1,05 | F2: *1,05 | G2: *1,05 | I2: *1,05 | J2: *1,05 | O2: *1,05 | S2: О.П. п.3.4.30.г | T2: В отношении объектов, реализуемых с привлечением средств бюджета города Москвы, затраты, учитывающие усложненные условия производства работ (стесненность, сложность складирования и транспортной логистики, наличие в зоне производства работ действующего технологического оборудования или движения технологического транспорта и т.п.), определяются заказчиком в задании на проектирование при составлении локальных сметных расчетов (смет): для объектов города Москвы, расположенных за пределами Московской кольцевой автомобильной дороги | U2: Глава 12
A3: 34 | B3: 1 | E3: *1,05 | F3: *1,05 | G3: *1,05 | I3: *1,05 | J3: *1,05 | O3: *1,05 | S3: О.П. п.3.4.30.г | T3: В отношении объектов, реализуемых с привлечением средств бюджета города Москвы, затраты, учитывающие усложненные условия производства работ (стесненность, сложность складирования и транспортной логистики, наличие в зоне производства работ действующего технологического оборудования или движения технологического транспорта и т.п.), определяются заказчиком в задании на проектирование при составлении локальных сметных расчетов (смет): для объектов города Москвы, расположенных за пределами Московской кольцевой автомобильной дороги | U3: Глава 12
A4: 37 | B4: 1 | E4: *1,05 | F4: *1,05 | G4: *1,05 | I4: *1,05 | J4: *1,05 | O4: *1,05 | S4: О.П. п.3.4.30.г | T4: В отношении объектов, реализуемых с привлечением средств бюджета города Москвы, затраты, учитывающие усложненные условия производства работ (стесненность, сложность складирования и транспортной логистики, наличие в зоне производства работ действующего технологического оборудования или движения технологического транспорта и т.п.), определяются заказчиком в задании на проектирование при составлении локальных сметных расчетов (смет): для объектов города Москвы, расположенных за пределами Московской кольцевой автомобильной дороги | U4: Глава 12
A5: 38 | B5: 1 | E5: *1,05 | F5: *1,05 | G5: *1,05 | I5: *1,05 | J5: *1,05 | O5: *1,05 | S5: О.П. п.3.4.30.г | T5: В отношении объектов, реализуемых с привлечением средств бюджета города Москвы, затраты, учитывающие усложненные условия производства работ (стесненность, сложность складирования и транспортной логистики, наличие в зоне производства работ действующего технологического оборудования или движения технологического транспорта и т.п.), определяются заказчиком в задании на проектирование при составлении локальных сметных расчетов (смет): для объектов города Москвы, расположенных за пределами Московской кольцевой автомобильной дороги | U5: Глава 12
A6: 39 | B6: 1 | E6: *1,05 | F6: *1,05 | G6: *1,05 | I6: *1,05 | J6: *1,05 | O6: *1,05 | S6: О.П. п.3.4.30.г | T6: В отношении объектов, реализуемых с привлечением средств бюджета города Москвы, затраты, учитывающие усложненные условия производства работ (стесненность, сложность складирования и транспортной логистики, наличие в зоне производства работ действующего технологического оборудования или движения технологического транспорта и т.п.), определяются заказчиком в задании на проектирование при составлении локальных сметных расчетов (смет): для объектов города Москвы, расположенных за пределами Московской кольцевой автомобильной дороги | U6: Глава 12
A7: 40 | B7: 1 | E7: *1,05 | F7: *1,05 | G7: *1,05 | I7: *1,05 | J7: *1,05 | O7: *1,05 | S7: О.П. п.3.4.30.г | T7: В отношении объектов, реализуемых с привлечением средств бюджета города Москвы, затраты, учитывающие усложненные условия производства работ (стесненность, сложность складирования и транспортной логистики, наличие в зоне производства работ действующего технологического оборудования или движения технологического транспорта и т.п.), определяются заказчиком в задании на проектирование при составлении локальных сметных расчетов (смет): для объектов города Москвы, расположенных за пределами Московской кольцевой автомобильной дороги | U7: Глава 12
A8: 41 | B8: 1 | E8: *1,05 | F8: *1,05 | G8: *1,05 | I8: *1,05 | J8: *1,05 | O8: *1,05 | S8: О.П. п.3.4.30.г | T8: В отношении объектов, реализуемых с привлечением средств бюджета города Москвы, затраты, учитывающие усложненные условия производства работ (стесненность, сложность складирования и транспортной логистики, наличие в зоне производства работ действующего технологического оборудования или движения технологического транспорта и т.п.), определяются заказчиком в задании на проектирование при составлении локальных сметных расчетов (смет): для объектов города Москвы, расположенных за пределами Московской кольцевой автомобильной дороги | U8: Глава 12
A9: 42 | B9: 1 | E9: *1,05 | F9: *1,05 | G9: *1,05 | I9: *1,05 | J9: *1,05 | O9: *1,05 | S9: О.П. п.3.4.30.г | T9: В отношении объектов, реализуемых с привлечением средств бюджета города Москвы, затраты, учитывающие усложненные условия производства работ (стесненность, сложность складирования и транспортной логистики, наличие в зоне производства работ действующего технологического оборудования или движения технологического транспорта и т.п.), определяются заказчиком в задании на проектирование при составлении локальных сметных расчетов (смет): для объектов города Москвы, расположенных за пределами Московской кольцевой автомобильной дороги | U9: Глава 12
A10: 78 | B10: 1 | E10: *1,05 | F10: *1,05 | G10: *1,05 | I10: *1,05 | J10: *1,05 | O10: *1,05 | S10: О.П. п.3.4.30.г | T10: В отношении объектов, реализуемых с привлечением средств бюджета города Москвы, затраты, учитывающие усложненные условия производства работ (стесненность, сложность складирования и транспортной логистики, наличие в зоне производства работ действующего технологического оборудования или движения технологического транспорта и т.п.), определяются заказчиком в задании на проектирование при составлении локальных сметных расчетов (смет): для объектов города Москвы, расположенных за пределами Московской кольцевой автомобильной дороги | U10: Глава 12
A11: 80 | B11: 1 | E11: *1,05 | F11: *1,05 | G11: *1,05 | I11: *1,05 | J11: *1,05 | O11: *1,05 | S11: О.П. п.3.4.30.г | T11: В отношении объектов, реализуемых с привлечением средств бюджета города Москвы, затраты, учитывающие усложненные условия производства работ (стесненность, сложность складирования и транспортной логистики, наличие в зоне производства работ действующего технологического оборудования или движения технологического транспорта и т.п.), определяются заказчиком в задании на проектирование при составлении локальных сметных расчетов (смет): для объектов города Москвы, расположенных за пределами Московской кольцевой автомобильной дороги | U11: Глава 12
A12: 81 | B12: 1 | E12: *1,05 | F12: *1,05 | G12: *1,05 | I12: *1,05 | J12: *1,05 | O12: *1,05 | S12: О.П. п.3.4.30.г | T12: В отношении объектов, реализуемых с привлечением средств бюджета города Москвы, затраты, учитывающие усложненные условия производства работ (стесненность, сложность складирования и транспортной логистики, наличие в зоне производства работ действующего технологического оборудования или движения технологического транспорта и т.п.), определяются заказчиком в задании на проектирование при составлении локальных сметных расчетов (смет): для объектов города Москвы, расположенных за пределами Московской кольцевой автомобильной дороги | U12: Глава 12
A13: 82 | B13: 1 | E13: *1,05 | F13: *1,05 | G13: *1,05 | I13: *1,05 | J13: *1,05 | O13: *1,05 | S13: О.П. п.3.4.30.г | T13: В отношении объектов, реализуемых с привлечением средств бюджета города Москвы, затраты, учитывающие усложненные условия производства работ (стесненность, сложность складирования и транспортной логистики, наличие в зоне производства работ действующего технологического оборудования или движения технологического транспорта и т.п.), определяются заказчиком в задании на проектирование при составлении локальных сметных расчетов (смет): для объектов города Москвы, расположенных за пределами Московской кольцевой автомобильной дороги | U13: Глава 12

Sheet SrcKA
A1: 0 | B1: Smeta.RU (495) 974-1589 | D1: _PS_ | F1: 0 | G1: 0 | H1: 0 | I1: Smeta.RU | K1: 1 | L1: 75112 | M1: 10 | N1: 11 | O1: 15 | P1: 0 | Q1: 1
F12: =Source!F12 -> 02-01-08 Закрытый переход_(2 этап) | G12: =Source!G12 -> 02-01-08 Закрытый переход | AJ12: 0 | CY12: 0
