Workbook

Sheet Смета по ТСН-2001(с доп.43
A1: =Source!B1 -> Smeta.RU (495) 974-1589
J2: Форма № 4б
A3: ПИР, СМР, ПНР, материалы, оборудование (за исключением замков, предоставляемых Заказчиком) по титулу: Строительство ТП-10/0,4кВ с тр-ми 2х400кВА, 4КЛ-10кВ от ТП-10/0,4кВ луч А,Б до КЛ-10кВ направлением ТП-10/0,4кВ № № 21782 - ТП-10/0,4кВ № 24478 луч А,Б, 8КЛ-0,4кВ от ТП-10/0,4кВ до ВРЩ-0,4кВ №1-3, в т.ч. ПИР: г.Москва, ул.Феодосийская, з/у 7 для нужд МКС – филиала ПАО «Россети Московский регион»
A4: (наименование стройки и/или объекта)
A6: ЛОКАЛЬНАЯ СМЕТА № 09-01-04
A8: Транспортировка грунта и мусора (2 этап)
A9: (наименование работ и затрат)
A11: =CONCATENATE( "Основание: чертежи № ", Source!J12) -> Основание: чертежи №
I13: В базисном уровне цен | J13: В текущем уровне цен
E14: Сметная стоимость | I14: =I15+I16+I17+I18 -> 4.87 | J14: =J15+J16+J17+J18 -> 71.22 | K14: тыс.руб.
E15: Строительные работы | I15: =ROUND(SUM(X1:X68)/1000, 2) -> 0 | J15: =ROUND((Source!P231)/1000, 2) -> 0 | K15: тыс.руб.
E16: Работы по монтажу оборудования | I16: =ROUND(SUM(Y1:Y68)/1000, 2) -> 0 | J16: =ROUND((Source!P232)/1000, 2) -> 0 | K16: тыс.руб.
E17: Оборудование | I17: =ROUND(SUM(Z1:Z68)/1000, 2) -> 0 | J17: =ROUND((Source!P223)/1000, 2) -> 0 | K17: тыс.руб.
E18: Прочие работы и затраты | I18: =ROUND(SUM(AA1:AA68)/1000, 2) -> 4.87 | J18: =ROUND((Source!P233+Source!P234)/1000, 2) -> 71.22 | K18: тыс.руб.
E19: Средства на оплату труда | I19: =ROUND(SUM(W1:W68)/1000, 2) -> 0 | J19: =((Source!P229 + Source!P228)/1000) -> 0 | K19: тыс.руб.
E20: Затраты труда | I20: =SUM(AB1:AB68) -> 0 | K20: чел.-ч.
E21: Кроме того:
E22: Возврат материалов | I22: =ROUND(SUM(AE1:AE68)/1000, 2) -> 0 | J22: =SUM(AF1:AF68)/1000 -> 0 | K22: тыс.руб.
A24: Составлен(а) по ТСН-2001 с учетом Дополнения №: 73
A25: № и период сборника коэффициентов (индексов) пересчета: Коэффициенты к ТСН-2001 МГЭ №212 III квартал 2024 года | AP25: № и период сборника коэффициентов (индексов) пересчета: Коэффициенты к ТСН-2001 МГЭ №212 III квартал 2024 года
A26: № п/п | B26: Шифр расценки и коды ресурсов | C26: Наименование работ и затрат | D26: Ед. изм. | E26: Кол-во единиц | F26: Цена на ед. изм., руб. | G26: Попра- вочные коэффи- циенты | H26: Коэффи- циенты зимних удорожа- ний | I26: Всего затрат в базисном уровне цен, руб. | J26: Коэффи- циенты (индек- сы) пере- счета, нормы НР и СП | K26: ВСЕГО затрат в текущем уровне цен, руб.
A27: 1 | B27: 2 | C27: 3 | D27: 4 | E27: 5 | F27: 6 | G27: 7 | H27: 8 | I27: 9 | J27: 10 | K27: 11
A30: =CONCATENATE("Раздел: ",IF(Source!G24<>"Новый раздел", Source!G24, "")) -> Раздел: Благоустройство
A31: 1 | B31: =Source!F29 -> 15.2-50-10 | C31: Перевозка строительного мусора на расстояние до 50 км автосамосвалами грузоподъемностью до 10 т | D31: =Source!DW29 -> т | E31: =Source!I29 -> 10.55 | Q31: =ROUND((Source!DN29/100)*ROUND((ROUND((Source!AF29*Source!AV29*Source!I29),2)),2), 2) -> 0 | R31: =Source!X29 -> 0 | S31: =ROUND((Source!DO29/100)*ROUND((ROUND((Source!AF29*Source!AV29*Source!I29),2)),2), 2) -> 0 | T31: =Source!Y29 -> 0 | U31: =ROUND((175/100)*ROUND((ROUND((Source!AE29*Source!AV29*Source!I29),2)),2), 2) -> 0 | V31: =ROUND((160/100)*ROUND(ROUND((ROUND((Source!AE29*Source!AV29*Source!I29),2)*Source!BS29),2), 2), 2) -> 0 | AI31: 0
C32: ЭМ | F32: =Source!AM29 -> 42.72 | G32: =Source!DE29 | H32: =Source!AV29 -> 1 | I32: =(ROUND((ROUND(((Source!ET29)*Source!AV29*Source!I29),2)),2)+ROUND((ROUND(((Source!AE29-(Source!EU29))*Source!AV29*Source!I29),2)),2)) -> 450.7 | J32: =IF(Source!BB29<> 0, Source!BB29, 1) -> 15.67 | K32: =Source!Q29 -> 7062.47
C33: Всего по позиции: | H33: =I32+0 -> 450.7 | J33: =K32+0 -> 7062.47 | O33: =I32+0 -> 450.7 | P33: =K32+0 -> 7062.47 | X33: =IF(Source!BI29<=1,I32-0, 0) -> 0 | Y33: =IF(Source!BI29=2,I32-0, 0) -> 0 | Z33: =IF(Source!BI29=3,I32-0, 0) -> 0 | AA33: =IF(Source!BI29=4,I32,0) -> 450.7
A35: 2 | B35: =Source!F31 -> 15.1-1300-02 | C35: Лом асфальтовых и асфальтобетонных покрытий малоопасный | D35: =Source!DW31 -> 1 Т | E35: =Source!I31 -> 10.55 | Q35: =ROUND((Source!DN31/100)*ROUND((ROUND((Source!AF31*Source!AV31*Source!I31),2)),2), 2) -> 0 | R35: =Source!X31 -> 0 | S35: =ROUND((Source!DO31/100)*ROUND((ROUND((Source!AF31*Source!AV31*Source!I31),2)),2), 2) -> 0 | T35: =Source!Y31 -> 0 | U35: =ROUND((175/100)*ROUND((ROUND((Source!AE31*Source!AV31*Source!I31),2)),2), 2) -> 0 | V35: =ROUND((160/100)*ROUND(ROUND((ROUND((Source!AE31*Source!AV31*Source!I31),2)*Source!BS31),2), 2), 2) -> 0 | AI35: 0
C36: ЭМ | F36: =Source!AM31 -> 36.59 | G36: =Source!DE31 | H36: =Source!AV31 -> 1 | I36: =(ROUND((ROUND(((Source!ET31)*Source!AV31*Source!I31),2)),2)+ROUND((ROUND(((Source!AE31-(Source!EU31))*Source!AV31*Source!I31),2)),2)) -> 386.02 | J36: =IF(Source!BB31<> 0, Source!BB31, 1) -> 8.2 | K36: =Source!Q31 -> 3165.36
C37: Всего по позиции: | H37: =I36+0 -> 386.02 | J37: =K36+0 -> 3165.36 | O37: =I36+0 -> 386.02 | P37: =K36+0 -> 3165.36 | X37: =IF(Source!BI31<=1,I36-0, 0) -> 0 | Y37: =IF(Source!BI31=2,I36-0, 0) -> 0 | Z37: =IF(Source!BI31=3,I36-0, 0) -> 0 | AA37: =IF(Source!BI31=4,I36,0) -> 386.02
A40: =CONCATENATE("Итого по разделу: ",IF(Source!G39<>"Новый раздел", Source!G39, "")) -> Итого по разделу: Благоустройство | H40: =SUM(O30:O39) -> 836.72 | J40: =SUM(P30:P39) -> 10227.83
A41: Итого по ТСН-2001.16 | H41: =SUM(AC30:AC40) -> 0 | J41: =SUM(AD30:AD40) -> 0
A42: Итого возвратных сумм | H42: =SUM(AE30:AE41) -> 0 | J42: =SUM(AF30:AF41) -> 0
A44: =CONCATENATE("Раздел: ",IF(Source!G69<>"Новый раздел", Source!G69, "")) -> Раздел: 10 кВ и 0,4 кВ
A45: 6 | B45: =Source!F74 -> 15.2-53-4 | C45: Перевозка грунтов скальных и дисперсных несвязных на расстояние до 53 км автосамосвалами грузоподъемностью до 10 т | D45: =Source!DW74 -> т | E45: =Source!I74 -> 69.86 | Q45: =ROUND((Source!DN74/100)*ROUND((ROUND((Source!AF74*Source!AV74*Source!I74),2)),2), 2) -> 0 | R45: =Source!X74 -> 0 | S45: =ROUND((Source!DO74/100)*ROUND((ROUND((Source!AF74*Source!AV74*Source!I74),2)),2), 2) -> 0 | T45: =Source!Y74 -> 0 | U45: =ROUND((175/100)*ROUND((ROUND((Source!AE74*Source!AV74*Source!I74),2)),2), 2) -> 0 | V45: =ROUND((160/100)*ROUND(ROUND((ROUND((Source!AE74*Source!AV74*Source!I74),2)*Source!BS74),2), 2), 2) -> 0 | AI45: 0
C46: ="Объем: "&Source!I74&"=(39,92)*"&"1,75" -> Объем: 69,86=(39,92)*1,75
C47: ЭМ | F47: =Source!AM74 -> 45.1 | G47: =Source!DE74 | H47: =Source!AV74 -> 1 | I47: =(ROUND((ROUND(((Source!ET74)*Source!AV74*Source!I74),2)),2)+ROUND((ROUND(((Source!AE74-(Source!EU74))*Source!AV74*Source!I74),2)),2)) -> 3150.69 | J47: =IF(Source!BB74<> 0, Source!BB74, 1) -> 15.65 | K47: =Source!Q74 -> 49308.3
C48: Всего по позиции: | H48: =I47+0 -> 3150.69 | J48: =K47+0 -> 49308.3 | O48: =I47+0 -> 3150.69 | P48: =K47+0 -> 49308.3 | X48: =IF(Source!BI74<=1,I47-0, 0) -> 0 | Y48: =IF(Source!BI74=2,I47-0, 0) -> 0 | Z48: =IF(Source!BI74=3,I47-0, 0) -> 0 | AA48: =IF(Source!BI74=4,I47,0) -> 3150.69
A50: 7 | B50: =Source!F76 -> 15.1-1102-01 | C50: Отходы грунта при проведении открытых земляных работ практически неопасные | D50: =Source!DW76 -> 1 Т | E50: =Source!I76 -> 69.86 | Q50: =ROUND((Source!DN76/100)*ROUND((ROUND((Source!AF76*Source!AV76*Source!I76),2)),2), 2) -> 0 | R50: =Source!X76 -> 0 | S50: =ROUND((Source!DO76/100)*ROUND((ROUND((Source!AF76*Source!AV76*Source!I76),2)),2), 2) -> 0 | T50: =Source!Y76 -> 0 | U50: =ROUND((175/100)*ROUND((ROUND((Source!AE76*Source!AV76*Source!I76),2)),2), 2) -> 0 | V50: =ROUND((160/100)*ROUND(ROUND((ROUND((Source!AE76*Source!AV76*Source!I76),2)*Source!BS76),2), 2), 2) -> 0 | AI50: 0
C51: ЭМ | F51: =Source!AM76 -> 12.61 | G51: =Source!DE76 | H51: =Source!AV76 -> 1 | I51: =(ROUND((ROUND(((Source!ET76)*Source!AV76*Source!I76),2)),2)+ROUND((ROUND(((Source!AE76-(Source!EU76))*Source!AV76*Source!I76),2)),2)) -> 880.93 | J51: =IF(Source!BB76<> 0, Source!BB76, 1) -> 13.26 | K51: =Source!Q76 -> 11681.13
C52: Всего по позиции: | H52: =I51+0 -> 880.93 | J52: =K51+0 -> 11681.13 | O52: =I51+0 -> 880.93 | P52: =K51+0 -> 11681.13 | X52: =IF(Source!BI76<=1,I51-0, 0) -> 0 | Y52: =IF(Source!BI76=2,I51-0, 0) -> 0 | Z52: =IF(Source!BI76=3,I51-0, 0) -> 0 | AA52: =IF(Source!BI76=4,I51,0) -> 880.93
A55: =CONCATENATE("Итого по разделу: ",IF(Source!G78<>"Новый раздел", Source!G78, "")) -> Итого по разделу: 10 кВ и 0,4 кВ | H55: =SUM(O44:O54) -> 4031.62 | J55: =SUM(P44:P54) -> 60989.43
A56: Итого по ТСН-2001.16 | H56: =SUM(AC44:AC55) -> 0 | J56: =SUM(AD44:AD55) -> 0
A57: Итого возвратных сумм | H57: =SUM(AE44:AE56) -> 0 | J57: =SUM(AF44:AF56) -> 0
A59: Итого по ТСН-2001.16 | H59: =SUM(#REF!) -> #REF! | J59: =SUM(#REF!) -> #REF!
A60: Итого возвратных сумм | H60: =SUM(AE59:AE59) -> 0 | J60: =SUM(AF59:AF59) -> 0
A62: =CONCATENATE("Итого по локальной смете: ",IF(Source!G184<>"Новая локальная смета", Source!G184, "")) -> Итого по локальной смете: | H62: =SUM(O29:O61) -> 4868.34 | J62: =SUM(P29:P61) -> 71217.26
A63: Итого по ТСН-2001.16 | H63: =SUM(AC29:AC62) -> 0 | J63: =SUM(AD29:AD62) -> 0
A64: Итого возвратных сумм | H64: =SUM(AE29:AE63) -> 0 | J64: =SUM(AF29:AF63) -> 0
A66: =CONCATENATE("Итого по смете: ",IF(Source!G214<>"Новый объект", Source!G214, "")) -> Итого по смете: 09-01-04 Транспортировка | H66: =SUM(O1:O65) -> 4868.34 | J66: =SUM(P1:P65) -> 71217.26
A67: Итого по ТСН-2001.16 | H67: =SUM(AC1:AC66) -> 0 | J67: =SUM(AD1:AD66) -> 0
A68: Итого возвратных сумм | H68: =SUM(AE1:AE67) -> 0 | J68: =SUM(AF1:AF67) -> 0
A71: Составил | C71: =IF(Source!AC12<>"", Source!AC12," ") | H71: =IF(Source!AB12<>"", Source!AB12," ")
C72: (должность, подпись, инициалы, фамилия)
A74: Проверил | C74: =IF(Source!AE12<>"", Source!AE12," ") | H74: =IF(Source!AD12<>"", Source!AD12," ")
C75: (должность, подпись, инициалы, фамилия)

Sheet Source
A1: 0 | B1: Smeta.RU (495) 974-1589 | D1: _PS_ | F1: 0 | G1: 0 | H1: 0 | I1: Smeta.RU | K1: 1 | L1: 75112 | M1: 10 | N1: 11 | O1: 15 | P1: 0 | Q1: 1
A12: 1 | B12: 249 | C12: 1 | D12: =ROW(A214) -> 214 | E12: 0 | F12: 09-01-04 Транспортировка_(2 этап) | G12: 09-01-04 Транспортировка | I12: 0 | K12: 0 | L12: 0 | M12: 4098 | O12: 0 | P12: 0 | Q12: 0 | R12: 175 | S12: 160 | T12: 1 | V12: 0 | BB12: 0 | BH12: Сметные нормы списания | BI12: Коды ОКП для ТСН-2001 МГЭ (История развития) | BJ12: 1 | BK12: 1 | BL12: 0 | BM12: 0 | BN12: 1 | BO12: 0 | BP12: 6 | BQ12: 2 | BR12: 1 | BS12: 1 | BT12: 0 | BU12: 0 | BV12: 0 | BW12: 0 | BX12: 0 | BZ12: Типовой расчет для ТСН-2001 МГЭ, Новая методика с выпуска доп. 43 (Строительство), Доп 73 | CA12: История развития для ТСН-2001 (МГЭ) 73 доп от 17.07.2024 | CB12: История развития для ТСН-2001 (МГЭ) 73 доп от 17.07.2024 | CC12: История развития для ТСН-2001 (МГЭ) 73 доп от 17.07.2024 | CD12: История развития для ТСН-2001 (МГЭ) 73 доп от 17.07.2024 | CE12: Поправки для ТСН-2001 от 16.04.2024 г. доп.72 | CF12: 0 | CG12: 0 | CH12: 8 | CK12: 79 | CQ12: Территориальные сметные нормативы для Москвы (ТСН-2001) | CR12: ТЕР | CS12: 41660 | CT12: 1 | CU12: 73 | CY12: 0 | EC12: 0
A15: 15 | B15: 1
A18: 52 | B18: =B214 -> 249 | C18: =C214 -> 1 | D18: =D214 -> 12 | E18: =E214 -> 0 | F18: =F214 -> 09-01-04 Транспортировка_(2 этап) | G18: =G214 -> 09-01-04 Транспортировка | O18: =O214 -> 4868.34 | P18: =P214 -> 0 | Q18: =Q214 -> 4868.34 | R18: =R214 -> 0 | S18: =S214 -> 0 | T18: =T214 -> 0 | U18: =U214 -> 0 | V18: =V214 -> 0 | ... GX18: =GX214 -> 0
A20: 3 | B20: 1 | D20: =ROW(A184) -> 184 | F20: Новая локальная смета | G20: Новая локальная смета | I20: 0 | K20: 0 | L20: Новая локальная смета | S20: 0 | T20: 0 | V20: 0 | BX20: 0 | CF20: 0 | CG20: 0
A22: 52 | B22: =B184 -> 1 | C22: =C184 -> 3 | D22: =D184 -> 20 | E22: =E184 -> 0 | F22: =F184 -> Новая локальная смета | G22: =G184 -> Новая локальная смета | O22: =O184 -> 4868.34 | P22: =P184 -> 0 | Q22: =Q184 -> 4868.34 | R22: =R184 -> 0 | S22: =S184 -> 0 | T22: =T184 -> 0 | U22: =U184 -> 0 | V22: =V184 -> 0 | ... GX22: =GX184 -> 0
A24: 4 | B24: 1 | D24: =ROW(A39) -> 39 | F24: Новый раздел | G24: Благоустройство | I24: 0 | K24: 0 | S24: 0 | T24: 0 | V24: 0 | BX24: 0 | CJ24: 0
A26: 52 | B26: =B39 -> 1 | C26: =C39 -> 4 | D26: =D39 -> 24 | E26: =E39 -> 0 | F26: =F39 -> Новый раздел | G26: =G39 -> Благоустройство | O26: =O39 -> 836.72 | P26: =P39 -> 0 | Q26: =Q39 -> 836.72 | R26: =R39 -> 0 | S26: =S39 -> 0 | T26: =T39 -> 0 | U26: =U39 -> 0 | V26: =V39 -> 0 | ... GX26: =GX39 -> 0
A28: 17 | B28: 1 | C28: =ROW(SmtRes!A1) -> 1 | D28: =ROW(EtalonRes!A1) -> 1 | E28: 1 | F28: 15.2-50-10 | G28: Перевозка строительного мусора на расстояние до 50 км автосамосвалами грузоподъемностью до 10 т | H28: т | I28: 10.55 | J28: 0 | K28: 10.55 | O28: =ROUND(CP28,2) -> 450.7 | P28: =ROUND((ROUND((AC28*AW28*I28),2)*BC28),2) -> 0 | Q28: =(ROUND((ROUND(((ET28)*AV28*I28),2)*BB28),2)+ROUND((ROUND(((AE28-(EU28))*AV28*I28),2)*BS28),2)) -> 450.7 | R28: =ROUND((ROUND((AE28*AV28*I28),2)*BS28),2) -> 0 | S28: =ROUND((ROUND((AF28*AV28*I28),2)*BA28),2) -> 0 | T28: =ROUND(CU28*I28,2) -> 0 | U28: =CV28*I28 -> 0 | V28: =CW28*I28 -> 0 | W28: =ROUND(CX28*I28,2) -> 0 | X28: =ROUND(CY28,2) -> 0 | Y28: =ROUND(CZ28,2) -> 0 | AA28: 57734472 | AB28: =ROUND((AC28+AD28+AF28),6) -> 42.72 | AC28: =ROUND((ES28),6) -> 0 | AD28: =ROUND((((ET28)-(EU28))+AE28),6) -> 42.72 | AE28: =ROUND((EU28),6) -> 0 | AF28: =ROUND((EV28),6) -> 0 | AG28: =ROUND((AP28),6) -> 0 | AH28: =(EW28) -> 0 | AI28: =(EX28) -> 0 | AJ28: =(AS28) -> 0 | AK28: 42.72 | AL28: 0 | AM28: 42.72 | AN28: 0 | AO28: 0 | AP28: 0 | AQ28: 0 | AR28: 0 | AS28: 0 | AT28: 0 | AU28: 0 | AV28: 1 | AW28: 1 | AZ28: 1 | BA28: 1 | BB28: 1 | BC28: 1 | BH28: 0 | BI28: 4 | BJ28: ТСН-2001.15 Доп. 68, Сб. 2, т. 50, поз. 10 | BM28: 1113 | BN28: 0 | BP28: 0 | BQ28: 150 | BR28: 0 | BS28: 1 | BT28: 1 | BU28: 1 | BV28: 1 | BW28: 1 | BX28: 1 | BZ28: 0 | CA28: 0 | CE28: 30 | CF28: 0 | CG28: 0 | CM28: 0 | CO28: 0 | CP28: =(P28+Q28+S28) -> 450.7 | CQ28: =ROUND((ROUND((AC28*AW28*1),2)*BC28),2) -> 0 | CR28: =(ROUND((ROUND(((ET28)*AV28*1),2)*BB28),2)+ROUND((ROUND(((AE28-(EU28))*AV28*1),2)*BS28),2)) -> 42.72 | CS28: =ROUND((ROUND((AE28*AV28*1),2)*BS28),2) -> 0 | CT28: =ROUND((ROUND((AF28*AV28*1),2)*BA28),2) -> 0 | CU28: =AG28 -> 0 | CV28: =(AH28*AV28) -> 0 | CW28: =AI28 -> 0 | CX28: =AJ28 -> 0 | CY28: =((S28*BZ28)/100) -> 0 | CZ28: =((S28*CA28)/100) -> 0 | DN28: 0 | DO28: 0 | DP28: 1 | DQ28: 1 | DU28: 1009 | DV28: т | DW28: т | DX28: 1000 | EE28: 51697152 | EF28: 150 | EG28: Транспортные затраты | EH28: 0 | EJ28: 4 | EK28: 1113 | EL28: ТСН-2001.15-1. Перевозка строительного мусора | EM28: ТСН-2001.15-1-5 | EQ28: 131072 | ER28: 42.72 | ES28: 0 | ET28: 42.72 | EU28: 0 | EV28: 0 | EW28: 0 | EX28: 0 | EY28: 0 | FQ28: 0 | FR28: 0 | FS28: 0 | FX28: 0 | FY28: 0 | GD28: 1 | GF28: -444714868 | GG28: 2 | GH28: 1 | GI28: -2 | GJ28: 0 | GK28: 0 | GL28: =ROUND(IF(AND(BH28=3,BI28=3,FS28<>0),P28,0),2) -> 0 | GM28: =ROUND(O28+X28+Y28,2)+GX28 -> 450.7 | GN28: =IF(OR(BI28=0,BI28=1),GM28-GX28,0) -> 0 | GO28: =IF(BI28=2,GM28-GX28,0) -> 0 | GP28: =IF(BI28=4,GM28-GX28,0) -> 450.7 | GR28: 0 | GS28: 0 | GT28: 0 | GV28: =ROUND((GT28),6) -> 0 | GW28: 1 | GX28: =ROUND(HC28*I28,2) -> 0 | HA28: 0 | HB28: 0 | HC28: =GV28*GW28 -> 0 | HS28: 0 | IK28: 0
A29: 17 | B29: 1 | C29: =ROW(SmtRes!A2) -> 2 | D29: =ROW(EtalonRes!A2) -> 2 | E29: 1 | F29: 15.2-50-10 | G29: Перевозка строительного мусора на расстояние до 50 км автосамосвалами грузоподъемностью до 10 т | H29: т | I29: 10.55 | J29: 0 | K29: 10.55 | O29: =ROUND(CP29,2) -> 7062.47 | P29: =ROUND((ROUND((AC29*AW29*I29),2)*BC29),2) -> 0 | Q29: =(ROUND((ROUND(((ET29)*AV29*I29),2)*BB29),2)+ROUND((ROUND(((AE29-(EU29))*AV29*I29),2)*BS29),2)) -> 7062.47 | R29: =ROUND((ROUND((AE29*AV29*I29),2)*BS29),2) -> 0 | S29: =ROUND((ROUND((AF29*AV29*I29),2)*BA29),2) -> 0 | T29: =ROUND(CU29*I29,2) -> 0 | U29: =CV29*I29 -> 0 | V29: =CW29*I29 -> 0 | W29: =ROUND(CX29*I29,2) -> 0 | X29: =ROUND(CY29,2) -> 0 | Y29: =ROUND(CZ29,2) -> 0 | AA29: 57734470 | AB29: =ROUND((AC29+AD29+AF29),6) -> 42.72 | AC29: =ROUND((ES29),6) -> 0 | AD29: =ROUND((((ET29)-(EU29))+AE29),6) -> 42.72 | AE29: =ROUND((EU29),6) -> 0 | AF29: =ROUND((EV29),6) -> 0 | AG29: =ROUND((AP29),6) -> 0 | AH29: =(EW29) -> 0 | AI29: =(EX29) -> 0 | AJ29: =(AS29) -> 0 | AK29: 42.72 | AL29: 0 | AM29: 42.72 | AN29: 0 | AO29: 0 | AP29: 0 | AQ29: 0 | AR29: 0 | AS29: 0 | AT29: 95 | AU29: 65 | AV29: 1 | AW29: 1 | AZ29: 1 | BA29: 1 | BB29: 15.67 | BC29: 1 | BH29: 0 | BI29: 4 | BJ29: ТСН-2001.15 Доп. 68, Сб. 2, т. 50, поз. 10 | BM29: 1113 | BN29: 0 | BO29: 15.2-50-10 | BP29: 1 | BQ29: 150 | BR29: 0 | BS29: 1 | BT29: 1 | BU29: 1 | BV29: 1 | BW29: 1 | BX29: 1 | BZ29: 95 | CA29: 65 | CE29: 30 | CF29: 0 | CG29: 0 | CM29: 0 | CO29: 0 | CP29: =(P29+Q29+S29) -> 7062.47 | CQ29: =ROUND((ROUND((AC29*AW29*1),2)*BC29),2) -> 0 | CR29: =(ROUND((ROUND(((ET29)*AV29*1),2)*BB29),2)+ROUND((ROUND(((AE29-(EU29))*AV29*1),2)*BS29),2)) -> 669.42 | CS29: =ROUND((ROUND((AE29*AV29*1),2)*BS29),2) -> 0 | CT29: =ROUND((ROUND((AF29*AV29*1),2)*BA29),2) -> 0 | CU29: =AG29 -> 0 | CV29: =(AH29*AV29) -> 0 | CW29: =AI29 -> 0 | CX29: =AJ29 -> 0 | CY29: =S29*(BZ29/100) -> 0 | CZ29: =S29*(CA29/100) -> 0 | DN29: 0 | DO29: 0 | DP29: 1 | DQ29: 1 | DU29: 1009 | DV29: т | DW29: т | DX29: 1000 | EE29: 51697152 | EF29: 150 | EG29: Транспортные затраты | EH29: 0 | EJ29: 4 | EK29: 1113 | EL29: ТСН-2001.15-1. Перевозка строительного мусора | EM29: ТСН-2001.15-1-5 | EQ29: 131072 | ER29: 42.72 | ES29: 0 | ET29: 42.72 | EU29: 0 | EV29: 0 | EW29: 0 | EX29: 0 | EY29: 0 | FQ29: 0 | FR29: 0 | FS29: 0 | FX29: 0 | FY29: 0 | GD29: 0 | GF29: -444714868 | GG29: 2 | GH29: 1 | GI29: 2 | GJ29: 0 | GK29: =ROUND(R29*(S12)/100,2) -> 0 | GL29: =ROUND(IF(AND(BH29=3,BI29=3,FS29<>0),P29,0),2) -> 0 | GM29: =ROUND(O29+X29+Y29+GK29,2)+GX29 -> 7062.47 | GN29: =IF(OR(BI29=0,BI29=1),GM29-GX29,0) -> 0 | GO29: =IF(BI29=2,GM29-GX29,0) -> 0 | GP29: =IF(BI29=4,GM29-GX29,0) -> 7062.47 | GR29: 0 | GS29: 3 | GT29: 0 | GV29: =ROUND((GT29),6) -> 0 | GW29: 1 | GX29: =ROUND(HC29*I29,2) -> 0 | HA29: 0 | HB29: 0 | HC29: =GV29*GW29 -> 0 | HS29: 0 | IK29: 0
A30: 17 | B30: 1 | D30: =ROW(EtalonRes!A3) -> 3 | E30: 2 | F30: 15.1-1300-02 | G30: Лом асфальтовых и асфальтобетонных покрытий малоопасный | H30: 1 Т | I30: 10.55 | J30: 0 | K30: 10.55 | O30: =ROUND(CP30,2) -> 386.02 | P30: =ROUND((ROUND((AC30*AW30*I30),2)*BC30),2) -> 0 | Q30: =(ROUND((ROUND(((ET30)*AV30*I30),2)*BB30),2)+ROUND((ROUND(((AE30-(EU30))*AV30*I30),2)*BS30),2)) -> 386.02 | R30: =ROUND((ROUND((AE30*AV30*I30),2)*BS30),2) -> 0 | S30: =ROUND((ROUND((AF30*AV30*I30),2)*BA30),2) -> 0 | T30: =ROUND(CU30*I30,2) -> 0 | U30: =CV30*I30 -> 0 | V30: =CW30*I30 -> 0 | W30: =ROUND(CX30*I30,2) -> 0 | X30: =ROUND(CY30,2) -> 0 | Y30: =ROUND(CZ30,2) -> 0 | AA30: 57734472 | AB30: =ROUND((AC30+AD30+AF30),6) -> 36.59 | AC30: =ROUND((ES30),6) -> 0 | AD30: =ROUND((((ET30)-(EU30))+AE30),6) -> 36.59 | AE30: =ROUND((EU30),6) -> 0 | AF30: =ROUND((EV30),6) -> 0 | AG30: =ROUND((AP30),6) -> 0 | AH30: =(EW30) -> 0 | AI30: =(EX30) -> 0 | AJ30: =(AS30) -> 0 | AK30: 36.59 | AL30: 0 | AM30: 36.59 | AN30: 0 | AO30: 0 | AP30: 0 | AQ30: 0 | AR30: 0 | AS30: 0 | AT30: 0 | AU30: 0 | AV30: 1 | AW30: 1 | AZ30: 1 | BA30: 1 | BB30: 1 | BC30: 1 | BH30: 0 | BI30: 4 | BJ30: ТСН-2001.15 Доп. 56, Сб. 1, т. 1300, поз. 2 | BM30: 1113 | BN30: 0 | BP30: 0 | BQ30: 150 | BR30: 0 | BS30: 1 | BT30: 1 | BU30: 1 | BV30: 1 | BW30: 1 | BX30: 1 | BZ30: 0 | CA30: 0 | CE30: 30 | CF30: 0 | CG30: 0 | CM30: 0 | CO30: 0 | CP30: =(P30+Q30+S30) -> 386.02 | CQ30: =ROUND((ROUND((AC30*AW30*1),2)*BC30),2) -> 0 | CR30: =(ROUND((ROUND(((ET30)*AV30*1),2)*BB30),2)+ROUND((ROUND(((AE30-(EU30))*AV30*1),2)*BS30),2)) -> 36.59 | CS30: =ROUND((ROUND((AE30*AV30*1),2)*BS30),2) -> 0 | CT30: =ROUND((ROUND((AF30*AV30*1),2)*BA30),2) -> 0 | CU30: =AG30 -> 0 | CV30: =(AH30*AV30) -> 0 | CW30: =AI30 -> 0 | CX30: =AJ30 -> 0 | CY30: =((S30*BZ30)/100) -> 0 | CZ30: =((S30*CA30)/100) -> 0 | DN30: 0 | DO30: 0 | DP30: 1 | DQ30: 1 | DU30: 1013 | DV30: 1 Т | DW30: 1 Т | DX30: 1 | EE30: 51697152 | EF30: 150 | EG30: Транспортные затраты | EH30: 0 | EJ30: 4 | EK30: 1113 | EL30: ТСН-2001.15-1. Перевозка строительного мусора | EM30: ТСН-2001.15-1-5 | EQ30: 131072 | ER30: 36.59 | ES30: 0 | ET30: 36.59 | EU30: 0 | EV30: 0 | EW30: 0 | EX30: 0 | EY30: 0 | FQ30: 0 | FR30: 0 | FS30: 0 | FX30: 0 | FY30: 0 | GD30: 1 | GF30: 1137320751 | GG30: 2 | GH30: 1 | GI30: -2 | GJ30: 0 | GK30: 0 | GL30: =ROUND(IF(AND(BH30=3,BI30=3,FS30<>0),P30,0),2) -> 0 | GM30: =ROUND(O30+X30+Y30,2)+GX30 -> 386.02 | GN30: =IF(OR(BI30=0,BI30=1),GM30-GX30,0) -> 0 | GO30: =IF(BI30=2,GM30-GX30,0) -> 0 | GP30: =IF(BI30=4,GM30-GX30,0) -> 386.02 | GR30: 0 | GS30: 0 | GT30: 0 | GV30: =ROUND((GT30),6) -> 0 | GW30: 1 | GX30: =ROUND(HC30*I30,2) -> 0 | HA30: 0 | HB30: 0 | HC30: =GV30*GW30 -> 0 | HS30: 0 | IK30: 0
A31: 17 | B31: 1 | D31: =ROW(EtalonRes!A4) -> 4 | E31: 2 | F31: 15.1-1300-02 | G31: Лом асфальтовых и асфальтобетонных покрытий малоопасный | H31: 1 Т | I31: 10.55 | J31: 0 | K31: 10.55 | O31: =ROUND(CP31,2) -> 3165.36 | P31: =ROUND((ROUND((AC31*AW31*I31),2)*BC31),2) -> 0 | Q31: =(ROUND((ROUND(((ET31)*AV31*I31),2)*BB31),2)+ROUND((ROUND(((AE31-(EU31))*AV31*I31),2)*BS31),2)) -> 3165.36 | R31: =ROUND((ROUND((AE31*AV31*I31),2)*BS31),2) -> 0 | S31: =ROUND((ROUND((AF31*AV31*I31),2)*BA31),2) -> 0 | T31: =ROUND(CU31*I31,2) -> 0 | U31: =CV31*I31 -> 0 | V31: =CW31*I31 -> 0 | W31: =ROUND(CX31*I31,2) -> 0 | X31: =ROUND(CY31,2) -> 0 | Y31: =ROUND(CZ31,2) -> 0 | AA31: 57734470 | AB31: =ROUND((AC31+AD31+AF31),6) -> 36.59 | AC31: =ROUND((ES31),6) -> 0 | AD31: =ROUND((((ET31)-(EU31))+AE31),6) -> 36.59 | AE31: =ROUND((EU31),6) -> 0 | AF31: =ROUND((EV31),6) -> 0 | AG31: =ROUND((AP31),6) -> 0 | AH31: =(EW31) -> 0 | AI31: =(EX31) -> 0 | AJ31: =(AS31) -> 0 | AK31: 36.59 | AL31: 0 | AM31: 36.59 | AN31: 0 | AO31: 0 | AP31: 0 | AQ31: 0 | AR31: 0 | AS31: 0 | AT31: 95 | AU31: 65 | AV31: 1 | AW31: 1 | AZ31: 1 | BA31: 1 | BB31: 8.2 | BC31: 1 | BH31: 0 | BI31: 4 | BJ31: ТСН-2001.15 Доп. 56, Сб. 1, т. 1300, поз. 2 | BM31: 1113 | BN31: 0 | BO31: 15.1-1300-02 | BP31: 1 | BQ31: 150 | BR31: 0 | BS31: 1 | BT31: 1 | BU31: 1 | BV31: 1 | BW31: 1 | BX31: 1 | BZ31: 95 | CA31: 65 | CE31: 30 | CF31: 0 | CG31: 0 | CM31: 0 | CO31: 0 | CP31: =(P31+Q31+S31) -> 3165.36 | CQ31: =ROUND((ROUND((AC31*AW31*1),2)*BC31),2) -> 0 | CR31: =(ROUND((ROUND(((ET31)*AV31*1),2)*BB31),2)+ROUND((ROUND(((AE31-(EU31))*AV31*1),2)*BS31),2)) -> 300.04 | CS31: =ROUND((ROUND((AE31*AV31*1),2)*BS31),2) -> 0 | CT31: =ROUND((ROUND((AF31*AV31*1),2)*BA31),2) -> 0 | CU31: =AG31 -> 0 | CV31: =(AH31*AV31) -> 0 | CW31: =AI31 -> 0 | CX31: =AJ31 -> 0 | CY31: =S31*(BZ31/100) -> 0 | CZ31: =S31*(CA31/100) -> 0 | DN31: 0 | DO31: 0 | DP31: 1 | DQ31: 1 | DU31: 1013 | DV31: 1 Т | DW31: 1 Т | DX31: 1 | EE31: 51697152 | EF31: 150 | EG31: Транспортные затраты | EH31: 0 | EJ31: 4 | EK31: 1113 | EL31: ТСН-2001.15-1. Перевозка строительного мусора | EM31: ТСН-2001.15-1-5 | EQ31: 131072 | ER31: 36.59 | ES31: 0 | ET31: 36.59 | EU31: 0 | EV31: 0 | EW31: 0 | EX31: 0 | EY31: 0 | FQ31: 0 | FR31: 0 | FS31: 0 | FX31: 0 | FY31: 0 | GD31: 0 | GF31: 1137320751 | GG31: 2 | GH31: 1 | GI31: 2 | GJ31: 0 | GK31: =ROUND(R31*(S12)/100,2) -> 0 | GL31: =ROUND(IF(AND(BH31=3,BI31=3,FS31<>0),P31,0),2) -> 0 | GM31: =ROUND(O31+X31+Y31+GK31,2)+GX31 -> 3165.36 | GN31: =IF(OR(BI31=0,BI31=1),GM31-GX31,0) -> 0 | GO31: =IF(BI31=2,GM31-GX31,0) -> 0 | GP31: =IF(BI31=4,GM31-GX31,0) -> 3165.36 | GR31: 0 | GS31: 3 | GT31: 0 | GV31: =ROUND((GT31),6) -> 0 | GW31: 1 | GX31: =ROUND(HC31*I31,2) -> 0 | HA31: 0 | HB31: 0 | HC31: =GV31*GW31 -> 0 | HS31: 0 | IK31: 0
A32: 17 | B32: 1 | D32: =ROW(EtalonRes!A5) -> 5 | E32: 3 | F32: 15.1-1201-03 | G32: Лом бетонных изделий, отходы бетона в кусковой форме, практически неопасные | H32: 1 Т | I32: 0 | J32: 0 | K32: 0 | O32: =ROUND(CP32,2) -> 0 | P32: =ROUND((ROUND((AC32*AW32*I32),2)*BC32),2) -> 0 | Q32: =(ROUND((ROUND(((ET32)*AV32*I32),2)*BB32),2)+ROUND((ROUND(((AE32-(EU32))*AV32*I32),2)*BS32),2)) -> 0 | R32: =ROUND((ROUND((AE32*AV32*I32),2)*BS32),2) -> 0 | S32: =ROUND((ROUND((AF32*AV32*I32),2)*BA32),2) -> 0 | T32: =ROUND(CU32*I32,2) -> 0 | U32: =CV32*I32 -> 0 | V32: =CW32*I32 -> 0 | W32: =ROUND(CX32*I32,2) -> 0 | X32: =ROUND(CY32,2) -> 0 | Y32: =ROUND(CZ32,2) -> 0 | AA32: 57734472 | AB32: =ROUND((AC32+AD32+AF32),6) -> 22.57 | AC32: =ROUND((ES32),6) -> 0 | AD32: =ROUND((((ET32)-(EU32))+AE32),6) -> 22.57 | AE32: =ROUND((EU32),6) -> 0 | AF32: =ROUND((EV32),6) -> 0 | AG32: =ROUND((AP32),6) -> 0 | AH32: =(EW32) -> 0 | AI32: =(EX32) -> 0 | AJ32: =(AS32) -> 0 | AK32: 22.57 | AL32: 0 | AM32: 22.57 | AN32: 0 | AO32: 0 | AP32: 0 | AQ32: 0 | AR32: 0 | AS32: 0 | AT32: 0 | AU32: 0 | AV32: 1 | AW32: 1 | AZ32: 1 | BA32: 1 | BB32: 1 | BC32: 1 | BH32: 0 | BI32: 4 | BJ32: ТСН-2001.15 Доп. 56, Сб. 1, т. 1201, поз. 3 | BM32: 1113 | BN32: 0 | BP32: 0 | BQ32: 150 | BR32: 0 | BS32: 1 | BT32: 1 | BU32: 1 | BV32: 1 | BW32: 1 | BX32: 1 | BZ32: 0 | CA32: 0 | CE32: 30 | CF32: 0 | CG32: 0 | CM32: 0 | CO32: 0 | CP32: =(P32+Q32+S32) -> 0 | CQ32: =ROUND((ROUND((AC32*AW32*1),2)*BC32),2) -> 0 | CR32: =(ROUND((ROUND(((ET32)*AV32*1),2)*BB32),2)+ROUND((ROUND(((AE32-(EU32))*AV32*1),2)*BS32),2)) -> 22.57 | CS32: =ROUND((ROUND((AE32*AV32*1),2)*BS32),2) -> 0 | CT32: =ROUND((ROUND((AF32*AV32*1),2)*BA32),2) -> 0 | CU32: =AG32 -> 0 | CV32: =(AH32*AV32) -> 0 | CW32: =AI32 -> 0 | CX32: =AJ32 -> 0 | CY32: =((S32*BZ32)/100) -> 0 | CZ32: =((S32*CA32)/100) -> 0 | DN32: 0 | DO32: 0 | DP32: 1 | DQ32: 1 | DU32: 1013 | DV32: 1 Т | DW32: 1 Т | DX32: 1 | EE32: 51697152 | EF32: 150 | EG32: Транспортные затраты | EH32: 0 | EJ32: 4 | EK32: 1113 | EL32: ТСН-2001.15-1. Перевозка строительного мусора | EM32: ТСН-2001.15-1-5 | EQ32: 131072 | ER32: 22.57 | ES32: 0 | ET32: 22.57 | EU32: 0 | EV32: 0 | EW32: 0 | EX32: 0 | EY32: 0 | FQ32: 0 | FR32: 0 | FS32: 0 | FX32: 0 | FY32: 0 | GD32: 1 | GF32: -1150173431 | GG32: 2 | GH32: 1 | GI32: -2 | GJ32: 0 | GK32: 0 | GL32: =ROUND(IF(AND(BH32=3,BI32=3,FS32<>0),P32,0),2) -> 0 | GM32: =ROUND(O32+X32+Y32,2)+GX32 -> 0 | GN32: =IF(OR(BI32=0,BI32=1),GM32-GX32,0) -> 0 | GO32: =IF(BI32=2,GM32-GX32,0) -> 0 | GP32: =IF(BI32=4,GM32-GX32,0) -> 0 | GR32: 0 | GS32: 0 | GT32: 0 | GV32: =ROUND((GT32),6) -> 0 | GW32: 1 | GX32: =ROUND(HC32*I32,2) -> 0 | HA32: 0 | HB32: 0 | HC32: =GV32*GW32 -> 0 | HS32: 0 | IK32: 0
A33: 17 | B33: 1 | D33: =ROW(EtalonRes!A6) -> 6 | E33: 3 | F33: 15.1-1201-03 | G33: Лом бетонных изделий, отходы бетона в кусковой форме, практически неопасные | H33: 1 Т | I33: 0 | J33: 0 | K33: 0 | O33: =ROUND(CP33,2) -> 0 | P33: =ROUND((ROUND((AC33*AW33*I33),2)*BC33),2) -> 0 | Q33: =(ROUND((ROUND(((ET33)*AV33*I33),2)*BB33),2)+ROUND((ROUND(((AE33-(EU33))*AV33*I33),2)*BS33),2)) -> 0 | R33: =ROUND((ROUND((AE33*AV33*I33),2)*BS33),2) -> 0 | S33: =ROUND((ROUND((AF33*AV33*I33),2)*BA33),2) -> 0 | T33: =ROUND(CU33*I33,2) -> 0 | U33: =CV33*I33 -> 0 | V33: =CW33*I33 -> 0 | W33: =ROUND(CX33*I33,2) -> 0 | X33: =ROUND(CY33,2) -> 0 | Y33: =ROUND(CZ33,2) -> 0 | AA33: 57734470 | AB33: =ROUND((AC33+AD33+AF33),6) -> 22.57 | AC33: =ROUND((ES33),6) -> 0 | AD33: =ROUND((((ET33)-(EU33))+AE33),6) -> 22.57 | AE33: =ROUND((EU33),6) -> 0 | AF33: =ROUND((EV33),6) -> 0 | AG33: =ROUND((AP33),6) -> 0 | AH33: =(EW33) -> 0 | AI33: =(EX33) -> 0 | AJ33: =(AS33) -> 0 | AK33: 22.57 | AL33: 0 | AM33: 22.57 | AN33: 0 | AO33: 0 | AP33: 0 | AQ33: 0 | AR33: 0 | AS33: 0 | AT33: 95 | AU33: 65 | AV33: 1 | AW33: 1 | AZ33: 1 | BA33: 1 | BB33: 6.48 | BC33: 1 | BH33: 0 | BI33: 4 | BJ33: ТСН-2001.15 Доп. 56, Сб. 1, т. 1201, поз. 3 | BM33: 1113 | BN33: 0 | BO33: 15.1-1201-03 | BP33: 1 | BQ33: 150 | BR33: 0 | BS33: 1 | BT33: 1 | BU33: 1 | BV33: 1 | BW33: 1 | BX33: 1 | BZ33: 95 | CA33: 65 | CE33: 30 | CF33: 0 | CG33: 0 | CM33: 0 | CO33: 0 | CP33: =(P33+Q33+S33) -> 0 | CQ33: =ROUND((ROUND((AC33*AW33*1),2)*BC33),2) -> 0 | CR33: =(ROUND((ROUND(((ET33)*AV33*1),2)*BB33),2)+ROUND((ROUND(((AE33-(EU33))*AV33*1),2)*BS33),2)) -> 146.25 | CS33: =ROUND((ROUND((AE33*AV33*1),2)*BS33),2) -> 0 | CT33: =ROUND((ROUND((AF33*AV33*1),2)*BA33),2) -> 0 | CU33: =AG33 -> 0 | CV33: =(AH33*AV33) -> 0 | CW33: =AI33 -> 0 | CX33: =AJ33 -> 0 | CY33: =S33*(BZ33/100) -> 0 | CZ33: =S33*(CA33/100) -> 0 | DN33: 0 | DO33: 0 | DP33: 1 | DQ33: 1 | DU33: 1013 | DV33: 1 Т | DW33: 1 Т | DX33: 1 | EE33: 51697152 | EF33: 150 | EG33: Транспортные затраты | EH33: 0 | EJ33: 4 | EK33: 1113 | EL33: ТСН-2001.15-1. Перевозка строительного мусора | EM33: ТСН-2001.15-1-5 | EQ33: 131072 | ER33: 22.57 | ES33: 0 | ET33: 22.57 | EU33: 0 | EV33: 0 | EW33: 0 | EX33: 0 | EY33: 0 | FQ33: 0 | FR33: 0 | FS33: 0 | FX33: 0 | FY33: 0 | GD33: 0 | GF33: -1150173431 | GG33: 2 | GH33: 1 | GI33: 2 | GJ33: 0 | GK33: =ROUND(R33*(S12)/100,2) -> 0 | GL33: =ROUND(IF(AND(BH33=3,BI33=3,FS33<>0),P33,0),2) -> 0 | GM33: =ROUND(O33+X33+Y33+GK33,2)+GX33 -> 0 | GN33: =IF(OR(BI33=0,BI33=1),GM33-GX33,0) -> 0 | GO33: =IF(BI33=2,GM33-GX33,0) -> 0 | GP33: =IF(BI33=4,GM33-GX33,0) -> 0 | GR33: 0 | GS33: 3 | GT33: 0 | GV33: =ROUND((GT33),6) -> 0 | GW33: 1 | GX33: =ROUND(HC33*I33,2) -> 0 | HA33: 0 | HB33: 0 | HC33: =GV33*GW33 -> 0 | HS33: 0 | IK33: 0
A34: 17 | B34: 1 | D34: =ROW(EtalonRes!A7) -> 7 | E34: 4 | F34: 15.1-1106-02 | G34: Отходы строительного щебня незагрязненные практически неопасные | H34: 1 Т | I34: 0 | J34: 0 | K34: 0 | O34: =ROUND(CP34,2) -> 0 | P34: =ROUND((ROUND((AC34*AW34*I34),2)*BC34),2) -> 0 | Q34: =(ROUND((ROUND(((ET34)*AV34*I34),2)*BB34),2)+ROUND((ROUND(((AE34-(EU34))*AV34*I34),2)*BS34),2)) -> 0 | R34: =ROUND((ROUND((AE34*AV34*I34),2)*BS34),2) -> 0 | S34: =ROUND((ROUND((AF34*AV34*I34),2)*BA34),2) -> 0 | T34: =ROUND(CU34*I34,2) -> 0 | U34: =CV34*I34 -> 0 | V34: =CW34*I34 -> 0 | W34: =ROUND(CX34*I34,2) -> 0 | X34: =ROUND(CY34,2) -> 0 | Y34: =ROUND(CZ34,2) -> 0 | AA34: 57734472 | AB34: =ROUND((AC34+AD34+AF34),6) -> 17.84 | AC34: =ROUND((ES34),6) -> 0 | AD34: =ROUND((((ET34)-(EU34))+AE34),6) -> 17.84 | AE34: =ROUND((EU34),6) -> 0 | AF34: =ROUND((EV34),6) -> 0 | AG34: =ROUND((AP34),6) -> 0 | AH34: =(EW34) -> 0 | AI34: =(EX34) -> 0 | AJ34: =(AS34) -> 0 | AK34: 17.84 | AL34: 0 | AM34: 17.84 | AN34: 0 | AO34: 0 | AP34: 0 | AQ34: 0 | AR34: 0 | AS34: 0 | AT34: 0 | AU34: 0 | AV34: 1 | AW34: 1 | AZ34: 1 | BA34: 1 | BB34: 1 | BC34: 1 | BH34: 0 | BI34: 4 | BJ34: ТСН-2001.15 Доп. 68, Сб. 1, т. 1106, поз. 2 | BM34: 1113 | BN34: 0 | BP34: 0 | BQ34: 150 | BR34: 0 | BS34: 1 | BT34: 1 | BU34: 1 | BV34: 1 | BW34: 1 | BX34: 1 | BZ34: 0 | CA34: 0 | CE34: 30 | CF34: 0 | CG34: 0 | CM34: 0 | CO34: 0 | CP34: =(P34+Q34+S34) -> 0 | CQ34: =ROUND((ROUND((AC34*AW34*1),2)*BC34),2) -> 0 | CR34: =(ROUND((ROUND(((ET34)*AV34*1),2)*BB34),2)+ROUND((ROUND(((AE34-(EU34))*AV34*1),2)*BS34),2)) -> 17.84 | CS34: =ROUND((ROUND((AE34*AV34*1),2)*BS34),2) -> 0 | CT34: =ROUND((ROUND((AF34*AV34*1),2)*BA34),2) -> 0 | CU34: =AG34 -> 0 | CV34: =(AH34*AV34) -> 0 | CW34: =AI34 -> 0 | CX34: =AJ34 -> 0 | CY34: =((S34*BZ34)/100) -> 0 | CZ34: =((S34*CA34)/100) -> 0 | DN34: 0 | DO34: 0 | DP34: 1 | DQ34: 1 | DU34: 1013 | DV34: 1 Т | DW34: 1 Т | DX34: 1 | EE34: 51697152 | EF34: 150 | EG34: Транспортные затраты | EH34: 0 | EJ34: 4 | EK34: 1113 | EL34: ТСН-2001.15-1. Перевозка строительного мусора | EM34: ТСН-2001.15-1-5 | EQ34: 131072 | ER34: 17.84 | ES34: 0 | ET34: 17.84 | EU34: 0 | EV34: 0 | EW34: 0 | EX34: 0 | EY34: 0 | FQ34: 0 | FR34: 0 | FS34: 0 | FX34: 0 | FY34: 0 | GD34: 1 | GF34: 821670597 | GG34: 2 | GH34: 1 | GI34: -2 | GJ34: 0 | GK34: 0 | GL34: =ROUND(IF(AND(BH34=3,BI34=3,FS34<>0),P34,0),2) -> 0 | GM34: =ROUND(O34+X34+Y34,2)+GX34 -> 0 | GN34: =IF(OR(BI34=0,BI34=1),GM34-GX34,0) -> 0 | GO34: =IF(BI34=2,GM34-GX34,0) -> 0 | GP34: =IF(BI34=4,GM34-GX34,0) -> 0 | GR34: 0 | GS34: 0 | GT34: 0 | GV34: =ROUND((GT34),6) -> 0 | GW34: 1 | GX34: =ROUND(HC34*I34,2) -> 0 | HA34: 0 | HB34: 0 | HC34: =GV34*GW34 -> 0 | HS34: 0 | IK34: 0
A35: 17 | B35: 1 | D35: =ROW(EtalonRes!A8) -> 8 | E35: 4 | F35: 15.1-1106-02 | G35: Отходы строительного щебня незагрязненные практически неопасные | H35: 1 Т | I35: 0 | J35: 0 | K35: 0 | O35: =ROUND(CP35,2) -> 0 | P35: =ROUND((ROUND((AC35*AW35*I35),2)*BC35),2) -> 0 | Q35: =(ROUND((ROUND(((ET35)*AV35*I35),2)*BB35),2)+ROUND((ROUND(((AE35-(EU35))*AV35*I35),2)*BS35),2)) -> 0 | R35: =ROUND((ROUND((AE35*AV35*I35),2)*BS35),2) -> 0 | S35: =ROUND((ROUND((AF35*AV35*I35),2)*BA35),2) -> 0 | T35: =ROUND(CU35*I35,2) -> 0 | U35: =CV35*I35 -> 0 | V35: =CW35*I35 -> 0 | W35: =ROUND(CX35*I35,2) -> 0 | X35: =ROUND(CY35,2) -> 0 | Y35: =ROUND(CZ35,2) -> 0 | AA35: 57734470 | AB35: =ROUND((AC35+AD35+AF35),6) -> 17.84 | AC35: =ROUND((ES35),6) -> 0 | AD35: =ROUND((((ET35)-(EU35))+AE35),6) -> 17.84 | AE35: =ROUND((EU35),6) -> 0 | AF35: =ROUND((EV35),6) -> 0 | AG35: =ROUND((AP35),6) -> 0 | AH35: =(EW35) -> 0 | AI35: =(EX35) -> 0 | AJ35: =(AS35) -> 0 | AK35: 17.84 | AL35: 0 | AM35: 17.84 | AN35: 0 | AO35: 0 | AP35: 0 | AQ35: 0 | AR35: 0 | AS35: 0 | AT35: 95 | AU35: 65 | AV35: 1 | AW35: 1 | AZ35: 1 | BA35: 1 | BB35: 12.3 | BC35: 1 | BH35: 0 | BI35: 4 | BJ35: ТСН-2001.15 Доп. 68, Сб. 1, т. 1106, поз. 2 | BM35: 1113 | BN35: 0 | BO35: 15.1-1106-02 | BP35: 1 | BQ35: 150 | BR35: 0 | BS35: 1 | BT35: 1 | BU35: 1 | BV35: 1 | BW35: 1 | BX35: 1 | BZ35: 95 | CA35: 65 | CE35: 30 | CF35: 0 | CG35: 0 | CM35: 0 | CO35: 0 | CP35: =(P35+Q35+S35) -> 0 | CQ35: =ROUND((ROUND((AC35*AW35*1),2)*BC35),2) -> 0 | CR35: =(ROUND((ROUND(((ET35)*AV35*1),2)*BB35),2)+ROUND((ROUND(((AE35-(EU35))*AV35*1),2)*BS35),2)) -> 219.43 | CS35: =ROUND((ROUND((AE35*AV35*1),2)*BS35),2) -> 0 | CT35: =ROUND((ROUND((AF35*AV35*1),2)*BA35),2) -> 0 | CU35: =AG35 -> 0 | CV35: =(AH35*AV35) -> 0 | CW35: =AI35 -> 0 | CX35: =AJ35 -> 0 | CY35: =S35*(BZ35/100) -> 0 | CZ35: =S35*(CA35/100) -> 0 | DN35: 0 | DO35: 0 | DP35: 1 | DQ35: 1 | DU35: 1013 | DV35: 1 Т | DW35: 1 Т | DX35: 1 | EE35: 51697152 | EF35: 150 | EG35: Транспортные затраты | EH35: 0 | EJ35: 4 | EK35: 1113 | EL35: ТСН-2001.15-1. Перевозка строительного мусора | EM35: ТСН-2001.15-1-5 | EQ35: 131072 | ER35: 17.84 | ES35: 0 | ET35: 17.84 | EU35: 0 | EV35: 0 | EW35: 0 | EX35: 0 | EY35: 0 | FQ35: 0 | FR35: 0 | FS35: 0 | FX35: 0 | FY35: 0 | GD35: 0 | GF35: 821670597 | GG35: 2 | GH35: 1 | GI35: 2 | GJ35: 0 | GK35: =ROUND(R35*(S12)/100,2) -> 0 | GL35: =ROUND(IF(AND(BH35=3,BI35=3,FS35<>0),P35,0),2) -> 0 | GM35: =ROUND(O35+X35+Y35+GK35,2)+GX35 -> 0 | GN35: =IF(OR(BI35=0,BI35=1),GM35-GX35,0) -> 0 | GO35: =IF(BI35=2,GM35-GX35,0) -> 0 | GP35: =IF(BI35=4,GM35-GX35,0) -> 0 | GR35: 0 | GS35: 3 | GT35: 0 | GV35: =ROUND((GT35),6) -> 0 | GW35: 1 | GX35: =ROUND(HC35*I35,2) -> 0 | HA35: 0 | HB35: 0 | HC35: =GV35*GW35 -> 0 | HS35: 0 | IK35: 0
A36: 17 | B36: 1 | D36: =ROW(EtalonRes!A9) -> 9 | E36: 5 | F36: 15.1-1200-01 | G36: Лом бортовых камней, брусчатки, булыжных камней и прочие отходы изделий из природного камня, практически неопасный | H36: 1 Т | I36: 0 | J36: 0 | K36: 0 | O36: =ROUND(CP36,2) -> 0 | P36: =ROUND((ROUND((AC36*AW36*I36),2)*BC36),2) -> 0 | Q36: =(ROUND((ROUND(((ET36)*AV36*I36),2)*BB36),2)+ROUND((ROUND(((AE36-(EU36))*AV36*I36),2)*BS36),2)) -> 0 | R36: =ROUND((ROUND((AE36*AV36*I36),2)*BS36),2) -> 0 | S36: =ROUND((ROUND((AF36*AV36*I36),2)*BA36),2) -> 0 | T36: =ROUND(CU36*I36,2) -> 0 | U36: =CV36*I36 -> 0 | V36: =CW36*I36 -> 0 | W36: =ROUND(CX36*I36,2) -> 0 | X36: =ROUND(CY36,2) -> 0 | Y36: =ROUND(CZ36,2) -> 0 | AA36: 57734472 | AB36: =ROUND((AC36+AD36+AF36),6) -> 21.71 | AC36: =ROUND((ES36),6) -> 0 | AD36: =ROUND((((ET36)-(EU36))+AE36),6) -> 21.71 | AE36: =ROUND((EU36),6) -> 0 | AF36: =ROUND((EV36),6) -> 0 | AG36: =ROUND((AP36),6) -> 0 | AH36: =(EW36) -> 0 | AI36: =(EX36) -> 0 | AJ36: =(AS36) -> 0 | AK36: 21.71 | AL36: 0 | AM36: 21.71 | AN36: 0 | AO36: 0 | AP36: 0 | AQ36: 0 | AR36: 0 | AS36: 0 | AT36: 0 | AU36: 0 | AV36: 1 | AW36: 1 | AZ36: 1 | BA36: 1 | BB36: 1 | BC36: 1 | BH36: 0 | BI36: 4 | BJ36: ТСН-2001.15 Доп. 56, Сб. 1, т. 1200, поз. 1 | BM36: 1113 | BN36: 0 | BP36: 0 | BQ36: 150 | BR36: 0 | BS36: 1 | BT36: 1 | BU36: 1 | BV36: 1 | BW36: 1 | BX36: 1 | BZ36: 0 | CA36: 0 | CE36: 30 | CF36: 0 | CG36: 0 | CM36: 0 | CO36: 0 | CP36: =(P36+Q36+S36) -> 0 | CQ36: =ROUND((ROUND((AC36*AW36*1),2)*BC36),2) -> 0 | CR36: =(ROUND((ROUND(((ET36)*AV36*1),2)*BB36),2)+ROUND((ROUND(((AE36-(EU36))*AV36*1),2)*BS36),2)) -> 21.71 | CS36: =ROUND((ROUND((AE36*AV36*1),2)*BS36),2) -> 0 | CT36: =ROUND((ROUND((AF36*AV36*1),2)*BA36),2) -> 0 | CU36: =AG36 -> 0 | CV36: =(AH36*AV36) -> 0 | CW36: =AI36 -> 0 | CX36: =AJ36 -> 0 | CY36: =((S36*BZ36)/100) -> 0 | CZ36: =((S36*CA36)/100) -> 0 | DN36: 0 | DO36: 0 | DP36: 1 | DQ36: 1 | DU36: 1013 | DV36: 1 Т | DW36: 1 Т | DX36: 1 | EE36: 51697152 | EF36: 150 | EG36: Транспортные затраты | EH36: 0 | EJ36: 4 | EK36: 1113 | EL36: ТСН-2001.15-1. Перевозка строительного мусора | EM36: ТСН-2001.15-1-5 | EQ36: 131072 | ER36: 21.71 | ES36: 0 | ET36: 21.71 | EU36: 0 | EV36: 0 | EW36: 0 | EX36: 0 | EY36: 0 | FQ36: 0 | FR36: 0 | FS36: 0 | FX36: 0 | FY36: 0 | GD36: 1 | GF36: -2025383143 | GG36: 2 | GH36: 1 | GI36: -2 | GJ36: 0 | GK36: 0 | GL36: =ROUND(IF(AND(BH36=3,BI36=3,FS36<>0),P36,0),2) -> 0 | GM36: =ROUND(O36+X36+Y36,2)+GX36 -> 0 | GN36: =IF(OR(BI36=0,BI36=1),GM36-GX36,0) -> 0 | GO36: =IF(BI36=2,GM36-GX36,0) -> 0 | GP36: =IF(BI36=4,GM36-GX36,0) -> 0 | GR36: 0 | GS36: 0 | GT36: 0 | GV36: =ROUND((GT36),6) -> 0 | GW36: 1 | GX36: =ROUND(HC36*I36,2) -> 0 | HA36: 0 | HB36: 0 | HC36: =GV36*GW36 -> 0 | HS36: 0 | IK36: 0
A37: 17 | B37: 1 | D37: =ROW(EtalonRes!A10) -> 10 | E37: 5 | F37: 15.1-1200-01 | G37: Лом бортовых камней, брусчатки, булыжных камней и прочие отходы изделий из природного камня, практически неопасный | H37: 1 Т | I37: 0 | J37: 0 | K37: 0 | O37: =ROUND(CP37,2) -> 0 | P37: =ROUND((ROUND((AC37*AW37*I37),2)*BC37),2) -> 0 | Q37: =(ROUND((ROUND(((ET37)*AV37*I37),2)*BB37),2)+ROUND((ROUND(((AE37-(EU37))*AV37*I37),2)*BS37),2)) -> 0 | R37: =ROUND((ROUND((AE37*AV37*I37),2)*BS37),2) -> 0 | S37: =ROUND((ROUND((AF37*AV37*I37),2)*BA37),2) -> 0 | T37: =ROUND(CU37*I37,2) -> 0 | U37: =CV37*I37 -> 0 | V37: =CW37*I37 -> 0 | W37: =ROUND(CX37*I37,2) -> 0 | X37: =ROUND(CY37,2) -> 0 | Y37: =ROUND(CZ37,2) -> 0 | AA37: 57734470 | AB37: =ROUND((AC37+AD37+AF37),6) -> 21.71 | AC37: =ROUND((ES37),6) -> 0 | AD37: =ROUND((((ET37)-(EU37))+AE37),6) -> 21.71 | AE37: =ROUND((EU37),6) -> 0 | AF37: =ROUND((EV37),6) -> 0 | AG37: =ROUND((AP37),6) -> 0 | AH37: =(EW37) -> 0 | AI37: =(EX37) -> 0 | AJ37: =(AS37) -> 0 | AK37: 21.71 | AL37: 0 | AM37: 21.71 | AN37: 0 | AO37: 0 | AP37: 0 | AQ37: 0 | AR37: 0 | AS37: 0 | AT37: 95 | AU37: 65 | AV37: 1 | AW37: 1 | AZ37: 1 | BA37: 1 | BB37: 9 | BC37: 1 | BH37: 0 | BI37: 4 | BJ37: ТСН-2001.15 Доп. 56, Сб. 1, т. 1200, поз. 1 | BM37: 1113 | BN37: 0 | BO37: 15.1-1200-01 | BP37: 1 | BQ37: 150 | BR37: 0 | BS37: 1 | BT37: 1 | BU37: 1 | BV37: 1 | BW37: 1 | BX37: 1 | BZ37: 95 | CA37: 65 | CE37: 30 | CF37: 0 | CG37: 0 | CM37: 0 | CO37: 0 | CP37: =(P37+Q37+S37) -> 0 | CQ37: =ROUND((ROUND((AC37*AW37*1),2)*BC37),2) -> 0 | CR37: =(ROUND((ROUND(((ET37)*AV37*1),2)*BB37),2)+ROUND((ROUND(((AE37-(EU37))*AV37*1),2)*BS37),2)) -> 195.39 | CS37: =ROUND((ROUND((AE37*AV37*1),2)*BS37),2) -> 0 | CT37: =ROUND((ROUND((AF37*AV37*1),2)*BA37),2) -> 0 | CU37: =AG37 -> 0 | CV37: =(AH37*AV37) -> 0 | CW37: =AI37 -> 0 | CX37: =AJ37 -> 0 | CY37: =S37*(BZ37/100) -> 0 | CZ37: =S37*(CA37/100) -> 0 | DN37: 0 | DO37: 0 | DP37: 1 | DQ37: 1 | DU37: 1013 | DV37: 1 Т | DW37: 1 Т | DX37: 1 | EE37: 51697152 | EF37: 150 | EG37: Транспортные затраты | EH37: 0 | EJ37: 4 | EK37: 1113 | EL37: ТСН-2001.15-1. Перевозка строительного мусора | EM37: ТСН-2001.15-1-5 | EQ37: 131072 | ER37: 21.71 | ES37: 0 | ET37: 21.71 | EU37: 0 | EV37: 0 | EW37: 0 | EX37: 0 | EY37: 0 | FQ37: 0 | FR37: 0 | FS37: 0 | FX37: 0 | FY37: 0 | GD37: 0 | GF37: -2025383143 | GG37: 2 | GH37: 1 | GI37: 2 | GJ37: 0 | GK37: =ROUND(R37*(S12)/100,2) -> 0 | GL37: =ROUND(IF(AND(BH37=3,BI37=3,FS37<>0),P37,0),2) -> 0 | GM37: =ROUND(O37+X37+Y37+GK37,2)+GX37 -> 0 | GN37: =IF(OR(BI37=0,BI37=1),GM37-GX37,0) -> 0 | GO37: =IF(BI37=2,GM37-GX37,0) -> 0 | GP37: =IF(BI37=4,GM37-GX37,0) -> 0 | GR37: 0 | GS37: 3 | GT37: 0 | GV37: =ROUND((GT37),6) -> 0 | GW37: 1 | GX37: =ROUND(HC37*I37,2) -> 0 | HA37: 0 | HB37: 0 | HC37: =GV37*GW37 -> 0 | HS37: 0 | IK37: 0
A39: 51 | B39: =B24 -> 1 | C39: =A24 -> 4 | D39: =ROW(A24) -> 24 | F39: =IF(F24<>"",F24,"") -> Новый раздел | G39: =IF(G24<>"",G24,"") -> Благоустройство | H39: 0 | O39: =ROUND(AB39,2) -> 836.72 | P39: =ROUND(AC39,2) -> 0 | Q39: =ROUND(AD39,2) -> 836.72 | R39: =ROUND(AE39,2) -> 0 | S39: =ROUND(AF39,2) -> 0 | T39: =ROUND(AG39,2) -> 0 | U39: =AH39 -> 0 | V39: =AI39 -> 0 | W39: =ROUND(AJ39,2) -> 0 | X39: =ROUND(AK39,2) -> 0 | Y39: =ROUND(AL39,2) -> 0 | AB39: =ROUND(SUMIF(AA28:AA37,"=57734472",O28:O37),2) -> 836.72 | AC39: =ROUND(SUMIF(AA28:AA37,"=57734472",P28:P37),2) -> 0 | AD39: =ROUND(SUMIF(AA28:AA37,"=57734472",Q28:Q37),2) -> 836.72 | AE39: =ROUND(SUMIF(AA28:AA37,"=57734472",R28:R37),2) -> 0 | AF39: =ROUND(SUMIF(AA28:AA37,"=57734472",S28:S37),2) -> 0 | AG39: =ROUND(SUMIF(AA28:AA37,"=57734472",T28:T37),2) -> 0 | AH39: =SUMIF(AA28:AA37,"=57734472",U28:U37) -> 0 | AI39: =SUMIF(AA28:AA37,"=57734472",V28:V37) -> 0 | AJ39: =ROUND(SUMIF(AA28:AA37,"=57734472",W28:W37),2) -> 0 | AK39: =ROUND(SUMIF(AA28:AA37,"=57734472",X28:X37),2) -> 0 | AL39: =ROUND(SUMIF(AA28:AA37,"=57734472",Y28:Y37),2) -> 0 | AO39: =ROUND(BX39,2) -> 0 | AP39: =ROUND(BY39,2) -> 0 | AQ39: =ROUND(BZ39,2) -> 0 | AR39: =ROUND(CA39,2) -> 836.72 | AS39: =ROUND(CB39,2) -> 0 | AT39: =ROUND(CC39,2) -> 0 | AU39: =ROUND(CD39,2) -> 836.72 | AV39: =ROUND(CE39,2) -> 0 | ... BD39: =ROUND(CM39,2) -> 0 | BX39: =ROUND(SUMIF(AA28:AA37,"=57734472",FQ28:FQ37),2) -> 0 | BY39: =ROUND(SUMIF(AA28:AA37,"=57734472",FR28:FR37),2) -> 0 | BZ39: =ROUND(SUMIF(AA28:AA37,"=57734472",GL28:GL37),2) -> 0 | CA39: =ROUND(SUMIF(AA28:AA37,"=57734472",GM28:GM37),2) -> 836.72 | CB39: =ROUND(SUMIF(AA28:AA37,"=57734472",GN28:GN37),2) -> 0 | CC39: =ROUND(SUMIF(AA28:AA37,"=57734472",GO28:GO37),2) -> 0 | CD39: =ROUND(SUMIF(AA28:AA37,"=57734472",GP28:GP37),2) -> 836.72 | CE39: =AC39-BX39 -> 0 | CF39: =AC39-BY39 -> 0 | CG39: =BX39-BZ39 -> 0 | CH39: =AC39-BX39-BY39+BZ39 -> 0 | CI39: =BY39-BZ39 -> 0 | CJ39: =ROUND(SUMIF(AA28:AA37,"=57734472",GX28:GX37),2) -> 0 | CK39: =ROUND(SUMIF(AA28:AA37,"=57734472",GY28:GY37),2) -> 0 | CL39: =ROUND(SUMIF(AA28:AA37,"=57734472",GZ28:GZ37),2) -> 0 | CM39: =ROUND(SUMIF(AA28:AA37,"=57734472",HD28:HD37),2) -> 0 | DG39: =ROUND(DT39,2) -> 10227.83 | DH39: =ROUND(DU39,2) -> 0 | DI39: =ROUND(DV39,2) -> 10227.83 | DJ39: =ROUND(DW39,2) -> 0 | DK39: =ROUND(DX39,2) -> 0 | DL39: =ROUND(DY39,2) -> 0 | DM39: =DZ39 -> 0 | DN39: =EA39 -> 0 | DO39: =ROUND(EB39,2) -> 0 | DP39: =ROUND(EC39,2) -> 0 | DQ39: =ROUND(ED39,2) -> 0 | DT39: =ROUND(SUMIF(AA28:AA37,"=57734470",O28:O37),2) -> 10227.83 | DU39: =ROUND(SUMIF(AA28:AA37,"=57734470",P28:P37),2) -> 0 | DV39: =ROUND(SUMIF(AA28:AA37,"=57734470",Q28:Q37),2) -> 10227.83 | DW39: =ROUND(SUMIF(AA28:AA37,"=57734470",R28:R37),2) -> 0 | DX39: =ROUND(SUMIF(AA28:AA37,"=57734470",S28:S37),2) -> 0 | DY39: =ROUND(SUMIF(AA28:AA37,"=57734470",T28:T37),2) -> 0 | DZ39: =SUMIF(AA28:AA37,"=57734470",U28:U37) -> 0 | EA39: =SUMIF(AA28:AA37,"=57734470",V28:V37) -> 0 | EB39: =ROUND(SUMIF(AA28:AA37,"=57734470",W28:W37),2) -> 0 | EC39: =ROUND(SUMIF(AA28:AA37,"=57734470",X28:X37),2) -> 0 | ED39: =ROUND(SUMIF(AA28:AA37,"=57734470",Y28:Y37),2) -> 0 | EG39: =ROUND(FP39,2) -> 0 | EH39: =ROUND(FQ39,2) -> 0 | EI39: =ROUND(FR39,2) -> 0 | EJ39: =ROUND(FS39,2) -> 10227.83 | EK39: =ROUND(FT39,2) -> 0 | EL39: =ROUND(FU39,2) -> 0 | EM39: =ROUND(FV39,2) -> 10227.83 | EN39: =ROUND(FW39,2) -> 0 | ... EV39: =ROUND(GE39,2) -> 0 | FP39: =ROUND(SUMIF(AA28:AA37,"=57734470",FQ28:FQ37),2) -> 0 | FQ39: =ROUND(SUMIF(AA28:AA37,"=57734470",FR28:FR37),2) -> 0 | FR39: =ROUND(SUMIF(AA28:AA37,"=57734470",GL28:GL37),2) -> 0 | FS39: =ROUND(SUMIF(AA28:AA37,"=57734470",GM28:GM37),2) -> 10227.83 | FT39: =ROUND(SUMIF(AA28:AA37,"=57734470",GN28:GN37),2) -> 0 | FU39: =ROUND(SUMIF(AA28:AA37,"=57734470",GO28:GO37),2) -> 0 | FV39: =ROUND(SUMIF(AA28:AA37,"=57734470",GP28:GP37),2) -> 10227.83 | FW39: =DU39-FP39 -> 0 | FX39: =DU39-FQ39 -> 0 | FY39: =FP39-FR39 -> 0 | FZ39: =DU39-FP39-FQ39+FR39 -> 0 | GA39: =FQ39-FR39 -> 0 | GB39: =ROUND(SUMIF(AA28:AA37,"=57734470",GX28:GX37),2) -> 0 | GC39: =ROUND(SUMIF(AA28:AA37,"=57734470",GY28:GY37),2) -> 0 | GD39: =ROUND(SUMIF(AA28:AA37,"=57734470",GZ28:GZ37),2) -> 0 | GE39: =ROUND(SUMIF(AA28:AA37,"=57734470",HD28:HD37),2) -> 0 | GX39: 0
A41: 50 | B41: 0 | C41: 0 | D41: 1 | E41: 201 | F41: =ROUND(Source!O39,O41) -> 836.72 | G41: ПЗ | H41: Прямые затраты | K41: 201 | L41: 1 | M41: 3 | O41: 2 | P41: =ROUND(Source!DG39,O41) -> 10227.83 | W41: 836.72 | X41: 1 | Y41: 836.72 | Z41: 10227.83 | AA41: 1 | AB41: 10227.83
A42: 50 | B42: 0 | C42: 0 | D42: 1 | E42: 202 | F42: =ROUND(Source!P39,O42) -> 0 | G42: СтМатОб | H42: Стоимость материальных ресурсов (всего) | K42: 202 | L42: 2 | M42: 3 | O42: 2 | P42: =ROUND(Source!DH39,O42) -> 0 | W42: 0 | X42: 1 | Y42: 0 | Z42: 0 | AA42: 1 | AB42: 0
A43: 50 | B43: 0 | C43: 0 | D43: 1 | E43: 222 | F43: =ROUND(Source!AO39,O43) -> 0 | G43: СтМатОбЗак | H43: Стоимость материалов и оборудования заказчика | K43: 222 | L43: 3 | M43: 3 | O43: 2 | P43: =ROUND(Source!EG39,O43) -> 0 | W43: 0 | X43: 1 | Y43: 0 | Z43: 0 | AA43: 1 | AB43: 0
A44: 50 | B44: 0 | C44: 0 | D44: 1 | E44: 225 | F44: =ROUND(Source!AV39,O44) -> 0 | G44: СтМатОбПод | H44: Стоимость материалов и оборудования подрядчика | K44: 225 | L44: 4 | M44: 3 | O44: 2 | P44: =ROUND(Source!EN39,O44) -> 0 | W44: 0 | X44: 1 | Y44: 0 | Z44: 0 | AA44: 1 | AB44: 0
A45: 50 | B45: 0 | C45: 0 | D45: 1 | E45: 226 | F45: =ROUND(Source!AW39,O45) -> 0 | G45: СтМат | H45: Стоимость материалов (всего) | K45: 226 | L45: 5 | M45: 3 | O45: 2 | P45: =ROUND(Source!EO39,O45) -> 0 | W45: 0 | X45: 1 | Y45: 0 | Z45: 0 | AA45: 1 | AB45: 0
A46: 50 | B46: 0 | C46: 0 | D46: 1 | E46: 227 | F46: =ROUND(Source!AX39,O46) -> 0 | G46: СтМатЗак | H46: Стоимость материалов заказчика | K46: 227 | L46: 6 | M46: 3 | O46: 2 | P46: =ROUND(Source!EP39,O46) -> 0 | W46: 0 | X46: 1 | Y46: 0 | Z46: 0 | AA46: 1 | AB46: 0
A47: 50 | B47: 0 | C47: 0 | D47: 1 | E47: 228 | F47: =ROUND(Source!AY39,O47) -> 0 | G47: СтМатПод | H47: Стоимость материалов подрядчика | K47: 228 | L47: 7 | M47: 3 | O47: 2 | P47: =ROUND(Source!EQ39,O47) -> 0 | W47: 0 | X47: 1 | Y47: 0 | Z47: 0 | AA47: 1 | AB47: 0
A48: 50 | B48: 0 | C48: 0 | D48: 1 | E48: 216 | F48: =ROUND(Source!AP39,O48) -> 0 | G48: Оборуд | H48: Стоимость оборудования (всего) | K48: 216 | L48: 8 | M48: 3 | O48: 2 | P48: =ROUND(Source!EH39,O48) -> 0 | W48: 0 | X48: 1 | Y48: 0 | Z48: 0 | AA48: 1 | AB48: 0
A49: 50 | B49: 0 | C49: 0 | D49: 1 | E49: 223 | F49: =ROUND(Source!AQ39,O49) -> 0 | G49: ОборудЗак | H49: Стоимость оборудования заказчика | K49: 223 | L49: 9 | M49: 3 | O49: 2 | P49: =ROUND(Source!EI39,O49) -> 0 | W49: 0 | X49: 1 | Y49: 0 | Z49: 0 | AA49: 1 | AB49: 0
A50: 50 | B50: 0 | C50: 0 | D50: 1 | E50: 229 | F50: =ROUND(Source!AZ39,O50) -> 0 | G50: ОборудПод | H50: Стоимость оборудования подрядчика | K50: 229 | L50: 10 | M50: 3 | O50: 2 | P50: =ROUND(Source!ER39,O50) -> 0 | W50: 0 | X50: 1 | Y50: 0 | Z50: 0 | AA50: 1 | AB50: 0
A51: 50 | B51: 0 | C51: 0 | D51: 1 | E51: 203 | F51: =ROUND(Source!Q39,O51) -> 836.72 | G51: ЭММ | H51: Эксплуатация машин | K51: 203 | L51: 11 | M51: 3 | O51: 2 | P51: =ROUND(Source!DI39,O51) -> 10227.83 | W51: 836.72 | X51: 1 | Y51: 836.72 | Z51: 10227.83 | AA51: 1 | AB51: 10227.83
A52: 50 | B52: 0 | C52: 0 | D52: 1 | E52: 231 | F52: =ROUND(Source!BB39,O52) -> 0 | G52: ЭММсНРиСП | H52: Эксплуатация машин по ТСН-2001.16 | K52: 231 | L52: 12 | M52: 3 | O52: 2 | P52: =ROUND(Source!ET39,O52) -> 0 | W52: 0 | X52: 1 | Y52: 0 | Z52: 0 | AA52: 1 | AB52: 0
A53: 50 | B53: 0 | C53: 0 | D53: 1 | E53: 204 | F53: =ROUND(Source!R39,O53) -> 0 | G53: ЗПМ | H53: ЗП машинистов | K53: 204 | L53: 13 | M53: 3 | O53: 2 | P53: =ROUND(Source!DJ39,O53) -> 0 | W53: 0 | X53: 1 | Y53: 0 | Z53: 0 | AA53: 1 | AB53: 0
A54: 50 | B54: 0 | C54: 0 | D54: 1 | E54: 205 | F54: =ROUND(Source!S39,O54) -> 0 | G54: ОЗП | H54: Основная ЗП рабочих | K54: 205 | L54: 14 | M54: 3 | O54: 2 | P54: =ROUND(Source!DK39,O54) -> 0 | W54: 0 | X54: 1 | Y54: 0 | Z54: 0 | AA54: 1 | AB54: 0
A55: 50 | B55: 0 | C55: 0 | D55: 1 | E55: 232 | F55: =ROUND(Source!BC39,O55) -> 0 | G55: ОЗПсНРиСП | H55: Основная ЗП рабочих по ТСН-2001.16 | K55: 232 | L55: 15 | M55: 3 | O55: 2 | P55: =ROUND(Source!EU39,O55) -> 0 | W55: 0 | X55: 1 | Y55: 0 | Z55: 0 | AA55: 1 | AB55: 0
A56: 50 | B56: 0 | C56: 0 | D56: 1 | E56: 214 | F56: =ROUND(Source!AS39,O56) -> 0 | G56: Строит | H56: Строительные работы с НР и СП | K56: 214 | L56: 16 | M56: 3 | O56: 2 | P56: =ROUND(Source!EK39,O56) -> 0 | W56: 0 | X56: 1 | Y56: 0 | Z56: 0 | AA56: 1 | AB56: 0
A57: 50 | B57: 0 | C57: 0 | D57: 1 | E57: 215 | F57: =ROUND(Source!AT39,O57) -> 0 | G57: Монтаж | H57: Монтажные работы с НР и СП | K57: 215 | L57: 17 | M57: 3 | O57: 2 | P57: =ROUND(Source!EL39,O57) -> 0 | W57: 0 | X57: 1 | Y57: 0 | Z57: 0 | AA57: 1 | AB57: 0
A58: 50 | B58: 0 | C58: 0 | D58: 1 | E58: 217 | F58: =ROUND(Source!AU39,O58) -> 836.72 | G58: Прочие | H58: Прочие работы с НР и СП | K58: 217 | L58: 18 | M58: 3 | O58: 2 | P58: =ROUND(Source!EM39,O58) -> 10227.83 | W58: 836.72 | X58: 1 | Y58: 836.72 | Z58: 10227.83 | AA58: 1 | AB58: 10227.83
A59: 50 | B59: 0 | C59: 0 | D59: 1 | E59: 230 | F59: =ROUND(Source!BA39,O59) -> 0 | G59: ПрочиеЗатр | H59: Прочие затраты по ТСН-2001.16 | K59: 230 | L59: 19 | M59: 3 | O59: 2 | P59: =ROUND(Source!ES39,O59) -> 0 | W59: 0 | X59: 1 | Y59: 0 | Z59: 0 | AA59: 1 | AB59: 0
A60: 50 | B60: 0 | C60: 0 | D60: 1 | E60: 206 | F60: =ROUND(Source!T39,O60) -> 0 | G60: ВозврМат | H60: Возврат материалов | K60: 206 | L60: 20 | M60: 3 | O60: 2 | P60: =ROUND(Source!DL39,O60) -> 0 | W60: 0 | X60: 1 | Y60: 0 | Z60: 0 | AA60: 1 | AB60: 0
A61: 50 | B61: 0 | C61: 0 | D61: 1 | E61: 207 | F61: =Source!U39 -> 0 | G61: ТрудСтр | H61: Трудозатраты строителей | K61: 207 | L61: 21 | M61: 3 | O61: -1 | P61: =Source!DM39 -> 0 | W61: 0 | X61: 1 | Y61: 0 | Z61: 0 | AA61: 1 | AB61: 0
A62: 50 | B62: 0 | C62: 0 | D62: 1 | E62: 208 | F62: =Source!V39 -> 0 | G62: ТрудМаш | H62: Трудозатраты машинистов | K62: 208 | L62: 22 | M62: 3 | O62: -1 | P62: =Source!DN39 -> 0 | W62: 0 | X62: 1 | Y62: 0 | Z62: 0 | AA62: 1 | AB62: 0
A63: 50 | B63: 0 | C63: 0 | D63: 1 | E63: 209 | F63: =ROUND(Source!W39,O63) -> 0 | G63: ТранспМат | H63: Транспорт материалов | K63: 209 | L63: 23 | M63: 3 | O63: 2 | P63: =ROUND(Source!DO39,O63) -> 0 | W63: 0 | X63: 1 | Y63: 0 | Z63: 0 | AA63: 1 | AB63: 0
A64: 50 | B64: 0 | C64: 0 | D64: 1 | E64: 233 | F64: =ROUND(Source!BD39,O64) -> 0 | G64: Перевозка | H64: Перевозка грузов | K64: 233 | L64: 24 | M64: 3 | O64: 2 | P64: =ROUND(Source!EV39,O64) -> 0 | W64: 0 | X64: 1 | Y64: 0 | Z64: 0 | AA64: 1 | AB64: 0
A65: 50 | B65: 0 | C65: 0 | D65: 1 | E65: 210 | F65: =ROUND(Source!X39,O65) -> 0 | G65: НР | H65: Накладные расходы | K65: 210 | L65: 25 | M65: 3 | O65: 2 | P65: =ROUND(Source!DP39,O65) -> 0 | W65: 0 | X65: 1 | Y65: 0 | Z65: 0 | AA65: 1 | AB65: 0
A66: 50 | B66: 0 | C66: 0 | D66: 1 | E66: 211 | F66: =ROUND(Source!Y39,O66) -> 0 | G66: СмПриб | H66: Сметная прибыль | K66: 211 | L66: 26 | M66: 3 | O66: 2 | P66: =ROUND(Source!DQ39,O66) -> 0 | W66: 0 | X66: 1 | Y66: 0 | Z66: 0 | AA66: 1 | AB66: 0
A67: 50 | B67: 0 | C67: 0 | D67: 1 | E67: 224 | F67: =ROUND(Source!AR39,O67) -> 836.72 | G67: Всего | H67: Всего с НР и СП | K67: 224 | L67: 27 | M67: 3 | O67: 2 | P67: =ROUND(Source!EJ39,O67) -> 10227.83 | W67: 836.72 | X67: 1 | Y67: 836.72 | Z67: 10227.83 | AA67: 1 | AB67: 10227.83
A69: 4 | B69: 1 | D69: =ROW(A78) -> 78 | F69: Новый раздел | G69: 10 кВ и 0,4 кВ | I69: 0 | K69: -1 | S69: 0 | T69: 0 | V69: 0 | BX69: 0 | CJ69: 0
A71: 52 | B71: =B78 -> 1 | C71: =C78 -> 4 | D71: =D78 -> 69 | E71: =E78 -> 0 | F71: =F78 -> Новый раздел | G71: =G78 -> 10 кВ и 0,4 кВ | O71: =O78 -> 4031.62 | P71: =P78 -> 0 | Q71: =Q78 -> 4031.62 | R71: =R78 -> 0 | S71: =S78 -> 0 | T71: =T78 -> 0 | U71: =U78 -> 0 | V71: =V78 -> 0 | ... GX71: =GX78 -> 0
A73: 17 | B73: 1 | D73: =ROW(EtalonRes!A11) -> 11 | E73: 6 | F73: 15.2-53-4 | G73: Перевозка грунтов скальных и дисперсных несвязных на расстояние до 53 км автосамосвалами грузоподъемностью до 10 т | H73: т | I73: =ROUND((39.92)*1.75,9) -> 69.86 | J73: 0 | K73: =ROUND((39.92)*1.75,9) -> 69.86 | O73: =ROUND(CP73,2) -> 3150.69 | P73: =ROUND((ROUND((AC73*AW73*I73),2)*BC73),2) -> 0 | Q73: =(ROUND((ROUND(((ET73)*AV73*I73),2)*BB73),2)+ROUND((ROUND(((AE73-(EU73))*AV73*I73),2)*BS73),2)) -> 3150.69 | R73: =ROUND((ROUND((AE73*AV73*I73),2)*BS73),2) -> 0 | S73: =ROUND((ROUND((AF73*AV73*I73),2)*BA73),2) -> 0 | T73: =ROUND(CU73*I73,2) -> 0 | U73: =CV73*I73 -> 0 | V73: =CW73*I73 -> 0 | W73: =ROUND(CX73*I73,2) -> 0 | X73: =ROUND(CY73,2) -> 0 | Y73: =ROUND(CZ73,2) -> 0 | AA73: 57734472 | AB73: =ROUND((AC73+AD73+AF73),6) -> 45.1 | AC73: =ROUND((ES73),6) -> 0 | AD73: =ROUND((((ET73)-(EU73))+AE73),6) -> 45.1 | AE73: =ROUND((EU73),6) -> 0 | AF73: =ROUND((EV73),6) -> 0 | AG73: =ROUND((AP73),6) -> 0 | AH73: =(EW73) -> 0 | AI73: =(EX73) -> 0 | AJ73: =(AS73) -> 0 | AK73: 45.1 | AL73: 0 | AM73: 45.1 | AN73: 0 | AO73: 0 | AP73: 0 | AQ73: 0 | AR73: 0 | AS73: 0 | AT73: 0 | AU73: 0 | AV73: 1 | AW73: 1 | AZ73: 1 | BA73: 1 | BB73: 1 | BC73: 1 | BH73: 0 | BI73: 4 | BJ73: ТСН-2001.15 Доп. 68, Сб. 2, т. 53, поз. 4 | BM73: 1111 | BN73: 0 | BP73: 0 | BQ73: 150 | BR73: 0 | BS73: 1 | BT73: 1 | BU73: 1 | BV73: 1 | BW73: 1 | BX73: 1 | BZ73: 0 | CA73: 0 | CE73: 30 | CF73: 0 | CG73: 0 | CM73: 0 | CO73: 0 | CP73: =(P73+Q73+S73) -> 3150.69 | CQ73: =ROUND((ROUND((AC73*AW73*1),2)*BC73),2) -> 0 | CR73: =(ROUND((ROUND(((ET73)*AV73*1),2)*BB73),2)+ROUND((ROUND(((AE73-(EU73))*AV73*1),2)*BS73),2)) -> 45.1 | CS73: =ROUND((ROUND((AE73*AV73*1),2)*BS73),2) -> 0 | CT73: =ROUND((ROUND((AF73*AV73*1),2)*BA73),2) -> 0 | CU73: =AG73 -> 0 | CV73: =(AH73*AV73) -> 0 | CW73: =AI73 -> 0 | CX73: =AJ73 -> 0 | CY73: =((S73*BZ73)/100) -> 0 | CZ73: =((S73*CA73)/100) -> 0 | DN73: 0 | DO73: 0 | DP73: 1 | DQ73: 1 | DU73: 1009 | DV73: т | DW73: т | DX73: 1000 | EE73: 51697150 | EF73: 150 | EG73: Транспортные затраты | EH73: 0 | EJ73: 4 | EK73: 1111 | EL73: ТСН-2001.15-1. Перевозка грунта | EM73: ТСН-2001.15-1-3 | EQ73: 131072 | ER73: 45.1 | ES73: 0 | ET73: 45.1 | EU73: 0 | EV73: 0 | EW73: 0 | EX73: 0 | EY73: 0 | FQ73: 0 | FR73: 0 | FS73: 0 | FX73: 0 | FY73: 0 | GD73: 1 | GF73: -1114147576 | GG73: 2 | GH73: 1 | GI73: -2 | GJ73: 0 | GK73: 0 | GL73: =ROUND(IF(AND(BH73=3,BI73=3,FS73<>0),P73,0),2) -> 0 | GM73: =ROUND(O73+X73+Y73,2)+GX73 -> 3150.69 | GN73: =IF(OR(BI73=0,BI73=1),GM73-GX73,0) -> 0 | GO73: =IF(BI73=2,GM73-GX73,0) -> 0 | GP73: =IF(BI73=4,GM73-GX73,0) -> 3150.69 | GR73: 0 | GS73: 0 | GT73: 0 | GV73: =ROUND((GT73),6) -> 0 | GW73: 1 | GX73: =ROUND(HC73*I73,2) -> 0 | HA73: 0 | HB73: 0 | HC73: =GV73*GW73 -> 0 | HS73: 0 | IK73: 0
A74: 17 | B74: 1 | D74: =ROW(EtalonRes!A12) -> 12 | E74: 6 | F74: 15.2-53-4 | G74: Перевозка грунтов скальных и дисперсных несвязных на расстояние до 53 км автосамосвалами грузоподъемностью до 10 т | H74: т | I74: =ROUND((39.92)*1.75,9) -> 69.86 | J74: 0 | K74: =ROUND((39.92)*1.75,9) -> 69.86 | O74: =ROUND(CP74,2) -> 49308.3 | P74: =ROUND((ROUND((AC74*AW74*I74),2)*BC74),2) -> 0 | Q74: =(ROUND((ROUND(((ET74)*AV74*I74),2)*BB74),2)+ROUND((ROUND(((AE74-(EU74))*AV74*I74),2)*BS74),2)) -> 49308.3 | R74: =ROUND((ROUND((AE74*AV74*I74),2)*BS74),2) -> 0 | S74: =ROUND((ROUND((AF74*AV74*I74),2)*BA74),2) -> 0 | T74: =ROUND(CU74*I74,2) -> 0 | U74: =CV74*I74 -> 0 | V74: =CW74*I74 -> 0 | W74: =ROUND(CX74*I74,2) -> 0 | X74: =ROUND(CY74,2) -> 0 | Y74: =ROUND(CZ74,2) -> 0 | AA74: 57734470 | AB74: =ROUND((AC74+AD74+AF74),6) -> 45.1 | AC74: =ROUND((ES74),6) -> 0 | AD74: =ROUND((((ET74)-(EU74))+AE74),6) -> 45.1 | AE74: =ROUND((EU74),6) -> 0 | AF74: =ROUND((EV74),6) -> 0 | AG74: =ROUND((AP74),6) -> 0 | AH74: =(EW74) -> 0 | AI74: =(EX74) -> 0 | AJ74: =(AS74) -> 0 | AK74: 45.1 | AL74: 0 | AM74: 45.1 | AN74: 0 | AO74: 0 | AP74: 0 | AQ74: 0 | AR74: 0 | AS74: 0 | AT74: 95 | AU74: 65 | AV74: 1 | AW74: 1 | AZ74: 1 | BA74: 1 | BB74: 15.65 | BC74: 1 | BH74: 0 | BI74: 4 | BJ74: ТСН-2001.15 Доп. 68, Сб. 2, т. 53, поз. 4 | BM74: 1111 | BN74: 0 | BO74: 15.2-53-4 | BP74: 1 | BQ74: 150 | BR74: 0 | BS74: 1 | BT74: 1 | BU74: 1 | BV74: 1 | BW74: 1 | BX74: 1 | BZ74: 95 | CA74: 65 | CE74: 30 | CF74: 0 | CG74: 0 | CM74: 0 | CO74: 0 | CP74: =(P74+Q74+S74) -> 49308.3 | CQ74: =ROUND((ROUND((AC74*AW74*1),2)*BC74),2) -> 0 | CR74: =(ROUND((ROUND(((ET74)*AV74*1),2)*BB74),2)+ROUND((ROUND(((AE74-(EU74))*AV74*1),2)*BS74),2)) -> 705.82 | CS74: =ROUND((ROUND((AE74*AV74*1),2)*BS74),2) -> 0 | CT74: =ROUND((ROUND((AF74*AV74*1),2)*BA74),2) -> 0 | CU74: =AG74 -> 0 | CV74: =(AH74*AV74) -> 0 | CW74: =AI74 -> 0 | CX74: =AJ74 -> 0 | CY74: =S74*(BZ74/100) -> 0 | CZ74: =S74*(CA74/100) -> 0 | DN74: 0 | DO74: 0 | DP74: 1 | DQ74: 1 | DU74: 1009 | DV74: т | DW74: т | DX74: 1000 | EE74: 51697150 | EF74: 150 | EG74: Транспортные затраты | EH74: 0 | EJ74: 4 | EK74: 1111 | EL74: ТСН-2001.15-1. Перевозка грунта | EM74: ТСН-2001.15-1-3 | EQ74: 131072 | ER74: 45.1 | ES74: 0 | ET74: 45.1 | EU74: 0 | EV74: 0 | EW74: 0 | EX74: 0 | EY74: 0 | FQ74: 0 | FR74: 0 | FS74: 0 | FX74: 0 | FY74: 0 | GD74: 0 | GF74: -1114147576 | GG74: 2 | GH74: 1 | GI74: 2 | GJ74: 0 | GK74: =ROUND(R74*(S12)/100,2) -> 0 | GL74: =ROUND(IF(AND(BH74=3,BI74=3,FS74<>0),P74,0),2) -> 0 | GM74: =ROUND(O74+X74+Y74+GK74,2)+GX74 -> 49308.3 | GN74: =IF(OR(BI74=0,BI74=1),GM74-GX74,0) -> 0 | GO74: =IF(BI74=2,GM74-GX74,0) -> 0 | GP74: =IF(BI74=4,GM74-GX74,0) -> 49308.3 | GR74: 0 | GS74: 3 | GT74: 0 | GV74: =ROUND((GT74),6) -> 0 | GW74: 1 | GX74: =ROUND(HC74*I74,2) -> 0 | HA74: 0 | HB74: 0 | HC74: =GV74*GW74 -> 0 | HS74: 0 | IK74: 0
A75: 17 | B75: 1 | D75: =ROW(EtalonRes!A13) -> 13 | E75: 7 | F75: 15.1-1102-01 | G75: Отходы грунта при проведении открытых земляных работ практически неопасные | H75: 1 Т | I75: =ROUND(I73,9) -> 69.86 | J75: 0 | K75: =ROUND(I73,9) -> 69.86 | O75: =ROUND(CP75,2) -> 880.93 | P75: =ROUND((ROUND((AC75*AW75*I75),2)*BC75),2) -> 0 | Q75: =(ROUND((ROUND(((ET75)*AV75*I75),2)*BB75),2)+ROUND((ROUND(((AE75-(EU75))*AV75*I75),2)*BS75),2)) -> 880.93 | R75: =ROUND((ROUND((AE75*AV75*I75),2)*BS75),2) -> 0 | S75: =ROUND((ROUND((AF75*AV75*I75),2)*BA75),2) -> 0 | T75: =ROUND(CU75*I75,2) -> 0 | U75: =CV75*I75 -> 0 | V75: =CW75*I75 -> 0 | W75: =ROUND(CX75*I75,2) -> 0 | X75: =ROUND(CY75,2) -> 0 | Y75: =ROUND(CZ75,2) -> 0 | AA75: 57734472 | AB75: =ROUND((AC75+AD75+AF75),6) -> 12.61 | AC75: =ROUND((ES75),6) -> 0 | AD75: =ROUND((((ET75)-(EU75))+AE75),6) -> 12.61 | AE75: =ROUND((EU75),6) -> 0 | AF75: =ROUND((EV75),6) -> 0 | AG75: =ROUND((AP75),6) -> 0 | AH75: =(EW75) -> 0 | AI75: =(EX75) -> 0 | AJ75: =(AS75) -> 0 | AK75: 12.61 | AL75: 0 | AM75: 12.61 | AN75: 0 | AO75: 0 | AP75: 0 | AQ75: 0 | AR75: 0 | AS75: 0 | AT75: 0 | AU75: 0 | AV75: 1 | AW75: 1 | AZ75: 1 | BA75: 1 | BB75: 1 | BC75: 1 | BH75: 0 | BI75: 4 | BJ75: ТСН-2001.15 Доп. 56, Сб. 1, т. 1102, поз. 1 | BM75: 1113 | BN75: 0 | BP75: 0 | BQ75: 150 | BR75: 0 | BS75: 1 | BT75: 1 | BU75: 1 | BV75: 1 | BW75: 1 | BX75: 1 | BZ75: 0 | CA75: 0 | CE75: 30 | CF75: 0 | CG75: 0 | CM75: 0 | CO75: 0 | CP75: =(P75+Q75+S75) -> 880.93 | CQ75: =ROUND((ROUND((AC75*AW75*1),2)*BC75),2) -> 0 | CR75: =(ROUND((ROUND(((ET75)*AV75*1),2)*BB75),2)+ROUND((ROUND(((AE75-(EU75))*AV75*1),2)*BS75),2)) -> 12.61 | CS75: =ROUND((ROUND((AE75*AV75*1),2)*BS75),2) -> 0 | CT75: =ROUND((ROUND((AF75*AV75*1),2)*BA75),2) -> 0 | CU75: =AG75 -> 0 | CV75: =(AH75*AV75) -> 0 | CW75: =AI75 -> 0 | CX75: =AJ75 -> 0 | CY75: =((S75*BZ75)/100) -> 0 | CZ75: =((S75*CA75)/100) -> 0 | DN75: 0 | DO75: 0 | DP75: 1 | DQ75: 1 | DU75: 1013 | DV75: 1 Т | DW75: 1 Т | DX75: 1 | EE75: 51697152 | EF75: 150 | EG75: Транспортные затраты | EH75: 0 | EJ75: 4 | EK75: 1113 | EL75: ТСН-2001.15-1. Перевозка строительного мусора | EM75: ТСН-2001.15-1-5 | EQ75: 131072 | ER75: 12.61 | ES75: 0 | ET75: 12.61 | EU75: 0 | EV75: 0 | EW75: 0 | EX75: 0 | EY75: 0 | FQ75: 0 | FR75: 0 | FS75: 0 | FX75: 0 | FY75: 0 | GD75: 1 | GF75: 1823831914 | GG75: 2 | GH75: 1 | GI75: -2 | GJ75: 0 | GK75: 0 | GL75: =ROUND(IF(AND(BH75=3,BI75=3,FS75<>0),P75,0),2) -> 0 | GM75: =ROUND(O75+X75+Y75,2)+GX75 -> 880.93 | GN75: =IF(OR(BI75=0,BI75=1),GM75-GX75,0) -> 0 | GO75: =IF(BI75=2,GM75-GX75,0) -> 0 | GP75: =IF(BI75=4,GM75-GX75,0) -> 880.93 | GR75: 0 | GS75: 0 | GT75: 0 | GV75: =ROUND((GT75),6) -> 0 | GW75: 1 | GX75: =ROUND(HC75*I75,2) -> 0 | HA75: 0 | HB75: 0 | HC75: =GV75*GW75 -> 0 | HS75: 0 | IK75: 0
A76: 17 | B76: 1 | D76: =ROW(EtalonRes!A14) -> 14 | E76: 7 | F76: 15.1-1102-01 | G76: Отходы грунта при проведении открытых земляных работ практически неопасные | H76: 1 Т | I76: =ROUND(I74,9) -> 69.86 | J76: 0 | K76: =ROUND(I74,9) -> 69.86 | O76: =ROUND(CP76,2) -> 11681.13 | P76: =ROUND((ROUND((AC76*AW76*I76),2)*BC76),2) -> 0 | Q76: =(ROUND((ROUND(((ET76)*AV76*I76),2)*BB76),2)+ROUND((ROUND(((AE76-(EU76))*AV76*I76),2)*BS76),2)) -> 11681.13 | R76: =ROUND((ROUND((AE76*AV76*I76),2)*BS76),2) -> 0 | S76: =ROUND((ROUND((AF76*AV76*I76),2)*BA76),2) -> 0 | T76: =ROUND(CU76*I76,2) -> 0 | U76: =CV76*I76 -> 0 | V76: =CW76*I76 -> 0 | W76: =ROUND(CX76*I76,2) -> 0 | X76: =ROUND(CY76,2) -> 0 | Y76: =ROUND(CZ76,2) -> 0 | AA76: 57734470 | AB76: =ROUND((AC76+AD76+AF76),6) -> 12.61 | AC76: =ROUND((ES76),6) -> 0 | AD76: =ROUND((((ET76)-(EU76))+AE76),6) -> 12.61 | AE76: =ROUND((EU76),6) -> 0 | AF76: =ROUND((EV76),6) -> 0 | AG76: =ROUND((AP76),6) -> 0 | AH76: =(EW76) -> 0 | AI76: =(EX76) -> 0 | AJ76: =(AS76) -> 0 | AK76: 12.61 | AL76: 0 | AM76: 12.61 | AN76: 0 | AO76: 0 | AP76: 0 | AQ76: 0 | AR76: 0 | AS76: 0 | AT76: 95 | AU76: 65 | AV76: 1 | AW76: 1 | AZ76: 1 | BA76: 1 | BB76: 13.26 | BC76: 1 | BH76: 0 | BI76: 4 | BJ76: ТСН-2001.15 Доп. 56, Сб. 1, т. 1102, поз. 1 | BM76: 1113 | BN76: 0 | BO76: 15.1-1102-01 | BP76: 1 | BQ76: 150 | BR76: 0 | BS76: 1 | BT76: 1 | BU76: 1 | BV76: 1 | BW76: 1 | BX76: 1 | BZ76: 95 | CA76: 65 | CE76: 30 | CF76: 0 | CG76: 0 | CM76: 0 | CO76: 0 | CP76: =(P76+Q76+S76) -> 11681.13 | CQ76: =ROUND((ROUND((AC76*AW76*1),2)*BC76),2) -> 0 | CR76: =(ROUND((ROUND(((ET76)*AV76*1),2)*BB76),2)+ROUND((ROUND(((AE76-(EU76))*AV76*1),2)*BS76),2)) -> 167.21 | CS76: =ROUND((ROUND((AE76*AV76*1),2)*BS76),2) -> 0 | CT76: =ROUND((ROUND((AF76*AV76*1),2)*BA76),2) -> 0 | CU76: =AG76 -> 0 | CV76: =(AH76*AV76) -> 0 | CW76: =AI76 -> 0 | CX76: =AJ76 -> 0 | CY76: =S76*(BZ76/100) -> 0 | CZ76: =S76*(CA76/100) -> 0 | DN76: 0 | DO76: 0 | DP76: 1 | DQ76: 1 | DU76: 1013 | DV76: 1 Т | DW76: 1 Т | DX76: 1 | EE76: 51697152 | EF76: 150 | EG76: Транспортные затраты | EH76: 0 | EJ76: 4 | EK76: 1113 | EL76: ТСН-2001.15-1. Перевозка строительного мусора | EM76: ТСН-2001.15-1-5 | EQ76: 131072 | ER76: 12.61 | ES76: 0 | ET76: 12.61 | EU76: 0 | EV76: 0 | EW76: 0 | EX76: 0 | EY76: 0 | FQ76: 0 | FR76: 0 | FS76: 0 | FX76: 0 | FY76: 0 | GD76: 0 | GF76: 1823831914 | GG76: 2 | GH76: 1 | GI76: 2 | GJ76: 0 | GK76: =ROUND(R76*(S12)/100,2) -> 0 | GL76: =ROUND(IF(AND(BH76=3,BI76=3,FS76<>0),P76,0),2) -> 0 | GM76: =ROUND(O76+X76+Y76+GK76,2)+GX76 -> 11681.13 | GN76: =IF(OR(BI76=0,BI76=1),GM76-GX76,0) -> 0 | GO76: =IF(BI76=2,GM76-GX76,0) -> 0 | GP76: =IF(BI76=4,GM76-GX76,0) -> 11681.13 | GR76: 0 | GS76: 3 | GT76: 0 | GV76: =ROUND((GT76),6) -> 0 | GW76: 1 | GX76: =ROUND(HC76*I76,2) -> 0 | HA76: 0 | HB76: 0 | HC76: =GV76*GW76 -> 0 | HS76: 0 | IK76: 0
A78: 51 | B78: =B69 -> 1 | C78: =A69 -> 4 | D78: =ROW(A69) -> 69 | F78: =IF(F69<>"",F69,"") -> Новый раздел | G78: =IF(G69<>"",G69,"") -> 10 кВ и 0,4 кВ | H78: 0 | O78: =ROUND(AB78,2) -> 4031.62 | P78: =ROUND(AC78,2) -> 0 | Q78: =ROUND(AD78,2) -> 4031.62 | R78: =ROUND(AE78,2) -> 0 | S78: =ROUND(AF78,2) -> 0 | T78: =ROUND(AG78,2) -> 0 | U78: =AH78 -> 0 | V78: =AI78 -> 0 | W78: =ROUND(AJ78,2) -> 0 | X78: =ROUND(AK78,2) -> 0 | Y78: =ROUND(AL78,2) -> 0 | AB78: =ROUND(SUMIF(AA73:AA76,"=57734472",O73:O76),2) -> 4031.62 | AC78: =ROUND(SUMIF(AA73:AA76,"=57734472",P73:P76),2) -> 0 | AD78: =ROUND(SUMIF(AA73:AA76,"=57734472",Q73:Q76),2) -> 4031.62 | AE78: =ROUND(SUMIF(AA73:AA76,"=57734472",R73:R76),2) -> 0 | AF78: =ROUND(SUMIF(AA73:AA76,"=57734472",S73:S76),2) -> 0 | AG78: =ROUND(SUMIF(AA73:AA76,"=57734472",T73:T76),2) -> 0 | AH78: =SUMIF(AA73:AA76,"=57734472",U73:U76) -> 0 | AI78: =SUMIF(AA73:AA76,"=57734472",V73:V76) -> 0 | AJ78: =ROUND(SUMIF(AA73:AA76,"=57734472",W73:W76),2) -> 0 | AK78: =ROUND(SUMIF(AA73:AA76,"=57734472",X73:X76),2) -> 0 | AL78: =ROUND(SUMIF(AA73:AA76,"=57734472",Y73:Y76),2) -> 0 | AO78: =ROUND(BX78,2) -> 0 | AP78: =ROUND(BY78,2) -> 0 | AQ78: =ROUND(BZ78,2) -> 0 | AR78: =ROUND(CA78,2) -> 4031.62 | AS78: =ROUND(CB78,2) -> 0 | AT78: =ROUND(CC78,2) -> 0 | AU78: =ROUND(CD78,2) -> 4031.62 | AV78: =ROUND(CE78,2) -> 0 | ... BD78: =ROUND(CM78,2) -> 0 | BX78: =ROUND(SUMIF(AA73:AA76,"=57734472",FQ73:FQ76),2) -> 0 | BY78: =ROUND(SUMIF(AA73:AA76,"=57734472",FR73:FR76),2) -> 0 | BZ78: =ROUND(SUMIF(AA73:AA76,"=57734472",GL73:GL76),2) -> 0 | CA78: =ROUND(SUMIF(AA73:AA76,"=57734472",GM73:GM76),2) -> 4031.62 | CB78: =ROUND(SUMIF(AA73:AA76,"=57734472",GN73:GN76),2) -> 0 | CC78: =ROUND(SUMIF(AA73:AA76,"=57734472",GO73:GO76),2) -> 0 | CD78: =ROUND(SUMIF(AA73:AA76,"=57734472",GP73:GP76),2) -> 4031.62 | CE78: =AC78-BX78 -> 0 | CF78: =AC78-BY78 -> 0 | CG78: =BX78-BZ78 -> 0 | CH78: =AC78-BX78-BY78+BZ78 -> 0 | CI78: =BY78-BZ78 -> 0 | CJ78: =ROUND(SUMIF(AA73:AA76,"=57734472",GX73:GX76),2) -> 0 | CK78: =ROUND(SUMIF(AA73:AA76,"=57734472",GY73:GY76),2) -> 0 | CL78: =ROUND(SUMIF(AA73:AA76,"=57734472",GZ73:GZ76),2) -> 0 | CM78: =ROUND(SUMIF(AA73:AA76,"=57734472",HD73:HD76),2) -> 0 | DG78: =ROUND(DT78,2) -> 60989.43 | DH78: =ROUND(DU78,2) -> 0 | DI78: =ROUND(DV78,2) -> 60989.43 | DJ78: =ROUND(DW78,2) -> 0 | DK78: =ROUND(DX78,2) -> 0 | DL78: =ROUND(DY78,2) -> 0 | DM78: =DZ78 -> 0 | DN78: =EA78 -> 0 | DO78: =ROUND(EB78,2) -> 0 | DP78: =ROUND(EC78,2) -> 0 | DQ78: =ROUND(ED78,2) -> 0 | DT78: =ROUND(SUMIF(AA73:AA76,"=57734470",O73:O76),2) -> 60989.43 | DU78: =ROUND(SUMIF(AA73:AA76,"=57734470",P73:P76),2) -> 0 | DV78: =ROUND(SUMIF(AA73:AA76,"=57734470",Q73:Q76),2) -> 60989.43 | DW78: =ROUND(SUMIF(AA73:AA76,"=57734470",R73:R76),2) -> 0 | DX78: =ROUND(SUMIF(AA73:AA76,"=57734470",S73:S76),2) -> 0 | DY78: =ROUND(SUMIF(AA73:AA76,"=57734470",T73:T76),2) -> 0 | DZ78: =SUMIF(AA73:AA76,"=57734470",U73:U76) -> 0 | EA78: =SUMIF(AA73:AA76,"=57734470",V73:V76) -> 0 | EB78: =ROUND(SUMIF(AA73:AA76,"=57734470",W73:W76),2) -> 0 | EC78: =ROUND(SUMIF(AA73:AA76,"=57734470",X73:X76),2) -> 0 | ED78: =ROUND(SUMIF(AA73:AA76,"=57734470",Y73:Y76),2) -> 0 | EG78: =ROUND(FP78,2) -> 0 | EH78: =ROUND(FQ78,2) -> 0 | EI78: =ROUND(FR78,2) -> 0 | EJ78: =ROUND(FS78,2) -> 60989.43 | EK78: =ROUND(FT78,2) -> 0 | EL78: =ROUND(FU78,2) -> 0 | EM78: =ROUND(FV78,2) -> 60989.43 | EN78: =ROUND(FW78,2) -> 0 | ... EV78: =ROUND(GE78,2) -> 0 | FP78: =ROUND(SUMIF(AA73:AA76,"=57734470",FQ73:FQ76),2) -> 0 | FQ78: =ROUND(SUMIF(AA73:AA76,"=57734470",FR73:FR76),2) -> 0 | FR78: =ROUND(SUMIF(AA73:AA76,"=57734470",GL73:GL76),2) -> 0 | FS78: =ROUND(SUMIF(AA73:AA76,"=57734470",GM73:GM76),2) -> 60989.43 | FT78: =ROUND(SUMIF(AA73:AA76,"=57734470",GN73:GN76),2) -> 0 | FU78: =ROUND(SUMIF(AA73:AA76,"=57734470",GO73:GO76),2) -> 0 | FV78: =ROUND(SUMIF(AA73:AA76,"=57734470",GP73:GP76),2) -> 60989.43 | FW78: =DU78-FP78 -> 0 | FX78: =DU78-FQ78 -> 0 | FY78: =FP78-FR78 -> 0 | FZ78: =DU78-FP78-FQ78+FR78 -> 0 | GA78: =FQ78-FR78 -> 0 | GB78: =ROUND(SUMIF(AA73:AA76,"=57734470",GX73:GX76),2) -> 0 | GC78: =ROUND(SUMIF(AA73:AA76,"=57734470",GY73:GY76),2) -> 0 | GD78: =ROUND(SUMIF(AA73:AA76,"=57734470",GZ73:GZ76),2) -> 0 | GE78: =ROUND(SUMIF(AA73:AA76,"=57734470",HD73:HD76),2) -> 0 | GX78: 0
A80: 50 | B80: 0 | C80: 0 | D80: 1 | E80: 0 | F80: =ROUND(Source!O78,O80) -> 4031.62 | G80: ПЗ | H80: Прямые затраты | K80: 201 | L80: 1 | M80: 3 | O80: 2 | P80: =ROUND(Source!DG78,O80) -> 60989.43 | W80: 4031.62 | X80: 1 | Y80: 4031.62 | Z80: 60989.43 | AA80: 1 | AB80: 60989.43
A81: 50 | B81: 0 | C81: 0 | D81: 1 | E81: 0 | F81: =ROUND(Source!P78,O81) -> 0 | G81: СтМатОб | H81: Стоимость материальных ресурсов (всего) | K81: 202 | L81: 2 | M81: 3 | O81: 2 | P81: =ROUND(Source!DH78,O81) -> 0 | W81: 0 | X81: 1 | Y81: 0 | Z81: 0 | AA81: 1 | AB81: 0
A82: 50 | B82: 0 | C82: 0 | D82: 1 | E82: 0 | F82: =ROUND(Source!AO78,O82) -> 0 | G82: СтМатОбЗак | H82: Стоимость материалов и оборудования заказчика | K82: 222 | L82: 3 | M82: 3 | O82: 2 | P82: =ROUND(Source!EG78,O82) -> 0 | W82: 0 | X82: 1 | Y82: 0 | Z82: 0 | AA82: 1 | AB82: 0
A83: 50 | B83: 0 | C83: 0 | D83: 1 | E83: 0 | F83: =ROUND(Source!AV78,O83) -> 0 | G83: СтМатОбПод | H83: Стоимость материалов и оборудования подрядчика | K83: 225 | L83: 4 | M83: 3 | O83: 2 | P83: =ROUND(Source!EN78,O83) -> 0 | W83: 0 | X83: 1 | Y83: 0 | Z83: 0 | AA83: 1 | AB83: 0
A84: 50 | B84: 0 | C84: 0 | D84: 1 | E84: 0 | F84: =ROUND(Source!AW78,O84) -> 0 | G84: СтМат | H84: Стоимость материалов (всего) | K84: 226 | L84: 5 | M84: 3 | O84: 2 | P84: =ROUND(Source!EO78,O84) -> 0 | W84: 0 | X84: 1 | Y84: 0 | Z84: 0 | AA84: 1 | AB84: 0
A85: 50 | B85: 0 | C85: 0 | D85: 1 | E85: 0 | F85: =ROUND(Source!AX78,O85) -> 0 | G85: СтМатЗак | H85: Стоимость материалов заказчика | K85: 227 | L85: 6 | M85: 3 | O85: 2 | P85: =ROUND(Source!EP78,O85) -> 0 | W85: 0 | X85: 1 | Y85: 0 | Z85: 0 | AA85: 1 | AB85: 0
A86: 50 | B86: 0 | C86: 0 | D86: 1 | E86: 0 | F86: =ROUND(Source!AY78,O86) -> 0 | G86: СтМатПод | H86: Стоимость материалов подрядчика | K86: 228 | L86: 7 | M86: 3 | O86: 2 | P86: =ROUND(Source!EQ78,O86) -> 0 | W86: 0 | X86: 1 | Y86: 0 | Z86: 0 | AA86: 1 | AB86: 0
A87: 50 | B87: 0 | C87: 0 | D87: 1 | E87: 0 | F87: =ROUND(Source!AP78,O87) -> 0 | G87: Оборуд | H87: Стоимость оборудования (всего) | K87: 216 | L87: 8 | M87: 3 | O87: 2 | P87: =ROUND(Source!EH78,O87) -> 0 | W87: 0 | X87: 1 | Y87: 0 | Z87: 0 | AA87: 1 | AB87: 0
A88: 50 | B88: 0 | C88: 0 | D88: 1 | E88: 0 | F88: =ROUND(Source!AQ78,O88) -> 0 | G88: ОборудЗак | H88: Стоимость оборудования заказчика | K88: 223 | L88: 9 | M88: 3 | O88: 2 | P88: =ROUND(Source!EI78,O88) -> 0 | W88: 0 | X88: 1 | Y88: 0 | Z88: 0 | AA88: 1 | AB88: 0
A89: 50 | B89: 0 | C89: 0 | D89: 1 | E89: 0 | F89: =ROUND(Source!AZ78,O89) -> 0 | G89: ОборудПод | H89: Стоимость оборудования подрядчика | K89: 229 | L89: 10 | M89: 3 | O89: 2 | P89: =ROUND(Source!ER78,O89) -> 0 | W89: 0 | X89: 1 | Y89: 0 | Z89: 0 | AA89: 1 | AB89: 0
A90: 50 | B90: 0 | C90: 0 | D90: 1 | E90: 0 | F90: =ROUND(Source!Q78,O90) -> 4031.62 | G90: ЭММ | H90: Эксплуатация машин | K90: 203 | L90: 11 | M90: 3 | O90: 2 | P90: =ROUND(Source!DI78,O90) -> 60989.43 | W90: 4031.62 | X90: 1 | Y90: 4031.62 | Z90: 60989.43 | AA90: 1 | AB90: 60989.43
A91: 50 | B91: 0 | C91: 0 | D91: 1 | E91: 0 | F91: =ROUND(Source!BB78,O91) -> 0 | G91: ЭММсНРиСП | H91: Эксплуатация машин по ТСН-2001.16 | K91: 231 | L91: 12 | M91: 3 | O91: 2 | P91: =ROUND(Source!ET78,O91) -> 0 | W91: 0 | X91: 1 | Y91: 0 | Z91: 0 | AA91: 1 | AB91: 0
A92: 50 | B92: 0 | C92: 0 | D92: 1 | E92: 0 | F92: =ROUND(Source!R78,O92) -> 0 | G92: ЗПМ | H92: ЗП машинистов | K92: 204 | L92: 13 | M92: 3 | O92: 2 | P92: =ROUND(Source!DJ78,O92) -> 0 | W92: 0 | X92: 1 | Y92: 0 | Z92: 0 | AA92: 1 | AB92: 0
A93: 50 | B93: 0 | C93: 0 | D93: 1 | E93: 0 | F93: =ROUND(Source!S78,O93) -> 0 | G93: ОЗП | H93: Основная ЗП рабочих | K93: 205 | L93: 14 | M93: 3 | O93: 2 | P93: =ROUND(Source!DK78,O93) -> 0 | W93: 0 | X93: 1 | Y93: 0 | Z93: 0 | AA93: 1 | AB93: 0
A94: 50 | B94: 0 | C94: 0 | D94: 1 | E94: 0 | F94: =ROUND(Source!BC78,O94) -> 0 | G94: ОЗПсНРиСП | H94: Основная ЗП рабочих по ТСН-2001.16 | K94: 232 | L94: 15 | M94: 3 | O94: 2 | P94: =ROUND(Source!EU78,O94) -> 0 | W94: 0 | X94: 1 | Y94: 0 | Z94: 0 | AA94: 1 | AB94: 0
A95: 50 | B95: 0 | C95: 0 | D95: 1 | E95: 0 | F95: =ROUND(Source!AS78,O95) -> 0 | G95: Строит | H95: Строительные работы с НР и СП | K95: 214 | L95: 16 | M95: 3 | O95: 2 | P95: =ROUND(Source!EK78,O95) -> 0 | W95: 0 | X95: 1 | Y95: 0 | Z95: 0 | AA95: 1 | AB95: 0
A96: 50 | B96: 0 | C96: 0 | D96: 1 | E96: 0 | F96: =ROUND(Source!AT78,O96) -> 0 | G96: Монтаж | H96: Монтажные работы с НР и СП | K96: 215 | L96: 17 | M96: 3 | O96: 2 | P96: =ROUND(Source!EL78,O96) -> 0 | W96: 0 | X96: 1 | Y96: 0 | Z96: 0 | AA96: 1 | AB96: 0
A97: 50 | B97: 0 | C97: 0 | D97: 1 | E97: 0 | F97: =ROUND(Source!AU78,O97) -> 4031.62 | G97: Прочие | H97: Прочие работы с НР и СП | K97: 217 | L97: 18 | M97: 3 | O97: 2 | P97: =ROUND(Source!EM78,O97) -> 60989.43 | W97: 4031.62 | X97: 1 | Y97: 4031.62 | Z97: 60989.43 | AA97: 1 | AB97: 60989.43
A98: 50 | B98: 0 | C98: 0 | D98: 1 | E98: 0 | F98: =ROUND(Source!BA78,O98) -> 0 | G98: ПрочиеЗатр | H98: Прочие затраты по ТСН-2001.16 | K98: 230 | L98: 19 | M98: 3 | O98: 2 | P98: =ROUND(Source!ES78,O98) -> 0 | W98: 0 | X98: 1 | Y98: 0 | Z98: 0 | AA98: 1 | AB98: 0
A99: 50 | B99: 0 | C99: 0 | D99: 1 | E99: 0 | F99: =ROUND(Source!T78,O99) -> 0 | G99: ВозврМат | H99: Возврат материалов | K99: 206 | L99: 20 | M99: 3 | O99: 2 | P99: =ROUND(Source!DL78,O99) -> 0 | W99: 0 | X99: 1 | Y99: 0 | Z99: 0 | AA99: 1 | AB99: 0
A100: 50 | B100: 0 | C100: 0 | D100: 1 | E100: 0 | F100: =Source!U78 -> 0 | G100: ТрудСтр | H100: Трудозатраты строителей | K100: 207 | L100: 21 | M100: 3 | O100: -1 | P100: =Source!DM78 -> 0 | W100: 0 | X100: 1 | Y100: 0 | Z100: 0 | AA100: 1 | AB100: 0
A101: 50 | B101: 0 | C101: 0 | D101: 1 | E101: 0 | F101: =Source!V78 -> 0 | G101: ТрудМаш | H101: Трудозатраты машинистов | K101: 208 | L101: 22 | M101: 3 | O101: -1 | P101: =Source!DN78 -> 0 | W101: 0 | X101: 1 | Y101: 0 | Z101: 0 | AA101: 1 | AB101: 0
A102: 50 | B102: 0 | C102: 0 | D102: 1 | E102: 0 | F102: =ROUND(Source!W78,O102) -> 0 | G102: ТранспМат | H102: Транспорт материалов | K102: 209 | L102: 23 | M102: 3 | O102: 2 | P102: =ROUND(Source!DO78,O102) -> 0 | W102: 0 | X102: 1 | Y102: 0 | Z102: 0 | AA102: 1 | AB102: 0
A103: 50 | B103: 0 | C103: 0 | D103: 1 | E103: 0 | F103: =ROUND(Source!BD78,O103) -> 0 | G103: Перевозка | H103: Перевозка грузов | K103: 233 | L103: 24 | M103: 3 | O103: 2 | P103: =ROUND(Source!EV78,O103) -> 0 | W103: 0 | X103: 1 | Y103: 0 | Z103: 0 | AA103: 1 | AB103: 0
A104: 50 | B104: 0 | C104: 0 | D104: 1 | E104: 210 | F104: =ROUND(Source!X78,O104) -> 0 | G104: НР | H104: Накладные расходы | K104: 210 | L104: 25 | M104: 3 | O104: 2 | P104: =ROUND(Source!DP78,O104) -> 0 | W104: 0 | X104: 1 | Y104: 0 | Z104: 0 | AA104: 1 | AB104: 0
A105: 50 | B105: 0 | C105: 0 | D105: 1 | E105: 211 | F105: =ROUND(Source!Y78,O105) -> 0 | G105: СмПриб | H105: Сметная прибыль | K105: 211 | L105: 26 | M105: 3 | O105: 2 | P105: =ROUND(Source!DQ78,O105) -> 0 | W105: 0 | X105: 1 | Y105: 0 | Z105: 0 | AA105: 1 | AB105: 0
A106: 50 | B106: 0 | C106: 0 | D106: 1 | E106: 224 | F106: =ROUND(Source!AR78,O106) -> 4031.62 | G106: Всего | H106: Всего с НР и СП | K106: 224 | L106: 27 | M106: 3 | O106: 2 | P106: =ROUND(Source!EJ78,O106) -> 60989.43 | W106: 4031.62 | X106: 1 | Y106: 4031.62 | Z106: 60989.43 | AA106: 1 | AB106: 60989.43
A108: 4 | B108: 1 | D108: =ROW(A117) -> 117 | F108: Новый раздел | G108: ТП | I108: 0 | K108: 0 | S108: 0 | T108: 0 | V108: 0 | BX108: 0 | CJ108: 0
A110: 52 | B110: =B117 -> 1 | C110: =C117 -> 4 | D110: =D117 -> 108 | E110: =E117 -> 0 | F110: =F117 -> Новый раздел | G110: =G117 -> ТП | O110: =O117 -> 0 | P110: =P117 -> 0 | Q110: =Q117 -> 0 | R110: =R117 -> 0 | S110: =S117 -> 0 | T110: =T117 -> 0 | U110: =U117 -> 0 | V110: =V117 -> 0 | ... GX110: =GX117 -> 0
A112: 17 | B112: 1 | D112: =ROW(EtalonRes!A15) -> 15 | F112: 15.2-53-4 | G112: Перевозка грунтов скальных и дисперсных несвязных на расстояние до 53 км автосамосвалами грузоподъемностью до 10 т | H112: т | I112: =ROUND(89.42*1.75,9) -> 156.485 | J112: 0 | K112: =ROUND(89.42*1.75,9) -> 156.485 | O112: =ROUND(CP112,2) -> 7057.47 | P112: =ROUND((ROUND((AC112*AW112*I112),2)*BC112),2) -> 0 | Q112: =(ROUND((ROUND(((ET112)*AV112*I112),2)*BB112),2)+ROUND((ROUND(((AE112-(EU112))*AV112*I112),2)*BS112),2)) -> 7057.47 | R112: =ROUND((ROUND((AE112*AV112*I112),2)*BS112),2) -> 0 | S112: =ROUND((ROUND((AF112*AV112*I112),2)*BA112),2) -> 0 | T112: =ROUND(CU112*I112,2) -> 0 | U112: =CV112*I112 -> 0 | V112: =CW112*I112 -> 0 | W112: =ROUND(CX112*I112,2) -> 0 | X112: =ROUND(CY112,2) -> 0 | Y112: =ROUND(CZ112,2) -> 0 | AA112: -1 | AB112: =ROUND((AC112+AD112+AF112),6) -> 45.1 | AC112: =ROUND((ES112),6) -> 0 | AD112: =ROUND((((ET112)-(EU112))+AE112),6) -> 45.1 | AE112: =ROUND((EU112),6) -> 0 | AF112: =ROUND((EV112),6) -> 0 | AG112: =ROUND((AP112),6) -> 0 | AH112: =(EW112) -> 0 | AI112: =(EX112) -> 0 | AJ112: =(AS112) -> 0 | AK112: 45.1 | AL112: 0 | AM112: 45.1 | AN112: 0 | AO112: 0 | AP112: 0 | AQ112: 0 | AR112: 0 | AS112: 0 | AT112: 0 | AU112: 0 | AV112: 1 | AW112: 1 | AZ112: 1 | BA112: 1 | BB112: 1 | BC112: 1 | BH112: 0 | BI112: 4 | BJ112: ТСН-2001.15 Доп. 68, Сб. 2, т. 53, поз. 4 | BM112: 1111 | BN112: 0 | BP112: 0 | BQ112: 150 | BR112: 0 | BS112: 1 | BT112: 1 | BU112: 1 | BV112: 1 | BW112: 1 | BX112: 1 | BZ112: 0 | CA112: 0 | CE112: 30 | CF112: 0 | CG112: 0 | CM112: 0 | CO112: 0 | CP112: =(P112+Q112+S112) -> 7057.47 | CQ112: =ROUND((ROUND((AC112*AW112*1),2)*BC112),2) -> 0 | CR112: =(ROUND((ROUND(((ET112)*AV112*1),2)*BB112),2)+ROUND((ROUND(((AE112-(EU112))*AV112*1),2)*BS112),2)) -> 45.1 | CS112: =ROUND((ROUND((AE112*AV112*1),2)*BS112),2) -> 0 | CT112: =ROUND((ROUND((AF112*AV112*1),2)*BA112),2) -> 0 | CU112: =AG112 -> 0 | CV112: =(AH112*AV112) -> 0 | CW112: =AI112 -> 0 | CX112: =AJ112 -> 0 | CY112: =((S112*BZ112)/100) -> 0 | CZ112: =((S112*CA112)/100) -> 0 | DN112: 0 | DO112: 0 | DP112: 1 | DQ112: 1 | DU112: 1009 | DV112: т | DW112: т | DX112: 1000 | EE112: 51697150 | EF112: 150 | EG112: Транспортные затраты | EH112: 0 | EJ112: 4 | EK112: 1111 | EL112: ТСН-2001.15-1. Перевозка грунта | EM112: ТСН-2001.15-1-3 | EQ112: 132096 | ER112: 45.1 | ES112: 0 | ET112: 45.1 | EU112: 0 | EV112: 0 | EW112: 0 | EX112: 0 | EY112: 0 | FQ112: 0 | FR112: 0 | FS112: 0 | FX112: 0 | FY112: 0 | GD112: 1 | GF112: -1114147576 | GG112: 2 | GH112: 1 | GI112: -2 | GJ112: 0 | GK112: 0 | GL112: =ROUND(IF(AND(BH112=3,BI112=3,FS112<>0),P112,0),2) -> 0 | GM112: =ROUND(O112+X112+Y112,2)+GX112 -> 7057.47 | GN112: =IF(OR(BI112=0,BI112=1),GM112-GX112,0) -> 0 | GO112: =IF(BI112=2,GM112-GX112,0) -> 0 | GP112: =IF(BI112=4,GM112-GX112,0) -> 7057.47 | GR112: 0 | GS112: 0 | GT112: 0 | GV112: =ROUND((GT112),6) -> 0 | GW112: 1 | GX112: =ROUND(HC112*I112,2) -> 0 | HA112: 0 | HB112: 0 | HC112: =GV112*GW112 -> 0 | HS112: 0 | IK112: 0
A113: 17 | B113: 1 | D113: =ROW(EtalonRes!A16) -> 16 | F113: 15.2-53-4 | G113: Перевозка грунтов скальных и дисперсных несвязных на расстояние до 53 км автосамосвалами грузоподъемностью до 10 т | H113: т | I113: =ROUND(89.42*1.75,9) -> 156.485 | J113: 0 | K113: =ROUND(89.42*1.75,9) -> 156.485 | O113: =ROUND(CP113,2) -> 110449.41 | P113: =ROUND((ROUND((AC113*AW113*I113),2)*BC113),2) -> 0 | Q113: =(ROUND((ROUND(((ET113)*AV113*I113),2)*BB113),2)+ROUND((ROUND(((AE113-(EU113))*AV113*I113),2)*BS113),2)) -> 110449.41 | R113: =ROUND((ROUND((AE113*AV113*I113),2)*BS113),2) -> 0 | S113: =ROUND((ROUND((AF113*AV113*I113),2)*BA113),2) -> 0 | T113: =ROUND(CU113*I113,2) -> 0 | U113: =CV113*I113 -> 0 | V113: =CW113*I113 -> 0 | W113: =ROUND(CX113*I113,2) -> 0 | X113: =ROUND(CY113,2) -> 0 | Y113: =ROUND(CZ113,2) -> 0 | AA113: -1 | AB113: =ROUND((AC113+AD113+AF113),6) -> 45.1 | AC113: =ROUND((ES113),6) -> 0 | AD113: =ROUND((((ET113)-(EU113))+AE113),6) -> 45.1 | AE113: =ROUND((EU113),6) -> 0 | AF113: =ROUND((EV113),6) -> 0 | AG113: =ROUND((AP113),6) -> 0 | AH113: =(EW113) -> 0 | AI113: =(EX113) -> 0 | AJ113: =(AS113) -> 0 | AK113: 45.1 | AL113: 0 | AM113: 45.1 | AN113: 0 | AO113: 0 | AP113: 0 | AQ113: 0 | AR113: 0 | AS113: 0 | AT113: 95 | AU113: 65 | AV113: 1 | AW113: 1 | AZ113: 1 | BA113: 1 | BB113: 15.65 | BC113: 1 | BH113: 0 | BI113: 4 | BJ113: ТСН-2001.15 Доп. 68, Сб. 2, т. 53, поз. 4 | BM113: 1111 | BN113: 0 | BO113: 15.2-53-4 | BP113: 1 | BQ113: 150 | BR113: 0 | BS113: 1 | BT113: 1 | BU113: 1 | BV113: 1 | BW113: 1 | BX113: 1 | BZ113: 95 | CA113: 65 | CE113: 30 | CF113: 0 | CG113: 0 | CM113: 0 | CO113: 0 | CP113: =(P113+Q113+S113) -> 110449.41 | CQ113: =ROUND((ROUND((AC113*AW113*1),2)*BC113),2) -> 0 | CR113: =(ROUND((ROUND(((ET113)*AV113*1),2)*BB113),2)+ROUND((ROUND(((AE113-(EU113))*AV113*1),2)*BS113),2)) -> 705.82 | CS113: =ROUND((ROUND((AE113*AV113*1),2)*BS113),2) -> 0 | CT113: =ROUND((ROUND((AF113*AV113*1),2)*BA113),2) -> 0 | CU113: =AG113 -> 0 | CV113: =(AH113*AV113) -> 0 | CW113: =AI113 -> 0 | CX113: =AJ113 -> 0 | CY113: =S113*(BZ113/100) -> 0 | CZ113: =S113*(CA113/100) -> 0 | DN113: 0 | DO113: 0 | DP113: 1 | DQ113: 1 | DU113: 1009 | DV113: т | DW113: т | DX113: 1000 | EE113: 51697150 | EF113: 150 | EG113: Транспортные затраты | EH113: 0 | EJ113: 4 | EK113: 1111 | EL113: ТСН-2001.15-1. Перевозка грунта | EM113: ТСН-2001.15-1-3 | EQ113: 132096 | ER113: 45.1 | ES113: 0 | ET113: 45.1 | EU113: 0 | EV113: 0 | EW113: 0 | EX113: 0 | EY113: 0 | FQ113: 0 | FR113: 0 | FS113: 0 | FX113: 0 | FY113: 0 | GD113: 0 | GF113: -1114147576 | GG113: 2 | GH113: 1 | GI113: 2 | GJ113: 0 | GK113: =ROUND(R113*(S12)/100,2) -> 0 | GL113: =ROUND(IF(AND(BH113=3,BI113=3,FS113<>0),P113,0),2) -> 0 | GM113: =ROUND(O113+X113+Y113+GK113,2)+GX113 -> 110449.41 | GN113: =IF(OR(BI113=0,BI113=1),GM113-GX113,0) -> 0 | GO113: =IF(BI113=2,GM113-GX113,0) -> 0 | GP113: =IF(BI113=4,GM113-GX113,0) -> 110449.41 | GR113: 0 | GS113: 3 | GT113: 0 | GV113: =ROUND((GT113),6) -> 0 | GW113: 1 | GX113: =ROUND(HC113*I113,2) -> 0 | HA113: 0 | HB113: 0 | HC113: =GV113*GW113 -> 0 | HS113: 0 | IK113: 0
A114: 17 | B114: 1 | D114: =ROW(EtalonRes!A17) -> 17 | F114: 15.1-1102-01 | G114: Отходы грунта при проведении открытых земляных работ практически неопасные | H114: 1 Т | I114: =ROUND(I112,9) -> 156.485 | J114: 0 | K114: =ROUND(I112,9) -> 156.485 | O114: =ROUND(CP114,2) -> 1973.28 | P114: =ROUND((ROUND((AC114*AW114*I114),2)*BC114),2) -> 0 | Q114: =(ROUND((ROUND(((ET114)*AV114*I114),2)*BB114),2)+ROUND((ROUND(((AE114-(EU114))*AV114*I114),2)*BS114),2)) -> 1973.28 | R114: =ROUND((ROUND((AE114*AV114*I114),2)*BS114),2) -> 0 | S114: =ROUND((ROUND((AF114*AV114*I114),2)*BA114),2) -> 0 | T114: =ROUND(CU114*I114,2) -> 0 | U114: =CV114*I114 -> 0 | V114: =CW114*I114 -> 0 | W114: =ROUND(CX114*I114,2) -> 0 | X114: =ROUND(CY114,2) -> 0 | Y114: =ROUND(CZ114,2) -> 0 | AA114: -1 | AB114: =ROUND((AC114+AD114+AF114),6) -> 12.61 | AC114: =ROUND((ES114),6) -> 0 | AD114: =ROUND((((ET114)-(EU114))+AE114),6) -> 12.61 | AE114: =ROUND((EU114),6) -> 0 | AF114: =ROUND((EV114),6) -> 0 | AG114: =ROUND((AP114),6) -> 0 | AH114: =(EW114) -> 0 | AI114: =(EX114) -> 0 | AJ114: =(AS114) -> 0 | AK114: 12.61 | AL114: 0 | AM114: 12.61 | AN114: 0 | AO114: 0 | AP114: 0 | AQ114: 0 | AR114: 0 | AS114: 0 | AT114: 0 | AU114: 0 | AV114: 1 | AW114: 1 | AZ114: 1 | BA114: 1 | BB114: 1 | BC114: 1 | BH114: 0 | BI114: 4 | BJ114: ТСН-2001.15 Доп. 56, Сб. 1, т. 1102, поз. 1 | BM114: 1113 | BN114: 0 | BP114: 0 | BQ114: 150 | BR114: 0 | BS114: 1 | BT114: 1 | BU114: 1 | BV114: 1 | BW114: 1 | BX114: 1 | BZ114: 0 | CA114: 0 | CE114: 30 | CF114: 0 | CG114: 0 | CM114: 0 | CO114: 0 | CP114: =(P114+Q114+S114) -> 1973.28 | CQ114: =ROUND((ROUND((AC114*AW114*1),2)*BC114),2) -> 0 | CR114: =(ROUND((ROUND(((ET114)*AV114*1),2)*BB114),2)+ROUND((ROUND(((AE114-(EU114))*AV114*1),2)*BS114),2)) -> 12.61 | CS114: =ROUND((ROUND((AE114*AV114*1),2)*BS114),2) -> 0 | CT114: =ROUND((ROUND((AF114*AV114*1),2)*BA114),2) -> 0 | CU114: =AG114 -> 0 | CV114: =(AH114*AV114) -> 0 | CW114: =AI114 -> 0 | CX114: =AJ114 -> 0 | CY114: =((S114*BZ114)/100) -> 0 | CZ114: =((S114*CA114)/100) -> 0 | DN114: 0 | DO114: 0 | DP114: 1 | DQ114: 1 | DU114: 1013 | DV114: 1 Т | DW114: 1 Т | DX114: 1 | EE114: 51697152 | EF114: 150 | EG114: Транспортные затраты | EH114: 0 | EJ114: 4 | EK114: 1113 | EL114: ТСН-2001.15-1. Перевозка строительного мусора | EM114: ТСН-2001.15-1-5 | EQ114: 132096 | ER114: 12.61 | ES114: 0 | ET114: 12.61 | EU114: 0 | EV114: 0 | EW114: 0 | EX114: 0 | EY114: 0 | FQ114: 0 | FR114: 0 | FS114: 0 | FX114: 0 | FY114: 0 | GD114: 1 | GF114: 1823831914 | GG114: 2 | GH114: 1 | GI114: -2 | GJ114: 0 | GK114: 0 | GL114: =ROUND(IF(AND(BH114=3,BI114=3,FS114<>0),P114,0),2) -> 0 | GM114: =ROUND(O114+X114+Y114,2)+GX114 -> 1973.28 | GN114: =IF(OR(BI114=0,BI114=1),GM114-GX114,0) -> 0 | GO114: =IF(BI114=2,GM114-GX114,0) -> 0 | GP114: =IF(BI114=4,GM114-GX114,0) -> 1973.28 | GR114: 0 | GS114: 0 | GT114: 0 | GV114: =ROUND((GT114),6) -> 0 | GW114: 1 | GX114: =ROUND(HC114*I114,2) -> 0 | HA114: 0 | HB114: 0 | HC114: =GV114*GW114 -> 0 | HS114: 0 | IK114: 0
A115: 17 | B115: 1 | D115: =ROW(EtalonRes!A18) -> 18 | F115: 15.1-1102-01 | G115: Отходы грунта при проведении открытых земляных работ практически неопасные | H115: 1 Т | I115: =ROUND(I113,9) -> 156.485 | J115: 0 | K115: =ROUND(I113,9) -> 156.485 | O115: =ROUND(CP115,2) -> 26165.69 | P115: =ROUND((ROUND((AC115*AW115*I115),2)*BC115),2) -> 0 | Q115: =(ROUND((ROUND(((ET115)*AV115*I115),2)*BB115),2)+ROUND((ROUND(((AE115-(EU115))*AV115*I115),2)*BS115),2)) -> 26165.69 | R115: =ROUND((ROUND((AE115*AV115*I115),2)*BS115),2) -> 0 | S115: =ROUND((ROUND((AF115*AV115*I115),2)*BA115),2) -> 0 | T115: =ROUND(CU115*I115,2) -> 0 | U115: =CV115*I115 -> 0 | V115: =CW115*I115 -> 0 | W115: =ROUND(CX115*I115,2) -> 0 | X115: =ROUND(CY115,2) -> 0 | Y115: =ROUND(CZ115,2) -> 0 | AA115: -1 | AB115: =ROUND((AC115+AD115+AF115),6) -> 12.61 | AC115: =ROUND((ES115),6) -> 0 | AD115: =ROUND((((ET115)-(EU115))+AE115),6) -> 12.61 | AE115: =ROUND((EU115),6) -> 0 | AF115: =ROUND((EV115),6) -> 0 | AG115: =ROUND((AP115),6) -> 0 | AH115: =(EW115) -> 0 | AI115: =(EX115) -> 0 | AJ115: =(AS115) -> 0 | AK115: 12.61 | AL115: 0 | AM115: 12.61 | AN115: 0 | AO115: 0 | AP115: 0 | AQ115: 0 | AR115: 0 | AS115: 0 | AT115: 95 | AU115: 65 | AV115: 1 | AW115: 1 | AZ115: 1 | BA115: 1 | BB115: 13.26 | BC115: 1 | BH115: 0 | BI115: 4 | BJ115: ТСН-2001.15 Доп. 56, Сб. 1, т. 1102, поз. 1 | BM115: 1113 | BN115: 0 | BO115: 15.1-1102-01 | BP115: 1 | BQ115: 150 | BR115: 0 | BS115: 1 | BT115: 1 | BU115: 1 | BV115: 1 | BW115: 1 | BX115: 1 | BZ115: 95 | CA115: 65 | CE115: 30 | CF115: 0 | CG115: 0 | CM115: 0 | CO115: 0 | CP115: =(P115+Q115+S115) -> 26165.69 | CQ115: =ROUND((ROUND((AC115*AW115*1),2)*BC115),2) -> 0 | CR115: =(ROUND((ROUND(((ET115)*AV115*1),2)*BB115),2)+ROUND((ROUND(((AE115-(EU115))*AV115*1),2)*BS115),2)) -> 167.21 | CS115: =ROUND((ROUND((AE115*AV115*1),2)*BS115),2) -> 0 | CT115: =ROUND((ROUND((AF115*AV115*1),2)*BA115),2) -> 0 | CU115: =AG115 -> 0 | CV115: =(AH115*AV115) -> 0 | CW115: =AI115 -> 0 | CX115: =AJ115 -> 0 | CY115: =S115*(BZ115/100) -> 0 | CZ115: =S115*(CA115/100) -> 0 | DN115: 0 | DO115: 0 | DP115: 1 | DQ115: 1 | DU115: 1013 | DV115: 1 Т | DW115: 1 Т | DX115: 1 | EE115: 51697152 | EF115: 150 | EG115: Транспортные затраты | EH115: 0 | EJ115: 4 | EK115: 1113 | EL115: ТСН-2001.15-1. Перевозка строительного мусора | EM115: ТСН-2001.15-1-5 | EQ115: 132096 | ER115: 12.61 | ES115: 0 | ET115: 12.61 | EU115: 0 | EV115: 0 | EW115: 0 | EX115: 0 | EY115: 0 | FQ115: 0 | FR115: 0 | FS115: 0 | FX115: 0 | FY115: 0 | GD115: 0 | GF115: 1823831914 | GG115: 2 | GH115: 1 | GI115: 2 | GJ115: 0 | GK115: =ROUND(R115*(S12)/100,2) -> 0 | GL115: =ROUND(IF(AND(BH115=3,BI115=3,FS115<>0),P115,0),2) -> 0 | GM115: =ROUND(O115+X115+Y115+GK115,2)+GX115 -> 26165.69 | GN115: =IF(OR(BI115=0,BI115=1),GM115-GX115,0) -> 0 | GO115: =IF(BI115=2,GM115-GX115,0) -> 0 | GP115: =IF(BI115=4,GM115-GX115,0) -> 26165.69 | GR115: 0 | GS115: 3 | GT115: 0 | GV115: =ROUND((GT115),6) -> 0 | GW115: 1 | GX115: =ROUND(HC115*I115,2) -> 0 | HA115: 0 | HB115: 0 | HC115: =GV115*GW115 -> 0 | HS115: 0 | IK115: 0
A117: 51 | B117: =B108 -> 1 | C117: =A108 -> 4 | D117: =ROW(A108) -> 108 | F117: =IF(F108<>"",F108,"") -> Новый раздел | G117: =IF(G108<>"",G108,"") -> ТП | H117: 0 | O117: =ROUND(AB117,2) -> 0 | P117: =ROUND(AC117,2) -> 0 | Q117: =ROUND(AD117,2) -> 0 | R117: =ROUND(AE117,2) -> 0 | S117: =ROUND(AF117,2) -> 0 | T117: =ROUND(AG117,2) -> 0 | U117: =AH117 -> 0 | V117: =AI117 -> 0 | W117: =ROUND(AJ117,2) -> 0 | X117: =ROUND(AK117,2) -> 0 | Y117: =ROUND(AL117,2) -> 0 | AB117: =ROUND(SUMIF(AA112:AA115,"=57734472",O112:O115),2) -> 0 | AC117: =ROUND(SUMIF(AA112:AA115,"=57734472",P112:P115),2) -> 0 | AD117: =ROUND(SUMIF(AA112:AA115,"=57734472",Q112:Q115),2) -> 0 | AE117: =ROUND(SUMIF(AA112:AA115,"=57734472",R112:R115),2) -> 0 | AF117: =ROUND(SUMIF(AA112:AA115,"=57734472",S112:S115),2) -> 0 | AG117: =ROUND(SUMIF(AA112:AA115,"=57734472",T112:T115),2) -> 0 | AH117: =SUMIF(AA112:AA115,"=57734472",U112:U115) -> 0 | AI117: =SUMIF(AA112:AA115,"=57734472",V112:V115) -> 0 | AJ117: =ROUND(SUMIF(AA112:AA115,"=57734472",W112:W115),2) -> 0 | AK117: =ROUND(SUMIF(AA112:AA115,"=57734472",X112:X115),2) -> 0 | AL117: =ROUND(SUMIF(AA112:AA115,"=57734472",Y112:Y115),2) -> 0 | AO117: =ROUND(BX117,2) -> 0 | AP117: =ROUND(BY117,2) -> 0 | AQ117: =ROUND(BZ117,2) -> 0 | AR117: =ROUND(CA117,2) -> 0 | AS117: =ROUND(CB117,2) -> 0 | AT117: =ROUND(CC117,2) -> 0 | AU117: =ROUND(CD117,2) -> 0 | AV117: =ROUND(CE117,2) -> 0 | ... BD117: =ROUND(CM117,2) -> 0 | BX117: =ROUND(SUMIF(AA112:AA115,"=57734472",FQ112:FQ115),2) -> 0 | BY117: =ROUND(SUMIF(AA112:AA115,"=57734472",FR112:FR115),2) -> 0 | BZ117: =ROUND(SUMIF(AA112:AA115,"=57734472",GL112:GL115),2) -> 0 | CA117: =ROUND(SUMIF(AA112:AA115,"=57734472",GM112:GM115),2) -> 0 | CB117: =ROUND(SUMIF(AA112:AA115,"=57734472",GN112:GN115),2) -> 0 | CC117: =ROUND(SUMIF(AA112:AA115,"=57734472",GO112:GO115),2) -> 0 | CD117: =ROUND(SUMIF(AA112:AA115,"=57734472",GP112:GP115),2) -> 0 | CE117: =AC117-BX117 -> 0 | CF117: =AC117-BY117 -> 0 | CG117: =BX117-BZ117 -> 0 | CH117: =AC117-BX117-BY117+BZ117 -> 0 | CI117: =BY117-BZ117 -> 0 | CJ117: =ROUND(SUMIF(AA112:AA115,"=57734472",GX112:GX115),2) -> 0 | CK117: =ROUND(SUMIF(AA112:AA115,"=57734472",GY112:GY115),2) -> 0 | CL117: =ROUND(SUMIF(AA112:AA115,"=57734472",GZ112:GZ115),2) -> 0 | CM117: =ROUND(SUMIF(AA112:AA115,"=57734472",HD112:HD115),2) -> 0 | DG117: =ROUND(DT117,2) -> 0 | DH117: =ROUND(DU117,2) -> 0 | DI117: =ROUND(DV117,2) -> 0 | DJ117: =ROUND(DW117,2) -> 0 | DK117: =ROUND(DX117,2) -> 0 | DL117: =ROUND(DY117,2) -> 0 | DM117: =DZ117 -> 0 | DN117: =EA117 -> 0 | DO117: =ROUND(EB117,2) -> 0 | DP117: =ROUND(EC117,2) -> 0 | DQ117: =ROUND(ED117,2) -> 0 | DT117: =ROUND(SUMIF(AA112:AA115,"=57734470",O112:O115),2) -> 0 | DU117: =ROUND(SUMIF(AA112:AA115,"=57734470",P112:P115),2) -> 0 | DV117: =ROUND(SUMIF(AA112:AA115,"=57734470",Q112:Q115),2) -> 0 | DW117: =ROUND(SUMIF(AA112:AA115,"=57734470",R112:R115),2) -> 0 | DX117: =ROUND(SUMIF(AA112:AA115,"=57734470",S112:S115),2) -> 0 | DY117: =ROUND(SUMIF(AA112:AA115,"=57734470",T112:T115),2) -> 0 | DZ117: =SUMIF(AA112:AA115,"=57734470",U112:U115) -> 0 | EA117: =SUMIF(AA112:AA115,"=57734470",V112:V115) -> 0 | EB117: =ROUND(SUMIF(AA112:AA115,"=57734470",W112:W115),2) -> 0 | EC117: =ROUND(SUMIF(AA112:AA115,"=57734470",X112:X115),2) -> 0 | ED117: =ROUND(SUMIF(AA112:AA115,"=57734470",Y112:Y115),2) -> 0 | EG117: =ROUND(FP117,2) -> 0 | EH117: =ROUND(FQ117,2) -> 0 | EI117: =ROUND(FR117,2) -> 0 | EJ117: =ROUND(FS117,2) -> 0 | EK117: =ROUND(FT117,2) -> 0 | EL117: =ROUND(FU117,2) -> 0 | EM117: =ROUND(FV117,2) -> 0 | EN117: =ROUND(FW117,2) -> 0 | ... EV117: =ROUND(GE117,2) -> 0 | FP117: =ROUND(SUMIF(AA112:AA115,"=57734470",FQ112:FQ115),2) -> 0 | FQ117: =ROUND(SUMIF(AA112:AA115,"=57734470",FR112:FR115),2) -> 0 | FR117: =ROUND(SUMIF(AA112:AA115,"=57734470",GL112:GL115),2) -> 0 | FS117: =ROUND(SUMIF(AA112:AA115,"=57734470",GM112:GM115),2) -> 0 | FT117: =ROUND(SUMIF(AA112:AA115,"=57734470",GN112:GN115),2) -> 0 | FU117: =ROUND(SUMIF(AA112:AA115,"=57734470",GO112:GO115),2) -> 0 | FV117: =ROUND(SUMIF(AA112:AA115,"=57734470",GP112:GP115),2) -> 0 | FW117: =DU117-FP117 -> 0 | FX117: =DU117-FQ117 -> 0 | FY117: =FP117-FR117 -> 0 | FZ117: =DU117-FP117-FQ117+FR117 -> 0 | GA117: =FQ117-FR117 -> 0 | GB117: =ROUND(SUMIF(AA112:AA115,"=57734470",GX112:GX115),2) -> 0 | GC117: =ROUND(SUMIF(AA112:AA115,"=57734470",GY112:GY115),2) -> 0 | GD117: =ROUND(SUMIF(AA112:AA115,"=57734470",GZ112:GZ115),2) -> 0 | GE117: =ROUND(SUMIF(AA112:AA115,"=57734470",HD112:HD115),2) -> 0 | GX117: 0
A119: 50 | B119: 0 | C119: 0 | D119: 1 | E119: 201 | F119: =ROUND(Source!O117,O119) -> 0 | G119: ПЗ | H119: Прямые затраты | K119: 201 | L119: 1 | M119: 3 | O119: 2 | P119: =ROUND(Source!DG117,O119) -> 0 | W119: 0 | X119: 1 | Y119: 0 | Z119: 0 | AA119: 1 | AB119: 0
A120: 50 | B120: 0 | C120: 0 | D120: 1 | E120: 202 | F120: =ROUND(Source!P117,O120) -> 0 | G120: СтМатОб | H120: Стоимость материальных ресурсов (всего) | K120: 202 | L120: 2 | M120: 3 | O120: 2 | P120: =ROUND(Source!DH117,O120) -> 0 | W120: 0 | X120: 1 | Y120: 0 | Z120: 0 | AA120: 1 | AB120: 0
A121: 50 | B121: 0 | C121: 0 | D121: 1 | E121: 222 | F121: =ROUND(Source!AO117,O121) -> 0 | G121: СтМатОбЗак | H121: Стоимость материалов и оборудования заказчика | K121: 222 | L121: 3 | M121: 3 | O121: 2 | P121: =ROUND(Source!EG117,O121) -> 0 | W121: 0 | X121: 1 | Y121: 0 | Z121: 0 | AA121: 1 | AB121: 0
A122: 50 | B122: 0 | C122: 0 | D122: 1 | E122: 225 | F122: =ROUND(Source!AV117,O122) -> 0 | G122: СтМатОбПод | H122: Стоимость материалов и оборудования подрядчика | K122: 225 | L122: 4 | M122: 3 | O122: 2 | P122: =ROUND(Source!EN117,O122) -> 0 | W122: 0 | X122: 1 | Y122: 0 | Z122: 0 | AA122: 1 | AB122: 0
A123: 50 | B123: 0 | C123: 0 | D123: 1 | E123: 226 | F123: =ROUND(Source!AW117,O123) -> 0 | G123: СтМат | H123: Стоимость материалов (всего) | K123: 226 | L123: 5 | M123: 3 | O123: 2 | P123: =ROUND(Source!EO117,O123) -> 0 | W123: 0 | X123: 1 | Y123: 0 | Z123: 0 | AA123: 1 | AB123: 0
A124: 50 | B124: 0 | C124: 0 | D124: 1 | E124: 227 | F124: =ROUND(Source!AX117,O124) -> 0 | G124: СтМатЗак | H124: Стоимость материалов заказчика | K124: 227 | L124: 6 | M124: 3 | O124: 2 | P124: =ROUND(Source!EP117,O124) -> 0 | W124: 0 | X124: 1 | Y124: 0 | Z124: 0 | AA124: 1 | AB124: 0
A125: 50 | B125: 0 | C125: 0 | D125: 1 | E125: 228 | F125: =ROUND(Source!AY117,O125) -> 0 | G125: СтМатПод | H125: Стоимость материалов подрядчика | K125: 228 | L125: 7 | M125: 3 | O125: 2 | P125: =ROUND(Source!EQ117,O125) -> 0 | W125: 0 | X125: 1 | Y125: 0 | Z125: 0 | AA125: 1 | AB125: 0
A126: 50 | B126: 0 | C126: 0 | D126: 1 | E126: 216 | F126: =ROUND(Source!AP117,O126) -> 0 | G126: Оборуд | H126: Стоимость оборудования (всего) | K126: 216 | L126: 8 | M126: 3 | O126: 2 | P126: =ROUND(Source!EH117,O126) -> 0 | W126: 0 | X126: 1 | Y126: 0 | Z126: 0 | AA126: 1 | AB126: 0
A127: 50 | B127: 0 | C127: 0 | D127: 1 | E127: 223 | F127: =ROUND(Source!AQ117,O127) -> 0 | G127: ОборудЗак | H127: Стоимость оборудования заказчика | K127: 223 | L127: 9 | M127: 3 | O127: 2 | P127: =ROUND(Source!EI117,O127) -> 0 | W127: 0 | X127: 1 | Y127: 0 | Z127: 0 | AA127: 1 | AB127: 0
A128: 50 | B128: 0 | C128: 0 | D128: 1 | E128: 229 | F128: =ROUND(Source!AZ117,O128) -> 0 | G128: ОборудПод | H128: Стоимость оборудования подрядчика | K128: 229 | L128: 10 | M128: 3 | O128: 2 | P128: =ROUND(Source!ER117,O128) -> 0 | W128: 0 | X128: 1 | Y128: 0 | Z128: 0 | AA128: 1 | AB128: 0
A129: 50 | B129: 0 | C129: 0 | D129: 1 | E129: 203 | F129: =ROUND(Source!Q117,O129) -> 0 | G129: ЭММ | H129: Эксплуатация машин | K129: 203 | L129: 11 | M129: 3 | O129: 2 | P129: =ROUND(Source!DI117,O129) -> 0 | W129: 0 | X129: 1 | Y129: 0 | Z129: 0 | AA129: 1 | AB129: 0
A130: 50 | B130: 0 | C130: 0 | D130: 1 | E130: 231 | F130: =ROUND(Source!BB117,O130) -> 0 | G130: ЭММсНРиСП | H130: Эксплуатация машин по ТСН-2001.16 | K130: 231 | L130: 12 | M130: 3 | O130: 2 | P130: =ROUND(Source!ET117,O130) -> 0 | W130: 0 | X130: 1 | Y130: 0 | Z130: 0 | AA130: 1 | AB130: 0
A131: 50 | B131: 0 | C131: 0 | D131: 1 | E131: 204 | F131: =ROUND(Source!R117,O131) -> 0 | G131: ЗПМ | H131: ЗП машинистов | K131: 204 | L131: 13 | M131: 3 | O131: 2 | P131: =ROUND(Source!DJ117,O131) -> 0 | W131: 0 | X131: 1 | Y131: 0 | Z131: 0 | AA131: 1 | AB131: 0
...

Sheet SourceObSm
A1: 0 | B1: Smeta.RU (495) 974-1589 | D1: _OBSM_ | F1: 0 | G1: 0 | H1: 0 | I1: Smeta.RU | K1: 1 | L1: 75112 | M1: 10 | N1: 11 | O1: 15 | P1: 0 | Q1: 1
A12: 1 | B12: 51 | C12: 1 | E12: 0 | F12: 09-01-04 Транспортировка_(2 этап) | G12: 09-01-04 Транспортировка | I12: 0 | K12: 0 | L12: 0 | M12: 4098 | O12: 0 | P12: 0 | Q12: 0 | R12: 175 | S12: 160 | T12: 1 | V12: 0 | BB12: 0 | BH12: Сметные нормы списания | BI12: Коды ОКП для ТСН-2001 МГЭ (История развития) | BJ12: 1 | BK12: 1 | BL12: 0 | BM12: 0 | BN12: 1 | BO12: 0 | BP12: 6 | BQ12: 2 | BR12: 1 | BS12: 1 | BT12: 0 | BU12: 0 | BV12: 0 | BW12: 0 | BX12: 0 | BZ12: Типовой расчет для ТСН-2001 МГЭ, Новая методика с выпуска доп. 43 (Строительство), Доп 73 | CA12: История развития для ТСН-2001 (МГЭ) 73 доп от 17.07.2024 | CB12: История развития для ТСН-2001 (МГЭ) 73 доп от 17.07.2024 | CC12: История развития для ТСН-2001 (МГЭ) 73 доп от 17.07.2024 | CD12: История развития для ТСН-2001 (МГЭ) 73 доп от 17.07.2024 | CE12: Поправки для ТСН-2001 от 16.04.2024 г. доп.72 | CF12: 0 | CG12: 0 | CH12: 8 | CK12: 79 | CQ12: Территориальные сметные нормативы для Москвы (ТСН-2001) | CR12: ТЕР | CS12: 41660 | CT12: 1 | CU12: 73 | CY12: 0 | EC12: 0
A14: 22 | B14: 1 | C14: 0 | D14: 57734472 | E14: 57734470 | F14: 2 | G14: 1
A16: 3 | B16: 1 | C16: Новая локальная смета | D16: Новая локальная смета | E16: =ROUND((Source!F201)/1000,2) -> 0 | F16: =ROUND((Source!F202)/1000,2) -> 0 | G16: =ROUND((Source!F193)/1000,2) -> 0 | H16: =ROUND((Source!F203)/1000+(Source!F204)/1000,2) -> 4.87 | I16: =E16+F16+G16+H16 -> 4.87 | J16: =ROUND((Source!F199+Source!F198)/1000,2) -> 0 | K16: 4.87 | L16: 0 | M16: 0 | N16: =I16+L16+M16 -> 4.87 | T16: =ROUND((Source!P201)/1000,2) -> 0 | U16: =ROUND((Source!P202)/1000,2) -> 0 | V16: =ROUND((Source!P193)/1000,2) -> 0 | W16: =ROUND((Source!P203)/1000+(Source!P204)/1000,2) -> 71.22 | X16: =T16+U16+V16+W16 -> 71.22 | Y16: =ROUND((Source!P199+Source!P198)/1000,2) -> 0 | Z16: 71.22 | AA16: 0 | AB16: 0 | AC16: =X16+AA16+AB16 -> 71.22 | AI16: 0 | AJ16: 0 | AN16: 0 | AT16: 4868.34 | AU16: 0 | AV16: 0 | AW16: 0 | AX16: 0 | AY16: 4868.34 | AZ16: 0 | BA16: 0 | BB16: 0 | BC16: 0 | BD16: 4868.34 | BE16: 0 | BF16: 0 | BG16: 0 | BH16: 0 | BI16: 0 | BJ16: 0 | BK16: 4868.34 | BR16: 71217.26 | BS16: 0 | BT16: 0 | BU16: 0 | BV16: 0 | BW16: 71217.26 | BX16: 0 | BY16: 0 | BZ16: 0 | CA16: 0 | CB16: 71217.26 | CC16: 0 | CD16: 0 | CE16: 0 | CF16: 0 | CG16: 0 | CH16: 0 | CI16: 71217.26
A18: 51 | E18: 0 | F18: 0 | G18: 0 | H18: 4.87 | I18: 4.87 | J18: 0 | K18: 4.87 | L18: 0 | M18: 0 | N18: 4.87 | T18: 0 | U18: 0 | V18: 0 | W18: 71.22 | X18: 71.22 | Y18: 0 | Z18: 71.22 | AA18: 0 | AB18: 0 | AC18: 71.22
A20: 50 | B20: 0 | C20: 0 | D20: 1 | E20: 201 | F20: 4868.34 | G20: ПЗ | H20: Прямые затраты | K20: 201 | L20: 1 | M20: 3 | O20: 2 | P20: 71217.26
A21: 50 | B21: 0 | C21: 0 | D21: 1 | E21: 202 | F21: 0 | G21: СтМатОб | H21: Стоимость материальных ресурсов (всего) | K21: 202 | L21: 2 | M21: 3 | O21: 2 | P21: 0
A22: 50 | B22: 0 | C22: 0 | D22: 1 | E22: 222 | F22: 0 | G22: СтМатОбЗак | H22: Стоимость материалов и оборудования заказчика | K22: 222 | L22: 3 | M22: 3 | O22: 2 | P22: 0
A23: 50 | B23: 0 | C23: 0 | D23: 1 | E23: 225 | F23: 0 | G23: СтМатОбПод | H23: Стоимость материалов и оборудования подрядчика | K23: 225 | L23: 4 | M23: 3 | O23: 2 | P23: 0
A24: 50 | B24: 0 | C24: 0 | D24: 1 | E24: 226 | F24: 0 | G24: СтМат | H24: Стоимость материалов (всего) | K24: 226 | L24: 5 | M24: 3 | O24: 2 | P24: 0
A25: 50 | B25: 0 | C25: 0 | D25: 1 | E25: 227 | F25: 0 | G25: СтМатЗак | H25: Стоимость материалов заказчика | K25: 227 | L25: 6 | M25: 3 | O25: 2 | P25: 0
A26: 50 | B26: 0 | C26: 0 | D26: 1 | E26: 228 | F26: 0 | G26: СтМатПод | H26: Стоимость материалов подрядчика | K26: 228 | L26: 7 | M26: 3 | O26: 2 | P26: 0
A27: 50 | B27: 0 | C27: 0 | D27: 1 | E27: 216 | F27: 0 | G27: Оборуд | H27: Стоимость оборудования (всего) | K27: 216 | L27: 8 | M27: 3 | O27: 2 | P27: 0
A28: 50 | B28: 0 | C28: 0 | D28: 1 | E28: 223 | F28: 0 | G28: ОборудЗак | H28: Стоимость оборудования заказчика | K28: 223 | L28: 9 | M28: 3 | O28: 2 | P28: 0
A29: 50 | B29: 0 | C29: 0 | D29: 1 | E29: 229 | F29: 0 | G29: ОборудПод | H29: Стоимость оборудования подрядчика | K29: 229 | L29: 10 | M29: 3 | O29: 2 | P29: 0
A30: 50 | B30: 0 | C30: 0 | D30: 1 | E30: 203 | F30: 4868.34 | G30: ЭММ | H30: Эксплуатация машин | K30: 203 | L30: 11 | M30: 3 | O30: 2 | P30: 71217.26
A31: 50 | B31: 0 | C31: 0 | D31: 1 | E31: 231 | F31: 0 | G31: ЭММсНРиСП | H31: Эксплуатация машин по ТСН-2001.16 | K31: 231 | L31: 12 | M31: 3 | O31: 2 | P31: 0
... A46: 50 | B46: 0 | C46: 0 | D46: 1 | E46: 224 | F46: 4868.34 | G46: Всего | H46: Всего с НР и СП | K46: 224 | L46: 27 | M46: 3 | O46: 2 | P46: 71217.26
A48: -1
A51: 75 | B51: Базовый уровень цен | C51: 2000 | D51: 0 | E51: 1 | G51: 0 | H51: 1 | I51: 0 | J51: 1 | K51: 98 | L51: 77 | M51: 0 | N51: 57734472 | O51: 1
A52: 75 | B52: Текущий уровень цен | C52: 2024 | D52: 0 | E52: 4 | G52: 0 | H52: 2 | I52: 1 | J52: 1 | K52: 95 | L52: 65 | M52: 1 | N52: 57734470 | O52: 2
A53: 1 | B53: Сборник индексов | C53: Коэффициенты к ТСН-2001 МГЭ | D53: 2024 | E53: 7 | F53: 1 | G53: 1 | H53: 0 | I53: 2 | J53: 1 | K53: 1 | L53: 1 | M53: 1 | N53: 1 | O53: 1 | P53: 1 | Q53: 1 | AA53: 212 | AN53: 57734471

Sheet SmtRes
A1: =ROW(Source!A28) -> 28 | B1: 57734472 | C1: 57734765 | D1: 47634960 | E1: 27786564 | F1: 1 | G1: 27786564 | H1: 2 | I1: 9999990007 | K1: Стоимость прочих машин (ЭСН) | L1: 1344 | N1: 1008 | O1: руб. | P1: руб. | Q1: 1 | W1: 0 | X1: -1180195794 | Y1: =AT1 -> 42.72 | AA1: 0 | AB1: 1 | AC1: 0 | AD1: 0 | AE1: 0 | AF1: 1 | AG1: 0 | AH1: 0 | AI1: 1 | AJ1: 1 | AK1: 1 | AL1: 1 | AM1: -2 | AN1: 0 | AO1: 1 | AP1: 1 | AQ1: 0 | AR1: 0 | AT1: 42.72 | AV1: 0 | AW1: 2 | AX1: 57734767 | AY1: 1 | AZ1: 0 | BA1: 1 | BB1: 0 | BC1: 0 | BD1: 0 | BE1: 0 | BF1: 0 | BG1: 0 | BH1: 0 | BI1: 0 | BJ1: 0 | BK1: 0 | BL1: 0 | BM1: 0 | BN1: 0 | BO1: 0 | BP1: 0 | BQ1: 0 | BR1: 0 | BS1: 0 | BT1: 0 | BU1: 0 | BV1: 0 | BW1: 0 | CV1: 0 | CW1: =ROUND(Y1*Source!I28*DO1,9) -> 0 | CX1: =ROUND(Y1*Source!I28,9) -> 450.696 | CY1: =AB1 -> 1 | CZ1: =AF1 -> 1 | DA1: =AJ1 -> 1 | DB1: =ROUND(ROUND(AT1*CZ1,2),6) -> 42.72 | DC1: =ROUND(ROUND(AT1*AG1,2),6) -> 0 | DF1: =ROUND(ROUND(AE1,2)*CX1,2) -> 0 | DG1: =ROUND(ROUND(AF1,2)*CX1,2) -> 450.7 | DH1: =ROUND(ROUND(AG1,2)*CX1,2) -> 0 | DI1: =ROUND(ROUND(AH1,2)*CX1,2) -> 0 | DJ1: =DG1 -> 450.7 | DK1: 0 | DM1: 0 | DO1: 0
A2: =ROW(Source!A29) -> 29 | B2: 57734470 | C2: 57734765 | D2: 47634960 | E2: 27786564 | F2: 1 | G2: 27786564 | H2: 2 | I2: 9999990007 | K2: Стоимость прочих машин (ЭСН) | L2: 1344 | N2: 1008 | O2: руб. | P2: руб. | Q2: 1 | W2: 0 | X2: -1180195794 | Y2: =AT2 -> 42.72 | AA2: 0 | AB2: 1 | AC2: 0 | AD2: 0 | AE2: 0 | AF2: 1 | AG2: 0 | AH2: 0 | AI2: 1 | AJ2: 1 | AK2: 1 | AL2: 1 | AM2: -2 | AN2: 0 | AO2: 1 | AP2: 1 | AQ2: 0 | AR2: 0 | AT2: 42.72 | AV2: 0 | AW2: 2 | AX2: 57734767 | AY2: 1 | AZ2: 0 | BA2: 2 | BB2: 0 | BC2: 0 | BD2: 0 | BE2: 0 | BF2: 0 | BG2: 0 | BH2: 0 | BI2: 0 | BJ2: 0 | BK2: 0 | BL2: 0 | BM2: 0 | BN2: 0 | BO2: 0 | BP2: 0 | BQ2: 0 | BR2: 0 | BS2: 0 | BT2: 0 | BU2: 0 | BV2: 0 | BW2: 0 | CV2: 0 | CW2: =ROUND(Y2*Source!I29*DO2,9) -> 0 | CX2: =ROUND(Y2*Source!I29,9) -> 450.696 | CY2: =AB2 -> 1 | CZ2: =AF2 -> 1 | DA2: =AJ2 -> 1 | DB2: =ROUND(ROUND(AT2*CZ2,2),6) -> 42.72 | DC2: =ROUND(ROUND(AT2*AG2,2),6) -> 0 | DF2: =ROUND(ROUND(AE2,2)*CX2,2) -> 0 | DG2: =ROUND(ROUND(AF2,2)*CX2,2) -> 450.7 | DH2: =ROUND(ROUND(AG2,2)*CX2,2) -> 0 | DI2: =ROUND(ROUND(AH2,2)*CX2,2) -> 0 | DJ2: =DG2 -> 450.7 | DK2: 0 | DM2: 0 | DO2: 0

Sheet EtalonRes
A1: =ROW(Source!A28) -> 28 | B1: 57734767 | C1: 57734765 | D1: 47634960 | E1: 27786564 | F1: 1 | G1: 27786564 | H1: 2 | I1: 9999990007 | K1: Стоимость прочих машин (ЭСН) | L1: 1344 | N1: 1008 | O1: руб. | P1: руб. | Q1: 1 | X1: 42.72 | Y1: 0 | Z1: 1 | AA1: 0 | AB1: 0 | AC1: 0 | AD1: 1 | AE1: 0 | AG1: 42.72 | AH1: 2 | AI1: 57734766 | AJ1: 1 | AK1: 0 | AL1: 0 | AM1: 0 | AN1: 0 | AO1: 0 | AP1: 0 | AQ1: 0 | AR1: 0
A2: =ROW(Source!A29) -> 29 | B2: 57734767 | C2: 57734765 | D2: 47634960 | E2: 27786564 | F2: 1 | G2: 27786564 | H2: 2 | I2: 9999990007 | K2: Стоимость прочих машин (ЭСН) | L2: 1344 | N2: 1008 | O2: руб. | P2: руб. | Q2: 1 | X2: 42.72 | Y2: 0 | Z2: 1 | AA2: 0 | AB2: 0 | AC2: 0 | AD2: 1 | AE2: 0 | AG2: 42.72 | AH2: 2 | AI2: 57734766 | AJ2: 2 | AK2: 0 | AL2: 0 | AM2: 0 | AN2: 0 | AO2: 0 | AP2: 0 | AQ2: 0 | AR2: 0
A3: =ROW(Source!A30) -> 30 | B3: 57734769 | C3: 57734768 | D3: 47634960 | E3: 27786564 | F3: 1 | G3: 27786564 | H3: 2 | I3: 9999990007 | K3: Стоимость прочих машин (ЭСН) | L3: 1344 | N3: 1008 | O3: руб. | P3: руб. | Q3: 1 | X3: 36.59 | Y3: 0 | Z3: 1 | AA3: 0 | AB3: 0 | AC3: 0 | AD3: 1 | AE3: 0 | AG3: 36.59 | AH3: 3 | AI3: -1 | AK3: 0 | AL3: 0 | AM3: 0 | AN3: 0 | AO3: 0 | AP3: 0 | AQ3: 0 | AR3: 0
A4: =ROW(Source!A31) -> 31 | B4: 57734769 | C4: 57734768 | D4: 47634960 | E4: 27786564 | F4: 1 | G4: 27786564 | H4: 2 | I4: 9999990007 | K4: Стоимость прочих машин (ЭСН) | L4: 1344 | N4: 1008 | O4: руб. | P4: руб. | Q4: 1 | X4: 36.59 | Y4: 0 | Z4: 1 | AA4: 0 | AB4: 0 | AC4: 0 | AD4: 1 | AE4: 0 | AG4: 36.59 | AH4: 3 | AI4: -1 | AK4: 0 | AL4: 0 | AM4: 0 | AN4: 0 | AO4: 0 | AP4: 0 | AQ4: 0 | AR4: 0
A5: =ROW(Source!A32) -> 32 | B5: 57734771 | C5: 57734770 | D5: 47634960 | E5: 27786564 | F5: 1 | G5: 27786564 | H5: 2 | I5: 9999990007 | K5: Стоимость прочих машин (ЭСН) | L5: 1344 | N5: 1008 | O5: руб. | P5: руб. | Q5: 1 | X5: 22.57 | Y5: 0 | Z5: 1 | AA5: 0 | AB5: 0 | AC5: 0 | AD5: 1 | AE5: 0 | AG5: 22.57 | AH5: 3 | AI5: -1 | AK5: 0 | AL5: 0 | AM5: 0 | AN5: 0 | AO5: 0 | AP5: 0 | AQ5: 0 | AR5: 0
A6: =ROW(Source!A33) -> 33 | B6: 57734771 | C6: 57734770 | D6: 47634960 | E6: 27786564 | F6: 1 | G6: 27786564 | H6: 2 | I6: 9999990007 | K6: Стоимость прочих машин (ЭСН) | L6: 1344 | N6: 1008 | O6: руб. | P6: руб. | Q6: 1 | X6: 22.57 | Y6: 0 | Z6: 1 | AA6: 0 | AB6: 0 | AC6: 0 | AD6: 1 | AE6: 0 | AG6: 22.57 | AH6: 3 | AI6: -1 | AK6: 0 | AL6: 0 | AM6: 0 | AN6: 0 | AO6: 0 | AP6: 0 | AQ6: 0 | AR6: 0
A7: =ROW(Source!A34) -> 34 | B7: 57734773 | C7: 57734772 | D7: 47634960 | E7: 27786564 | F7: 1 | G7: 27786564 | H7: 2 | I7: 9999990007 | K7: Стоимость прочих машин (ЭСН) | L7: 1344 | N7: 1008 | O7: руб. | P7: руб. | Q7: 1 | X7: 17.84 | Y7: 0 | Z7: 1 | AA7: 0 | AB7: 0 | AC7: 0 | AD7: 1 | AE7: 0 | AG7: 17.84 | AH7: 3 | AI7: -1 | AK7: 0 | AL7: 0 | AM7: 0 | AN7: 0 | AO7: 0 | AP7: 0 | AQ7: 0 | AR7: 0
A8: =ROW(Source!A35) -> 35 | B8: 57734773 | C8: 57734772 | D8: 47634960 | E8: 27786564 | F8: 1 | G8: 27786564 | H8: 2 | I8: 9999990007 | K8: Стоимость прочих машин (ЭСН) | L8: 1344 | N8: 1008 | O8: руб. | P8: руб. | Q8: 1 | X8: 17.84 | Y8: 0 | Z8: 1 | AA8: 0 | AB8: 0 | AC8: 0 | AD8: 1 | AE8: 0 | AG8: 17.84 | AH8: 3 | AI8: -1 | AK8: 0 | AL8: 0 | AM8: 0 | AN8: 0 | AO8: 0 | AP8: 0 | AQ8: 0 | AR8: 0
A9: =ROW(Source!A36) -> 36 | B9: 57734775 | C9: 57734774 | D9: 47634960 | E9: 27786564 | F9: 1 | G9: 27786564 | H9: 2 | I9: 9999990007 | K9: Стоимость прочих машин (ЭСН) | L9: 1344 | N9: 1008 | O9: руб. | P9: руб. | Q9: 1 | X9: 21.71 | Y9: 0 | Z9: 1 | AA9: 0 | AB9: 0 | AC9: 0 | AD9: 1 | AE9: 0 | AG9: 21.71 | AH9: 3 | AI9: -1 | AK9: 0 | AL9: 0 | AM9: 0 | AN9: 0 | AO9: 0 | AP9: 0 | AQ9: 0 | AR9: 0
A10: =ROW(Source!A37) -> 37 | B10: 57734775 | C10: 57734774 | D10: 47634960 | E10: 27786564 | F10: 1 | G10: 27786564 | H10: 2 | I10: 9999990007 | K10: Стоимость прочих машин (ЭСН) | L10: 1344 | N10: 1008 | O10: руб. | P10: руб. | Q10: 1 | X10: 21.71 | Y10: 0 | Z10: 1 | AA10: 0 | AB10: 0 | AC10: 0 | AD10: 1 | AE10: 0 | AG10: 21.71 | AH10: 3 | AI10: -1 | AK10: 0 | AL10: 0 | AM10: 0 | AN10: 0 | AO10: 0 | AP10: 0 | AQ10: 0 | AR10: 0
A11: =ROW(Source!A73) -> 73 | B11: 57734777 | C11: 57734776 | D11: 47634960 | E11: 27786564 | F11: 1 | G11: 27786564 | H11: 2 | I11: 9999990007 | K11: Стоимость прочих машин (ЭСН) | L11: 1344 | N11: 1008 | O11: руб. | P11: руб. | Q11: 1 | X11: 45.1 | Y11: 0 | Z11: 1 | AA11: 0 | AB11: 0 | AC11: 0 | AD11: 1 | AE11: 0 | AG11: 45.1 | AH11: 3 | AI11: -1 | AK11: 0 | AL11: 0 | AM11: 0 | AN11: 0 | AO11: 0 | AP11: 0 | AQ11: 0 | AR11: 0
A12: =ROW(Source!A74) -> 74 | B12: 57734777 | C12: 57734776 | D12: 47634960 | E12: 27786564 | F12: 1 | G12: 27786564 | H12: 2 | I12: 9999990007 | K12: Стоимость прочих машин (ЭСН) | L12: 1344 | N12: 1008 | O12: руб. | P12: руб. | Q12: 1 | X12: 45.1 | Y12: 0 | Z12: 1 | AA12: 0 | AB12: 0 | AC12: 0 | AD12: 1 | AE12: 0 | AG12: 45.1 | AH12: 3 | AI12: -1 | AK12: 0 | AL12: 0 | AM12: 0 | AN12: 0 | AO12: 0 | AP12: 0 | AQ12: 0 | AR12: 0
A13: =ROW(Source!A75) -> 75 | B13: 57734779 | C13: 57734778 | D13: 47634960 | E13: 27786564 | F13: 1 | G13: 27786564 | H13: 2 | I13: 9999990007 | K13: Стоимость прочих машин (ЭСН) | L13: 1344 | N13: 1008 | O13: руб. | P13: руб. | Q13: 1 | X13: 12.61 | Y13: 0 | Z13: 1 | AA13: 0 | AB13: 0 | AC13: 0 | AD13: 1 | AE13: 0 | AG13: 12.61 | AH13: 3 | AI13: -1 | AK13: 0 | AL13: 0 | AM13: 0 | AN13: 0 | AO13: 0 | AP13: 0 | AQ13: 0 | AR13: 0
A14: =ROW(Source!A76) -> 76 | B14: 57734779 | C14: 57734778 | D14: 47634960 | E14: 27786564 | F14: 1 | G14: 27786564 | H14: 2 | I14: 9999990007 | K14: Стоимость прочих машин (ЭСН) | L14: 1344 | N14: 1008 | O14: руб. | P14: руб. | Q14: 1 | X14: 12.61 | Y14: 0 | Z14: 1 | AA14: 0 | AB14: 0 | AC14: 0 | AD14: 1 | AE14: 0 | AG14: 12.61 | AH14: 3 | AI14: -1 | AK14: 0 | AL14: 0 | AM14: 0 | AN14: 0 | AO14: 0 | AP14: 0 | AQ14: 0 | AR14: 0
A15: =ROW(Source!A112) -> 112 | B15: 57734781 | C15: 57734780 | D15: 47634960 | E15: 27786564 | F15: 1 | G15: 27786564 | H15: 2 | I15: 9999990007 | K15: Стоимость прочих машин (ЭСН) | L15: 1344 | N15: 1008 | O15: руб. | P15: руб. | Q15: 1 | X15: 45.1 | Y15: 0 | Z15: 1 | AA15: 0 | AB15: 0 | AC15: 0 | AD15: 1 | AE15: 0 | AG15: 45.1 | AH15: 3 | AI15: -1 | AK15: 0 | AL15: 0 | AM15: 0 | AN15: 0 | AO15: 0 | AP15: 0 | AQ15: 0 | AR15: 0
A16: =ROW(Source!A113) -> 113 | B16: 57734781 | C16: 57734780 | D16: 47634960 | E16: 27786564 | F16: 1 | G16: 27786564 | H16: 2 | I16: 9999990007 | K16: Стоимость прочих машин (ЭСН) | L16: 1344 | N16: 1008 | O16: руб. | P16: руб. | Q16: 1 | X16: 45.1 | Y16: 0 | Z16: 1 | AA16: 0 | AB16: 0 | AC16: 0 | AD16: 1 | AE16: 0 | AG16: 45.1 | AH16: 3 | AI16: -1 | AK16: 0 | AL16: 0 | AM16: 0 | AN16: 0 | AO16: 0 | AP16: 0 | AQ16: 0 | AR16: 0
A17: =ROW(Source!A114) -> 114 | B17: 57734783 | C17: 57734782 | D17: 47634960 | E17: 27786564 | F17: 1 | G17: 27786564 | H17: 2 | I17: 9999990007 | K17: Стоимость прочих машин (ЭСН) | L17: 1344 | N17: 1008 | O17: руб. | P17: руб. | Q17: 1 | X17: 12.61 | Y17: 0 | Z17: 1 | AA17: 0 | AB17: 0 | AC17: 0 | AD17: 1 | AE17: 0 | AG17: 12.61 | AH17: 3 | AI17: -1 | AK17: 0 | AL17: 0 | AM17: 0 | AN17: 0 | AO17: 0 | AP17: 0 | AQ17: 0 | AR17: 0
A18: =ROW(Source!A115) -> 115 | B18: 57734783 | C18: 57734782 | D18: 47634960 | E18: 27786564 | F18: 1 | G18: 27786564 | H18: 2 | I18: 9999990007 | K18: Стоимость прочих машин (ЭСН) | L18: 1344 | N18: 1008 | O18: руб. | P18: руб. | Q18: 1 | X18: 12.61 | Y18: 0 | Z18: 1 | AA18: 0 | AB18: 0 | AC18: 0 | AD18: 1 | AE18: 0 | AG18: 12.61 | AH18: 3 | AI18: -1 | AK18: 0 | AL18: 0 | AM18: 0 | AN18: 0 | AO18: 0 | AP18: 0 | AQ18: 0 | AR18: 0
A19: =ROW(Source!A151) -> 151 | B19: 57734785 | C19: 57734784 | D19: 47634960 | E19: 27786564 | F19: 1 | G19: 27786564 | H19: 2 | I19: 9999990007 | K19: Стоимость прочих машин (ЭСН) | L19: 1344 | N19: 1008 | O19: руб. | P19: руб. | Q19: 1 | X19: 11.17 | Y19: 0 | Z19: 1 | AA19: 0 | AB19: 0 | AC19: 0 | AD19: 1 | AE19: 0 | AG19: 11.17 | AH19: 3 | AI19: -1 | AK19: 0 | AL19: 0 | AM19: 0 | AN19: 0 | AO19: 0 | AP19: 0 | AQ19: 0 | AR19: 0
A20: =ROW(Source!A152) -> 152 | B20: 57734785 | C20: 57734784 | D20: 47634960 | E20: 27786564 | F20: 1 | G20: 27786564 | H20: 2 | I20: 9999990007 | K20: Стоимость прочих машин (ЭСН) | L20: 1344 | N20: 1008 | O20: руб. | P20: руб. | Q20: 1 | X20: 11.17 | Y20: 0 | Z20: 1 | AA20: 0 | AB20: 0 | AC20: 0 | AD20: 1 | AE20: 0 | AG20: 11.17 | AH20: 3 | AI20: -1 | AK20: 0 | AL20: 0 | AM20: 0 | AN20: 0 | AO20: 0 | AP20: 0 | AQ20: 0 | AR20: 0

Sheet SrcPoprs

Sheet SrcKA
A1: 0 | B1: Smeta.RU (495) 974-1589 | D1: _PS_ | F1: 0 | G1: 0 | H1: 0 | I1: Smeta.RU | K1: 1 | L1: 75112 | M1: 10 | N1: 11 | O1: 15 | P1: 0 | Q1: 1
F12: =Source!F12 -> 09-01-04 Транспортировка_(2 этап) | G12: =Source!G12 -> 09-01-04 Транспортировка | AJ12: 0 | CY12: 0
